Workbook

Sheet Sheet1
B2: Company | C2: Current Market Price (₹) | D2: DCF Intrinsic Value (₹) | E2: Upside (%) | F2: Valuation Recommendation | G2: Implied Price (EV/EBITDA) | H2: Implied Price (P/E) | I2: WACC (%) | J2: PV of Explicit FCFF | K2: PV of Terminal Value | L2: Enterprise Value | M2: Cash | N2: Debt | O2: Equity Value | P2: Share Outstanding | Q2: Return on Assets (%) | R2: Return on Equity (%) | S2: Altman's Score | T2: EBITDA | U2: Net Profit
B4: Hind. Unilever | C4: =[1]DCF!$D$43 | D4: =[1]DCF!$D$41 | E4: =(D4-C4)/C4 | F4: =IF(E4 > 0.1, "BUY", IF(E4 < -0.1, "SELL", "HOLD")) | G4: =[1]Comp_Valuation!$P$36 | H4: =[1]Comp_Valuation!$Q$36 | I4: =[1]WACC!$K$46 | J4: =[1]DCF!$D$32 | K4: =[1]DCF!$D$33 | L4: =[1]DCF!$D$34 | M4: =[1]DCF!$D$36 | N4: =[1]DCF!$D$37 | O4: =[1]DCF!$D$39 | P4: =[1]DCF!$D$40 | Q4: ='[1]Dupont Analysis'!$I$87 | R4: ='[1]Dupont Analysis'!$I$81 | S4: ='[1]Altman''s Z Score'!$I$93 | T4: ='[1]Historical FS'!$L$19 | U4: ='[1]Historical FS'!$L$37
B5: ITC | C5: =[2]DCF!$D$44 | D5: =[2]DCF!$D$42 | E5: =(D5-C5)/C5 | F5: =IF(E5 > 0.1, "BUY", IF(E5 < -0.1, "SELL", "HOLD")) | G5: =[2]Comp_Valuation!$P$37 | H5: =[2]Comp_Valuation!$Q$37 | I5: =[2]WACC!$K$46 | J5: =[2]DCF!$D$33 | K5: =[2]DCF!$D$34 | L5: =[2]DCF!$D$35 | M5: =[2]DCF!$D$37 | N5: =[2]DCF!$D$38 | O5: =[2]DCF!$D$39 | P5: =[2]DCF!$D$40 | Q5: ='[2]Dupont Analysis'!$I$96 | R5: ='[2]Dupont Analysis'!$I$78 | S5: ='[2]Altman''s Z Score'!$I$89 | T5: ='[2]Historical FS'!$L$19 | U5: ='[2]Historical FS'!$L$37
B6: Nestle India | C6: =[3]DCF!$D$44 | D6: =[3]DCF!$D$42 | E6: =(D6-C6)/C6 | F6: =IF(E6 > 0.1, "BUY", IF(E6 < -0.1, "SELL", "HOLD")) | G6: =[3]Comp_Valuation!$P$37 | H6: =[3]Comp_Valuation!$Q$37 | I6: =[3]WACC!$K$46 | J6: =[3]DCF!$D$33 | K6: =[3]DCF!$D$34 | L6: =[3]DCF!$D$35 | M6: =[3]DCF!$D$37 | N6: =[3]DCF!$D$38 | O6: =[3]DCF!$D$39 | P6: =[3]DCF!$D$40 | Q6: ='[3]Dupont Analysis'!$I$96 | R6: ='[3]Dupont Analysis'!$I$78 | S6: ='[3]Altman''s Z Score'!$I$89 | T6: ='[3]Historical FS'!$L$19 | U6: ='[3]Historical FS'!$L$37
B7: Varun Beverages | C7: =[4]DCF!$D$44 | D7: =[4]DCF!$D$42 | E7: =(D7-C7)/C7 | F7: =IF(E7 > 0.1, "BUY", IF(E7 < -0.1, "SELL", "HOLD")) | G7: =[4]Comp_Valuation!$P$37 | H7: =[4]Comp_Valuation!$Q$37 | I7: =[4]WACC!$K$46 | J7: =[4]DCF!$D$33 | K7: =[4]DCF!$D$34 | L7: =[4]DCF!$D$35 | M7: =[4]DCF!$D$37 | N7: =[4]DCF!$D$38 | O7: =[4]DCF!$D$39 | P7: =[4]DCF!$D$40 | Q7: ='[4]Dupont Analysis'!$I$95 | R7: ='[4]Dupont Analysis'!$I$77 | S7: ='[4]Altman''s Z Score'!$I$88 | T7: ='[4]Historical FS'!$L$19 | U7: ='[4]Historical FS'!$L$37
B8: Britannia Inds. | C8: =[5]DCF!$D$44 | D8: =[5]DCF!$D$42 | E8: =(D8-C8)/C8 | F8: =IF(E8 > 0.1, "BUY", IF(E8 < -0.1, "SELL", "HOLD")) | G8: =[5]Comp_Valuation!$P$37 | H8: =[5]Comp_Valuation!$Q$37 | I8: =[5]WACC!$K$46 | J8: =[5]DCF!$D$33 | K8: =[5]DCF!$D$34 | L8: =[5]DCF!$D$35 | M8: =[5]DCF!$D$37 | N8: =[5]DCF!$D$38 | O8: =[5]DCF!$D$39 | P8: =[5]DCF!$D$40 | Q8: ='[5]Dupont Analysis'!$I$95 | R8: ='[5]Dupont Analysis'!$I$77 | S8: ='[5]Altman''s Z Score'!$I$88 | T8: ='[5]Historical FS'!$L$19 | U8: ='[5]Historical FS'!$L$37

Sheet Control
B2: INSTITUTIONAL MODEL CONTROL PANEL & ASSUMPTIONS
B3: Single Source of Truth for Global Valuation Inputs, Scenarios & Route Configuration
B5: 1. MODEL METADATA & REPORTING SETTINGS | E5: COUNTRY | F5: RISK-FREE (Rf) | G5: ERP | H5: MARGINAL TAX | J5: SCENARIO | K5: GROWTH MULT | L5: MARGIN ADJ (NOT WIRED) | M5: WACC SPREAD
B6: Valuation Date | C6: =TODAY() | E6: India | F6: 0.068 | G6: 0.065 | H6: 0.2517 | J6: 1 - Bear Case | K6: 0.7 | L6: -0.02 | M6: 0.01
B7: Reporting Currency | C7: INR | E7: United States | F7: 0.042 | G7: 0.05 | H7: 0.21 | J7: 2 - Base Case | K7: 1 | L7: 0 | M7: 0
B8: Financial Reporting Unit | C8: Crores | E8: United Kingdom | F8: 0.044 | G8: 0.055 | H8: 0.25 | J8: 3 - Bull Case | K8: 1.3 | L8: 0.02 | M8: -0.005
B9: Unit Scale Factor | C9: 10000000 | E9: Germany | F9: 0.025 | G9: 0.05 | H9: 0.3
B10: Target Country | C10: India | E10: Japan | F10: 0.011 | G10: 0.055 | H10: 0.3062 | J10: ACTIVE MULTIPLIERS: | K10: =CHOOSE(C14, K6, K7, K8) | L10: =CHOOSE(C14, L6, L7, L8) | M10: =CHOOSE(C14, M6, M7, M8)
B11: Target Sector / Industry | C11: Corporate / Non-Financial | E11: Singapore | F11: 0.03 | G11: 0.05 | H11: 0.17
B12: Valuation Framework Switch | C12: FCFF DCF | E12: UAE | F12: 0.045 | G12: 0.055 | H12: 0.09
B13: Benchmark Market Index | C13: NIFTY 50
B14: Active Valuation Scenario | C14: 2
B16: 2. COST OF CAPITAL & DCF ASSUMPTIONS
B17: Risk-Free Rate (Rf) | C17: =VLOOKUP(C10, E6:H12, 2, FALSE())
B18: Equity Risk Premium (ERP) | C18: =VLOOKUP(C10, E6:H12, 3, FALSE())
B19: Marginal Corporate Tax Rate | C19: =VLOOKUP(C10, E6:H12, 4, FALSE())
B20: Effective Dynamic Tax Rate | C20: =MEDIAN(MAX(0.15, MIN(0.35, INDEX('Data Sheet'!$B29:$K29, C26)/MAX(1, INDEX('Data Sheet'!$B28:$K28, C26)))), C19)
B21: Terminal Growth Rate (g) | C21: 0.04
B22: Reinvestment Rate Ceiling | C22: 0.85
B23: Investments Fair-Value Haircut | C23: 0.1
B24: Minority Interest Method | C24: Book Value
B25: 3. DYNAMIC STATEMENT PERIOD SELECTOR
B26: Latest Historical Period Column Index | C26: =MATCH(MAX('Data Sheet'!$B56:$K56), 'Data Sheet'!$B56:$K56, 0)
B27: Latest Statement Header Date | C27: =INDEX('Data Sheet'!$B56:$K56, C26)
B28: Latest Stock Price (Data Sheet) | C28: ='Data Sheet'!B8
B29: Default Credit Spread over Rf (used when debt is negligible) | C29: 0.015
B30: Max Credit Spread Cap (calc outside Rf..Rf+cap is rejected) | C30: 0.05
B32: 4. OPTIONAL ALTERNATE 10-YEAR DCF (parallel view - base DCF unchanged)
B33: Year-1 EBIT Growth Override (blank = use model)
B34: Exit EV/EBIT Multiple (x) | C34: 18
B35: Terminal Method (Gordon Growth / Exit Multiple) | C35: Gordon Growth
B36: Incremental ROIC Override (blank = model ROIC)

Sheet Checks
B2: MODEL AUDIT & INTEGRITY CHECK PANEL
B3: OVERALL MODEL STATUS: | C3: =IF(AND(F6="PASS", F7="PASS", F8="PASS", F9="PASS", F10="PASS", F11="PASS", F12="PASS", F13="PASS", F14="PASS", F15="PASS"), "MODEL STATUS: OK", "MODEL STATUS: CHECK REQUIRED")
B5: CHECK ITEM | C5: VALIDATION LOGIC & FORMULA | D5: CURRENT VALUE / VARIANCE | E5: THRESHOLD | F5: STATUS
B6: 1. Balance Sheet Identity | C6: Total liabilities side ties to its components and to total assets | D6: =MAX(ABS(INDEX('Data Sheet'!$B61:$K61,Control!$C$26)-(INDEX('Data Sheet'!$B57:$K57,Control!$C$26)+INDEX('Data Sheet'!$B58:$K58,Control!$C$26)+INDEX('Data Sheet'!$B59:$K59,Control!$C$26)+INDEX('Data Sheet'!$B60:$K60,Control!$C$26))),ABS(INDEX('Data Sheet'!$B61:$K61,Control!$C$26)-INDEX('Data Sheet'!$B66:$K66,Control!$C$26))) | E6: < ₹ 5.0 Cr | F6: =IF(D6<5, "PASS", "CHECK")
B7: 2. PBT Mathematical Tie | C7: Sales less all expenses plus other income less depreciation and interest ties to PBT | D7: =ABS(INDEX('Data Sheet'!$B17:$K17,Control!$C$26)-SUM(INDEX('Data Sheet'!$B$18:$K$24,0,Control!$C$26))+INDEX('Data Sheet'!$B25:$K25,Control!$C$26)-INDEX('Data Sheet'!$B26:$K26,Control!$C$26)-INDEX('Data Sheet'!$B27:$K27,Control!$C$26)-INDEX('Data Sheet'!$B28:$K28,Control!$C$26))/MAX(1,INDEX('Data Sheet'!$B28:$K28,Control!$C$26)) | E7: < 1.5% | F7: =IF(D7<0.015, "PASS", "CHECK")
B8: 3. Debt Schedule Concordance | C8: Data Sheet Borrowings ties to the independently pasted Raw FS borrowings (latest year) | D8: =ABS(INDEX('Data Sheet'!$B59:$K59,Control!$C$26)-LOOKUP(2,1/ISNUMBER('Raw FS'!$C7:$N7),'Raw FS'!$C7:$N7)) | E8: < ₹ 5.0 Cr | F8: =IF(D8<5, "PASS", "CHECK")
B9: 4. P&L Expenses Agreement | C9: Data Sheet total expenses (rows 18-24) tie to Raw FS total expenses | D9: =ABS(SUM(INDEX('Data Sheet'!$B$18:$K$24,0,Control!$C$26))-'Raw FS'!AD5) | E9: < ₹ 10.0 Cr | F9: =IF(D9<10, "PASS", "CHECK")
B10: 5. Formula Error Counter | C10: Zero formula errors on Summary, DCF, WACC, Intrinsic Valuation, Comps and Beta tabs | D10: =SUMPRODUCT(--ISERROR('AI Valuation Summary'!A4:H47))+SUMPRODUCT(--ISERROR(DCF!A1:M55))+SUMPRODUCT(--ISERROR(WACC!A1:K46))+SUMPRODUCT(--ISERROR('Intrinsic Valuation'!A1:L65))+SUMPRODUCT(--ISERROR(Comp_Valuation!A1:Q39))+SUMPRODUCT(--ISERROR('Beta-Regression'!A1:O302)) | E10: 0 Errors | F10: =IF(D10=0, "PASS", "CHECK")
B11: 6. Terminal Value EV Share | C11: Terminal Value percentage of Enterprise Value is sustainable | D11: =DCF!D34 / MAX(1, DCF!D35) | E11: < 75.0% | F11: =IF(D11<0.75, "PASS", "CHECK")
B12: 7. Growth vs WACC Boundary | C12: Terminal growth rate is less than WACC and within Risk-Free rate | D12: =DCF!D20 - DCF!D19 | E12: > 0.5% | F12: =IF(AND(D12>0.005, DCF!D19<=Control!$C$17), "PASS", "CHECK")
B13: 8. Trading Price Freshness | C13: Market trading price quote is within acceptable institutional window | D13: =TODAY()-SUMPRODUCT(MAX(IFERROR(DATEVALUE('Raw Data'!G6:G252),IF(ISNUMBER('Raw Data'!G6:G252),'Raw Data'!G6:G252,0)))) | E13: <= 45 Days | F13: =IF(D13<=45, "PASS", "CHECK")
B14: 9. Peer Group Sample Size | C14: Comparable peer valuation set contains minimum robust observations | D14: =COUNTA(Comp_Valuation!C12:C26) | E14: >= 4 Peers | F14: =IF(D14>=4, "PASS", "CHECK")
B15: 10. DCF Bridge Mathematical Tie | C15: Equity Value equals EV + Cash + Investments - Debt - Minority Interest | D15: =ABS(DCF!D40 - (DCF!D35 + DCF!D37 - DCF!D38 - DCF!D39)) | E15: < ₹ 0.01 | F15: =IF(D15<0.01, "PASS", "CHECK")
B17: ADVISORY CHECKS (informational - NOT included in overall status)
B18: A1. DCF vs Market Divergence | C18: Absolute gap between DCF value per share and market price | D18: =ABS(DCF!D46) | E18: < 50% | F18: =IF(D18<0.5,"PASS","REVIEW")
B19: A2. WACC Sanity Range | C19: WACC sits inside a plausible band for the target market | D19: =DCF!D20 | E19: 8% - 16% | F19: =IF(AND(D19>=0.08,D19<=0.16),"PASS","REVIEW")
B20: A3. Market Cap Tie | C20: Market cap used in WACC weights ties to Price x Shares on Data Sheet | D20: =ABS(WACC!C35/'Data Sheet'!B9-1) | E20: < 2% | F20: =IF(D20<0.02,"PASS","REVIEW")
B21: A4. Reinvestment History Spike | C21: Largest historical reinvestment rate (blank-year / acquisition spikes distort median) | D21: =MAX('Intrinsic Valuation'!H52:L52) | E21: <= 100% | F21: =IF(D21<=1,"PASS","REVIEW")
