Workbook
Name UPDATE: 'Data Sheet'!$E$1
Name UPDATE: '[1]Data Sheet'!$E$1

Sheet AI Valuation Summary
A1: Adani Enterprises Ltd (ADANIENT) - Institutional Valuation
A4: Current Price | B4: Intrinsic Value | C4: Margin of Safety | D4: Verdict | E4: WACC | F4: Altman Z-Score | G4: DuPont ROE
A5: =DCF!D44 | B5: =DCF!D42 | C5: =(B5-A5)/A5 | D5: =IF(C5>0.15,"UNDERVALUED / BUY",IF(C5<-0.15,"OVERVALUED / SELL","FAIRLY VALUED / HOLD")) | E5: =DCF!D20 | F5: ='Altman''s Z Score'!B15 | G5: ='Dupont Analysis'!B15
C6: =DCF!D42
A7: THE 4 CORE VALUATION PILLARS | C7: =DCF!D44
A8: Pillar 1: FCF Engine | B8: CFO ₹N/A Cr vs PAT ₹N/A Cr | EBIT Mgn N/A% | CCC N/A days | C8: =(C6-C7)/C7
A9: Pillar 2: Growth Trajectory | B9: 3Y Sales CAGR N/A% | 5Y CAGR N/A% | Forecast g 10% | Terminal g 3%
A10: Pillar 3: Cost of Capital (WACC) | B10: WACC 10.67% | Ke N/A% | Beta 1.0 | ERP 6.5% | Rf 7.0% | C10: =WACC!K29
A11: Pillar 4: Relative Multiples | B11: P/E N/Ax | P/B N/Ax | EV/EBITDA N/Ax | EV/Sales N/Ax | C11: =WACC!K26
C12: =WACC!K28
A13: 5-Year Discounted Cash Flow (DCF) Schedule (Amounts in ₹ Cr)
A14: Year | B14: EBIT | C14: NOPAT | D14: Reinvest Rate | E14: FCFF | F14: Discount Factor | G14: PV of FCFF
A15: Year 1 | B15: =DCF!I8 | C15: =DCF!I10 | D15: =DCF!I11 | E15: =DCF!I12 | F15: =DCF!I14 | G15: =DCF!I16
A16: Year 2 | B16: =DCF!J8 | C16: =DCF!J10 | D16: =DCF!J11 | E16: =DCF!J12 | F16: =DCF!J14 | G16: =DCF!J16
A17: Year 3 | B17: =DCF!K8 | C17: =DCF!K10 | D17: =DCF!K11 | E17: =DCF!K12 | F17: =DCF!K14 | G17: =DCF!K16
A18: Year 4 | B18: =DCF!L8 | C18: =DCF!L10 | D18: =DCF!L11 | E18: =DCF!L12 | F18: =DCF!L14 | G18: =DCF!L16
A19: Year 5 | B19: =DCF!M8 | C19: =DCF!M10 | D19: =DCF!M11 | E19: =DCF!M12 | F19: =DCF!M14 | G19: =DCF!M16
A21: Enterprise to Equity Value Bridge
A22: PV of 5-Year FCFFs | B22: =DCF!D33 | C22: =MEDIAN(Comp_Valuation!I10:I15)
A23: Terminal Value | B23: =DCF!D29 | C23: =MEDIAN(Comp_Valuation!J10:J15)
A24: PV of Terminal Value | B24: =DCF!D34
A25: Enterprise Value (Operating Assets) | B25: =DCF!D35
A26: Add: Estimated Cash & Liquid Assets | B26: =DCF!D37
A27: Less: Total Debt & Borrowings | B27: =DCF!D38
A28: Net Equity Value | B28: =DCF!D39
A29: Shares Outstanding | B29: =DCF!D40
A30: Intrinsic Value per Share | B30: =DCF!D42
A31: Current Market Price | B31: =DCF!D44
A32: Margin of Safety / Discount | B32: =(B30-B31)/B31

Sheet Profit & Loss
A1: ='Data Sheet'!B1 | H1: =UPDATE | M1: SCREENER.IN
A3: Narration | B3: ='Data Sheet'!B16 | C3: ='Data Sheet'!C16 | D3: ='Data Sheet'!D16 | E3: ='Data Sheet'!E16 | F3: ='Data Sheet'!F16 | G3: ='Data Sheet'!G16 | H3: ='Data Sheet'!H16 | I3: ='Data Sheet'!I16 | ... K3: ='Data Sheet'!K16 | L3: Trailing | M3: Best Case | N3: Worst Case
A4: Sales | B4: ='Data Sheet'!B17 | C4: ='Data Sheet'!C17 | D4: ='Data Sheet'!D17 | E4: ='Data Sheet'!E17 | F4: ='Data Sheet'!F17 | G4: ='Data Sheet'!G17 | H4: ='Data Sheet'!H17 | I4: ='Data Sheet'!I17 | ... K4: ='Data Sheet'!K17 | L4: =SUM(Quarters!H4:K4) | M4: =$K4+M23*K4 | N4: =$K4+N23*L4
A5: Expenses | B5: =SUM('Data Sheet'!B18,'Data Sheet'!B20:B24, -1*'Data Sheet'!B19) | C5: =SUM('Data Sheet'!C18,'Data Sheet'!C20:C24, -1*'Data Sheet'!C19) | D5: =SUM('Data Sheet'!D18,'Data Sheet'!D20:D24, -1*'Data Sheet'!D19) | E5: =SUM('Data Sheet'!E18,'Data Sheet'!E20:E24, -1*'Data Sheet'!E19) | F5: =SUM('Data Sheet'!F18,'Data Sheet'!F20:F24, -1*'Data Sheet'!F19) | G5: =SUM('Data Sheet'!G18,'Data Sheet'!G20:G24, -1*'Data Sheet'!G19) | H5: =SUM('Data Sheet'!H18,'Data Sheet'!H20:H24, -1*'Data Sheet'!H19) | I5: =SUM('Data Sheet'!I18,'Data Sheet'!I20:I24, -1*'Data Sheet'!I19) | ... K5: =SUM('Data Sheet'!K18,'Data Sheet'!K20:K24, -1*'Data Sheet'!K19) | L5: =SUM(Quarters!H5:K5) | M5: =M4-M6 | N5: =N4-N6
A6: Operating Profit | B6: =B4-B5 | C6: =C4-C5 | D6: =D4-D5 | E6: =E4-E5 | F6: =F4-F5 | G6: =G4-G5 | H6: =H4-H5 | I6: =I4-I5 | ... K6: =K4-K5 | L6: =SUM(Quarters!H6:K6) | M6: =M4*M24 | N6: =N4*N24
A7: Other Income | B7: ='Data Sheet'!B25 | C7: ='Data Sheet'!C25 | D7: ='Data Sheet'!D25 | E7: ='Data Sheet'!E25 | F7: ='Data Sheet'!F25 | G7: ='Data Sheet'!G25 | H7: ='Data Sheet'!H25 | I7: ='Data Sheet'!I25 | ... K7: ='Data Sheet'!K25 | L7: =SUM(Quarters!H7:K7) | M7: 0 | N7: 0
A8: Depreciation | B8: ='Data Sheet'!B26 | C8: ='Data Sheet'!C26 | D8: ='Data Sheet'!D26 | E8: ='Data Sheet'!E26 | F8: ='Data Sheet'!F26 | G8: ='Data Sheet'!G26 | H8: ='Data Sheet'!H26 | I8: ='Data Sheet'!I26 | ... K8: ='Data Sheet'!K26 | L8: =SUM(Quarters!H8:K8) | M8: =+$L8 | N8: =+$L8
A9: Interest | B9: ='Data Sheet'!B27 | C9: ='Data Sheet'!C27 | D9: ='Data Sheet'!D27 | E9: ='Data Sheet'!E27 | F9: ='Data Sheet'!F27 | G9: ='Data Sheet'!G27 | H9: ='Data Sheet'!H27 | I9: ='Data Sheet'!I27 | ... K9: ='Data Sheet'!K27 | L9: =SUM(Quarters!H9:K9) | M9: =+$L9 | N9: =+$L9
A10: Profit before tax | B10: ='Data Sheet'!B28 | C10: ='Data Sheet'!C28 | D10: ='Data Sheet'!D28 | E10: ='Data Sheet'!E28 | F10: ='Data Sheet'!F28 | G10: ='Data Sheet'!G28 | H10: ='Data Sheet'!H28 | I10: ='Data Sheet'!I28 | ... K10: ='Data Sheet'!K28 | L10: =SUM(Quarters!H10:K10) | M10: =M6+M7-SUM(M8:M9) | N10: =N6+N7-SUM(N8:N9)
A11: Tax | B11: ='Data Sheet'!B29 | C11: ='Data Sheet'!C29 | D11: ='Data Sheet'!D29 | E11: ='Data Sheet'!E29 | F11: ='Data Sheet'!F29 | G11: ='Data Sheet'!G29 | H11: ='Data Sheet'!H29 | I11: ='Data Sheet'!I29 | ... K11: ='Data Sheet'!K29 | L11: =SUM(Quarters!H11:K11) | M11: =IF($L10>0,$L11/$L10,0) | N11: =IF($L10>0,$L11/$L10,0)
A12: Net profit | B12: ='Data Sheet'!B30 | C12: ='Data Sheet'!C30 | D12: ='Data Sheet'!D30 | E12: ='Data Sheet'!E30 | F12: ='Data Sheet'!F30 | G12: ='Data Sheet'!G30 | H12: ='Data Sheet'!H30 | I12: ='Data Sheet'!I30 | ... K12: ='Data Sheet'!K30 | L12: =SUM(Quarters!H12:K12) | M12: =M10-M11*M10 | N12: =N10-N11*N10
A13: EPS | B13: =IF('Data Sheet'!B93>0,B12/'Data Sheet'!B93,0) | C13: =IF('Data Sheet'!C93>0,C12/'Data Sheet'!C93,0) | D13: =IF('Data Sheet'!D93>0,D12/'Data Sheet'!D93,0) | E13: =IF('Data Sheet'!E93>0,E12/'Data Sheet'!E93,0) | F13: =IF('Data Sheet'!F93>0,F12/'Data Sheet'!F93,0) | G13: =IF('Data Sheet'!G93>0,G12/'Data Sheet'!G93,0) | H13: =IF('Data Sheet'!H93>0,H12/'Data Sheet'!H93,0) | I13: =IF('Data Sheet'!I93>0,I12/'Data Sheet'!I93,0) | ... K13: =IF('Data Sheet'!K93>0,K12/'Data Sheet'!K93,0) | L13: =IF('Data Sheet'!$B6>0,'Profit & Loss'!L12/'Data Sheet'!$B6,0) | M13: =IF('Data Sheet'!$B6>0,'Profit & Loss'!M12/'Data Sheet'!$B6,0) | N13: =IF('Data Sheet'!$B6>0,'Profit & Loss'!N12/'Data Sheet'!$B6,0)
A14: Price to earning | B14: =IF(B15>0,B15/B13,"") | C14: =IF(C15>0,C15/C13,"") | D14: =IF(D15>0,D15/D13,"") | E14: =IF(E15>0,E15/E13,"") | F14: =IF(F15>0,F15/F13,"") | G14: =IF(G15>0,G15/G13,"") | H14: =IF(H15>0,H15/H13,"") | I14: =IF(I15>0,I15/I13,"") | ... K14: =IF(K15>0,K15/K13,"") | L14: =IF(L13>0,L15/L13,0) | M14: =M25 | N14: =N25
A15: Price | B15: ='Data Sheet'!B90 | C15: ='Data Sheet'!C90 | D15: ='Data Sheet'!D90 | E15: ='Data Sheet'!E90 | F15: ='Data Sheet'!F90 | G15: ='Data Sheet'!G90 | H15: ='Data Sheet'!H90 | I15: ='Data Sheet'!I90 | ... K15: ='Data Sheet'!K90 | L15: ='Data Sheet'!B8 | M15: =M13*M14 | N15: =N13*N14
A17: RATIOS:
A18: Dividend Payout | B18: =IF('Data Sheet'!B30>0, 'Data Sheet'!B31/'Data Sheet'!B30, 0) | C18: =IF('Data Sheet'!C30>0, 'Data Sheet'!C31/'Data Sheet'!C30, 0) | D18: =IF('Data Sheet'!D30>0, 'Data Sheet'!D31/'Data Sheet'!D30, 0) | E18: =IF('Data Sheet'!E30>0, 'Data Sheet'!E31/'Data Sheet'!E30, 0) | F18: =IF('Data Sheet'!F30>0, 'Data Sheet'!F31/'Data Sheet'!F30, 0) | G18: =IF('Data Sheet'!G30>0, 'Data Sheet'!G31/'Data Sheet'!G30, 0) | H18: =IF('Data Sheet'!H30>0, 'Data Sheet'!H31/'Data Sheet'!H30, 0) | I18: =IF('Data Sheet'!I30>0, 'Data Sheet'!I31/'Data Sheet'!I30, 0) | ... K18: =IF('Data Sheet'!K30>0, 'Data Sheet'!K31/'Data Sheet'!K30, 0)
A19: OPM | B19: =IF(B6>0,B6/B4,0) | C19: =IF(C6>0,C6/C4,0) | D19: =IF(D6>0,D6/D4,0) | E19: =IF(E6>0,E6/E4,0) | F19: =IF(F6>0,F6/F4,0) | G19: =IF(G6>0,G6/G4,0) | H19: =IF(H6>0,H6/H4,0) | I19: =IF(I6>0,I6/I4,0) | ... L19: =IF(L6>0,L6/L4,0)
G22: TRENDS: | H22: 10 YEARS | I22: 7 YEARS | J22: 5 YEARS | K22: 3 YEARS | L22: RECENT | M22: BEST | N22: WORST
G23: Sales Growth | H23: =IF(B4=0,"",POWER($K4/B4,1/9)-1) | I23: =IF(D4=0,"",POWER($K4/D4,1/7)-1) | J23: =IF(F4=0,"",POWER($K4/F4,1/5)-1) | K23: =IF(H4=0,"",POWER($K4/H4, 1/3)-1) | L23: =IF(ISERROR(MAX(IF(J4=0,"",(K4-J4)/J4),IF(K4=0,"",(L4-K4)/K4))),"",MAX(IF(J4=0,"",(K4-J4)/J4),IF(K4=0,"",(L4-K4)/K4))) | M23: =MAX(K23:L23) | N23: =MIN(H23:L23)
G24: OPM | H24: =IF(SUM(B4:$K$4)=0,"",SUMPRODUCT(B19:$K$19,B4:$K$4)/SUM(B4:$K$4)) | I24: =IF(SUM(E4:$K$4)=0,"",SUMPRODUCT(E19:$K$19,E4:$K$4)/SUM(E4:$K$4)) | J24: =IF(SUM(G4:$K$4)=0,"",SUMPRODUCT(G19:$K$19,G4:$K$4)/SUM(G4:$K$4)) | K24: =IF(SUM(I4:$K$4)=0, "", SUMPRODUCT(I19:$K$19,I4:$K$4)/SUM(I4:$K$4)) | L24: =L19 | M24: =MAX(K24:L24) | N24: =MIN(H24:L24)
G25: Price to Earning | H25: =IF(ISERROR(AVERAGEIF(B14:$L14,">0")),"",AVERAGEIF(B14:$L14,">0")) | I25: =IF(ISERROR(AVERAGEIF(E14:$L14,">0")),"",AVERAGEIF(E14:$L14,">0")) | J25: =IF(ISERROR(AVERAGEIF(G14:$L14,">0")),"",AVERAGEIF(G14:$L14,">0")) | K25: =IF(ISERROR(AVERAGEIF(I14:$L14,">0")),"",AVERAGEIF(I14:$L14,">0")) | L25: =L14 | M25: =MAX(K25:L25) | N25: =MIN(H25:L25)

Sheet Quarters
A1: ='Profit & Loss'!A1 | E1: =UPDATE | J1: SCREENER.IN
A3: Narration | B3: ='Data Sheet'!B41 | C3: ='Data Sheet'!C41 | D3: ='Data Sheet'!D41 | E3: ='Data Sheet'!E41 | F3: ='Data Sheet'!F41 | G3: ='Data Sheet'!G41 | H3: ='Data Sheet'!H41 | I3: ='Data Sheet'!I41 | ... K3: ='Data Sheet'!K41
A4: Sales | B4: ='Data Sheet'!B42 | C4: ='Data Sheet'!C42 | D4: ='Data Sheet'!D42 | E4: ='Data Sheet'!E42 | F4: ='Data Sheet'!F42 | G4: ='Data Sheet'!G42 | H4: ='Data Sheet'!H42 | I4: ='Data Sheet'!I42 | ... K4: ='Data Sheet'!K42
A5: Expenses | B5: ='Data Sheet'!B43 | C5: ='Data Sheet'!C43 | D5: ='Data Sheet'!D43 | E5: ='Data Sheet'!E43 | F5: ='Data Sheet'!F43 | G5: ='Data Sheet'!G43 | H5: ='Data Sheet'!H43 | I5: ='Data Sheet'!I43 | ... K5: ='Data Sheet'!K43
A6: Operating Profit | B6: ='Data Sheet'!B50 | C6: ='Data Sheet'!C50 | D6: ='Data Sheet'!D50 | E6: ='Data Sheet'!E50 | F6: ='Data Sheet'!F50 | G6: ='Data Sheet'!G50 | H6: ='Data Sheet'!H50 | I6: ='Data Sheet'!I50 | ... K6: ='Data Sheet'!K50
A7: Other Income | B7: ='Data Sheet'!B44 | C7: ='Data Sheet'!C44 | D7: ='Data Sheet'!D44 | E7: ='Data Sheet'!E44 | F7: ='Data Sheet'!F44 | G7: ='Data Sheet'!G44 | H7: ='Data Sheet'!H44 | I7: ='Data Sheet'!I44 | ... K7: ='Data Sheet'!K44
A8: Depreciation | B8: ='Data Sheet'!B45 | C8: ='Data Sheet'!C45 | D8: ='Data Sheet'!D45 | E8: ='Data Sheet'!E45 | F8: ='Data Sheet'!F45 | G8: ='Data Sheet'!G45 | H8: ='Data Sheet'!H45 | I8: ='Data Sheet'!I45 | ... K8: ='Data Sheet'!K45
A9: Interest | B9: ='Data Sheet'!B46 | C9: ='Data Sheet'!C46 | D9: ='Data Sheet'!D46 | E9: ='Data Sheet'!E46 | F9: ='Data Sheet'!F46 | G9: ='Data Sheet'!G46 | H9: ='Data Sheet'!H46 | I9: ='Data Sheet'!I46 | ... K9: ='Data Sheet'!K46
A10: Profit before tax | B10: ='Data Sheet'!B47 | C10: ='Data Sheet'!C47 | D10: ='Data Sheet'!D47 | E10: ='Data Sheet'!E47 | F10: ='Data Sheet'!F47 | G10: ='Data Sheet'!G47 | H10: ='Data Sheet'!H47 | I10: ='Data Sheet'!I47 | ... K10: ='Data Sheet'!K47
A11: Tax | B11: ='Data Sheet'!B48 | C11: ='Data Sheet'!C48 | D11: ='Data Sheet'!D48 | E11: ='Data Sheet'!E48 | F11: ='Data Sheet'!F48 | G11: ='Data Sheet'!G48 | H11: ='Data Sheet'!H48 | I11: ='Data Sheet'!I48 | ... K11: ='Data Sheet'!K48
A12: Net profit | B12: ='Data Sheet'!B49 | C12: ='Data Sheet'!C49 | D12: ='Data Sheet'!D49 | E12: ='Data Sheet'!E49 | F12: ='Data Sheet'!F49 | G12: ='Data Sheet'!G49 | H12: ='Data Sheet'!H49 | I12: ='Data Sheet'!I49 | ... K12: ='Data Sheet'!K49
A14: OPM | B14: =IF(B4>0,B6/B4,"") | C14: =IF(C4>0,C6/C4,"") | D14: =IF(D4>0,D6/D4,"") | E14: =IF(E4>0,E6/E4,"") | F14: =IF(F4>0,F6/F4,"") | G14: =IF(G4>0,G6/G4,"") | H14: =IF(H4>0,H6/H4,"") | I14: =IF(I4>0,I6/I4,"") | ... K14: =IF(K4>0,K6/K4,"")

Sheet Balance Sheet
A1: ='Profit & Loss'!A1 | E1: =UPDATE | J1: SCREENER.IN
A3: Narration | B3: ='Data Sheet'!B56 | C3: ='Data Sheet'!C56 | D3: ='Data Sheet'!D56 | E3: ='Data Sheet'!E56 | F3: ='Data Sheet'!F56 | G3: ='Data Sheet'!G56 | H3: ='Data Sheet'!H56 | I3: ='Data Sheet'!I56 | ... K3: ='Data Sheet'!K56
A4: Equity Share Capital | B4: ='Data Sheet'!B57 | C4: ='Data Sheet'!C57 | D4: ='Data Sheet'!D57 | E4: ='Data Sheet'!E57 | F4: ='Data Sheet'!F57 | G4: ='Data Sheet'!G57 | H4: ='Data Sheet'!H57 | I4: ='Data Sheet'!I57 | ... K4: ='Data Sheet'!K57
A5: Reserves | B5: ='Data Sheet'!B58 | C5: ='Data Sheet'!C58 | D5: ='Data Sheet'!D58 | E5: ='Data Sheet'!E58 | F5: ='Data Sheet'!F58 | G5: ='Data Sheet'!G58 | H5: ='Data Sheet'!H58 | I5: ='Data Sheet'!I58 | ... K5: ='Data Sheet'!K58
A6: Borrowings | B6: ='Data Sheet'!B59 | C6: ='Data Sheet'!C59 | D6: ='Data Sheet'!D59 | E6: ='Data Sheet'!E59 | F6: ='Data Sheet'!F59 | G6: ='Data Sheet'!G59 | H6: ='Data Sheet'!H59 | I6: ='Data Sheet'!I59 | ... K6: ='Data Sheet'!K59
A7: Other Liabilities | B7: ='Data Sheet'!B60 | C7: ='Data Sheet'!C60 | D7: ='Data Sheet'!D60 | E7: ='Data Sheet'!E60 | F7: ='Data Sheet'!F60 | G7: ='Data Sheet'!G60 | H7: ='Data Sheet'!H60 | I7: ='Data Sheet'!I60 | ... K7: ='Data Sheet'!K60
A8: Total | B8: ='Data Sheet'!B61 | C8: ='Data Sheet'!C61 | D8: ='Data Sheet'!D61 | E8: ='Data Sheet'!E61 | F8: ='Data Sheet'!F61 | G8: ='Data Sheet'!G61 | H8: ='Data Sheet'!H61 | I8: ='Data Sheet'!I61 | ... K8: ='Data Sheet'!K61
A10: Net Block | B10: ='Data Sheet'!B62 | C10: ='Data Sheet'!C62 | D10: ='Data Sheet'!D62 | E10: ='Data Sheet'!E62 | F10: ='Data Sheet'!F62 | G10: ='Data Sheet'!G62 | H10: ='Data Sheet'!H62 | I10: ='Data Sheet'!I62 | ... K10: ='Data Sheet'!K62
A11: Capital Work in Progress | B11: ='Data Sheet'!B63 | C11: ='Data Sheet'!C63 | D11: ='Data Sheet'!D63 | E11: ='Data Sheet'!E63 | F11: ='Data Sheet'!F63 | G11: ='Data Sheet'!G63 | H11: ='Data Sheet'!H63 | I11: ='Data Sheet'!I63 | ... K11: ='Data Sheet'!K63
A12: Investments | B12: ='Data Sheet'!B64 | C12: ='Data Sheet'!C64 | D12: ='Data Sheet'!D64 | E12: ='Data Sheet'!E64 | F12: ='Data Sheet'!F64 | G12: ='Data Sheet'!G64 | H12: ='Data Sheet'!H64 | I12: ='Data Sheet'!I64 | ... K12: ='Data Sheet'!K64
A13: Other Assets | B13: ='Data Sheet'!B65 | C13: ='Data Sheet'!C65 | D13: ='Data Sheet'!D65 | E13: ='Data Sheet'!E65 | F13: ='Data Sheet'!F65 | G13: ='Data Sheet'!G65 | H13: ='Data Sheet'!H65 | I13: ='Data Sheet'!I65 | ... K13: ='Data Sheet'!K65
A14: Total | B14: ='Data Sheet'!B66 | C14: ='Data Sheet'!C66 | D14: ='Data Sheet'!D66 | E14: ='Data Sheet'!E66 | F14: ='Data Sheet'!F66 | G14: ='Data Sheet'!G66 | H14: ='Data Sheet'!H66 | I14: ='Data Sheet'!I66 | ... K14: ='Data Sheet'!K66
A16: Working Capital | B16: =B13-B7 | C16: =C13-C7 | D16: =D13-D7 | E16: =E13-E7 | F16: =F13-F7 | G16: =G13-G7 | H16: =H13-H7 | I16: =I13-I7 | ... K16: =K13-K7
A17: Debtors | B17: ='Data Sheet'!B67 | C17: ='Data Sheet'!C67 | D17: ='Data Sheet'!D67 | E17: ='Data Sheet'!E67 | F17: ='Data Sheet'!F67 | G17: ='Data Sheet'!G67 | H17: ='Data Sheet'!H67 | I17: ='Data Sheet'!I67 | ... K17: ='Data Sheet'!K67
A18: Inventory | B18: ='Data Sheet'!B68 | C18: ='Data Sheet'!C68 | D18: ='Data Sheet'!D68 | E18: ='Data Sheet'!E68 | F18: ='Data Sheet'!F68 | G18: ='Data Sheet'!G68 | H18: ='Data Sheet'!H68 | I18: ='Data Sheet'!I68 | ... K18: ='Data Sheet'!K68
A20: Debtor Days | B20: =IF('Profit & Loss'!B4>0,'Balance Sheet'!B17/('Profit & Loss'!B4/365),0) | C20: =IF('Profit & Loss'!C4>0,'Balance Sheet'!C17/('Profit & Loss'!C4/365),0) | D20: =IF('Profit & Loss'!D4>0,'Balance Sheet'!D17/('Profit & Loss'!D4/365),0) | E20: =IF('Profit & Loss'!E4>0,'Balance Sheet'!E17/('Profit & Loss'!E4/365),0) | F20: =IF('Profit & Loss'!F4>0,'Balance Sheet'!F17/('Profit & Loss'!F4/365),0) | G20: =IF('Profit & Loss'!G4>0,'Balance Sheet'!G17/('Profit & Loss'!G4/365),0) | H20: =IF('Profit & Loss'!H4>0,'Balance Sheet'!H17/('Profit & Loss'!H4/365),0) | I20: =IF('Profit & Loss'!I4>0,'Balance Sheet'!I17/('Profit & Loss'!I4/365),0) | ... K20: =IF('Profit & Loss'!K4>0,'Balance Sheet'!K17/('Profit & Loss'!K4/365),0)
A21: Inventory Turnover | B21: =IF('Balance Sheet'!B18>0,'Profit & Loss'!B4/'Balance Sheet'!B18,0) | C21: =IF('Balance Sheet'!C18>0,'Profit & Loss'!C4/'Balance Sheet'!C18,0) | D21: =IF('Balance Sheet'!D18>0,'Profit & Loss'!D4/'Balance Sheet'!D18,0) | E21: =IF('Balance Sheet'!E18>0,'Profit & Loss'!E4/'Balance Sheet'!E18,0) | F21: =IF('Balance Sheet'!F18>0,'Profit & Loss'!F4/'Balance Sheet'!F18,0) | G21: =IF('Balance Sheet'!G18>0,'Profit & Loss'!G4/'Balance Sheet'!G18,0) | H21: =IF('Balance Sheet'!H18>0,'Profit & Loss'!H4/'Balance Sheet'!H18,0) | I21: =IF('Balance Sheet'!I18>0,'Profit & Loss'!I4/'Balance Sheet'!I18,0) | ... K21: =IF('Balance Sheet'!K18>0,'Profit & Loss'!K4/'Balance Sheet'!K18,0)
A23: Return on Equity | B23: =IF(SUM('Balance Sheet'!B4:B5)>0,'Profit & Loss'!B12/SUM('Balance Sheet'!B4:B5),"") | C23: =IF(SUM('Balance Sheet'!C4:C5)>0,'Profit & Loss'!C12/SUM('Balance Sheet'!C4:C5),"") | D23: =IF(SUM('Balance Sheet'!D4:D5)>0,'Profit & Loss'!D12/SUM('Balance Sheet'!D4:D5),"") | E23: =IF(SUM('Balance Sheet'!E4:E5)>0,'Profit & Loss'!E12/SUM('Balance Sheet'!E4:E5),"") | F23: =IF(SUM('Balance Sheet'!F4:F5)>0,'Profit & Loss'!F12/SUM('Balance Sheet'!F4:F5),"") | G23: =IF(SUM('Balance Sheet'!G4:G5)>0,'Profit & Loss'!G12/SUM('Balance Sheet'!G4:G5),"") | H23: =IF(SUM('Balance Sheet'!H4:H5)>0,'Profit & Loss'!H12/SUM('Balance Sheet'!H4:H5),"") | I23: =IF(SUM('Balance Sheet'!I4:I5)>0,'Profit & Loss'!I12/SUM('Balance Sheet'!I4:I5),"") | ... K23: =IF(SUM('Balance Sheet'!K4:K5)>0,'Profit & Loss'!K12/SUM('Balance Sheet'!K4:K5),"")
A24: Return on Capital Emp | C24: =IF((B4+B5+B6+C4+C5+C6)>0,('Profit & Loss'!C10+'Profit & Loss'!C9)*2/(B4+B5+B6+C4+C5+C6),"") | D24: =IF((C4+C5+C6+D4+D5+D6)>0,('Profit & Loss'!D10+'Profit & Loss'!D9)*2/(C4+C5+C6+D4+D5+D6),"") | E24: =IF((D4+D5+D6+E4+E5+E6)>0,('Profit & Loss'!E10+'Profit & Loss'!E9)*2/(D4+D5+D6+E4+E5+E6),"") | F24: =IF((E4+E5+E6+F4+F5+F6)>0,('Profit & Loss'!F10+'Profit & Loss'!F9)*2/(E4+E5+E6+F4+F5+F6),"") | G24: =IF((F4+F5+F6+G4+G5+G6)>0,('Profit & Loss'!G10+'Profit & Loss'!G9)*2/(F4+F5+F6+G4+G5+G6),"") | H24: =IF((G4+G5+G6+H4+H5+H6)>0,('Profit & Loss'!H10+'Profit & Loss'!H9)*2/(G4+G5+G6+H4+H5+H6),"") | I24: =IF((H4+H5+H6+I4+I5+I6)>0,('Profit & Loss'!I10+'Profit & Loss'!I9)*2/(H4+H5+H6+I4+I5+I6),"") | J24: =IF((I4+I5+I6+J4+J5+J6)>0,('Profit & Loss'!J10+'Profit & Loss'!J9)*2/(I4+I5+I6+J4+J5+J6),"") | K24: =IF((J4+J5+J6+K4+K5+K6)>0,('Profit & Loss'!K10+'Profit & Loss'!K9)*2/(J4+J5+J6+K4+K5+K6),"")

Sheet Cash Flow
A1: ='Balance Sheet'!A1 | E1: =UPDATE | J1: SCREENER.IN
A3: Narration | B3: ='Data Sheet'!B81 | C3: ='Data Sheet'!C81 | D3: ='Data Sheet'!D81 | E3: ='Data Sheet'!E81 | F3: ='Data Sheet'!F81 | G3: ='Data Sheet'!G81 | H3: ='Data Sheet'!H81 | I3: ='Data Sheet'!I81 | ... K3: ='Data Sheet'!K81
A4: Cash from Operating Activity | B4: ='Data Sheet'!B82 | C4: ='Data Sheet'!C82 | D4: ='Data Sheet'!D82 | E4: ='Data Sheet'!E82 | F4: ='Data Sheet'!F82 | G4: ='Data Sheet'!G82 | H4: ='Data Sheet'!H82 | I4: ='Data Sheet'!I82 | ... K4: ='Data Sheet'!K82
A5: Cash from Investing Activity | B5: ='Data Sheet'!B83 | C5: ='Data Sheet'!C83 | D5: ='Data Sheet'!D83 | E5: ='Data Sheet'!E83 | F5: ='Data Sheet'!F83 | G5: ='Data Sheet'!G83 | H5: ='Data Sheet'!H83 | I5: ='Data Sheet'!I83 | ... K5: ='Data Sheet'!K83
A6: Cash from Financing Activity | B6: ='Data Sheet'!B84 | C6: ='Data Sheet'!C84 | D6: ='Data Sheet'!D84 | E6: ='Data Sheet'!E84 | F6: ='Data Sheet'!F84 | G6: ='Data Sheet'!G84 | H6: ='Data Sheet'!H84 | I6: ='Data Sheet'!I84 | ... K6: ='Data Sheet'!K84
A7: Net Cash Flow | B7: ='Data Sheet'!B85 | C7: ='Data Sheet'!C85 | D7: ='Data Sheet'!D85 | E7: ='Data Sheet'!E85 | F7: ='Data Sheet'!F85 | G7: ='Data Sheet'!G85 | H7: ='Data Sheet'!H85 | I7: ='Data Sheet'!I85 | ... K7: ='Data Sheet'!K85

Sheet Customization
A1: How to use it?
A3: You can customize this workbook as you want.
B4: You can add custom formating, add conditional formating, add your own formulas… do ANYTHING.
B5: Please don't edit the "Data Sheet" only.
A7: After customization, you can upload this back on Screener.
B8: Upload on: | C8: https://www.screener.in/excel/
A10: Download your customized workbooks now onwards.
B11: Now whenever you will "Export to excel" from Screener, it will export your customized file.
A14: TESTING:
B15: This is a testing feature currently.
B16: You can report any formula errors on the worksheet at: support@screener.in

Sheet Common Size Statement
B2: ="Common Size Statement - "&'Data Sheet'!$B$1
B4: Particulars | C4: ='Data Sheet'!B$16 | D4: ='Data Sheet'!C$16 | E4: ='Data Sheet'!D$16 | F4: ='Data Sheet'!E$16 | G4: ='Data Sheet'!F$16 | H4: ='Data Sheet'!G$16 | I4: ='Data Sheet'!H$16 | J4: ='Data Sheet'!I$16 | ... L4: ='Data Sheet'!K$16
B6: ='Data Sheet'!A17 | C6: ='Data Sheet'!B17/'Data Sheet'!B$17 | D6: ='Data Sheet'!C17/'Data Sheet'!C$17 | E6: ='Data Sheet'!D17/'Data Sheet'!D$17 | F6: ='Data Sheet'!E17/'Data Sheet'!E$17 | G6: ='Data Sheet'!F17/'Data Sheet'!F$17 | H6: ='Data Sheet'!G17/'Data Sheet'!G$17 | I6: ='Data Sheet'!H17/'Data Sheet'!H$17 | J6: ='Data Sheet'!I17/'Data Sheet'!I$17 | ... L6: ='Data Sheet'!K17/'Data Sheet'!K$17
B7: ='Data Sheet'!A18 | C7: ='Data Sheet'!B18/'Data Sheet'!B$17 | D7: ='Data Sheet'!C18/'Data Sheet'!C$17 | E7: ='Data Sheet'!D18/'Data Sheet'!D$17 | F7: ='Data Sheet'!E18/'Data Sheet'!E$17 | G7: ='Data Sheet'!F18/'Data Sheet'!F$17 | H7: ='Data Sheet'!G18/'Data Sheet'!G$17 | I7: ='Data Sheet'!H18/'Data Sheet'!H$17 | J7: ='Data Sheet'!I18/'Data Sheet'!I$17 | ... L7: ='Data Sheet'!K18/'Data Sheet'!K$17
B8: ='Data Sheet'!A19 | C8: ='Data Sheet'!B19/'Data Sheet'!B$17 | D8: ='Data Sheet'!C19/'Data Sheet'!C$17 | E8: ='Data Sheet'!D19/'Data Sheet'!D$17 | F8: ='Data Sheet'!E19/'Data Sheet'!E$17 | G8: ='Data Sheet'!F19/'Data Sheet'!F$17 | H8: ='Data Sheet'!G19/'Data Sheet'!G$17 | I8: ='Data Sheet'!H19/'Data Sheet'!H$17 | J8: ='Data Sheet'!I19/'Data Sheet'!I$17 | ... L8: ='Data Sheet'!K19/'Data Sheet'!K$17
B9: ='Data Sheet'!A20 | C9: ='Data Sheet'!B20/'Data Sheet'!B$17 | D9: ='Data Sheet'!C20/'Data Sheet'!C$17 | E9: ='Data Sheet'!D20/'Data Sheet'!D$17 | F9: ='Data Sheet'!E20/'Data Sheet'!E$17 | G9: ='Data Sheet'!F20/'Data Sheet'!F$17 | H9: ='Data Sheet'!G20/'Data Sheet'!G$17 | I9: ='Data Sheet'!H20/'Data Sheet'!H$17 | J9: ='Data Sheet'!I20/'Data Sheet'!I$17 | ... L9: ='Data Sheet'!K20/'Data Sheet'!K$17
B10: ='Data Sheet'!A21 | C10: ='Data Sheet'!B21/'Data Sheet'!B$17 | D10: ='Data Sheet'!C21/'Data Sheet'!C$17 | E10: ='Data Sheet'!D21/'Data Sheet'!D$17 | F10: ='Data Sheet'!E21/'Data Sheet'!E$17 | G10: ='Data Sheet'!F21/'Data Sheet'!F$17 | H10: ='Data Sheet'!G21/'Data Sheet'!G$17 | I10: ='Data Sheet'!H21/'Data Sheet'!H$17 | J10: ='Data Sheet'!I21/'Data Sheet'!I$17 | ... L10: ='Data Sheet'!K21/'Data Sheet'!K$17
B11: ='Data Sheet'!A22 | C11: ='Data Sheet'!B22/'Data Sheet'!B$17 | D11: ='Data Sheet'!C22/'Data Sheet'!C$17 | E11: ='Data Sheet'!D22/'Data Sheet'!D$17 | F11: ='Data Sheet'!E22/'Data Sheet'!E$17 | G11: ='Data Sheet'!F22/'Data Sheet'!F$17 | H11: ='Data Sheet'!G22/'Data Sheet'!G$17 | I11: ='Data Sheet'!H22/'Data Sheet'!H$17 | J11: ='Data Sheet'!I22/'Data Sheet'!I$17 | ... L11: ='Data Sheet'!K22/'Data Sheet'!K$17
B12: ='Data Sheet'!A23 | C12: ='Data Sheet'!B23/'Data Sheet'!B$17 | D12: ='Data Sheet'!C23/'Data Sheet'!C$17 | E12: ='Data Sheet'!D23/'Data Sheet'!D$17 | F12: ='Data Sheet'!E23/'Data Sheet'!E$17 | G12: ='Data Sheet'!F23/'Data Sheet'!F$17 | H12: ='Data Sheet'!G23/'Data Sheet'!G$17 | I12: ='Data Sheet'!H23/'Data Sheet'!H$17 | J12: ='Data Sheet'!I23/'Data Sheet'!I$17 | ... L12: ='Data Sheet'!K23/'Data Sheet'!K$17
B13: ='Data Sheet'!A24 | C13: ='Data Sheet'!B24/'Data Sheet'!B$17 | D13: ='Data Sheet'!C24/'Data Sheet'!C$17 | E13: ='Data Sheet'!D24/'Data Sheet'!D$17 | F13: ='Data Sheet'!E24/'Data Sheet'!E$17 | G13: ='Data Sheet'!F24/'Data Sheet'!F$17 | H13: ='Data Sheet'!G24/'Data Sheet'!G$17 | I13: ='Data Sheet'!H24/'Data Sheet'!H$17 | J13: ='Data Sheet'!I24/'Data Sheet'!I$17 | ... L13: ='Data Sheet'!K24/'Data Sheet'!K$17
B14: ='Data Sheet'!A25 | C14: ='Data Sheet'!B25/'Data Sheet'!B$17 | D14: ='Data Sheet'!C25/'Data Sheet'!C$17 | E14: ='Data Sheet'!D25/'Data Sheet'!D$17 | F14: ='Data Sheet'!E25/'Data Sheet'!E$17 | G14: ='Data Sheet'!F25/'Data Sheet'!F$17 | H14: ='Data Sheet'!G25/'Data Sheet'!G$17 | I14: ='Data Sheet'!H25/'Data Sheet'!H$17 | J14: ='Data Sheet'!I25/'Data Sheet'!I$17 | ... L14: ='Data Sheet'!K25/'Data Sheet'!K$17
B15: ='Data Sheet'!A26 | C15: ='Data Sheet'!B26/'Data Sheet'!B$17 | D15: ='Data Sheet'!C26/'Data Sheet'!C$17 | E15: ='Data Sheet'!D26/'Data Sheet'!D$17 | F15: ='Data Sheet'!E26/'Data Sheet'!E$17 | G15: ='Data Sheet'!F26/'Data Sheet'!F$17 | H15: ='Data Sheet'!G26/'Data Sheet'!G$17 | I15: ='Data Sheet'!H26/'Data Sheet'!H$17 | J15: ='Data Sheet'!I26/'Data Sheet'!I$17 | ... L15: ='Data Sheet'!K26/'Data Sheet'!K$17
B16: ='Data Sheet'!A27 | C16: ='Data Sheet'!B27/'Data Sheet'!B$17 | D16: ='Data Sheet'!C27/'Data Sheet'!C$17 | E16: ='Data Sheet'!D27/'Data Sheet'!D$17 | F16: ='Data Sheet'!E27/'Data Sheet'!E$17 | G16: ='Data Sheet'!F27/'Data Sheet'!F$17 | H16: ='Data Sheet'!G27/'Data Sheet'!G$17 | I16: ='Data Sheet'!H27/'Data Sheet'!H$17 | J16: ='Data Sheet'!I27/'Data Sheet'!I$17 | ... L16: ='Data Sheet'!K27/'Data Sheet'!K$17
B17: ='Data Sheet'!A28 | C17: ='Data Sheet'!B28/'Data Sheet'!B$17 | D17: ='Data Sheet'!C28/'Data Sheet'!C$17 | E17: ='Data Sheet'!D28/'Data Sheet'!D$17 | F17: ='Data Sheet'!E28/'Data Sheet'!E$17 | G17: ='Data Sheet'!F28/'Data Sheet'!F$17 | H17: ='Data Sheet'!G28/'Data Sheet'!G$17 | I17: ='Data Sheet'!H28/'Data Sheet'!H$17 | J17: ='Data Sheet'!I28/'Data Sheet'!I$17 | ... L17: ='Data Sheet'!K28/'Data Sheet'!K$17
... B21: ='Data Sheet'!A32 | C21: ='Data Sheet'!B32/'Data Sheet'!B$17 | D21: ='Data Sheet'!C32/'Data Sheet'!C$17 | E21: ='Data Sheet'!D32/'Data Sheet'!D$17 | F21: ='Data Sheet'!E32/'Data Sheet'!E$17 | G21: ='Data Sheet'!F32/'Data Sheet'!F$17 | H21: ='Data Sheet'!G32/'Data Sheet'!G$17 | I21: ='Data Sheet'!H32/'Data Sheet'!H$17 | J21: ='Data Sheet'!I32/'Data Sheet'!I$17 | ... L21: ='Data Sheet'!K32/'Data Sheet'!K$17
B23: ="Common Size Balance Sheet - "&'Data Sheet'!$B$1
B25: Particulars | C25: ='Data Sheet'!B$16 | D25: ='Data Sheet'!C$16 | E25: ='Data Sheet'!D$16 | F25: ='Data Sheet'!E$16 | G25: ='Data Sheet'!F$16 | H25: ='Data Sheet'!G$16 | I25: ='Data Sheet'!H$16 | J25: ='Data Sheet'!I$16 | ... L25: ='Data Sheet'!K$16
B27: Total Liabilities | C27: ='Data Sheet'!B61/'Data Sheet'!B$61 | D27: ='Data Sheet'!C61/'Data Sheet'!C$61 | E27: ='Data Sheet'!D61/'Data Sheet'!D$61 | F27: ='Data Sheet'!E61/'Data Sheet'!E$61 | G27: ='Data Sheet'!F61/'Data Sheet'!F$61 | H27: ='Data Sheet'!G61/'Data Sheet'!G$61 | I27: ='Data Sheet'!H61/'Data Sheet'!H$61 | J27: ='Data Sheet'!I61/'Data Sheet'!I$61 | ... L27: ='Data Sheet'!K61/'Data Sheet'!K$61
B28: ='Data Sheet'!A57 | C28: ='Data Sheet'!B57/'Data Sheet'!B$61 | D28: ='Data Sheet'!C57/'Data Sheet'!C$61 | E28: ='Data Sheet'!D57/'Data Sheet'!D$61 | F28: ='Data Sheet'!E57/'Data Sheet'!E$61 | G28: ='Data Sheet'!F57/'Data Sheet'!F$61 | H28: ='Data Sheet'!G57/'Data Sheet'!G$61 | I28: ='Data Sheet'!H57/'Data Sheet'!H$61 | J28: ='Data Sheet'!I57/'Data Sheet'!I$61 | ... L28: ='Data Sheet'!K57/'Data Sheet'!K$61
B29: ='Data Sheet'!A58 | C29: ='Data Sheet'!B58/'Data Sheet'!B$61 | D29: ='Data Sheet'!C58/'Data Sheet'!C$61 | E29: ='Data Sheet'!D58/'Data Sheet'!D$61 | F29: ='Data Sheet'!E58/'Data Sheet'!E$61 | G29: ='Data Sheet'!F58/'Data Sheet'!F$61 | H29: ='Data Sheet'!G58/'Data Sheet'!G$61 | I29: ='Data Sheet'!H58/'Data Sheet'!H$61 | J29: ='Data Sheet'!I58/'Data Sheet'!I$61 | ... L29: ='Data Sheet'!K58/'Data Sheet'!K$61
B30: ='Data Sheet'!A59 | C30: ='Data Sheet'!B59/'Data Sheet'!B$61 | D30: ='Data Sheet'!C59/'Data Sheet'!C$61 | E30: ='Data Sheet'!D59/'Data Sheet'!D$61 | F30: ='Data Sheet'!E59/'Data Sheet'!E$61 | G30: ='Data Sheet'!F59/'Data Sheet'!F$61 | H30: ='Data Sheet'!G59/'Data Sheet'!G$61 | I30: ='Data Sheet'!H59/'Data Sheet'!H$61 | J30: ='Data Sheet'!I59/'Data Sheet'!I$61 | ... L30: ='Data Sheet'!K59/'Data Sheet'!K$61
B31: ='Data Sheet'!A60 | C31: ='Data Sheet'!B60/'Data Sheet'!B$61 | D31: ='Data Sheet'!C60/'Data Sheet'!C$61 | E31: ='Data Sheet'!D60/'Data Sheet'!D$61 | F31: ='Data Sheet'!E60/'Data Sheet'!E$61 | G31: ='Data Sheet'!F60/'Data Sheet'!F$61 | H31: ='Data Sheet'!G60/'Data Sheet'!G$61 | I31: ='Data Sheet'!H60/'Data Sheet'!H$61 | J31: ='Data Sheet'!I60/'Data Sheet'!I$61 | ... L31: ='Data Sheet'!K60/'Data Sheet'!K$61
B33: Total Assets | C33: ='Data Sheet'!B66/'Data Sheet'!B$66 | D33: ='Data Sheet'!C66/'Data Sheet'!C$66 | E33: ='Data Sheet'!D66/'Data Sheet'!D$66 | F33: ='Data Sheet'!E66/'Data Sheet'!E$66 | G33: ='Data Sheet'!F66/'Data Sheet'!F$66 | H33: ='Data Sheet'!G66/'Data Sheet'!G$66 | I33: ='Data Sheet'!H66/'Data Sheet'!H$66 | J33: ='Data Sheet'!I66/'Data Sheet'!I$66 | ... L33: ='Data Sheet'!K66/'Data Sheet'!K$66
B34: Fixed Assets Net Block | C34: ='Data Sheet'!B62/'Data Sheet'!B$66 | D34: ='Data Sheet'!C62/'Data Sheet'!C$66 | E34: ='Data Sheet'!D62/'Data Sheet'!D$66 | F34: ='Data Sheet'!E62/'Data Sheet'!E$66 | G34: ='Data Sheet'!F62/'Data Sheet'!F$66 | H34: ='Data Sheet'!G62/'Data Sheet'!G$66 | I34: ='Data Sheet'!H62/'Data Sheet'!H$66 | J34: ='Data Sheet'!I62/'Data Sheet'!I$66 | ... L34: ='Data Sheet'!K62/'Data Sheet'!K$66
B35: ='Data Sheet'!A63 | C35: ='Data Sheet'!B63/'Data Sheet'!B$66 | D35: ='Data Sheet'!C63/'Data Sheet'!C$66 | E35: ='Data Sheet'!D63/'Data Sheet'!D$66 | F35: ='Data Sheet'!E63/'Data Sheet'!E$66 | G35: ='Data Sheet'!F63/'Data Sheet'!F$66 | H35: ='Data Sheet'!G63/'Data Sheet'!G$66 | I35: ='Data Sheet'!H63/'Data Sheet'!H$66 | J35: ='Data Sheet'!I63/'Data Sheet'!I$66 | ... L35: ='Data Sheet'!K63/'Data Sheet'!K$66
B36: ='Data Sheet'!A64 | C36: ='Data Sheet'!B64/'Data Sheet'!B$66 | D36: ='Data Sheet'!C64/'Data Sheet'!C$66 | E36: ='Data Sheet'!D64/'Data Sheet'!D$66 | F36: ='Data Sheet'!E64/'Data Sheet'!E$66 | G36: ='Data Sheet'!F64/'Data Sheet'!F$66 | H36: ='Data Sheet'!G64/'Data Sheet'!G$66 | I36: ='Data Sheet'!H64/'Data Sheet'!H$66 | J36: ='Data Sheet'!I64/'Data Sheet'!I$66 | ... L36: ='Data Sheet'!K64/'Data Sheet'!K$66
B37: ='Data Sheet'!A65 | C37: ='Data Sheet'!B74/'Data Sheet'!B66 | D37: ='Data Sheet'!C74/'Data Sheet'!C66 | E37: ='Data Sheet'!D74/'Data Sheet'!D66 | F37: ='Data Sheet'!E74/'Data Sheet'!E66 | G37: ='Data Sheet'!F74/'Data Sheet'!F66 | H37: ='Data Sheet'!G74/'Data Sheet'!G66 | I37: ='Data Sheet'!H74/'Data Sheet'!H66 | J37: ='Data Sheet'!I74/'Data Sheet'!I66 | ... L37: ='Data Sheet'!K74/'Data Sheet'!K66
B38: ='Data Sheet'!A67 | C38: ='Data Sheet'!B67/'Data Sheet'!B$66 | D38: ='Data Sheet'!C67/'Data Sheet'!C$66 | E38: ='Data Sheet'!D67/'Data Sheet'!D$66 | F38: ='Data Sheet'!E67/'Data Sheet'!E$66 | G38: ='Data Sheet'!F67/'Data Sheet'!F$66 | H38: ='Data Sheet'!G67/'Data Sheet'!G$66 | I38: ='Data Sheet'!H67/'Data Sheet'!H$66 | J38: ='Data Sheet'!I67/'Data Sheet'!I$66 | ... L38: ='Data Sheet'!K67/'Data Sheet'!K$66
B39: ='Data Sheet'!A68 | C39: ='Data Sheet'!B68/'Data Sheet'!B$66 | D39: ='Data Sheet'!C68/'Data Sheet'!C$66 | E39: ='Data Sheet'!D68/'Data Sheet'!D$66 | F39: ='Data Sheet'!E68/'Data Sheet'!E$66 | G39: ='Data Sheet'!F68/'Data Sheet'!F$66 | H39: ='Data Sheet'!G68/'Data Sheet'!G$66 | I39: ='Data Sheet'!H68/'Data Sheet'!H$66 | J39: ='Data Sheet'!I68/'Data Sheet'!I$66 | ... L39: ='Data Sheet'!K68/'Data Sheet'!K$66
B40: ='Data Sheet'!A69 | C40: ='Data Sheet'!B69/'Data Sheet'!B$66 | D40: ='Data Sheet'!C69/'Data Sheet'!C$66 | E40: ='Data Sheet'!D69/'Data Sheet'!D$66 | F40: ='Data Sheet'!E69/'Data Sheet'!E$66 | G40: ='Data Sheet'!F69/'Data Sheet'!F$66 | H40: ='Data Sheet'!G69/'Data Sheet'!G$66 | I40: ='Data Sheet'!H69/'Data Sheet'!H$66 | J40: ='Data Sheet'!I69/'Data Sheet'!I$66 | ... L40: ='Data Sheet'!K69/'Data Sheet'!K$66

Sheet Data Sheet
A1: COMPANY NAME | B1: ADANI ENTERPRISES LTD | E1: =IF(B2<>B3, "A NEW VERSION OF THE WORKSHEET IS AVAILABLE", "")
A2: LATEST VERSION | B2: 2.1 | E2: PLEASE DO NOT MAKE ANY CHANGES TO THIS SHEET
A3: CURRENT VERSION | B3: 2.1
A5: META
A6: Number of shares | B6: =IF(B9>0, B9/B8, 0)
A7: Face Value | B7: 1
A8: Current Price | B8: 2999
A9: Market Capitalization | B9: 405443
A15: PROFIT & LOSS
A16: Report Date | B16: 42825 | C16: 43190 | D16: 43555 | E16: 43921 | F16: 44286 | G16: 44651 | H16: 45016 | I16: 45382 | J16: 45747 | K16: 46112
A17: Sales | B17: 36532.86 | C17: 35923.92 | D17: 40378.66 | E17: 43402.56 | F17: 39537.13 | G17: 69420.18 | H17: 127539.5 | I17: 96420.98 | J17: 97894.75 | K17: 100468.61
A18: Raw Material Cost | B18: 30945.16 | C18: 30771.08 | D18: 33821.4 | E18: 34350.2 | F18: 29791.08 | G18: 57651.32 | H18: 93814.06 | I18: 51507.72 | J18: 49524.73 | K18: 56933.41
A19: Change in Inventory | B19: -36.38 | C19: 772.74 | D19: 499.99 | E19: -310.13 | F19: -456.74 | G19: 3933.82 | H19: 327.16 | I19: 1116.49 | J19: -1844.54 | K19: 2824.59
A20: Power and Fuel | B20: 7.42 | C20: 2.91 | D20: 5.74 | E20: 12.22 | F20: 13.4 | G20: 58.98 | H20: 18.42 | I20: 26.46 | J20: 2037.48 | K20: 2142.7
A21: Other Mfr. Exp | B21: 1910.37 | C21: 2204.89 | D21: 2551.28 | E21: 3115.25 | F21: 4357.88 | G21: 7793.57 | H21: 14377.83 | I21: 22793.04 | J21: 16964.51 | K21: 15610.12
A22: Employee Cost | B22: 511.48 | C22: 568.97 | D22: 657.18 | E22: 683.28 | F22: 830.36 | G22: 1182.1 | H22: 1879.07 | I22: 2332.96 | J22: 3121.84 | K22: 3661.56
A23: Selling and admin | B23: 1004.69 | C23: 928.28 | D23: 1230.62 | E23: 1954.57 | F23: 1306.48 | G23: 2412.38 | H23: 8135.29 | I23: 8272.86 | J23: 9245.98 | K23: 9817.24
A24: Other Expenses | B24: 215.13 | C24: 182.82 | D24: 643.09 | E24: 682.52 | F24: 275.54 | G24: 542.05 | H24: 824.3 | I24: 1227.83 | J24: 903.64 | K24: 1137.39
A25: Other Income | B25: 749.41 | C25: 363.21 | D25: 504.22 | E25: 872.32 | F25: 494.31 | G25: 1012.11 | H25: 834.23 | I25: 1146.39 | J25: 6403.1 | K25: 11688.34
A26: Depreciation | B26: 315.46 | C26: 663.92 | D26: 389.77 | E26: 472.06 | F26: 537.14 | G26: 1247.78 | H26: 2436.14 | I26: 3042.15 | J26: 4211.33 | K26: 6135.34
A27: Interest | B27: 1257.31 | C27: 1250.17 | D27: 1625.07 | E27: 1572.32 | F27: 1376.85 | G27: 2525.88 | H27: 3968.9 | I27: 4554.7 | J27: 5978.02 | K27: 6019.12
... A32: EBITDA | B32: 2651.64 | C32: 2400.92 | D32: 2473.56 | E32: 3166.71 | F32: 2999.96 | G32: 4725.71 | H32: 9651.92 | I32: 12522.99 | J32: 20655.13 | K32: 25679.12
A40: Quarters
A41: Report Date | B41: 45382 | C41: 45473 | D41: 45565 | E41: 45657 | F41: 45747 | G41: 45838 | H41: 45930 | I41: 46022 | J41: 46112 | K41: 46203
A42: Sales | B42: 29180.02 | C42: 25472.4 | D42: 22608.07 | E42: 22848.42 | F42: 26965.86 | G42: 21961.2 | H42: 21248.51 | I42: 24819.59 | J42: 32439.31 | K42: 32923.98
A43: Expenses | B43: 25984.58 | C43: 21766.59 | D43: 18842.27 | E43: 19778.01 | F43: 23255.85 | G43: 18650.91 | H43: 17941.95 | I43: 21178.07 | J43: 28708.56 | K43: 27904.69
A44: Other Income | B44: -175.65 | C44: 590.56 | D44: 582.57 | E44: 648.46 | F44: 4581.51 | G44: 475.42 | H44: 4178.84 | I44: 6287.94 | J44: 747.8 | K44: -2021.74
A45: Depreciation | B45: 811.47 | C45: 934.08 | D45: 1035.19 | E45: 1005.65 | F45: 1236.41 | G45: 1283.95 | H45: 1376.55 | I45: 1371.59 | J45: 2103.25 | K45: 1926
A46: Interest | B46: 1512.62 | C46: 1130.49 | D46: 909.83 | E46: 2141.32 | F46: 1796.38 | G46: 1035.48 | H46: 1711.22 | I46: 1625.94 | J46: 1646.48 | K46: 2420.93
A47: Profit before tax | B47: 695.7 | C47: 2231.8 | D47: 2403.35 | E47: 571.9 | F47: 5258.73 | G47: 1466.28 | H47: 4397.63 | I47: 6931.93 | J47: 728.82 | K47: -1349.38
A48: Tax | B48: 430.12 | C48: 583.6 | D48: 512.37 | E48: 588.44 | F48: 1284.11 | G48: 571.25 | H48: 1001.07 | I48: 1405.11 | J48: 853.72 | K48: 219.04
A49: Net profit | B49: 450.58 | C49: 1454.5 | D49: 1741.75 | E49: 57.83 | F49: 3844.91 | G49: 885.23 | H49: 3198.75 | I49: 5627.02 | J49: -104.93 | K49: -1160.23
A50: Operating Profit | B50: 3195.44 | C50: 3705.81 | D50: 3765.8 | E50: 3070.41 | F50: 3710.01 | G50: 3310.29 | H50: 3306.56 | I50: 3641.52 | J50: 3730.75 | K50: 5019.29
A55: BALANCE SHEET
A56: Report Date | B56: 42825 | C56: 43190 | D56: 43555 | E56: 43921 | F56: 44286 | G56: 44651 | H56: 45016 | I56: 45382 | J56: 45747 | K56: 46112
A57: Equity Share Capital | B57: 109.98 | C57: 109.98 | D57: 109.98 | E57: 109.98 | F57: 109.98 | G57: 109.98 | H57: 114 | I57: 114 | J57: 115.42 | K57: 129.24
A58: Reserves | B58: 14025.99 | C58: 14979.19 | D58: 14645.96 | E58: 16836.59 | F58: 17048.59 | G58: 22146.53 | H58: 32937.01 | I58: 38962.09 | J58: 50198.55 | K58: 80796.71
A59: Borrowings | B59: 20845.72 | C59: 17636.69 | D59: 11243.2 | E59: 12419.3 | F59: 16227.06 | G59: 41604.03 | H59: 53200.46 | I59: 65310.15 | J59: 91472.6 | K59: 106621.79
A60: Other Liabilities | B60: 12629.78 | C60: 23679.48 | D60: 16537.04 | E60: 17509.19 | F60: 18231.09 | G60: 37725.82 | H60: 55027.01 | I60: 56200 | J60: 56056.31 | K60: 73320.64
A61: Total | B61: 47611.47 | C61: 56405.34 | D61: 42536.18 | E61: 46875.06 | F61: 51616.72 | G61: 101586.36 | H61: 141278.48 | I61: 160586.24 | J61: 197842.88 | K61: 260868.38
A62: Net Block | B62: 13667.98 | C62: 10555.19 | D62: 9020.11 | E62: 10476.46 | F62: 10837.61 | G62: 30122.77 | H62: 56881.13 | I62: 65978.3 | J62: 77260.14 | K62: 115173.81
A63: Capital Work in Progress | B63: 7731.49 | C63: 5525.87 | D63: 5764.92 | E63: 7346.73 | F63: 8825.46 | G63: 23544.42 | H63: 24025.21 | I63: 35179.5 | J63: 51515.81 | K63: 51753.42
A64: Investments | B64: 1041.75 | C64: 1460.72 | D64: 1511.35 | E64: 1952.49 | F64: 5502.94 | G64: 4292.21 | H64: 6310.17 | I64: 8700.69 | J64: 9886.61 | K64: 9428.37
A65: Other Assets | B65: 25170.25 | C65: 38863.56 | D65: 26239.8 | E65: 27099.38 | F65: 26450.71 | G65: 43626.96 | H65: 54061.97 | I65: 50727.75 | J65: 59180.32 | K65: 84512.78
A66: Total | B66: 47611.47 | C66: 56405.34 | D66: 42536.18 | E66: 46875.06 | F66: 51616.72 | G66: 101586.36 | H66: 141278.48 | I66: 160586.24 | J66: 197842.88 | K66: 260868.38
A67: Receivables | B67: 12741.75 | C67: 12098.77 | D67: 14307.03 | E67: 13146.53 | F67: 11982.65 | G67: 13712.19 | H67: 12552.88 | I67: 9792.93 | J67: 9616.47 | K67: 12542.61
... A70: No. of Equity Shares | B70: 1099810083 | C70: 1099810083 | D70: 1099810083 | E70: 1099810083 | F70: 1099810083 | G70: 1099810083 | H70: 1140001121 | I70: 1140001121 | J70: 1154180729 | K70: 1.3519273e+09
A71: New Bonus Shares
A72: Face value | B72: 1 | C72: 1 | D72: 1 | E72: 1 | F72: 1 | G72: 1 | H72: 1 | I72: 1 | J72: 1 | K72: 1
B74: 9061.51 | C74: 22537.98 | D74: 7554.67 | E74: 8013.8 | F74: 10900.2 | G74: 19210.63 | H74: 29217.35 | I74: 24379.48 | J74: 32314 | K74: 41447.77
A75: Other Assets
A80: CASH FLOW:
A81: Report Date | B81: 42825 | C81: 43190 | D81: 43555 | E81: 43921 | F81: 44286 | G81: 44651 | H81: 45016 | I81: 45382 | J81: 45747 | K81: 46112
A82: Cash from Operating Activity | B82: 774.07 | C82: 2942.39 | D82: 3235.92 | E82: 2453.56 | F82: 4043.31 | G82: 1385.28 | H82: 17626.46 | I82: 10312.19 | J82: 4513.1 | K82: 2356.91
A83: Cash from Investing Activity | B83: -1459.77 | C83: -7648.85 | D83: 2486.91 | E83: -1081.85 | F83: -8610.66 | G83: -17040.62 | H83: -15458.84 | I83: -18766.65 | J83: -26417.33 | K83: -27680.49
A84: Cash from Financing Activity | B84: 715.82 | C84: 5119.57 | D84: -6158.41 | E84: -220.9 | F84: 3108.81 | G84: 15901.42 | H84: -1197.52 | I84: 8878.68 | J84: 22655.34 | K84: 28484.47
A85: Net Cash Flow | B85: 30.12 | C85: 413.11 | D85: -435.58 | E85: 1150.81 | F85: -1458.54 | G85: 246.08 | H85: 970.1 | I85: 424.22 | J85: 751.11 | K85: 3160.89
A90: PRICE: | B90: 70.32 | C90: 101.31 | D90: 142.27 | E90: 133.4 | F90: 999.68 | G90: 1953.27 | H90: 1697.04 | I90: 3099.54 | J90: 2245.13 | K90: 1758.8
A92: DERIVED:
A93: Adjusted Equity Shares in Cr | B93: 123.18 | C93: 123.18 | D93: 123.18 | E93: 123.18 | F93: 123.18 | G93: 123.18 | H93: 127.68 | I93: 127.68 | J93: 129.27 | K93: 129.16

Sheet Cash Flow Statement
B2: ="Cash Flow Statement - "&'Data Sheet'!$B$1
B4: Particulars | C4: 42064 | D4: 42430 | E4: 42795 | F4: 43160 | G4: 43525 | H4: 43891 | I4: 44256 | J4: 44621 | K4: 44986 | L4: 45352 | M4: 45717 | N4: 46082
B6: Cash from Operating Activity - | C6: 9843 | D6: 9799 | E6: 10627 | F6: 13169 | G6: 12583 | H6: 14690 | I6: 12527 | J6: 15776 | K6: 18878 | L6: 17179 | M6: 17627 | N6: 18464
B7: Profit from operations | C7: 14261 | D7: 15154 | E7: 16075 | F7: 17433 | G7: 18862 | H7: 19416 | I7: 17326 | J7: 20857 | K7: 26052 | L7: 26635 | M7: 26719 | N7: 27600
B8: Receivables | C8: 558 | D8: -207 | E8: -870 | F8: -964 | G8: -755 | H8: 1411 | I8: -66 | J8: -732 | K8: -884 | L8: -934 | M8: -1023 | N8: 468
B9: Inventory | C9: -505 | D9: -693 | E9: 593 | F9: 602 | G9: -359 | H9: -508 | I9: -1460 | J9: -466 | K9: -1098 | L9: -2545 | M9: -2975 | N9: -3306
B10: Payables | C10: -23 | D10: 622 | E10: 321 | F10: 2098 | G10: 639 | H10: -607 | I10: 1112 | J10: 1099 | K10: 1058 | L10: 141 | M10: 1256 | N10: 76
B11: Working capital changes | C11: 31 | D11: -277 | E11: 44 | F11: 1736 | G11: -476 | H11: 296 | I11: -413 | J11: -100 | K11: -924 | L11: -3337 | M11: -2742 | N11: -2762
B12: Direct taxes | C12: -4449 | D12: -5078 | E12: -5492 | F12: -6000 | G12: -5803 | H12: -5023 | I12: -4387 | J12: -4982 | K12: -6250 | L12: -6120 | M12: -6350 | N12: -6374
B13: Cash from Investing Activity - | C13: -5275 | D13: -3921 | E13: -3251 | F13: -7114 | G13: -5546 | H13: -6174 | I13: 5740 | J13: -2238 | K13: -5732 | L13: 1563 | M13: -564 | N13: -2321
B14: Fixed assets purchased | C14: -3300 | D14: -2348 | E14: -3122 | F14: -2878 | G14: -3169 | H14: -2441 | I14: -1837 | J14: -2142 | K14: -2743 | L14: -3563 | M14: -2279 | N14: -2183
B15: Fixed assets sold | C15: 9 | D15: 8 | E15: 50 | F15: 80 | G15: 28 | H15: 27 | I15: 3 | J15: 133 | K15: 49 | L15: 107 | M15: 175 | N15: 50
B16: Investments purchased | C16: -98742 | D16: -154081 | E16: -85683 | F16: -98330 | G16: -94187 | H16: -79835 | I16: -57553 | J16: -69776 | K16: -80932 | L16: -75107 | M16: -66373 | N16: -68173
... B32: Net Cash Flow | C32: -93 | D32: 266 | E32: 75 | F32: -166 | G32: 169 | H32: 334 | I32: -367 | J32: -43 | K32: 139 | L32: 191 | M32: 26 | N32: -4

Sheet Historical FS
B2: ="Historical Financial Statement - "&'Data Sheet'!$B$1
B3: Particulars | C3: ='Data Sheet'!B56 | D3: ='Data Sheet'!C56 | E3: ='Data Sheet'!D56 | F3: ='Data Sheet'!E56 | G3: ='Data Sheet'!F56 | H3: ='Data Sheet'!G56 | I3: ='Data Sheet'!H56 | J3: ='Data Sheet'!I56 | ... L3: ='Data Sheet'!K56 | M3: LTM
A5: # | B5: Income Statement
B7: Sales | C7: ='Data Sheet'!B17 | D7: ='Data Sheet'!C17 | E7: ='Data Sheet'!D17 | F7: ='Data Sheet'!E17 | G7: ='Data Sheet'!F17 | H7: ='Data Sheet'!G17 | I7: ='Data Sheet'!H17 | J7: ='Data Sheet'!I17 | ... L7: ='Data Sheet'!K17
B8: Sales Growth | C8: - | D8: =D7/C7-1 | E8: =E7/D7-1 | F8: =F7/E7-1 | G8: =G7/F7-1 | H8: =H7/G7-1 | I8: =I7/H7-1 | J8: =J7/I7-1 | K8: =K7/J7-1 | L8: =L7/K7-1
B10: Cost of Goods Sold | C10: =SUM('Data Sheet'!B18,'Data Sheet'!B20:B22)-'Data Sheet'!B19 | D10: =SUM('Data Sheet'!C18,'Data Sheet'!C20:C22)-'Data Sheet'!C19 | E10: =SUM('Data Sheet'!D18,'Data Sheet'!D20:D22)-'Data Sheet'!D19 | F10: =SUM('Data Sheet'!E18,'Data Sheet'!E20:E22)-'Data Sheet'!E19 | G10: =SUM('Data Sheet'!F18,'Data Sheet'!F20:F22)-'Data Sheet'!F19 | H10: =SUM('Data Sheet'!G18,'Data Sheet'!G20:G22)-'Data Sheet'!G19 | I10: =SUM('Data Sheet'!H18,'Data Sheet'!H20:H22)-'Data Sheet'!H19 | J10: =SUM('Data Sheet'!I18,'Data Sheet'!I20:I22)-'Data Sheet'!I19 | ... L10: =SUM('Data Sheet'!K18,'Data Sheet'!K20:K22)-'Data Sheet'!K19
B11: COGS % Sales | C11: =C10/C7 | D11: =D10/D7 | E11: =E10/E7 | F11: =F10/F7 | G11: =G10/G7 | H11: =H10/H7 | I11: =I10/I7 | J11: =J10/J7 | ... L11: =L10/L7
B13: Gross Profit | C13: =C7-C10 | D13: =D7-D10 | E13: =E7-E10 | F13: =F7-F10 | G13: =G7-G10 | H13: =H7-H10 | I13: =I7-I10 | J13: =J7-J10 | ... L13: =L7-L10
B14: Gross Profit % Sales | C14: =C13/C7 | D14: =D13/D7 | E14: =E13/E7 | F14: =F13/F7 | G14: =G13/G7 | H14: =H13/H7 | I14: =I13/I7 | J14: =J13/J7 | ... L14: =L13/L7
B16: Selling % General Expenses | C16: ='Data Sheet'!B23 | D16: ='Data Sheet'!C23 | E16: ='Data Sheet'!D23 | F16: ='Data Sheet'!E23 | G16: ='Data Sheet'!F23 | H16: ='Data Sheet'!G23 | I16: ='Data Sheet'!H23 | J16: ='Data Sheet'!I23 | ... L16: ='Data Sheet'!K23
B17: S&G % Sales | C17: =C16/C7 | D17: =D16/D7 | E17: =E16/E7 | F17: =F16/F7 | G17: =G16/G7 | H17: =H16/H7 | I17: =I16/I7 | J17: =J16/J7 | ... L17: =L16/L7
B19: EBITDA | C19: =C13-C16 | D19: =D13-D16 | E19: =E13-E16 | F19: =F13-F16 | G19: =G13-G16 | H19: =H13-H16 | I19: =I13-I16 | J19: =J13-J16 | ... L19: =L13-L16
B20: EBITDA % Sales | C20: =C19/C7 | D20: =D19/D7 | E20: =E19/E7 | F20: =F19/F7 | G20: =G19/G7 | H20: =H19/H7 | I20: =I19/I7 | J20: =J19/J7 | ... L20: =L19/L7
B22: Depreciation | C22: ='Data Sheet'!B26 | D22: ='Data Sheet'!C26 | E22: ='Data Sheet'!D26 | F22: ='Data Sheet'!E26 | G22: ='Data Sheet'!F26 | H22: ='Data Sheet'!G26 | I22: ='Data Sheet'!H26 | J22: ='Data Sheet'!I26 | ... L22: ='Data Sheet'!K26
B23: Depreciation % Sales | C23: =C22/C7 | D23: =D22/D7 | E23: =E22/E7 | F23: =F22/F7 | G23: =G22/G7 | H23: =H22/H7 | I23: =I22/I7 | J23: =J22/J7 | ... L23: =L22/L7
B25: EBIT | C25: =C19-C22 | D25: =D19-D22 | E25: =E19-E22 | F25: =F19-F22 | G25: =G19-G22 | H25: =H19-H22 | I25: =I19-I22 | J25: =J19-J22 | ... L25: =L19-L22
B26: EBIT % Sales | C26: =C25/C7 | D26: =D25/D7 | E26: =E25/E7 | F26: =F25/F7 | G26: =G25/G7 | H26: =H25/H7 | I26: =I25/I7 | J26: =J25/J7 | ... L26: =L25/L7
B28: Interest | C28: ='Data Sheet'!B27 | D28: ='Data Sheet'!C27 | E28: ='Data Sheet'!D27 | F28: ='Data Sheet'!E27 | G28: ='Data Sheet'!F27 | H28: ='Data Sheet'!G27 | I28: ='Data Sheet'!H27 | J28: ='Data Sheet'!I27 | ... L28: ='Data Sheet'!K27
B29: Interest % Sales | C29: =C28/C7 | D29: =D28/D7 | E29: =E28/E7 | F29: =F28/F7 | G29: =G28/G7 | H29: =H28/H7 | I29: =I28/I7 | J29: =J28/J7 | ... L29: =L28/L7
B31: Earning Before Tax | C31: =C25-C28 | D31: =D25-D28 | E31: =E25-E28 | F31: =F25-F28 | G31: =G25-G28 | H31: =H25-H28 | I31: =I25-I28 | J31: =J25-J28 | ... L31: =L25-L28
B32: EBT % Sales | C32: =C31/C7 | D32: =D31/D7 | E32: =E31/E7 | F32: =F31/F7 | G32: =G31/G7 | H32: =H31/H7 | I32: =I31/I7 | J32: =J31/J7 | ... L32: =L31/L7
B34: Tax Rate | C34: ='Data Sheet'!B29 | D34: ='Data Sheet'!C29 | E34: ='Data Sheet'!D29 | F34: ='Data Sheet'!E29 | G34: ='Data Sheet'!F29 | H34: ='Data Sheet'!G29 | I34: ='Data Sheet'!H29 | J34: ='Data Sheet'!I29 | ... L34: ='Data Sheet'!K29
B35: Effective Tax Rate | C35: =C34/C31 | D35: =D34/D31 | E35: =E34/E31 | F35: =F34/F31 | G35: =G34/G31 | H35: =H34/H31 | I35: =I34/I31 | J35: =J34/J31 | ... L35: =L34/L31
B37: Net Profit | C37: =C31-C34 | D37: =D31-D34 | E37: =E31-E34 | F37: =F31-F34 | G37: =G31-G34 | H37: =H31-H34 | I37: =I31-I34 | J37: =J31-J34 | ... L37: =L31-L34
B38: Net Profit % Sales | C38: =C37/C7 | D38: =D37/D7 | E38: =E37/E7 | F38: =F37/F7 | G38: =G37/G7 | H38: =H37/H7 | I38: =I37/I7 | J38: =J37/J7 | ... L38: =L37/L7
B40: No. of Equity Shares | C40: ='Data Sheet'!B93 | D40: ='Data Sheet'!C93 | E40: ='Data Sheet'!D93 | F40: ='Data Sheet'!E93 | G40: ='Data Sheet'!F93 | H40: ='Data Sheet'!G93 | I40: ='Data Sheet'!H93 | J40: ='Data Sheet'!I93 | ... L40: ='Data Sheet'!K93
B42: Earning per Share | C42: =C37/C40 | D42: =D37/D40 | E42: =E37/E40 | F42: =F37/F40 | G42: =G37/G40 | H42: =H37/H40 | I42: =I37/I40 | J42: =J37/J40 | ... L42: =L37/L40
B43: EPS Growth | C43: - | D43: =D42/C42-1 | E43: =E42/D42-1 | F43: =F42/E42-1 | G43: =G42/F42-1 | H43: =H42/G42-1 | I43: =I42/H42-1 | J43: =J42/I42-1 | K43: =K42/J42-1 | L43: =L42/K42-1
B45: Dividend per Share | C45: ='Data Sheet'!B31/'Historical FS'!C40 | D45: ='Data Sheet'!C31/'Historical FS'!D40 | E45: ='Data Sheet'!D31/'Historical FS'!E40 | F45: ='Data Sheet'!E31/'Historical FS'!F40 | G45: ='Data Sheet'!F31/'Historical FS'!G40 | H45: ='Data Sheet'!G31/'Historical FS'!H40 | I45: ='Data Sheet'!H31/'Historical FS'!I40 | J45: ='Data Sheet'!I31/'Historical FS'!J40 | ... L45: ='Data Sheet'!K31/'Historical FS'!L40
B46: Dividend Payout Ratio | C46: =C45/C42 | D46: =D45/D42 | E46: =E45/E42 | F46: =F45/F42 | G46: =G45/G42 | H46: =H45/H42 | I46: =I45/I42 | J46: =J45/J42 | ... L46: =L45/L42
B48: Retained Earnings | C48: =(1-C46) | D48: =(1-D46) | E48: =(1-E46) | F48: =(1-F46) | G48: =(1-G46) | H48: =(1-H46) | I48: =(1-I46) | J48: =(1-J46) | ... L48: =(1-L46)
B50: Balance Sheet
B51: ='Data Sheet'!A57 | C51: ='Data Sheet'!B57 | D51: ='Data Sheet'!C57 | E51: ='Data Sheet'!D57 | F51: ='Data Sheet'!E57 | G51: ='Data Sheet'!F57 | H51: ='Data Sheet'!G57 | I51: ='Data Sheet'!H57 | ... L51: ='Data Sheet'!K57
B52: ='Data Sheet'!A58 | C52: ='Data Sheet'!B58 | D52: ='Data Sheet'!C58 | E52: ='Data Sheet'!D58 | F52: ='Data Sheet'!E58 | G52: ='Data Sheet'!F58 | H52: ='Data Sheet'!G58 | I52: ='Data Sheet'!H58 | ... L52: ='Data Sheet'!K58
B53: ='Data Sheet'!A59 | C53: ='Data Sheet'!B59 | D53: ='Data Sheet'!C59 | E53: ='Data Sheet'!D59 | F53: ='Data Sheet'!E59 | G53: ='Data Sheet'!F59 | H53: ='Data Sheet'!G59 | I53: ='Data Sheet'!H59 | ... L53: ='Data Sheet'!K59
B54: ='Data Sheet'!A60 | C54: ='Data Sheet'!B60 | D54: ='Data Sheet'!C60 | E54: ='Data Sheet'!D60 | F54: ='Data Sheet'!E60 | G54: ='Data Sheet'!F60 | H54: ='Data Sheet'!G60 | I54: ='Data Sheet'!H60 | ... L54: ='Data Sheet'!K60
B55: Total Liabilities | C55: =SUM(C51:C54) | D55: =SUM(D51:D54) | E55: =SUM(E51:E54) | F55: =SUM(F51:F54) | G55: =SUM(G51:G54) | H55: =SUM(H51:H54) | I55: =SUM(I51:I54) | J55: =SUM(J51:J54) | ... L55: =SUM(L51:L54)
B57: Fixed Asset Net Block | C57: ='Data Sheet'!B62 | D57: ='Data Sheet'!C62 | E57: ='Data Sheet'!D62 | F57: ='Data Sheet'!E62 | G57: ='Data Sheet'!F62 | H57: ='Data Sheet'!G62 | I57: ='Data Sheet'!H62 | J57: ='Data Sheet'!I62 | ... L57: ='Data Sheet'!K62
B58: ='Data Sheet'!A63 | C58: ='Data Sheet'!B63 | D58: ='Data Sheet'!C63 | E58: ='Data Sheet'!D63 | F58: ='Data Sheet'!E63 | G58: ='Data Sheet'!F63 | H58: ='Data Sheet'!G63 | I58: ='Data Sheet'!H63 | ... L58: ='Data Sheet'!K63
B59: ='Data Sheet'!A64 | C59: ='Data Sheet'!B64 | D59: ='Data Sheet'!C64 | E59: ='Data Sheet'!D64 | F59: ='Data Sheet'!E64 | G59: ='Data Sheet'!F64 | H59: ='Data Sheet'!G64 | I59: ='Data Sheet'!H64 | ... L59: ='Data Sheet'!K64
B60: ='Data Sheet'!A65 | C60: ='Data Sheet'!B75 | D60: ='Data Sheet'!C75 | E60: ='Data Sheet'!D75 | F60: ='Data Sheet'!E75 | G60: ='Data Sheet'!F75 | H60: ='Data Sheet'!G75 | I60: ='Data Sheet'!H75 | J60: ='Data Sheet'!I75 | ... O60: ='Data Sheet'!N75
B61: Total Non Current Assets | C61: =SUM(C57:C60) | D61: =SUM(D57:D60) | E61: =SUM(E57:E60) | F61: =SUM(F57:F60) | G61: =SUM(G57:G60) | H61: =SUM(H57:H60) | I61: =SUM(I57:I60) | J61: =SUM(J57:J60) | ... L61: =SUM(L57:L60)
B63: ='Data Sheet'!A67 | C63: ='Data Sheet'!B67 | D63: ='Data Sheet'!C67 | E63: ='Data Sheet'!D67 | F63: ='Data Sheet'!E67 | G63: ='Data Sheet'!F67 | H63: ='Data Sheet'!G67 | I63: ='Data Sheet'!H67 | ... L63: ='Data Sheet'!K67
B64: ='Data Sheet'!A68 | C64: ='Data Sheet'!B68 | D64: ='Data Sheet'!C68 | E64: ='Data Sheet'!D68 | F64: ='Data Sheet'!E68 | G64: ='Data Sheet'!F68 | H64: ='Data Sheet'!G68 | I64: ='Data Sheet'!H68 | ... L64: ='Data Sheet'!K68
B65: ='Data Sheet'!A69 | C65: ='Data Sheet'!B69 | D65: ='Data Sheet'!C69 | E65: ='Data Sheet'!D69 | F65: ='Data Sheet'!E69 | G65: ='Data Sheet'!F69 | H65: ='Data Sheet'!G69 | I65: ='Data Sheet'!H69 | ... L65: ='Data Sheet'!K69
B66: Total Current Assets | C66: =SUM(C63:C65) | D66: =SUM(D63:D65) | E66: =SUM(E63:E65) | F66: =SUM(F63:F65) | G66: =SUM(G63:G65) | H66: =SUM(H63:H65) | I66: =SUM(I63:I65) | J66: =SUM(J63:J65) | ... L66: =SUM(L63:L65)
B68: Total Assets | C68: =C61+C66 | D68: =D61+D66 | E68: =E61+E66 | F68: =F61+F66 | G68: =G61+G66 | H68: =H61+H66 | I68: =I61+I66 | J68: =J61+J66 | ... L68: =L61+L66
B70: Check | C70: =C68=C55 | D70: =D68=D55 | E70: =E68=E55 | F70: =F68=F55 | G70: =G68=G55 | H70: =H68=H55 | I70: =I68=I55 | J70: =J68=J55 | ... L70: =L68=L55
B72: Cash Flow Statement
B73: Operating Activity
B74: ='Cash Flow Statement'!B7 | C74: ='Cash Flow Statement'!E7 | D74: ='Cash Flow Statement'!F7 | E74: ='Cash Flow Statement'!G7 | F74: ='Cash Flow Statement'!H7 | G74: ='Cash Flow Statement'!I7 | H74: ='Cash Flow Statement'!J7 | I74: ='Cash Flow Statement'!K7 | J74: ='Cash Flow Statement'!L7 | ... L74: ='Cash Flow Statement'!N7
B75: ='Cash Flow Statement'!B8 | C75: ='Cash Flow Statement'!E8 | D75: ='Cash Flow Statement'!F8 | E75: ='Cash Flow Statement'!G8 | F75: ='Cash Flow Statement'!H8 | G75: ='Cash Flow Statement'!I8 | H75: ='Cash Flow Statement'!J8 | I75: ='Cash Flow Statement'!K8 | J75: ='Cash Flow Statement'!L8 | ... L75: ='Cash Flow Statement'!N8
B76: ='Cash Flow Statement'!B9 | C76: ='Cash Flow Statement'!E9 | D76: ='Cash Flow Statement'!F9 | E76: ='Cash Flow Statement'!G9 | F76: ='Cash Flow Statement'!H9 | G76: ='Cash Flow Statement'!I9 | H76: ='Cash Flow Statement'!J9 | I76: ='Cash Flow Statement'!K9 | J76: ='Cash Flow Statement'!L9 | ... L76: ='Cash Flow Statement'!N9
B77: ='Cash Flow Statement'!B10 | C77: ='Cash Flow Statement'!E10 | D77: ='Cash Flow Statement'!F10 | E77: ='Cash Flow Statement'!G10 | F77: ='Cash Flow Statement'!H10 | G77: ='Cash Flow Statement'!I10 | H77: ='Cash Flow Statement'!J10 | I77: ='Cash Flow Statement'!K10 | J77: ='Cash Flow Statement'!L10 | ... L77: ='Cash Flow Statement'!N10
B78: ='Cash Flow Statement'!B11 | C78: ='Cash Flow Statement'!E11 | D78: ='Cash Flow Statement'!F11 | E78: ='Cash Flow Statement'!G11 | F78: ='Cash Flow Statement'!H11 | G78: ='Cash Flow Statement'!I11 | H78: ='Cash Flow Statement'!J11 | I78: ='Cash Flow Statement'!K11 | J78: ='Cash Flow Statement'!L11 | ... L78: ='Cash Flow Statement'!N11
B79: ='Cash Flow Statement'!B12 | C79: ='Cash Flow Statement'!E12 | D79: ='Cash Flow Statement'!F12 | E79: ='Cash Flow Statement'!G12 | F79: ='Cash Flow Statement'!H12 | G79: ='Cash Flow Statement'!I12 | H79: ='Cash Flow Statement'!J12 | I79: ='Cash Flow Statement'!K12 | J79: ='Cash Flow Statement'!L12 | ... L79: ='Cash Flow Statement'!N12
B80: Cash From Operating Activities | C80: =SUM(C74:C79) | D80: =SUM(D74:D79) | E80: =SUM(E74:E79) | F80: =SUM(F74:F79) | G80: =SUM(G74:G79) | H80: =SUM(H74:H79) | I80: =SUM(I74:I79) | J80: =SUM(J74:J79) | ... L80: =SUM(L74:L79)
B82: Investing Activities
B83: ='Cash Flow Statement'!B14 | C83: ='Cash Flow Statement'!E14 | D83: ='Cash Flow Statement'!F14 | E83: ='Cash Flow Statement'!G14 | F83: ='Cash Flow Statement'!H14 | G83: ='Cash Flow Statement'!I14 | H83: ='Cash Flow Statement'!J14 | I83: ='Cash Flow Statement'!K14 | J83: ='Cash Flow Statement'!L14 | ... L83: ='Cash Flow Statement'!N14
B84: ='Cash Flow Statement'!B15 | C84: ='Cash Flow Statement'!E15 | D84: ='Cash Flow Statement'!F15 | E84: ='Cash Flow Statement'!G15 | F84: ='Cash Flow Statement'!H15 | G84: ='Cash Flow Statement'!I15 | H84: ='Cash Flow Statement'!J15 | I84: ='Cash Flow Statement'!K15 | J84: ='Cash Flow Statement'!L15 | ... L84: ='Cash Flow Statement'!N15
B85: ='Cash Flow Statement'!B16 | C85: ='Cash Flow Statement'!E16 | D85: ='Cash Flow Statement'!F16 | E85: ='Cash Flow Statement'!G16 | F85: ='Cash Flow Statement'!H16 | G85: ='Cash Flow Statement'!I16 | H85: ='Cash Flow Statement'!J16 | I85: ='Cash Flow Statement'!K16 | J85: ='Cash Flow Statement'!L16 | ... L85: ='Cash Flow Statement'!N16
B86: ='Cash Flow Statement'!B17 | C86: ='Cash Flow Statement'!E17 | D86: ='Cash Flow Statement'!F17 | E86: ='Cash Flow Statement'!G17 | F86: ='Cash Flow Statement'!H17 | G86: ='Cash Flow Statement'!I17 | H86: ='Cash Flow Statement'!J17 | I86: ='Cash Flow Statement'!K17 | J86: ='Cash Flow Statement'!L17 | ... L86: ='Cash Flow Statement'!N17
B87: ='Cash Flow Statement'!B18 | C87: ='Cash Flow Statement'!E18 | D87: ='Cash Flow Statement'!F18 | E87: ='Cash Flow Statement'!G18 | F87: ='Cash Flow Statement'!H18 | G87: ='Cash Flow Statement'!I18 | H87: ='Cash Flow Statement'!J18 | I87: ='Cash Flow Statement'!K18 | J87: ='Cash Flow Statement'!L18 | ... L87: ='Cash Flow Statement'!N18
B88: ='Cash Flow Statement'!B19 | C88: ='Cash Flow Statement'!E19 | D88: ='Cash Flow Statement'!F19 | E88: ='Cash Flow Statement'!G19 | F88: ='Cash Flow Statement'!H19 | G88: ='Cash Flow Statement'!I19 | H88: ='Cash Flow Statement'!J19 | I88: ='Cash Flow Statement'!K19 | J88: ='Cash Flow Statement'!L19 | ... L88: ='Cash Flow Statement'!N19
B89: ='Cash Flow Statement'!B20 | C89: ='Cash Flow Statement'!E20 | D89: ='Cash Flow Statement'!F20 | E89: ='Cash Flow Statement'!G20 | F89: ='Cash Flow Statement'!H20 | G89: ='Cash Flow Statement'!I20 | H89: ='Cash Flow Statement'!J20 | I89: ='Cash Flow Statement'!K20 | J89: ='Cash Flow Statement'!L20 | ... L89: ='Cash Flow Statement'!N20
B90: ='Cash Flow Statement'!B21 | C90: ='Cash Flow Statement'!E21 | D90: ='Cash Flow Statement'!F21 | E90: ='Cash Flow Statement'!G21 | F90: ='Cash Flow Statement'!H21 | G90: ='Cash Flow Statement'!I21 | H90: ='Cash Flow Statement'!J21 | I90: ='Cash Flow Statement'!K21 | J90: ='Cash Flow Statement'!L21 | ... L90: ='Cash Flow Statement'!N21
B91: ='Cash Flow Statement'!B22 | C91: ='Cash Flow Statement'!E22 | D91: ='Cash Flow Statement'!F22 | E91: ='Cash Flow Statement'!G22 | F91: ='Cash Flow Statement'!H22 | G91: ='Cash Flow Statement'!I22 | H91: ='Cash Flow Statement'!J22 | I91: ='Cash Flow Statement'!K22 | J91: ='Cash Flow Statement'!L22 | ... L91: ='Cash Flow Statement'!N22
B92: ='Cash Flow Statement'!B23 | C92: ='Cash Flow Statement'!E23 | D92: ='Cash Flow Statement'!F23 | E92: ='Cash Flow Statement'!G23 | F92: ='Cash Flow Statement'!H23 | G92: ='Cash Flow Statement'!I23 | H92: ='Cash Flow Statement'!J23 | I92: ='Cash Flow Statement'!K23 | J92: ='Cash Flow Statement'!L23 | ... L92: ='Cash Flow Statement'!N23
B93: Cash From Investing Activities | C93: =SUM(C83:C92) | D93: =SUM(D83:D92) | E93: =SUM(E83:E92) | F93: =SUM(F83:F92) | G93: =SUM(G83:G92) | H93: =SUM(H83:H92) | I93: =SUM(I83:I92) | J93: =SUM(J83:J92) | ... L93: =SUM(L83:L92)
B95: Financing Activities
B96: ='Cash Flow Statement'!B25 | C96: ='Cash Flow Statement'!E25 | D96: ='Cash Flow Statement'!F25 | E96: ='Cash Flow Statement'!G25 | F96: ='Cash Flow Statement'!H25 | G96: ='Cash Flow Statement'!I25 | H96: ='Cash Flow Statement'!J25 | I96: ='Cash Flow Statement'!K25 | J96: ='Cash Flow Statement'!L25 | ... L96: ='Cash Flow Statement'!N25
B97: ='Cash Flow Statement'!B26 | C97: ='Cash Flow Statement'!E26 | D97: ='Cash Flow Statement'!F26 | E97: ='Cash Flow Statement'!G26 | F97: ='Cash Flow Statement'!H26 | G97: ='Cash Flow Statement'!I26 | H97: ='Cash Flow Statement'!J26 | I97: ='Cash Flow Statement'!K26 | J97: ='Cash Flow Statement'!L26 | ... L97: ='Cash Flow Statement'!N26
B98: ='Cash Flow Statement'!B27 | C98: ='Cash Flow Statement'!E27 | D98: ='Cash Flow Statement'!F27 | E98: ='Cash Flow Statement'!G27 | F98: ='Cash Flow Statement'!H27 | G98: ='Cash Flow Statement'!I27 | H98: ='Cash Flow Statement'!J27 | I98: ='Cash Flow Statement'!K27 | J98: ='Cash Flow Statement'!L27 | ... L98: ='Cash Flow Statement'!N27
B99: ='Cash Flow Statement'!B28 | C99: ='Cash Flow Statement'!E28 | D99: ='Cash Flow Statement'!F28 | E99: ='Cash Flow Statement'!G28 | F99: ='Cash Flow Statement'!H28 | G99: ='Cash Flow Statement'!I28 | H99: ='Cash Flow Statement'!J28 | I99: ='Cash Flow Statement'!K28 | J99: ='Cash Flow Statement'!L28 | ... L99: ='Cash Flow Statement'!N28
B100: ='Cash Flow Statement'!B29 | C100: ='Cash Flow Statement'!E29 | D100: ='Cash Flow Statement'!F29 | E100: ='Cash Flow Statement'!G29 | F100: ='Cash Flow Statement'!H29 | G100: ='Cash Flow Statement'!I29 | H100: ='Cash Flow Statement'!J29 | I100: ='Cash Flow Statement'!K29 | J100: ='Cash Flow Statement'!L29 | ... L100: ='Cash Flow Statement'!N29
B101: ='Cash Flow Statement'!B30 | C101: ='Cash Flow Statement'!E30 | D101: ='Cash Flow Statement'!F30 | E101: ='Cash Flow Statement'!G30 | F101: ='Cash Flow Statement'!H30 | G101: ='Cash Flow Statement'!I30 | H101: ='Cash Flow Statement'!J30 | I101: ='Cash Flow Statement'!K30 | J101: ='Cash Flow Statement'!L30 | ... L101: ='Cash Flow Statement'!N30
B102: ='Cash Flow Statement'!B31 | C102: ='Cash Flow Statement'!E31 | D102: ='Cash Flow Statement'!F31 | E102: ='Cash Flow Statement'!G31 | F102: ='Cash Flow Statement'!H31 | G102: ='Cash Flow Statement'!I31 | H102: ='Cash Flow Statement'!J31 | I102: ='Cash Flow Statement'!K31 | J102: ='Cash Flow Statement'!L31 | ... L102: ='Cash Flow Statement'!N31
B103: Cash From Financing Activities | C103: =SUM(C96:C102) | D103: =SUM(D96:D102) | E103: =SUM(E96:E102) | F103: =SUM(F96:F102) | G103: =SUM(G96:G102) | H103: =SUM(H96:H102) | I103: =SUM(I96:I102) | J103: =SUM(J96:J102) | ... L103: =SUM(L96:L102)
B105: Net Cash Flow | C105: =C80+C93+C103 | D105: =D80+D93+D103 | E105: =E80+E93+E103 | F105: =F80+F93+F103 | G105: =G80+G93+G103 | H105: =H80+H93+H103 | I105: =I80+I93+I103 | J105: =J80+J93+J103 | ... L105: =L80+L93+L103

Sheet Ratio Analysis
B2: ="Ratio Analysis - "&'Data Sheet'!$B$1
B3: Years | C3: ='Data Sheet'!B56 | D3: ='Data Sheet'!C56 | E3: ='Data Sheet'!D56 | F3: ='Data Sheet'!E56 | G3: ='Data Sheet'!F56 | H3: ='Data Sheet'!G56 | I3: ='Data Sheet'!H56 | J3: ='Data Sheet'!I56 | ... L3: ='Data Sheet'!K56 | M3: Trend | N3: Mean | O3: Median
B5: SalesGrowth | D5: =IFERROR('Historical FS'!D8,0) | E5: =IFERROR('Historical FS'!E8,0) | F5: =IFERROR('Historical FS'!F8,0) | G5: =IFERROR('Historical FS'!G8,0) | H5: =IFERROR('Historical FS'!H8,0) | I5: =IFERROR('Historical FS'!I8,0) | J5: =IFERROR('Historical FS'!J8,0) | K5: =IFERROR('Historical FS'!K8,0) | L5: =IFERROR('Historical FS'!L8,0) | N5: =IFERROR(AVERAGE(D5:L5),0) | O5: =IFERROR(MEDIAN(D5:L5),0)
B6: EBITDA Growth | D6: =IFERROR(('Historical FS'!D19/'Historical FS'!C19-1),0) | E6: =IFERROR(('Historical FS'!E19/'Historical FS'!D19-1),0) | F6: =IFERROR(('Historical FS'!F19/'Historical FS'!E19-1),0) | G6: =IFERROR(('Historical FS'!G19/'Historical FS'!F19-1),0) | H6: =IFERROR(('Historical FS'!H19/'Historical FS'!G19-1),0) | I6: =IFERROR(('Historical FS'!I19/'Historical FS'!H19-1),0) | J6: =IFERROR(('Historical FS'!J19/'Historical FS'!I19-1),0) | K6: =IFERROR(('Historical FS'!K19/'Historical FS'!J19-1),0) | L6: =IFERROR(('Historical FS'!L19/'Historical FS'!K19-1),0) | N6: =IFERROR(AVERAGE(D6:L6),0) | O6: =IFERROR(MEDIAN(D6:L6),0)
B7: EBIT Growth | D7: =IFERROR(('Historical FS'!D25/'Historical FS'!C25-1),0) | E7: =IFERROR(('Historical FS'!E25/'Historical FS'!D25-1),0) | F7: =IFERROR(('Historical FS'!F25/'Historical FS'!E25-1),0) | G7: =IFERROR(('Historical FS'!G25/'Historical FS'!F25-1),0) | H7: =IFERROR(('Historical FS'!H25/'Historical FS'!G25-1),0) | I7: =IFERROR(('Historical FS'!I25/'Historical FS'!H25-1),0) | J7: =IFERROR(('Historical FS'!J25/'Historical FS'!I25-1),0) | K7: =IFERROR(('Historical FS'!K25/'Historical FS'!J25-1),0) | L7: =IFERROR(('Historical FS'!L25/'Historical FS'!K25-1),0) | N7: =IFERROR(AVERAGE(D7:L7),0) | O7: =IFERROR(MEDIAN(D7:L7),0)
B8: Net Profit Growth | D8: =IFERROR(('Historical FS'!D37/'Historical FS'!C37-1),0) | E8: =IFERROR(('Historical FS'!E37/'Historical FS'!D37-1),0) | F8: =IFERROR(('Historical FS'!F37/'Historical FS'!E37-1),0) | G8: =IFERROR(('Historical FS'!G37/'Historical FS'!F37-1),0) | H8: =IFERROR(('Historical FS'!H37/'Historical FS'!G37-1),0) | I8: =IFERROR(('Historical FS'!I37/'Historical FS'!H37-1),0) | J8: =IFERROR(('Historical FS'!J37/'Historical FS'!I37-1),0) | K8: =IFERROR(('Historical FS'!K37/'Historical FS'!J37-1),0) | L8: =IFERROR(('Historical FS'!L37/'Historical FS'!K37-1),0) | N8: =IFERROR(AVERAGE(D8:L8),0) | O8: =IFERROR(MEDIAN(D8:L8),0)
B9: Dividend Growth | D9: =IFERROR(('Historical FS'!D45/'Historical FS'!C45-1),0) | E9: =IFERROR(('Historical FS'!E45/'Historical FS'!D45-1),0) | F9: =IFERROR(('Historical FS'!F45/'Historical FS'!E45-1),0) | G9: =IFERROR(('Historical FS'!G45/'Historical FS'!F45-1),0) | H9: =IFERROR(('Historical FS'!H45/'Historical FS'!G45-1),0) | I9: =IFERROR(('Historical FS'!I45/'Historical FS'!H45-1),0) | J9: =IFERROR(('Historical FS'!J45/'Historical FS'!I45-1),0) | K9: =IFERROR(('Historical FS'!K45/'Historical FS'!J45-1),0) | L9: =IFERROR(('Historical FS'!L45/'Historical FS'!K45-1),0) | N9: =IFERROR(AVERAGE(D9:L9),0) | O9: =IFERROR(MEDIAN(D9:L9),0)
B11: Gross Margin | C11: =IFERROR('Historical FS'!C14,0) | D11: =IFERROR('Historical FS'!D14,0) | E11: =IFERROR('Historical FS'!E14,0) | F11: =IFERROR('Historical FS'!F14,0) | G11: =IFERROR('Historical FS'!G14,0) | H11: =IFERROR('Historical FS'!H14,0) | I11: =IFERROR('Historical FS'!I14,0) | J11: =IFERROR('Historical FS'!J14,0) | ... L11: =IFERROR('Historical FS'!L14,0) | N11: =IFERROR(AVERAGE(C11:L11),0) | O11: =IFERROR(MEDIAN(C11:L11),0)
B12: EBITDA Margin | C12: =IFERROR('Historical FS'!C20,0) | D12: =IFERROR('Historical FS'!D20,0) | E12: =IFERROR('Historical FS'!E20,0) | F12: =IFERROR('Historical FS'!F20,0) | G12: =IFERROR('Historical FS'!G20,0) | H12: =IFERROR('Historical FS'!H20,0) | I12: =IFERROR('Historical FS'!I20,0) | J12: =IFERROR('Historical FS'!J20,0) | ... L12: =IFERROR('Historical FS'!L20,0) | N12: =IFERROR(AVERAGE(C12:L12),0) | O12: =IFERROR(MEDIAN(C12:L12),0)
B13: EBIT Margin | C13: =IFERROR('Historical FS'!C25/'Historical FS'!C7,0) | D13: =IFERROR('Historical FS'!D25/'Historical FS'!D7,0) | E13: =IFERROR('Historical FS'!E25/'Historical FS'!E7,0) | F13: =IFERROR('Historical FS'!F25/'Historical FS'!F7,0) | G13: =IFERROR('Historical FS'!G25/'Historical FS'!G7,0) | H13: =IFERROR('Historical FS'!H25/'Historical FS'!H7,0) | I13: =IFERROR('Historical FS'!I25/'Historical FS'!I7,0) | J13: =IFERROR('Historical FS'!J25/'Historical FS'!J7,0) | ... L13: =IFERROR('Historical FS'!L25/'Historical FS'!L7,0) | N13: =IFERROR(AVERAGE(C13:L13),0) | O13: =IFERROR(MEDIAN(C13:L13),0)
B14: EBT Margin | C14: =IFERROR('Historical FS'!C32,0) | D14: =IFERROR('Historical FS'!D32,0) | E14: =IFERROR('Historical FS'!E32,0) | F14: =IFERROR('Historical FS'!F32,0) | G14: =IFERROR('Historical FS'!G32,0) | H14: =IFERROR('Historical FS'!H32,0) | I14: =IFERROR('Historical FS'!I32,0) | J14: =IFERROR('Historical FS'!J32,0) | ... L14: =IFERROR('Historical FS'!L32,0) | N14: =IFERROR(AVERAGE(C14:L14),0) | O14: =IFERROR(MEDIAN(C14:L14),0)
B15: Net Profit Margin | C15: =IFERROR('Historical FS'!C38,0) | D15: =IFERROR('Historical FS'!D38,0) | E15: =IFERROR('Historical FS'!E38,0) | F15: =IFERROR('Historical FS'!F38,0) | G15: =IFERROR('Historical FS'!G38,0) | H15: =IFERROR('Historical FS'!H38,0) | I15: =IFERROR('Historical FS'!I38,0) | J15: =IFERROR('Historical FS'!J38,0) | ... L15: =IFERROR('Historical FS'!L38,0) | N15: =IFERROR(AVERAGE(C15:L15),0) | O15: =IFERROR(MEDIAN(C15:L15),0)
B17: SalesExpenses%sales | C17: =IFERROR('Historical FS'!C17,0) | D17: =IFERROR('Historical FS'!D17,0) | E17: =IFERROR('Historical FS'!E17,0) | F17: =IFERROR('Historical FS'!F17,0) | G17: =IFERROR('Historical FS'!G17,0) | H17: =IFERROR('Historical FS'!H17,0) | I17: =IFERROR('Historical FS'!I17,0) | J17: =IFERROR('Historical FS'!J17,0) | ... L17: =IFERROR('Historical FS'!L17,0) | N17: =IFERROR(AVERAGE(C17:L17),0) | O17: =IFERROR(MEDIAN(C17:L17),0)
B18: Depreciation%Sales | C18: =IFERROR('Historical FS'!C23,0) | D18: =IFERROR('Historical FS'!D23,0) | E18: =IFERROR('Historical FS'!E23,0) | F18: =IFERROR('Historical FS'!F23,0) | G18: =IFERROR('Historical FS'!G23,0) | H18: =IFERROR('Historical FS'!H23,0) | I18: =IFERROR('Historical FS'!I23,0) | J18: =IFERROR('Historical FS'!J23,0) | ... L18: =IFERROR('Historical FS'!L23,0) | N18: =IFERROR(AVERAGE(C18:L18),0) | O18: =IFERROR(MEDIAN(C18:L18),0)
B19: OperatingIncome%sales | C19: =C13 | D19: =D13 | E19: =E13 | F19: =F13 | G19: =G13 | H19: =H13 | I19: =I13 | J19: =J13 | ... L19: =L13 | N19: =IFERROR(AVERAGE(C19:L19),0) | O19: =IFERROR(MEDIAN(C19:L19),0)
B21: Return on Capital Employed | C21: =IFERROR('Historical FS'!C25/SUM('Historical FS'!C51:'Historical FS'!C53),0) | D21: =IFERROR('Historical FS'!D25/SUM('Historical FS'!D51:'Historical FS'!D53),0) | E21: =IFERROR('Historical FS'!E25/SUM('Historical FS'!E51:'Historical FS'!E53),0) | F21: =IFERROR('Historical FS'!F25/SUM('Historical FS'!F51:'Historical FS'!F53),0) | G21: =IFERROR('Historical FS'!G25/SUM('Historical FS'!G51:'Historical FS'!G53),0) | H21: =IFERROR('Historical FS'!H25/SUM('Historical FS'!H51:'Historical FS'!H53),0) | I21: =IFERROR('Historical FS'!I25/SUM('Historical FS'!I51:'Historical FS'!I53),0) | J21: =IFERROR('Historical FS'!J25/SUM('Historical FS'!J51:'Historical FS'!J53),0) | ... L21: =IFERROR('Historical FS'!L25/SUM('Historical FS'!L51:'Historical FS'!L53),0) | N21: =IFERROR(AVERAGE(C21:L21),0) | O21: =IFERROR(MEDIAN(C21:L21),0)
B22: Retained Earnings% | C22: =IFERROR('Historical FS'!C48,0) | D22: =IFERROR('Historical FS'!D48,0) | E22: =IFERROR('Historical FS'!E48,0) | F22: =IFERROR('Historical FS'!F48,0) | G22: =IFERROR('Historical FS'!G48,0) | H22: =IFERROR('Historical FS'!H48,0) | I22: =IFERROR('Historical FS'!I48,0) | J22: =IFERROR('Historical FS'!J48,0) | ... L22: =IFERROR('Historical FS'!L48,0) | N22: =IFERROR(AVERAGE(C22:L22),0) | O22: =IFERROR(MEDIAN(C22:L22),0)
B23: Return on Equity% | C23: =IFERROR('Historical FS'!C37/SUM('Historical FS'!C51:'Historical FS'!C52),0) | D23: =IFERROR('Historical FS'!D37/SUM('Historical FS'!D51:'Historical FS'!D52),0) | E23: =IFERROR('Historical FS'!E37/SUM('Historical FS'!E51:'Historical FS'!E52),0) | F23: =IFERROR('Historical FS'!F37/SUM('Historical FS'!F51:'Historical FS'!F52),0) | G23: =IFERROR('Historical FS'!G37/SUM('Historical FS'!G51:'Historical FS'!G52),0) | H23: =IFERROR('Historical FS'!H37/SUM('Historical FS'!H51:'Historical FS'!H52),0) | I23: =IFERROR('Historical FS'!I37/SUM('Historical FS'!I51:'Historical FS'!I52),0) | J23: =IFERROR('Historical FS'!J37/SUM('Historical FS'!J51:'Historical FS'!J52),0) | ... L23: =IFERROR('Historical FS'!L37/SUM('Historical FS'!L51:'Historical FS'!L52),0) | N23: =IFERROR(AVERAGE(C23:L23),0) | O23: =IFERROR(MEDIAN(C23:L23),0)
B24: Self Sustained Growth Rate | C24: =IFERROR(C22*C23,0) | D24: =IFERROR(D22*D23,0) | E24: =IFERROR(E22*E23,0) | F24: =IFERROR(F22*F23,0) | G24: =IFERROR(G22*G23,0) | H24: =IFERROR(H22*H23,0) | I24: =IFERROR(I22*I23,0) | J24: =IFERROR(J22*J23,0) | ... L24: =IFERROR(L22*L23,0) | N24: =IFERROR(AVERAGE(C24:L24),0) | O24: =IFERROR(MEDIAN(C24:L24),0)
B25: Interest Coverage Ratio | C25: =IFERROR('Historical FS'!C25/'Historical FS'!C28,0) | D25: =IFERROR('Historical FS'!D25/'Historical FS'!D28,0) | E25: =IFERROR('Historical FS'!E25/'Historical FS'!E28,0) | F25: =IFERROR('Historical FS'!F25/'Historical FS'!F28,0) | G25: =IFERROR('Historical FS'!G25/'Historical FS'!G28,0) | H25: =IFERROR('Historical FS'!H25/'Historical FS'!H28,0) | I25: =IFERROR('Historical FS'!I25/'Historical FS'!I28,0) | J25: =IFERROR('Historical FS'!J25/'Historical FS'!J28,0) | ... L25: =IFERROR('Historical FS'!L25/'Historical FS'!L28,0) | N25: =IFERROR(AVERAGE(C25:L25),0) | O25: =IFERROR(MEDIAN(C25:L25),0)
B27: Debtor Turnover Ratio | C27: =IFERROR('Historical FS'!C7/'Historical FS'!C63,0) | D27: =IFERROR('Historical FS'!D7/'Historical FS'!D63,0) | E27: =IFERROR('Historical FS'!E7/'Historical FS'!E63,0) | F27: =IFERROR('Historical FS'!F7/'Historical FS'!F63,0) | G27: =IFERROR('Historical FS'!G7/'Historical FS'!G63,0) | H27: =IFERROR('Historical FS'!H7/'Historical FS'!H63,0) | I27: =IFERROR('Historical FS'!I7/'Historical FS'!I63,0) | J27: =IFERROR('Historical FS'!J7/'Historical FS'!J63,0) | ... L27: =IFERROR('Historical FS'!L7/'Historical FS'!L63,0) | N27: =IFERROR(AVERAGE(C27:L27),0) | O27: =IFERROR(MEDIAN(C27:L27),0)
B28: Creditor Turnover Ratio | C28: =IFERROR('Historical FS'!C7/'Historical FS'!C54,0) | D28: =IFERROR('Historical FS'!D7/'Historical FS'!D54,0) | E28: =IFERROR('Historical FS'!E7/'Historical FS'!E54,0) | F28: =IFERROR('Historical FS'!F7/'Historical FS'!F54,0) | G28: =IFERROR('Historical FS'!G7/'Historical FS'!G54,0) | H28: =IFERROR('Historical FS'!H7/'Historical FS'!H54,0) | I28: =IFERROR('Historical FS'!I7/'Historical FS'!I54,0) | J28: =IFERROR('Historical FS'!J7/'Historical FS'!J54,0) | ... L28: =IFERROR('Historical FS'!L7/'Historical FS'!L54,0) | N28: =IFERROR(AVERAGE(C28:L28),0) | O28: =IFERROR(MEDIAN(C28:L28),0)
B29: Inventory Turnover | C29: =IFERROR('Historical FS'!C7/'Historical FS'!C64,0) | D29: =IFERROR('Historical FS'!D7/'Historical FS'!D64,0) | E29: =IFERROR('Historical FS'!E7/'Historical FS'!E64,0) | F29: =IFERROR('Historical FS'!F7/'Historical FS'!F64,0) | G29: =IFERROR('Historical FS'!G7/'Historical FS'!G64,0) | H29: =IFERROR('Historical FS'!H7/'Historical FS'!H64,0) | I29: =IFERROR('Historical FS'!I7/'Historical FS'!I64,0) | J29: =IFERROR('Historical FS'!J7/'Historical FS'!J64,0) | ... L29: =IFERROR('Historical FS'!L7/'Historical FS'!L64,0) | N29: =IFERROR(AVERAGE(C29:L29),0) | O29: =IFERROR(MEDIAN(C29:L29),0)
B30: Fixed Assets Turnover | C30: =IFERROR('Historical FS'!C7/'Historical FS'!C57,0) | D30: =IFERROR('Historical FS'!D7/'Historical FS'!D57,0) | E30: =IFERROR('Historical FS'!E7/'Historical FS'!E57,0) | F30: =IFERROR('Historical FS'!F7/'Historical FS'!F57,0) | G30: =IFERROR('Historical FS'!G7/'Historical FS'!G57,0) | H30: =IFERROR('Historical FS'!H7/'Historical FS'!H57,0) | I30: =IFERROR('Historical FS'!I7/'Historical FS'!I57,0) | J30: =IFERROR('Historical FS'!J7/'Historical FS'!J57,0) | ... L30: =IFERROR('Historical FS'!L7/'Historical FS'!L57,0) | N30: =IFERROR(AVERAGE(C30:L30),0) | O30: =IFERROR(MEDIAN(C30:L30),0)
B31: Capital Turnover Ratio | C31: =IFERROR('Historical FS'!C7/SUM('Historical FS'!C51:'Historical FS'!C52),0) | D31: =IFERROR('Historical FS'!D7/SUM('Historical FS'!D51:'Historical FS'!D52),0) | E31: =IFERROR('Historical FS'!E7/SUM('Historical FS'!E51:'Historical FS'!E52),0) | F31: =IFERROR('Historical FS'!F7/SUM('Historical FS'!F51:'Historical FS'!F52),0) | G31: =IFERROR('Historical FS'!G7/SUM('Historical FS'!G51:'Historical FS'!G52),0) | H31: =IFERROR('Historical FS'!H7/SUM('Historical FS'!H51:'Historical FS'!H52),0) | I31: =IFERROR('Historical FS'!I7/SUM('Historical FS'!I51:'Historical FS'!I52),0) | J31: =IFERROR('Historical FS'!J7/SUM('Historical FS'!J51:'Historical FS'!J52),0) | ... L31: =IFERROR('Historical FS'!L7/SUM('Historical FS'!L51:'Historical FS'!L52),0) | N31: =IFERROR(AVERAGE(C31:L31),0) | O31: =IFERROR(MEDIAN(C31:L31),0)
B33: (in days)
B34: Debtor Days | C34: =IFERROR(365/C27,0) | D34: =IFERROR(365/D27,0) | E34: =IFERROR(365/E27,0) | F34: =IFERROR(365/F27,0) | G34: =IFERROR(365/G27,0) | H34: =IFERROR(365/H27,0) | I34: =IFERROR(365/I27,0) | J34: =IFERROR(365/J27,0) | ... L34: =IFERROR(365/L27,0) | N34: =IFERROR(AVERAGE(C34:L34),0) | O34: =IFERROR(MEDIAN(C34:L34),0)
B35: Payable Days | C35: =IFERROR(365/C28,0) | D35: =IFERROR(365/D28,0) | E35: =IFERROR(365/E28,0) | F35: =IFERROR(365/F28,0) | G35: =IFERROR(365/G28,0) | H35: =IFERROR(365/H28,0) | I35: =IFERROR(365/I28,0) | J35: =IFERROR(365/J28,0) | ... L35: =IFERROR(365/L28,0) | N35: =IFERROR(AVERAGE(C35:L35),0) | O35: =IFERROR(MEDIAN(C35:L35),0)
B36: Inventory Days | C36: =IFERROR(365/C29,0) | D36: =IFERROR(365/D29,0) | E36: =IFERROR(365/E29,0) | F36: =IFERROR(365/F29,0) | G36: =IFERROR(365/G29,0) | H36: =IFERROR(365/H29,0) | I36: =IFERROR(365/I29,0) | J36: =IFERROR(365/J29,0) | ... L36: =IFERROR(365/L29,0) | N36: =IFERROR(AVERAGE(C36:L36),0) | O36: =IFERROR(MEDIAN(C36:L36),0)
B37: Cash Conversion Cycle | C37: =SUM(C34,C36)-C35 | D37: =SUM(D34,D36)-D35 | E37: =SUM(E34,E36)-E35 | F37: =SUM(F34,F36)-F35 | G37: =SUM(G34,G36)-G35 | H37: =SUM(H34,H36)-H35 | I37: =SUM(I34,I36)-I35 | J37: =SUM(J34,J36)-J35 | ... L37: =SUM(L34,L36)-L35 | N37: =IFERROR(AVERAGE(C37:L37),0) | O37: =IFERROR(MEDIAN(C37:L37),0)
B39: CFO/Sales | C39: =IFERROR('Historical FS'!C80/'Historical FS'!C7,0) | D39: =IFERROR('Historical FS'!D80/'Historical FS'!D7,0) | E39: =IFERROR('Historical FS'!E80/'Historical FS'!E7,0) | F39: =IFERROR('Historical FS'!F80/'Historical FS'!F7,0) | G39: =IFERROR('Historical FS'!G80/'Historical FS'!G7,0) | H39: =IFERROR('Historical FS'!H80/'Historical FS'!H7,0) | I39: =IFERROR('Historical FS'!I80/'Historical FS'!I7,0) | J39: =IFERROR('Historical FS'!J80/'Historical FS'!J7,0) | ... L39: =IFERROR('Historical FS'!L80/'Historical FS'!L7,0) | N39: =IFERROR(AVERAGE(C39:L39),0) | O39: =IFERROR(MEDIAN(C39:L39),0)
B40: CFO/Total Assets | C40: =IFERROR('Historical FS'!C80/'Historical FS'!C68,0) | D40: =IFERROR('Historical FS'!D80/'Historical FS'!D68,0) | E40: =IFERROR('Historical FS'!E80/'Historical FS'!E68,0) | F40: =IFERROR('Historical FS'!F80/'Historical FS'!F68,0) | G40: =IFERROR('Historical FS'!G80/'Historical FS'!G68,0) | H40: =IFERROR('Historical FS'!H80/'Historical FS'!H68,0) | I40: =IFERROR('Historical FS'!I80/'Historical FS'!I68,0) | J40: =IFERROR('Historical FS'!J80/'Historical FS'!J68,0) | ... L40: =IFERROR('Historical FS'!L80/'Historical FS'!L68,0) | N40: =IFERROR(AVERAGE(C40:L40),0) | O40: =IFERROR(MEDIAN(C40:L40),0)
B41: CFO/Total Debt | C41: =IFERROR('Historical FS'!C80/'Historical FS'!C53,0) | D41: =IFERROR('Historical FS'!D80/'Historical FS'!D53,0) | E41: =IFERROR('Historical FS'!E80/'Historical FS'!E53,0) | F41: =IFERROR('Historical FS'!F80/'Historical FS'!F53,0) | G41: =IFERROR('Historical FS'!G80/'Historical FS'!G53,0) | H41: =IFERROR('Historical FS'!H80/'Historical FS'!H53,0) | I41: =IFERROR('Historical FS'!I80/'Historical FS'!I53,0) | J41: =IFERROR('Historical FS'!J80/'Historical FS'!J53,0) | ... L41: =IFERROR('Historical FS'!L80/'Historical FS'!L53,0) | N41: =IFERROR(AVERAGE(C41:L41),0) | O41: =IFERROR(MEDIAN(C41:L41),0)

Sheet Forecasting
B2: ='Data Sheet'!$B$1&" -"&'Data Sheet'!A17&" Forecasting" | G2: ='Data Sheet'!$B$1&" -"&'Historical FS'!B19&" Forecasting" | L2: ='Data Sheet'!$B$1&" -"&'Historical FS'!B37&" Forecasting"
B3: Year Weight | C3: Year | D3: Sales | E3: Sales Growth | G3: Year Weight | H3: Year | I3: EBITDA | J3: EBITDA Growth | L3: Year Weight | M3: Year | N3: Net Profit | O3: Net Profit Growth
B5: 1 | C5: {=TRANSPOSE('Data Sheet'!B16:J16)} | D5: {=TRANSPOSE('Data Sheet'!B17:K17)} | E5: - | G5: 1 | H5: {=TRANSPOSE('Data Sheet'!B16:J16)} | I5: {=TRANSPOSE('Historical FS'!C19:L19)} | J5: - | L5: 1 | M5: {=TRANSPOSE('Data Sheet'!B16:J16)} | N5: {=TRANSPOSE('Historical FS'!C37:L37)} | O5: -
B6: =B5+1 | C6: 43190 | D6: 35923.92 | E6: =D6/D5-1 | G6: =G5+1 | H6: 43190 | I6: 2220.53 | J6: =I6/I5-1 | L6: =L5+1 | M6: 43190 | N6: 194.33 | O6: =N6/N5-1
B7: =B6+1 | C7: 43555 | D7: 40378.66 | E7: =D7/D6-1 | G7: =G6+1 | H7: 43555 | I7: 2612.43 | J7: =I7/I6-1 | L7: =L6+1 | M7: 43555 | N7: 453.05 | O7: =N7/N6-1
B8: =B7+1 | C8: 43921 | D8: 43402.56 | E8: =D8/D7-1 | G8: =G7+1 | H8: 43921 | I8: 2976.91 | J8: =I8/I7-1 | L8: =L7+1 | M8: 43921 | N8: 608.2 | O8: =N8/N7-1
B9: =B8+1 | C9: 44286 | D9: 39537.13 | E9: =D9/D8-1 | G9: =G8+1 | H9: 44286 | I9: 2781.19 | J9: =I9/I8-1 | L9: =L8+1 | M9: 44286 | N9: 527.55 | O9: =N9/N8-1
B10: =B9+1 | C10: 44651 | D10: 69420.18 | E10: =D10/D9-1 | G10: =G9+1 | H10: 44651 | I10: 4255.65 | J10: =I10/I9-1 | L10: =L9+1 | M10: 44651 | N10: 5.31 | O10: =N10/N9-1
B11: =B10+1 | C11: 45016 | D11: 127539.5 | E11: =D11/D10-1 | G11: =G10+1 | H11: 45016 | I11: 9641.99 | J11: =I11/I10-1 | L11: =L10+1 | M11: 45016 | N11: 2199.01 | O11: =N11/N10-1
B12: =B11+1 | C12: 45382 | D12: 96420.98 | E12: =D12/D11-1 | G12: =G11+1 | H12: 45382 | I12: 12604.43 | J12: =I12/I11-1 | L12: =L11+1 | M12: 45382 | N12: 3376.07 | O12: =N12/N11-1
B13: =B12+1 | C13: 45747 | D13: 97894.75 | E13: =D13/D12-1 | G13: =G12+1 | H13: 45747 | I13: 15155.67 | J13: =I13/I12-1 | L13: =L12+1 | M13: 45747 | N13: 1997.8 | O13: =N13/N12-1
B14: =B13+1 | C14: =C13+365 | D14: 100468.61 | E14: =D14/D13-1 | G14: =G13+1 | H14: =H13+365 | I14: 15128.17 | J14: =I14/I13-1 | L14: =L13+1 | M14: =M13+365 | N14: -857.44 | O14: =N14/N13-1
B15: =B14+1 | C15: =C14+365 | D15: =FORECAST(B15,$D$5:$D$14,$B$5:$B$14) | E15: =D15/D14-1 | G15: =G14+1 | H15: =H14+365 | I15: =FORECAST(G15,$I$5:$I$14,$G$5:$G$14) | J15: =I15/I14-1 | L15: =L14+1 | M15: =M14+365 | N15: =FORECAST(L15,$N$5:$N$14,$L$5:$L$14) | O15: =N15/N14-1
B16: =B15+1 | C16: =C15+365 | D16: =FORECAST(B16,$D$5:$D$14,$B$5:$B$14) | E16: =D16/D15-1 | G16: =G15+1 | H16: =H15+365 | I16: =FORECAST(G16,$I$5:$I$14,$G$5:$G$14) | J16: =I16/I15-1 | L16: =L15+1 | M16: =M15+365 | N16: =FORECAST(L16,$N$5:$N$14,$L$5:$L$14) | O16: =N16/N15-1
B17: =B16+1 | C17: =C16+365 | D17: =FORECAST(B17,$D$5:$D$14,$B$5:$B$14) | E17: =D17/D16-1 | G17: =G16+1 | H17: =H16+365 | I17: =FORECAST(G17,$I$5:$I$14,$G$5:$G$14) | J17: =I17/I16-1 | L17: =L16+1 | M17: =M16+365 | N17: =FORECAST(L17,$N$5:$N$14,$L$5:$L$14) | O17: =N17/N16-1
B18: =B17+1 | C18: =C17+365 | D18: =FORECAST(B18,$D$5:$D$14,$B$5:$B$14) | E18: =D18/D17-1 | G18: =G17+1 | H18: =H17+365 | I18: =FORECAST(G18,$I$5:$I$14,$G$5:$G$14) | J18: =I18/I17-1 | L18: =L17+1 | M18: =M17+365 | N18: =FORECAST(L18,$N$5:$N$14,$L$5:$L$14) | O18: =N18/N17-1
B19: =B18+1 | C19: =C18+365 | D19: =FORECAST(B19,$D$5:$D$14,$B$5:$B$14) | E19: =D19/D18-1 | G19: =G18+1 | H19: =H18+365 | I19: =FORECAST(G19,$I$5:$I$14,$G$5:$G$14) | J19: =I19/I18-1 | L19: =L18+1 | M19: =M18+365 | N19: =FORECAST(L19,$N$5:$N$14,$L$5:$L$14) | O19: =N19/N18-1

Sheet Rm
B6: Return on Markets
B8: Date | C8: Annual
B9: ='Raw Data'!B6 | C9: ='Raw Data'!C6
B10: ='Raw Data'!B7 | C10: ='Raw Data'!C7
B11: ='Raw Data'!B8 | C11: ='Raw Data'!C8
B12: ='Raw Data'!B9 | C12: ='Raw Data'!C9 | E12: Average Market Returns | H12: =AVERAGE(C9:C32)
B13: ='Raw Data'!B10 | C13: ='Raw Data'!C10 | E13: Dividend Yield | H13: 0.0128
B14: ='Raw Data'!B11 | C14: ='Raw Data'!C11 | E14: Total Market Returns | H14: =SUM(H12:H13)
B15: ='Raw Data'!B12 | C15: ='Raw Data'!C12
B16: ='Raw Data'!B13 | C16: ='Raw Data'!C13
B17: ='Raw Data'!B14 | C17: ='Raw Data'!C14
B18: ='Raw Data'!B15 | C18: ='Raw Data'!C15
B19: ='Raw Data'!B16 | C19: ='Raw Data'!C16
B20: ='Raw Data'!B17 | C20: ='Raw Data'!C17
B21: ='Raw Data'!B18 | C21: ='Raw Data'!C18
B22: ='Raw Data'!B19 | C22: ='Raw Data'!C19
B23: ='Raw Data'!B20 | C23: ='Raw Data'!C20
B24: ='Raw Data'!B21 | C24: ='Raw Data'!C21
B25: ='Raw Data'!B22 | C25: ='Raw Data'!C22
B26: ='Raw Data'!B23 | C26: ='Raw Data'!C23
... B32: ='Raw Data'!B29 | C32: ='Raw Data'!C29

Sheet Beta-Regression
B6: Beta Regression
B7: ='Data Sheet'!B1&" Daily Returns" | F7: Nifty 50 Daily Returns | J7: Beta Drifting
B9: Date | C9: Closing Price | D9: Daily Returns | F9: Date | G9: Closing Price | H9: Daily Returns | J9: Levered Raw Beta | L9: =O11
B10: ='Raw Data'!G6 | C10: 285.05 | D10: - | F10: ='Raw Data'!G6 | G10: ='Raw Data'!J6 | H10: - | J10: Raw Beta Weight | L10: 0.75
B11: ='Raw Data'!G7 | C11: 286.25 | D11: =C10/C11-1 | F11: ='Raw Data'!G7 | G11: ='Raw Data'!J7 | H11: =G10/G11-1 | N11: Beta 1 | O11: =SLOPE(D10:D252,H10:H252)
B12: ='Raw Data'!G8 | C12: 284.65 | D12: =C11/C12-1 | F12: ='Raw Data'!G8 | G12: ='Raw Data'!J8 | H12: =G11/G12-1 | J12: Market Beta | L12: 1 | N12: Beta 2 | O12: =_xlfn.COVARIANCE.S(D10:D252,H10:H252)/_xlfn.VAR.S(H10:H252)
B13: ='Raw Data'!G9 | C13: 285.85 | D13: =C12/C13-1 | F13: ='Raw Data'!G9 | G13: ='Raw Data'!J9 | H13: =G12/G13-1 | J13: Market Beta Weight | L13: 0.25
B14: ='Raw Data'!G10 | C14: 283.45 | D14: =C13/C14-1 | F14: ='Raw Data'!G10 | G14: ='Raw Data'!J10 | H14: =G13/G14-1
B15: ='Raw Data'!G11 | C15: 281.3 | D15: =C14/C15-1 | F15: ='Raw Data'!G11 | G15: ='Raw Data'!J11 | H15: =G14/G15-1 | J15: Adjusted Beta | L15: =(L9*L10)+(L12*L13)
B16: ='Raw Data'!G12 | C16: 280.8 | D16: =C15/C16-1 | F16: ='Raw Data'!G12 | G16: ='Raw Data'!J12 | H16: =G15/G16-1
B17: ='Raw Data'!G13 | C17: 281 | D17: =C16/C17-1 | F17: ='Raw Data'!G13 | G17: ='Raw Data'!J13 | H17: =G16/G17-1
B18: ='Raw Data'!G14 | C18: 282.7 | D18: =C17/C18-1 | F18: ='Raw Data'!G14 | G18: ='Raw Data'!J14 | H18: =G17/G18-1
B19: ='Raw Data'!G15 | C19: 280.7 | D19: =C18/C19-1 | F19: ='Raw Data'!G15 | G19: ='Raw Data'!J15 | H19: =G18/G19-1
B20: ='Raw Data'!G16 | C20: 279.35 | D20: =C19/C20-1 | F20: ='Raw Data'!G16 | G20: ='Raw Data'!J16 | H20: =G19/G20-1
B21: ='Raw Data'!G17 | C21: 276.65 | D21: =C20/C21-1 | F21: ='Raw Data'!G17 | G21: ='Raw Data'!J17 | H21: =G20/G21-1
B22: ='Raw Data'!G18 | C22: 275.55 | D22: =C21/C22-1 | F22: ='Raw Data'!G18 | G22: ='Raw Data'!J18 | H22: =G21/G22-1
B23: ='Raw Data'!G19 | C23: 279.65 | D23: =C22/C23-1 | F23: ='Raw Data'!G19 | G23: ='Raw Data'!J19 | H23: =G22/G23-1
B24: ='Raw Data'!G20 | C24: 281.75 | D24: =C23/C24-1 | F24: ='Raw Data'!G20 | G24: ='Raw Data'!J20 | H24: =G23/G24-1
B25: ='Raw Data'!G21 | C25: 282.05 | D25: =C24/C25-1 | F25: ='Raw Data'!G21 | G25: ='Raw Data'!J21 | H25: =G24/G25-1
B26: ='Raw Data'!G22 | C26: 280.65 | D26: =C25/C26-1 | F26: ='Raw Data'!G22 | G26: ='Raw Data'!J22 | H26: =G25/G26-1
B27: ='Raw Data'!G23 | C27: 288.75 | D27: =C26/C27-1 | F27: ='Raw Data'!G23 | G27: ='Raw Data'!J23 | H27: =G26/G27-1
... B252: ='Raw Data'!G248 | C252: 414.15 | D252: =C251/C252-1 | F252: ='Raw Data'!G248 | G252: ='Raw Data'!J248 | H252: =G251/G252-1

Sheet WACC
B6: Weighted Average Cost of Capital
B8: All figures are in INR unless stated otherwise
B10: Peer Comps
E11: Total Debt | F11: Total Equity | H11: Debt /Equity | I11: Debt /Capital | J11: Levered Beta | K11: Unlevered Beta
B12: Name of the Comp | D12: Country | G12: Tax Rate
B14: ='Raw Data'!O24 | D14: ='Raw Data'!Q24 | E14: ='Raw Data'!R24 | F14: ='Raw Data'!S24 | G14: ='Raw Data'!T24 | H14: =E14/F14 | I14: =E14/SUM(E14:F14) | J14: 0.7 | K14: =J14/(1+(1-G14)*H14)
B15: ='Raw Data'!O25 | D15: ='Raw Data'!Q25 | E15: ='Raw Data'!R25 | F15: ='Raw Data'!S25 | G15: ='Raw Data'!T25 | H15: =E15/F15 | I15: =E15/SUM(E15:F15) | J15: ='Beta-Regression'!L15 | K15: =J15/(1+(1-G15)*H15)
B16: ='Raw Data'!O26 | D16: ='Raw Data'!Q26 | E16: ='Raw Data'!R26 | F16: ='Raw Data'!S26 | G16: ='Raw Data'!T26 | H16: =E16/F16 | I16: =E16/SUM(E16:F16) | J16: 0.69 | K16: =J16/(1+(1-G16)*H16)
B17: ='Raw Data'!O27 | D17: ='Raw Data'!Q27 | E17: ='Raw Data'!R27 | F17: ='Raw Data'!S27 | G17: ='Raw Data'!T27 | H17: =E17/F17 | I17: =E17/SUM(E17:F17) | J17: 0.9 | K17: =J17/(1+(1-G17)*H17)
B18: ='Raw Data'!O28 | D18: ='Raw Data'!Q28 | E18: ='Raw Data'!R28 | F18: ='Raw Data'!S28 | G18: ='Raw Data'!T28 | H18: =E18/F18 | I18: =E18/SUM(E18:F18) | J18: 0.73 | K18: =J18/(1+(1-G18)*H18)
F20: Average | G20: =AVERAGE(G14:G18) | H20: =AVERAGE(H14:H18) | I20: =AVERAGE(I14:I18) | J20: =AVERAGE(J14:J18) | K20: =AVERAGE(K14:K18)
F21: Median | G21: =MEDIAN(G14:G18) | H21: =MEDIAN(H14:H18) | I21: =MEDIAN(I14:I18) | J21: =MEDIAN(J14:J18) | K21: =MEDIAN(K14:K18)
B24: Cost of Debt | G24: Cost of Capital
B26: Pre-Tax Cost of Debt | E26: 0.0805 | G26: Risk Free Rate | K26: 0.07
B27: Tax Rate | E27: =G14 | G27: Equity Risk Premium | K27: 0.065
B28: Post-Tax Cost of Debt | E28: =E26*(1-E27) | G28: Levered Beta | K28: =K36
G29: Cost of Capital | K29: =K26+K27*K28
B31: Capital Structure | G31: Levered Beta
D33: Current | E33: Target | G33: Comps Median Unlevered Beta | K33: =K21
B34: Total Debt | C34: =E14 | D34: =C34/C$36 | E34: =I20 | G34: Target Debt/Equity | K34: =E38
B35: Market Capitalization | C35: =F14 | D35: =C35/C$36 | E35: =E36-E34 | G35: Tax Rate | K35: =E27
B36: Total Capital | C36: =SUM(C34:C35) | D36: =C36/C$36 | E36: =D36 | G36: Levered Beta | K36: =K33*(1+(1-K35)*K34)
B38: Debt /Equity | D38: =D34/D35 | E38: =E34/E35 | G38: WACC
G40: Cost of Equity | K40: =K29
G41: Equity Weight | K41: =E35
G43: Cost of Debt | K43: =E28
G44: Debt Weight | K44: =E34
G46: WACC | K46: =(K40*K41)+(K43*K44)

Sheet Intrinsic Valuation
B6: Calculation of ROIC | H6: ='Raw FS'!J$3 | I6: ='Raw FS'!K$3 | J6: ='Raw FS'!L$3 | K6: ='Raw FS'!M$3 | L6: ='Raw FS'!N$3
B8: Current Assets
B9: ='Raw FS'!B39 | H9: ='Raw FS'!J39 | I9: ='Raw FS'!K39 | J9: ='Raw FS'!L39 | K9: ='Raw FS'!M39 | L9: ='Raw FS'!N39
B10: Trade Receivables | H10: ='Raw FS'!J40 | I10: ='Raw FS'!K40 | J10: ='Raw FS'!L40 | K10: ='Raw FS'!M40 | L10: ='Raw FS'!N40
B11: ='Raw FS'!B42 | H11: ='Raw FS'!J42 | I11: ='Raw FS'!K42 | J11: ='Raw FS'!L42 | K11: ='Raw FS'!M42 | L11: ='Raw FS'!N42
B12: ='Raw FS'!B43 | H12: ='Raw FS'!J43 | I12: ='Raw FS'!K43 | J12: ='Raw FS'!L43 | K12: ='Raw FS'!M43 | L12: ='Raw FS'!N43
B13: Total Current Assets | H13: =SUM(H9:H12) | I13: =SUM(I9:I12) | J13: =SUM(J9:J12) | K13: =SUM(K9:K12) | L13: =SUM(L9:L12)
B15: Current Liabilities
B16: ='Raw FS'!B14 | H16: ='Raw FS'!J14 | I16: ='Raw FS'!K14 | J16: ='Raw FS'!L14 | K16: ='Raw FS'!M14 | L16: ='Raw FS'!N14
B17: ='Raw FS'!B15 | H17: ='Raw FS'!J15 | I17: ='Raw FS'!K15 | J17: ='Raw FS'!L15 | K17: ='Raw FS'!M15 | L17: ='Raw FS'!N15
B18: ='Raw FS'!B16 | H18: ='Raw FS'!J16 | I18: ='Raw FS'!K16 | J18: ='Raw FS'!L16 | K18: ='Raw FS'!M16 | L18: ='Raw FS'!N16
B19: Total Current Liabilities | H19: =SUM(H16:H18) | I19: =SUM(I16:I18) | J19: =SUM(J16:J18) | K19: =SUM(K16:K18) | L19: =SUM(L16:L18)
A21: # | B21: Net Working Capital | H21: =H13-H19 | I21: =I13-I19 | J21: =J13-J19 | K21: =K13-K19 | L21: =L13-L19
B23: Non Current Assets
B24: ='Raw FS'!B22 | H24: ='Raw FS'!J22 | I24: ='Raw FS'!K22 | J24: ='Raw FS'!L22 | K24: ='Raw FS'!M22 | L24: ='Raw FS'!N22
B25: ='Raw FS'!B23 | H25: ='Raw FS'!J23 | I25: ='Raw FS'!K23 | J25: ='Raw FS'!L23 | K25: ='Raw FS'!M23 | L25: ='Raw FS'!N23
B26: ='Raw FS'!B24 | H26: ='Raw FS'!J24 | I26: ='Raw FS'!K24 | J26: ='Raw FS'!L24 | K26: ='Raw FS'!M24 | L26: ='Raw FS'!N24
B27: ='Raw FS'!B25 | H27: ='Raw FS'!J25 | I27: ='Raw FS'!K25 | J27: ='Raw FS'!L25 | K27: ='Raw FS'!M25 | L27: ='Raw FS'!N25
B28: ='Raw FS'!B26 | H28: ='Raw FS'!J26 | I28: ='Raw FS'!K26 | J28: ='Raw FS'!L26 | K28: ='Raw FS'!M26 | L28: ='Raw FS'!N26
B29: ='Raw FS'!B27 | H29: ='Raw FS'!J27 | I29: ='Raw FS'!K27 | J29: ='Raw FS'!L27 | K29: ='Raw FS'!M27 | L29: ='Raw FS'!N27
B30: ='Raw FS'!B28 | H30: ='Raw FS'!J28 | I30: ='Raw FS'!K28 | J30: ='Raw FS'!L28 | K30: ='Raw FS'!M28 | L30: ='Raw FS'!N28
B31: ='Raw FS'!B29 | H31: ='Raw FS'!J29 | I31: ='Raw FS'!K29 | J31: ='Raw FS'!L29 | K31: ='Raw FS'!M29 | L31: ='Raw FS'!N29
B32: ='Raw FS'!B30 | H32: ='Raw FS'!J30 | I32: ='Raw FS'!K30 | J32: ='Raw FS'!L30 | K32: ='Raw FS'!M30 | L32: ='Raw FS'!N30
B33: ='Raw FS'!B31 | H33: ='Raw FS'!J31 | I33: ='Raw FS'!K31 | J33: ='Raw FS'!L31 | K33: ='Raw FS'!M31 | L33: ='Raw FS'!N31
B34: ='Raw FS'!B32 | H34: ='Raw FS'!J32 | I34: ='Raw FS'!K32 | J34: ='Raw FS'!L32 | K34: ='Raw FS'!M32 | L34: ='Raw FS'!N32
B35: Net Non Current Assets | H35: ='Raw FS'!J33 | I35: ='Raw FS'!K33 | J35: ='Raw FS'!L33 | K35: ='Raw FS'!M33 | L35: ='Raw FS'!N33
B37: Invested Capital | H37: =H35+H21 | I37: =I35+I21 | J37: =J35+J21 | K37: =K35+K21 | L37: =L35+L21
B38: EBIT | H38: ='Raw FS'!Z11+'Raw FS'!Z9 | I38: ='Raw FS'!AA11+'Raw FS'!AA9 | J38: ='Raw FS'!AB11+'Raw FS'!AB9 | K38: ='Raw FS'!AC11+'Raw FS'!AC9 | L38: ='Raw FS'!AD11+'Raw FS'!AD9
B40: ROIC | H40: =H38/H37 | I40: =I38/I37 | J40: =J38/J37 | K40: =K38/K37 | L40: =L38/L37
B42: Calculation of Reinvestment Rate | H42: ='Raw FS'!J$3 | I42: ='Raw FS'!K$3 | J42: ='Raw FS'!L$3 | K42: ='Raw FS'!M$3 | L42: ='Raw FS'!N$3
B44: Net Capex | H44: =-SUM('Raw FS'!Z27:Z28) | I44: =-SUM('Raw FS'!AA27:AA28) | J44: =-SUM('Raw FS'!AB27:AB28) | K44: =-SUM('Raw FS'!AC27:AC28) | L44: =-SUM('Raw FS'!AD27:AD28)
B45: Change in Work Cap | H45: - | I45: =I21-H21 | J45: =J21-I21 | K45: =K21-J21 | L45: =L21-K21
B47: EBIT | H47: =H38 | I47: =I38 | J47: =J38 | K47: =K38 | L47: =L38
B48: Tax Rate | H48: =WACC!E27 | I48: =H48 | J48: =I48 | K48: =J48 | L48: =K48
B49: EBIT(1-T) | H49: =H47*(1-H48) | I49: =I47*(1-I48) | J49: =J47*(1-J48) | K49: =K47*(1-K48) | L49: =L47*(1-L48)
B51: Reinvestment | H51: - | I51: =SUM(I44:I45) | J51: =SUM(J44:J45) | K51: =SUM(K44:K45) | L51: =SUM(L44:L45)
B52: Reinvestment Rate | H52: - | I52: =I51/I49 | J52: =J51/J49 | K52: =K51/K49 | L52: =L51/L49
J54: 4 Year Average | L54: =AVERAGE(I52:L52)
J55: 4 Year Median | L55: =MEDIAN(I52:L52)
B57: Calculation of Growth Rate | H57: ='Raw FS'!J$3 | I57: ='Raw FS'!K$3 | J57: ='Raw FS'!L$3 | K57: ='Raw FS'!M$3 | L57: ='Raw FS'!N$3
B59: ROIC | H59: =H40 | I59: =I40 | J59: =J40 | K59: =K40 | L59: =L40
B60: Reinvestment Rate | H60: - | I60: =I52 | J60: =J52 | K60: =K52 | L60: =L52
B62: Intrinsic Growth | I62: =I59*I60 | J62: =J59*J60 | K62: =K59*K60 | L62: =L59*L60
J64: 4 Year Average | L64: =AVERAGE(I62:L62)
J65: 4 Year Median | L65: =MEDIAN(I62:L62)

Sheet DCF
B6: Calculation of PV of FCFF | H6: ='Data Sheet'!K56 | I6: =H6+365 | J6: =I6+365 | K6: =J6+365 | L6: =K6+365 | M6: =L6+365
B8: EBIT | H8: ='Intrinsic Valuation'!L38 | I8: =H8*(1+$D$18) | J8: =I8*(1+$D$18) | K8: =J8*(1+$D$18) | L8: =K8*(1+$D$18) | M8: =L8*(1+$D$18)
B9: Tax Rate | H9: =WACC!G14 | I9: =H9 | J9: =I9 | K9: =J9 | L9: =K9 | M9: =L9
B10: EBIT(1-T) | H10: =H8*(1-H9) | I10: =I8*(1-I9) | J10: =J8*(1-J9) | K10: =K8*(1-K9) | L10: =L8*(1-L9) | M10: =M8*(1-M9)
B11: Less: Reinvestment Rate | H11: ='Intrinsic Valuation'!$L$55 | I11: =MIN(0.85, MAX(0.15, 'Intrinsic Valuation'!$L$55)) | J11: =$I$11+($M$11-$I$11)/4*1 | K11: =$I$11+($M$11-$I$11)/4*2 | L11: =$I$11+($M$11-$I$11)/4*3 | M11: =D21 | N11: 0
B12: Free Cash Flow to Firm | H12: =H10*(1-H11) | I12: =I10*(1-MIN(0.85, I11)) | J12: =J10*(1-MIN(0.85, J11)) | K12: =K10*(1-MIN(0.85, K11)) | L12: =L10*(1-MIN(0.85, L11)) | M12: =M10*(1-MIN(0.85, M11))
B13: Mid Year Convention | H13: - | I13: 0.5 | J13: =I13+1 | K13: =J13+1 | L13: =K13+1 | M13: =L13+1
B14: Discounting Factor | I14: =1/(1+$D$20)^I13 | J14: =1/(1+$D$20)^J13 | K14: =1/(1+$D$20)^K13 | L14: =1/(1+$D$20)^L13 | M14: =1/(1+$D$20)^M13
B16: PV of FCFF | I16: =I12*I14 | J16: =J12*J14 | K16: =K12*K14 | L16: =L12*L14 | M16: =M12*M14
B18: Expected Growth Rate | D18: 0.052
B19: Terminal Growth Rate | D19: 0.04
B20: WACC | D20: =WACC!K46
B21: Terminal Reinvestment Rate | D21: =D19/D20
B23: Calculation of Terminal Value
B25: FCFF(n+1) | D25: =M12*(1+D19)
B26: WACC | D26: =D20
B27: Terminal Growth Rate | D27: =D19
B29: Terminal value | D29: =D25/(D26-D27)
B31: Calculation of Equity Value
B33: PV of FCFF | D33: =SUM(I16:M16)
B34: Terminal value | D34: =D29*M14
B35: Value of Operating Assets | D35: =SUM(D33:D34)
B37: Add: Cash | D37: ='Data Sheet'!K69
B38: Less: Debt | D38: ='Data Sheet'!K59
B39: Equity Value | D39: =D35+D37-D38
B40: No. of Shares | D40: ='Data Sheet'!K70/10000000
B42: Equity Value per Share | D42: =D39/D40
B44: Share Price | D44: 2999
B45: Discount /Premium | D45: =D44/D42

Sheet Raw Data
B6: 2025 | C6: 0.1051 | G6: 46233 | H6: 2107.9 | J6: 24474.3
B7: 2024 | C7: 0.0875 | G7: 46232 | H7: 2117.8 | J7: 24566.8
B8: 2023 | C8: 0.1942 | G8: 46231 | H8: 2022.7 | J8: 24236.8
B9: 2022 | C9: 0.0432 | G9: 46230 | H9: 2174.6 | J9: 24101.8
B10: 2021 | C10: 0.2412 | G10: 46227 | H10: 2145 | J10: 23874.6
B11: 2020 | C11: 0.149 | G11: 46226 | H11: 2161.8 | J11: 24082.5 | N11: S.No. | O11: Name | P11: CMP Rs. | Q11: No. Eq. Shares Cr. | R11: Mar Cap Rs.Cr. | S11: Debt Rs.Cr. | T11: Cash End Rs.Cr. | U11: EV Rs.Cr. | V11: Sales Rs.Cr. | W11: EV / EBITDA | X11: NP 12M Rs.Cr.
B12: 2019 | C12: 0.1202 | G12: 46225 | H12: 2154.6 | J12: 23988.4 | N12: 1 | O12: Hind. Unilever | P12: 2087.2 | Q12: 234.96 | R12: 494084.03 | S12: 1478 | T12: 3248 | U12: 492314.03 | V12: 66052 | W12: 30.61 | X12: 14971
B13: 2018 | C13: 0.0315 | G13: 46224 | H13: 2142.5 | J13: 24180.6 | N13: 2 | O13: ITC | P13: 282.65 | Q13: 1252.95 | R13: 354889.69 | S13: 2399.06 | T13: 3008.79 | U13: 354279.96 | V13: 76487.98 | W13: 12.44 | X13: 20183.53
B14: 2017 | C14: 0.2865 | G14: 46223 | H14: 2139.7 | J14: 24487.8 | N14: 3 | O14: Hindustan Foods | P14: 585.6 | Q14: 12.12 | R14: 7105.77 | S14: 1088.26 | T14: 51.71 | U14: 8142.32 | V14: 4400.19 | W14: 20.53 | X14: 158.3
B15: 2016 | C15: 0.0301 | G15: 46220 | H15: 2143.8 | J15: 24321.7 | N15: 4 | O15: Godavari Bioref. | P15: 240.1 | Q15: 5.12 | R15: 1227 | S15: 530.76 | T15: 32.15 | U15: 1725.61 | V15: 2012.58 | W15: 12.74 | X15: 0.22
B16: 2015 | C16: -0.0406 | G16: 46219 | H16: 2098.4 | J16: 24190.6 | N16: 5 | O16: Davangere Sugar | P16: 3.08 | Q16: 143 | R16: 440.44 | S16: 250.05 | T16: 6.57 | U16: 683.92 | V16: 238.77 | W16: 13.43 | X16: 8.51
B17: 2014 | C17: 0.3139 | G17: 46218 | H17: 2102.6 | J17: 24067.8
B18: 2013 | C18: 0.0676 | G18: 46217 | H18: 2120.2 | J18: 24266.4
B19: 2012 | C19: 0.277 | G19: 46216 | H19: 2130.6 | J19: 24472.6
B20: 2011 | C20: -0.2462 | G20: 46213 | H20: 2150.6 | J20: 24328.7
B21: 2010 | C21: 0.1795 | G21: 46212 | H21: 2144.5 | J21: 24090.8
B22: 2009 | C22: 0.7576 | G22: 46211 | H22: 2135.8 | J22: 24170
B23: 2008 | C23: -0.5179 | G23: 46210 | H23: 2208.8 | J23: 24440.3
B24: 2007 | C24: 0.5477 | G24: 46209 | H24: 2202 | J24: 24482.9 | O24: Adani Enterprises Ltd | Q24: India | R24: 106622 | S24: 405443 | T24: 0.3
B25: 2006 | C25: 0.3983 | G25: 46206 | H25: 2201.2 | J25: 24614.3 | O25: Starlineps Enter | Q25: =Q24 | R25: 4 | S25: 357.27 | T25: =T24
B26: 2005 | C26: 0.3634 | G26: 46205 | H26: 2210.6 | J26: 24265 | O26: Rajdarshan Inds | Q26: =Q25 | R26: 0.5 | S26: 10.27 | T26: =T25
B27: 2004 | C27: 0.1068 | G27: 46204 | H27: 2182 | J27: 24195.3 | O27: Median: 2 Co. | Q27: =Q26 | R27: 0 | S27: 202899.94 | T27: =T26
B28: 2003 | C28: 0.719 | G28: 46203 | H28: 2118.2 | J28: 24111.9 | O28: Peer 5 | Q28: =Q27 | R28: 0 | S28: 10000 | T28: =T27
B29: 2002 | C29: 0.0325 | G29: 46202 | H29: 2151.3 | J29: 24142.3
G30: 46198 | H30: 2174.2 | J30: 24170.5
G31: 46197 | H31: 2157.8 | J31: 24125.2
G32: 46196 | H32: 2160.1 | J32: 24070.5
G33: 46195 | H33: 2184.9 | J33: 24123.8
G34: 46192 | H34: 2194.6 | J34: 24056.9
G35: 46191 | H35: 2218.5 | J35: 24382.4
G36: 46190 | H36: 2197.6 | J36: 24094
G37: 46189 | H37: 2199.9 | J37: 24087.9
G38: 46188 | H38: 2156.1 | J38: 23916.6
G39: 46185 | H39: 2168.8 | J39: 23873.5
G40: 46184 | H40: 2139.8 | J40: 23397.4
G41: 46183 | H41: 2169.5 | J41: 23344.9
... G248: 45874 | H248: 2534.7 | J248: 25041.8

Sheet Comp_Valuation
B6: Amount in crores
B7: Company Comparable Valuation
D9: Market Data | K9: Financials | O9: Valuation
B10: Larsen & Toubro | C10: 485000 | D10: 118000 | E10: 18000 | F10: 585000 | G10: 221000 | H10: 24500 | I10: =IF(G10>0, F10/G10, "N/A") | J10: =IF(H10>0, F10/H10, "N/A") | K10: Revenue | L10: EBITDA | M10: Net Income | O10: EV/Revenue | P10: EV/EBITDA | Q10: P/E
B11: Reliance Industries | C11: 2015000 | D11: 310000 | E11: 85000 | F11: 2240000 | G11: 900000 | H11: 165000 | I11: =IF(G11>0, F11/G11, "N/A") | J11: =IF(H11>0, F11/H11, "N/A")
B12: Adani Ports & SEZ | C12: 315000 | D12: 45000 | E12: 8000 | F12: 352000 | G12: 27000 | H12: 15800 | I12: =IF(G12>0, F12/G12, "N/A") | J12: =IF(H12>0, F12/H12, "N/A") | K12: ='Raw FS'!AU56 | L12: ='Raw FS'!AV56 | M12: ='Raw FS'!AW56 | O12: =$H12/K12 | P12: =$H12/L12 | Q12: =F12/M12
B13: Tata Power Co. | C13: 138000 | D13: 52000 | E13: 4000 | F13: 186000 | G13: 62000 | H13: 12500 | I13: =IF(G13>0, F13/G13, "N/A") | J13: =IF(H13>0, F13/H13, "N/A") | K13: ='Raw FS'!AU57 | L13: ='Raw FS'!AV57 | M13: ='Raw FS'!AW57 | O13: =$H13/K13 | P13: =$H13/L13 | Q13: =F13/M13
B14: NTPC Ltd | C14: 395000 | D14: 210000 | E14: 7000 | F14: 598000 | G14: 178000 | H14: 51000 | I14: =IF(G14>0, F14/G14, "N/A") | J14: =IF(H14>0, F14/H14, "N/A") | K14: ='Raw FS'!AU58 | L14: ='Raw FS'!AV58 | M14: ='Raw FS'!AW58 | O14: =$H14/K14 | P14: =$H14/L14 | Q14: =F14/M14
B23: High | O23: =MAX(O13:O21) | P23: =MAX(P13:P21) | Q23: =MAX(Q13:Q21)
B24: 25th Percentile | O24: =QUARTILE(O13:O21,1) | P24: =QUARTILE(P13:P21,1) | Q24: =QUARTILE(Q13:Q21,1)
B25: Median | O25: =MEDIAN(I10:I14) | P25: =MEDIAN(J10:J14) | Q25: =MEDIAN(Q13:Q21)
B26: Average | O26: =AVERAGE(I10:I14) | P26: =AVERAGE(J10:J14) | Q26: =AVERAGE(Q13:Q21)
B27: 75th Percentile | O27: =QUARTILE(O13:O21,3) | P27: =QUARTILE(P13:P21,3) | Q27: =QUARTILE(Q13:Q21,3)
B28: Low | O28: =MIN(O13:O21) | P28: =MIN(P13:P21) | Q28: =MIN(Q13:Q21)
B30: Adani Enterprises Ltd Comparable Valuation | O30: EV/Revenue | P30: EV/EBITDA | Q30: P/E
B32: Implied Enterprise Value | O32: =K12*O26 | P32: =L12*P26 | Q32: =M12*Q26
B33: Net Debt Value | O33: =$G$12 | P33: =$G$12 | Q33: =$G$12
B34: Implied Market Value | O34: =O32-O33 | P34: =P32-P33 | Q34: =Q32
B35: Share Outstanding | O35: =$E$12 | P35: =$E$12 | Q35: =$E$12
B37: Implied Value per Share | O37: =O34/O35 | P37: =P34/P35 | Q37: =Q34/Q35
B38: Source : Screener.in
O39: =IF(O37>$D$12,"Overvalued","Undervalued") | P39: =IF(P37>$D$12,"Overvalued","Undervalued") | Q39: =IF(Q37>$D$12,"Overvalued","Undervalued")

Sheet Dupont Analysis
B2: ='Data Sheet'!B1
B3: =CONCATENATE("(",VLOOKUP(B2,'List of Stocks'!B2:E5442,3,FALSE)," | ","BSE Code: ",VLOOKUP('Dupont Analysis'!B2,'List of Stocks'!B2:E5442,2,FALSE))
B4: =CONCATENATE(" ","INR "&'Data Sheet'!B8)
B5: 52 Week (High - INR - 427.00 & low INR - 275.00)
B6: About the Company
B8: ITC Limited is an Indian conglomerate, headquartered in Kolkata.It has a presence across six business segments, namely FMCG, agribusiness, information technology, paper products, and packaging. It generates a plurality of its revenue from tobacco products.In terms of market capitalization, ITC is the second-largest FMCG company in India and the third-largest tobacco company in the world
B15: Financial Summary
B35: Recent Updates
A37: • | B37: This move immediately scales up ITC's pulp, writing, and printing paper capacities to target India's booming FMCG, pharma, and e-commerce packaging sectors
A39: • | B39: While cigarettes lagged, consumer categories like dairy and snacks maintained steady YoY growth. The company is actively chasing a ₹8 lakh crore FMCG market opportunity by 2035 through AI-led infrastructure and strategic acquisitions
A41: • | B41: ITC Infotech will deliver AI-enabled innovation, scaling capabilities inside BAT's new Future Capabilities Centre in India alongside hubs in Poland, Romania, and Malaysia
A43: • | B43: ITC completed the integration of Century Pulp & Paper from Aditya Birla Real Estate.Net Profit Drop: Declined by 27.1% YoY to ₹3,579 crore (estimated at ₹4,368 crore)
A45: • | B45: Despite severe margin pressures in its core tobacco business, the conglomerate continues aggressive expansions across its FMCG, hospitality, paper, and technology segments
A47: • | B47: ITC Limited’s Q1 FY27 net profit plunged 27% year-on-year to approximately ₹3,579 crore, missing street estimates due to sharp cigarette excise duty hikes and geopolitical disruptions.
B54: Dupont Analysis - Return on Equity & Return on Assets
B58: Return on Equity
E59: ='Data Sheet'!G$56 | F59: ='Data Sheet'!H$56 | G59: ='Data Sheet'!I$56 | H59: ='Data Sheet'!J$56 | I59: ='Data Sheet'!K$56
B60: Net Profit | E60: =E66 | F60: =F66 | G60: =G66 | H60: =H66 | I60: =I66
B61: Average Shareholder's Equity | E61: =E75 | F61: =F75 | G61: =G75 | H61: =H75 | I61: =I75
B62: Return on Equity | E62: =E60/E61 | F62: =F60/F61 | G62: =G60/G61 | H62: =H60/H61 | I62: =I60/I61
B64: ROE - Dupont Analysis
E65: ='Data Sheet'!G$56 | F65: ='Data Sheet'!H$56 | G65: ='Data Sheet'!I$56 | H65: ='Data Sheet'!J$56 | I65: ='Data Sheet'!K$56
B66: Net Profit | E66: ='Data Sheet'!G30 | F66: ='Data Sheet'!H30 | G66: ='Data Sheet'!I30 | H66: ='Data Sheet'!J30 | I66: ='Data Sheet'!K30
B67: Revenue | E67: ='Data Sheet'!G17 | F67: ='Data Sheet'!H17 | G67: ='Data Sheet'!I17 | H67: ='Data Sheet'!J17 | I67: ='Data Sheet'!K17
B68: Net Profit Margin (A) | E68: =E66/E67 | F68: =F66/F67 | G68: =G66/G67 | H68: =H66/H67 | I68: =I66/I67
B70: Revenue | E70: =E67 | F70: =F67 | G70: =G67 | H70: =H67 | I70: =I67
B71: Average Total Assets | E71: =SUM('Data Sheet'!F66:G66)/2 | F71: =SUM('Data Sheet'!G66:H66)/2 | G71: =SUM('Data Sheet'!H66:I66)/2 | H71: =SUM('Data Sheet'!I66:J66)/2 | I71: =SUM('Data Sheet'!J66:K66)/2
B72: Asset Turnover Ratio (B) | E72: =E70/E71 | F72: =F70/F71 | G72: =G70/G71 | H72: =H70/H71 | I72: =I70/I71
B74: Average Total Assets | E74: =E71 | F74: =F71 | G74: =G71 | H74: =H71 | I74: =I71
B75: Average Shareholder's Equity | E75: =(SUM('Data Sheet'!F57:F58)+SUM('Data Sheet'!G57:G58))/2 | F75: =(SUM('Data Sheet'!G57:G58)+SUM('Data Sheet'!H57:H58))/2 | G75: =(SUM('Data Sheet'!H57:H58)+SUM('Data Sheet'!I57:I58))/2 | H75: =(SUM('Data Sheet'!I57:I58)+SUM('Data Sheet'!J57:J58))/2 | I75: =(SUM('Data Sheet'!J57:J58)+SUM('Data Sheet'!K57:K58))/2
B76: Equity Multiplier (C) | E76: =E74/E75 | F76: =F74/F75 | G76: =G74/G75 | H76: =H74/H75 | I76: =I74/I75
B78: Return on Equity(A*B*C) | E78: =E68*E72*E76 | F78: =F68*F72*F76 | G78: =G68*G72*G76 | H78: =H68*H72*H76 | I78: =I68*I72*I76
B80: Return on Assets
E81: ='Data Sheet'!G$56 | F81: ='Data Sheet'!H$56 | G81: ='Data Sheet'!I$56 | H81: ='Data Sheet'!J$56 | I81: ='Data Sheet'!K$56
B82: Net Profit | E82: =E66 | F82: =F66 | G82: =G66 | H82: =H66 | I82: =I66
B83: Average Total Assets | E83: =E74 | F83: =F74 | G83: =G74 | H83: =H74 | I83: =I74
B84: Return on Assets | E84: =E82/E83 | F84: =F82/F83 | G84: =G82/G83 | H84: =H82/H83 | I84: =I82/I83
B86: ROA - Dupont Equation
E87: ='Data Sheet'!G$56 | F87: ='Data Sheet'!H$56 | G87: ='Data Sheet'!I$56 | H87: ='Data Sheet'!J$56 | I87: ='Data Sheet'!K$56
B88: Net Profit | E88: =E66 | F88: =F66 | G88: =G66 | H88: =H66 | I88: =I66
B89: Revenue | E89: =E67 | F89: =F67 | G89: =G67 | H89: =H67 | I89: =I67
B90: Net Profit Margin (A) | E90: =E68 | F90: =F68 | G90: =G68 | H90: =H68 | I90: =I68
B92: Revenue | E92: =E67 | F92: =F67 | G92: =G67 | H92: =H67 | I92: =I67
B93: Average Total Assets | E93: =E71 | F93: =F71 | G93: =G71 | H93: =H71 | I93: =I71
B94: Asset Turnover Ratio (B) | E94: =E72 | F94: =F72 | G94: =G72 | H94: =H72 | I94: =I72
B96: Return on Assets (A*B) | E96: =E90*E94 | F96: =F90*F94 | G96: =G90*G94 | H96: =H90*H94 | I96: =I90*I94

Sheet Altman's Z Score
B2: ='Data Sheet'!B1
B3: =CONCATENATE("(",VLOOKUP(B2,'List of Stocks'!B2:E5442,3,FALSE)," | ","BSE Code: ",VLOOKUP('Altman''s Z Score'!B2,'List of Stocks'!B2:E5442,2,FALSE))
B4: =CONCATENATE(" ","INR "&'Data Sheet'!B8)
B5: 52 Week (High - INR - 427.00 & low INR - 275.00)
B6: About the Company
B8: ITC Limited is an Indian conglomerate, headquartered in Kolkata.It has a presence across six business segments, namely FMCG, agribusiness, information technology, paper products, and packaging. It generates a plurality of its revenue from tobacco products.In terms of market capitalization, ITC is the second-largest FMCG company in India and the third-largest tobacco company in the world
B14: Financial Summary
B34: Recent Updates
A36: • | B36: This move immediately scales up ITC's pulp, writing, and printing paper capacities to target India's booming FMCG, pharma, and e-commerce packaging sectors
A38: • | B38: While cigarettes lagged, consumer categories like dairy and snacks maintained steady YoY growth. The company is actively chasing a ₹8 lakh crore FMCG market opportunity by 2035 through AI-led infrastructure and strategic acquisitions
A40: • | B40: ITC Infotech will deliver AI-enabled innovation, scaling capabilities inside BAT's new Future Capabilities Centre in India alongside hubs in Poland, Romania, and Malaysia
A42: • | B42: ITC completed the integration of Century Pulp & Paper from Aditya Birla Real Estate.Net Profit Drop: Declined by 27.1% YoY to ₹3,579 crore (estimated at ₹4,368 crore)
A44: • | B44: Despite severe margin pressures in its core tobacco business, the conglomerate continues aggressive expansions across its FMCG, hospitality, paper, and technology segments
A46: • | B46: ITC Limited’s Q1 FY27 net profit plunged 27% year-on-year to approximately ₹3,579 crore, missing street estimates due to sharp cigarette excise duty hikes and geopolitical disruptions.
B53: Altman's Z Score Analysis Calculation
B57: Working Capital /Total assets (A)
E58: ='Data Sheet'!G$56 | F58: ='Data Sheet'!H$56 | G58: ='Data Sheet'!I$56 | H58: ='Data Sheet'!J$56 | I58: ='Data Sheet'!K$56
B59: Working Capital | E59: ='Data Sheet'!G65-'Data Sheet'!G60 | F59: ='Data Sheet'!H65-'Data Sheet'!H60 | G59: ='Data Sheet'!I65-'Data Sheet'!I60 | H59: ='Data Sheet'!J65-'Data Sheet'!J60 | I59: ='Data Sheet'!K65-'Data Sheet'!K60
B60: Total Assets | E60: ='Data Sheet'!G66 | F60: ='Data Sheet'!H66 | G60: ='Data Sheet'!I66 | H60: ='Data Sheet'!J66 | I60: ='Data Sheet'!K66
B61: Working Capital / Total assets (A) | E61: =E59/E60 | F61: =F59/F60 | G61: =G59/G60 | H61: =H59/H60 | I61: =I59/I60
B63: Retained Earnings /Total Assets (B)
E64: ='Data Sheet'!G$56 | F64: ='Data Sheet'!H$56 | G64: ='Data Sheet'!I$56 | H64: ='Data Sheet'!J$56 | I64: ='Data Sheet'!K$56
B65: Retained Earnings | E65: ='Data Sheet'!G58 | F65: ='Data Sheet'!H58 | G65: ='Data Sheet'!I58 | H65: ='Data Sheet'!J58 | I65: ='Data Sheet'!K58
B66: Total Assets | E66: =E60 | F66: =F60 | G66: =G60 | H66: =H60 | I66: =I60
B67: Retained Earnings /Total Assets (B) | E67: =E65/E66 | F67: =F65/F66 | G67: =G65/G66 | H67: =H65/H66 | I67: =I65/I66
B69: EBIT /Total Assets (C)
E70: ='Data Sheet'!G$56 | F70: ='Data Sheet'!H$56 | G70: ='Data Sheet'!I$56 | H70: ='Data Sheet'!J$56 | I70: ='Data Sheet'!K$56
B71: EBIT | E71: ='Intrinsic Valuation'!H47 | F71: ='Intrinsic Valuation'!I47 | G71: ='Intrinsic Valuation'!J47 | H71: ='Intrinsic Valuation'!K47 | I71: ='Intrinsic Valuation'!L47
B72: Total Assets | E72: =E66 | F72: =F66 | G72: =G66 | H72: =H66 | I72: =I66
B73: EBIT /Total Assets (C) | E73: =E71/E72 | F73: =F71/F72 | G73: =G71/G72 | H73: =H71/H72 | I73: =I71/I72
B75: Market Cap /Long Term Liabilities (D)
E76: ='Data Sheet'!G$56 | F76: ='Data Sheet'!H$56 | G76: ='Data Sheet'!I$56 | H76: ='Data Sheet'!J$56 | I76: ='Data Sheet'!K$56
B77: Market Capital | E77: ='Data Sheet'!G90*'Data Sheet'!G93 | F77: ='Data Sheet'!H90*'Data Sheet'!H93 | G77: ='Data Sheet'!I90*'Data Sheet'!I93 | H77: ='Data Sheet'!J90*'Data Sheet'!J93 | I77: ='Data Sheet'!K90*'Data Sheet'!K93
B78: Long Term Liabilities | E78: =SUM('Data Sheet'!G59:G60) | F78: =SUM('Data Sheet'!H59:H60) | G78: =SUM('Data Sheet'!I59:I60) | H78: =SUM('Data Sheet'!J59:J60) | I78: =SUM('Data Sheet'!K59:K60)
B79: Market Cap /Long Term Liabilities (D) | E79: =E77/E78 | F79: =F77/F78 | G79: =G77/G78 | H79: =H77/H78 | I79: =I77/I78
B81: Total Sales /Total Assets (E)
E82: ='Data Sheet'!G$56 | F82: ='Data Sheet'!H$56 | G82: ='Data Sheet'!I$56 | H82: ='Data Sheet'!J$56 | I82: ='Data Sheet'!K$56
B83: Total Sales | E83: ='Data Sheet'!G17 | F83: ='Data Sheet'!H17 | G83: ='Data Sheet'!I17 | H83: ='Data Sheet'!J17 | I83: ='Data Sheet'!K17
B84: Total Assets | E84: =E72 | F84: =F72 | G84: =G72 | H84: =H72 | I84: =I72
B85: Total Sales /Total Assets (E) | E85: =E83/E84 | F85: =F83/F84 | G85: =G83/G84 | H85: =H83/H84 | I85: =I83/I84
B87: Altman's Z Score
E88: ='Data Sheet'!G$56 | F88: ='Data Sheet'!H$56 | G88: ='Data Sheet'!I$56 | H88: ='Data Sheet'!J$56 | I88: ='Data Sheet'!K$56
B89: Final Score | E89: =(1.2*E61)+(1.4*E67)+(3.3*E73)+(0.6*E79)+(E85*1) | F89: =(1.2*F61)+(1.4*F67)+(3.3*F73)+(0.6*F79)+(F85*1) | G89: =(1.2*G61)+(1.4*G67)+(3.3*G73)+(0.6*G79)+(G85*1) | H89: =(1.2*H61)+(1.4*H67)+(3.3*H73)+(0.6*H79)+(H85*1) | I89: =(1.2*I61)+(1.4*I67)+(3.3*I73)+(0.6*I79)+(I85*1)
B90: Financial Stability | E90: =IF(E89<1.81,"Distressed",IF(E89>3,"Strong","Grey Zone")) | F90: =IF(F89<1.81,"Distressed",IF(F89>3,"Strong","Grey Zone")) | G90: =IF(G89<1.81,"Distressed",IF(G89>3,"Strong","Grey Zone")) | H90: =IF(H89<1.81,"Distressed",IF(H89>3,"Strong","Grey Zone")) | I90: =IF(I89<1.81,"Distressed",IF(I89>3,"Strong","Grey Zone"))

Sheet Raw FS
B3: Particulars | C3: 42064 | D3: 42430 | E3: 42795 | F3: 43160 | G3: 43525 | H3: 43891 | I3: 44256 | J3: 44621 | K3: 44986 | L3: 45352 | M3: 45717 | N3: 46082 | S3: 42064 | T3: 42430 | U3: 42795 | V3: 43160 | W3: 43525 | X3: 43891 | Y3: 44256 | Z3: 44621 | AA3: 44986 | AB3: 45352 | AC3: 45717 | AD3: 46082 | AE3: TTM
R4: Sales + | S4: 64465 | T4: 34008 | U4: 36533 | V4: 35924 | W4: 40379 | X4: 43403 | Y4: 39537 | Z4: 69420 | AA4: 127540 | AB4: 96421 | AC4: 97895 | AD4: 100469 | AE4: 111431
B5: Equity Capital | C5: 110 | D5: 110 | E5: 110 | F5: 110 | G5: 110 | H5: 110 | I5: 110 | J5: 110 | K5: 114 | L5: 114 | M5: 115 | N5: 129 | R5: Expenses + | S5: 52015 | T5: 32325 | U5: 34631 | V5: 33886 | W5: 38409 | X5: 41108 | Y5: 37031 | Z5: 65707 | AA5: 118722 | AB5: 85044 | AC5: 83643 | AD5: 86478 | AE5: 95733
B6: Reserves | C6: 25618 | D6: 13268 | E6: 14026 | F6: 14979 | G6: 14646 | H6: 16837 | I6: 17049 | J6: 22147 | K6: 32937 | L6: 38962 | M6: 50199 | N6: 80797 | R6: Operating Profit | S6: 12450 | T6: 1684 | U6: 1902 | V6: 2038 | W6: 1969 | X6: 2294 | Y6: 2506 | Z6: 3714 | AA6: 8818 | AB6: 11377 | AC6: 14252 | AD6: 13991 | AE6: 15698
B7: Borrowings - | C7: 83571 | D7: 19169 | E7: 20846 | F7: 17637 | G7: 11243 | H7: 12419 | I7: 16227 | J7: 41604 | K7: 53200 | L7: 65310 | M7: 91473 | N7: 106622 | R7: OPM % | S7: 19 | T7: 5 | U7: 5 | V7: 6 | W7: 4.9 | X7: 5 | Y7: 6 | Z7: 5 | AA7: 7 | AB7: 12 | AC7: 15 | AD7: 14 | AE7: 14
B8: Long term Borrowings | C8: 55487 | D8: 7009 | E8: 9173 | F8: 4273 | G8: 2992 | H8: 3516 | I8: 9523 | J8: 20803 | K8: 32590 | L8: 43718 | M8: 64601 | N8: 76166 | R8: Other Income + | S8: 792 | T8: 1044 | U8: 749 | V8: 363 | W8: 504 | X8: 872 | Y8: 494 | Z8: 1012 | AA8: 834 | AB8: 1146 | AC8: 6403 | AD8: 11688 | AE8: 9193
B9: Short term Borrowings | C9: 19413 | D9: 11006 | E9: 10680 | F9: 12599 | G9: 6959 | H9: 8137 | I9: 6528 | J9: 20220 | K9: 5730 | L9: 6406 | M9: 11289 | N9: 10536 | R9: Interest | S9: 7056 | T9: 1357 | U9: 1257 | V9: 1250 | W9: 1625 | X9: 1572 | Y9: 1377 | Z9: 2526 | AA9: 3969 | AB9: 4555 | AC9: 5978 | AD9: 6019 | AE9: 7405
B10: Lease Liabilities | C10: 0 | D10: 0 | E10: 0 | F10: 0 | G10: 0 | H10: 0 | I10: 176 | J10: 580 | K10: 14881 | L10: 15186 | M10: 15583 | N10: 19920 | R10: Depreciation | S10: 3522 | T10: 314 | U10: 315 | V10: 664 | W10: 390 | X10: 472 | Y10: 537 | Z10: 1248 | AA10: 2436 | AB10: 3042 | AC10: 4211 | AD10: 6135 | AE10: 6777
B11: Other Borrowings | C11: 8671 | D11: 1154 | E11: 993 | F11: 764 | G11: 1292 | H11: 767 | I11: 0 | J11: 0 | K11: 0 | L11: 0 | M11: 0 | N11: 0 | R11: Profit before tax | S11: 2663 | T11: 1056 | U11: 1079 | V11: 487 | W11: 459 | X11: 1122 | Y11: 1086 | Z11: 952 | AA11: 3247 | AB11: 4926 | AC11: 10466 | AD11: 13525 | AE11: 10709
B12: Other Liabilities - | C12: 21420 | D12: 9132 | E12: 12630 | F12: 23679 | G12: 16537 | H12: 17509 | I12: 18231 | J12: 37726 | K12: 55027 | L12: 56200 | M12: 56056 | N12: 73321 | R12: Tax % | S12: 14 | T12: 7 | U12: 25 | V12: 23 | W12: 32 | X12: 29 | Y12: 31 | Z12: 50 | AA12: 32 | AB12: 33 | AC12: 28 | AD12: 28 | AE12: 65535
B13: Non controlling int | C13: 4102 | D13: 85 | E13: 562 | F13: 778 | G13: 388 | H13: 1263 | I13: 1751 | J13: 4672 | K13: 4839 | L13: 5110 | M13: 6156 | N13: 8252 | R13: Net Profit + | S13: 2298 | T13: 1000 | U13: 925 | V13: 594 | W13: 506 | X13: 1040 | Y13: 1046 | Z13: 788 | AA13: 2422 | AB13: 3335 | AC13: 8005 | AD13: 9951 | AE13: 7513
B14: Trade Payables | C14: 10383 | D14: 5347 | E14: 8555 | F14: 8549 | G14: 12117 | H14: 11999 | I14: 11756 | J14: 17648 | K14: 28547 | L14: 24669 | M14: 21214 | N14: 27370 | S14: 15.81 | T14: 8.21 | U14: 8.02 | V14: 6.15 | W14: 5.82 | X14: 9.24 | Y14: 7.49 | Z14: 6.3 | AA14: 19.3 | AB14: 25.37 | AC14: 55.02 | AD14: 72.31 | AE14: 58.54
B15: Advance from Customers | C15: 713 | D15: 1197 | E15: 1035 | F15: 1275 | G15: 1406 | H15: 1697 | I15: 1353 | J15: 1829 | K15: 0 | L15: 0 | M15: 0 | N15: 0 | S15: 8 | T15: 4 | U15: 4 | V15: 6 | W15: 6 | X15: 10 | Y15: 12 | Z15: 14 | AA15: 6 | AB15: 5 | AC15: 2 | AD15: 2 | AE15: 65535
B16: Other liability items | C16: 6222 | D16: 2503 | E16: 2477 | F16: 13078 | G16: 2626 | H16: 2549 | I16: 3370 | J16: 13577 | K16: 21641 | L16: 26421 | M16: 28686 | N16: 37698
B18: Total Liabilities | C18: 130718 | D18: 41679 | E18: 47611 | F18: 56405 | G18: 42536 | H18: 46875 | I18: 51617 | J18: 101586 | K18: 141278 | L18: 160586 | M18: 197843 | N18: 260868 | S18: 42064 | T18: 42430 | U18: 42795 | V18: 43160 | W18: 43525 | X18: 43891 | Y18: 44256 | Z18: 44621 | AA18: 44986 | AB18: 45352 | AC18: 45717 | AD18: 46082
R19: Cash from Operating Activity - | S19: 8532 | T19: 5112 | U19: 774 | V19: 2942 | W19: 3236 | X19: 2454 | Y19: 4043 | Z19: 1385 | AA19: 17626 | AB19: 10312 | AC19: 4513 | AD19: 2357
R20: Profit from operations | S20: 12601 | T20: 1775 | U20: 2344 | V20: 3462 | W20: 2129 | X20: 3182 | Y20: 2355 | Z20: 4122 | AA20: 9191 | AB20: 12049 | AC20: 15445 | AD20: 15148
B21: Fixed Assets - | C21: 83834 | D21: 10473 | E21: 13668 | F21: 10555 | G21: 9020 | H21: 10476 | I21: 10838 | J21: 30123 | K21: 56881 | L21: 65978 | M21: 77260 | N21: 115174 | R21: Receivables | S21: -5251 | T21: 2818 | U21: -3965 | V21: -532 | W21: -2109 | X21: 455 | Y21: -248 | Z21: -2939 | AA21: -2064 | AB21: 1320 | AC21: -1454 | AD21: -5299
B22: Land | C22: 2808 | D22: 1232 | E22: 1596 | F22: 1633 | G22: 1225 | H22: 1224 | I22: 986 | J22: 1313 | K22: 2731 | L22: 2122 | M22: 2630 | N22: 3087 | R22: Inventory | S22: -165 | T22: -133 | U22: -352 | V22: -713 | W22: -369 | X22: 173 | Y22: 343 | Z22: -5024 | AA22: -130 | AB22: -2569 | AC22: -767 | AD22: -8340
B23: Building | C23: 5392 | D23: 487 | E23: 742 | F23: 1142 | G23: 1059 | H23: 1121 | I23: 1389 | J23: 11481 | K23: 14391 | L23: 18021 | M23: 20081 | N23: 39156 | R23: Payables | S23: 2549 | T23: 81 | U23: 3395 | V23: 288 | W23: 4110 | X23: -870 | Y23: 1985 | Z23: 7188 | AA23: 12806 | AB23: -2846 | AC23: -2955 | AD23: 6335
B24: Plant Machinery | C24: 69255 | D24: 3544 | E24: 6582 | F24: 3253 | G24: 2493 | H24: 3376 | I24: 3821 | J24: 5388 | K24: 9093 | L24: 15270 | M24: 23785 | N24: 32095 | R24: Working capital changes | S24: -3235 | T24: 3568 | U24: -1350 | V24: -270 | W24: 1409 | X24: -461 | Y24: 1800 | Z24: -2532 | AA24: 9345 | AB24: -29 | AC24: -8837 | AD24: -10079
B25: Equipments | C25: 155 | D25: 25 | E25: 38 | F25: 46 | G25: 45 | H25: 48 | I25: 66 | J25: 108 | K25: 182 | L25: 345 | M25: 666 | N25: 1065 | R25: Direct taxes | S25: -834 | T25: -231 | U25: -220 | V25: -250 | W25: -211 | X25: -267 | Y25: -112 | Z25: -205 | AA25: -910 | AB25: -1708 | AC25: -2095 | AD25: -2712
B26: Furniture n fittings | C26: 324 | D26: 92 | E26: 106 | F26: 172 | G26: 171 | H26: 186 | I26: 187 | J26: 565 | K26: 583 | L26: 898 | M26: 1516 | N26: 2146 | R26: Cash from Investing Activity - | S26: -11465 | T26: -1825 | U26: -1460 | V26: -7649 | W26: 2487 | X26: -1082 | Y26: -8611 | Z26: -17041 | AA26: -15459 | AB26: -18767 | AC26: -26417 | AD26: -27680
B27: Railway sidings | C27: 1449 | D27: 74 | E27: 74 | F27: 74 | G27: 0 | H27: 0 | I27: 0 | J27: 0 | K27: 12712 | L27: 13980 | M27: 13383 | N27: 16579 | R27: Fixed assets purchased | S27: -9557 | T27: -5920 | U27: -4167 | V27: -7305 | W27: -1772 | X27: -2901 | Y27: -4139 | Z27: -11647 | AA27: -14725 | AB27: -22366 | AC27: -29879 | AD27: -33369
B28: Vehicles | C28: 477 | D28: 25 | E28: 29 | F28: 35 | G28: 44 | H28: 54 | I28: 68 | J28: 436 | K28: 498 | L28: 554 | M28: 658 | N28: 908 | R28: Fixed assets sold | S28: 405 | T28: 30 | U28: 20 | V28: 11 | W28: 7 | X28: 180 | Y28: 780 | Z28: 2 | AA28: 70 | AB28: 120 | AC28: 364 | AD28: 19
B29: Intangible Assets | C29: 2130 | D29: 80 | E29: 80 | F29: 80 | G29: 54 | H29: 139 | I29: 152 | J29: 301 | K29: 887 | L29: 1040 | M29: 1086 | N29: 899 | R29: Investments purchased | S29: -401 | T29: 8 | U29: -52 | V29: 0 | W29: 0 | X29: -40 | Y29: 0 | Z29: -32 | AA29: -260 | AB29: -1191 | AC29: -1347 | AD29: -1489
B30: Other fixed assets | C30: 11411 | D30: 3527 | E30: 3518 | F30: 3569 | G30: 3380 | H30: 4114 | I30: 5324 | J30: 12909 | K30: 19939 | L30: 20792 | M30: 24605 | N30: 35591 | R30: Investments sold | S30: 0 | T30: 0 | U30: 0 | V30: 6 | W30: 243 | X30: 0 | Y30: 222 | Z30: 89 | AA30: 28 | AB30: 159 | AC30: 4751 | AD30: 10799
B31: Gross Block | C31: 96486 | D31: 10813 | E31: 14634 | F31: 11907 | G31: 10482 | H31: 12442 | I31: 13035 | J31: 33692 | K31: 62378 | L31: 74560 | M31: 89964 | N31: 134265 | R31: Interest received | S31: 872 | T31: 754 | U31: 651 | V31: 547 | W31: 476 | X31: 459 | Y31: 322 | Z31: 821 | AA31: 608 | AB31: 1127 | AC31: 1184 | AD31: 1042
B32: Accumulated Depreciation | C32: 12652 | D32: 339 | E32: 966 | F32: 1352 | G32: 1462 | H32: 1965 | I32: 2197 | J32: 3570 | K32: 5497 | L32: 8582 | M32: 12703 | N32: 19091 | R32: Dividends received | S32: 15 | T32: 177 | U32: 4 | V32: 4 | W32: 3 | X32: 0 | Y32: 0 | Z32: 0 | AA32: 0 | AB32: 11 | AC32: 0 | AD32: 0
B33: Net Block | C33: 83834 | D33: 10473 | E33: 13668 | F33: 10555 | G33: 9020 | H33: 10476 | I33: 10838 | J33: 30123 | K33: 56881 | L33: 65978 | M33: 77260 | N33: 115174 | R33: Invest in subsidiaries | S33: 0 | T33: -8 | U33: 0 | V33: 0 | W33: 0 | X33: 0 | Y33: 0 | Z33: 0 | AA33: 0 | AB33: 0 | AC33: 0 | AD33: 0
R34: Investment in group cos | S34: -558 | T34: 3173 | U34: 2157 | V34: -832 | W34: 2584 | X34: 1474 | Y34: -2308 | Z34: -4426 | AA34: 1105 | AB34: 4458 | AC34: -208 | AD34: -1708
B35: CWIP | C35: 6733 | D35: 7705 | E35: 7731 | F35: 5526 | G35: 5765 | H35: 7347 | I35: 8825 | J35: 23544 | K35: 24025 | L35: 35180 | M35: 51516 | N35: 51753 | R35: Redemp n Canc of Shares | S35: 0 | T35: 0 | U35: 129 | V35: 18 | W35: 18 | X35: 0 | Y35: 0 | Z35: 0 | AA35: 56 | AB35: 0 | AC35: 0 | AD35: 0
B36: Investments | C36: 744 | D36: 805 | E36: 1042 | F36: 1461 | G36: 1511 | H36: 1952 | I36: 5503 | J36: 4292 | K36: 6310 | L36: 8701 | M36: 9887 | N36: 9428 | R36: Other investing items | S36: 3445 | T36: -3448 | U36: 716 | V36: 5120 | W36: -6158 | X36: -221 | Y36: 3109 | Z36: 15901 | AA36: -1198 | AB36: 8879 | AC36: 22655 | AD36: 28484
R37: Cash from Financing Activity - | S37: 0 | T37: 0 | U37: 0 | V37: 0 | W37: 0 | X37: 0 | Y37: 0 | Z37: 0 | AA37: 7700 | AB37: 0 | AC37: 4168 | AD37: 24854
B38: Other Assets - | C38: 39407 | D38: 22696 | E38: 25170 | F38: 38864 | G38: 26240 | H38: 27099 | I38: 26451 | J38: 43627 | K38: 54062 | L38: 50728 | M38: 59180 | N38: 84513 | R38: Proceeds from shares | S38: 30297 | T38: 4772 | U38: 4266 | V38: 15069 | W38: 3031 | X38: 4435 | Y38: 7520 | Z38: 18364 | AA38: 30339 | AB38: 22522 | AC38: 34819 | AD38: 40870
B39: Inventories | C39: 4082 | D39: 1300 | E39: 1652 | F39: 2343 | G39: 2669 | H39: 2562 | I39: 1757 | J39: 6788 | K39: 6918 | L39: 9487 | M39: 10287 | N39: 18713 | R39: Proceeds from borrowings | S39: -18760 | T39: -6518 | U39: -2547 | V39: -8484 | W39: -7636 | X39: -3255 | Y39: -3047 | Z39: -270 | AA39: -34403 | AB39: -10717 | AC39: -9910 | AD39: -33623
B40: Trade receivables + | C40: 15319 | D40: 10187 | E40: 12742 | F40: 12099 | G40: 14307 | H40: 13147 | I40: 11983 | J40: 13712 | K40: 12553 | L40: 9793 | M40: 9616 | N40: 12543 | R40: Repayment of borrowings | S40: -7941 | T40: -1494 | U40: -1581 | V40: -1726 | W40: -1606 | X40: -1532 | Y40: -1212 | Z40: -2601 | AA40: -3342 | AB40: -4055 | AC40: -5599 | AD40: -5102
B41: Cash Equivalents | C41: 3651 | D41: 1540 | E41: 1715 | F41: 1884 | G41: 1709 | H41: 3377 | I41: 1811 | J41: 3916 | K41: 5374 | L41: 7068 | M41: 6962 | N41: 11809 | R41: Interest paid fin | S41: -146 | T41: -208 | U41: 0 | V41: -53 | W41: -53 | X41: -186 | Y41: 0 | Z41: -110 | AA41: -114 | AB41: -137 | AC41: -148 | AD41: -640
B42: Loans n Advances | C42: 290 | D42: 62 | E42: 4027 | F42: 4256 | G42: 2332 | H42: 2093 | I42: 1509 | J42: 1740 | K42: 4931 | L42: 1683 | M42: 1755 | N42: 2190 | R42: Dividends paid | S42: -4876 | T42: -5133 | U42: -6994 | V42: -5952 | W42: -6519 | X42: -7302 | Y42: -18881 | Z42: -13788 | AA42: -15418 | AB42: -19899 | AC42: -17782 | AD42: -18271
B43: Other asset items | C43: 16065 | D43: 9607 | E43: 5034 | F43: 18282 | G43: 5222 | H43: 5921 | I43: 9392 | J43: 17470 | K43: 24286 | L43: 22696 | M43: 30559 | N43: 39258 | R43: Financial liabilities | S43: 0 | T43: 0 | U43: 0 | V43: 0 | W43: 0 | X43: -49 | Y43: -55 | Z43: -59 | AA43: -59 | AB43: -67 | AC43: -66 | AD43: -68
B44: Total Assets | C44: 130718 | D44: 41679 | E44: 47611 | F44: 56405 | G44: 42536 | H44: 46875 | I44: 51617 | J44: 101586 | K44: 141278 | L44: 160586 | M44: 197843 | N44: 260868 | R44: Other financing items | S44: -734 | T44: -971 | U44: -1335 | V44: -1136 | W44: -1203 | X44: -1409 | Y44: 55 | Z44: 15 | AA44: 35 | AB44: 12 | AC44: 28 | AD44: -146
R45: Net Cash Flow | S45: 512 | T45: -161 | U45: 30 | V45: 413 | W45: -436 | X45: 1151 | Y45: -1459 | Z45: 246 | AA45: 970 | AB45: 424 | AC45: 751 | AD45: 3161 | AT45: Interest paid fin | AU45: -18 | AV45: -2 | AW45: -14 | AX45: -6 | AY45: -7 | AZ45: -90 | BA45: -92 | BB45: -82 | BC45: -88 | BD45: -110 | BE45: -130 | BF45: -133
AT46: Dividends paid | AU46: -2912 | AV46: -3354 | AW46: -3572 | AX46: -3911 | AY46: -4554 | AZ46: -5196 | BA46: -8811 | BB46: -7526 | BC46: -8474 | BD46: -9416 | BE46: -12473 | BF46: -10124
AT47: Financial liabilities | AU47: 0 | AV47: 0 | AW47: 0 | AX47: 0 | AY47: 0 | AZ47: -373 | BA47: -406 | BB47: -407 | BC47: -467 | BD47: -423 | BE47: -498 | BF47: -507
AT48: Other financing items | AU48: -533 | AV48: -685 | AW48: -728 | AX48: -781 | AY48: -928 | AZ48: -1061 | BA48: 0 | BB48: 0 | BC48: -2 | BD48: 0 | BE48: 0 | BF48: 0
AT49: Net Cash Flow | AU49: -33 | AV49: 25 | AW49: -202 | AX49: 21 | AY49: -28 | AZ49: 2595 | BA49: -1374 | BB49: -695 | BC49: -446 | BD49: 111 | BE49: 5258 | BF49: -3487
AR55: Mar Cap Rs.Cr. | AS55: Net Debt | AT55: EV Rs.Cr. | AU55: Sales Rs.Cr. | AV55: EBITDA | AW55: NP 12M Rs.Cr. | AX55: EV / EBITDA | AZ55: Debt Rs.Cr. | BA55: Cash End Rs.Cr.
K56: S.No. | L56: Adani Enterprises Ltd | M56: 2999 | N56: 135.19273 | AR56: 405442.61 | AS56: =AZ56-BA56 | AT56: =AR56+AS56 | AU56: 131695.92 | AV56: =AT56/AX56 | AW56: 14971 | AX56: 5.8 | AZ56: 106622 | BA56: 21128.25
K57: 1 | L57: Adani Enterp. | M57: 2999.1 | N57: 135.19 | AR57: 357.27 | AS57: =AZ57-BA57 | AT57: =AR57+AS57 | AU57: 80.68 | AV57: =AT57/AX57 | AW57: 1.56 | AX57: 7.05 | AZ57: 2399.06 | BA57: 3008.79
K58: 2 | L58: Starlineps Enter | M58: 8.29 | N58: 43.1 | AR58: 10.27 | AS58: =AZ58-BA58 | AT58: =AR58+AS58 | AU58: 1.2 | AV58: =AT58/AX58 | AW58: 1.44 | AX58: 0.19 | AZ58: 444.16 | BA58: 1340.87
K59: 3 | L59: Rajdarshan Inds | M59: 33.02 | N59: 0.31 | AR59: 202899.94 | AS59: =AZ59-BA59 | AT59: =AR59+AS59 | AU59: 65888.32 | AV59: =AT59/AX59 | AW59: 3409.28 | AX59: 6.42 | AZ59: 2508.18 | BA59: 1998.49
K60: 4 | L60: Median: 2 Co. | M60: 1503.69 | N60: 134.93 | AR60: 135577.79 | AS60: =AZ60-BA60 | AT60: 136605.63 | AU60: 19529.34 | AV60: =AT60/AX60 | AW60: 2610.26 | AX60: 35.68 | AZ60: 1380.28 | BA60: 352.44
K61: 5 | L61: Britannia Inds. | M61: 5617.2 | N61: 24.09 | AR61: 111986.06 | AS61: =AZ61-BA61 | AT61: 112050.06 | AU61: 14277 | AV61: =AT61/AX61 | AW61: 1952 | AX61: 41.69 | AZ61: 557 | BA61: 493
K62: 6 | L62: Marico | M62: 864 | N62: 129.84 | AR62: 111137.21 | AS62: =AZ62-BA62 | AT62: 109573.21 | AU62: 12626 | AV62: =AT62/AX62 | AW62: 1884 | AX62: 39.29 | AZ62: 413 | BA62: 1977
K63: 7 | L63: United Spirits | M63: 1535 | N63: 72.74 | AR63: 108322.98 | AS63: =AZ63-BA63 | AT63: 107722 | AU63: 20860.4 | AV63: =AT63/AX63 | AW63: 1642.24 | AX63: 34.7 | AZ63: 2819.51 | BA63: 3420.49
K64: 8 | L64: Tata Consumer | M64: 1087.9 | N64: 98.97 | AR64: 103910.9 | AS64: =AZ64-BA64 | AT64: 107326.01 | AU64: 15948.95 | AV64: =AT64/AX64 | AW64: 1913.54 | AX64: 30.69 | AZ64: 4420.52 | BA64: 1005.41
K65: 9 | L65: Godrej Consumer | M65: 1018 | N65: 102.33 | AR65: 72767.19 | AS65: =AZ65-BA65 | AT65: 73492.44 | AU65: 13552.38 | AV65: =AT65/AX65 | AW65: 1946.56 | AX65: 23.32 | AZ65: 1287.32 | BA65: 562.07
K66: 10 | L66: Dabur India | M66: 410 | N66: 177.4

Sheet List of Stocks
B2: COMPANY_NAME | C2: BSE | D2: NSE | E2: Industry
B3: 20 MICRONS LTD | C3: 533022 | D3: 20MICRONS | E3: Mining
B4: 21ST CENTURY MANAGEMENT SERVICES LTD | C4: 526921 | D4: 21STCENMGM | E4: Other Financial Services
B5: 3I INFOTECH LTD | C5: 532628 | D5: 3IINFOTECH | E5: IT Consulting & Software
B6: 3M (INDIA) LTD | C6: 523395 | D6: 3M(INDIA) | E6: Diversified
B7: 3M INDIA LTD | C7: 523395 | D7: 3MINDIA | E7: Diversified
B8: 3P LAND HOLDINGS LTD | C8: 516092 | D8: 3PLAND | E8: Paper & Paper Products
B9: 5PAISA CAPITAL LTD | C9: 540776 | D9: 5PAISA | E9: Other Financial Services
B10: 63 MOONS TECHNOLOGIES LTD | C10: 526881 | D10: 63MOONS | E10: IT Consulting & Software
B11: 7NR RETAIL LTD | C11: 540615 | D11: Not Listed | E11: Specialty Retail
B12: 7SEAS ENTERTAINMENT LTD | C12: 540874 | D12: Not Listed | E12: Movies & Entertainment
B13: 8K MILES SOFTWARE SERVICES LTD | C13: 512161 | D13: 8KMILES | E13: Internet Software & Services
B14: A & M FEBCON LTD | C14: 540697 | D14: Not Listed | E14: Industrial Machinery
B15: A AND M JUMBO BAGS LTD | C15: Not Listed | D15: AMJUMBO | E15: SME
B16: A INFRASTRUCTURE LTD | C16: 539620 | D16: Not Listed | E16: Cement & Cement Products
B17: A K SPINTEX LTD | C17: 539300 | D17: Not Listed | E17: Textiles
B18: A K CAPITAL SERVICES LTD | C18: 530499 | D18: Not Listed | E18: Finance (including NBFCs)
B19: A.F. Enterprises Ltd | C19: 538351 | D19: AFEL | E19: Investment Companies
B20: A-1 ACID LTD | C20: 542012 | D20: Not Listed | E20: Comm.Trading & Distribution
B21: A2Z INFRA ENGINEERING LTD | C21: 533292 | D21: A2ZINFRA | E21: Utilities:Non-Elec.
B22: AADHAAR VENTURES (INDIA) LTD | C22: 531611 | D22: Not Listed | E22: Finance (including NBFCs)
B23: AADHAAR VENTURES INDIA LTD | C23: 531611 | D23: Not Listed | E23: Finance (including NBFCs)
B24: AAKASH EXPLORATION SERVICES LTD | C24: Not Listed | D24: AAKASH | E24: SME
B25: AANANDA LAKSHMI SPINNING MILLS LTD | C25: 539096 | D25: Not Listed | E25: Textiles
B26: AANCHAL ISPAT LTD | C26: 538812 | D26: Not Listed | E26: Iron & Steel/Interm.Products
B27: AAR COMMERCIAL COMPANY LTD | C27: 539632 | D27: Not Listed | E27: Distributors
B28: Aar Shyam India Investment Company Ltd | C28: 542377 | D28: AARSHYAM | E28: Finance (including NBFCs)
B29: AAREY DRUGS & PHARMACEUTICALS LTD | C29: 524412 | D29: Not Listed | E29: Pharmaceuticals
B30: AARON INDUSTRIES LTD | C30: Not Listed | D30: AARON | E30: SME
B31: Aartech Solonics Ltd | C31: 542580 | D31: AARTECH | E31: Heavy Electrical Equipment
B32: AARTI DRUGS LTD | C32: 524348 | D32: AARTIDRUGS | E32: Pharmaceuticals
B33: AARTI INDUSTRIES LTD | C33: 524208 | D33: AARTIIND | E33: Commodity Chemicals
B34: AARV INFRATEL LTD | C34: 526488 | D34: Not Listed | E34: Textiles
B35: AARVEE DENIMS & EXPORTS LTD | C35: 514274 | D35: AARVEEDEN | E35: Textiles
B36: AARVI ENCON LTD | C36: Not Listed | D36: AARVI | E36: SME
B37: AASHEE INFOTECH LTD | C37: 519319 | D37: Not Listed | E37: Internet Software & Services
B38: AASWA TRADING & EXPORTS LTD | C38: 512038 | D38: Not Listed | E38: Comm.Trading & Distribution
B39: AAVAS FINANCIERS LTD | C39: 541988 | D39: AAVAS | E39: Housing Finance
B40: AAYUSH FOOD AND HERBS LTD | C40: 539528 | D40: Not Listed | E40: Packaged Foods
B41: ABAN OFFSHORE LTD | C41: 523204 | D41: ABAN | E41: Exploration & Production
B42: ABANS ENTERPRISES LTD | C42: 512165 | D42: Not Listed | E42: Comm.Trading & Distribution
B43: ABB INDIA LTD | C43: 500002 | D43: ABB | E43: Heavy Electrical Equipment
B44: ABBOTT (INDIA) LTD | C44: 500488 | D44: ABBOT(INDIA) | E44: Pharmaceuticals
B45: ABBOTT INDIA LTD | C45: 500488 | D45: ABBOTINDIA | E45: Pharmaceuticals
B46: ABC (INDIA) LTD | C46: 520123 | D46: Not Listed | E46: Surface Transportation
B47: ABC GAS INTERNATIONAL LTD | C47: 513119 | D47: Not Listed | E47: Copper
B48: ABC INDIA LTD | C48: 520123 | D48: Not Listed | E48: Surface Transportation
... B56: ABIRAMI FINANCIAL SERVICES INDIA LTD | C56: 511756 | D56: Not Listed | E56: Finance (including NBFCs)
B57: ABM INTERNATIONAL LTD | C57: Not Listed | D57: ABMINTLTD | E57: Others
B58: ABM KNOWLEDGEWARE LTD | C58: 531161 | D58: Not Listed | E58: IT Software Products
B59: ACC LTD | C59: 500410 | D59: ACC | E59: Cement & Cement Products
B60: ACCEL LTD | C60: 517494 | D60: Not Listed | E60: Storage Media & Peripherals
B61: ACCELYA KALE SOLUTIONS LTD | C61: 532268 | D61: ACCELYA | E61: IT Consulting & Software
B62: ACCORD SYNERGY LTD | C62: Not Listed | D62: ACCORD | E62: SME
B63: ACCURACY SHIPPING LTD | C63: Not Listed | D63: ACCURACY | E63: SME
B64: ACE EDUTREND LTD | C64: 530093 | D64: Not Listed | E64: Education
B65: ACE INTEGRATED SOLUTIONS LTD | C65: Not Listed | D65: ACEINTEG | E65: SME
B66: ACE MEN ENGG WORKS LTD | C66: 539661 | D66: Not Listed | E66: Distributors
B67: ACE SOFTWARE EXPORTS LTD | C67: 531525 | D67: Not Listed | E67: IT Software Products
B68: Achal Investments Ltd | C68: 538570 | D68: ACHAL | E68: Other Financial Services
B69: ACI INFOCOM LTD | C69: 517356 | D69: Not Listed | E69: Storage Media & Peripherals
B70: ACKNIT INDUSTRIES LTD | C70: 530043 | D70: Not Listed | E70: Other Apparels & Accessories
B71: ACME RESOURCES LTD | C71: 539391 | D71: Not Listed | E71: Finance (including NBFCs)
B72: ACROW INDIA LTD. | C72: 513149 | D72: ACROW | E72: Iron &amp; Steel Products
B73: ACRYSIL LTD | C73: 524091 | D73: Not Listed | E73: Plastic Products
B74: ACTION CONSTRUCTION EQUIPMENT LTD | C74: 532762 | D74: ACE | E74: Transport Related Services
B75: ACTION FINANCIAL SERVICES (INDIA) LTD | C75: 511706 | D75: Not Listed | E75: Other Financial Services
B76: ACTION FINANCIAL SERVICES INDIA LTD | C76: 511706 | D76: Not Listed | E76: Other Financial Services
B77: ACTIVE CLOTHING CO LTD | C77: 541144 | D77: Not Listed | E77: Other Apparels & Accessories
... B135: AGRI-TECH INDIA LTD | C135: 537292 | D135: AGRITECH | E135: Other Agricultural Products
B136: AGRO PHOS (INDIA) LTD | C136: Not Listed | D136: AGROPHOS | E136: SME
B137: AGRO PHOS INDIA LTD | C137: Not Listed | D137: AGROPHOS | E137: SME
B138: AGRO TECH FOODS LTD | C138: 500215 | D138: ATFL | E138: Other Agricultural Products
B139: AHIMSA INDUSTRIES LTD | C139: Not Listed | D139: AHIMSA | E139: SME
B140: AHLADA ENGINEERS LTD | C140: Not Listed | D140: AHLADA | E140: SME
B141: AHLUWALIA CONTRACTS (INDIA) LTD | C141: 532811 | D141: AHLUCONT | E141: Realty
B142: AHLUWALIA CONTRACTS INDIA LTD | C142: 532811 | D142: AHLUCONT | E142: Realty
B143: AHMEDABAD STEELCRAFT LTD | C143: 522273 | D143: Not Listed | E143: Iron & Steel/Interm.Products
B144: AI CHAMPDANY INDUSTRIES LTD | C144: 532806 | D144: Not Listed | E144: Jute & Jute Products
B145: AIA ENGINEERING LTD | C145: 532683 | D145: AIAENG | E145: Other Industrial Goods
B146: AIMCO PESTICIDES LTD | C146: 524288 | D146: Not Listed | E146: Agrochemicals
B147: AIRAN LTD | C147: Not Listed | D147: AIRAN | E147: SME
B148: AIRO LAM LTD | C148: Not Listed | D148: AIROLAM | E148: SME
B149: AISHWARYA TELECOM LTD | C149: 532975 | D149: Not Listed | E149: Telecom Equipment
B150: AJANTA PHARMA LTD | C150: 532331 | D150: AJANTPHARM | E150: Pharmaceuticals
B151: AJANTA SOYA LTD | C151: 519216 | D151: Not Listed | E151: Edible Oils
B152: AJCON GLOBAL SERVICES LTD | C152: 511692 | D152: Not Listed | E152: Other Financial Services
B153: AJEL LTD | C153: 530713 | D153: Not Listed | E153: IT Consulting & Software
B154: AJMERA REALTY & INFRA (INDIA) LTD | C154: 513349 | D154: AJMERA | E154: Realty
B155: AJMERA REALTY & INFRA INDIA LTD | C155: 513349 | D155: AJMERA | E155: Realty
B156: AJOONI BIOTECH LTD | C156: Not Listed | D156: AJOONI | E156: SME
B157: AJWA FUN WORLD & RESORT LTD | C157: 526628 | D157: Not Listed | E157: Other Leisure Facilities
B158: AKAR AUTO INDUSTRIES LTD | C158: 530621 | D158: Not Listed | E158: Industrial Machinery
B159: AKASH INFRA PROJECTS LTD | C159: Not Listed | D159: AKASH | E159: SME
B160: AKASHDEEP METAL INDUSTRIES LTD | C160: 538778 | D160: Not Listed | E160: Finance (including NBFCs)
B161: AKG EXIM LTD | C161: Not Listed | D161: AKG | E161: SME
B162: AKI (INDIA) LTD | C162: 542020 | D162: Not Listed | E162: Other Apparels & Accessories
B163: AKI INDIA LTD | C163: 542020 | D163: Not Listed | E163: Other Apparels & Accessories
B164: AKM LACE AND EMBROTEX LTD | C164: 540718 | D164: Not Listed | E164: Textiles
B165: AKME STAR HOUSING FINANCE LTD | C165: 539017 | D165: Not Listed | E165: Housing Finance
...
