Workbook
Name UPDATE: '[1]Data Sheet'!$E$1
Name UPDATE: 'Data Sheet'!$E$1

Sheet AI Valuation Summary
A1: BRITANNIA INDUSTRIES LTD (BRITANNIA) - Institutional Valuation
A4: Current Price | B4: Intrinsic Value | C4: Margin of Safety | D4: Verdict | E4: WACC | F4: Altman Z-Score | G4: DuPont ROE
A5: =DCF!D45 -> 4929 | B5: =DCF!D43 -> 1159.8694 | C5: =(B5-A5)/A5 -> -0.76468463 | D5: =IF(C5>0.15,"UNDERVALUED / BUY",IF(C5<-0.15,"OVERVALUED / SELL","FAIRLY VALUED / HOLD")) -> OVERVALUED / SELL | E5: =DCF!D20 -> 0.10941053 | F5: ='Altman''s Z Score'!I89 -> 22.548975 | G5: ='Dupont Analysis'!I78 -> 0.53625026
B7: KEY VALUATION PARAMETERS & LIVE MODEL INPUTS
B8: Discount Rate (WACC) | C8: =WACC!K46 -> 0.10941053 | D8: 0
B9: Cost of Equity (Ke) | C9: =WACC!K29 -> 0.10941053 | D9: 0
B10: Risk-Free Rate (Rf) | C10: =WACC!K26 -> 0.07 | D10: 0
B11: Equity Risk Premium (ERP) | C11: =WACC!K27 -> 0.065 | D11: 0
B12: Levered Beta | C12: =WACC!K28 -> 0.60631585 | D12: 0
B13: Terminal Growth Rate | C13: =DCF!D19 -> 0.04 | D13: 0
B14: Post-Tax Cost of Debt (Kd) | C14: =WACC!K43 -> 0.060375 | D14: 0
B15: Cash & Liquid Investments | C15: ='Data Sheet'!K69 -> 352 | D15: #,##0.00
B16: Total Debt & Borrowings | C16: ='Data Sheet'!K59 -> 1380 | D16: #,##0.00
B17: Shares Outstanding | C17: ='Data Sheet'!K70/10000000 -> 24 | D17: #,##0.00
B18: Sector Median EV/Revenue | C18: =Comp_Valuation!O25 -> 6.4757407 | D18: 0.00"x"
B19: Sector Median EV/EBITDA | C19: =Comp_Valuation!P25 -> 34.440046 | D19: 0.00"x"
A20: 5-Year Discounted Cash Flow (DCF) Schedule (Amounts in ₹ Cr) | B20: Sector Median P/E | C20: =Comp_Valuation!Q25 -> 19.999824 | D20: 0.00"x"
A21: Year | B21: EBIT | C21: NOPAT | D21: Reinvest Rate | E21: FCFF | F21: Discount Factor | G21: PV of FCFF
A22: Year 1 | B22: =DCF!I8 -> 3578.904 | C22: =DCF!I10 -> 2684.178 | D22: =DCF!I11 -> 0.031805628 | E22: =DCF!I12 -> 2598.806 | F22: =DCF!I14 -> 0.94941012 | G22: =DCF!I16 -> 2467.3328
A23: Year 2 | B23: =DCF!J8 -> 3765.007 | C23: =DCF!J10 -> 2823.7553 | D23: =DCF!J11 -> 0.1152531 | E23: =DCF!J12 -> 2498.3087 | F23: =DCF!J14 -> 0.8557789 | G23: =DCF!J16 -> 2137.9999
A24: Year 3 | B24: =DCF!K8 -> 3960.7874 | C24: =DCF!K10 -> 2970.5905 | D24: =DCF!K11 -> 0.19870057 | E24: =DCF!K12 -> 2380.3325 | F24: =DCF!K14 -> 0.77138163 | G24: =DCF!K16 -> 1836.1447
A25: Year 4 | B25: =DCF!L8 -> 4166.7483 | C25: =DCF!L10 -> 3125.0612 | D25: =DCF!L11 -> 0.28214805 | E25: =DCF!L12 -> 2243.3313 | F25: =DCF!L14 -> 0.69530765 | G25: =DCF!L16 -> 1559.8054
A26: Year 5 | B26: =DCF!M8 -> 4383.4192 | C26: =DCF!M10 -> 3287.5644 | D26: =DCF!M11 -> 0.36559552 | E26: =DCF!M12 -> 2085.6456 | F26: =DCF!M14 -> 0.62673612 | G26: =DCF!M16 -> 1307.1494
B28: Enterprise to Equity Value Bridge
B29: PV of 5-Year FCFFs | C29: =DCF!D33 -> 9308.4322 | D29: ₹ Cr
B30: Terminal Value | C30: =DCF!D29 -> 31249.89 | D30: ₹ Cr
B31: PV of Terminal Value | C31: =DCF!D34 -> 19585.434 | D31: ₹ Cr
B32: Enterprise Value (Operating Assets) | C32: =DCF!D35 -> 28893.867 | D32: ₹ Cr
B33: Add: Estimated Cash & Liquid Assets | C33: =DCF!D37 -> 352 | D33: ₹ Cr
B34: Less: Total Debt & Borrowings | C34: =DCF!D38 -> 1380 | D34: ₹ Cr
B35: Less: Minority Interest | C35: =DCF!D39 -> 29 | D35: ₹ Cr
B36: Net Equity Value | C36: =DCF!D40 -> 27836.867 | D36: ₹ Cr
B37: Shares Outstanding | C37: =DCF!D41 -> 24 | D37: Cr shares
B38: Intrinsic Value per Share | C38: =DCF!D43 -> 1159.8694 | D38: ₹
B39: Current Market Price | C39: =DCF!D45 -> 4929 | D39: ₹
B40: Margin of Safety / Discount | C40: =(C38-C39)/C39 -> -0.76468463 | D40: %

Sheet Profit & Loss
A1: ='Data Sheet'!B1 -> BRITANNIA INDUSTRIES LTD | H1: =UPDATE | M1: SCREENER.IN
A3: Narration | B3: ='Data Sheet'!B16 -> 42795 | C3: ='Data Sheet'!C16 -> 43160 | D3: ='Data Sheet'!D16 -> 43525 | E3: ='Data Sheet'!E16 -> 43891 | F3: ='Data Sheet'!F16 -> 44256 | G3: ='Data Sheet'!G16 -> 44621 | H3: ='Data Sheet'!H16 -> 44986 | I3: ='Data Sheet'!I16 -> 45352 | ... K3: ='Data Sheet'!K16 -> 46082 | L3: Trailing | M3: Best Case | N3: Worst Case
A4: Sales | B4: ='Data Sheet'!B17 -> 9054 | C4: ='Data Sheet'!C17 -> 9914 | D4: ='Data Sheet'!D17 -> 11055 | E4: ='Data Sheet'!E17 -> 11600 | F4: ='Data Sheet'!F17 -> 13136 | G4: ='Data Sheet'!G17 -> 14136 | H4: ='Data Sheet'!H17 -> 16301 | I4: ='Data Sheet'!I17 -> 16769 | ... K4: ='Data Sheet'!K17 -> 19152 | L4: =SUM(Quarters!H4:K4) -> 19530 | M4: =$K4+M23*K4 -> 20442.462 | N4: =$K4+N23*L4 -> 20229.985
A5: Expenses | B5: =SUM('Data Sheet'!B18,'Data Sheet'!B20:B24, -1*'Data Sheet'!B19) -> 7869.96 | C5: =SUM('Data Sheet'!C18,'Data Sheet'!C20:C24, -1*'Data Sheet'!C19) -> 8375.22 | D5: =SUM('Data Sheet'!D18,'Data Sheet'!D20:D24, -1*'Data Sheet'!D19) -> 9435.75 | E5: =SUM('Data Sheet'!E18,'Data Sheet'!E20:E24, -1*'Data Sheet'!E19) -> 9606 | F5: =SUM('Data Sheet'!F18,'Data Sheet'!F20:F24, -1*'Data Sheet'!F19) -> 10589.92 | G5: =SUM('Data Sheet'!G18,'Data Sheet'!G20:G24, -1*'Data Sheet'!G19) -> 12162.28 | H5: =SUM('Data Sheet'!H18,'Data Sheet'!H20:H24, -1*'Data Sheet'!H19) -> 13649.24 | I5: =SUM('Data Sheet'!I18,'Data Sheet'!I20:I24, -1*'Data Sheet'!I19) -> 13508.56 | ... K5: =SUM('Data Sheet'!K18,'Data Sheet'!K20:K24, -1*'Data Sheet'!K19) -> 15773.48 | L5: =SUM(Quarters!H5:K5) -> 15928 | M5: =M4-M6 -> 16674.267 | N5: =N4-N6 -> 16850.752
A6: Operating Profit | B6: =B4-B5 -> 1184.04 | C6: =C4-C5 -> 1538.78 | D6: =D4-D5 -> 1619.25 | E6: =E4-E5 -> 1994 | F6: =F4-F5 -> 2546.08 | G6: =G4-G5 -> 1973.72 | H6: =H4-H5 -> 2651.76 | I6: =I4-I5 -> 3260.44 | ... K6: =K4-K5 -> 3378.52 | L6: =SUM(Quarters!H6:K6) -> 3600 | M6: =M4*M24 -> 3768.1958 | N6: =N4*N24 -> 3379.2339
A7: Other Income | B7: ='Data Sheet'!B25 -> 151 | C7: ='Data Sheet'!C25 -> 166 | D7: ='Data Sheet'!D25 -> 206 | E7: ='Data Sheet'!E25 -> 263 | F7: ='Data Sheet'!F25 -> 313 | G7: ='Data Sheet'!G25 -> 222 | H7: ='Data Sheet'!H25 -> 597 | I7: ='Data Sheet'!I25 -> 211 | ... K7: ='Data Sheet'!K25 -> 224 | L7: =SUM(Quarters!H7:K7) -> 227 | M7: 0 | N7: 0
A8: Depreciation | B8: ='Data Sheet'!B26 -> 119 | C8: ='Data Sheet'!C26 -> 142 | D8: ='Data Sheet'!D26 -> 162 | E8: ='Data Sheet'!E26 -> 185 | F8: ='Data Sheet'!F26 -> 198 | G8: ='Data Sheet'!G26 -> 201 | H8: ='Data Sheet'!H26 -> 226 | I8: ='Data Sheet'!I26 -> 300 | ... K8: ='Data Sheet'!K26 -> 337 | L8: =SUM(Quarters!H8:K8) -> 335 | M8: =+$L8 -> 335 | N8: =+$L8 -> 335
A9: Interest | B9: ='Data Sheet'!B27 -> 5 | C9: ='Data Sheet'!C27 -> 8 | D9: ='Data Sheet'!D27 -> 9 | E9: ='Data Sheet'!E27 -> 77 | F9: ='Data Sheet'!F27 -> 111 | G9: ='Data Sheet'!G27 -> 144 | H9: ='Data Sheet'!H27 -> 169 | I9: ='Data Sheet'!I27 -> 164 | ... K9: ='Data Sheet'!K27 -> 113 | L9: =SUM(Quarters!H9:K9) -> 110 | M9: =+$L9 -> 110 | N9: =+$L9 -> 110
A10: Profit before tax | B10: ='Data Sheet'!B28 -> 1304 | C10: ='Data Sheet'!C28 -> 1518 | D10: ='Data Sheet'!D28 -> 1768 | E10: ='Data Sheet'!E28 -> 1844 | F10: ='Data Sheet'!F28 -> 2514 | G10: ='Data Sheet'!G28 -> 2078 | H10: ='Data Sheet'!H28 -> 3033 | I10: ='Data Sheet'!I28 -> 2913 | ... K10: ='Data Sheet'!K28 -> 3289 | L10: =SUM(Quarters!H10:K10) -> 3385 | M10: =M6+M7-SUM(M8:M9) -> 3323.1958 | N10: =N6+N7-SUM(N8:N9) -> 2934.2339
A11: Tax | B11: ='Data Sheet'!B29 -> 419 | C11: ='Data Sheet'!C29 -> 514 | D11: ='Data Sheet'!D29 -> 613 | E11: ='Data Sheet'!E29 -> 450 | F11: ='Data Sheet'!F29 -> 663 | G11: ='Data Sheet'!G29 -> 562 | H11: ='Data Sheet'!H29 -> 717 | I11: ='Data Sheet'!I29 -> 779 | ... K11: ='Data Sheet'!K29 -> 752 | L11: =SUM(Quarters!H11:K11) -> 775 | M11: =IF($L10>0,$L11/$L10,0) -> 0.22895126 | N11: =IF($L10>0,$L11/$L10,0) -> 0.22895126
A12: Net profit | B12: ='Data Sheet'!B30 -> 885 | C12: ='Data Sheet'!C30 -> 1004 | D12: ='Data Sheet'!D30 -> 1155 | E12: ='Data Sheet'!E30 -> 1394 | F12: ='Data Sheet'!F30 -> 1851 | G12: ='Data Sheet'!G30 -> 1516 | H12: ='Data Sheet'!H30 -> 2316 | I12: ='Data Sheet'!I30 -> 2134 | ... K12: ='Data Sheet'!K30 -> 2537 | L12: =SUM(Quarters!H12:K12) -> 2610 | M12: =M10-M11*M10 -> 2562.346 | N12: =N10-N11*N10 -> 2262.4373
A13: EPS | B13: =IF('Data Sheet'!B93>0,B12/'Data Sheet'!B93,0) -> 36.875 | C13: =IF('Data Sheet'!C93>0,C12/'Data Sheet'!C93,0) -> 41.833333 | D13: =IF('Data Sheet'!D93>0,D12/'Data Sheet'!D93,0) -> 48.125 | E13: =IF('Data Sheet'!E93>0,E12/'Data Sheet'!E93,0) -> 58.083333 | F13: =IF('Data Sheet'!F93>0,F12/'Data Sheet'!F93,0) -> 77.125 | G13: =IF('Data Sheet'!G93>0,G12/'Data Sheet'!G93,0) -> 63.166667 | H13: =IF('Data Sheet'!H93>0,H12/'Data Sheet'!H93,0) -> 96.5 | I13: =IF('Data Sheet'!I93>0,I12/'Data Sheet'!I93,0) -> 88.916667 | ... K13: =IF('Data Sheet'!K93>0,K12/'Data Sheet'!K93,0) -> 105.70833 | L13: =IF('Data Sheet'!$B6>0,'Profit & Loss'!L12/'Data Sheet'!$B6,0) -> 108.51242 | M13: =IF('Data Sheet'!$B6>0,'Profit & Loss'!M12/'Data Sheet'!$B6,0) -> 106.53117 | N13: =IF('Data Sheet'!$B6>0,'Profit & Loss'!N12/'Data Sheet'!$B6,0) -> 94.062281
A14: Price to earning | B14: =IF(B15>0,B15/B13,"") -> 41.989966 | C14: =IF(C15>0,C15/C13,"") -> 59.08996 | D14: =IF(D15>0,D15/D13,"") -> 63.942857 | E14: =IF(E15>0,E15/E13,"") -> 51.136872 | F14: =IF(F15>0,F15/F13,"") -> 43.614263 | G14: =IF(G15>0,G15/G13,"") -> 53.372296 | H14: =IF(H15>0,H15/H13,"") -> 45.719689 | I14: =IF(I15>0,I15/I13,"") -> 55.361387 | ... K14: =IF(K15>0,K15/K13,"") -> 56.783603 | L14: =IF(L13>0,L15/L13,0) -> 45.423372 | M14: =M25 -> 52.051732 | N14: =N25 -> 45.423372
A15: Price | B15: ='Data Sheet'!B90 -> 1548.38 | C15: ='Data Sheet'!C90 -> 2471.93 | D15: ='Data Sheet'!D90 -> 3077.25 | E15: ='Data Sheet'!E90 -> 2970.2 | F15: ='Data Sheet'!F90 -> 3363.75 | G15: ='Data Sheet'!G90 -> 3371.35 | H15: ='Data Sheet'!H90 -> 4411.95 | I15: ='Data Sheet'!I90 -> 4922.55 | ... K15: ='Data Sheet'!K90 -> 6002.5 | L15: ='Data Sheet'!B8 -> 4929 | M15: =M13*M14 -> 5545.1322 | N15: =N13*N14 -> 4272.6259
A17: RATIOS:
A18: Dividend Payout | B18: =IF('Data Sheet'!B30>0, 'Data Sheet'!B31/'Data Sheet'!B30, 0) -> 0.3 | C18: =IF('Data Sheet'!C30>0, 'Data Sheet'!C31/'Data Sheet'!C30, 0) -> 0.3 | D18: =IF('Data Sheet'!D30>0, 'Data Sheet'!D31/'Data Sheet'!D30, 0) -> 0.31 | E18: =IF('Data Sheet'!E30>0, 'Data Sheet'!E31/'Data Sheet'!E30, 0) -> 0.6 | F18: =IF('Data Sheet'!F30>0, 'Data Sheet'!F31/'Data Sheet'!F30, 0) -> 2.04 | G18: =IF('Data Sheet'!G30>0, 'Data Sheet'!G31/'Data Sheet'!G30, 0) -> 0.89 | H18: =IF('Data Sheet'!H30>0, 'Data Sheet'!H31/'Data Sheet'!H30, 0) -> 0.75 | I18: =IF('Data Sheet'!I30>0, 'Data Sheet'!I31/'Data Sheet'!I30, 0) -> 0.83 | ... K18: =IF('Data Sheet'!K30>0, 'Data Sheet'!K31/'Data Sheet'!K30, 0) -> 0.86
A19: OPM | B19: =IF(B6>0,B6/B4,0) -> 0.13077535 | C19: =IF(C6>0,C6/C4,0) -> 0.15521283 | D19: =IF(D6>0,D6/D4,0) -> 0.14647218 | E19: =IF(E6>0,E6/E4,0) -> 0.17189655 | F19: =IF(F6>0,F6/F4,0) -> 0.1938246 | G19: =IF(G6>0,G6/G4,0) -> 0.13962366 | H19: =IF(H6>0,H6/H4,0) -> 0.16267468 | I19: =IF(I6>0,I6/I4,0) -> 0.19443258 | ... L19: =IF(L6>0,L6/L4,0) -> 0.1843318
G22: TRENDS: | H22: 10 YEARS | I22: 7 YEARS | J22: 5 YEARS | K22: 3 YEARS | L22: RECENT | M22: BEST | N22: WORST
G23: Sales Growth | H23: =IF(B4=0,"",POWER($K4/B4,1/9)-1) -> 0.0868075 | I23: =IF(D4=0,"",POWER($K4/D4,1/7)-1) -> 0.081667115 | J23: =IF(F4=0,"",POWER($K4/F4,1/5)-1) -> 0.078326303 | K23: =IF(H4=0,"",POWER($K4/H4, 1/3)-1) -> 0.055196386 | L23: =IF(ISERROR(MAX(IF(J4=0,"",(K4-J4)/J4),IF(K4=0,"",(L4-K4)/K4))),"",MAX(IF(J4=0,"",(K4-J4)/J4),IF(K4=0,"",(L4-K4)/K4))) -> 0.067380037 | M23: =MAX(K23:L23) -> 0.067380037 | N23: =MIN(H23:L23) -> 0.055196386
G24: OPM | H24: =IF(SUM(B4:$K$4)=0,"",SUMPRODUCT(B19:$K$19,B4:$K$4)/SUM(B4:$K$4)) -> 0.16704085 | I24: =IF(SUM(E4:$K$4)=0,"",SUMPRODUCT(E19:$K$19,E4:$K$4)/SUM(E4:$K$4)) -> 0.17321304 | J24: =IF(SUM(G4:$K$4)=0,"",SUMPRODUCT(G19:$K$19,G4:$K$4)/SUM(G4:$K$4)) -> 0.17018244 | K24: =IF(SUM(I4:$K$4)=0, "", SUMPRODUCT(I19:$K$19,I4:$K$4)/SUM(I4:$K$4)) -> 0.18047434 | L24: =L19 -> 0.1843318 | M24: =MAX(K24:L24) -> 0.1843318 | N24: =MIN(H24:L24) -> 0.16704085
G25: Price to Earning | H25: =IF(ISERROR(AVERAGEIF(B14:$L14,">0")),"",AVERAGEIF(B14:$L14,">0")) -> 51.552076 | I25: =IF(ISERROR(AVERAGEIF(E14:$L14,">0")),"",AVERAGEIF(E14:$L14,">0")) -> 50.256256 | J25: =IF(ISERROR(AVERAGEIF(G14:$L14,">0")),"",AVERAGEIF(G14:$L14,">0")) -> 51.216486 | K25: =IF(ISERROR(AVERAGEIF(I14:$L14,">0")),"",AVERAGEIF(I14:$L14,">0")) -> 52.051732 | L25: =L14 -> 45.423372 | M25: =MAX(K25:L25) -> 52.051732 | N25: =MIN(H25:L25) -> 45.423372

Sheet Quarters
A1: ='Profit & Loss'!A1 -> BRITANNIA INDUSTRIES LTD | E1: =UPDATE | J1: SCREENER.IN
A3: Narration | B3: ='Data Sheet'!B41 -> 45352 | C3: ='Data Sheet'!C41 -> 45444 | D3: ='Data Sheet'!D41 -> 45536 | E3: ='Data Sheet'!E41 -> 45627 | F3: ='Data Sheet'!F41 -> 45717 | G3: ='Data Sheet'!G41 -> 45809 | H3: ='Data Sheet'!H41 -> 45901 | I3: ='Data Sheet'!I41 -> 45992 | ... K3: ='Data Sheet'!K41 -> 46174
A4: Sales | B4: ='Data Sheet'!B42 -> 4069 | C4: ='Data Sheet'!C42 -> 4250 | D4: ='Data Sheet'!D42 -> 4668 | E4: ='Data Sheet'!E42 -> 4593 | F4: ='Data Sheet'!F42 -> 4432 | G4: ='Data Sheet'!G42 -> 4622 | H4: ='Data Sheet'!H42 -> 4841 | I4: ='Data Sheet'!I42 -> 4970 | ... K4: ='Data Sheet'!K42 -> 5000
A5: Expenses | B5: ='Data Sheet'!B43 -> 3286 | C5: ='Data Sheet'!C43 -> 3497 | D5: ='Data Sheet'!D43 -> 3888 | E5: ='Data Sheet'!E43 -> 3750 | F5: ='Data Sheet'!F43 -> 3632 | G5: ='Data Sheet'!G43 -> 3870 | H5: ='Data Sheet'!H43 -> 3889 | I5: ='Data Sheet'!I43 -> 3992 | ... K5: ='Data Sheet'!K43 -> 4162
A6: Operating Profit | B6: ='Data Sheet'!B50 -> 784 | C6: ='Data Sheet'!C50 -> 753 | D6: ='Data Sheet'!D50 -> 780 | E6: ='Data Sheet'!E50 -> 843 | F6: ='Data Sheet'!F50 -> 801 | G6: ='Data Sheet'!G50 -> 752 | H6: ='Data Sheet'!H50 -> 951 | I6: ='Data Sheet'!I50 -> 977 | ... K6: ='Data Sheet'!K50 -> 838
A7: Other Income | B7: ='Data Sheet'!B44 -> 57 | C7: ='Data Sheet'!C44 -> 31 | D7: ='Data Sheet'!D44 -> 46 | E7: ='Data Sheet'!E44 -> 62 | F7: ='Data Sheet'!F44 -> 63 | G7: ='Data Sheet'!G44 -> 57 | H7: ='Data Sheet'!H44 -> 52 | I7: ='Data Sheet'!I44 -> 59 | ... K7: ='Data Sheet'!K44 -> 61
A8: Depreciation | B8: ='Data Sheet'!B45 -> 80 | C8: ='Data Sheet'!C45 -> 74 | D8: ='Data Sheet'!D45 -> 76 | E8: ='Data Sheet'!E45 -> 82 | F8: ='Data Sheet'!F45 -> 81 | G8: ='Data Sheet'!G45 -> 82 | H8: ='Data Sheet'!H45 -> 85 | I8: ='Data Sheet'!I45 -> 85 | ... K8: ='Data Sheet'!K45 -> 80
A9: Interest | B9: ='Data Sheet'!B46 -> 26 | C9: ='Data Sheet'!C46 -> 29 | D9: ='Data Sheet'!D46 -> 35 | E9: ='Data Sheet'!E46 -> 45 | F9: ='Data Sheet'!F46 -> 31 | G9: ='Data Sheet'!G46 -> 26 | H9: ='Data Sheet'!H46 -> 35 | I9: ='Data Sheet'!I46 -> 33 | ... K9: ='Data Sheet'!K46 -> 23
A10: Profit before tax | B10: ='Data Sheet'!B47 -> 735 | C10: ='Data Sheet'!C47 -> 681 | D10: ='Data Sheet'!D47 -> 715 | E10: ='Data Sheet'!E47 -> 778 | F10: ='Data Sheet'!F47 -> 752 | G10: ='Data Sheet'!G47 -> 701 | H10: ='Data Sheet'!H47 -> 884 | I10: ='Data Sheet'!I47 -> 919 | ... K10: ='Data Sheet'!K47 -> 797
A11: Tax | B11: ='Data Sheet'!B48 -> 198 | C11: ='Data Sheet'!C48 -> 176 | D11: ='Data Sheet'!D48 -> 183 | E11: ='Data Sheet'!E48 -> 196 | F11: ='Data Sheet'!F48 -> 193 | G11: ='Data Sheet'!G48 -> 181 | H11: ='Data Sheet'!H48 -> 229 | I11: ='Data Sheet'!I48 -> 237 | ... K11: ='Data Sheet'!K48 -> 204
A12: Net profit | B12: ='Data Sheet'!B49 -> 537 | C12: ='Data Sheet'!C49 -> 505 | D12: ='Data Sheet'!D49 -> 532 | E12: ='Data Sheet'!E49 -> 582 | F12: ='Data Sheet'!F49 -> 559 | G12: ='Data Sheet'!G49 -> 520 | H12: ='Data Sheet'!H49 -> 655 | I12: ='Data Sheet'!I49 -> 682 | ... K12: ='Data Sheet'!K49 -> 593
A14: OPM | B14: =IF(B4>0,B6/B4,"") -> 0.19267633 | C14: =IF(C4>0,C6/C4,"") -> 0.17717647 | D14: =IF(D4>0,D6/D4,"") -> 0.16709512 | E14: =IF(E4>0,E6/E4,"") -> 0.18354017 | F14: =IF(F4>0,F6/F4,"") -> 0.18073105 | G14: =IF(G4>0,G6/G4,"") -> 0.16270013 | H14: =IF(H4>0,H6/H4,"") -> 0.19644702 | I14: =IF(I4>0,I6/I4,"") -> 0.19657948 | ... K14: =IF(K4>0,K6/K4,"") -> 0.1676

Sheet Balance Sheet
A1: ='Profit & Loss'!A1 -> BRITANNIA INDUSTRIES LTD | E1: =UPDATE | J1: SCREENER.IN
A3: Narration | B3: ='Data Sheet'!B56 -> 42795 | C3: ='Data Sheet'!C56 -> 43160 | D3: ='Data Sheet'!D56 -> 43525 | E3: ='Data Sheet'!E56 -> 43891 | F3: ='Data Sheet'!F56 -> 44256 | G3: ='Data Sheet'!G56 -> 44621 | H3: ='Data Sheet'!H56 -> 44986 | I3: ='Data Sheet'!I56 -> 45352 | ... K3: ='Data Sheet'!K56 -> 46082
A4: Equity Share Capital | B4: ='Data Sheet'!B57 -> 24 | C4: ='Data Sheet'!C57 -> 24 | D4: ='Data Sheet'!D57 -> 24 | E4: ='Data Sheet'!E57 -> 24 | F4: ='Data Sheet'!F57 -> 24 | G4: ='Data Sheet'!G57 -> 24 | H4: ='Data Sheet'!H57 -> 24 | I4: ='Data Sheet'!I57 -> 24 | ... K4: ='Data Sheet'!K57 -> 24
A5: Reserves | B5: ='Data Sheet'!B58 -> 2672 | C5: ='Data Sheet'!C58 -> 3382 | D5: ='Data Sheet'!D58 -> 4229 | E5: ='Data Sheet'!E58 -> 4379 | F5: ='Data Sheet'!F58 -> 3524 | G5: ='Data Sheet'!G58 -> 2534 | H5: ='Data Sheet'!H58 -> 3510 | I5: ='Data Sheet'!I58 -> 3917 | ... K5: ='Data Sheet'!K58 -> 5082
A6: Borrowings | B6: ='Data Sheet'!B59 -> 125 | C6: ='Data Sheet'!C59 -> 201 | D6: ='Data Sheet'!D59 -> 156 | E6: ='Data Sheet'!E59 -> 1538 | F6: ='Data Sheet'!F59 -> 2107 | G6: ='Data Sheet'!G59 -> 2481 | H6: ='Data Sheet'!H59 -> 2997 | I6: ='Data Sheet'!I59 -> 2065 | ... K6: ='Data Sheet'!K59 -> 1380
A7: Other Liabilities | B7: ='Data Sheet'!B60 -> 1288 | C7: ='Data Sheet'!C60 -> 1581 | D7: ='Data Sheet'!D60 -> 1829 | E7: ='Data Sheet'!E60 -> 1889 | F7: ='Data Sheet'!F60 -> 2345 | G7: ='Data Sheet'!G60 -> 2487 | H7: ='Data Sheet'!H60 -> 2819 | I7: ='Data Sheet'!I60 -> 3065 | ... K7: ='Data Sheet'!K60 -> 3243
A8: Total | B8: ='Data Sheet'!B61 -> 4109 | C8: ='Data Sheet'!C61 -> 5188 | D8: ='Data Sheet'!D61 -> 6238 | E8: ='Data Sheet'!E61 -> 7830 | F8: ='Data Sheet'!F61 -> 8000 | G8: ='Data Sheet'!G61 -> 7527 | H8: ='Data Sheet'!H61 -> 9351 | I8: ='Data Sheet'!I61 -> 9072 | ... K8: ='Data Sheet'!K61 -> 9730
A10: Net Block | B10: ='Data Sheet'!B62 -> 1160 | C10: ='Data Sheet'!C62 -> 1346 | D10: ='Data Sheet'!D62 -> 1688 | E10: ='Data Sheet'!E62 -> 1878 | F10: ='Data Sheet'!F62 -> 1793 | G10: ='Data Sheet'!G62 -> 1753 | H10: ='Data Sheet'!H62 -> 2655 | I10: ='Data Sheet'!I62 -> 2771 | ... K10: ='Data Sheet'!K62 -> 2850
A11: Capital Work in Progress | B11: ='Data Sheet'!B63 -> 30 | C11: ='Data Sheet'!C63 -> 203 | D11: ='Data Sheet'!D63 -> 101 | E11: ='Data Sheet'!E63 -> 40 | F11: ='Data Sheet'!F63 -> 117 | G11: ='Data Sheet'!G63 -> 536 | H11: ='Data Sheet'!H63 -> 105 | I11: ='Data Sheet'!I63 -> 188 | ... K11: ='Data Sheet'!K63 -> 39
A12: Investments | B12: ='Data Sheet'!B64 -> 487 | C12: ='Data Sheet'!C64 -> 1079 | D12: ='Data Sheet'!D64 -> 1476 | E12: ='Data Sheet'!E64 -> 2893 | F12: ='Data Sheet'!F64 -> 2781 | G12: ='Data Sheet'!G64 -> 1762 | H12: ='Data Sheet'!H64 -> 3324 | I12: ='Data Sheet'!I64 -> 2767 | ... K12: ='Data Sheet'!K64 -> 3610
A13: Other Assets | B13: ='Data Sheet'!B65 -> 2432 | C13: ='Data Sheet'!C65 -> 2560 | D13: ='Data Sheet'!D65 -> 2972 | E13: ='Data Sheet'!E65 -> 3019 | F13: ='Data Sheet'!F65 -> 3310 | G13: ='Data Sheet'!G65 -> 3475 | H13: ='Data Sheet'!H65 -> 3266 | I13: ='Data Sheet'!I65 -> 3346 | ... K13: ='Data Sheet'!K65 -> 3232
A14: Total | B14: ='Data Sheet'!B66 -> 4109 | C14: ='Data Sheet'!C66 -> 5188 | D14: ='Data Sheet'!D66 -> 6238 | E14: ='Data Sheet'!E66 -> 7830 | F14: ='Data Sheet'!F66 -> 8000 | G14: ='Data Sheet'!G66 -> 7527 | H14: ='Data Sheet'!H66 -> 9351 | I14: ='Data Sheet'!I66 -> 9072 | ... K14: ='Data Sheet'!K66 -> 9730
A16: Working Capital | B16: =B13-B7 -> 1144 | C16: =C13-C7 -> 979 | D16: =D13-D7 -> 1143 | E16: =E13-E7 -> 1130 | F16: =F13-F7 -> 965 | G16: =G13-G7 -> 988 | H16: =H13-H7 -> 447 | I16: =I13-I7 -> 281 | ... K16: =K13-K7 -> -11
A17: Debtors | B17: ='Data Sheet'!B67 -> 179 | C17: ='Data Sheet'!C67 -> 305 | D17: ='Data Sheet'!D67 -> 394 | E17: ='Data Sheet'!E67 -> 320 | F17: ='Data Sheet'!F67 -> 257 | G17: ='Data Sheet'!G67 -> 332 | H17: ='Data Sheet'!H67 -> 329 | I17: ='Data Sheet'!I67 -> 393 | ... K17: ='Data Sheet'!K67 -> 469
A18: Inventory | B18: ='Data Sheet'!B68 -> 661 | C18: ='Data Sheet'!C68 -> 653 | D18: ='Data Sheet'!D68 -> 781 | E18: ='Data Sheet'!E68 -> 741 | F18: ='Data Sheet'!F68 -> 1091 | G18: ='Data Sheet'!G68 -> 1367 | H18: ='Data Sheet'!H68 -> 1193 | I18: ='Data Sheet'!I68 -> 1181 | ... K18: ='Data Sheet'!K68 -> 1346
A20: Debtor Days | B20: =IF('Profit & Loss'!B4>0,'Balance Sheet'!B17/('Profit & Loss'!B4/365),0) -> 7.2161476 | C20: =IF('Profit & Loss'!C4>0,'Balance Sheet'!C17/('Profit & Loss'!C4/365),0) -> 11.22907 | D20: =IF('Profit & Loss'!D4>0,'Balance Sheet'!D17/('Profit & Loss'!D4/365),0) -> 13.008593 | E20: =IF('Profit & Loss'!E4>0,'Balance Sheet'!E17/('Profit & Loss'!E4/365),0) -> 10.068966 | F20: =IF('Profit & Loss'!F4>0,'Balance Sheet'!F17/('Profit & Loss'!F4/365),0) -> 7.1410627 | G20: =IF('Profit & Loss'!G4>0,'Balance Sheet'!G17/('Profit & Loss'!G4/365),0) -> 8.5724392 | H20: =IF('Profit & Loss'!H4>0,'Balance Sheet'!H17/('Profit & Loss'!H4/365),0) -> 7.366726 | I20: =IF('Profit & Loss'!I4>0,'Balance Sheet'!I17/('Profit & Loss'!I4/365),0) -> 8.5541774 | ... K20: =IF('Profit & Loss'!K4>0,'Balance Sheet'!K17/('Profit & Loss'!K4/365),0) -> 8.938231
A21: Inventory Turnover | B21: =IF('Balance Sheet'!B18>0,'Profit & Loss'!B4/'Balance Sheet'!B18,0) -> 13.697428 | C21: =IF('Balance Sheet'!C18>0,'Profit & Loss'!C4/'Balance Sheet'!C18,0) -> 15.182236 | D21: =IF('Balance Sheet'!D18>0,'Profit & Loss'!D4/'Balance Sheet'!D18,0) -> 14.15493 | E21: =IF('Balance Sheet'!E18>0,'Profit & Loss'!E4/'Balance Sheet'!E18,0) -> 15.654521 | F21: =IF('Balance Sheet'!F18>0,'Profit & Loss'!F4/'Balance Sheet'!F18,0) -> 12.04033 | G21: =IF('Balance Sheet'!G18>0,'Profit & Loss'!G4/'Balance Sheet'!G18,0) -> 10.340892 | H21: =IF('Balance Sheet'!H18>0,'Profit & Loss'!H4/'Balance Sheet'!H18,0) -> 13.663873 | I21: =IF('Balance Sheet'!I18>0,'Profit & Loss'!I4/'Balance Sheet'!I18,0) -> 14.198984 | ... K21: =IF('Balance Sheet'!K18>0,'Profit & Loss'!K4/'Balance Sheet'!K18,0) -> 14.228826
A23: Return on Equity | B23: =IF(SUM('Balance Sheet'!B4:B5)>0,'Profit & Loss'!B12/SUM('Balance Sheet'!B4:B5),"") -> 0.32826409 | C23: =IF(SUM('Balance Sheet'!C4:C5)>0,'Profit & Loss'!C12/SUM('Balance Sheet'!C4:C5),"") -> 0.29477393 | D23: =IF(SUM('Balance Sheet'!D4:D5)>0,'Profit & Loss'!D12/SUM('Balance Sheet'!D4:D5),"") -> 0.27157301 | E23: =IF(SUM('Balance Sheet'!E4:E5)>0,'Profit & Loss'!E12/SUM('Balance Sheet'!E4:E5),"") -> 0.31660232 | F23: =IF(SUM('Balance Sheet'!F4:F5)>0,'Profit & Loss'!F12/SUM('Balance Sheet'!F4:F5),"") -> 0.52170237 | G23: =IF(SUM('Balance Sheet'!G4:G5)>0,'Profit & Loss'!G12/SUM('Balance Sheet'!G4:G5),"") -> 0.59265051 | H23: =IF(SUM('Balance Sheet'!H4:H5)>0,'Profit & Loss'!H12/SUM('Balance Sheet'!H4:H5),"") -> 0.65534805 | I23: =IF(SUM('Balance Sheet'!I4:I5)>0,'Profit & Loss'!I12/SUM('Balance Sheet'!I4:I5),"") -> 0.54148693 | ... K23: =IF(SUM('Balance Sheet'!K4:K5)>0,'Profit & Loss'!K12/SUM('Balance Sheet'!K4:K5),"") -> 0.49686643
A24: Return on Capital Emp | C24: =IF((B4+B5+B6+C4+C5+C6)>0,('Profit & Loss'!C10+'Profit & Loss'!C9)*2/(B4+B5+B6+C4+C5+C6),"") -> 0.47479776 | D24: =IF((C4+C5+C6+D4+D5+D6)>0,('Profit & Loss'!D10+'Profit & Loss'!D9)*2/(C4+C5+C6+D4+D5+D6),"") -> 0.44336327 | E24: =IF((D4+D5+D6+E4+E5+E6)>0,('Profit & Loss'!E10+'Profit & Loss'!E9)*2/(D4+D5+D6+E4+E5+E6),"") -> 0.37120773 | F24: =IF((E4+E5+E6+F4+F5+F6)>0,('Profit & Loss'!F10+'Profit & Loss'!F9)*2/(E4+E5+E6+F4+F5+F6),"") -> 0.45274232 | G24: =IF((F4+F5+F6+G4+G5+G6)>0,('Profit & Loss'!G10+'Profit & Loss'!G9)*2/(F4+F5+F6+G4+G5+G6),"") -> 0.41556013 | H24: =IF((G4+G5+G6+H4+H5+H6)>0,('Profit & Loss'!H10+'Profit & Loss'!H9)*2/(G4+G5+G6+H4+H5+H6),"") -> 0.55350043 | I24: =IF((H4+H5+H6+I4+I5+I6)>0,('Profit & Loss'!I10+'Profit & Loss'!I9)*2/(H4+H5+H6+I4+I5+I6),"") -> 0.49086703 | J24: =IF((I4+I5+I6+J4+J5+J6)>0,('Profit & Loss'!J10+'Profit & Loss'!J9)*2/(I4+I5+I6+J4+J5+J6),"") -> 0.52821087 | K24: =IF((J4+J5+J6+K4+K5+K6)>0,('Profit & Loss'!K10+'Profit & Loss'!K9)*2/(J4+J5+J6+K4+K5+K6),"") -> 0.56282571

Sheet Cash Flow
A1: ='Balance Sheet'!A1 -> BRITANNIA INDUSTRIES LTD | E1: =UPDATE | J1: SCREENER.IN
A3: Narration | B3: ='Data Sheet'!B81 -> 42795 | C3: ='Data Sheet'!C81 -> 43160 | D3: ='Data Sheet'!D81 -> 43525 | E3: ='Data Sheet'!E81 -> 43891 | F3: ='Data Sheet'!F81 -> 44256 | G3: ='Data Sheet'!G81 -> 44621 | H3: ='Data Sheet'!H81 -> 44986 | I3: ='Data Sheet'!I81 -> 45352 | ... K3: ='Data Sheet'!K81 -> 46082
A4: Cash from Operating Activity | B4: ='Data Sheet'!B82 -> 441 | C4: ='Data Sheet'!C82 -> 1249 | D4: ='Data Sheet'!D82 -> 1156 | E4: ='Data Sheet'!E82 -> 1485 | F4: ='Data Sheet'!F82 -> 1851 | G4: ='Data Sheet'!G82 -> 1300 | H4: ='Data Sheet'!H82 -> 2526 | I4: ='Data Sheet'!I82 -> 2573 | ... K4: ='Data Sheet'!K82 -> 2612
A5: Cash from Investing Activity | B5: ='Data Sheet'!B83 -> -150 | C5: ='Data Sheet'!C83 -> -957 | D5: ='Data Sheet'!D83 -> -852 | E5: ='Data Sheet'!E83 -> -1526 | F5: ='Data Sheet'!F83 -> 459 | G5: ='Data Sheet'!G83 -> 914 | H5: ='Data Sheet'!H83 -> -1507 | I5: ='Data Sheet'!I83 -> 485 | ... K5: ='Data Sheet'!K83 -> -741
A6: Cash from Financing Activity | B6: ='Data Sheet'!B84 -> -295 | C6: ='Data Sheet'!C84 -> -232 | D6: ='Data Sheet'!D84 -> -353 | E6: ='Data Sheet'!E84 -> 58 | F6: ='Data Sheet'!F84 -> -2244 | G6: ='Data Sheet'!G84 -> -2246 | H6: ='Data Sheet'!H84 -> -1028 | I6: ='Data Sheet'!I84 -> -2839 | ... K6: ='Data Sheet'!K84 -> -1783
A7: Net Cash Flow | B7: ='Data Sheet'!B85 -> -4 | C7: ='Data Sheet'!C85 -> 60 | D7: ='Data Sheet'!D85 -> -49 | E7: ='Data Sheet'!E85 -> 17 | F7: ='Data Sheet'!F85 -> 66 | G7: ='Data Sheet'!G85 -> -32 | H7: ='Data Sheet'!H85 -> -9 | I7: ='Data Sheet'!I85 -> 219 | ... K7: ='Data Sheet'!K85 -> 88

Sheet Customization
A1: How to use it?
A3: You can customize this workbook as you want.
B4: You can add custom formating, add conditional formating, add your own formulas… do ANYTHING.
B5: Please don't edit the "Data Sheet" only.
A7: After customization, you can upload this back on Screener.
B8: Upload on: | C8: https://www.screener.in/excel/
A10: Download your customized workbooks now onwards.
B11: Now whenever you will "Export to excel" from Screener, it will export your customized file.
A14: TESTING:
B15: This is a testing feature currently.
B16: You can report any formula errors on the worksheet at: support@screener.in

Sheet Common Size Statement
B2: ="Common Size Statement - "&'Data Sheet'!$B$1 -> Common Size Statement - BRITANNIA INDUSTRIES LTD
B4: Particulars | C4: ='Data Sheet'!B$16 -> 42795 | D4: ='Data Sheet'!C$16 -> 43160 | E4: ='Data Sheet'!D$16 -> 43525 | F4: ='Data Sheet'!E$16 -> 43891 | G4: ='Data Sheet'!F$16 -> 44256 | H4: ='Data Sheet'!G$16 -> 44621 | I4: ='Data Sheet'!H$16 -> 44986 | J4: ='Data Sheet'!I$16 -> 45352 | ... L4: ='Data Sheet'!K$16 -> 46082
B6: ='Data Sheet'!A17 -> Sales | C6: ='Data Sheet'!B17/'Data Sheet'!B$17 -> 1 | D6: ='Data Sheet'!C17/'Data Sheet'!C$17 -> 1 | E6: ='Data Sheet'!D17/'Data Sheet'!D$17 -> 1 | F6: ='Data Sheet'!E17/'Data Sheet'!E$17 -> 1 | G6: ='Data Sheet'!F17/'Data Sheet'!F$17 -> 1 | H6: ='Data Sheet'!G17/'Data Sheet'!G$17 -> 1 | I6: ='Data Sheet'!H17/'Data Sheet'!H$17 -> 1 | J6: ='Data Sheet'!I17/'Data Sheet'!I$17 -> 1 | ... L6: ='Data Sheet'!K17/'Data Sheet'!K$17 -> 1
B7: ='Data Sheet'!A18 -> Raw Material Cost | C7: ='Data Sheet'!B18/'Data Sheet'!B$17 -> 0.62326044 | D7: ='Data Sheet'!C18/'Data Sheet'!C$17 -> 0.61539237 | E7: ='Data Sheet'!D18/'Data Sheet'!D$17 -> 0.59855269 | F7: ='Data Sheet'!E18/'Data Sheet'!E$17 -> 0.59267241 | G7: ='Data Sheet'!F18/'Data Sheet'!F$17 -> 0.58335871 | H7: ='Data Sheet'!G18/'Data Sheet'!G$17 -> 0.62507074 | I7: ='Data Sheet'!H18/'Data Sheet'!H$17 -> 0.59284706 | J7: ='Data Sheet'!I18/'Data Sheet'!I$17 -> 0.56580595 | ... L7: ='Data Sheet'!K18/'Data Sheet'!K$17 -> 0.5824457
B8: ='Data Sheet'!A19 -> Change in Inventory | C8: ='Data Sheet'!B19/'Data Sheet'!B$17 -> -0.0059642147 | D8: ='Data Sheet'!C19/'Data Sheet'!C$17 -> 0.00060520476 | E8: ='Data Sheet'!D19/'Data Sheet'!D$17 -> -0.0049751244 | F8: ='Data Sheet'!E19/'Data Sheet'!E$17 -> 0.0045689655 | G8: ='Data Sheet'!F19/'Data Sheet'!F$17 -> -0.002816687 | H8: ='Data Sheet'!G19/'Data Sheet'!G$17 -> -0.0053056027 | I8: ='Data Sheet'!H19/'Data Sheet'!H$17 -> -0.0044782529 | J8: ='Data Sheet'!I19/'Data Sheet'!I$17 -> 0.00023853539 | ... L8: ='Data Sheet'!K19/'Data Sheet'!K$17 -> -0.0011487051
B9: ='Data Sheet'!A20 -> Power and Fuel | C9: ='Data Sheet'!B20/'Data Sheet'!B$17 -> 0 | D9: ='Data Sheet'!C20/'Data Sheet'!C$17 -> 0 | E9: ='Data Sheet'!D20/'Data Sheet'!D$17 -> 0 | F9: ='Data Sheet'!E20/'Data Sheet'!E$17 -> 0 | G9: ='Data Sheet'!F20/'Data Sheet'!F$17 -> 0 | H9: ='Data Sheet'!G20/'Data Sheet'!G$17 -> 0 | I9: ='Data Sheet'!H20/'Data Sheet'!H$17 -> 0 | J9: ='Data Sheet'!I20/'Data Sheet'!I$17 -> 0 | ... L9: ='Data Sheet'!K20/'Data Sheet'!K$17 -> 0
B10: ='Data Sheet'!A21 -> Other Mfr. Exp | C10: ='Data Sheet'!B21/'Data Sheet'!B$17 -> 0.07 | D10: ='Data Sheet'!C21/'Data Sheet'!C$17 -> 0.06 | E10: ='Data Sheet'!D21/'Data Sheet'!D$17 -> 0.07 | F10: ='Data Sheet'!E21/'Data Sheet'!E$17 -> 0.07 | G10: ='Data Sheet'!F21/'Data Sheet'!F$17 -> 0.06 | H10: ='Data Sheet'!G21/'Data Sheet'!G$17 -> 0.07 | I10: ='Data Sheet'!H21/'Data Sheet'!H$17 -> 0.07 | J10: ='Data Sheet'!I21/'Data Sheet'!I$17 -> 0.07 | ... L10: ='Data Sheet'!K21/'Data Sheet'!K$17 -> 0.07
B11: ='Data Sheet'!A22 -> Employee Cost | C11: ='Data Sheet'!B22/'Data Sheet'!B$17 -> 0.04 | D11: ='Data Sheet'!C22/'Data Sheet'!C$17 -> 0.04 | E11: ='Data Sheet'!D22/'Data Sheet'!D$17 -> 0.04 | F11: ='Data Sheet'!E22/'Data Sheet'!E$17 -> 0.04 | G11: ='Data Sheet'!F22/'Data Sheet'!F$17 -> 0.04 | H11: ='Data Sheet'!G22/'Data Sheet'!G$17 -> 0.04 | I11: ='Data Sheet'!H22/'Data Sheet'!H$17 -> 0.04 | J11: ='Data Sheet'!I22/'Data Sheet'!I$17 -> 0.04 | ... L11: ='Data Sheet'!K22/'Data Sheet'!K$17 -> 0.04
B12: ='Data Sheet'!A23 -> Selling and admin | C12: ='Data Sheet'!B23/'Data Sheet'!B$17 -> 0 | D12: ='Data Sheet'!C23/'Data Sheet'!C$17 -> 0 | E12: ='Data Sheet'!D23/'Data Sheet'!D$17 -> 0 | F12: ='Data Sheet'!E23/'Data Sheet'!E$17 -> 0 | G12: ='Data Sheet'!F23/'Data Sheet'!F$17 -> 0 | H12: ='Data Sheet'!G23/'Data Sheet'!G$17 -> 0 | I12: ='Data Sheet'!H23/'Data Sheet'!H$17 -> 0 | J12: ='Data Sheet'!I23/'Data Sheet'!I$17 -> 0 | ... L12: ='Data Sheet'!K23/'Data Sheet'!K$17 -> 0
B13: ='Data Sheet'!A24 -> Other Expenses | C13: ='Data Sheet'!B24/'Data Sheet'!B$17 -> 0.13 | D13: ='Data Sheet'!C24/'Data Sheet'!C$17 -> 0.13 | E13: ='Data Sheet'!D24/'Data Sheet'!D$17 -> 0.14 | F13: ='Data Sheet'!E24/'Data Sheet'!E$17 -> 0.13 | G13: ='Data Sheet'!F24/'Data Sheet'!F$17 -> 0.12 | H13: ='Data Sheet'!G24/'Data Sheet'!G$17 -> 0.12 | I13: ='Data Sheet'!H24/'Data Sheet'!H$17 -> 0.13 | J13: ='Data Sheet'!I24/'Data Sheet'!I$17 -> 0.13 | ... L13: ='Data Sheet'!K24/'Data Sheet'!K$17 -> 0.13
B14: ='Data Sheet'!A25 -> Other Income | C14: ='Data Sheet'!B25/'Data Sheet'!B$17 -> 0.016677712 | D14: ='Data Sheet'!C25/'Data Sheet'!C$17 -> 0.016743998 | E14: ='Data Sheet'!D25/'Data Sheet'!D$17 -> 0.018634102 | F14: ='Data Sheet'!E25/'Data Sheet'!E$17 -> 0.022672414 | G14: ='Data Sheet'!F25/'Data Sheet'!F$17 -> 0.023827649 | H14: ='Data Sheet'!G25/'Data Sheet'!G$17 -> 0.015704584 | I14: ='Data Sheet'!H25/'Data Sheet'!H$17 -> 0.03662352 | J14: ='Data Sheet'!I25/'Data Sheet'!I$17 -> 0.012582742 | ... L14: ='Data Sheet'!K25/'Data Sheet'!K$17 -> 0.011695906
B15: ='Data Sheet'!A26 -> Depreciation | C15: ='Data Sheet'!B26/'Data Sheet'!B$17 -> 0.013143362 | D15: ='Data Sheet'!C26/'Data Sheet'!C$17 -> 0.014323179 | E15: ='Data Sheet'!D26/'Data Sheet'!D$17 -> 0.014654003 | F15: ='Data Sheet'!E26/'Data Sheet'!E$17 -> 0.015948276 | G15: ='Data Sheet'!F26/'Data Sheet'!F$17 -> 0.015073082 | H15: ='Data Sheet'!G26/'Data Sheet'!G$17 -> 0.014219015 | I15: ='Data Sheet'!H26/'Data Sheet'!H$17 -> 0.01386418 | J15: ='Data Sheet'!I26/'Data Sheet'!I$17 -> 0.017890154 | ... L15: ='Data Sheet'!K26/'Data Sheet'!K$17 -> 0.017596074
B16: ='Data Sheet'!A27 -> Interest | C16: ='Data Sheet'!B27/'Data Sheet'!B$17 -> 0.0005522421 | D16: ='Data Sheet'!C27/'Data Sheet'!C$17 -> 0.00080693968 | E16: ='Data Sheet'!D27/'Data Sheet'!D$17 -> 0.00081411126 | F16: ='Data Sheet'!E27/'Data Sheet'!E$17 -> 0.006637931 | G16: ='Data Sheet'!F27/'Data Sheet'!F$17 -> 0.0084500609 | H16: ='Data Sheet'!G27/'Data Sheet'!G$17 -> 0.010186757 | I16: ='Data Sheet'!H27/'Data Sheet'!H$17 -> 0.010367462 | J16: ='Data Sheet'!I27/'Data Sheet'!I$17 -> 0.0097799511 | ... L16: ='Data Sheet'!K27/'Data Sheet'!K$17 -> 0.0059001671
B17: ='Data Sheet'!A28 -> Profit before tax | C17: ='Data Sheet'!B28/'Data Sheet'!B$17 -> 0.14402474 | D17: ='Data Sheet'!C28/'Data Sheet'!C$17 -> 0.1531168 | E17: ='Data Sheet'!D28/'Data Sheet'!D$17 -> 0.15992763 | F17: ='Data Sheet'!E28/'Data Sheet'!E$17 -> 0.15896552 | G17: ='Data Sheet'!F28/'Data Sheet'!F$17 -> 0.19138246 | H17: ='Data Sheet'!G28/'Data Sheet'!G$17 -> 0.14700057 | I17: ='Data Sheet'!H28/'Data Sheet'!H$17 -> 0.1860622 | J17: ='Data Sheet'!I28/'Data Sheet'!I$17 -> 0.1737134 | ... L17: ='Data Sheet'!K28/'Data Sheet'!K$17 -> 0.17173141
... B21: ='Data Sheet'!A32 -> EBITDA | C21: ='Data Sheet'!B32/'Data Sheet'!B$17 -> 0.15772034 | D21: ='Data Sheet'!C32/'Data Sheet'!C$17 -> 0.16824692 | E21: ='Data Sheet'!D32/'Data Sheet'!D$17 -> 0.17539575 | F21: ='Data Sheet'!E32/'Data Sheet'!E$17 -> 0.18155172 | G21: ='Data Sheet'!F32/'Data Sheet'!F$17 -> 0.2149056 | H21: ='Data Sheet'!G32/'Data Sheet'!G$17 -> 0.17140634 | I21: ='Data Sheet'!H32/'Data Sheet'!H$17 -> 0.21029385 | J21: ='Data Sheet'!I32/'Data Sheet'!I$17 -> 0.20138351 | ... L21: ='Data Sheet'!K32/'Data Sheet'!K$17 -> 0.19522765
B23: ="Common Size Balance Sheet - "&'Data Sheet'!$B$1 -> Common Size Balance Sheet - BRITANNIA INDUSTRIES LTD
B25: Particulars | C25: ='Data Sheet'!B$16 -> 42795 | D25: ='Data Sheet'!C$16 -> 43160 | E25: ='Data Sheet'!D$16 -> 43525 | F25: ='Data Sheet'!E$16 -> 43891 | G25: ='Data Sheet'!F$16 -> 44256 | H25: ='Data Sheet'!G$16 -> 44621 | I25: ='Data Sheet'!H$16 -> 44986 | J25: ='Data Sheet'!I$16 -> 45352 | ... L25: ='Data Sheet'!K$16 -> 46082
B27: Total Liabilities | C27: ='Data Sheet'!B61/'Data Sheet'!B$61 -> 1 | D27: ='Data Sheet'!C61/'Data Sheet'!C$61 -> 1 | E27: ='Data Sheet'!D61/'Data Sheet'!D$61 -> 1 | F27: ='Data Sheet'!E61/'Data Sheet'!E$61 -> 1 | G27: ='Data Sheet'!F61/'Data Sheet'!F$61 -> 1 | H27: ='Data Sheet'!G61/'Data Sheet'!G$61 -> 1 | I27: ='Data Sheet'!H61/'Data Sheet'!H$61 -> 1 | J27: ='Data Sheet'!I61/'Data Sheet'!I$61 -> 1 | ... L27: ='Data Sheet'!K61/'Data Sheet'!K$61 -> 1
B28: ='Data Sheet'!A57 -> Equity Share Capital | C28: ='Data Sheet'!B57/'Data Sheet'!B$61 -> 0.0058408372 | D28: ='Data Sheet'!C57/'Data Sheet'!C$61 -> 0.0046260601 | E28: ='Data Sheet'!D57/'Data Sheet'!D$61 -> 0.003847387 | F28: ='Data Sheet'!E57/'Data Sheet'!E$61 -> 0.0030651341 | G28: ='Data Sheet'!F57/'Data Sheet'!F$61 -> 0.003 | H28: ='Data Sheet'!G57/'Data Sheet'!G$61 -> 0.0031885213 | I28: ='Data Sheet'!H57/'Data Sheet'!H$61 -> 0.0025665704 | J28: ='Data Sheet'!I57/'Data Sheet'!I$61 -> 0.0026455026 | ... L28: ='Data Sheet'!K57/'Data Sheet'!K$61 -> 0.0024665982
B29: ='Data Sheet'!A58 -> Reserves | C29: ='Data Sheet'!B58/'Data Sheet'!B$61 -> 0.65027987 | D29: ='Data Sheet'!C58/'Data Sheet'!C$61 -> 0.65188897 | E29: ='Data Sheet'!D58/'Data Sheet'!D$61 -> 0.67794165 | F29: ='Data Sheet'!E58/'Data Sheet'!E$61 -> 0.55925926 | G29: ='Data Sheet'!F58/'Data Sheet'!F$61 -> 0.4405 | H29: ='Data Sheet'!G58/'Data Sheet'!G$61 -> 0.33665471 | I29: ='Data Sheet'!H58/'Data Sheet'!H$61 -> 0.37536092 | J29: ='Data Sheet'!I58/'Data Sheet'!I$61 -> 0.43176808 | ... L29: ='Data Sheet'!K58/'Data Sheet'!K$61 -> 0.52230216
B30: ='Data Sheet'!A59 -> Borrowings | C30: ='Data Sheet'!B59/'Data Sheet'!B$61 -> 0.030421027 | D30: ='Data Sheet'!C59/'Data Sheet'!C$61 -> 0.038743254 | E30: ='Data Sheet'!D59/'Data Sheet'!D$61 -> 0.025008015 | F30: ='Data Sheet'!E59/'Data Sheet'!E$61 -> 0.19642401 | G30: ='Data Sheet'!F59/'Data Sheet'!F$61 -> 0.263375 | H30: ='Data Sheet'!G59/'Data Sheet'!G$61 -> 0.32961339 | I30: ='Data Sheet'!H59/'Data Sheet'!H$61 -> 0.32050048 | J30: ='Data Sheet'!I59/'Data Sheet'!I$61 -> 0.22762346 | ... L30: ='Data Sheet'!K59/'Data Sheet'!K$61 -> 0.14182939
B31: ='Data Sheet'!A60 -> Other Liabilities | C31: ='Data Sheet'!B60/'Data Sheet'!B$61 -> 0.31345826 | D31: ='Data Sheet'!C60/'Data Sheet'!C$61 -> 0.30474171 | E31: ='Data Sheet'!D60/'Data Sheet'!D$61 -> 0.29320295 | F31: ='Data Sheet'!E60/'Data Sheet'!E$61 -> 0.2412516 | G31: ='Data Sheet'!F60/'Data Sheet'!F$61 -> 0.293125 | H31: ='Data Sheet'!G60/'Data Sheet'!G$61 -> 0.33041052 | I31: ='Data Sheet'!H60/'Data Sheet'!H$61 -> 0.30146508 | J31: ='Data Sheet'!I60/'Data Sheet'!I$61 -> 0.33785273 | ... L31: ='Data Sheet'!K60/'Data Sheet'!K$61 -> 0.33329908
B33: Total Assets | C33: ='Data Sheet'!B66/'Data Sheet'!B$66 -> 1 | D33: ='Data Sheet'!C66/'Data Sheet'!C$66 -> 1 | E33: ='Data Sheet'!D66/'Data Sheet'!D$66 -> 1 | F33: ='Data Sheet'!E66/'Data Sheet'!E$66 -> 1 | G33: ='Data Sheet'!F66/'Data Sheet'!F$66 -> 1 | H33: ='Data Sheet'!G66/'Data Sheet'!G$66 -> 1 | I33: ='Data Sheet'!H66/'Data Sheet'!H$66 -> 1 | J33: ='Data Sheet'!I66/'Data Sheet'!I$66 -> 1 | ... L33: ='Data Sheet'!K66/'Data Sheet'!K$66 -> 1
B34: Fixed Assets Net Block | C34: ='Data Sheet'!B62/'Data Sheet'!B$66 -> 0.28230713 | D34: ='Data Sheet'!C62/'Data Sheet'!C$66 -> 0.25944487 | E34: ='Data Sheet'!D62/'Data Sheet'!D$66 -> 0.27059955 | F34: ='Data Sheet'!E62/'Data Sheet'!E$66 -> 0.23984674 | G34: ='Data Sheet'!F62/'Data Sheet'!F$66 -> 0.224125 | H34: ='Data Sheet'!G62/'Data Sheet'!G$66 -> 0.23289491 | I34: ='Data Sheet'!H62/'Data Sheet'!H$66 -> 0.28392685 | J34: ='Data Sheet'!I62/'Data Sheet'!I$66 -> 0.30544533 | ... L34: ='Data Sheet'!K62/'Data Sheet'!K$66 -> 0.29290853
B35: ='Data Sheet'!A63 -> Capital Work in Progress | C35: ='Data Sheet'!B63/'Data Sheet'!B$66 -> 0.0073010465 | D35: ='Data Sheet'!C63/'Data Sheet'!C$66 -> 0.039128759 | E35: ='Data Sheet'!D63/'Data Sheet'!D$66 -> 0.016191087 | F35: ='Data Sheet'!E63/'Data Sheet'!E$66 -> 0.0051085568 | G35: ='Data Sheet'!F63/'Data Sheet'!F$66 -> 0.014625 | H35: ='Data Sheet'!G63/'Data Sheet'!G$66 -> 0.07121031 | I35: ='Data Sheet'!H63/'Data Sheet'!H$66 -> 0.011228746 | J35: ='Data Sheet'!I63/'Data Sheet'!I$66 -> 0.020723104 | ... L35: ='Data Sheet'!K63/'Data Sheet'!K$66 -> 0.004008222
B36: ='Data Sheet'!A64 -> Investments | C36: ='Data Sheet'!B64/'Data Sheet'!B$66 -> 0.11852032 | D36: ='Data Sheet'!C64/'Data Sheet'!C$66 -> 0.20797995 | E36: ='Data Sheet'!D64/'Data Sheet'!D$66 -> 0.2366143 | F36: ='Data Sheet'!E64/'Data Sheet'!E$66 -> 0.36947637 | G36: ='Data Sheet'!F64/'Data Sheet'!F$66 -> 0.347625 | H36: ='Data Sheet'!G64/'Data Sheet'!G$66 -> 0.23409061 | I36: ='Data Sheet'!H64/'Data Sheet'!H$66 -> 0.35547 | J36: ='Data Sheet'!I64/'Data Sheet'!I$66 -> 0.30500441 | ... L36: ='Data Sheet'!K64/'Data Sheet'!K$66 -> 0.37101747
B37: ='Data Sheet'!A65 -> Other Assets | C37: ='Data Sheet'!B74/'Data Sheet'!B66 -> 0 | D37: ='Data Sheet'!C74/'Data Sheet'!C66 -> 0 | E37: ='Data Sheet'!D74/'Data Sheet'!D66 -> 0 | F37: ='Data Sheet'!E74/'Data Sheet'!E66 -> 0 | G37: ='Data Sheet'!F74/'Data Sheet'!F66 -> 0 | H37: ='Data Sheet'!G74/'Data Sheet'!G66 -> 0 | I37: ='Data Sheet'!H74/'Data Sheet'!H66 -> 0 | J37: ='Data Sheet'!I74/'Data Sheet'!I66 -> 0 | ... L37: ='Data Sheet'!K74/'Data Sheet'!K66 -> 0
B38: ='Data Sheet'!A67 -> Receivables | C38: ='Data Sheet'!B67/'Data Sheet'!B$66 -> 0.043562911 | D38: ='Data Sheet'!C67/'Data Sheet'!C$66 -> 0.058789514 | E38: ='Data Sheet'!D67/'Data Sheet'!D$66 -> 0.06316127 | F38: ='Data Sheet'!E67/'Data Sheet'!E$66 -> 0.040868455 | G38: ='Data Sheet'!F67/'Data Sheet'!F$66 -> 0.032125 | H38: ='Data Sheet'!G67/'Data Sheet'!G$66 -> 0.044107878 | I38: ='Data Sheet'!H67/'Data Sheet'!H$66 -> 0.035183403 | J38: ='Data Sheet'!I67/'Data Sheet'!I$66 -> 0.043320106 | ... L38: ='Data Sheet'!K67/'Data Sheet'!K$66 -> 0.048201439
B39: ='Data Sheet'!A68 -> Inventory | C39: ='Data Sheet'!B68/'Data Sheet'!B$66 -> 0.16086639 | D39: ='Data Sheet'!C68/'Data Sheet'!C$66 -> 0.12586739 | E39: ='Data Sheet'!D68/'Data Sheet'!D$66 -> 0.12520038 | F39: ='Data Sheet'!E68/'Data Sheet'!E$66 -> 0.094636015 | G39: ='Data Sheet'!F68/'Data Sheet'!F$66 -> 0.136375 | H39: ='Data Sheet'!G68/'Data Sheet'!G$66 -> 0.18161286 | I39: ='Data Sheet'!H68/'Data Sheet'!H$66 -> 0.12757994 | J39: ='Data Sheet'!I68/'Data Sheet'!I$66 -> 0.13018078 | ... L39: ='Data Sheet'!K68/'Data Sheet'!K$66 -> 0.13833505
B40: ='Data Sheet'!A69 -> Cash & Bank | C40: ='Data Sheet'!B69/'Data Sheet'!B$66 -> 0.029447554 | D40: ='Data Sheet'!C69/'Data Sheet'!C$66 -> 0.035851966 | E40: ='Data Sheet'!D69/'Data Sheet'!D$66 -> 0.017633857 | F40: ='Data Sheet'!E69/'Data Sheet'!E$66 -> 0.015708812 | G40: ='Data Sheet'!F69/'Data Sheet'!F$66 -> 0.026375 | H40: ='Data Sheet'!G69/'Data Sheet'!G$66 -> 0.024578185 | I40: ='Data Sheet'!H69/'Data Sheet'!H$66 -> 0.021174206 | J40: ='Data Sheet'!I69/'Data Sheet'!I$66 -> 0.049162257 | ... L40: ='Data Sheet'!K69/'Data Sheet'!K$66 -> 0.036176773

Sheet Data Sheet
A1: COMPANY NAME | B1: BRITANNIA INDUSTRIES LTD | E1: =IF(B2<>B3, "A NEW VERSION OF THE WORKSHEET IS AVAILABLE", "")
A2: LATEST VERSION | B2: 2.1 | E2: PLEASE DO NOT MAKE ANY CHANGES TO THIS SHEET
A3: CURRENT VERSION | B3: 2.1
A5: META
A6: Number of shares | B6: =IF(B9>0, B9/B8, 0) -> 24.052546
A7: Face Value | B7: 1
A8: Current Price | B8: 4929
A9: Market Capitalization | B9: 118555
A15: PROFIT & LOSS
A16: Report Date | B16: 42795 | C16: 43160 | D16: 43525 | E16: 43891 | F16: 44256 | G16: 44621 | H16: 44986 | I16: 45352 | J16: 45717 | K16: 46082
A17: Sales | B17: 9054 | C17: 9914 | D17: 11055 | E17: 11600 | F17: 13136 | G17: 14136 | H17: 16301 | I17: 16769 | J17: 17943 | K17: 19152
A18: Raw Material Cost | B18: 5643 | C18: 6101 | D18: 6617 | E18: 6875 | F18: 7663 | G18: 8836 | H18: 9664 | I18: 9488 | J18: 10669 | K18: 11155
A19: Change in Inventory | B19: -54 | C19: 6 | D19: -55 | E19: 53 | F19: -37 | G19: -75 | H19: -73 | I19: 4 | J19: -65 | K19: -22
A20: Power and Fuel | B20: 0 | C20: 0 | D20: 0 | E20: 0 | F20: 0 | G20: 0 | H20: 0 | I20: 0 | J20: 0 | K20: 0
A21: Other Mfr. Exp | B21: 633.78 | C21: 594.84 | D21: 773.85 | E21: 812 | F21: 788.16 | G21: 989.52 | H21: 1141.07 | I21: 1173.83 | J21: 1256.01 | K21: 1340.64
A22: Employee Cost | B22: 362.16 | C22: 396.56 | D22: 442.2 | E22: 464 | F22: 525.44 | G22: 565.44 | H22: 652.04 | I22: 670.76 | J22: 717.72 | K22: 766.08
A23: Selling and admin | B23: 0 | C23: 0 | D23: 0 | E23: 0 | F23: 0 | G23: 0 | H23: 0 | I23: 0 | J23: 0 | K23: 0
A24: Other Expenses | B24: 1177.02 | C24: 1288.82 | D24: 1547.7 | E24: 1508 | F24: 1576.32 | G24: 1696.32 | H24: 2119.13 | I24: 2179.97 | J24: 2153.16 | K24: 2489.76
A25: Other Income | B25: 151 | C25: 166 | D25: 206 | E25: 263 | F25: 313 | G25: 222 | H25: 597 | I25: 211 | J25: 202 | K25: 224
A26: Depreciation | B26: 119 | C26: 142 | D26: 162 | E26: 185 | F26: 198 | G26: 201 | H26: 226 | I26: 300 | J26: 313 | K26: 337
A27: Interest | B27: 5 | C27: 8 | D27: 9 | E27: 77 | F27: 111 | G27: 144 | H27: 169 | I27: 164 | J27: 139 | K27: 113
... A31: Dividend Amount | B31: 265.5 | C31: 301.2 | D31: 358.05 | E31: 836.4 | F31: 3776.04 | G31: 1349.24 | H31: 1737 | I31: 1771.22 | J31: 1807.74 | K31: 2181.82
A32: EBITDA | B32: =SUM(B26:B28) -> 1428 | C32: =SUM(C26:C28) -> 1668 | D32: =SUM(D26:D28) -> 1939 | E32: =SUM(E26:E28) -> 2106 | F32: =SUM(F26:F28) -> 2823 | G32: =SUM(G26:G28) -> 2423 | H32: =SUM(H26:H28) -> 3428 | I32: =SUM(I26:I28) -> 3377 | ... K32: =SUM(K26:K28) -> 3739
A40: Quarters
A41: Report Date | B41: 45352 | C41: 45444 | D41: 45536 | E41: 45627 | F41: 45717 | G41: 45809 | H41: 45901 | I41: 45992 | J41: 46082 | K41: 46174
A42: Sales | B42: 4069 | C42: 4250 | D42: 4668 | E42: 4593 | F42: 4432 | G42: 4622 | H42: 4841 | I42: 4970 | J42: 4719 | K42: 5000
A43: Expenses | B43: 3286 | C43: 3497 | D43: 3888 | E43: 3750 | F43: 3632 | G43: 3870 | H43: 3889 | I43: 3992 | J43: 3885 | K43: 4162
A44: Other Income | B44: 57 | C44: 31 | D44: 46 | E44: 62 | F44: 63 | G44: 57 | H44: 52 | I44: 59 | J44: 55 | K44: 61
A45: Depreciation | B45: 80 | C45: 74 | D45: 76 | E45: 82 | F45: 81 | G45: 82 | H45: 85 | I45: 85 | J45: 85 | K45: 80
A46: Interest | B46: 26 | C46: 29 | D46: 35 | E46: 45 | F46: 31 | G46: 26 | H46: 35 | I46: 33 | J46: 19 | K46: 23
A47: Profit before tax | B47: 735 | C47: 681 | D47: 715 | E47: 778 | F47: 752 | G47: 701 | H47: 884 | I47: 919 | J47: 785 | K47: 797
A48: Tax | B48: 198 | C48: 176 | D48: 183 | E48: 196 | F48: 193 | G48: 181 | H48: 229 | I48: 237 | J48: 105 | K48: 204
A49: Net profit | B49: 537 | C49: 505 | D49: 532 | E49: 582 | F49: 559 | G49: 520 | H49: 655 | I49: 682 | J49: 680 | K49: 593
A50: Operating Profit | B50: 784 | C50: 753 | D50: 780 | E50: 843 | F50: 801 | G50: 752 | H50: 951 | I50: 977 | J50: 834 | K50: 838
A55: BALANCE SHEET
A56: Report Date | B56: 42795 | C56: 43160 | D56: 43525 | E56: 43891 | F56: 44256 | G56: 44621 | H56: 44986 | I56: 45352 | J56: 45717 | K56: 46082
A57: Equity Share Capital | B57: 24 | C57: 24 | D57: 24 | E57: 24 | F57: 24 | G57: 24 | H57: 24 | I57: 24 | J57: 24 | K57: 24
A58: Reserves | B58: 2672 | C58: 3382 | D58: 4229 | E58: 4379 | F58: 3524 | G58: 2534 | H58: 3510 | I58: 3917 | J58: 4332 | K58: 5082
A59: Borrowings | B59: 125 | C59: 201 | D59: 156 | E59: 1538 | F59: 2107 | G59: 2481 | H59: 2997 | I59: 2065 | J59: 1247 | K59: 1380
A60: Other Liabilities | B60: 1288 | C60: 1581 | D60: 1829 | E60: 1889 | F60: 2345 | G60: 2487 | H60: 2819 | I60: 3065 | J60: 3235 | K60: 3243
A61: Total | B61: 4109 | C61: 5188 | D61: 6238 | E61: 7830 | F61: 8000 | G61: 7527 | H61: 9351 | I61: 9072 | J61: 8837 | K61: 9730
A62: Net Block | B62: 1160 | C62: 1346 | D62: 1688 | E62: 1878 | F62: 1793 | G62: 1753 | H62: 2655 | I62: 2771 | J62: 2904 | K62: 2850
A63: Capital Work in Progress | B63: 30 | C63: 203 | D63: 101 | E63: 40 | F63: 117 | G63: 536 | H63: 105 | I63: 188 | J63: 89 | K63: 39
A64: Investments | B64: 487 | C64: 1079 | D64: 1476 | E64: 2893 | F64: 2781 | G64: 1762 | H64: 3324 | I64: 2767 | J64: 2865 | K64: 3610
A65: Other Assets | B65: 2432 | C65: 2560 | D65: 2972 | E65: 3019 | F65: 3310 | G65: 3475 | H65: 3266 | I65: 3346 | J65: 2978 | K65: 3232
A66: Total | B66: 4109 | C66: 5188 | D66: 6238 | E66: 7830 | F66: 8000 | G66: 7527 | H66: 9351 | I66: 9072 | J66: 8837 | K66: 9730
A67: Receivables | B67: 179 | C67: 305 | D67: 394 | E67: 320 | F67: 257 | G67: 332 | H67: 329 | I67: 393 | J67: 449 | K67: 469
... A70: No. of Equity Shares | B70: 240000000 | C70: 240000000 | D70: 240000000 | E70: 240000000 | F70: 240000000 | G70: 240000000 | H70: 240000000 | I70: 240000000 | J70: 240000000 | K70: 240000000
A71: New Bonus Shares
A72: Face value | B72: 1 | C72: 1 | D72: 1 | E72: 1 | F72: 1 | G72: 1 | H72: 1 | I72: 1 | J72: 1 | K72: 1
A73: Minority Interest | B73: 0 | C73: 0 | D73: 0 | E73: 0 | F73: 0 | G73: 0 | H73: 0 | I73: 0 | J73: 0 | K73: 29
B74: 0 | C74: 0 | D74: 0 | E74: 0 | F74: 0 | G74: 0 | H74: 0 | I74: 0 | J74: 0 | K74: 0
A75: Other Assets | B75: =B65-SUM(B67:B69) -> 1471 | C75: =C65-SUM(C67:C69) -> 1416 | D75: =D65-SUM(D67:D69) -> 1687 | E75: =E65-SUM(E67:E69) -> 1835 | F75: =F65-SUM(F67:F69) -> 1751 | G75: =G65-SUM(G67:G69) -> 1591 | H75: =H65-SUM(H67:H69) -> 1546 | I75: =I65-SUM(I67:I69) -> 1326 | ... K75: =K65-SUM(K67:K69) -> 1065
A80: CASH FLOW:
A81: Report Date | B81: 42795 | C81: 43160 | D81: 43525 | E81: 43891 | F81: 44256 | G81: 44621 | H81: 44986 | I81: 45352 | J81: 45717 | K81: 46082
A82: Cash from Operating Activity | B82: 441 | C82: 1249 | D82: 1156 | E82: 1485 | F82: 1851 | G82: 1300 | H82: 2526 | I82: 2573 | J82: 2491 | K82: 2612
A83: Cash from Investing Activity | B83: -150 | C83: -957 | D83: -852 | E83: -1526 | F83: 459 | G83: 914 | H83: -1507 | I83: 485 | J83: 69 | K83: -741
A84: Cash from Financing Activity | B84: -295 | C84: -232 | D84: -353 | E84: 58 | F84: -2244 | G84: -2246 | H84: -1028 | I84: -2839 | J84: -2754 | K84: -1783
A85: Net Cash Flow | B85: -4 | C85: 60 | D85: -49 | E85: 17 | F85: 66 | G85: -32 | H85: -9 | I85: 219 | J85: -194 | K85: 88
A90: PRICE: | B90: 1548.38 | C90: 2471.93 | D90: 3077.25 | E90: 2970.2 | F90: 3363.75 | G90: 3371.35 | H90: 4411.95 | I90: 4922.55 | J90: 4595.45 | K90: 6002.5
A92: DERIVED:
A93: Adjusted Equity Shares in Cr | B93: 24 | C93: 24 | D93: 24 | E93: 24 | F93: 24 | G93: 24 | H93: 24 | I93: 24 | J93: 24 | K93: 24

Sheet Cash Flow Statement
B2: Cash Flow Statement - BRITANNIA INDUSTRIES LTD
B4: Particulars | C4: 42064 | D4: 42430 | E4: 42795 | F4: 43160 | G4: 43525 | H4: 43891 | I4: 44256 | J4: 44621 | K4: 44986 | L4: 45352 | M4: 45717 | N4: 46082
B6: Cash from Operating Activity - | C6: 584 | D6: 959 | E6: 441 | F6: 1249 | G6: 1156 | H6: 1485 | I6: 1851 | J6: 1300 | K6: 2526 | L6: 2573 | M6: 2491 | N6: 2612
B7: Profit from operations | C7: 861 | D7: 1230 | E7: 1289 | F7: 1517 | G7: 1754 | H7: 1860 | I7: 2540 | J7: 2214 | K7: 2846 | L7: 3177 | M7: 3174 | N7: 3555
B8: Receivables | C8: -25 | D8: -32 | E8: -9 | F8: -125 | G8: -87 | H8: 79 | I8: 61 | J8: -72 | K8: 1 | L8: -64 | M8: -53 | N8: -13
B9: Inventory | C9: 17 | D9: -35 | E9: -221 | F9: 9 | G9: -127 | H9: 43 | I9: -351 | J9: -275 | K9: 177 | L9: 13 | M9: -54 | N9: -105
B10: Payables | C10: 0 | D10: 0 | E10: 0 | F10: 0 | G10: 0 | H10: 0 | I10: 0 | J10: 64 | K10: 292 | L10: 237 | M10: 202 | N10: 25
B11: Working capital changes | C11: 25 | D11: 133 | E11: -451 | F11: 228 | G11: -2 | H11: 127 | I11: -56 | J11: -327 | K11: 406 | L11: 161 | M11: 6 | N11: -121
B12: Direct taxes | C12: -301 | D12: -403 | E12: -397 | F12: -496 | G12: -596 | H12: -503 | I12: -633 | J12: -587 | K12: -726 | L12: -765 | M12: -689 | N12: -822
B13: Cash from Investing Activity - | C13: -450 | D13: -705 | E13: -150 | F13: -957 | G13: -852 | H13: -1526 | I13: 459 | J13: 914 | K13: -1507 | L13: 485 | M13: 69 | N13: -741
B14: Fixed assets purchased | C14: -118 | D14: -251 | E14: -360 | F14: -423 | G14: -401 | H14: -244 | I14: -242 | J14: -550 | K14: -711 | L14: -553 | M14: -375 | N14: -206
B15: Fixed assets sold | C15: 164 | D15: 1 | E15: 8 | F15: 2 | G15: 2 | H15: 1 | I15: 2 | J15: 3 | K15: 78 | L15: 65 | M15: 5 | N15: 2
B16: Investments purchased | C16: -277 | D16: -211 | E16: 0 | F16: -537 | G16: -334 | H16: -1327 | I16: 0 | J16: -21 | K16: -1468 | L16: -191 | M16: -945 | N16: -976
... B32: Net Cash Flow | C32: -47 | D32: 8 | E32: -4 | F32: 60 | G32: -49 | H32: 17 | I32: 66 | J32: -32 | K32: -9 | L32: 219 | M32: -194 | N32: 88

Sheet Historical FS
B2: ="Historical Financial Statement - "&'Data Sheet'!$B$1 -> Historical Financial Statement - BRITANNIA INDUSTRIES LTD
B3: Particulars | C3: ='Data Sheet'!B56 -> 42795 | D3: ='Data Sheet'!C56 -> 43160 | E3: ='Data Sheet'!D56 -> 43525 | F3: ='Data Sheet'!E56 -> 43891 | G3: ='Data Sheet'!F56 -> 44256 | H3: ='Data Sheet'!G56 -> 44621 | I3: ='Data Sheet'!H56 -> 44986 | J3: ='Data Sheet'!I56 -> 45352 | ... L3: ='Data Sheet'!K56 -> 46082 | M3: LTM
A5: # | B5: Income Statement
B7: Sales | C7: ='Data Sheet'!B17 -> 9054 | D7: ='Data Sheet'!C17 -> 9914 | E7: ='Data Sheet'!D17 -> 11055 | F7: ='Data Sheet'!E17 -> 11600 | G7: ='Data Sheet'!F17 -> 13136 | H7: ='Data Sheet'!G17 -> 14136 | I7: ='Data Sheet'!H17 -> 16301 | J7: ='Data Sheet'!I17 -> 16769 | ... L7: ='Data Sheet'!K17 -> 19152
B8: Sales Growth | C8: - | D8: =D7/C7-1 -> 0.094985642 | E8: =E7/D7-1 -> 0.11508977 | F8: =F7/E7-1 -> 0.04929896 | G8: =G7/F7-1 -> 0.13241379 | H8: =H7/G7-1 -> 0.076126675 | I8: =I7/H7-1 -> 0.15315507 | J8: =J7/I7-1 -> 0.028709895 | K8: =K7/J7-1 -> 0.070010138 | L8: =L7/K7-1 -> 0.067380037
B10: Cost of Goods Sold | C10: =SUM('Data Sheet'!B18,'Data Sheet'!B20:B22)-'Data Sheet'!B19 -> 6692.94 | D10: =SUM('Data Sheet'!C18,'Data Sheet'!C20:C22)-'Data Sheet'!C19 -> 7086.4 | E10: =SUM('Data Sheet'!D18,'Data Sheet'!D20:D22)-'Data Sheet'!D19 -> 7888.05 | F10: =SUM('Data Sheet'!E18,'Data Sheet'!E20:E22)-'Data Sheet'!E19 -> 8098 | G10: =SUM('Data Sheet'!F18,'Data Sheet'!F20:F22)-'Data Sheet'!F19 -> 9013.6 | H10: =SUM('Data Sheet'!G18,'Data Sheet'!G20:G22)-'Data Sheet'!G19 -> 10465.96 | I10: =SUM('Data Sheet'!H18,'Data Sheet'!H20:H22)-'Data Sheet'!H19 -> 11530.11 | J10: =SUM('Data Sheet'!I18,'Data Sheet'!I20:I22)-'Data Sheet'!I19 -> 11328.59 | ... L10: =SUM('Data Sheet'!K18,'Data Sheet'!K20:K22)-'Data Sheet'!K19 -> 13283.72
B11: COGS % Sales | C11: =C10/C7 -> 0.73922465 | D11: =D10/D7 -> 0.71478717 | E11: =E10/E7 -> 0.71352782 | F11: =F10/F7 -> 0.69810345 | G11: =G10/G7 -> 0.6861754 | H11: =H10/H7 -> 0.74037634 | I11: =I10/I7 -> 0.70732532 | J11: =J10/J7 -> 0.67556742 | ... L11: =L10/L7 -> 0.6935944
B13: Gross Profit | C13: =C7-C10 -> 2361.06 | D13: =D7-D10 -> 2827.6 | E13: =E7-E10 -> 3166.95 | F13: =F7-F10 -> 3502 | G13: =G7-G10 -> 4122.4 | H13: =H7-H10 -> 3670.04 | I13: =I7-I10 -> 4770.89 | J13: =J7-J10 -> 5440.41 | ... L13: =L7-L10 -> 5868.28
B14: Gross Profit % Sales | C14: =C13/C7 -> 0.26077535 | D14: =D13/D7 -> 0.28521283 | E14: =E13/E7 -> 0.28647218 | F14: =F13/F7 -> 0.30189655 | G14: =G13/G7 -> 0.3138246 | H14: =H13/H7 -> 0.25962366 | I14: =I13/I7 -> 0.29267468 | J14: =J13/J7 -> 0.32443258 | ... L14: =L13/L7 -> 0.3064056
B16: Selling % General Expenses | C16: ='Data Sheet'!B23+'Data Sheet'!B24 -> 1177.02 | D16: ='Data Sheet'!C23+'Data Sheet'!C24 -> 1288.82 | E16: ='Data Sheet'!D23+'Data Sheet'!D24 -> 1547.7 | F16: ='Data Sheet'!E23+'Data Sheet'!E24 -> 1508 | G16: ='Data Sheet'!F23+'Data Sheet'!F24 -> 1576.32 | H16: ='Data Sheet'!G23+'Data Sheet'!G24 -> 1696.32 | I16: ='Data Sheet'!H23+'Data Sheet'!H24 -> 2119.13 | J16: ='Data Sheet'!I23+'Data Sheet'!I24 -> 2179.97 | ... O16: ='Data Sheet'!N23+'Data Sheet'!N24 -> 0
B17: S&G % Sales | C17: =C16/C7 -> 0.13 | D17: =D16/D7 -> 0.13 | E17: =E16/E7 -> 0.14 | F17: =F16/F7 -> 0.13 | G17: =G16/G7 -> 0.12 | H17: =H16/H7 -> 0.12 | I17: =I16/I7 -> 0.13 | J17: =J16/J7 -> 0.13 | ... L17: =L16/L7 -> 0.13
B19: EBITDA | C19: =C13-C16 -> 1184.04 | D19: =D13-D16 -> 1538.78 | E19: =E13-E16 -> 1619.25 | F19: =F13-F16 -> 1994 | G19: =G13-G16 -> 2546.08 | H19: =H13-H16 -> 1973.72 | I19: =I13-I16 -> 2651.76 | J19: =J13-J16 -> 3260.44 | ... L19: =L13-L16 -> 3378.52
B20: EBITDA % Sales | C20: =C19/C7 -> 0.13077535 | D20: =D19/D7 -> 0.15521283 | E20: =E19/E7 -> 0.14647218 | F20: =F19/F7 -> 0.17189655 | G20: =G19/G7 -> 0.1938246 | H20: =H19/H7 -> 0.13962366 | I20: =I19/I7 -> 0.16267468 | J20: =J19/J7 -> 0.19443258 | ... L20: =L19/L7 -> 0.1764056
B22: Depreciation | C22: ='Data Sheet'!B26 -> 119 | D22: ='Data Sheet'!C26 -> 142 | E22: ='Data Sheet'!D26 -> 162 | F22: ='Data Sheet'!E26 -> 185 | G22: ='Data Sheet'!F26 -> 198 | H22: ='Data Sheet'!G26 -> 201 | I22: ='Data Sheet'!H26 -> 226 | J22: ='Data Sheet'!I26 -> 300 | ... L22: ='Data Sheet'!K26 -> 337
B23: Depreciation % Sales | C23: =C22/C7 -> 0.013143362 | D23: =D22/D7 -> 0.014323179 | E23: =E22/E7 -> 0.014654003 | F23: =F22/F7 -> 0.015948276 | G23: =G22/G7 -> 0.015073082 | H23: =H22/H7 -> 0.014219015 | I23: =I22/I7 -> 0.01386418 | J23: =J22/J7 -> 0.017890154 | ... L23: =L22/L7 -> 0.017596074
B25: EBIT | C25: =C19-C22 -> 1065.04 | D25: =D19-D22 -> 1396.78 | E25: =E19-E22 -> 1457.25 | F25: =F19-F22 -> 1809 | G25: =G19-G22 -> 2348.08 | H25: =H19-H22 -> 1772.72 | I25: =I19-I22 -> 2425.76 | J25: =J19-J22 -> 2960.44 | ... L25: =L19-L22 -> 3041.52
B26: EBIT % Sales | C26: =C25/C7 -> 0.11763199 | D26: =D25/D7 -> 0.14088965 | E26: =E25/E7 -> 0.13181818 | F26: =F25/F7 -> 0.15594828 | G26: =G25/G7 -> 0.17875152 | H26: =H25/H7 -> 0.12540464 | I26: =I25/I7 -> 0.1488105 | J26: =J25/J7 -> 0.17654243 | ... L26: =L25/L7 -> 0.15880952
B28: Interest | C28: ='Data Sheet'!B27 -> 5 | D28: ='Data Sheet'!C27 -> 8 | E28: ='Data Sheet'!D27 -> 9 | F28: ='Data Sheet'!E27 -> 77 | G28: ='Data Sheet'!F27 -> 111 | H28: ='Data Sheet'!G27 -> 144 | I28: ='Data Sheet'!H27 -> 169 | J28: ='Data Sheet'!I27 -> 164 | ... L28: ='Data Sheet'!K27 -> 113
B29: Interest % Sales | C29: =C28/C7 -> 0.0005522421 | D29: =D28/D7 -> 0.00080693968 | E29: =E28/E7 -> 0.00081411126 | F29: =F28/F7 -> 0.006637931 | G29: =G28/G7 -> 0.0084500609 | H29: =H28/H7 -> 0.010186757 | I29: =I28/I7 -> 0.010367462 | J29: =J28/J7 -> 0.0097799511 | ... L29: =L28/L7 -> 0.0059001671
B31: Earning Before Tax | C31: =C25-C28 -> 1060.04 | D31: =D25-D28 -> 1388.78 | E31: =E25-E28 -> 1448.25 | F31: =F25-F28 -> 1732 | G31: =G25-G28 -> 2237.08 | H31: =H25-H28 -> 1628.72 | I31: =I25-I28 -> 2256.76 | J31: =J25-J28 -> 2796.44 | ... L31: =L25-L28 -> 2928.52
B32: EBT % Sales | C32: =C31/C7 -> 0.11707974 | D32: =D31/D7 -> 0.14008271 | E32: =E31/E7 -> 0.13100407 | F32: =F31/F7 -> 0.14931034 | G32: =G31/G7 -> 0.17030146 | H32: =H31/H7 -> 0.11521788 | I32: =I31/I7 -> 0.13844304 | J32: =J31/J7 -> 0.16676248 | ... L32: =L31/L7 -> 0.15290936
B34: Tax Rate | C34: ='Data Sheet'!B29 -> 419 | D34: ='Data Sheet'!C29 -> 514 | E34: ='Data Sheet'!D29 -> 613 | F34: ='Data Sheet'!E29 -> 450 | G34: ='Data Sheet'!F29 -> 663 | H34: ='Data Sheet'!G29 -> 562 | I34: ='Data Sheet'!H29 -> 717 | J34: ='Data Sheet'!I29 -> 779 | ... L34: ='Data Sheet'!K29 -> 752
B35: Effective Tax Rate | C35: =C34/C31 -> 0.3952681 | D35: =D34/D31 -> 0.37010902 | E35: =E34/E31 -> 0.42326946 | F35: =F34/F31 -> 0.25981524 | G35: =G34/G31 -> 0.29636848 | H35: =H34/H31 -> 0.34505624 | I35: =I34/I31 -> 0.31771212 | J35: =J34/J31 -> 0.27856847 | ... L35: =L34/L31 -> 0.256785
B37: Net Profit | C37: =C31-C34 -> 641.04 | D37: =D31-D34 -> 874.78 | E37: =E31-E34 -> 835.25 | F37: =F31-F34 -> 1282 | G37: =G31-G34 -> 1574.08 | H37: =H31-H34 -> 1066.72 | I37: =I31-I34 -> 1539.76 | J37: =J31-J34 -> 2017.44 | ... L37: =L31-L34 -> 2176.52
B38: Net Profit % Sales | C38: =C37/C7 -> 0.070801856 | D38: =D37/D7 -> 0.088236837 | E38: =E37/E7 -> 0.075554048 | F38: =F37/F7 -> 0.11051724 | G38: =G37/G7 -> 0.11982948 | H38: =H37/H7 -> 0.075461234 | I38: =I37/I7 -> 0.094458009 | J38: =J37/J7 -> 0.12030771 | ... L38: =L37/L7 -> 0.11364453
B40: No. of Equity Shares | C40: ='Data Sheet'!B93 -> 24 | D40: ='Data Sheet'!C93 -> 24 | E40: ='Data Sheet'!D93 -> 24 | F40: ='Data Sheet'!E93 -> 24 | G40: ='Data Sheet'!F93 -> 24 | H40: ='Data Sheet'!G93 -> 24 | I40: ='Data Sheet'!H93 -> 24 | J40: ='Data Sheet'!I93 -> 24 | ... L40: ='Data Sheet'!K93 -> 24
B42: Earning per Share | C42: =C37/C40 -> 26.71 | D42: =D37/D40 -> 36.449167 | E42: =E37/E40 -> 34.802083 | F42: =F37/F40 -> 53.416667 | G42: =G37/G40 -> 65.586667 | H42: =H37/H40 -> 44.446667 | I42: =I37/I40 -> 64.156667 | J42: =J37/J40 -> 84.06 | ... L42: =L37/L40 -> 90.688333
B43: EPS Growth | C43: - | D43: =D42/C42-1 -> 0.36462623 | E43: =E42/D42-1 -> -0.045188505 | F43: =F42/E42-1 -> 0.5348698 | G43: =G42/F42-1 -> 0.22783151 | H43: =H42/G42-1 -> -0.32232161 | I43: =I42/H42-1 -> 0.44345283 | J43: =J42/I42-1 -> 0.31023017 | K43: =K42/J42-1 -> -0.06757574 | L43: =L42/K42-1 -> 0.15704026
B45: Dividend per Share | C45: ='Data Sheet'!B31/'Historical FS'!C40 -> 11.0625 | D45: ='Data Sheet'!C31/'Historical FS'!D40 -> 12.55 | E45: ='Data Sheet'!D31/'Historical FS'!E40 -> 14.91875 | F45: ='Data Sheet'!E31/'Historical FS'!F40 -> 34.85 | G45: ='Data Sheet'!F31/'Historical FS'!G40 -> 157.335 | H45: ='Data Sheet'!G31/'Historical FS'!H40 -> 56.218333 | I45: ='Data Sheet'!H31/'Historical FS'!I40 -> 72.375 | J45: ='Data Sheet'!I31/'Historical FS'!J40 -> 73.800833 | ... L45: ='Data Sheet'!K31/'Historical FS'!L40 -> 90.909167
B46: Dividend Payout Ratio | C46: =C45/C42 -> 0.41417072 | D46: =D45/D42 -> 0.34431514 | E46: =E45/E42 -> 0.42867405 | F46: =F45/F42 -> 0.6524181 | G46: =G45/G42 -> 2.398887 | H46: =H45/H42 -> 1.2648493 | I46: =I45/I42 -> 1.1280979 | J46: =J45/J42 -> 0.87795424 | ... L46: =L45/L42 -> 1.0024351
B48: Retained Earnings | C48: =(1-C46) -> 0.58582928 | D48: =(1-D46) -> 0.65568486 | E48: =(1-E46) -> 0.57132595 | F48: =(1-F46) -> 0.3475819 | G48: =(1-G46) -> -1.398887 | H48: =(1-H46) -> -0.26484926 | I48: =(1-I46) -> -0.12809789 | J48: =(1-J46) -> 0.12204576 | ... L48: =(1-L46) -> -0.0024350799
B50: Balance Sheet
B51: ='Data Sheet'!A57 -> Equity Share Capital | C51: ='Data Sheet'!B57 -> 24 | D51: ='Data Sheet'!C57 -> 24 | E51: ='Data Sheet'!D57 -> 24 | F51: ='Data Sheet'!E57 -> 24 | G51: ='Data Sheet'!F57 -> 24 | H51: ='Data Sheet'!G57 -> 24 | I51: ='Data Sheet'!H57 -> 24 | ... L51: ='Data Sheet'!K57 -> 24
B52: ='Data Sheet'!A58 -> Reserves | C52: ='Data Sheet'!B58 -> 2672 | D52: ='Data Sheet'!C58 -> 3382 | E52: ='Data Sheet'!D58 -> 4229 | F52: ='Data Sheet'!E58 -> 4379 | G52: ='Data Sheet'!F58 -> 3524 | H52: ='Data Sheet'!G58 -> 2534 | I52: ='Data Sheet'!H58 -> 3510 | ... L52: ='Data Sheet'!K58 -> 5082
B53: ='Data Sheet'!A59 -> Borrowings | C53: ='Data Sheet'!B59 -> 125 | D53: ='Data Sheet'!C59 -> 201 | E53: ='Data Sheet'!D59 -> 156 | F53: ='Data Sheet'!E59 -> 1538 | G53: ='Data Sheet'!F59 -> 2107 | H53: ='Data Sheet'!G59 -> 2481 | I53: ='Data Sheet'!H59 -> 2997 | ... L53: ='Data Sheet'!K59 -> 1380
B54: ='Data Sheet'!A60 -> Other Liabilities | C54: ='Data Sheet'!B60 -> 1288 | D54: ='Data Sheet'!C60 -> 1581 | E54: ='Data Sheet'!D60 -> 1829 | F54: ='Data Sheet'!E60 -> 1889 | G54: ='Data Sheet'!F60 -> 2345 | H54: ='Data Sheet'!G60 -> 2487 | I54: ='Data Sheet'!H60 -> 2819 | ... L54: ='Data Sheet'!K60 -> 3243
B55: Total Liabilities | C55: =SUM(C51:C54) -> 4109 | D55: =SUM(D51:D54) -> 5188 | E55: =SUM(E51:E54) -> 6238 | F55: =SUM(F51:F54) -> 7830 | G55: =SUM(G51:G54) -> 8000 | H55: =SUM(H51:H54) -> 7526 | I55: =SUM(I51:I54) -> 9350 | J55: =SUM(J51:J54) -> 9071 | ... L55: =SUM(L51:L54) -> 9729
B57: Fixed Asset Net Block | C57: ='Data Sheet'!B62 -> 1160 | D57: ='Data Sheet'!C62 -> 1346 | E57: ='Data Sheet'!D62 -> 1688 | F57: ='Data Sheet'!E62 -> 1878 | G57: ='Data Sheet'!F62 -> 1793 | H57: ='Data Sheet'!G62 -> 1753 | I57: ='Data Sheet'!H62 -> 2655 | J57: ='Data Sheet'!I62 -> 2771 | ... L57: ='Data Sheet'!K62 -> 2850
B58: ='Data Sheet'!A63 -> Capital Work in Progress | C58: ='Data Sheet'!B63 -> 30 | D58: ='Data Sheet'!C63 -> 203 | E58: ='Data Sheet'!D63 -> 101 | F58: ='Data Sheet'!E63 -> 40 | G58: ='Data Sheet'!F63 -> 117 | H58: ='Data Sheet'!G63 -> 536 | I58: ='Data Sheet'!H63 -> 105 | ... L58: ='Data Sheet'!K63 -> 39
B59: ='Data Sheet'!A64 -> Investments | C59: ='Data Sheet'!B64 -> 487 | D59: ='Data Sheet'!C64 -> 1079 | E59: ='Data Sheet'!D64 -> 1476 | F59: ='Data Sheet'!E64 -> 2893 | G59: ='Data Sheet'!F64 -> 2781 | H59: ='Data Sheet'!G64 -> 1762 | I59: ='Data Sheet'!H64 -> 3324 | ... L59: ='Data Sheet'!K64 -> 3610
B60: ='Data Sheet'!A65 -> Other Assets | C60: ='Data Sheet'!B75 -> 1471 | D60: ='Data Sheet'!C75 -> 1416 | E60: ='Data Sheet'!D75 -> 1687 | F60: ='Data Sheet'!E75 -> 1835 | G60: ='Data Sheet'!F75 -> 1751 | H60: ='Data Sheet'!G75 -> 1591 | I60: ='Data Sheet'!H75 -> 1546 | J60: ='Data Sheet'!I75 -> 1326 | ... O60: ='Data Sheet'!N75 -> 0
B61: Total Non Current Assets | C61: =SUM(C57:C60) -> 3148 | D61: =SUM(D57:D60) -> 4044 | E61: =SUM(E57:E60) -> 4952 | F61: =SUM(F57:F60) -> 6646 | G61: =SUM(G57:G60) -> 6442 | H61: =SUM(H57:H60) -> 5642 | I61: =SUM(I57:I60) -> 7630 | J61: =SUM(J57:J60) -> 7052 | ... L61: =SUM(L57:L60) -> 7564
B63: ='Data Sheet'!A67 -> Receivables | C63: ='Data Sheet'!B67 -> 179 | D63: ='Data Sheet'!C67 -> 305 | E63: ='Data Sheet'!D67 -> 394 | F63: ='Data Sheet'!E67 -> 320 | G63: ='Data Sheet'!F67 -> 257 | H63: ='Data Sheet'!G67 -> 332 | I63: ='Data Sheet'!H67 -> 329 | ... L63: ='Data Sheet'!K67 -> 469
B64: ='Data Sheet'!A68 -> Inventory | C64: ='Data Sheet'!B68 -> 661 | D64: ='Data Sheet'!C68 -> 653 | E64: ='Data Sheet'!D68 -> 781 | F64: ='Data Sheet'!E68 -> 741 | G64: ='Data Sheet'!F68 -> 1091 | H64: ='Data Sheet'!G68 -> 1367 | I64: ='Data Sheet'!H68 -> 1193 | ... L64: ='Data Sheet'!K68 -> 1346
B65: ='Data Sheet'!A69 -> Cash & Bank | C65: ='Data Sheet'!B69 -> 121 | D65: ='Data Sheet'!C69 -> 186 | E65: ='Data Sheet'!D69 -> 110 | F65: ='Data Sheet'!E69 -> 123 | G65: ='Data Sheet'!F69 -> 211 | H65: ='Data Sheet'!G69 -> 185 | I65: ='Data Sheet'!H69 -> 198 | ... L65: ='Data Sheet'!K69 -> 352
B66: Total Current Assets | C66: =SUM(C63:C65) -> 961 | D66: =SUM(D63:D65) -> 1144 | E66: =SUM(E63:E65) -> 1285 | F66: =SUM(F63:F65) -> 1184 | G66: =SUM(G63:G65) -> 1559 | H66: =SUM(H63:H65) -> 1884 | I66: =SUM(I63:I65) -> 1720 | J66: =SUM(J63:J65) -> 2020 | ... L66: =SUM(L63:L65) -> 2167
B68: Total Assets | C68: =C61+C66 -> 4109 | D68: =D61+D66 -> 5188 | E68: =E61+E66 -> 6237 | F68: =F61+F66 -> 7830 | G68: =G61+G66 -> 8001 | H68: =H61+H66 -> 7526 | I68: =I61+I66 -> 9350 | J68: =J61+J66 -> 9072 | ... L68: =L61+L66 -> 9731
B70: Check | C70: =C68=C55 -> TRUE | D70: =D68=D55 -> TRUE | E70: =E68=E55 -> FALSE | F70: =F68=F55 -> TRUE | G70: =G68=G55 -> FALSE | H70: =H68=H55 -> TRUE | I70: =I68=I55 -> TRUE | J70: =J68=J55 -> FALSE | ... L70: =L68=L55 -> FALSE
B72: Cash Flow Statement
B73: Operating Activity
B74: ='Cash Flow Statement'!B7 -> Profit from operations | C74: ='Cash Flow Statement'!E7 -> 1289 | D74: ='Cash Flow Statement'!F7 -> 1517 | E74: ='Cash Flow Statement'!G7 -> 1754 | F74: ='Cash Flow Statement'!H7 -> 1860 | G74: ='Cash Flow Statement'!I7 -> 2540 | H74: ='Cash Flow Statement'!J7 -> 2214 | I74: ='Cash Flow Statement'!K7 -> 2846 | J74: ='Cash Flow Statement'!L7 -> 3177 | ... L74: ='Cash Flow Statement'!N7 -> 3555
B75: ='Cash Flow Statement'!B8 -> Receivables | C75: ='Cash Flow Statement'!E8 -> -9 | D75: ='Cash Flow Statement'!F8 -> -125 | E75: ='Cash Flow Statement'!G8 -> -87 | F75: ='Cash Flow Statement'!H8 -> 79 | G75: ='Cash Flow Statement'!I8 -> 61 | H75: ='Cash Flow Statement'!J8 -> -72 | I75: ='Cash Flow Statement'!K8 -> 1 | J75: ='Cash Flow Statement'!L8 -> -64 | ... L75: ='Cash Flow Statement'!N8 -> -13
B76: ='Cash Flow Statement'!B9 -> Inventory | C76: ='Cash Flow Statement'!E9 -> -221 | D76: ='Cash Flow Statement'!F9 -> 9 | E76: ='Cash Flow Statement'!G9 -> -127 | F76: ='Cash Flow Statement'!H9 -> 43 | G76: ='Cash Flow Statement'!I9 -> -351 | H76: ='Cash Flow Statement'!J9 -> -275 | I76: ='Cash Flow Statement'!K9 -> 177 | J76: ='Cash Flow Statement'!L9 -> 13 | ... L76: ='Cash Flow Statement'!N9 -> -105
B77: ='Cash Flow Statement'!B10 -> Payables | C77: ='Cash Flow Statement'!E10 -> 0 | D77: ='Cash Flow Statement'!F10 -> 0 | E77: ='Cash Flow Statement'!G10 -> 0 | F77: ='Cash Flow Statement'!H10 -> 0 | G77: ='Cash Flow Statement'!I10 -> 0 | H77: ='Cash Flow Statement'!J10 -> 64 | I77: ='Cash Flow Statement'!K10 -> 292 | J77: ='Cash Flow Statement'!L10 -> 237 | ... L77: ='Cash Flow Statement'!N10 -> 25
B78: ='Cash Flow Statement'!B11 -> Working capital changes | C78: ='Cash Flow Statement'!E11 -> -451 | D78: ='Cash Flow Statement'!F11 -> 228 | E78: ='Cash Flow Statement'!G11 -> -2 | F78: ='Cash Flow Statement'!H11 -> 127 | G78: ='Cash Flow Statement'!I11 -> -56 | H78: ='Cash Flow Statement'!J11 -> -327 | I78: ='Cash Flow Statement'!K11 -> 406 | J78: ='Cash Flow Statement'!L11 -> 161 | ... L78: ='Cash Flow Statement'!N11 -> -121
B79: ='Cash Flow Statement'!B12 -> Direct taxes | C79: ='Cash Flow Statement'!E12 -> -397 | D79: ='Cash Flow Statement'!F12 -> -496 | E79: ='Cash Flow Statement'!G12 -> -596 | F79: ='Cash Flow Statement'!H12 -> -503 | G79: ='Cash Flow Statement'!I12 -> -633 | H79: ='Cash Flow Statement'!J12 -> -587 | I79: ='Cash Flow Statement'!K12 -> -726 | J79: ='Cash Flow Statement'!L12 -> -765 | ... L79: ='Cash Flow Statement'!N12 -> -822
B80: Cash From Operating Activities | C80: =SUM(C74:C79) -> 211 | D80: =SUM(D74:D79) -> 1133 | E80: =SUM(E74:E79) -> 942 | F80: =SUM(F74:F79) -> 1606 | G80: =SUM(G74:G79) -> 1561 | H80: =SUM(H74:H79) -> 1017 | I80: =SUM(I74:I79) -> 2996 | J80: =SUM(J74:J79) -> 2759 | ... L80: =SUM(L74:L79) -> 2519
B82: Investing Activities
B83: ='Cash Flow Statement'!B14 -> Fixed assets purchased | C83: ='Cash Flow Statement'!E14 -> -360 | D83: ='Cash Flow Statement'!F14 -> -423 | E83: ='Cash Flow Statement'!G14 -> -401 | F83: ='Cash Flow Statement'!H14 -> -244 | G83: ='Cash Flow Statement'!I14 -> -242 | H83: ='Cash Flow Statement'!J14 -> -550 | I83: ='Cash Flow Statement'!K14 -> -711 | J83: ='Cash Flow Statement'!L14 -> -553 | ... L83: ='Cash Flow Statement'!N14 -> -206
B84: ='Cash Flow Statement'!B15 -> Fixed assets sold | C84: ='Cash Flow Statement'!E15 -> 8 | D84: ='Cash Flow Statement'!F15 -> 2 | E84: ='Cash Flow Statement'!G15 -> 2 | F84: ='Cash Flow Statement'!H15 -> 1 | G84: ='Cash Flow Statement'!I15 -> 2 | H84: ='Cash Flow Statement'!J15 -> 3 | I84: ='Cash Flow Statement'!K15 -> 78 | J84: ='Cash Flow Statement'!L15 -> 65 | ... L84: ='Cash Flow Statement'!N15 -> 2
B85: ='Cash Flow Statement'!B16 -> Investments purchased | C85: ='Cash Flow Statement'!E16 -> 0 | D85: ='Cash Flow Statement'!F16 -> -537 | E85: ='Cash Flow Statement'!G16 -> -334 | F85: ='Cash Flow Statement'!H16 -> -1327 | G85: ='Cash Flow Statement'!I16 -> 0 | H85: ='Cash Flow Statement'!J16 -> -21 | I85: ='Cash Flow Statement'!K16 -> -1468 | J85: ='Cash Flow Statement'!L16 -> -191 | ... L85: ='Cash Flow Statement'!N16 -> -976
B86: ='Cash Flow Statement'!B17 -> Investments sold | C86: ='Cash Flow Statement'!E17 -> 359 | D86: ='Cash Flow Statement'!F17 -> 0 | E86: ='Cash Flow Statement'!G17 -> 0 | F86: ='Cash Flow Statement'!H17 -> 0 | G86: ='Cash Flow Statement'!I17 -> 179 | H86: ='Cash Flow Statement'!J17 -> 1069 | I86: ='Cash Flow Statement'!K17 -> 443 | J86: ='Cash Flow Statement'!L17 -> 771 | ... L86: ='Cash Flow Statement'!N17 -> 254
B87: ='Cash Flow Statement'!B18 -> Interest received | C87: ='Cash Flow Statement'!E18 -> 75 | D87: ='Cash Flow Statement'!F18 -> 109 | E87: ='Cash Flow Statement'!G18 -> 117 | F87: ='Cash Flow Statement'!H18 -> 128 | G87: ='Cash Flow Statement'!I18 -> 233 | H87: ='Cash Flow Statement'!J18 -> 207 | I87: ='Cash Flow Statement'!K18 -> 175 | J87: ='Cash Flow Statement'!L18 -> 170 | ... L87: ='Cash Flow Statement'!N18 -> 143
B88: ='Cash Flow Statement'!B19 -> Dividends received | C88: ='Cash Flow Statement'!E19 -> 0 | D88: ='Cash Flow Statement'!F19 -> 0 | E88: ='Cash Flow Statement'!G19 -> 0 | F88: ='Cash Flow Statement'!H19 -> 0 | G88: ='Cash Flow Statement'!I19 -> 0 | H88: ='Cash Flow Statement'!J19 -> 0 | I88: ='Cash Flow Statement'!K19 -> 0 | J88: ='Cash Flow Statement'!L19 -> 0 | ... L88: ='Cash Flow Statement'!N19 -> 0
B89: ='Cash Flow Statement'!B20 -> Invest in subsidiaries | C89: ='Cash Flow Statement'!E20 -> 0 | D89: ='Cash Flow Statement'!F20 -> 0 | E89: ='Cash Flow Statement'!G20 -> 0 | F89: ='Cash Flow Statement'!H20 -> 0 | G89: ='Cash Flow Statement'!I20 -> 0 | H89: ='Cash Flow Statement'!J20 -> 0 | I89: ='Cash Flow Statement'!K20 -> 0 | J89: ='Cash Flow Statement'!L20 -> 0 | ... L89: ='Cash Flow Statement'!N20 -> 0
B90: ='Cash Flow Statement'!B21 -> Investment in group cos | C90: ='Cash Flow Statement'!E21 -> -14 | D90: ='Cash Flow Statement'!F21 -> 0 | E90: ='Cash Flow Statement'!G21 -> 0 | F90: ='Cash Flow Statement'!H21 -> 0 | G90: ='Cash Flow Statement'!I21 -> 0 | H90: ='Cash Flow Statement'!J21 -> 0 | I90: ='Cash Flow Statement'!K21 -> -215 | J90: ='Cash Flow Statement'!L21 -> 0 | ... L90: ='Cash Flow Statement'!N21 -> 0
B91: ='Cash Flow Statement'!B22 -> Redemp n Canc of Shares | C91: ='Cash Flow Statement'!E22 -> 0 | D91: ='Cash Flow Statement'!F22 -> 0 | E91: ='Cash Flow Statement'!G22 -> 0 | F91: ='Cash Flow Statement'!H22 -> 0 | G91: ='Cash Flow Statement'!I22 -> 0 | H91: ='Cash Flow Statement'!J22 -> 0 | I91: ='Cash Flow Statement'!K22 -> 262 | J91: ='Cash Flow Statement'!L22 -> 0 | ... L91: ='Cash Flow Statement'!N22 -> 0
B92: ='Cash Flow Statement'!B23 -> Other investing items | C92: ='Cash Flow Statement'!E23 -> 0 | D92: ='Cash Flow Statement'!F23 -> 0 | E92: ='Cash Flow Statement'!G23 -> 3 | F92: ='Cash Flow Statement'!H23 -> 6 | G92: ='Cash Flow Statement'!I23 -> -2 | H92: ='Cash Flow Statement'!J23 -> 5 | I92: ='Cash Flow Statement'!K23 -> -159 | J92: ='Cash Flow Statement'!L23 -> -27 | ... L92: ='Cash Flow Statement'!N23 -> 55
B93: Cash From Investing Activities | C93: =SUM(C83:C92) -> 68 | D93: =SUM(D83:D92) -> -849 | E93: =SUM(E83:E92) -> -613 | F93: =SUM(F83:F92) -> -1436 | G93: =SUM(G83:G92) -> 170 | H93: =SUM(H83:H92) -> 713 | I93: =SUM(I83:I92) -> -1595 | J93: =SUM(J83:J92) -> 235 | ... L93: =SUM(L83:L92) -> -728
B95: Financing Activities
B96: ='Cash Flow Statement'!B25 -> Proceeds from shares | C96: ='Cash Flow Statement'!E25 -> 6 | D96: ='Cash Flow Statement'!F25 -> 15 | E96: ='Cash Flow Statement'!G25 -> 30 | F96: ='Cash Flow Statement'!H25 -> 24 | G96: ='Cash Flow Statement'!I25 -> 103 | H96: ='Cash Flow Statement'!J25 -> 0 | I96: ='Cash Flow Statement'!K25 -> 0 | J96: ='Cash Flow Statement'!L25 -> 0 | ... L96: ='Cash Flow Statement'!N25 -> 0
B97: ='Cash Flow Statement'!B26 -> Proceeds from borrowings | C97: ='Cash Flow Statement'!E26 -> 0 | D97: ='Cash Flow Statement'!F26 -> 0 | E97: ='Cash Flow Statement'!G26 -> 0 | F97: ='Cash Flow Statement'!H26 -> 641 | G97: ='Cash Flow Statement'!I26 -> 568 | H97: ='Cash Flow Statement'!J26 -> 645 | I97: ='Cash Flow Statement'!K26 -> 1312 | J97: ='Cash Flow Statement'!L26 -> 201 | ... L97: ='Cash Flow Statement'!N26 -> 324
B98: ='Cash Flow Statement'!B27 -> Repayment of borrowings | C98: ='Cash Flow Statement'!E27 -> 0 | D98: ='Cash Flow Statement'!F27 -> 0 | E98: ='Cash Flow Statement'!G27 -> -42 | F98: ='Cash Flow Statement'!H27 -> 0 | G98: ='Cash Flow Statement'!I27 -> 0 | H98: ='Cash Flow Statement'!J27 -> -984 | I98: ='Cash Flow Statement'!K27 -> -70 | J98: ='Cash Flow Statement'!L27 -> -1141 | ... L98: ='Cash Flow Statement'!N27 -> -192
B99: ='Cash Flow Statement'!B28 -> Interest paid fin | C99: ='Cash Flow Statement'!E28 -> -6 | D99: ='Cash Flow Statement'!F28 -> -7 | E99: ='Cash Flow Statement'!G28 -> -9 | F99: ='Cash Flow Statement'!H28 -> -36 | G99: ='Cash Flow Statement'!I28 -> -102 | H99: ='Cash Flow Statement'!J28 -> -119 | I99: ='Cash Flow Statement'!K28 -> -196 | J99: ='Cash Flow Statement'!L28 -> -165 | ... L99: ='Cash Flow Statement'!N28 -> -108
B100: ='Cash Flow Statement'!B29 -> Dividends paid | C100: ='Cash Flow Statement'!E29 -> -288 | D100: ='Cash Flow Statement'!F29 -> -317 | E100: ='Cash Flow Statement'!G29 -> -354 | F100: ='Cash Flow Statement'!H29 -> -433 | G100: ='Cash Flow Statement'!I29 -> -2824 | H100: ='Cash Flow Statement'!J29 -> -2485 | I100: ='Cash Flow Statement'!K29 -> -1359 | J100: ='Cash Flow Statement'!L29 -> -1732 | ... L100: ='Cash Flow Statement'!N29 -> -1804
B101: ='Cash Flow Statement'!B30 -> Financial liabilities | C101: ='Cash Flow Statement'!E30 -> 0 | D101: ='Cash Flow Statement'!F30 -> 0 | E101: ='Cash Flow Statement'!G30 -> 0 | F101: ='Cash Flow Statement'!H30 -> -2 | G101: ='Cash Flow Statement'!I30 -> -3 | H101: ='Cash Flow Statement'!J30 -> -2 | I101: ='Cash Flow Statement'!K30 -> -3 | J101: ='Cash Flow Statement'!L30 -> -2 | ... L101: ='Cash Flow Statement'!N30 -> -3
B102: ='Cash Flow Statement'!B31 -> Other financing items | C102: ='Cash Flow Statement'!E31 -> -7 | D102: ='Cash Flow Statement'!F31 -> 78 | E102: ='Cash Flow Statement'!G31 -> 23 | F102: ='Cash Flow Statement'!H31 -> 12 | G102: ='Cash Flow Statement'!I31 -> 14 | H102: ='Cash Flow Statement'!J31 -> 0 | I102: ='Cash Flow Statement'!K31 -> 9 | J102: ='Cash Flow Statement'!L31 -> 0 | ... L102: ='Cash Flow Statement'!N31 -> 0
B103: Cash From Financing Activities | C103: =SUM(C96:C102) -> -295 | D103: =SUM(D96:D102) -> -231 | E103: =SUM(E96:E102) -> -352 | F103: =SUM(F96:F102) -> 206 | G103: =SUM(G96:G102) -> -2244 | H103: =SUM(H96:H102) -> -2945 | I103: =SUM(I96:I102) -> -307 | J103: =SUM(J96:J102) -> -2839 | ... L103: =SUM(L96:L102) -> -1783
B105: Net Cash Flow | C105: =C80+C93+C103 -> -16 | D105: =D80+D93+D103 -> 53 | E105: =E80+E93+E103 -> -23 | F105: =F80+F93+F103 -> 376 | G105: =G80+G93+G103 -> -513 | H105: =H80+H93+H103 -> -1215 | I105: =I80+I93+I103 -> 1094 | J105: =J80+J93+J103 -> 155 | ... L105: =L80+L93+L103 -> 8

Sheet Ratio Analysis
B2: ="Ratio Analysis - "&'Data Sheet'!$B$1 -> Ratio Analysis - BRITANNIA INDUSTRIES LTD
B3: Years | C3: ='Data Sheet'!B56 -> 42795 | D3: ='Data Sheet'!C56 -> 43160 | E3: ='Data Sheet'!D56 -> 43525 | F3: ='Data Sheet'!E56 -> 43891 | G3: ='Data Sheet'!F56 -> 44256 | H3: ='Data Sheet'!G56 -> 44621 | I3: ='Data Sheet'!H56 -> 44986 | J3: ='Data Sheet'!I56 -> 45352 | ... L3: ='Data Sheet'!K56 -> 46082 | M3: Trend | N3: Mean | O3: Median
B5: SalesGrowth | D5: =IFERROR('Historical FS'!D8,0) -> 0.094985642 | E5: =IFERROR('Historical FS'!E8,0) -> 0.11508977 | F5: =IFERROR('Historical FS'!F8,0) -> 0.04929896 | G5: =IFERROR('Historical FS'!G8,0) -> 0.13241379 | H5: =IFERROR('Historical FS'!H8,0) -> 0.076126675 | I5: =IFERROR('Historical FS'!I8,0) -> 0.15315507 | J5: =IFERROR('Historical FS'!J8,0) -> 0.028709895 | K5: =IFERROR('Historical FS'!K8,0) -> 0.070010138 | L5: =IFERROR('Historical FS'!L8,0) -> 0.067380037 | N5: =IFERROR(AVERAGE(D5:L5),0) -> 0.087463331 | O5: =IFERROR(MEDIAN(D5:L5),0) -> 0.076126675
B6: EBITDA Growth | D6: =IFERROR(('Historical FS'!D19/'Historical FS'!C19-1),0) -> 0.29960136 | E6: =IFERROR(('Historical FS'!E19/'Historical FS'!D19-1),0) -> 0.052294675 | F6: =IFERROR(('Historical FS'!F19/'Historical FS'!E19-1),0) -> 0.23143431 | G6: =IFERROR(('Historical FS'!G19/'Historical FS'!F19-1),0) -> 0.27687061 | H6: =IFERROR(('Historical FS'!H19/'Historical FS'!G19-1),0) -> -0.22480048 | I6: =IFERROR(('Historical FS'!I19/'Historical FS'!H19-1),0) -> 0.34353404 | J6: =IFERROR(('Historical FS'!J19/'Historical FS'!I19-1),0) -> 0.22953812 | K6: =IFERROR(('Historical FS'!K19/'Historical FS'!J19-1),0) -> -0.054695072 | L6: =IFERROR(('Historical FS'!L19/'Historical FS'!K19-1),0) -> 0.09617113 | N6: =IFERROR(AVERAGE(D6:L6),0) -> 0.13888319 | O6: =IFERROR(MEDIAN(D6:L6),0) -> 0.22953812
B7: EBIT Growth | D7: =IFERROR(('Historical FS'!D25/'Historical FS'!C25-1),0) -> 0.31148126 | E7: =IFERROR(('Historical FS'!E25/'Historical FS'!D25-1),0) -> 0.04329243 | F7: =IFERROR(('Historical FS'!F25/'Historical FS'!E25-1),0) -> 0.24137931 | G7: =IFERROR(('Historical FS'!G25/'Historical FS'!F25-1),0) -> 0.29799889 | H7: =IFERROR(('Historical FS'!H25/'Historical FS'!G25-1),0) -> -0.24503424 | I7: =IFERROR(('Historical FS'!I25/'Historical FS'!H25-1),0) -> 0.36838305 | J7: =IFERROR(('Historical FS'!J25/'Historical FS'!I25-1),0) -> 0.22041752 | K7: =IFERROR(('Historical FS'!K25/'Historical FS'!J25-1),0) -> -0.064628907 | L7: =IFERROR(('Historical FS'!L25/'Historical FS'!K25-1),0) -> 0.098374568 | N7: =IFERROR(AVERAGE(D7:L7),0) -> 0.14129599 | O7: =IFERROR(MEDIAN(D7:L7),0) -> 0.22041752
B8: Net Profit Growth | D8: =IFERROR(('Historical FS'!D37/'Historical FS'!C37-1),0) -> 0.36462623 | E8: =IFERROR(('Historical FS'!E37/'Historical FS'!D37-1),0) -> -0.045188505 | F8: =IFERROR(('Historical FS'!F37/'Historical FS'!E37-1),0) -> 0.5348698 | G8: =IFERROR(('Historical FS'!G37/'Historical FS'!F37-1),0) -> 0.22783151 | H8: =IFERROR(('Historical FS'!H37/'Historical FS'!G37-1),0) -> -0.32232161 | I8: =IFERROR(('Historical FS'!I37/'Historical FS'!H37-1),0) -> 0.44345283 | J8: =IFERROR(('Historical FS'!J37/'Historical FS'!I37-1),0) -> 0.31023017 | K8: =IFERROR(('Historical FS'!K37/'Historical FS'!J37-1),0) -> -0.06757574 | L8: =IFERROR(('Historical FS'!L37/'Historical FS'!K37-1),0) -> 0.15704026 | N8: =IFERROR(AVERAGE(D8:L8),0) -> 0.17810722 | O8: =IFERROR(MEDIAN(D8:L8),0) -> 0.22783151
B9: Dividend Growth | D9: =IFERROR(('Historical FS'!D45/'Historical FS'!C45-1),0) -> 0.13446328 | E9: =IFERROR(('Historical FS'!E45/'Historical FS'!D45-1),0) -> 0.18874502 | F9: =IFERROR(('Historical FS'!F45/'Historical FS'!E45-1),0) -> 1.3359866 | G9: =IFERROR(('Historical FS'!G45/'Historical FS'!F45-1),0) -> 3.5146341 | H9: =IFERROR(('Historical FS'!H45/'Historical FS'!G45-1),0) -> -0.64268387 | I9: =IFERROR(('Historical FS'!I45/'Historical FS'!H45-1),0) -> 0.28739142 | J9: =IFERROR(('Historical FS'!J45/'Historical FS'!I45-1),0) -> 0.019700633 | K9: =IFERROR(('Historical FS'!K45/'Historical FS'!J45-1),0) -> 0.020618557 | L9: =IFERROR(('Historical FS'!L45/'Historical FS'!K45-1),0) -> 0.20693241 | N9: =IFERROR(AVERAGE(D9:L9),0) -> 0.56286535 | O9: =IFERROR(MEDIAN(D9:L9),0) -> 0.18874502
B11: Gross Margin | C11: =IFERROR('Historical FS'!C14,0) -> 0.26077535 | D11: =IFERROR('Historical FS'!D14,0) -> 0.28521283 | E11: =IFERROR('Historical FS'!E14,0) -> 0.28647218 | F11: =IFERROR('Historical FS'!F14,0) -> 0.30189655 | G11: =IFERROR('Historical FS'!G14,0) -> 0.3138246 | H11: =IFERROR('Historical FS'!H14,0) -> 0.25962366 | I11: =IFERROR('Historical FS'!I14,0) -> 0.29267468 | J11: =IFERROR('Historical FS'!J14,0) -> 0.32443258 | ... L11: =IFERROR('Historical FS'!L14,0) -> 0.3064056 | N11: =IFERROR(AVERAGE(C11:L11),0) -> 0.29230903 | O11: =IFERROR(MEDIAN(C11:L11),0) -> 0.29222348
B12: EBITDA Margin | C12: =IFERROR('Historical FS'!C20,0) -> 0.13077535 | D12: =IFERROR('Historical FS'!D20,0) -> 0.15521283 | E12: =IFERROR('Historical FS'!E20,0) -> 0.14647218 | F12: =IFERROR('Historical FS'!F20,0) -> 0.17189655 | G12: =IFERROR('Historical FS'!G20,0) -> 0.1938246 | H12: =IFERROR('Historical FS'!H20,0) -> 0.13962366 | I12: =IFERROR('Historical FS'!I20,0) -> 0.16267468 | J12: =IFERROR('Historical FS'!J20,0) -> 0.19443258 | ... L12: =IFERROR('Historical FS'!L20,0) -> 0.1764056 | N12: =IFERROR(AVERAGE(C12:L12),0) -> 0.16430903 | O12: =IFERROR(MEDIAN(C12:L12),0) -> 0.16722348
B13: EBIT Margin | C13: =IFERROR('Historical FS'!C26,0) -> 0.11763199 | D13: =IFERROR('Historical FS'!D26,0) -> 0.14088965 | E13: =IFERROR('Historical FS'!E26,0) -> 0.13181818 | F13: =IFERROR('Historical FS'!F26,0) -> 0.15594828 | G13: =IFERROR('Historical FS'!G26,0) -> 0.17875152 | H13: =IFERROR('Historical FS'!H26,0) -> 0.12540464 | I13: =IFERROR('Historical FS'!I26,0) -> 0.1488105 | J13: =IFERROR('Historical FS'!J26,0) -> 0.17654243 | ... L13: =IFERROR('Historical FS'!L26,0) -> 0.15880952 | N13: =IFERROR(AVERAGE(C13:L13),0) -> 0.14889349 | O13: =IFERROR(MEDIAN(C13:L13),0) -> 0.15156933
B14: EBT Margin | C14: =IFERROR('Historical FS'!C32,0) -> 0.11707974 | D14: =IFERROR('Historical FS'!D32,0) -> 0.14008271 | E14: =IFERROR('Historical FS'!E32,0) -> 0.13100407 | F14: =IFERROR('Historical FS'!F32,0) -> 0.14931034 | G14: =IFERROR('Historical FS'!G32,0) -> 0.17030146 | H14: =IFERROR('Historical FS'!H32,0) -> 0.11521788 | I14: =IFERROR('Historical FS'!I32,0) -> 0.13844304 | J14: =IFERROR('Historical FS'!J32,0) -> 0.16676248 | ... L14: =IFERROR('Historical FS'!L32,0) -> 0.15290936 | N14: =IFERROR(AVERAGE(C14:L14),0) -> 0.14276925 | O14: =IFERROR(MEDIAN(C14:L14),0) -> 0.14333205
B15: Net Profit Margin | C15: =IFERROR('Historical FS'!C38,0) -> 0.070801856 | D15: =IFERROR('Historical FS'!D38,0) -> 0.088236837 | E15: =IFERROR('Historical FS'!E38,0) -> 0.075554048 | F15: =IFERROR('Historical FS'!F38,0) -> 0.11051724 | G15: =IFERROR('Historical FS'!G38,0) -> 0.11982948 | H15: =IFERROR('Historical FS'!H38,0) -> 0.075461234 | I15: =IFERROR('Historical FS'!I38,0) -> 0.094458009 | J15: =IFERROR('Historical FS'!J38,0) -> 0.12030771 | ... L15: =IFERROR('Historical FS'!L38,0) -> 0.11364453 | N15: =IFERROR(AVERAGE(C15:L15),0) -> 0.097364904 | O15: =IFERROR(MEDIAN(C15:L15),0) -> 0.099648054
B17: SalesExpenses%sales | C17: =IFERROR('Historical FS'!C17,0) -> 0.13 | D17: =IFERROR('Historical FS'!D17,0) -> 0.13 | E17: =IFERROR('Historical FS'!E17,0) -> 0.14 | F17: =IFERROR('Historical FS'!F17,0) -> 0.13 | G17: =IFERROR('Historical FS'!G17,0) -> 0.12 | H17: =IFERROR('Historical FS'!H17,0) -> 0.12 | I17: =IFERROR('Historical FS'!I17,0) -> 0.13 | J17: =IFERROR('Historical FS'!J17,0) -> 0.13 | ... L17: =IFERROR('Historical FS'!L17,0) -> 0.13 | N17: =IFERROR(AVERAGE(C17:L17),0) -> 0.128 | O17: =IFERROR(MEDIAN(C17:L17),0) -> 0.13
B18: Depreciation%Sales | C18: =IFERROR('Historical FS'!C23,0) -> 0.013143362 | D18: =IFERROR('Historical FS'!D23,0) -> 0.014323179 | E18: =IFERROR('Historical FS'!E23,0) -> 0.014654003 | F18: =IFERROR('Historical FS'!F23,0) -> 0.015948276 | G18: =IFERROR('Historical FS'!G23,0) -> 0.015073082 | H18: =IFERROR('Historical FS'!H23,0) -> 0.014219015 | I18: =IFERROR('Historical FS'!I23,0) -> 0.01386418 | J18: =IFERROR('Historical FS'!J23,0) -> 0.017890154 | ... L18: =IFERROR('Historical FS'!L23,0) -> 0.017596074 | N18: =IFERROR(AVERAGE(C18:L18),0) -> 0.015415545 | O18: =IFERROR(MEDIAN(C18:L18),0) -> 0.014863542
B19: OperatingIncome%sales | C19: =C13 -> 0.11763199 | D19: =D13 -> 0.14088965 | E19: =E13 -> 0.13181818 | F19: =F13 -> 0.15594828 | G19: =G13 -> 0.17875152 | H19: =H13 -> 0.12540464 | I19: =I13 -> 0.1488105 | J19: =J13 -> 0.17654243 | ... L19: =L13 -> 0.15880952 | N19: =IFERROR(AVERAGE(C19:L19),0) -> 0.14889349 | O19: =IFERROR(MEDIAN(C19:L19),0) -> 0.15156933
B21: Return on Capital Employed | C21: =IFERROR('Historical FS'!C25/SUM('Historical FS'!C51:'Historical FS'!C53),0) -> 0.37753988 | D21: =IFERROR('Historical FS'!D25/SUM('Historical FS'!D51:'Historical FS'!D53),0) -> 0.38724147 | E21: =IFERROR('Historical FS'!E25/SUM('Historical FS'!E51:'Historical FS'!E53),0) -> 0.33051712 | F21: =IFERROR('Historical FS'!F25/SUM('Historical FS'!F51:'Historical FS'!F53),0) -> 0.30449419 | G21: =IFERROR('Historical FS'!G25/SUM('Historical FS'!G51:'Historical FS'!G53),0) -> 0.41522193 | H21: =IFERROR('Historical FS'!H25/SUM('Historical FS'!H51:'Historical FS'!H53),0) -> 0.35179996 | I21: =IFERROR('Historical FS'!I25/SUM('Historical FS'!I51:'Historical FS'!I53),0) -> 0.37142245 | J21: =IFERROR('Historical FS'!J25/SUM('Historical FS'!J51:'Historical FS'!J53),0) -> 0.49291375 | ... L21: =IFERROR('Historical FS'!L25/SUM('Historical FS'!L51:'Historical FS'!L53),0) -> 0.46893617 | N21: =IFERROR(AVERAGE(C21:L21),0) -> 0.39943061 | O21: =IFERROR(MEDIAN(C21:L21),0) -> 0.38239068
B22: Retained Earnings% | C22: =IFERROR('Historical FS'!C48,0) -> 0.58582928 | D22: =IFERROR('Historical FS'!D48,0) -> 0.65568486 | E22: =IFERROR('Historical FS'!E48,0) -> 0.57132595 | F22: =IFERROR('Historical FS'!F48,0) -> 0.3475819 | G22: =IFERROR('Historical FS'!G48,0) -> -1.398887 | H22: =IFERROR('Historical FS'!H48,0) -> -0.26484926 | I22: =IFERROR('Historical FS'!I48,0) -> -0.12809789 | J22: =IFERROR('Historical FS'!J48,0) -> 0.12204576 | ... L22: =IFERROR('Historical FS'!L48,0) -> -0.0024350799 | N22: =IFERROR(AVERAGE(C22:L22),0) -> 0.052720213 | O22: =IFERROR(MEDIAN(C22:L22),0) -> 0.080524664
B23: Return on Equity% | C23: =IFERROR('Historical FS'!C37/SUM('Historical FS'!C51:'Historical FS'!C52),0) -> 0.23777448 | D23: =IFERROR('Historical FS'!D37/SUM('Historical FS'!D51:'Historical FS'!D52),0) -> 0.256835 | E23: =IFERROR('Historical FS'!E37/SUM('Historical FS'!E51:'Historical FS'!E52),0) -> 0.19639078 | F23: =IFERROR('Historical FS'!F37/SUM('Historical FS'!F51:'Historical FS'!F52),0) -> 0.29116511 | G23: =IFERROR('Historical FS'!G37/SUM('Historical FS'!G51:'Historical FS'!G52),0) -> 0.44365276 | H23: =IFERROR('Historical FS'!H37/SUM('Historical FS'!H51:'Historical FS'!H52),0) -> 0.41701329 | I23: =IFERROR('Historical FS'!I37/SUM('Historical FS'!I51:'Historical FS'!I52),0) -> 0.43569892 | J23: =IFERROR('Historical FS'!J37/SUM('Historical FS'!J51:'Historical FS'!J52),0) -> 0.51191068 | ... L23: =IFERROR('Historical FS'!L37/SUM('Historical FS'!L51:'Historical FS'!L52),0) -> 0.42626714 | N23: =IFERROR(AVERAGE(C23:L23),0) -> 0.36485516 | O23: =IFERROR(MEDIAN(C23:L23),0) -> 0.42164021
B24: Self Sustained Growth Rate | C24: =IFERROR(C22*C23,0) -> 0.13929525 | D24: =IFERROR(D22*D23,0) -> 0.16840282 | E24: =IFERROR(E22*E23,0) -> 0.11220315 | F24: =IFERROR(F22*F23,0) -> 0.10120372 | G24: =IFERROR(G22*G23,0) -> -0.62062007 | H24: =IFERROR(H22*H23,0) -> -0.11044566 | I24: =IFERROR(I22*I23,0) -> -0.055812111 | J24: =IFERROR(J22*J23,0) -> 0.062476529 | ... L24: =IFERROR(L22*L23,0) -> -0.0010379945 | N24: =IFERROR(AVERAGE(C24:L24),0) -> -0.018749092 | O24: =IFERROR(MEDIAN(C24:L24),0) -> 0.039659982
B25: Interest Coverage Ratio | C25: =IFERROR('Historical FS'!C25/'Historical FS'!C28,0) -> 213.008 | D25: =IFERROR('Historical FS'!D25/'Historical FS'!D28,0) -> 174.5975 | E25: =IFERROR('Historical FS'!E25/'Historical FS'!E28,0) -> 161.91667 | F25: =IFERROR('Historical FS'!F25/'Historical FS'!F28,0) -> 23.493506 | G25: =IFERROR('Historical FS'!G25/'Historical FS'!G28,0) -> 21.153874 | H25: =IFERROR('Historical FS'!H25/'Historical FS'!H28,0) -> 12.310556 | I25: =IFERROR('Historical FS'!I25/'Historical FS'!I28,0) -> 14.353609 | J25: =IFERROR('Historical FS'!J25/'Historical FS'!J28,0) -> 18.051463 | ... L25: =IFERROR('Historical FS'!L25/'Historical FS'!L28,0) -> 26.916106 | N25: =IFERROR(AVERAGE(C25:L25),0) -> 68.572294 | O25: =IFERROR(MEDIAN(C25:L25),0) -> 22.32369
B27: Debtor Turnover Ratio | C27: =IFERROR('Historical FS'!C7/'Historical FS'!C63,0) -> 50.581006 | D27: =IFERROR('Historical FS'!D7/'Historical FS'!D63,0) -> 32.504918 | E27: =IFERROR('Historical FS'!E7/'Historical FS'!E63,0) -> 28.058376 | F27: =IFERROR('Historical FS'!F7/'Historical FS'!F63,0) -> 36.25 | G27: =IFERROR('Historical FS'!G7/'Historical FS'!G63,0) -> 51.11284 | H27: =IFERROR('Historical FS'!H7/'Historical FS'!H63,0) -> 42.578313 | I27: =IFERROR('Historical FS'!I7/'Historical FS'!I63,0) -> 49.547112 | J27: =IFERROR('Historical FS'!J7/'Historical FS'!J63,0) -> 42.669211 | ... L27: =IFERROR('Historical FS'!L7/'Historical FS'!L63,0) -> 40.835821 | N27: =IFERROR(AVERAGE(C27:L27),0) -> 41.409974 | O27: =IFERROR(MEDIAN(C27:L27),0) -> 41.707067
B28: Creditor Turnover Ratio | C28: =IFERROR('Historical FS'!C7/'Historical FS'!C54,0) -> 7.0295031 | D28: =IFERROR('Historical FS'!D7/'Historical FS'!D54,0) -> 6.2707147 | E28: =IFERROR('Historical FS'!E7/'Historical FS'!E54,0) -> 6.0442865 | F28: =IFERROR('Historical FS'!F7/'Historical FS'!F54,0) -> 6.1408152 | G28: =IFERROR('Historical FS'!G7/'Historical FS'!G54,0) -> 5.6017058 | H28: =IFERROR('Historical FS'!H7/'Historical FS'!H54,0) -> 5.6839566 | I28: =IFERROR('Historical FS'!I7/'Historical FS'!I54,0) -> 5.782547 | J28: =IFERROR('Historical FS'!J7/'Historical FS'!J54,0) -> 5.4711256 | ... L28: =IFERROR('Historical FS'!L7/'Historical FS'!L54,0) -> 5.9056429 | N28: =IFERROR(AVERAGE(C28:L28),0) -> 5.947682 | O28: =IFERROR(MEDIAN(C28:L28),0) -> 5.844095
B29: Inventory Turnover | C29: =IFERROR('Historical FS'!C7/'Historical FS'!C64,0) -> 13.697428 | D29: =IFERROR('Historical FS'!D7/'Historical FS'!D64,0) -> 15.182236 | E29: =IFERROR('Historical FS'!E7/'Historical FS'!E64,0) -> 14.15493 | F29: =IFERROR('Historical FS'!F7/'Historical FS'!F64,0) -> 15.654521 | G29: =IFERROR('Historical FS'!G7/'Historical FS'!G64,0) -> 12.04033 | H29: =IFERROR('Historical FS'!H7/'Historical FS'!H64,0) -> 10.340892 | I29: =IFERROR('Historical FS'!I7/'Historical FS'!I64,0) -> 13.663873 | J29: =IFERROR('Historical FS'!J7/'Historical FS'!J64,0) -> 14.198984 | ... L29: =IFERROR('Historical FS'!L7/'Historical FS'!L64,0) -> 14.228826 | N29: =IFERROR(AVERAGE(C29:L29),0) -> 13.766727 | O29: =IFERROR(MEDIAN(C29:L29),0) -> 14.176957
B30: Fixed Assets Turnover | C30: =IFERROR('Historical FS'!C7/'Historical FS'!C57,0) -> 7.8051724 | D30: =IFERROR('Historical FS'!D7/'Historical FS'!D57,0) -> 7.3655275 | E30: =IFERROR('Historical FS'!E7/'Historical FS'!E57,0) -> 6.5491706 | F30: =IFERROR('Historical FS'!F7/'Historical FS'!F57,0) -> 6.1767838 | G30: =IFERROR('Historical FS'!G7/'Historical FS'!G57,0) -> 7.3262688 | H30: =IFERROR('Historical FS'!H7/'Historical FS'!H57,0) -> 8.0638905 | I30: =IFERROR('Historical FS'!I7/'Historical FS'!I57,0) -> 6.1397363 | J30: =IFERROR('Historical FS'!J7/'Historical FS'!J57,0) -> 6.0516059 | ... L30: =IFERROR('Historical FS'!L7/'Historical FS'!L57,0) -> 6.72 | N30: =IFERROR(AVERAGE(C30:L30),0) -> 6.8376875 | O30: =IFERROR(MEDIAN(C30:L30),0) -> 6.6345853
B31: Capital Turnover Ratio | C31: =IFERROR('Historical FS'!C7/SUM('Historical FS'!C51:'Historical FS'!C52),0) -> 3.3583086 | D31: =IFERROR('Historical FS'!D7/SUM('Historical FS'!D51:'Historical FS'!D52),0) -> 2.9107457 | E31: =IFERROR('Historical FS'!E7/SUM('Historical FS'!E51:'Historical FS'!E52),0) -> 2.5993416 | F31: =IFERROR('Historical FS'!F7/SUM('Historical FS'!F51:'Historical FS'!F52),0) -> 2.6345673 | G31: =IFERROR('Historical FS'!G7/SUM('Historical FS'!G51:'Historical FS'!G52),0) -> 3.7023675 | H31: =IFERROR('Historical FS'!H7/SUM('Historical FS'!H51:'Historical FS'!H52),0) -> 5.5261923 | I31: =IFERROR('Historical FS'!I7/SUM('Historical FS'!I51:'Historical FS'!I52),0) -> 4.6126203 | J31: =IFERROR('Historical FS'!J7/SUM('Historical FS'!J51:'Historical FS'!J52),0) -> 4.2550114 | ... L31: =IFERROR('Historical FS'!L7/SUM('Historical FS'!L51:'Historical FS'!L52),0) -> 3.7508813 | N31: =IFERROR(AVERAGE(C31:L31),0) -> 3.7469182 | O31: =IFERROR(MEDIAN(C31:L31),0) -> 3.7266244
B33: (in days)
B34: Debtor Days | C34: =IFERROR(365/C27,0) -> 7.2161476 | D34: =IFERROR(365/D27,0) -> 11.22907 | E34: =IFERROR(365/E27,0) -> 13.008593 | F34: =IFERROR(365/F27,0) -> 10.068966 | G34: =IFERROR(365/G27,0) -> 7.1410627 | H34: =IFERROR(365/H27,0) -> 8.5724392 | I34: =IFERROR(365/I27,0) -> 7.366726 | J34: =IFERROR(365/J27,0) -> 8.5541774 | ... L34: =IFERROR(365/L27,0) -> 8.938231 | N34: =IFERROR(AVERAGE(C34:L34),0) -> 9.1229058 | O34: =IFERROR(MEDIAN(C34:L34),0) -> 8.7553351
B35: Payable Days | C35: =IFERROR(365/C28,0) -> 51.924011 | D35: =IFERROR(365/D28,0) -> 58.207081 | E35: =IFERROR(365/E28,0) -> 60.387607 | F35: =IFERROR(365/F28,0) -> 59.438362 | G35: =IFERROR(365/G28,0) -> 65.158724 | H35: =IFERROR(365/H28,0) -> 64.215832 | I35: =IFERROR(365/I28,0) -> 63.120974 | J35: =IFERROR(365/J28,0) -> 66.713877 | ... L35: =IFERROR(365/L28,0) -> 61.805294 | N35: =IFERROR(AVERAGE(C35:L35),0) -> 61.677876 | O35: =IFERROR(MEDIAN(C35:L35),0) -> 62.463134
B36: Inventory Days | C36: =IFERROR(365/C29,0) -> 26.647338 | D36: =IFERROR(365/D29,0) -> 24.041255 | E36: =IFERROR(365/E29,0) -> 25.78607 | F36: =IFERROR(365/F29,0) -> 23.315948 | G36: =IFERROR(365/G29,0) -> 30.314784 | H36: =IFERROR(365/H29,0) -> 35.29676 | I36: =IFERROR(365/I29,0) -> 26.712778 | J36: =IFERROR(365/J29,0) -> 25.706065 | ... L36: =IFERROR(365/L29,0) -> 25.652151 | N36: =IFERROR(AVERAGE(C36:L36),0) -> 26.863644 | O36: =IFERROR(MEDIAN(C36:L36),0) -> 25.746067
B37: Cash Conversion Cycle | C37: =SUM(C34,C36)-C35 -> -18.060526 | D37: =SUM(D34,D36)-D35 -> -22.936756 | E37: =SUM(E34,E36)-E35 -> -21.592944 | F37: =SUM(F34,F36)-F35 -> -26.053448 | G37: =SUM(G34,G36)-G35 -> -27.702878 | H37: =SUM(H34,H36)-H35 -> -20.346633 | I37: =SUM(I34,I36)-I35 -> -29.04147 | J37: =SUM(J34,J36)-J35 -> -32.453635 | ... L37: =SUM(L34,L36)-L35 -> -27.214912 | N37: =IFERROR(AVERAGE(C37:L37),0) -> -25.691326 | O37: =IFERROR(MEDIAN(C37:L37),0) -> -26.63418
B39: CFO/Sales | C39: =IFERROR('Historical FS'!C80/'Historical FS'!C7,0) -> 0.023304617 | D39: =IFERROR('Historical FS'!D80/'Historical FS'!D7,0) -> 0.11428283 | E39: =IFERROR('Historical FS'!E80/'Historical FS'!E7,0) -> 0.085210312 | F39: =IFERROR('Historical FS'!F80/'Historical FS'!F7,0) -> 0.13844828 | G39: =IFERROR('Historical FS'!G80/'Historical FS'!G7,0) -> 0.11883374 | H39: =IFERROR('Historical FS'!H80/'Historical FS'!H7,0) -> 0.071943973 | I39: =IFERROR('Historical FS'!I80/'Historical FS'!I7,0) -> 0.18379241 | J39: =IFERROR('Historical FS'!J80/'Historical FS'!J7,0) -> 0.16452979 | ... L39: =IFERROR('Historical FS'!L80/'Historical FS'!L7,0) -> 0.13152673 | N39: =IFERROR(AVERAGE(C39:L39),0) -> 0.11759957 | O39: =IFERROR(MEDIAN(C39:L39),0) -> 0.12518024
B40: CFO/Total Assets | C40: =IFERROR('Historical FS'!C80/'Historical FS'!C68,0) -> 0.051350694 | D40: =IFERROR('Historical FS'!D80/'Historical FS'!D68,0) -> 0.21838859 | E40: =IFERROR('Historical FS'!E80/'Historical FS'!E68,0) -> 0.15103415 | F40: =IFERROR('Historical FS'!F80/'Historical FS'!F68,0) -> 0.20510856 | G40: =IFERROR('Historical FS'!G80/'Historical FS'!G68,0) -> 0.19510061 | H40: =IFERROR('Historical FS'!H80/'Historical FS'!H68,0) -> 0.13513154 | I40: =IFERROR('Historical FS'!I80/'Historical FS'!I68,0) -> 0.32042781 | J40: =IFERROR('Historical FS'!J80/'Historical FS'!J68,0) -> 0.30412257 | ... L40: =IFERROR('Historical FS'!L80/'Historical FS'!L68,0) -> 0.25886343 | N40: =IFERROR(AVERAGE(C40:L40),0) -> 0.21321943 | O40: =IFERROR(MEDIAN(C40:L40),0) -> 0.21174857
B41: CFO/Total Debt | C41: =IFERROR('Historical FS'!C80/'Historical FS'!C53,0) -> 1.688 | D41: =IFERROR('Historical FS'!D80/'Historical FS'!D53,0) -> 5.6368159 | E41: =IFERROR('Historical FS'!E80/'Historical FS'!E53,0) -> 6.0384615 | F41: =IFERROR('Historical FS'!F80/'Historical FS'!F53,0) -> 1.0442133 | G41: =IFERROR('Historical FS'!G80/'Historical FS'!G53,0) -> 0.74086379 | H41: =IFERROR('Historical FS'!H80/'Historical FS'!H53,0) -> 0.40991536 | I41: =IFERROR('Historical FS'!I80/'Historical FS'!I53,0) -> 0.99966633 | J41: =IFERROR('Historical FS'!J80/'Historical FS'!J53,0) -> 1.3360775 | ... L41: =IFERROR('Historical FS'!L80/'Historical FS'!L53,0) -> 1.8253623 | N41: =IFERROR(AVERAGE(C41:L41),0) -> 2.1793153 | O41: =IFERROR(MEDIAN(C41:L41),0) -> 1.5120387

Sheet Forecasting
B2: ='Data Sheet'!$B$1&" -"&'Data Sheet'!A17&" Forecasting" -> BRITANNIA INDUSTRIES LTD -Sales Forecasting | G2: ='Data Sheet'!$B$1&" -"&'Historical FS'!B19&" Forecasting" -> BRITANNIA INDUSTRIES LTD -EBITDA Forecasting | L2: ='Data Sheet'!$B$1&" -"&'Historical FS'!B37&" Forecasting" -> BRITANNIA INDUSTRIES LTD -Net Profit Forecasting
B3: Year Weight | C3: Year | D3: Sales | E3: Sales Growth | G3: Year Weight | H3: Year | I3: EBITDA | J3: EBITDA Growth | L3: Year Weight | M3: Year | N3: Net Profit | O3: Net Profit Growth
B5: 1 | C5: {=TRANSPOSE('Data Sheet'!B16:J16)} -> 42795 | D5: {=TRANSPOSE('Data Sheet'!B17:K17)} -> 9054 | E5: - | G5: 1 | H5: {=TRANSPOSE('Data Sheet'!B16:J16)} -> 42795 | I5: {=TRANSPOSE('Historical FS'!C19:L19)} -> 1184.04 | J5: - | L5: 1 | M5: {=TRANSPOSE('Data Sheet'!B16:J16)} -> 42795 | N5: {=TRANSPOSE('Historical FS'!C37:L37)} -> 641.04 | O5: -
B6: =B5+1 -> 2 | C6: 43160 | D6: 9914 | E6: =D6/D5-1 -> 0.094985642 | G6: =G5+1 -> 2 | H6: 43160 | I6: 1538.78 | J6: =I6/I5-1 -> 0.29960136 | L6: =L5+1 -> 2 | M6: 43160 | N6: 874.78 | O6: =N6/N5-1 -> 0.36462623
B7: =B6+1 -> 3 | C7: 43525 | D7: 11055 | E7: =D7/D6-1 -> 0.11508977 | G7: =G6+1 -> 3 | H7: 43525 | I7: 1619.25 | J7: =I7/I6-1 -> 0.052294675 | L7: =L6+1 -> 3 | M7: 43525 | N7: 835.25 | O7: =N7/N6-1 -> -0.045188505
B8: =B7+1 -> 4 | C8: 43891 | D8: 11600 | E8: =D8/D7-1 -> 0.04929896 | G8: =G7+1 -> 4 | H8: 43891 | I8: 1994 | J8: =I8/I7-1 -> 0.23143431 | L8: =L7+1 -> 4 | M8: 43891 | N8: 1282 | O8: =N8/N7-1 -> 0.5348698
B9: =B8+1 -> 5 | C9: 44256 | D9: 13136 | E9: =D9/D8-1 -> 0.13241379 | G9: =G8+1 -> 5 | H9: 44256 | I9: 2546.08 | J9: =I9/I8-1 -> 0.27687061 | L9: =L8+1 -> 5 | M9: 44256 | N9: 1574.08 | O9: =N9/N8-1 -> 0.22783151
B10: =B9+1 -> 6 | C10: 44621 | D10: 14136 | E10: =D10/D9-1 -> 0.076126675 | G10: =G9+1 -> 6 | H10: 44621 | I10: 1973.72 | J10: =I10/I9-1 -> -0.22480048 | L10: =L9+1 -> 6 | M10: 44621 | N10: 1066.72 | O10: =N10/N9-1 -> -0.32232161
B11: =B10+1 -> 7 | C11: 44986 | D11: 16301 | E11: =D11/D10-1 -> 0.15315507 | G11: =G10+1 -> 7 | H11: 44986 | I11: 2651.76 | J11: =I11/I10-1 -> 0.34353404 | L11: =L10+1 -> 7 | M11: 44986 | N11: 1539.76 | O11: =N11/N10-1 -> 0.44345283
B12: =B11+1 -> 8 | C12: 45352 | D12: 16769 | E12: =D12/D11-1 -> 0.028709895 | G12: =G11+1 -> 8 | H12: 45352 | I12: 3260.44 | J12: =I12/I11-1 -> 0.22953812 | L12: =L11+1 -> 8 | M12: 45352 | N12: 2017.44 | O12: =N12/N11-1 -> 0.31023017
B13: =B12+1 -> 9 | C13: 45717 | D13: 17943 | E13: =D13/D12-1 -> 0.070010138 | G13: =G12+1 -> 9 | H13: 45717 | I13: 3082.11 | J13: =I13/I12-1 -> -0.054695072 | L13: =L12+1 -> 9 | M13: 45717 | N13: 1881.11 | O13: =N13/N12-1 -> -0.06757574
B14: =B13+1 -> 10 | C14: =C13+365 -> 46082 | D14: 19152 | E14: =D14/D13-1 -> 0.067380037 | G14: =G13+1 -> 10 | H14: =H13+365 -> 46082 | I14: 3378.52 | J14: =I14/I13-1 -> 0.09617113 | L14: =L13+1 -> 10 | M14: =M13+365 -> 46082 | N14: 2176.52 | O14: =N14/N13-1 -> 0.15704026
B15: =B14+1 -> 11 | C15: =C14+365 -> 46447 | D15: =FORECAST(B15,$D$5:$D$14,$B$5:$B$14) -> 20264.6 | E15: =D15/D14-1 -> 0.05809315 | G15: =G14+1 -> 11 | H15: =H14+365 -> 46447 | I15: =FORECAST(G15,$I$5:$I$14,$G$5:$G$14) -> 3661.5533 | J15: =I15/I14-1 -> 0.083774355 | L15: =L14+1 -> 11 | M15: =M14+365 -> 46447 | N15: =FORECAST(L15,$N$5:$N$14,$L$5:$L$14) -> 2290.22 | O15: =N15/N14-1 -> 0.052239355
B16: =B15+1 -> 12 | C16: =C15+365 -> 46812 | D16: =FORECAST(B16,$D$5:$D$14,$B$5:$B$14) -> 21420.709 | E16: =D16/D15-1 -> 0.057050674 | G16: =G15+1 -> 12 | H16: =H15+365 -> 46812 | I16: =FORECAST(G16,$I$5:$I$14,$G$5:$G$14) -> 3904.9503 | J16: =I16/I15-1 -> 0.066473692 | L16: =L15+1 -> 12 | M16: =M15+365 -> 46812 | N16: =FORECAST(L16,$N$5:$N$14,$L$5:$L$14) -> 2454.1018 | O16: =N16/N15-1 -> 0.071557238
B17: =B16+1 -> 13 | C17: =C16+365 -> 47177 | D17: =FORECAST(B17,$D$5:$D$14,$B$5:$B$14) -> 22576.818 | E17: =D17/D16-1 -> 0.05397156 | G17: =G16+1 -> 13 | H17: =H16+365 -> 47177 | I17: =FORECAST(G17,$I$5:$I$14,$G$5:$G$14) -> 4148.3473 | J17: =I17/I16-1 -> 0.062330363 | L17: =L16+1 -> 13 | M17: =M16+365 -> 47177 | N17: =FORECAST(L17,$N$5:$N$14,$L$5:$L$14) -> 2617.9836 | O17: =N17/N16-1 -> 0.066778736
B18: =B17+1 -> 14 | C18: =C17+365 -> 47542 | D18: =FORECAST(B18,$D$5:$D$14,$B$5:$B$14) -> 23732.927 | E18: =D18/D17-1 -> 0.051207796 | G18: =G17+1 -> 14 | H18: =H17+365 -> 47542 | I18: =FORECAST(G18,$I$5:$I$14,$G$5:$G$14) -> 4391.7442 | J18: =I18/I17-1 -> 0.058673239 | L18: =L17+1 -> 14 | M18: =M17+365 -> 47542 | N18: =FORECAST(L18,$N$5:$N$14,$L$5:$L$14) -> 2781.8655 | O18: =N18/N17-1 -> 0.062598488
B19: =B18+1 -> 15 | C19: =C18+365 -> 47907 | D19: =FORECAST(B19,$D$5:$D$14,$B$5:$B$14) -> 24889.036 | E19: =D19/D18-1 -> 0.048713295 | G19: =G18+1 -> 15 | H19: =H18+365 -> 47907 | I19: =FORECAST(G19,$I$5:$I$14,$G$5:$G$14) -> 4635.1412 | J19: =I19/I18-1 -> 0.055421481 | L19: =L18+1 -> 15 | M19: =M18+365 -> 47907 | N19: =FORECAST(L19,$N$5:$N$14,$L$5:$L$14) -> 2945.7473 | O19: =N19/N18-1 -> 0.058910764

Sheet Rm
B6: Return on Markets
B8: Date | C8: Annual
B9: ='Raw Data'!B6 -> 2025 | C9: ='Raw Data'!C6 -> 0.1051
B10: ='Raw Data'!B7 -> 2024 | C10: ='Raw Data'!C7 -> 0.0875
B11: ='Raw Data'!B8 -> 2023 | C11: ='Raw Data'!C8 -> 0.1942
B12: ='Raw Data'!B9 -> 2022 | C12: ='Raw Data'!C9 -> 0.0432 | E12: Average Market Returns | H12: =AVERAGE(C9:C32) -> 0.1769625
B13: ='Raw Data'!B10 -> 2021 | C13: ='Raw Data'!C10 -> 0.2412 | E13: Dividend Yield | H13: 0.0128
B14: ='Raw Data'!B11 -> 2020 | C14: ='Raw Data'!C11 -> 0.149 | E14: Total Market Returns | H14: =SUM(H12:H13) -> 0.1897625
B15: ='Raw Data'!B12 -> 2019 | C15: ='Raw Data'!C12 -> 0.1202
B16: ='Raw Data'!B13 -> 2018 | C16: ='Raw Data'!C13 -> 0.0315
B17: ='Raw Data'!B14 -> 2017 | C17: ='Raw Data'!C14 -> 0.2865
B18: ='Raw Data'!B15 -> 2016 | C18: ='Raw Data'!C15 -> 0.0301
B19: ='Raw Data'!B16 -> 2015 | C19: ='Raw Data'!C16 -> -0.0406
B20: ='Raw Data'!B17 -> 2014 | C20: ='Raw Data'!C17 -> 0.3139
B21: ='Raw Data'!B18 -> 2013 | C21: ='Raw Data'!C18 -> 0.0676
B22: ='Raw Data'!B19 -> 2012 | C22: ='Raw Data'!C19 -> 0.277
B23: ='Raw Data'!B20 -> 2011 | C23: ='Raw Data'!C20 -> -0.2462
B24: ='Raw Data'!B21 -> 2010 | C24: ='Raw Data'!C21 -> 0.1795
B25: ='Raw Data'!B22 -> 2009 | C25: ='Raw Data'!C22 -> 0.7576
B26: ='Raw Data'!B23 -> 2008 | C26: ='Raw Data'!C23 -> -0.5179
... B32: ='Raw Data'!B29 -> 2002 | C32: ='Raw Data'!C29 -> 0.0325

Sheet Beta-Regression
B6: Beta Regression
B7: ='Data Sheet'!B1&" Daily Returns" -> BRITANNIA INDUSTRIES LTD Daily Returns | F7: Nifty 50 Daily Returns | J7: Beta Drifting
B9: Date | C9: Closing Price | D9: Daily Returns | F9: Date | G9: Closing Price | H9: Daily Returns | J9: Levered Raw Beta | L9: =O11 -> 0.65982264
B10: ='Raw Data'!G6 -> 46288 | C10: ='Raw Data'!H6 -> 4929 | D10: - | F10: ='Raw Data'!G6 -> 46288 | G10: ='Raw Data'!J6 -> 23414.3 | H10: - | J10: Raw Beta Weight | L10: 0.75
B11: ='Raw Data'!G7 -> 46287 | C11: ='Raw Data'!H7 -> 4918 | D11: =C10/C11-1 -> 0.0022366816 | F11: ='Raw Data'!G7 -> 46287 | G11: ='Raw Data'!J7 -> 23414.3 | H11: =G10/G11-1 -> 0 | N11: Beta 1 | O11: =SLOPE(D10:D252, H10:H252) -> 0.65982264
B12: ='Raw Data'!G8 -> 46286 | C12: ='Raw Data'!H8 -> 5023 | D12: =C11/C12-1 -> -0.020903842 | F12: ='Raw Data'!G8 -> 46286 | G12: ='Raw Data'!J8 -> 23414.3 | H12: =G11/G12-1 -> 0 | J12: Market Beta | L12: 1 | N12: Beta 2 | O12: =_xlfn.COVARIANCE.S(D10:D252, H10:H252)/_xlfn.VAR.S(H10:H252) -> 0.65982264
B13: ='Raw Data'!G9 -> 46283 | C13: ='Raw Data'!H9 -> 4998 | D13: =C12/C13-1 -> 0.0050020008 | F13: ='Raw Data'!G9 -> 46283 | G13: ='Raw Data'!J9 -> 23346.4 | H13: =G12/G13-1 -> 0.0029083713 | J13: Market Beta Weight | L13: 0.25
B14: ='Raw Data'!G10 -> 46282 | C14: ='Raw Data'!H10 -> 4982 | D14: =C13/C14-1 -> 0.0032115616 | F14: ='Raw Data'!G10 -> 46282 | G14: ='Raw Data'!J10 -> 23270.6 | H14: =G13/G14-1 -> 0.003257329
B15: ='Raw Data'!G11 -> 46281 | C15: ='Raw Data'!H11 -> 4999.5 | D15: =C14/C15-1 -> -0.00350035 | F15: ='Raw Data'!G11 -> 46281 | G15: ='Raw Data'!J11 -> 23217.6 | H15: =G14/G15-1 -> 0.002282751 | J15: Adjusted Beta | L15: =(L9*L10)+(L12*L13) -> 0.74486698
B16: ='Raw Data'!G12 -> 46280 | C16: ='Raw Data'!H12 -> 4947.5 | D16: =C15/C16-1 -> 0.010510359 | F16: ='Raw Data'!G12 -> 46280 | G16: ='Raw Data'!J12 -> 23118.6 | H16: =G15/G16-1 -> 0.0042822662
B17: ='Raw Data'!G13 -> 46276 | C17: ='Raw Data'!H13 -> 4962 | D17: =C16/C17-1 -> -0.0029222088 | F17: ='Raw Data'!G13 -> 46276 | G17: ='Raw Data'!J13 -> 23398.1 | H17: =G16/G17-1 -> -0.011945414
B18: ='Raw Data'!G14 -> 46275 | C18: ='Raw Data'!H14 -> 5009 | D18: =C17/C18-1 -> -0.0093831104 | F18: ='Raw Data'!G14 -> 46275 | G18: ='Raw Data'!J14 -> 23477.8 | H18: =G17/G18-1 -> -0.0033946963
B19: ='Raw Data'!G15 -> 46274 | C19: ='Raw Data'!H15 -> 5090 | D19: =C18/C19-1 -> -0.015913556 | F19: ='Raw Data'!G15 -> 46274 | G19: ='Raw Data'!J15 -> 23431.5 | H19: =G18/G19-1 -> 0.0019759725
B20: ='Raw Data'!G16 -> 46273 | C20: ='Raw Data'!H16 -> 5064 | D20: =C19/C20-1 -> 0.0051342812 | F20: ='Raw Data'!G16 -> 46273 | G20: ='Raw Data'!J16 -> 23635.1 | H20: =G19/G20-1 -> -0.0086143067
B21: ='Raw Data'!G17 -> 46272 | C21: ='Raw Data'!H17 -> 5042.5 | D21: =C20/C21-1 -> 0.0042637581 | F21: ='Raw Data'!G17 -> 46272 | G21: ='Raw Data'!J17 -> 23779.15 | H21: =G20/G21-1 -> -0.006057828
B22: ='Raw Data'!G18 -> 46269 | C22: ='Raw Data'!H18 -> 5101.5 | D22: =C21/C22-1 -> -0.011565226 | F22: ='Raw Data'!G18 -> 46269 | G22: ='Raw Data'!J18 -> 23897.7 | H22: =G21/G22-1 -> -0.0049607284
B23: ='Raw Data'!G19 -> 46268 | C23: ='Raw Data'!H19 -> 5130 | D23: =C22/C23-1 -> -0.0055555556 | F23: ='Raw Data'!G19 -> 46268 | G23: ='Raw Data'!J19 -> 23873.45 | H23: =G22/G23-1 -> 0.0010157728
B24: ='Raw Data'!G20 -> 46267 | C24: ='Raw Data'!H20 -> 5154 | D24: =C23/C24-1 -> -0.0046565774 | F24: ='Raw Data'!G20 -> 46267 | G24: ='Raw Data'!J20 -> 23914.45 | H24: =G23/G24-1 -> -0.0017144446
B25: ='Raw Data'!G21 -> 46266 | C25: ='Raw Data'!H21 -> 5187 | D25: =C24/C25-1 -> -0.006362059 | F25: ='Raw Data'!G21 -> 46266 | G25: ='Raw Data'!J21 -> 24055.8 | H25: =G24/G25-1 -> -0.0058759218
B26: ='Raw Data'!G22 -> 46265 | C26: ='Raw Data'!H22 -> 5250 | D26: =C25/C26-1 -> -0.012 | F26: ='Raw Data'!G22 -> 46265 | G26: ='Raw Data'!J22 -> 24080.4 | H26: =G25/G26-1 -> -0.0010215777
B27: ='Raw Data'!G23 -> 46262 | C27: ='Raw Data'!H23 -> 5308.5 | D27: =C26/C27-1 -> -0.011020062 | F27: ='Raw Data'!G23 -> 46262 | G27: ='Raw Data'!J23 -> 24175.65 | H27: =G26/G27-1 -> -0.0039399147
... B256: ='Raw Data'!G252 -> 45924 | C256: ='Raw Data'!H252 -> 5970.5 | D256: =C255/C256-1 -> -0.0028473327 | F256: ='Raw Data'!G252 -> 45924 | G256: ='Raw Data'!J252 -> 25056.9 | H256: =G255/G256-1 -> -0.0066269171

Sheet WACC
B6: Weighted Average Cost of Capital
B8: All figures are in INR unless stated otherwise
B10: Peer Comps
E11: Total Debt | F11: Total Equity | H11: Debt /Equity | I11: Debt /Capital | J11: Levered Beta | K11: Unlevered Beta
B12: Name of the Comp | D12: Country | G12: Tax Rate
B14: ='Raw Data'!O24 -> Nestle India | D14: ='Raw Data'!Q24 -> India | E14: ='Raw Data'!R24 -> 66815.2 | F14: ='Raw Data'!S24 -> 267260.6 | G14: ='Raw Data'!T24 -> 0.25 | H14: =E14/F14 -> 0.25000019 | I14: =E14/SUM(E14:F14) -> 0.20000012 | J14: 0.58 | K14: =J14/(1+(1-G14)*H14) -> 0.48842099
B15: ='Raw Data'!O25 -> Bikaji Foods | D15: ='Raw Data'!Q25 -> India | E15: ='Raw Data'!R25 -> 3708.9 | F15: ='Raw Data'!S25 -> 14835.8 | G15: ='Raw Data'!T25 -> 0.25 | H15: =E15/F15 -> 0.24999663 | I15: =E15/SUM(E15:F15) -> 0.19999784 | J15: 0.95 | K15: =J15/(1+(1-G15)*H15) -> 0.8000017
B16: ='Raw Data'!O26 -> Milky Mist Dairy | D16: ='Raw Data'!Q26 -> India | E16: ='Raw Data'!R26 -> 6104.8 | F16: ='Raw Data'!S26 -> 24419.2 | G16: ='Raw Data'!T26 -> 0.25 | H16: =E16/F16 -> 0.25 | I16: =E16/SUM(E16:F16) -> 0.2 | J16: 0.95 | K16: =J16/(1+(1-G16)*H16) -> 0.8
B17: ='Raw Data'!O27 -> Marico | D17: ='Raw Data'!Q27 -> India | E17: ='Raw Data'!R27 -> 27065.1 | F17: ='Raw Data'!S27 -> 108260.3 | G17: ='Raw Data'!T27 -> 0.25 | H17: =E17/F17 -> 0.25000023 | I17: =E17/SUM(E17:F17) -> 0.20000015 | J17: 0.62 | K17: =J17/(1+(1-G17)*H17) -> 0.52210519
B18: ='Raw Data'!O28 -> Varun Beverages | D18: ='Raw Data'!Q28 -> India | E18: ='Raw Data'!R28 -> 36864.7 | F18: ='Raw Data'!S28 -> 147458.9 | G18: ='Raw Data'!T28 -> 0.25 | H18: =E18/F18 -> 0.24999983 | I18: =E18/SUM(E18:F18) -> 0.19999989 | J18: 0.72 | K18: =J18/(1+(1-G18)*H18) -> 0.60631585
F20: Average | G20: =AVERAGE(G14:G18) -> 0.25 | H20: =AVERAGE(H14:H18) -> 0.24999938 | I20: =AVERAGE(I14:I18) -> 0.1999996 | J20: =AVERAGE(J14:J18) -> 0.764 | K20: =AVERAGE(K14:K18) -> 0.64336875
F21: Median | G21: =MEDIAN(G14:G18) -> 0.25 | H21: =MEDIAN(H14:H18) -> 0.25 | I21: =MEDIAN(I14:I18) -> 0.2 | J21: =MEDIAN(J14:J18) -> 0.72 | K21: =MEDIAN(K14:K18) -> 0.60631585
B24: Cost of Debt | G24: Cost of Capital
B26: Pre-Tax Cost of Debt | E26: 0.0805 | G26: Risk Free Rate | K26: 0.07
B27: Tax Rate | E27: 0.25 | G27: Equity Risk Premium | K27: 0.065
B28: Post-Tax Cost of Debt | E28: =E26*(1-E27) -> 0.060375 | G28: Levered Beta | K28: =K36 -> 0.60631585
G29: Cost of Capital | K29: =K26+K27*K28 -> 0.10941053
B31: Capital Structure | G31: Levered Beta
D33: Current | E33: Target | G33: Comps Median Unlevered Beta | K33: =K21 -> 0.60631585
B34: Total Debt | C34: 0 | D34: =C34/C$36 -> 0 | E34: =I20 -> 0.1999996 | G34: Target Debt/Equity | K34: =D38 -> 0
B35: Market Capitalization | C35: 118555 | D35: =C35/C$36 -> 1 | E35: =E36-E34 -> 0.8000004 | G35: Tax Rate | K35: =E27 -> 0.25
B36: Total Capital | C36: =SUM(C34:C35) -> 118555 | D36: =C36/C$36 -> 1 | E36: =D36 -> 1 | G36: Levered Beta | K36: =K33*(1+(1-K35)*K34) -> 0.60631585
B38: Debt /Equity | D38: =D34/D35 -> 0 | E38: =E34/E35 -> 0.24999938 | G38: WACC
G40: Cost of Equity | K40: =K29 -> 0.10941053
G41: Equity Weight | K41: =D35 -> 1
G43: Cost of Debt | K43: =E28 -> 0.060375
G44: Debt Weight | K44: =D34 -> 0
G46: WACC | K46: =(K40*K41)+(K43*K44) -> 0.10941053

Sheet Intrinsic Valuation
B6: Calculation of ROIC | H6: ='Raw FS'!J$3 -> 44621 | I6: ='Raw FS'!K$3 -> 44986 | J6: ='Raw FS'!L$3 -> 45352 | K6: ='Raw FS'!M$3 -> 45717 | L6: ='Raw FS'!N$3 -> 46082
B8: Current Assets
B9: ='Raw FS'!B39 -> Inventories | H9: ='Raw FS'!J39 -> 1367 | I9: ='Raw FS'!K39 -> 1193 | J9: ='Raw FS'!L39 -> 1181 | K9: ='Raw FS'!M39 -> 1237 | L9: ='Raw FS'!N39 -> 1346
B10: Trade Receivables | H10: ='Raw FS'!J40 -> 332 | I10: ='Raw FS'!K40 -> 329 | J10: ='Raw FS'!L40 -> 393 | K10: ='Raw FS'!M40 -> 449 | L10: ='Raw FS'!N40 -> 469
B11: ='Raw FS'!B42 -> Loans n Advances | H11: ='Raw FS'!J42 -> 63 | I11: ='Raw FS'!K42 -> 83 | J11: ='Raw FS'!L42 -> 62 | K11: ='Raw FS'!M42 -> 67 | L11: ='Raw FS'!N42 -> 55
B12: ='Raw FS'!B43 -> Other asset items | H12: ='Raw FS'!J43 -> 1528 | I12: ='Raw FS'!K43 -> 1463 | J12: ='Raw FS'!L43 -> 1263 | K12: ='Raw FS'!M43 -> 914 | L12: ='Raw FS'!N43 -> 1009
B13: Total Current Assets | H13: =SUM(H9:H12) -> 3290 | I13: =SUM(I9:I12) -> 3068 | J13: =SUM(J9:J12) -> 2899 | K13: =SUM(K9:K12) -> 2667 | L13: =SUM(L9:L12) -> 2879
B15: Current Liabilities
B16: ='Raw FS'!B14 -> Trade Payables | H16: ='Raw FS'!J14 -> 1323 | I16: ='Raw FS'!K14 -> 1449 | J16: ='Raw FS'!L14 -> 1627 | K16: ='Raw FS'!M14 -> 1752 | L16: ='Raw FS'!N14 -> 1896
B17: ='Raw FS'!B15 -> Advance from Customers | H17: ='Raw FS'!J15 -> 34 | I17: ='Raw FS'!K15 -> 55 | J17: ='Raw FS'!L15 -> 42 | K17: ='Raw FS'!M15 -> 46 | L17: ='Raw FS'!N15 -> 53
B18: ='Raw FS'!B16 -> Other liability items | H18: ='Raw FS'!J16 -> 1103 | I18: ='Raw FS'!K16 -> 1285 | J18: ='Raw FS'!L16 -> 1371 | K18: ='Raw FS'!M16 -> 1410 | L18: ='Raw FS'!N16 -> 1265
B19: Total Current Liabilities | H19: =SUM(H16:H18) -> 2460 | I19: =SUM(I16:I18) -> 2789 | J19: =SUM(J16:J18) -> 3040 | K19: =SUM(K16:K18) -> 3208 | L19: =SUM(L16:L18) -> 3214
A21: # | B21: Net Working Capital | H21: =H13-H19 -> 830 | I21: =I13-I19 -> 279 | J21: =J13-J19 -> -141 | K21: =K13-K19 -> -541 | L21: =L13-L19 -> -335
B23: Non Current Assets
B24: ='Raw FS'!B22 -> Land | H24: ='Raw FS'!J22 -> 334 | I24: ='Raw FS'!K22 -> 376 | J24: ='Raw FS'!L22 -> 384 | K24: ='Raw FS'!M22 -> 395 | L24: ='Raw FS'!N22 -> 397
B25: ='Raw FS'!B23 -> Building | H25: ='Raw FS'!J23 -> 782 | I25: ='Raw FS'!K23 -> 1143 | J25: ='Raw FS'!L23 -> 1298 | K25: ='Raw FS'!M23 -> 1395 | L25: ='Raw FS'!N23 -> 1429
B26: ='Raw FS'!B24 -> Plant Machinery | H26: ='Raw FS'!J24 -> 1546 | I26: ='Raw FS'!K24 -> 2303 | J26: ='Raw FS'!L24 -> 2543 | K26: ='Raw FS'!M24 -> 2844 | L26: ='Raw FS'!N24 -> 3028
B27: ='Raw FS'!B25 -> Equipments | H27: ='Raw FS'!J25 -> 52 | I27: ='Raw FS'!K25 -> 61 | J27: ='Raw FS'!L25 -> 75 | K27: ='Raw FS'!M25 -> 81 | L27: ='Raw FS'!N25 -> 79
B28: ='Raw FS'!B26 -> Furniture n fittings | H28: ='Raw FS'!J26 -> 32 | I28: ='Raw FS'!K26 -> 43 | J28: ='Raw FS'!L26 -> 46 | K28: ='Raw FS'!M26 -> 49 | L28: ='Raw FS'!N26 -> 50
B29: ='Raw FS'!B27 -> Railway sidings | H29: ='Raw FS'!J27 -> 2 | I29: ='Raw FS'!K27 -> 2 | J29: ='Raw FS'!L27 -> 2 | K29: ='Raw FS'!M27 -> 2 | L29: ='Raw FS'!N27 -> 2
B30: ='Raw FS'!B28 -> Vehicles | H30: ='Raw FS'!J28 -> 6 | I30: ='Raw FS'!K28 -> 10 | J30: ='Raw FS'!L28 -> 10 | K30: ='Raw FS'!M28 -> 9 | L30: ='Raw FS'!N28 -> 9
B31: ='Raw FS'!B29 -> Intangible Assets | H31: ='Raw FS'!J29 -> 140 | I31: ='Raw FS'!K29 -> 130 | J31: ='Raw FS'!L29 -> 131 | K31: ='Raw FS'!M29 -> 134 | L31: ='Raw FS'!N29 -> 146
B32: ='Raw FS'!B30 -> Other fixed assets | H32: ='Raw FS'!J30 -> 57 | I32: ='Raw FS'!K30 -> 86 | J32: ='Raw FS'!L30 -> 72 | K32: ='Raw FS'!M30 -> 67 | L32: ='Raw FS'!N30 -> 67
B33: ='Raw FS'!B31 -> Gross Block | H33: ='Raw FS'!J31 -> 2948 | I33: ='Raw FS'!K31 -> 4150 | J33: ='Raw FS'!L31 -> 4559 | K33: ='Raw FS'!M31 -> 4974 | L33: ='Raw FS'!N31 -> 5206
B34: ='Raw FS'!B32 -> Accumulated Depreciation | H34: ='Raw FS'!J32 -> 1195 | I34: ='Raw FS'!K32 -> 1495 | J34: ='Raw FS'!L32 -> 1788 | K34: ='Raw FS'!M32 -> 2070 | L34: ='Raw FS'!N32 -> 2356
B35: Net Non Current Assets | H35: ='Raw FS'!J33 -> 1753 | I35: ='Raw FS'!K33 -> 2655 | J35: ='Raw FS'!L33 -> 2771 | K35: ='Raw FS'!M33 -> 2904 | L35: ='Raw FS'!N33 -> 2850
B37: Invested Capital | H37: =H35+H21 -> 2583 | I37: =I35+I21 -> 2934 | J37: =J35+J21 -> 2630 | K37: =K35+K21 -> 2363 | L37: =L35+L21 -> 2515
B38: EBIT | H38: ='Raw FS'!Z11+'Raw FS'!Z9 -> 2222 | I38: ='Raw FS'!AA11+'Raw FS'!AA9 -> 3202 | J38: ='Raw FS'!AB11+'Raw FS'!AB9 -> 3077 | K38: ='Raw FS'!AC11+'Raw FS'!AC9 -> 3066 | L38: ='Raw FS'!AD11+'Raw FS'!AD9 -> 3402
B40: ROIC | H40: =H38/H37 -> 0.86024003 | I40: =I38/I37 -> 1.0913429 | J40: =J38/J37 -> 1.169962 | K40: =K38/K37 -> 1.2975032 | L40: =L38/L37 -> 1.3526839
B42: Calculation of Reinvestment Rate | H42: ='Raw FS'!J$3 -> 44621 | I42: ='Raw FS'!K$3 -> 44986 | J42: ='Raw FS'!L$3 -> 45352 | K42: ='Raw FS'!M$3 -> 45717 | L42: ='Raw FS'!N$3 -> 46082
B44: Net Capex | H44: =-SUM('Raw FS'!Z27:Z28) -> 547 | I44: =-SUM('Raw FS'!AA27:AA28) -> 633 | J44: =-SUM('Raw FS'!AB27:AB28) -> 488 | K44: =-SUM('Raw FS'!AC27:AC28) -> 370 | L44: =-SUM('Raw FS'!AD27:AD28) -> 204
B45: Change in Work Cap | H45: - | I45: =I21-H21 -> -551 | J45: =J21-I21 -> -420 | K45: =K21-J21 -> -400 | L45: =L21-K21 -> 206
B47: EBIT | H47: =H38 -> 2222 | I47: =I38 -> 3202 | J47: =J38 -> 3077 | K47: =K38 -> 3066 | L47: =L38 -> 3402
B48: Tax Rate | H48: =WACC!E27 -> 0.25 | I48: =H48 -> 0.25 | J48: =I48 -> 0.25 | K48: =J48 -> 0.25 | L48: =K48 -> 0.25
B49: EBIT(1-T) | H49: =H47*(1-H48) -> 1666.5 | I49: =I47*(1-I48) -> 2401.5 | J49: =J47*(1-J48) -> 2307.75 | K49: =K47*(1-K48) -> 2299.5 | L49: =L47*(1-L48) -> 2551.5
B51: Reinvestment | H51: - | I51: =SUM(I44:I45) -> 82 | J51: =SUM(J44:J45) -> 68 | K51: =SUM(K44:K45) -> -30 | L51: =SUM(L44:L45) -> 410
B52: Reinvestment Rate | H52: - | I52: =I51/I49 -> 0.034145326 | J52: =J51/J49 -> 0.02946593 | K52: =K51/K49 -> -0.013046314 | L52: =L51/L49 -> 0.16068979
J54: 4 Year Average | L54: =AVERAGE(I52:L52) -> 0.052813683
J55: 4 Year Median | L55: =MEDIAN(I52:L52) -> 0.031805628
B57: Calculation of Growth Rate | H57: ='Raw FS'!J$3 -> 44621 | I57: ='Raw FS'!K$3 -> 44986 | J57: ='Raw FS'!L$3 -> 45352 | K57: ='Raw FS'!M$3 -> 45717 | L57: ='Raw FS'!N$3 -> 46082
B59: ROIC | H59: =H40 -> 0.86024003 | I59: =I40 -> 1.0913429 | J59: =J40 -> 1.169962 | K59: =K40 -> 1.2975032 | L59: =L40 -> 1.3526839
B60: Reinvestment Rate | H60: - | I60: =I52 -> 0.034145326 | J60: =J52 -> 0.02946593 | K60: =K52 -> -0.013046314 | L60: =L52 -> 0.16068979
B62: Intrinsic Growth | I62: =I59*I60 -> 0.037264258 | J62: =J59*J60 -> 0.034474018 | K62: =K59*K60 -> -0.016927634 | L62: =L59*L60 -> 0.21736249
J64: 4 Year Average | L64: =AVERAGE(I62:L62) -> 0.068043283
J65: 4 Year Median | L65: =MEDIAN(I62:L62) -> 0.035869138

Sheet DCF
B6: Calculation of PV of FCFF | H6: ='Data Sheet'!K56 -> 46082 | I6: =H6+365 -> 46447 | J6: =I6+365 -> 46812 | K6: =J6+365 -> 47177 | L6: =K6+365 -> 47542 | M6: =L6+365 -> 47907
B8: EBIT | H8: ='Intrinsic Valuation'!L38 -> 3402 | I8: =H8*(1+$D$18) -> 3578.904 | J8: =I8*(1+$D$18) -> 3765.007 | K8: =J8*(1+$D$18) -> 3960.7874 | L8: =K8*(1+$D$18) -> 4166.7483 | M8: =L8*(1+$D$18) -> 4383.4192
B9: Tax Rate | H9: =WACC!G14 -> 0.25 | I9: =H9 -> 0.25 | J9: =I9 -> 0.25 | K9: =J9 -> 0.25 | L9: =K9 -> 0.25 | M9: =L9 -> 0.25
B10: EBIT(1-T) | H10: =H8*(1-H9) -> 2551.5 | I10: =I8*(1-I9) -> 2684.178 | J10: =J8*(1-J9) -> 2823.7553 | K10: =K8*(1-K9) -> 2970.5905 | L10: =L8*(1-L9) -> 3125.0612 | M10: =M8*(1-M9) -> 3287.5644
B11: Less: Reinvestment Rate | H11: ='Intrinsic Valuation'!$L$55 -> 0.031805628 | I11: ='Intrinsic Valuation'!$L$55 -> 0.031805628 | J11: =$I$11+($M$11-$I$11)/4*1 -> 0.1152531 | K11: =$I$11+($M$11-$I$11)/4*2 -> 0.19870057 | L11: =$I$11+($M$11-$I$11)/4*3 -> 0.28214805 | M11: =D21 -> 0.36559552
B12: Free Cash Flow to Firm | H12: =H10*(1-H11) -> 2470.3479 | I12: =I10*(1-I11) -> 2598.806 | J12: =J10*(1-J11) -> 2498.3087 | K12: =K10*(1-K11) -> 2380.3325 | L12: =L10*(1-L11) -> 2243.3313 | M12: =M10*(1-M11) -> 2085.6456
B13: Mid Year Convention | H13: - | I13: 0.5 | J13: =I13+1 -> 1.5 | K13: =J13+1 -> 2.5 | L13: =K13+1 -> 3.5 | M13: =L13+1 -> 4.5
B14: Discounting Factor | I14: =1/(1+$D$20)^I13 -> 0.94941012 | J14: =1/(1+$D$20)^J13 -> 0.8557789 | K14: =1/(1+$D$20)^K13 -> 0.77138163 | L14: =1/(1+$D$20)^L13 -> 0.69530765 | M14: =1/(1+$D$20)^M13 -> 0.62673612
B16: PV of FCFF | I16: =I12*I14 -> 2467.3328 | J16: =J12*J14 -> 2137.9999 | K16: =K12*K14 -> 1836.1447 | L16: =L12*L14 -> 1559.8054 | M16: =M12*M14 -> 1307.1494
B18: Expected Growth Rate | D18: 0.052
B19: Terminal Growth Rate | D19: 0.04
B20: WACC | D20: =WACC!K46 -> 0.10941053
B21: Terminal Reinvestment Rate | D21: =D19/D20 -> 0.36559552
B23: Calculation of Terminal Value
B25: FCFF(n+1) | D25: =M12*(1+D19) -> 2169.0714
B26: WACC | D26: =D20 -> 0.10941053
B27: Terminal Growth Rate | D27: =D19 -> 0.04
B29: Terminal value | D29: =D25/(D26-D27) -> 31249.89
B31: Calculation of Equity Value
B33: PV of FCFF | D33: =SUM(I16:M16) -> 9308.4322
B34: Terminal value | D34: =D29*M14 -> 19585.434
B35: Value of Operating Assets | D35: =SUM(D33:D34) -> 28893.867
B37: Add: Cash | D37: ='Data Sheet'!K69 -> 352
B38: Less: Debt | D38: ='Data Sheet'!K59 -> 1380
B39: Less: Minority Interest | D39: ='Data Sheet'!K73 -> 29
B40: Equity Value | D40: =D35+D37-D38-D39 -> 27836.867
B41: No. of Shares | D41: ='Data Sheet'!K70/10000000 -> 24
B43: Equity Value per Share | D43: =D40/D41 -> 1159.8694
B45: Share Price | D45: ='Data Sheet'!B8 -> 4929
B46: Discount /Premium | D46: =D45/D43 -> 4.2496162

Sheet Raw Data
B6: 2025 | C6: 0.1051 | G6: 46288 | H6: 4929 | J6: 23414.3
B7: 2024 | C7: 0.0875 | G7: 46287 | H7: 4918 | J7: 23414.3
B8: 2023 | C8: 0.1942 | G8: 46286 | H8: 5023 | J8: 23414.3
B9: 2022 | C9: 0.0432 | G9: 46283 | H9: 4998 | J9: 23346.4
B10: 2021 | C10: 0.2412 | G10: 46282 | H10: 4982 | J10: 23270.6
B11: 2020 | C11: 0.149 | G11: 46281 | H11: 4999.5 | J11: 23217.6 | N11: S.No. | O11: Name | P11: CMP Rs. | Q11: No. Eq. Shares Cr. | R11: Mar Cap Rs.Cr. | S11: Debt Rs.Cr. | T11: Cash End Rs.Cr. | U11: EV Rs.Cr. | V11: Sales Rs.Cr. | W11: EV / EBITDA | X11: NP 12M Rs.Cr.
B12: 2019 | C12: 0.1202 | G12: 46280 | H12: 4947.5 | J12: 23118.6 | N12: 1 | O12: Nestle India | P12: 1387.2 | Q12: 192.66 | R12: 267260.6 | S12: 66815.2 | T12: 13363 | U12: 320712.7 | V12: 66052 | W12: 30.61 | X12: 14971
B13: 2018 | C13: 0.0315 | G13: 46276 | H13: 4962 | J13: 23398.1 | N13: 2 | O13: Bikaji Foods | P13: 591.1 | Q13: 25.1 | R13: 14835.8 | S13: 3708.9 | T13: 741.8 | U13: 17802.9 | V13: 76487.98 | W13: 12.44 | X13: 20183.53
B14: 2017 | C14: 0.2865 | G14: 46275 | H14: 5009 | J14: 23477.8 | N14: 3 | O14: Milky Mist Dairy | P14: 317.25 | Q14: 76.97 | R14: 24419.2 | S14: 6104.8 | T14: 1221 | U14: 29303.1 | V14: 4400.19 | W14: 20.53 | X14: 158.3
B15: 2016 | C15: 0.0301 | G15: 46274 | H15: 5090 | J15: 23431.5 | N15: 4 | O15: Marico | P15: 832.3 | Q15: 130.07 | R15: 108260.3 | S15: 27065.1 | T15: 5413 | U15: 129912.4 | V15: 2012.58 | W15: 12.74 | X15: 0.22
B16: 2015 | C16: -0.0406 | G16: 46273 | H16: 5064 | J16: 23635.1 | N16: 5 | O16: Varun Beverages | P16: 436.15 | Q16: 338.09 | R16: 147458.9 | S16: 36864.7 | T16: 7372.9 | U16: 176950.7 | V16: 238.77 | W16: 13.43 | X16: 8.51
B17: 2014 | C17: 0.3139 | G17: 46272 | H17: 5042.5 | J17: 23779.15 | N17: 6 | O17: Godrej Consumer | P17: 879.75 | Q17: 102.28 | R17: 89984.1 | S17: 22496 | T17: 4499.2 | U17: 107980.9
B18: 2013 | C18: 0.0676 | G18: 46269 | H18: 5101.5 | J18: 23897.7 | N18: 7 | O18: Dabur India | P18: 387.4 | Q18: 177.28 | R18: 68678.9 | S18: 17169.7 | T18: 3433.9 | U18: 82414.6
B19: 2012 | C19: 0.277 | G19: 46268 | H19: 5130 | J19: 23873.45 | N19: 8 | O19: Patanjali Foods | P19: 409.45 | Q19: 108.68 | R19: 44497.5 | S19: 11124.4 | T19: 2224.9 | U19: 53397
B20: 2011 | C20: -0.2462 | G20: 46267 | H20: 5154 | J20: 23914.45
B21: 2010 | C21: 0.1795 | G21: 46266 | H21: 5187 | J21: 24055.8
B22: 2009 | C22: 0.7576 | G22: 46265 | H22: 5250 | J22: 24080.4
B23: 2008 | C23: -0.5179 | G23: 46262 | H23: 5308.5 | J23: 24175.65
B24: 2007 | C24: 0.5477 | G24: 46261 | H24: 5298 | J24: 24090.85 | O24: Nestle India | Q24: India | R24: 66815.2 | S24: 267260.6 | T24: 0.25
B25: 2006 | C25: 0.3983 | G25: 46260 | H25: 5310 | J25: 24207.75 | O25: Bikaji Foods | Q25: =Q24 -> India | R25: 3708.9 | S25: 14835.8 | T25: =T24 -> 0.25
B26: 2005 | C26: 0.3634 | G26: 46259 | H26: 5382.5 | J26: 24334.55 | O26: Milky Mist Dairy | Q26: =Q25 -> India | R26: 6104.8 | S26: 24419.2 | T26: =T25 -> 0.25
B27: 2004 | C27: 0.1068 | G27: 46258 | H27: 5311 | J27: 24219.05 | O27: Marico | Q27: =Q26 -> India | R27: 27065.1 | S27: 108260.3 | T27: =T26 -> 0.25
B28: 2003 | C28: 0.719 | G28: 46255 | H28: 5365 | J28: 24252 | O28: Varun Beverages | Q28: =Q27 -> India | R28: 36864.7 | S28: 147458.9 | T28: =T27 -> 0.25
B29: 2002 | C29: 0.0325 | G29: 46254 | H29: 5548 | J29: 24231.85
G30: 46253 | H30: 5453 | J30: 24078.3
G31: 46252 | H31: 5495 | J31: 24154.9
G32: 46251 | H32: 5521 | J32: 24287.65
G33: 46248 | H33: 5558 | J33: 24366
G34: 46247 | H34: 5615 | J34: 24395.85
G35: 46246 | H35: 5645.5 | J35: 24435.95
G36: 46245 | H36: 5598 | J36: 24471.7
G37: 46244 | H37: 5623.5 | J37: 24583.8
G38: 46241 | H38: 5510 | J38: 24570.65
G39: 46240 | H39: 5404 | J39: 24636
G40: 46239 | H40: 5440 | J40: 24624.65
G41: 46238 | H41: 5478 | J41: 24614.9
... G252: 45924 | H252: 5970.5 | J252: 25056.9

Sheet Comp_Valuation
B6: Amount in crores
B7: Company Comparable Valuation
D9: Market Data | K9: Financials | O9: Valuation
B10: Company | C10: Ticker | D10: Share Price | E10: Share Outstanding | F10: Equity Value | G10: Net Debt value | H10: Enterprise Value | I10: EV/Revenue | J10: EV/EBITDA | K10: Revenue | L10: EBITDA | M10: Net Income | O10: EV/Revenue | P10: EV/EBITDA | Q10: P/E
B12: ='Raw FS'!L57 -> Nestle India | C12: NESTLEIND | D12: ='Raw FS'!M57 -> 1387.2 | E12: ='Raw FS'!N57 -> 192.66 | F12: =D12*E12 -> 267257.95 | G12: ='Raw FS'!AS57 -> 53452.2 | H12: ='Raw FS'!AT57 -> 320712.8 | I12: =IF(OR(ISBLANK(K12), K12<=0), "N/A", IFERROR($H12/K12, "N/A")) -> 12.570712 | J12: =IF(OR(ISBLANK(L12), L12<=0), "N/A", IFERROR($H12/L12, "N/A")) -> 54.816142 | K12: ='Raw FS'!AU57 -> 25512.7 | L12: ='Raw FS'!AV57 -> 5850.7 | M12: ='Raw FS'!AW57 -> 13363.03 | O12: =IF(OR(ISBLANK(K12), K12<=0), "N/A", IFERROR($H12/K12, "N/A")) -> 12.570712 | P12: =IF(OR(ISBLANK(L12), L12<=0), "N/A", IFERROR($H12/L12, "N/A")) -> 54.816142 | Q12: =IF(OR(ISBLANK(M12), M12<=0), "N/A", IFERROR(F12/M12, "N/A")) -> 19.999802
B13: ='Raw FS'!L58 -> Bikaji Foods | C13: BIKAJI | D13: ='Raw FS'!M58 -> 591.1 | E13: ='Raw FS'!N58 -> 25.1 | F13: =D13*E13 -> 14836.61 | G13: ='Raw FS'!AS58 -> 2967.1 | H13: ='Raw FS'!AT58 -> 17802.9 | I13: =IF(OR(ISBLANK(K13), K13<=0), "N/A", IFERROR($H13/K13, "N/A")) -> 6.5627972 | J13: =IF(OR(ISBLANK(L13), L13<=0), "N/A", IFERROR($H13/L13, "N/A")) -> 45.954827 | K13: ='Raw FS'!AU58 -> 2712.7 | L13: ='Raw FS'!AV58 -> 387.4 | M13: ='Raw FS'!AW58 -> 741.79 | O13: =IF(OR(ISBLANK(K13), K13<=0), "N/A", IFERROR($H13/K13, "N/A")) -> 6.5627972 | P13: =IF(OR(ISBLANK(L13), L13<=0), "N/A", IFERROR($H13/L13, "N/A")) -> 45.954827 | Q13: =IF(OR(ISBLANK(M13), M13<=0), "N/A", IFERROR(F13/M13, "N/A")) -> 20.001092
B14: ='Raw FS'!L59 -> Milky Mist Dairy | C14: MILKYMIST | D14: ='Raw FS'!M59 -> 317.25 | E14: ='Raw FS'!N59 -> 76.97 | F14: =D14*E14 -> 24418.732 | G14: ='Raw FS'!AS59 -> 4883.8 | H14: ='Raw FS'!AT59 -> 29303 | I14: =IF(OR(ISBLANK(K14), K14<=0), "N/A", IFERROR($H14/K14, "N/A")) -> 7.52594 | J14: =IF(OR(ISBLANK(L14), L14<=0), "N/A", IFERROR($H14/L14, "N/A")) -> 75.777088 | K14: ='Raw FS'!AU59 -> 3893.6 | L14: ='Raw FS'!AV59 -> 386.7 | M14: ='Raw FS'!AW59 -> 1220.96 | O14: =IF(OR(ISBLANK(K14), K14<=0), "N/A", IFERROR($H14/K14, "N/A")) -> 7.52594 | P14: =IF(OR(ISBLANK(L14), L14<=0), "N/A", IFERROR($H14/L14, "N/A")) -> 75.777088 | Q14: =IF(OR(ISBLANK(M14), M14<=0), "N/A", IFERROR(F14/M14, "N/A")) -> 19.999617
B15: ='Raw FS'!L60 -> Marico | C15: MARICO | D15: ='Raw FS'!M60 -> 832.3 | E15: ='Raw FS'!N60 -> 130.07 | F15: =D15*E15 -> 108257.26 | G15: ='Raw FS'!AS60 -> 21652.1 | H15: ='Raw FS'!AT60 -> 129912.4 | I15: =IF(OR(ISBLANK(K15), K15<=0), "N/A", IFERROR($H15/K15, "N/A")) -> 8.2077584 | J15: =IF(OR(ISBLANK(L15), L15<=0), "N/A", IFERROR($H15/L15, "N/A")) -> 33.208691 | K15: ='Raw FS'!AU60 -> 15828 | L15: ='Raw FS'!AV60 -> 3912 | M15: ='Raw FS'!AW60 -> 5413.02 | O15: =IF(OR(ISBLANK(K15), K15<=0), "N/A", IFERROR($H15/K15, "N/A")) -> 8.2077584 | P15: =IF(OR(ISBLANK(L15), L15<=0), "N/A", IFERROR($H15/L15, "N/A")) -> 33.208691 | Q15: =IF(OR(ISBLANK(M15), M15<=0), "N/A", IFERROR(F15/M15, "N/A")) -> 19.99942
B16: ='Raw FS'!L61 -> Varun Beverages | C16: VBL | D16: ='Raw FS'!M61 -> 436.15 | E16: ='Raw FS'!N61 -> 338.09 | F16: =D16*E16 -> 147457.95 | G16: ='Raw FS'!AS61 -> 29491.8 | H16: ='Raw FS'!AT61 -> 176950.7 | I16: =IF(OR(ISBLANK(K16), K16<=0), "N/A", IFERROR($H16/K16, "N/A")) -> 5.234469 | J16: =IF(OR(ISBLANK(L16), L16<=0), "N/A", IFERROR($H16/L16, "N/A")) -> 19.334226 | K16: ='Raw FS'!AU61 -> 33804.9 | L16: ='Raw FS'!AV61 -> 9152.2 | M16: ='Raw FS'!AW61 -> 7372.94 | O16: =IF(OR(ISBLANK(K16), K16<=0), "N/A", IFERROR($H16/K16, "N/A")) -> 5.234469 | P16: =IF(OR(ISBLANK(L16), L16<=0), "N/A", IFERROR($H16/L16, "N/A")) -> 19.334226 | Q16: =IF(OR(ISBLANK(M16), M16<=0), "N/A", IFERROR(F16/M16, "N/A")) -> 19.999885
B17: ='Raw FS'!L62 -> Godrej Consumer | C17: GODREJCP | D17: ='Raw FS'!M62 -> 879.75 | E17: ='Raw FS'!N62 -> 102.28 | F17: =D17*E17 -> 89980.83 | G17: ='Raw FS'!AS62 -> 17996.8 | H17: ='Raw FS'!AT62 -> 107980.9 | I17: =IF(OR(ISBLANK(K17), K17<=0), "N/A", IFERROR($H17/K17, "N/A")) -> 6.3886841 | J17: =IF(OR(ISBLANK(L17), L17<=0), "N/A", IFERROR($H17/L17, "N/A")) -> 35.671402 | K17: ='Raw FS'!AU62 -> 16901.9 | L17: ='Raw FS'!AV62 -> 3027.1 | M17: ='Raw FS'!AW62 -> 4499.21 | O17: =IF(OR(ISBLANK(K17), K17<=0), "N/A", IFERROR($H17/K17, "N/A")) -> 6.3886841 | P17: =IF(OR(ISBLANK(L17), L17<=0), "N/A", IFERROR($H17/L17, "N/A")) -> 35.671402 | Q17: =IF(OR(ISBLANK(M17), M17<=0), "N/A", IFERROR(F17/M17, "N/A")) -> 19.999251
B18: ='Raw FS'!L63 -> Dabur India | C18: DABUR | D18: ='Raw FS'!M63 -> 387.4 | E18: ='Raw FS'!N63 -> 177.28 | F18: =D18*E18 -> 68678.272 | G18: ='Raw FS'!AS63 -> 13735.8 | H18: ='Raw FS'!AT63 -> 82414.7 | I18: =IF(OR(ISBLANK(K18), K18<=0), "N/A", IFERROR($H18/K18, "N/A")) -> 5.4732959 | J18: =IF(OR(ISBLANK(L18), L18<=0), "N/A", IFERROR($H18/L18, "N/A")) -> 23.433239 | K18: ='Raw FS'!AU63 -> 15057.6 | L18: ='Raw FS'!AV63 -> 3517 | M18: ='Raw FS'!AW63 -> 3433.94 | O18: =IF(OR(ISBLANK(K18), K18<=0), "N/A", IFERROR($H18/K18, "N/A")) -> 5.4732959 | P18: =IF(OR(ISBLANK(L18), L18<=0), "N/A", IFERROR($H18/L18, "N/A")) -> 23.433239 | Q18: =IF(OR(ISBLANK(M18), M18<=0), "N/A", IFERROR(F18/M18, "N/A")) -> 19.999846
B19: ='Raw FS'!L64 -> Patanjali Foods | C19: PATANJALI | D19: ='Raw FS'!M64 -> 409.45 | E19: ='Raw FS'!N64 -> 108.68 | F19: =D19*E19 -> 44499.026 | G19: ='Raw FS'!AS64 -> 8899.5 | H19: ='Raw FS'!AT64 -> 53397 | I19: =IF(OR(ISBLANK(K19), K19<=0), "N/A", IFERROR($H19/K19, "N/A")) -> 1.1774473 | J19: =IF(OR(ISBLANK(L19), L19<=0), "N/A", IFERROR($H19/L19, "N/A")) -> 26.497122 | K19: ='Raw FS'!AU64 -> 45349.8 | L19: ='Raw FS'!AV64 -> 2015.2 | M19: ='Raw FS'!AW64 -> 2224.88 | O19: =IF(OR(ISBLANK(K19), K19<=0), "N/A", IFERROR($H19/K19, "N/A")) -> 1.1774473 | P19: =IF(OR(ISBLANK(L19), L19<=0), "N/A", IFERROR($H19/L19, "N/A")) -> 26.497122 | Q19: =IF(OR(ISBLANK(M19), M19<=0), "N/A", IFERROR(F19/M19, "N/A")) -> 20.000641
B23: High | I23: =MAX(I12:I19) -> 12.570712 | J23: =MAX(J12:J19) -> 75.777088 | O23: =MAX(O12:O19) -> 12.570712 | P23: =MAX(P12:P19) -> 75.777088 | Q23: =MAX(Q12:Q19) -> 20.001092
B24: 25th Percentile | I24: =_xlfn.QUARTILE.INC(I12:I19,1) -> 5.4135891 | J24: =_xlfn.QUARTILE.INC(J12:J19,1) -> 25.731151 | O24: =_xlfn.QUARTILE.INC(O12:O19,1) -> 5.4135891 | P24: =_xlfn.QUARTILE.INC(P12:P19,1) -> 25.731151 | Q24: =_xlfn.QUARTILE.INC(Q12:Q19,1) -> 19.999568
B25: Median | I25: =MEDIAN(I12:I19) -> 6.4757407 | J25: =MEDIAN(J12:J19) -> 34.440046 | O25: =MEDIAN(O12:O19) -> 6.4757407 | P25: =MEDIAN(P12:P19) -> 34.440046 | Q25: =MEDIAN(Q12:Q19) -> 19.999824
B26: Average | I26: =AVERAGE(I12:I19) -> 6.642638 | J26: =AVERAGE(J12:J19) -> 39.336592 | O26: =AVERAGE(O12:O19) -> 6.642638 | P26: =AVERAGE(P12:P19) -> 39.336592 | Q26: =AVERAGE(Q12:Q19) -> 19.999944
B27: 75th Percentile | I27: =_xlfn.QUARTILE.INC(I12:I19,3) -> 7.6963946 | J27: =_xlfn.QUARTILE.INC(J12:J19,3) -> 48.170156 | O27: =_xlfn.QUARTILE.INC(O12:O19,3) -> 7.6963946 | P27: =_xlfn.QUARTILE.INC(P12:P19,3) -> 48.170156 | Q27: =_xlfn.QUARTILE.INC(Q12:Q19,3) -> 20.000074
B28: Low | I28: =MIN(I12:I19) -> 1.1774473 | J28: =MIN(J12:J19) -> 19.334226 | O28: =MIN(O12:O19) -> 1.1774473 | P28: =MIN(P12:P19) -> 19.334226 | Q28: =MIN(Q12:Q19) -> 19.999251
B30: BRITANNIA INDUSTRIES LTD Comparable Valuation | I30: EV/Revenue | J30: EV/EBITDA | O30: EV/Revenue | P30: EV/EBITDA | Q30: P/E
B32: Implied Enterprise Value | I32: ='Raw FS'!AU56*I25 -> 124023.39 | J32: ='Raw FS'!AV56*J25 -> 128771.33 | O32: ='Raw FS'!AU56*O25 -> 124023.39 | P32: ='Raw FS'!AV56*P25 -> 128771.33 | Q32: ='Raw FS'!AW56*Q25 -> 50739.554
B33: Net Debt Value | I33: ='Raw FS'!AS56 -> 1028 | J33: ='Raw FS'!AS56 -> 1028 | O33: ='Raw FS'!AS56 -> 1028 | P33: ='Raw FS'!AS56 -> 1028 | Q33: 0
B34: Implied Market Value | I34: =I32-I33 -> 122995.39 | J34: =J32-J33 -> 127743.33 | O34: =O32-O33 -> 122995.39 | P34: =P32-P33 -> 127743.33 | Q34: =Q32 -> 50739.554
B35: Share Outstanding | I35: ='Raw FS'!N56 -> 24.052546 | J35: ='Raw FS'!N56 -> 24.052546 | O35: ='Raw FS'!N56 -> 24.052546 | P35: ='Raw FS'!N56 -> 24.052546 | Q35: ='Raw FS'!N56 -> 24.052546
B37: Implied Value per Share | I37: =I34/I35 -> 5113.6119 | J37: =J34/J35 -> 5311.0109 | O37: =O34/O35 -> 5113.6119 | P37: =P34/P35 -> 5311.0109 | Q37: =Q34/Q35 -> 2109.5294
B38: Source : Screener.in
B39: Verdict | I39: =IF(I37="N/A","N/A",IF(I37>'Raw FS'!M56,"Undervalued","Overvalued")) -> Undervalued | J39: =IF(J37="N/A","N/A",IF(J37>'Raw FS'!M56,"Undervalued","Overvalued")) -> Undervalued | O39: =IF(O37="N/A","N/A",IF(O37>'Raw FS'!M56,"Undervalued","Overvalued")) -> Undervalued | P39: =IF(P37="N/A","N/A",IF(P37>'Raw FS'!M56,"Undervalued","Overvalued")) -> Undervalued | Q39: =IF(Q37="N/A","N/A",IF(Q37>'Raw FS'!M56,"Undervalued","Overvalued")) -> Overvalued

Sheet Dupont Analysis
B2: ='Data Sheet'!B1 -> BRITANNIA INDUSTRIES LTD
B3: =CONCATENATE("(",VLOOKUP(B2,'List of Stocks'!B2:E5442,3,FALSE)," | ","BSE Code: ",VLOOKUP('Dupont Analysis'!B2,'List of Stocks'!B2:E5442,2,FALSE)) -> (BRITANNIA | BSE Code: 500825
B4: =CONCATENATE(" ","INR "&'Data Sheet'!B8) -> INR 4929
B5: 52 Week (High - INR - 6,271.00 & low INR - 4,905.00)
B6: About the Company
B8: Britannia Industries Limited is an Indian multinational food products company, which sells biscuits, breads and dairy products. Founded in 1892, it is one of India's oldest existing companies and currently part of the Wadia Group headed by Nusli Wadia. As of 2023, about 80% of its revenues came from biscuit products.
B15: Financial Summary
B35: Recent Updates
A37: • | B37: Britannia Industries - Maruti Suzuki among 8 large-cap stocks to hit 52-week lows and fall up to 12% in a month
A39: • | B39: Goldman Sachs says Britannia could see biggest cost impact as sugar prices continue to soar
A41: • | B41: Britannia Q1 Results: Profit rises 14% to Rs 593 crore on volumes, price rise
A43: • | B43: Britannia shares fall 5% despite decent Q4 show. Do Morgan Stanley, Nomura see any upside?
A45: • | B45: Stocks in news: BSE, Britannia, Paytm, Meesho, RIL
A47: • | B47: BRITANNIA INDUSTRIES LTD continued strategic operational investments and customer engagements to drive sustainable long-term business performance.
B54: Dupont Analysis - Return on Equity & Return on Assets
B58: Return on Equity
E59: ='Data Sheet'!G$56 -> 44621 | F59: ='Data Sheet'!H$56 -> 44986 | G59: ='Data Sheet'!I$56 -> 45352 | H59: ='Data Sheet'!J$56 -> 45717 | I59: ='Data Sheet'!K$56 -> 46082
B60: Net Profit | E60: =E66 -> 1516 | F60: =F66 -> 2316 | G60: =G66 -> 2134 | H60: =H66 -> 2178 | I60: =I66 -> 2537
B61: Average Shareholder's Equity | E61: =E75 -> 3053 | F61: =F75 -> 3046 | G61: =G75 -> 3737.5 | H61: =H75 -> 4148.5 | I61: =I75 -> 4731
B62: Return on Equity | E62: =E60/E61 -> 0.49656076 | F62: =F60/F61 -> 0.76034143 | G62: =G60/G61 -> 0.5709699 | H62: =H60/H61 -> 0.52500904 | I62: =I60/I61 -> 0.53625026
B64: ROE - Dupont Analysis
E65: ='Data Sheet'!G$56 -> 44621 | F65: ='Data Sheet'!H$56 -> 44986 | G65: ='Data Sheet'!I$56 -> 45352 | H65: ='Data Sheet'!J$56 -> 45717 | I65: ='Data Sheet'!K$56 -> 46082
B66: Net Profit | E66: ='Data Sheet'!G30 -> 1516 | F66: ='Data Sheet'!H30 -> 2316 | G66: ='Data Sheet'!I30 -> 2134 | H66: ='Data Sheet'!J30 -> 2178 | I66: ='Data Sheet'!K30 -> 2537
B67: Revenue | E67: ='Data Sheet'!G17 -> 14136 | F67: ='Data Sheet'!H17 -> 16301 | G67: ='Data Sheet'!I17 -> 16769 | H67: ='Data Sheet'!J17 -> 17943 | I67: ='Data Sheet'!K17 -> 19152
B68: Net Profit Margin (A) | E68: =E66/E67 -> 0.10724392 | F68: =F66/F67 -> 0.14207717 | G68: =G66/G67 -> 0.12725863 | H68: =H66/H67 -> 0.12138438 | I68: =I66/I67 -> 0.13246658
B70: Revenue | E70: =E67 -> 14136 | F70: =F67 -> 16301 | G70: =G67 -> 16769 | H70: =H67 -> 17943 | I70: =I67 -> 19152
B71: Average Total Assets | E71: =SUM('Data Sheet'!F66:G66)/2 -> 7763.5 | F71: =SUM('Data Sheet'!G66:H66)/2 -> 8439 | G71: =SUM('Data Sheet'!H66:I66)/2 -> 9211.5 | H71: =SUM('Data Sheet'!I66:J66)/2 -> 8954.5 | I71: =SUM('Data Sheet'!J66:K66)/2 -> 9283.5
B72: Asset Turnover Ratio (B) | E72: =E70/E71 -> 1.8208282 | F72: =F70/F71 -> 1.931627 | G72: =G70/G71 -> 1.8204418 | H72: =H70/H71 -> 2.003797 | I72: =I70/I71 -> 2.063015
B74: Average Total Assets | E74: =E71 -> 7763.5 | F74: =F71 -> 8439 | G74: =G71 -> 9211.5 | H74: =H71 -> 8954.5 | I74: =I71 -> 9283.5
B75: Average Shareholder's Equity | E75: =(SUM('Data Sheet'!F57:F58)+SUM('Data Sheet'!G57:G58))/2 -> 3053 | F75: =(SUM('Data Sheet'!G57:G58)+SUM('Data Sheet'!H57:H58))/2 -> 3046 | G75: =(SUM('Data Sheet'!H57:H58)+SUM('Data Sheet'!I57:I58))/2 -> 3737.5 | H75: =(SUM('Data Sheet'!I57:I58)+SUM('Data Sheet'!J57:J58))/2 -> 4148.5 | I75: =(SUM('Data Sheet'!J57:J58)+SUM('Data Sheet'!K57:K58))/2 -> 4731
B76: Equity Multiplier (C) | E76: =E74/E75 -> 2.5429086 | F76: =F74/F75 -> 2.7705187 | G76: =G74/G75 -> 2.4646154 | H76: =H74/H75 -> 2.158491 | I76: =I74/I75 -> 1.9622701
B78: Return on Equity(A*B*C) | E78: =E68*E72*E76 -> 0.49656076 | F78: =F68*F72*F76 -> 0.76034143 | G78: =G68*G72*G76 -> 0.5709699 | H78: =H68*H72*H76 -> 0.52500904 | I78: =I68*I72*I76 -> 0.53625026
B80: Return on Assets
E81: ='Data Sheet'!G$56 -> 44621 | F81: ='Data Sheet'!H$56 -> 44986 | G81: ='Data Sheet'!I$56 -> 45352 | H81: ='Data Sheet'!J$56 -> 45717 | I81: ='Data Sheet'!K$56 -> 46082
B82: Net Profit | E82: =E66 -> 1516 | F82: =F66 -> 2316 | G82: =G66 -> 2134 | H82: =H66 -> 2178 | I82: =I66 -> 2537
B83: Average Total Assets | E83: =E74 -> 7763.5 | F83: =F74 -> 8439 | G83: =G74 -> 9211.5 | H83: =H74 -> 8954.5 | I83: =I74 -> 9283.5
B84: Return on Assets | E84: =E82/E83 -> 0.19527275 | F84: =F82/F83 -> 0.2744401 | G84: =G82/G83 -> 0.23166694 | H84: =H82/H83 -> 0.24322966 | I84: =I82/I83 -> 0.27328055
B86: ROA - Dupont Equation
E87: ='Data Sheet'!G$56 -> 44621 | F87: ='Data Sheet'!H$56 -> 44986 | G87: ='Data Sheet'!I$56 -> 45352 | H87: ='Data Sheet'!J$56 -> 45717 | I87: ='Data Sheet'!K$56 -> 46082
B88: Net Profit | E88: =E66 -> 1516 | F88: =F66 -> 2316 | G88: =G66 -> 2134 | H88: =H66 -> 2178 | I88: =I66 -> 2537
B89: Revenue | E89: =E67 -> 14136 | F89: =F67 -> 16301 | G89: =G67 -> 16769 | H89: =H67 -> 17943 | I89: =I67 -> 19152
B90: Net Profit Margin (A) | E90: =E68 -> 0.10724392 | F90: =F68 -> 0.14207717 | G90: =G68 -> 0.12725863 | H90: =H68 -> 0.12138438 | I90: =I68 -> 0.13246658
B92: Revenue | E92: =E67 -> 14136 | F92: =F67 -> 16301 | G92: =G67 -> 16769 | H92: =H67 -> 17943 | I92: =I67 -> 19152
B93: Average Total Assets | E93: =E71 -> 7763.5 | F93: =F71 -> 8439 | G93: =G71 -> 9211.5 | H93: =H71 -> 8954.5 | I93: =I71 -> 9283.5
B94: Asset Turnover Ratio (B) | E94: =E72 -> 1.8208282 | F94: =F72 -> 1.931627 | G94: =G72 -> 1.8204418 | H94: =H72 -> 2.003797 | I94: =I72 -> 2.063015
B96: Return on Assets (A*B) | E96: =E90*E94 -> 0.19527275 | F96: =F90*F94 -> 0.2744401 | G96: =G90*G94 -> 0.23166694 | H96: =H90*H94 -> 0.24322966 | I96: =I90*I94 -> 0.27328055

Sheet Altman's Z Score
B2: ='Data Sheet'!B1 -> BRITANNIA INDUSTRIES LTD
B3: =CONCATENATE("(",VLOOKUP(B2,'List of Stocks'!B2:E5442,3,FALSE)," | ","BSE Code: ",VLOOKUP('Altman''s Z Score'!B2,'List of Stocks'!B2:E5442,2,FALSE)) -> (BRITANNIA | BSE Code: 500825
B4: =CONCATENATE(" ","INR "&'Data Sheet'!B8) -> INR 4929
B5: 52 Week (High - INR - 6,271.00 & low INR - 4,905.00)
B6: About the Company
B8: Britannia Industries Limited is an Indian multinational food products company, which sells biscuits, breads and dairy products. Founded in 1892, it is one of India's oldest existing companies and currently part of the Wadia Group headed by Nusli Wadia. As of 2023, about 80% of its revenues came from biscuit products.
B14: Financial Summary
B34: Recent Updates
A36: • | B36: Britannia Industries - Maruti Suzuki among 8 large-cap stocks to hit 52-week lows and fall up to 12% in a month
A38: • | B38: Goldman Sachs says Britannia could see biggest cost impact as sugar prices continue to soar
A40: • | B40: Britannia Q1 Results: Profit rises 14% to Rs 593 crore on volumes, price rise
A42: • | B42: Britannia shares fall 5% despite decent Q4 show. Do Morgan Stanley, Nomura see any upside?
A44: • | B44: Stocks in news: BSE, Britannia, Paytm, Meesho, RIL
A46: • | B46: BRITANNIA INDUSTRIES LTD continued strategic operational investments and customer engagements to drive sustainable long-term business performance.
B53: Altman's Z Score Analysis Calculation
B57: Working Capital /Total assets (A)
E58: ='Data Sheet'!G$56 -> 44621 | F58: ='Data Sheet'!H$56 -> 44986 | G58: ='Data Sheet'!I$56 -> 45352 | H58: ='Data Sheet'!J$56 -> 45717 | I58: ='Data Sheet'!K$56 -> 46082
B59: Working Capital | E59: ='Data Sheet'!G65-'Data Sheet'!G60 -> 988 | F59: ='Data Sheet'!H65-'Data Sheet'!H60 -> 447 | G59: ='Data Sheet'!I65-'Data Sheet'!I60 -> 281 | H59: ='Data Sheet'!J65-'Data Sheet'!J60 -> -257 | I59: ='Data Sheet'!K65-'Data Sheet'!K60 -> -11
B60: Total Assets | E60: ='Data Sheet'!G66 -> 7527 | F60: ='Data Sheet'!H66 -> 9351 | G60: ='Data Sheet'!I66 -> 9072 | H60: ='Data Sheet'!J66 -> 8837 | I60: ='Data Sheet'!K66 -> 9730
B61: Working Capital / Total assets (A) | E61: =E59/E60 -> 0.13126079 | F61: =F59/F60 -> 0.047802374 | G61: =G59/G60 -> 0.030974427 | H61: =H59/H60 -> -0.029082268 | I61: =I59/I60 -> -0.0011305242
B63: Retained Earnings /Total Assets (B)
E64: ='Data Sheet'!G$56 -> 44621 | F64: ='Data Sheet'!H$56 -> 44986 | G64: ='Data Sheet'!I$56 -> 45352 | H64: ='Data Sheet'!J$56 -> 45717 | I64: ='Data Sheet'!K$56 -> 46082
B65: Retained Earnings | E65: ='Data Sheet'!G58 -> 2534 | F65: ='Data Sheet'!H58 -> 3510 | G65: ='Data Sheet'!I58 -> 3917 | H65: ='Data Sheet'!J58 -> 4332 | I65: ='Data Sheet'!K58 -> 5082
B66: Total Assets | E66: =E60 -> 7527 | F66: =F60 -> 9351 | G66: =G60 -> 9072 | H66: =H60 -> 8837 | I66: =I60 -> 9730
B67: Retained Earnings /Total Assets (B) | E67: =E65/E66 -> 0.33665471 | F67: =F65/F66 -> 0.37536092 | G67: =G65/G66 -> 0.43176808 | H67: =H65/H66 -> 0.49021161 | I67: =I65/I66 -> 0.52230216
B69: EBIT /Total Assets (C)
E70: ='Data Sheet'!G$56 -> 44621 | F70: ='Data Sheet'!H$56 -> 44986 | G70: ='Data Sheet'!I$56 -> 45352 | H70: ='Data Sheet'!J$56 -> 45717 | I70: ='Data Sheet'!K$56 -> 46082
B71: EBIT | E71: ='Intrinsic Valuation'!H47 -> 2222 | F71: ='Intrinsic Valuation'!I47 -> 3202 | G71: ='Intrinsic Valuation'!J47 -> 3077 | H71: ='Intrinsic Valuation'!K47 -> 3066 | I71: ='Intrinsic Valuation'!L47 -> 3402
B72: Total Assets | E72: =E66 -> 7527 | F72: =F66 -> 9351 | G72: =G66 -> 9072 | H72: =H66 -> 8837 | I72: =I66 -> 9730
B73: EBIT /Total Assets (C) | E73: =E71/E72 -> 0.29520393 | F73: =F71/F72 -> 0.34242327 | G73: =G71/G72 -> 0.33917549 | H73: =H71/H72 -> 0.34695032 | I73: =I71/I72 -> 0.34964029
B75: Market Cap /Long Term Liabilities (D)
E76: ='Data Sheet'!G$56 -> 44621 | F76: ='Data Sheet'!H$56 -> 44986 | G76: ='Data Sheet'!I$56 -> 45352 | H76: ='Data Sheet'!J$56 -> 45717 | I76: ='Data Sheet'!K$56 -> 46082
B77: Market Capital | E77: ='Data Sheet'!G90*'Data Sheet'!G93 -> 80912.4 | F77: ='Data Sheet'!H90*'Data Sheet'!H93 -> 105886.8 | G77: ='Data Sheet'!I90*'Data Sheet'!I93 -> 118141.2 | H77: ='Data Sheet'!J90*'Data Sheet'!J93 -> 110290.8 | I77: ='Data Sheet'!K90*'Data Sheet'!K93 -> 144060
B78: Long Term Liabilities | E78: =SUM('Data Sheet'!G59:G60) -> 4968 | F78: =SUM('Data Sheet'!H59:H60) -> 5816 | G78: =SUM('Data Sheet'!I59:I60) -> 5130 | H78: =SUM('Data Sheet'!J59:J60) -> 4482 | I78: =SUM('Data Sheet'!K59:K60) -> 4623
B79: Market Cap /Long Term Liabilities (D) | E79: =E77/E78 -> 16.286715 | F79: =F77/F78 -> 18.206121 | G79: =G77/G78 -> 23.029474 | H79: =H77/H78 -> 24.607497 | I79: =I77/I78 -> 31.161583
B81: Total Sales /Total Assets (E)
E82: ='Data Sheet'!G$56 -> 44621 | F82: ='Data Sheet'!H$56 -> 44986 | G82: ='Data Sheet'!I$56 -> 45352 | H82: ='Data Sheet'!J$56 -> 45717 | I82: ='Data Sheet'!K$56 -> 46082
B83: Total Sales | E83: ='Data Sheet'!G17 -> 14136 | F83: ='Data Sheet'!H17 -> 16301 | G83: ='Data Sheet'!I17 -> 16769 | H83: ='Data Sheet'!J17 -> 17943 | I83: ='Data Sheet'!K17 -> 19152
B84: Total Assets | E84: =E72 -> 7527 | F84: =F72 -> 9351 | G84: =G72 -> 9072 | H84: =H72 -> 8837 | I84: =I72 -> 9730
B85: Total Sales /Total Assets (E) | E85: =E83/E84 -> 1.8780391 | F85: =F83/F84 -> 1.743236 | G85: =G83/G84 -> 1.8484347 | H85: =H83/H84 -> 2.0304402 | I85: =I83/I84 -> 1.9683453
B87: Altman's Z Score
E88: ='Data Sheet'!G$56 -> 44621 | F88: ='Data Sheet'!H$56 -> 44986 | G88: ='Data Sheet'!I$56 -> 45352 | H88: ='Data Sheet'!J$56 -> 45717 | I88: ='Data Sheet'!K$56 -> 46082
B89: Final Score | E89: =(1.2*E61)+(1.4*E67)+(3.3*E73)+(0.6*E79)+(E85*1) -> 13.253071 | F89: =(1.2*F61)+(1.4*F67)+(3.3*F73)+(0.6*F79)+(F85*1) -> 14.379774 | G89: =(1.2*G61)+(1.4*G67)+(3.3*G73)+(0.6*G79)+(G85*1) -> 17.427043 | H89: =(1.2*H61)+(1.4*H67)+(3.3*H73)+(0.6*H79)+(H85*1) -> 18.591272 | I89: =(1.2*I61)+(1.4*I67)+(3.3*I73)+(0.6*I79)+(I85*1) -> 22.548975
B90: Financial Stability | E90: =IF(E89<1.81,"Distressed",IF(E89>3,"Strong","Grey Zone")) -> Strong | F90: =IF(F89<1.81,"Distressed",IF(F89>3,"Strong","Grey Zone")) -> Strong | G90: =IF(G89<1.81,"Distressed",IF(G89>3,"Strong","Grey Zone")) -> Strong | H90: =IF(H89<1.81,"Distressed",IF(H89>3,"Strong","Grey Zone")) -> Strong | I90: =IF(I89<1.81,"Distressed",IF(I89>3,"Strong","Grey Zone")) -> Strong

Sheet Raw FS
B3: Particulars | C3: 42064 | D3: 42430 | E3: 42795 | F3: 43160 | G3: 43525 | H3: 43891 | I3: 44256 | J3: 44621 | K3: 44986 | L3: 45352 | M3: 45717 | N3: 46082 | S3: 42064 | T3: 42430 | U3: 42795 | V3: 43160 | W3: 43525 | X3: 43891 | Y3: 44256 | Z3: 44621 | AA3: 44986 | AB3: 45352 | AC3: 45717 | AD3: 46082 | AE3: TTM
R4: Sales + | S4: 7858 | T4: 8397 | U4: 9054 | V4: 9914 | W4: 11055 | X4: 11600 | Y4: 13136 | Z4: 14136 | AA4: 16301 | AB4: 16769 | AC4: 17943 | AD4: 19152 | AE4: 19529
B5: Equity Capital | C5: 24 | D5: 24 | E5: 24 | F5: 24 | G5: 24 | H5: 24 | I5: 24 | J5: 24 | K5: 24 | L5: 24 | M5: 24 | N5: 24 | R5: Expenses + | S5: 6988 | T5: 7174 | U5: 7776 | V5: 8413 | W5: 9322 | X5: 9756 | Y5: 10627 | Z5: 11935 | AA5: 13470 | AB5: 13603 | AC5: 14766 | AD5: 15637 | AE5: 15929
B6: Reserves | C6: 1221 | D6: 2068 | E6: 2672 | F6: 3382 | G6: 4229 | H6: 4379 | I6: 3524 | J6: 2534 | K6: 3510 | L6: 3917 | M6: 4332 | N6: 5082 | R6: Operating Profit | S6: 870 | T6: 1224 | U6: 1278 | V6: 1501 | W6: 1732 | X6: 1843 | Y6: 2509 | Z6: 2201 | AA6: 2831 | AB6: 3167 | AC6: 3176 | AD6: 3514 | AE6: 3600
B7: Borrowings - | C7: 145 | D7: 131 | E7: 125 | F7: 201 | G7: 156 | H7: 1538 | I7: 2107 | J7: 2481 | K7: 2997 | L7: 2065 | M7: 1247 | N7: 1380 | R7: OPM % | S7: 11 | T7: 15 | U7: 14 | V7: 15 | W7: 16 | X7: 16 | Y7: 19 | Z7: 16 | AA7: 17 | AB7: 19 | AC7: 18 | AD7: 18 | AE7: 18
B8: Long term Borrowings | C8: 43 | D8: 38 | E8: 31 | F8: 85 | G8: 62 | H8: 766 | I8: 748 | J8: 707 | K8: 1552 | L8: 905 | M8: 713 | N8: 286 | R8: Other Income + | S8: 228 | T8: 115 | U8: 151 | V8: 166 | W8: 206 | X8: 263 | Y8: 313 | Z8: 222 | AA8: 597 | AB8: 211 | AC8: 202 | AD8: 224 | AE8: 228
B9: Short term Borrowings | C9: 97 | D9: 86 | E9: 84 | F9: 94 | G9: 76 | H9: 748 | I9: 1339 | J9: 1759 | K9: 1429 | L9: 1136 | M9: 512 | N9: 1072 | R9: Interest | S9: 4 | T9: 5 | U9: 5 | V9: 8 | W9: 9 | X9: 77 | Y9: 111 | Z9: 144 | AA9: 169 | AB9: 164 | AC9: 139 | AD9: 113 | AE9: 109
B10: Lease Liabilities | C10: 0 | D10: 0 | E10: 0 | F10: 0 | G10: 0 | H10: 0 | I10: 0 | J10: 16 | K10: 17 | L10: 24 | M10: 22 | N10: 22 | R10: Depreciation | S10: 144 | T10: 113 | U10: 119 | V10: 142 | W10: 162 | X10: 185 | Y10: 198 | Z10: 201 | AA10: 226 | AB10: 300 | AC10: 313 | AD10: 337 | AE10: 334
B11: Other Borrowings | C11: 5 | D11: 7 | E11: 9 | F11: 22 | G11: 18 | H11: 24 | I11: 20 | J11: 0 | K11: 0 | L11: 0 | M11: 0 | N11: 0 | R11: Profit before tax | S11: 950 | T11: 1220 | U11: 1304 | V11: 1518 | W11: 1768 | X11: 1844 | Y11: 2514 | Z11: 2078 | AA11: 3033 | AB11: 2913 | AC11: 2927 | AD11: 3289 | AE11: 3385
B12: Other Liabilities - | C12: 1403 | D12: 1271 | E12: 1288 | F12: 1581 | G12: 1829 | H12: 1889 | I12: 2345 | J12: 2487 | K12: 2819 | L12: 3065 | M12: 3235 | N12: 3243 | R12: Tax % | S12: 28 | T12: 32 | U12: 32 | V12: 34 | W12: 35 | X12: 24 | Y12: 26 | Z12: 27 | AA12: 24 | AB12: 27 | AC12: 26 | AD12: 23 | AE12: 0
B13: Non controlling int | C13: 2 | D13: 2 | E13: 3 | F13: 13 | G13: 33 | H13: 36 | I13: 36 | J13: 28 | K13: 30 | L13: 24 | M13: 26 | N13: 29 | R13: Net Profit + | S13: 689 | T13: 825 | U13: 885 | V13: 1004 | W13: 1155 | X13: 1394 | Y13: 1851 | Z13: 1516 | AA13: 2316 | AB13: 2134 | AC13: 2178 | AD13: 2537 | AE13: 2610
B14: Trade Payables | C14: 703 | D14: 769 | E14: 757 | F14: 994 | G14: 1141 | H14: 1047 | I14: 1315 | J14: 1323 | K14: 1449 | L14: 1627 | M14: 1752 | N14: 1896 | S14: 28.71 | T14: 34.36 | U14: 36.85 | V14: 41.83 | W14: 48.23 | X14: 58.33 | Y14: 77.38 | Z14: 63.31 | AA14: 96.39 | AB14: 88.84 | AC14: 90.45 | AD14: 105.18 | AE14: 108.11
B15: Advance from Customers | C15: 18 | D15: 16 | E15: 17 | F15: 31 | G15: 41 | H15: 78 | I15: 55 | J15: 34 | K15: 55 | L15: 42 | M15: 46 | N15: 53 | S15: 28 | T15: 29 | U15: 30 | V15: 30 | W15: 31 | X15: 60 | Y15: 204 | Z15: 89 | AA15: 75 | AB15: 83 | AC15: 83 | AD15: 86 | AE15: 0
B16: Other liability items | C16: 680 | D16: 483 | E16: 511 | F16: 543 | G16: 615 | H16: 729 | I16: 940 | J16: 1103 | K16: 1285 | L16: 1371 | M16: 1410 | N16: 1265
B18: Total Liabilities | C18: 2793 | D18: 3494 | E18: 4109 | F18: 5188 | G18: 6238 | H18: 7830 | I18: 8000 | J18: 7527 | K18: 9351 | L18: 9072 | M18: 8837 | N18: 9730 | S18: 42064 | T18: 42430 | U18: 42795 | V18: 43160 | W18: 43525 | X18: 43891 | Y18: 44256 | Z18: 44621 | AA18: 44986 | AB18: 45352 | AC18: 45717 | AD18: 46082
R19: Cash from Operating Activity - | S19: 584 | T19: 959 | U19: 441 | V19: 1249 | W19: 1156 | X19: 1485 | Y19: 1851 | Z19: 1300 | AA19: 2526 | AB19: 2573 | AC19: 2491 | AD19: 2612
R20: Profit from operations | S20: 861 | T20: 1230 | U20: 1289 | V20: 1517 | W20: 1754 | X20: 1860 | Y20: 2540 | Z20: 2214 | AA20: 2846 | AB20: 3177 | AC20: 3174 | AD20: 3555
B21: Fixed Assets - | C21: 844 | D21: 950 | E21: 1160 | F21: 1346 | G21: 1688 | H21: 1878 | I21: 1793 | J21: 1753 | K21: 2655 | L21: 2771 | M21: 2904 | N21: 2850 | R21: Receivables | S21: -25 | T21: -32 | U21: -9 | V21: -125 | W21: -87 | X21: 79 | Y21: 61 | Z21: -72 | AA21: 1 | AB21: -64 | AC21: -53 | AD21: -13
B22: Land | C22: 107 | D22: 105 | E22: 128 | F22: 246 | G22: 247 | H22: 319 | I22: 326 | J22: 334 | K22: 376 | L22: 384 | M22: 395 | N22: 397 | R22: Inventory | S22: 17 | T22: -35 | U22: -221 | V22: 9 | W22: -127 | X22: 43 | Y22: -351 | Z22: -275 | AA22: 177 | AB22: 13 | AC22: -54 | AD22: -105
B23: Building | C23: 346 | D23: 316 | E23: 376 | F23: 515 | G23: 660 | H23: 732 | I23: 758 | J23: 782 | K23: 1143 | L23: 1298 | M23: 1395 | N23: 1429 | R23: Payables | S23: 0 | T23: 0 | U23: 0 | V23: 0 | W23: 0 | X23: 0 | Y23: 0 | Z23: 64 | AA23: 292 | AB23: 237 | AC23: 202 | AD23: 25
B24: Plant Machinery | C24: 981 | D24: 447 | E24: 641 | F24: 705 | G24: 1053 | H24: 1305 | I24: 1407 | J24: 1546 | K24: 2303 | L24: 2543 | M24: 2844 | N24: 3028 | R24: Working capital changes | S24: 25 | T24: 133 | U24: -451 | V24: 228 | W24: -2 | X24: 127 | Y24: -56 | Z24: -327 | AA24: 406 | AB24: 161 | AC24: 6 | AD24: -121
B25: Equipments | C25: 58 | D25: 16 | E25: 22 | F25: 25 | G25: 31 | H25: 40 | I25: 46 | J25: 52 | K25: 61 | L25: 75 | M25: 81 | N25: 79 | R25: Direct taxes | S25: -301 | T25: -403 | U25: -397 | V25: -496 | W25: -596 | X25: -503 | Y25: -633 | Z25: -587 | AA25: -726 | AB25: -765 | AC25: -689 | AD25: -822
B26: Furniture n fittings | C26: 24 | D26: 22 | E26: 25 | F26: 25 | G26: 28 | H26: 31 | I26: 32 | J26: 32 | K26: 43 | L26: 46 | M26: 49 | N26: 50 | R26: Cash from Investing Activity - | S26: -450 | T26: -705 | U26: -150 | V26: -957 | W26: -852 | X26: -1526 | Y26: 459 | Z26: 914 | AA26: -1507 | AB26: 485 | AC26: 69 | AD26: -741
B27: Railway sidings | C27: 2 | D27: 2 | E27: 2 | F27: 2 | G27: 2 | H27: 2 | I27: 2 | J27: 2 | K27: 2 | L27: 2 | M27: 2 | N27: 2 | R27: Fixed assets purchased | S27: -118 | T27: -251 | U27: -360 | V27: -423 | W27: -401 | X27: -244 | Y27: -242 | Z27: -550 | AA27: -711 | AB27: -553 | AC27: -375 | AD27: -206
B28: Vehicles | C28: 4 | D28: 2 | E28: 2 | F28: 2 | G28: 3 | H28: 5 | I28: 5 | J28: 6 | K28: 10 | L28: 10 | M28: 9 | N28: 9 | R28: Fixed assets sold | S28: 164 | T28: 1 | U28: 8 | V28: 2 | W28: 2 | X28: 1 | Y28: 2 | Z28: 3 | AA28: 78 | AB28: 65 | AC28: 5 | AD28: 2
B29: Intangible Assets | C29: 145 | D29: 116 | E29: 128 | F29: 128 | G29: 134 | H29: 143 | I29: 139 | J29: 140 | K29: 130 | L29: 131 | M29: 134 | N29: 146 | R29: Investments purchased | S29: -277 | T29: -211 | U29: 0 | V29: -537 | W29: -334 | X29: -1327 | Y29: 0 | Z29: -21 | AA29: -1468 | AB29: -191 | AC29: -945 | AD29: -976
B30: Other fixed assets | C30: 44 | D30: 17 | E30: 36 | F30: 36 | G30: 40 | H30: 43 | I30: 46 | J30: 57 | K30: 86 | L30: 72 | M30: 67 | N30: 67 | R30: Investments sold | S30: 0 | T30: 0 | U30: 359 | V30: 0 | W30: 0 | X30: 0 | Y30: 179 | Z30: 1069 | AA30: 443 | AB30: 771 | AC30: 919 | AD30: 254
B31: Gross Block | C31: 1710 | D31: 1041 | E31: 1359 | F31: 1684 | G31: 2195 | H31: 2618 | I31: 2760 | J31: 2948 | K31: 4150 | L31: 4559 | M31: 4974 | N31: 5206 | R31: Interest received | S31: 30 | T31: 66 | U31: 75 | V31: 109 | W31: 117 | X31: 128 | Y31: 233 | Z31: 207 | AA31: 175 | AB31: 170 | AC31: 151 | AD31: 143
B32: Accumulated Depreciation | C32: 866 | D32: 91 | E32: 199 | F32: 338 | G32: 507 | H32: 739 | I32: 967 | J32: 1195 | K32: 1495 | L32: 1788 | M32: 2070 | N32: 2356 | R32: Dividends received | S32: 0 | T32: 0 | U32: 0 | V32: 0 | W32: 0 | X32: 0 | Y32: 0 | Z32: 0 | AA32: 0 | AB32: 0 | AC32: 0 | AD32: 0
B33: Net Block | C33: 844 | D33: 950 | E33: 1160 | F33: 1346 | G33: 1688 | H33: 1878 | I33: 1793 | J33: 1753 | K33: 2655 | L33: 2771 | M33: 2904 | N33: 2850 | R33: Invest in subsidiaries | S33: 0 | T33: -8 | U33: 0 | V33: 0 | W33: 0 | X33: 0 | Y33: 0 | Z33: 0 | AA33: 0 | AB33: 0 | AC33: 0 | AD33: 0
R34: Investment in group cos | S34: 0 | T34: 0 | U34: 0 | V34: 0 | W34: 3 | X34: 6 | Y34: -2 | Z34: 5 | AA34: -159 | AB34: -27 | AC34: -71 | AD34: 55
B35: CWIP | C35: 48 | D35: 90 | E35: 30 | F35: 203 | G35: 101 | H35: 40 | I35: 117 | J35: 536 | K35: 105 | L35: 188 | M35: 89 | N35: 39 | R35: Redemp n Canc of Shares | S35: 0 | T35: 0 | U35: 129 | V35: 18 | W35: 18 | X35: 0 | Y35: 0 | Z35: 0 | AA35: 56 | AB35: 0 | AC35: 0 | AD35: 0
B36: Investments | C36: 518 | D36: 788 | E36: 487 | F36: 1079 | G36: 1476 | H36: 2893 | I36: 2781 | J36: 1762 | K36: 3324 | L36: 2767 | M36: 2865 | N36: 3610 | R36: Other investing items | S36: -181 | T36: -246 | U36: -295 | V36: -232 | W36: -353 | X36: 58 | Y36: -2244 | Z36: -2246 | AA36: -1028 | AB36: -2839 | AC36: -2754 | AD36: -1783
R37: Cash from Financing Activity - | S37: 0 | T37: 4 | U37: 6 | V37: 15 | W37: 30 | X37: 24 | Y37: 103 | Z37: 0 | AA37: 0 | AB37: 0 | AC37: 0 | AD37: 0
B38: Other Assets - | C38: 1383 | D38: 1665 | E38: 2432 | F38: 2560 | G38: 2972 | H38: 3019 | I38: 3310 | J38: 3475 | K38: 3266 | L38: 3346 | M38: 2978 | N38: 3232 | R38: Proceeds from shares | S38: 17 | T38: 0 | U38: 0 | V38: 0 | W38: 0 | X38: 641 | Y38: 568 | Z38: 645 | AA38: 1312 | AB38: 201 | AC38: 26 | AD38: 324
B39: Inventories | C39: 404 | D39: 441 | E39: 661 | F39: 653 | G39: 781 | H39: 741 | I39: 1091 | J39: 1367 | K39: 1193 | L39: 1181 | M39: 1237 | N39: 1346 | R39: Proceeds from borrowings | S39: -27 | T39: 0 | U39: 0 | V39: 0 | W39: -42 | X39: 0 | Y39: 0 | Z39: -984 | AA39: -70 | AB39: -1141 | AC39: -149 | AD39: -192
B40: Trade receivables + | C40: 136 | D40: 171 | E40: 179 | F40: 305 | G40: 394 | H40: 320 | I40: 257 | J40: 332 | K40: 329 | L40: 393 | M40: 449 | N40: 469 | R40: Repayment of borrowings | S40: -3 | T40: -5 | U40: -6 | V40: -7 | W40: -9 | X40: -36 | Y40: -102 | Z40: -119 | AA40: -196 | AB40: -165 | AC40: -172 | AD40: -108
B41: Cash Equivalents | C41: 226 | D41: 88 | E41: 121 | F41: 186 | G41: 110 | H41: 123 | I41: 211 | J41: 185 | K41: 198 | L41: 446 | M41: 312 | N41: 352 | R41: Interest paid fin | S41: -168 | T41: -231 | U41: -288 | V41: -317 | W41: -354 | X41: -433 | Y41: -2824 | Z41: -2485 | AA41: -1359 | AB41: -1732 | AC41: -1768 | AD41: -1804
B42: Loans n Advances | C42: -3 | D42: 8 | E42: 217 | F42: 150 | G42: 63 | H42: 50 | I42: 45 | J42: 63 | K42: 83 | L42: 62 | M42: 67 | N42: 55 | R42: Dividends paid | S42: -4876 | T42: -5133 | U42: -6994 | V42: -5952 | W42: -6519 | X42: -7302 | Y42: -18881 | Z42: -13788 | AA42: -15418 | AB42: -19899 | AC42: -17782 | AD42: -18271
B43: Other asset items | C43: 620 | D43: 958 | E43: 1254 | F43: 1267 | G43: 1623 | H43: 1784 | I43: 1705 | J43: 1528 | K43: 1463 | L43: 1263 | M43: 914 | N43: 1009 | R43: Financial liabilities | S43: 0 | T43: 0 | U43: 0 | V43: 0 | W43: 0 | X43: -49 | Y43: -55 | Z43: -59 | AA43: -59 | AB43: -67 | AC43: -66 | AD43: -68
B44: Total Assets | C44: 2793 | D44: 3494 | E44: 4109 | F44: 5188 | G44: 6238 | H44: 7830 | I44: 8000 | J44: 7527 | K44: 9351 | L44: 9072 | M44: 8837 | N44: 9730 | R44: Other financing items | S44: -734 | T44: -971 | U44: -1335 | V44: -1136 | W44: -1203 | X44: -1409 | Y44: 55 | Z44: 15 | AA44: 35 | AB44: 12 | AC44: 28 | AD44: -146
R45: Net Cash Flow | S45: -47 | T45: 8 | U45: -4 | V45: 60 | W45: -49 | X45: 17 | Y45: 66 | Z45: -32 | AA45: -9 | AB45: 219 | AC45: -194 | AD45: 88 | AT45: Interest paid fin | AU45: -18 | AV45: -2 | AW45: -14 | AX45: -6 | AY45: -7 | AZ45: -90 | BA45: -92 | BB45: -82 | BC45: -88 | BD45: -110 | BE45: -130 | BF45: -133
AT46: Dividends paid | AU46: -2912 | AV46: -3354 | AW46: -3572 | AX46: -3911 | AY46: -4554 | AZ46: -5196 | BA46: -8811 | BB46: -7526 | BC46: -8474 | BD46: -9416 | BE46: -12473 | BF46: -10124
AT47: Financial liabilities | AU47: 0 | AV47: 0 | AW47: 0 | AX47: 0 | AY47: 0 | AZ47: -373 | BA47: -406 | BB47: -407 | BC47: -467 | BD47: -423 | BE47: -498 | BF47: -507
AT48: Other financing items | AU48: -533 | AV48: -685 | AW48: -728 | AX48: -781 | AY48: -928 | AZ48: -1061 | BA48: 0 | BB48: 0 | BC48: -2 | BD48: 0 | BE48: 0 | BF48: 0
AT49: Net Cash Flow | AU49: -33 | AV49: 25 | AW49: -202 | AX49: 21 | AY49: -28 | AZ49: 2595 | BA49: -1374 | BB49: -695 | BC49: -446 | BD49: 111 | BE49: 5258 | BF49: -3487
AR55: Mar Cap Rs.Cr. | AS55: Net Debt | AT55: EV Rs.Cr. | AU55: Sales Rs.Cr. | AV55: EBITDA | AW55: NP 12M Rs.Cr. | AX55: EV / EBITDA | AZ55: Debt Rs.Cr. | BA55: Cash End Rs.Cr.
K56: S.No. | L56: ='Data Sheet'!B1 -> BRITANNIA INDUSTRIES LTD | M56: ='Data Sheet'!B8 -> 4929 | N56: ='Data Sheet'!B6 -> 24.052546 | AR56: ='Data Sheet'!B9 -> 118555 | AS56: =AZ56-BA56 -> 1028 | AT56: =AR56+AS56 -> 119583 | AU56: ='Data Sheet'!K17 -> 19152 | AV56: ='Data Sheet'!K32 -> 3739 | AW56: ='Data Sheet'!K30 -> 2537 | AX56: 30.12 | AZ56: ='Data Sheet'!K59 -> 1380 | BA56: ='Data Sheet'!K69 -> 352
K57: 1 | L57: Nestle India | M57: 1387.2 | N57: 192.66 | AR57: 267260.6 | AS57: =AZ57-BA57 -> 53452.2 | AT57: =AR57+AS57 -> 320712.8 | AU57: 25512.7 | AV57: 5850.7 | AW57: 13363.03 | AX57: 15 | AZ57: 66815.2 | BA57: 13363
K58: 2 | L58: Bikaji Foods | M58: 591.1 | N58: 25.1 | AR58: 14835.8 | AS58: =AZ58-BA58 -> 2967.1 | AT58: =AR58+AS58 -> 17802.9 | AU58: 2712.7 | AV58: 387.4 | AW58: 741.79 | AX58: 15 | AZ58: 3708.9 | BA58: 741.8
K59: 3 | L59: Milky Mist Dairy | M59: 317.25 | N59: 76.97 | AR59: 24419.2 | AS59: =AZ59-BA59 -> 4883.8 | AT59: =AR59+AS59 -> 29303 | AU59: 3893.6 | AV59: 386.7 | AW59: 1220.96 | AX59: 15 | AZ59: 6104.8 | BA59: 1221
K60: 4 | L60: Marico | M60: 832.3 | N60: 130.07 | AR60: 108260.3 | AS60: =AZ60-BA60 -> 21652.1 | AT60: =AR60+AS60 -> 129912.4 | AU60: 15828 | AV60: 3912 | AW60: 5413.02 | AX60: 15 | AZ60: 27065.1 | BA60: 5413
K61: 5 | L61: Varun Beverages | M61: 436.15 | N61: 338.09 | AR61: 147458.9 | AS61: =AZ61-BA61 -> 29491.8 | AT61: =AR61+AS61 -> 176950.7 | AU61: 33804.9 | AV61: 9152.2 | AW61: 7372.94 | AX61: 15 | AZ61: 36864.7 | BA61: 7372.9
K62: 6 | L62: Godrej Consumer | M62: 879.75 | N62: 102.28 | AR62: 89984.1 | AS62: =AZ62-BA62 -> 17996.8 | AT62: =AR62+AS62 -> 107980.9 | AU62: 16901.9 | AV62: 3027.1 | AW62: 4499.21 | AX62: 15 | AZ62: 22496 | BA62: 4499.2
K63: 7 | L63: Dabur India | M63: 387.4 | N63: 177.28 | AR63: 68678.9 | AS63: =AZ63-BA63 -> 13735.8 | AT63: =AR63+AS63 -> 82414.7 | AU63: 15057.6 | AV63: 3517 | AW63: 3433.94 | AX63: 15 | AZ63: 17169.7 | BA63: 3433.9
K64: 8 | L64: Patanjali Foods | M64: 409.45 | N64: 108.68 | AR64: 44497.5 | AS64: =AZ64-BA64 -> 8899.5 | AT64: =AR64+AS64 -> 53397 | AU64: 45349.8 | AV64: 2015.2 | AW64: 2224.88 | AX64: 15 | AZ64: 11124.4 | BA64: 2224.9

Sheet List of Stocks
B2: COMPANY_NAME | C2: BSE | D2: NSE | E2: Industry
B3: 20 MICRONS LTD | C3: 533022 | D3: 20MICRONS | E3: Mining
B4: 21ST CENTURY MANAGEMENT SERVICES LTD | C4: 526921 | D4: 21STCENMGM | E4: Other Financial Services
B5: 3I INFOTECH LTD | C5: 532628 | D5: 3IINFOTECH | E5: IT Consulting & Software
B6: 3M (INDIA) LTD | C6: 523395 | D6: 3M(INDIA) | E6: Diversified
B7: 3M INDIA LTD | C7: 523395 | D7: 3MINDIA | E7: Diversified
B8: 3P LAND HOLDINGS LTD | C8: 516092 | D8: 3PLAND | E8: Paper & Paper Products
B9: 5PAISA CAPITAL LTD | C9: 540776 | D9: 5PAISA | E9: Other Financial Services
B10: 63 MOONS TECHNOLOGIES LTD | C10: 526881 | D10: 63MOONS | E10: IT Consulting & Software
B11: 7NR RETAIL LTD | C11: 540615 | D11: Not Listed | E11: Specialty Retail
B12: 7SEAS ENTERTAINMENT LTD | C12: 540874 | D12: Not Listed | E12: Movies & Entertainment
B13: 8K MILES SOFTWARE SERVICES LTD | C13: 512161 | D13: 8KMILES | E13: Internet Software & Services
B14: A & M FEBCON LTD | C14: 540697 | D14: Not Listed | E14: Industrial Machinery
B15: A AND M JUMBO BAGS LTD | C15: Not Listed | D15: AMJUMBO | E15: SME
B16: A INFRASTRUCTURE LTD | C16: 539620 | D16: Not Listed | E16: Cement & Cement Products
B17: A K SPINTEX LTD | C17: 539300 | D17: Not Listed | E17: Textiles
B18: A K CAPITAL SERVICES LTD | C18: 530499 | D18: Not Listed | E18: Finance (including NBFCs)
B19: A.F. Enterprises Ltd | C19: 538351 | D19: AFEL | E19: Investment Companies
B20: A-1 ACID LTD | C20: 542012 | D20: Not Listed | E20: Comm.Trading & Distribution
B21: A2Z INFRA ENGINEERING LTD | C21: 533292 | D21: A2ZINFRA | E21: Utilities:Non-Elec.
B22: AADHAAR VENTURES (INDIA) LTD | C22: 531611 | D22: Not Listed | E22: Finance (including NBFCs)
B23: AADHAAR VENTURES INDIA LTD | C23: 531611 | D23: Not Listed | E23: Finance (including NBFCs)
B24: AAKASH EXPLORATION SERVICES LTD | C24: Not Listed | D24: AAKASH | E24: SME
B25: AANANDA LAKSHMI SPINNING MILLS LTD | C25: 539096 | D25: Not Listed | E25: Textiles
B26: AANCHAL ISPAT LTD | C26: 538812 | D26: Not Listed | E26: Iron & Steel/Interm.Products
B27: AAR COMMERCIAL COMPANY LTD | C27: 539632 | D27: Not Listed | E27: Distributors
B28: Aar Shyam India Investment Company Ltd | C28: 542377 | D28: AARSHYAM | E28: Finance (including NBFCs)
B29: AAREY DRUGS & PHARMACEUTICALS LTD | C29: 524412 | D29: Not Listed | E29: Pharmaceuticals
B30: AARON INDUSTRIES LTD | C30: Not Listed | D30: AARON | E30: SME
B31: Aartech Solonics Ltd | C31: 542580 | D31: AARTECH | E31: Heavy Electrical Equipment
B32: AARTI DRUGS LTD | C32: 524348 | D32: AARTIDRUGS | E32: Pharmaceuticals
B33: AARTI INDUSTRIES LTD | C33: 524208 | D33: AARTIIND | E33: Commodity Chemicals
B34: AARV INFRATEL LTD | C34: 526488 | D34: Not Listed | E34: Textiles
B35: AARVEE DENIMS & EXPORTS LTD | C35: 514274 | D35: AARVEEDEN | E35: Textiles
B36: AARVI ENCON LTD | C36: Not Listed | D36: AARVI | E36: SME
B37: AASHEE INFOTECH LTD | C37: 519319 | D37: Not Listed | E37: Internet Software & Services
B38: AASWA TRADING & EXPORTS LTD | C38: 512038 | D38: Not Listed | E38: Comm.Trading & Distribution
B39: AAVAS FINANCIERS LTD | C39: 541988 | D39: AAVAS | E39: Housing Finance
B40: AAYUSH FOOD AND HERBS LTD | C40: 539528 | D40: Not Listed | E40: Packaged Foods
B41: ABAN OFFSHORE LTD | C41: 523204 | D41: ABAN | E41: Exploration & Production
B42: ABANS ENTERPRISES LTD | C42: 512165 | D42: Not Listed | E42: Comm.Trading & Distribution
B43: ABB INDIA LTD | C43: 500002 | D43: ABB | E43: Heavy Electrical Equipment
B44: ABBOTT (INDIA) LTD | C44: 500488 | D44: ABBOT(INDIA) | E44: Pharmaceuticals
B45: ABBOTT INDIA LTD | C45: 500488 | D45: ABBOTINDIA | E45: Pharmaceuticals
B46: ABC (INDIA) LTD | C46: 520123 | D46: Not Listed | E46: Surface Transportation
B47: ABC GAS INTERNATIONAL LTD | C47: 513119 | D47: Not Listed | E47: Copper
B48: ABC INDIA LTD | C48: 520123 | D48: Not Listed | E48: Surface Transportation
... B56: ABIRAMI FINANCIAL SERVICES INDIA LTD | C56: 511756 | D56: Not Listed | E56: Finance (including NBFCs)
B57: ABM INTERNATIONAL LTD | C57: Not Listed | D57: ABMINTLTD | E57: Others
B58: ABM KNOWLEDGEWARE LTD | C58: 531161 | D58: Not Listed | E58: IT Software Products
B59: ACC LTD | C59: 500410 | D59: ACC | E59: Cement & Cement Products
B60: ACCEL LTD | C60: 517494 | D60: Not Listed | E60: Storage Media & Peripherals
B61: ACCELYA KALE SOLUTIONS LTD | C61: 532268 | D61: ACCELYA | E61: IT Consulting & Software
B62: ACCORD SYNERGY LTD | C62: Not Listed | D62: ACCORD | E62: SME
B63: ACCURACY SHIPPING LTD | C63: Not Listed | D63: ACCURACY | E63: SME
B64: ACE EDUTREND LTD | C64: 530093 | D64: Not Listed | E64: Education
B65: ACE INTEGRATED SOLUTIONS LTD | C65: Not Listed | D65: ACEINTEG | E65: SME
B66: ACE MEN ENGG WORKS LTD | C66: 539661 | D66: Not Listed | E66: Distributors
B67: ACE SOFTWARE EXPORTS LTD | C67: 531525 | D67: Not Listed | E67: IT Software Products
B68: Achal Investments Ltd | C68: 538570 | D68: ACHAL | E68: Other Financial Services
B69: ACI INFOCOM LTD | C69: 517356 | D69: Not Listed | E69: Storage Media & Peripherals
B70: ACKNIT INDUSTRIES LTD | C70: 530043 | D70: Not Listed | E70: Other Apparels & Accessories
B71: ACME RESOURCES LTD | C71: 539391 | D71: Not Listed | E71: Finance (including NBFCs)
B72: ACROW INDIA LTD. | C72: 513149 | D72: ACROW | E72: Iron &amp; Steel Products
B73: ACRYSIL LTD | C73: 524091 | D73: Not Listed | E73: Plastic Products
B74: ACTION CONSTRUCTION EQUIPMENT LTD | C74: 532762 | D74: ACE | E74: Transport Related Services
B75: ACTION FINANCIAL SERVICES (INDIA) LTD | C75: 511706 | D75: Not Listed | E75: Other Financial Services
B76: ACTION FINANCIAL SERVICES INDIA LTD | C76: 511706 | D76: Not Listed | E76: Other Financial Services
B77: ACTIVE CLOTHING CO LTD | C77: 541144 | D77: Not Listed | E77: Other Apparels & Accessories
... B135: AGRI-TECH INDIA LTD | C135: 537292 | D135: AGRITECH | E135: Other Agricultural Products
B136: AGRO PHOS (INDIA) LTD | C136: Not Listed | D136: AGROPHOS | E136: SME
B137: AGRO PHOS INDIA LTD | C137: Not Listed | D137: AGROPHOS | E137: SME
B138: AGRO TECH FOODS LTD | C138: 500215 | D138: ATFL | E138: Other Agricultural Products
B139: AHIMSA INDUSTRIES LTD | C139: Not Listed | D139: AHIMSA | E139: SME
B140: AHLADA ENGINEERS LTD | C140: Not Listed | D140: AHLADA | E140: SME
B141: AHLUWALIA CONTRACTS (INDIA) LTD | C141: 532811 | D141: AHLUCONT | E141: Realty
B142: AHLUWALIA CONTRACTS INDIA LTD | C142: 532811 | D142: AHLUCONT | E142: Realty
B143: AHMEDABAD STEELCRAFT LTD | C143: 522273 | D143: Not Listed | E143: Iron & Steel/Interm.Products
B144: AI CHAMPDANY INDUSTRIES LTD | C144: 532806 | D144: Not Listed | E144: Jute & Jute Products
B145: AIA ENGINEERING LTD | C145: 532683 | D145: AIAENG | E145: Other Industrial Goods
B146: AIMCO PESTICIDES LTD | C146: 524288 | D146: Not Listed | E146: Agrochemicals
B147: AIRAN LTD | C147: Not Listed | D147: AIRAN | E147: SME
B148: AIRO LAM LTD | C148: Not Listed | D148: AIROLAM | E148: SME
B149: AISHWARYA TELECOM LTD | C149: 532975 | D149: Not Listed | E149: Telecom Equipment
B150: AJANTA PHARMA LTD | C150: 532331 | D150: AJANTPHARM | E150: Pharmaceuticals
B151: AJANTA SOYA LTD | C151: 519216 | D151: Not Listed | E151: Edible Oils
B152: AJCON GLOBAL SERVICES LTD | C152: 511692 | D152: Not Listed | E152: Other Financial Services
B153: AJEL LTD | C153: 530713 | D153: Not Listed | E153: IT Consulting & Software
B154: AJMERA REALTY & INFRA (INDIA) LTD | C154: 513349 | D154: AJMERA | E154: Realty
B155: AJMERA REALTY & INFRA INDIA LTD | C155: 513349 | D155: AJMERA | E155: Realty
B156: AJOONI BIOTECH LTD | C156: Not Listed | D156: AJOONI | E156: SME
B157: AJWA FUN WORLD & RESORT LTD | C157: 526628 | D157: Not Listed | E157: Other Leisure Facilities
B158: AKAR AUTO INDUSTRIES LTD | C158: 530621 | D158: Not Listed | E158: Industrial Machinery
B159: AKASH INFRA PROJECTS LTD | C159: Not Listed | D159: AKASH | E159: SME
B160: AKASHDEEP METAL INDUSTRIES LTD | C160: 538778 | D160: Not Listed | E160: Finance (including NBFCs)
B161: AKG EXIM LTD | C161: Not Listed | D161: AKG | E161: SME
B162: AKI (INDIA) LTD | C162: 542020 | D162: Not Listed | E162: Other Apparels & Accessories
B163: AKI INDIA LTD | C163: 542020 | D163: Not Listed | E163: Other Apparels & Accessories
B164: AKM LACE AND EMBROTEX LTD | C164: 540718 | D164: Not Listed | E164: Textiles
B165: AKME STAR HOUSING FINANCE LTD | C165: 539017 | D165: Not Listed | E165: Housing Finance
...
