Workbook
Name UPDATE: '[1]Data Sheet'!$E$1
Name UPDATE: 'Data Sheet'!$E$1

Sheet AI Valuation Summary
A1: Infosys Ltd (INFY) - Institutional Valuation
A4: Current Price | B4: Intrinsic Value | C4: Margin of Safety | D4: Verdict | E4: WACC | F4: Altman Z-Score | G4: DuPont ROE
A5: =DCF!D44 -> 1051 | B5: =DCF!D42 -> 711.71706 | C5: =(B5-A5)/A5 -> -0.32281917 | D5: =IF(C5>0.15,"UNDERVALUED / BUY",IF(C5<-0.15,"OVERVALUED / SELL","FAIRLY VALUED / HOLD")) -> OVERVALUED / SELL | E5: =DCF!D20 -> 0.12035248 | F5: ='Altman''s Z Score'!I89 -> 9.0746518 | G5: ='Dupont Analysis'!I78 -> 0.32146075
A7: THE 4 CORE VALUATION PILLARS
A8: Pillar 1: FCF Engine | B8: CFO ₹33986.0 Cr vs PAT ₹29474.0 Cr | EBIT Mgn 22.62% | CCC 72.0 days
A9: Pillar 2: Growth Trajectory | B9: 3Y Sales CAGR 6.3% | 5Y CAGR 8.7% | Forecast g 5.2% | Terminal g 4.0%
A10: Pillar 3: Cost of Capital (WACC) | B10: WACC 13.33% | Ke 12.73% | Beta 0.88 | ERP 6.5% | Rf 7.0%
A11: Pillar 4: Relative Multiples | B11: P/E 13.7x | P/B 4.67x | EV/EBITDA 5.9x | EV/Sales 1.39x
A13: 5-Year Discounted Cash Flow (DCF) Schedule (Amounts in ₹ Cr)
A14: Year | B14: EBIT | C14: NOPAT | D14: Reinvest Rate | E14: FCFF | F14: Discount Factor | G14: PV of FCFF
A15: Year 1 | B15: =DCF!I8 -> 42512.372 | C15: =DCF!I10 -> 29758.66 | D15: =DCF!I11 -> 0.28501193 | E15: =DCF!I12 -> 21277.087 | F15: =DCF!I14 -> 0.94476253 | G15: =DCF!I16 -> 20101.795
A16: Year 2 | B16: =DCF!J8 -> 44723.015 | C16: =DCF!J10 -> 31306.111 | D16: =DCF!J11 -> 0.29684822 | E16: =DCF!J12 -> 22012.947 | F16: =DCF!J14 -> 0.84327259 | G16: =DCF!J16 -> 18562.915
A17: Year 3 | B17: =DCF!K8 -> 47048.612 | C17: =DCF!K10 -> 32934.028 | D17: =DCF!K11 -> 0.30868451 | E17: =DCF!K12 -> 22767.804 | F17: =DCF!K14 -> 0.75268507 | G17: =DCF!K16 -> 17136.986
A18: Year 4 | B18: =DCF!L8 -> 49495.14 | C18: =DCF!L10 -> 34646.598 | D18: =DCF!L11 -> 0.3205208 | E18: =DCF!L12 -> 23541.643 | F18: =DCF!L14 -> 0.67182881 | G18: =DCF!L16 -> 15815.954
A19: Year 5 | B19: =DCF!M8 -> 52068.887 | C19: =DCF!M10 -> 36448.221 | D19: =DCF!M11 -> 0.3323571 | E19: =DCF!M12 -> 24334.396 | F19: =DCF!M14 -> 0.59965843 | G19: =DCF!M16 -> 14592.326
A21: Enterprise to Equity Value Bridge
A22: PV of 5-Year FCFFs | B22: =DCF!D33 -> 86209.976
A23: Terminal Value | B23: =DCF!D29 -> 314959.45
A24: PV of Terminal Value | B24: =DCF!D34 -> 188868.09
A25: Enterprise Value (Operating Assets) | B25: =DCF!D35 -> 275078.06
A26: Add: Estimated Cash & Liquid Assets | B26: =DCF!D37 -> 22201
A27: Less: Total Debt & Borrowings | B27: =DCF!D38 -> 9176
A28: Net Equity Value | B28: =DCF!D39 -> 288103.06
A29: Shares Outstanding | B29: =DCF!D40 -> 404.8
A30: Intrinsic Value per Share | B30: =DCF!D42 -> 711.71706
A31: Current Market Price | B31: =DCF!D44 -> 1051
A32: Margin of Safety / Discount | B32: =(B5-A5)/A5 -> -0.32281917

Sheet Profit & Loss
A1: ='Data Sheet'!B1 -> Infosys Ltd | H1: =UPDATE | M1: SCREENER.IN
A3: Narration | B3: ='Data Sheet'!B16 -> 43160 | C3: ='Data Sheet'!C16 -> 43525 | D3: ='Data Sheet'!D16 -> 43891 | E3: ='Data Sheet'!E16 -> 44256 | F3: ='Data Sheet'!F16 -> 44621 | G3: ='Data Sheet'!G16 -> 44986 | H3: ='Data Sheet'!H16 -> 45352 | I3: ='Data Sheet'!I16 -> 45717 | ... K3: ='Data Sheet'!K16 -> TTM | L3: Trailing | M3: Best Case | N3: Worst Case
A4: Sales | B4: ='Data Sheet'!B17 -> 70522 | C4: ='Data Sheet'!C17 -> 82675 | D4: ='Data Sheet'!D17 -> 90791 | E4: ='Data Sheet'!E17 -> 100472 | F4: ='Data Sheet'!F17 -> 121641 | G4: ='Data Sheet'!G17 -> 146767 | H4: ='Data Sheet'!H17 -> 153670 | I4: ='Data Sheet'!I17 -> 162990 | ... K4: ='Data Sheet'!K17 -> 184582 | L4: =SUM(Quarters!H4:K4) -> 184582 | M4: =$K4+M23*K4 -> 196210.74 | N4: =$K4+N23*L4 -> 190710.97
A5: Expenses | B5: =SUM('Data Sheet'!B18,'Data Sheet'!B20:B24, -1*'Data Sheet'!B19) -> 52186.28 | C5: =SUM('Data Sheet'!C18,'Data Sheet'!C20:C24, -1*'Data Sheet'!C19) -> 62833 | D5: =SUM('Data Sheet'!D18,'Data Sheet'!D20:D24, -1*'Data Sheet'!D19) -> 68093.25 | E5: =SUM('Data Sheet'!E18,'Data Sheet'!E20:E24, -1*'Data Sheet'!E19) -> 72339.84 | F5: =SUM('Data Sheet'!F18,'Data Sheet'!F20:F24, -1*'Data Sheet'!F19) -> 90014.34 | G5: =SUM('Data Sheet'!G18,'Data Sheet'!G20:G24, -1*'Data Sheet'!G19) -> 111542.92 | H5: =SUM('Data Sheet'!H18,'Data Sheet'!H20:H24, -1*'Data Sheet'!H19) -> 118325.9 | I5: =SUM('Data Sheet'!I18,'Data Sheet'!I20:I24, -1*'Data Sheet'!I19) -> 123872.4 | ... K5: =SUM('Data Sheet'!K18,'Data Sheet'!K20:K24, -1*'Data Sheet'!K19) -> 0 | L5: =SUM(Quarters!H5:K5) -> 140837 | M5: =M4-M6 -> 97479.66 | N5: =N4-N6 -> 145513.43
A6: Operating Profit | B6: =B4-B5 -> 18335.72 | C6: =C4-C5 -> 19842 | D6: =D4-D5 -> 22697.75 | E6: =E4-E5 -> 28132.16 | F6: =F4-F5 -> 31626.66 | G6: =G4-G5 -> 35224.08 | H6: =H4-H5 -> 35344.1 | I6: =I4-I5 -> 39117.6 | ... K6: =K4-K5 -> 184582 | L6: =SUM(Quarters!H6:K6) -> 43745 | M6: =M4*M24 -> 98731.076 | N6: =N4*N24 -> 45197.535
A7: Other Income | B7: ='Data Sheet'!B25 -> 3311 | C7: ='Data Sheet'!C25 -> 2882 | D7: ='Data Sheet'!D25 -> 2803 | E7: ='Data Sheet'!E25 -> 2201 | F7: ='Data Sheet'!F25 -> 2295 | G7: ='Data Sheet'!G25 -> 2701 | H7: ='Data Sheet'!H25 -> 4711 | I7: ='Data Sheet'!I25 -> 3600 | ... K7: ='Data Sheet'!K25 -> 2975 | L7: =SUM(Quarters!H7:K7) -> 2975 | M7: 0 | N7: 0
A8: Depreciation | B8: ='Data Sheet'!B26 -> 1863 | C8: ='Data Sheet'!C26 -> 2011 | D8: ='Data Sheet'!D26 -> 2893 | E8: ='Data Sheet'!E26 -> 3267 | F8: ='Data Sheet'!F26 -> 3476 | G8: ='Data Sheet'!G26 -> 4225 | H8: ='Data Sheet'!H26 -> 4678 | I8: ='Data Sheet'!I26 -> 4812 | ... K8: ='Data Sheet'!K26 -> 5007 | L8: =SUM(Quarters!H8:K8) -> 5007 | M8: =+$L8 -> 5007 | N8: =+$L8 -> 5007
A9: Interest | B9: ='Data Sheet'!B27 -> 0 | C9: ='Data Sheet'!C27 -> 0 | D9: ='Data Sheet'!D27 -> 170 | E9: ='Data Sheet'!E27 -> 195 | F9: ='Data Sheet'!F27 -> 200 | G9: ='Data Sheet'!G27 -> 284 | H9: ='Data Sheet'!H27 -> 470 | I9: ='Data Sheet'!I27 -> 416 | ... K9: ='Data Sheet'!K27 -> 430 | L9: =SUM(Quarters!H9:K9) -> 430 | M9: =+$L9 -> 430 | N9: =+$L9 -> 430
A10: Profit before tax | B10: ='Data Sheet'!B28 -> 20270 | C10: ='Data Sheet'!C28 -> 21041 | D10: ='Data Sheet'!D28 -> 22007 | E10: ='Data Sheet'!E28 -> 26628 | F10: ='Data Sheet'!F28 -> 30110 | G10: ='Data Sheet'!G28 -> 33322 | H10: ='Data Sheet'!H28 -> 35988 | I10: ='Data Sheet'!I28 -> 37608 | ... K10: ='Data Sheet'!K28 -> 41283 | L10: =SUM(Quarters!H10:K10) -> 41283 | M10: =M6+M7-SUM(M8:M9) -> 93294.076 | N10: =N6+N7-SUM(N8:N9) -> 39760.535
A11: Tax | B11: ='Data Sheet'!B29 -> 20270 | C11: ='Data Sheet'!C29 -> 21041 | D11: ='Data Sheet'!D29 -> 22007 | E11: ='Data Sheet'!E29 -> 26628 | F11: ='Data Sheet'!F29 -> 30110 | G11: ='Data Sheet'!G29 -> 33322 | H11: ='Data Sheet'!H29 -> 35988 | I11: ='Data Sheet'!I29 -> 37608 | ... K11: ='Data Sheet'!K29 -> 41283 | L11: =SUM(Quarters!H11:K11) -> 41283 | M11: =IF($L10>0,$L11/$L10,0) -> 1 | N11: =IF($L10>0,$L11/$L10,0) -> 1
A12: Net profit | B12: ='Data Sheet'!B30 -> 16029 | C12: ='Data Sheet'!C30 -> 15410 | D12: ='Data Sheet'!D30 -> 16639 | E12: ='Data Sheet'!E30 -> 19423 | F12: ='Data Sheet'!F30 -> 22146 | G12: ='Data Sheet'!G30 -> 24108 | H12: ='Data Sheet'!H30 -> 26248 | I12: ='Data Sheet'!I30 -> 26750 | ... K12: ='Data Sheet'!K30 -> 30325 | L12: =SUM(Quarters!H12:K12) -> 30325 | M12: =M10-M11*M10 -> 0 | N12: =N10-N11*N10 -> 0
A13: EPS | B13: =IF('Data Sheet'!B93>0,B12/'Data Sheet'!B93,0) -> 34.890403 | C13: =IF('Data Sheet'!C93>0,C12/'Data Sheet'!C93,0) -> 33.543023 | D13: =IF('Data Sheet'!D93>0,D12/'Data Sheet'!D93,0) -> 36.218193 | E13: =IF('Data Sheet'!E93>0,E12/'Data Sheet'!E93,0) -> 42.278139 | F13: =IF('Data Sheet'!F93>0,F12/'Data Sheet'!F93,0) -> 48.205307 | G13: =IF('Data Sheet'!G93>0,G12/'Data Sheet'!G93,0) -> 52.476002 | H13: =IF('Data Sheet'!H93>0,H12/'Data Sheet'!H93,0) -> 57.13415 | I13: =IF('Data Sheet'!I93>0,I12/'Data Sheet'!I93,0) -> 58.226856 | ... K13: =IF('Data Sheet'!K93>0,K12/'Data Sheet'!K93,0) -> 66.008576 | L13: =IF('Data Sheet'!$B6>0,'Profit & Loss'!L12/'Data Sheet'!$B6,0) -> 74.696144 | M13: =IF('Data Sheet'!$B6>0,'Profit & Loss'!M12/'Data Sheet'!$B6,0) -> 0 | N13: =IF('Data Sheet'!$B6>0,'Profit & Loss'!N12/'Data Sheet'!$B6,0) -> 0
A14: Price to earning | B14: =IF(B15>0,B15/B13,"") -> 14.777703 | C14: =IF(C15>0,C15/C13,"") -> 17.302555 | D14: =IF(D15>0,D15/D13,"") -> 20.48418 | E14: =IF(E15>0,E15/E13,"") -> 17.306817 | F14: =IF(F15>0,F15/F13,"") -> 25.999212 | G14: =IF(G15>0,G15/G13,"") -> 32.839773 | H14: =IF(H15>0,H15/H13,"") -> 25.891695 | I14: =IF(I15>0,I15/I13,"") -> 28.445637 | ... K14: =IF(K15>0,K15/K13,"") -> 19.695926 | L14: =IF(L13>0,L15/L13,0) -> 14.070338 | M14: =M25 -> 22.129502 | N14: =N25 -> 14.070338
A15: Price | B15: ='Data Sheet'!B90 -> 515.6 | C15: ='Data Sheet'!C90 -> 580.38 | D15: ='Data Sheet'!D90 -> 741.9 | E15: ='Data Sheet'!E90 -> 731.7 | F15: ='Data Sheet'!F90 -> 1253.3 | G15: ='Data Sheet'!G90 -> 1723.3 | H15: ='Data Sheet'!H90 -> 1479.3 | I15: ='Data Sheet'!I90 -> 1656.3 | ... K15: ='Data Sheet'!K90 -> 1300.1 | L15: ='Data Sheet'!B8 -> 1051 | M15: =M13*M14 -> 0 | N15: =N13*N14 -> 0
A17: RATIOS:
A18: Dividend Payout | B18: =IF('Data Sheet'!B30>0, 'Data Sheet'!B31/'Data Sheet'!B30, 0) -> 0.59 | C18: =IF('Data Sheet'!C30>0, 'Data Sheet'!C31/'Data Sheet'!C30, 0) -> 0.6 | D18: =IF('Data Sheet'!D30>0, 'Data Sheet'!D31/'Data Sheet'!D30, 0) -> 0.45 | E18: =IF('Data Sheet'!E30>0, 'Data Sheet'!E31/'Data Sheet'!E30, 0) -> 0.59 | F18: =IF('Data Sheet'!F30>0, 'Data Sheet'!F31/'Data Sheet'!F30, 0) -> 0.59 | G18: =IF('Data Sheet'!G30>0, 'Data Sheet'!G31/'Data Sheet'!G30, 0) -> 0.58 | H18: =IF('Data Sheet'!H30>0, 'Data Sheet'!H31/'Data Sheet'!H30, 0) -> 0.73 | I18: =IF('Data Sheet'!I30>0, 'Data Sheet'!I31/'Data Sheet'!I30, 0) -> 0.67 | ... K18: =IF('Data Sheet'!K30>0, 'Data Sheet'!K31/'Data Sheet'!K30, 0) -> 0
A19: OPM | B19: =IF(B6>0,B6/B4,0) -> 0.26 | C19: =IF(C6>0,C6/C4,0) -> 0.24 | D19: =IF(D6>0,D6/D4,0) -> 0.25 | E19: =IF(E6>0,E6/E4,0) -> 0.28 | F19: =IF(F6>0,F6/F4,0) -> 0.26 | G19: =IF(G6>0,G6/G4,0) -> 0.24 | H19: =IF(H6>0,H6/H4,0) -> 0.23 | I19: =IF(I6>0,I6/I4,0) -> 0.24 | ... L19: =IF(L6>0,L6/L4,0) -> 0.23699494
G22: TRENDS: | H22: 10 YEARS | I22: 7 YEARS | J22: 5 YEARS | K22: 3 YEARS | L22: RECENT | M22: BEST | N22: WORST
G23: Sales Growth | H23: =IF(B4=0,"",POWER($K4/B4,1/9)-1) -> 0.11283151 | I23: =IF(D4=0,"",POWER($K4/D4,1/7)-1) -> 0.10667713 | J23: =IF(F4=0,"",POWER($K4/F4,1/5)-1) -> 0.0869808 | K23: =IF(H4=0,"",POWER($K4/H4, 1/3)-1) -> 0.063000377 | L23: =IF(ISERROR(MAX(IF(J4=0,"",(K4-J4)/J4),IF(K4=0,"",(L4-K4)/K4))),"",MAX(IF(J4=0,"",(K4-J4)/J4),IF(K4=0,"",(L4-K4)/K4))) -> 0.03320459 | M23: =MAX(K23:L23) -> 0.063000377 | N23: =MIN(H23:L23) -> 0.03320459
G24: OPM | H24: =IF(SUM(B4:$K$4)=0,"",SUMPRODUCT(B19:$K$19,B4:$K$4)/SUM(B4:$K$4)) -> 0.35272717 | I24: =IF(SUM(E4:$K$4)=0,"",SUMPRODUCT(E19:$K$19,E4:$K$4)/SUM(E4:$K$4)) -> 0.37674166 | J24: =IF(SUM(G4:$K$4)=0,"",SUMPRODUCT(G19:$K$19,G4:$K$4)/SUM(G4:$K$4)) -> 0.40567789 | K24: =IF(SUM(I4:$K$4)=0, "", SUMPRODUCT(I19:$K$19,I4:$K$4)/SUM(I4:$K$4)) -> 0.50318896 | L24: =L19 -> 0.23699494 | M24: =MAX(K24:L24) -> 0.50318896 | N24: =MIN(H24:L24) -> 0.23699494
G25: Price to Earning | H25: =IF(ISERROR(AVERAGEIF(B14:$L14,">0")),"",AVERAGEIF(B14:$L14,">0")) -> 22.101813 | I25: =IF(ISERROR(AVERAGEIF(E14:$L14,">0")),"",AVERAGEIF(E14:$L14,">0")) -> 23.819438 | J25: =IF(ISERROR(AVERAGEIF(G14:$L14,">0")),"",AVERAGEIF(G14:$L14,">0")) -> 24.54158 | K25: =IF(ISERROR(AVERAGEIF(I14:$L14,">0")),"",AVERAGEIF(I14:$L14,">0")) -> 22.129502 | L25: =L14 -> 14.070338 | M25: =MAX(K25:L25) -> 22.129502 | N25: =MIN(H25:L25) -> 14.070338

Sheet Quarters
A1: ='Profit & Loss'!A1 -> Infosys Ltd | E1: =UPDATE | J1: SCREENER.IN
A3: Narration | B3: ='Data Sheet'!B41 -> 45352 | C3: ='Data Sheet'!C41 -> 45444 | D3: ='Data Sheet'!D41 -> 45536 | E3: ='Data Sheet'!E41 -> 45627 | F3: ='Data Sheet'!F41 -> 45717 | G3: ='Data Sheet'!G41 -> 45809 | H3: ='Data Sheet'!H41 -> 45901 | I3: ='Data Sheet'!I41 -> 45992 | ... K3: ='Data Sheet'!K41 -> 46174
A4: Sales | B4: ='Data Sheet'!B42 -> 37923 | C4: ='Data Sheet'!C42 -> 39315 | D4: ='Data Sheet'!D42 -> 40986 | E4: ='Data Sheet'!E42 -> 41764 | F4: ='Data Sheet'!F42 -> 40925 | G4: ='Data Sheet'!G42 -> 42279 | H4: ='Data Sheet'!H42 -> 44490 | I4: ='Data Sheet'!I42 -> 45479 | ... K4: ='Data Sheet'!K42 -> 48211
A5: Expenses | B5: ='Data Sheet'!B43 -> 29139 | C5: ='Data Sheet'!C43 -> 29878 | D5: ='Data Sheet'!D43 -> 31177 | E5: ='Data Sheet'!E43 -> 31649 | F5: ='Data Sheet'!F43 -> 31051 | G5: ='Data Sheet'!G43 -> 32336 | H5: ='Data Sheet'!H43 -> 33955 | I5: ='Data Sheet'!I43 -> 34845 | ... K5: ='Data Sheet'!K43 -> 36802
A6: Operating Profit | B6: ='Data Sheet'!B50 -> 8784 | C6: ='Data Sheet'!C50 -> 9437 | D6: ='Data Sheet'!D50 -> 9809 | E6: ='Data Sheet'!E50 -> 10115 | F6: ='Data Sheet'!F50 -> 9874 | G6: ='Data Sheet'!G50 -> 9943 | H6: ='Data Sheet'!H50 -> 10535 | I6: ='Data Sheet'!I50 -> 10634 | ... K6: ='Data Sheet'!K50 -> 11409
A7: Other Income | B7: ='Data Sheet'!B44 -> 2729 | C7: ='Data Sheet'!C44 -> 838 | D7: ='Data Sheet'!D44 -> 712 | E7: ='Data Sheet'!E44 -> 859 | F7: ='Data Sheet'!F44 -> 1190 | G7: ='Data Sheet'!G44 -> 1042 | H7: ='Data Sheet'!H44 -> 982 | I7: ='Data Sheet'!I44 -> -150 | ... K7: ='Data Sheet'!K44 -> 984
A8: Depreciation | B8: ='Data Sheet'!B45 -> 1163 | C8: ='Data Sheet'!C45 -> 1149 | D8: ='Data Sheet'!D45 -> 1160 | E8: ='Data Sheet'!E45 -> 1203 | F8: ='Data Sheet'!F45 -> 1299 | G8: ='Data Sheet'!G45 -> 1140 | H8: ='Data Sheet'!H45 -> 1182 | I8: ='Data Sheet'!I45 -> 1155 | ... K8: ='Data Sheet'!K45 -> 1246
A9: Interest | B9: ='Data Sheet'!B46 -> 110 | C9: ='Data Sheet'!C46 -> 105 | D9: ='Data Sheet'!D46 -> 108 | E9: ='Data Sheet'!E46 -> 101 | F9: ='Data Sheet'!F46 -> 102 | G9: ='Data Sheet'!G46 -> 105 | H9: ='Data Sheet'!H46 -> 106 | I9: ='Data Sheet'!I46 -> 100 | ... K9: ='Data Sheet'!K46 -> 119
A10: Profit before tax | B10: ='Data Sheet'!B47 -> 10240 | C10: ='Data Sheet'!C47 -> 9021 | D10: ='Data Sheet'!D47 -> 9253 | E10: ='Data Sheet'!E47 -> 9670 | F10: ='Data Sheet'!F47 -> 9663 | G10: ='Data Sheet'!G47 -> 9740 | H10: ='Data Sheet'!H47 -> 10229 | I10: ='Data Sheet'!I47 -> 9229 | ... K10: ='Data Sheet'!K47 -> 11028
A11: Tax | B11: ='Data Sheet'!B48 -> 10240 | C11: ='Data Sheet'!C48 -> 9021 | D11: ='Data Sheet'!D48 -> 9253 | E11: ='Data Sheet'!E48 -> 9670 | F11: ='Data Sheet'!F48 -> 9663 | G11: ='Data Sheet'!G48 -> 9740 | H11: ='Data Sheet'!H48 -> 10229 | I11: ='Data Sheet'!I48 -> 9229 | ... K11: ='Data Sheet'!K48 -> 11028
A12: Net profit | B12: ='Data Sheet'!B49 -> 7975 | C12: ='Data Sheet'!C49 -> 6374 | D12: ='Data Sheet'!D49 -> 6516 | E12: ='Data Sheet'!E49 -> 6822 | F12: ='Data Sheet'!F49 -> 7038 | G12: ='Data Sheet'!G49 -> 6924 | H12: ='Data Sheet'!H49 -> 7375 | I12: ='Data Sheet'!I49 -> 6666 | ... K12: ='Data Sheet'!K49 -> 7775
A14: OPM | B14: =IF(B4>0,B6/B4,"") -> 0.23162724 | C14: =IF(C4>0,C6/C4,"") -> 0.24003561 | D14: =IF(D4>0,D6/D4,"") -> 0.23932562 | E14: =IF(E4>0,E6/E4,"") -> 0.24219423 | F14: =IF(F4>0,F6/F4,"") -> 0.24127062 | G14: =IF(G4>0,G6/G4,"") -> 0.23517586 | H14: =IF(H4>0,H6/H4,"") -> 0.23679479 | I14: =IF(I4>0,I6/I4,"") -> 0.2338222 | ... K14: =IF(K4>0,K6/K4,"") -> 0.23664724

Sheet Balance Sheet
A1: ='Profit & Loss'!A1 -> Infosys Ltd | E1: =UPDATE | J1: SCREENER.IN
A3: Narration | B3: ='Data Sheet'!B56 -> 42795 | C3: ='Data Sheet'!C56 -> 43160 | D3: ='Data Sheet'!D56 -> 43525 | E3: ='Data Sheet'!E56 -> 43891 | F3: ='Data Sheet'!F56 -> 44256 | G3: ='Data Sheet'!G56 -> 44621 | H3: ='Data Sheet'!H56 -> 44986 | I3: ='Data Sheet'!I56 -> 45352 | ... K3: ='Data Sheet'!K56 -> 46082
A4: Equity Share Capital | B4: ='Data Sheet'!B57 -> 1144 | C4: ='Data Sheet'!C57 -> 1088 | D4: ='Data Sheet'!D57 -> 2170 | E4: ='Data Sheet'!E57 -> 2122 | F4: ='Data Sheet'!F57 -> 2124 | G4: ='Data Sheet'!G57 -> 2098 | H4: ='Data Sheet'!H57 -> 2069 | I4: ='Data Sheet'!I57 -> 2071 | ... K4: ='Data Sheet'!K57 -> 2024
A5: Reserves | B5: ='Data Sheet'!B58 -> 67838 | C5: ='Data Sheet'!C58 -> 63835 | D5: ='Data Sheet'!D58 -> 62778 | E5: ='Data Sheet'!E58 -> 63328 | F5: ='Data Sheet'!F58 -> 74227 | G5: ='Data Sheet'!G58 -> 73252 | H5: ='Data Sheet'!H58 -> 73338 | I5: ='Data Sheet'!I58 -> 86045 | ... K5: ='Data Sheet'!K58 -> 90828
A6: Borrowings | B6: ='Data Sheet'!B59 -> 0 | C6: ='Data Sheet'!C59 -> 0 | D6: ='Data Sheet'!D59 -> 0 | E6: ='Data Sheet'!E59 -> 4633 | F6: ='Data Sheet'!F59 -> 5325 | G6: ='Data Sheet'!G59 -> 5474 | H6: ='Data Sheet'!H59 -> 8299 | I6: ='Data Sheet'!I59 -> 8359 | ... K6: ='Data Sheet'!K59 -> 9176
A7: Other Liabilities | B7: ='Data Sheet'!B60 -> 14166 | C7: ='Data Sheet'!C60 -> 14426 | D7: ='Data Sheet'!D60 -> 19118 | E7: ='Data Sheet'!E60 -> 21717 | F7: ='Data Sheet'!F60 -> 25835 | G7: ='Data Sheet'!G60 -> 35905 | H7: ='Data Sheet'!H60 -> 40890 | I7: ='Data Sheet'!I60 -> 39545 | ... K7: ='Data Sheet'!K60 -> 52260
A8: Total | B8: ='Data Sheet'!B61 -> 83148 | C8: ='Data Sheet'!C61 -> 79349 | D8: ='Data Sheet'!D61 -> 84066 | E8: ='Data Sheet'!E61 -> 91800 | F8: ='Data Sheet'!F61 -> 107511 | G8: ='Data Sheet'!G61 -> 116729 | H8: ='Data Sheet'!H61 -> 124596 | I8: ='Data Sheet'!I61 -> 136020 | ... K8: ='Data Sheet'!K61 -> 154288
A10: Net Block | B10: ='Data Sheet'!B62 -> 14179 | C10: ='Data Sheet'!C62 -> 12574 | D10: ='Data Sheet'!D62 -> 15710 | E10: ='Data Sheet'!E62 -> 23789 | F10: ='Data Sheet'!F62 -> 25505 | G10: ='Data Sheet'!G62 -> 25800 | H10: ='Data Sheet'!H62 -> 29225 | I10: ='Data Sheet'!I62 -> 27622 | ... K10: ='Data Sheet'!K62 -> 33770
A11: Capital Work in Progress | B11: ='Data Sheet'!B63 -> 1365 | C11: ='Data Sheet'!C63 -> 1606 | D11: ='Data Sheet'!D63 -> 1388 | E11: ='Data Sheet'!E63 -> 954 | F11: ='Data Sheet'!F63 -> 922 | G11: ='Data Sheet'!G63 -> 416 | H11: ='Data Sheet'!H63 -> 288 | I11: ='Data Sheet'!I63 -> 293 | ... K11: ='Data Sheet'!K63 -> 526
A12: Investments | B12: ='Data Sheet'!B64 -> 16423 | C12: ='Data Sheet'!C64 -> 12163 | D12: ='Data Sheet'!D64 -> 11261 | E12: ='Data Sheet'!E64 -> 8792 | F12: ='Data Sheet'!F64 -> 14205 | G12: ='Data Sheet'!G64 -> 20324 | H12: ='Data Sheet'!H64 -> 19478 | I12: ='Data Sheet'!I64 -> 24623 | ... K12: ='Data Sheet'!K64 -> 21880
A13: Other Assets | B13: ='Data Sheet'!B65 -> 51181 | C13: ='Data Sheet'!C65 -> 53006 | D13: ='Data Sheet'!D65 -> 55707 | E13: ='Data Sheet'!E65 -> 58265 | F13: ='Data Sheet'!F65 -> 66879 | G13: ='Data Sheet'!G65 -> 70189 | H13: ='Data Sheet'!H65 -> 75605 | I13: ='Data Sheet'!I65 -> 83482 | ... K13: ='Data Sheet'!K65 -> 98112
A14: Total | B14: ='Data Sheet'!B66 -> 83148 | C14: ='Data Sheet'!C66 -> 79349 | D14: ='Data Sheet'!D66 -> 84066 | E14: ='Data Sheet'!E66 -> 91800 | F14: ='Data Sheet'!F66 -> 107511 | G14: ='Data Sheet'!G66 -> 116729 | H14: ='Data Sheet'!H66 -> 124596 | I14: ='Data Sheet'!I66 -> 136020 | ... K14: ='Data Sheet'!K66 -> 154288
A16: Working Capital | B16: =B13-B7 -> 37015 | C16: =C13-C7 -> 38580 | D16: =D13-D7 -> 36589 | E16: =E13-E7 -> 36548 | F16: =F13-F7 -> 41044 | G16: =G13-G7 -> 34284 | H16: =H13-H7 -> 34715 | I16: =I13-I7 -> 43937 | ... K16: =K13-K7 -> 45852
A17: Debtors | B17: ='Data Sheet'!B67 -> 12322 | C17: ='Data Sheet'!C67 -> 13142 | D17: ='Data Sheet'!D67 -> 14827 | E17: ='Data Sheet'!E67 -> 18487 | F17: ='Data Sheet'!F67 -> 19294 | G17: ='Data Sheet'!G67 -> 22698 | H17: ='Data Sheet'!H67 -> 25424 | I17: ='Data Sheet'!I67 -> 30193 | ... K17: ='Data Sheet'!K67 -> 35234
A18: Inventory | B18: ='Data Sheet'!B68 -> 8116.1 | C18: ='Data Sheet'!C68 -> 7495.09 | D18: ='Data Sheet'!D68 -> 7859.56 | E18: ='Data Sheet'!E68 -> 8879.33 | F18: ='Data Sheet'!F68 -> 10397.16 | G18: ='Data Sheet'!G68 -> 10864.15 | H18: ='Data Sheet'!H68 -> 11771.16 | I18: ='Data Sheet'!I68 -> 14152.88 | ... K18: ='Data Sheet'!K68 -> 18622.96
A20: Debtor Days | B20: =IF('Profit & Loss'!B4>0,'Balance Sheet'!B17/('Profit & Loss'!B4/365),0) -> 63.77485 | C20: =IF('Profit & Loss'!C4>0,'Balance Sheet'!C17/('Profit & Loss'!C4/365),0) -> 58.020321 | D20: =IF('Profit & Loss'!D4>0,'Balance Sheet'!D17/('Profit & Loss'!D4/365),0) -> 59.607836 | E20: =IF('Profit & Loss'!E4>0,'Balance Sheet'!E17/('Profit & Loss'!E4/365),0) -> 67.160552 | F20: =IF('Profit & Loss'!F4>0,'Balance Sheet'!F17/('Profit & Loss'!F4/365),0) -> 57.894213 | G20: =IF('Profit & Loss'!G4>0,'Balance Sheet'!G17/('Profit & Loss'!G4/365),0) -> 56.448452 | H20: =IF('Profit & Loss'!H4>0,'Balance Sheet'!H17/('Profit & Loss'!H4/365),0) -> 60.387584 | I20: =IF('Profit & Loss'!I4>0,'Balance Sheet'!I17/('Profit & Loss'!I4/365),0) -> 67.61424 | ... K20: =IF('Profit & Loss'!K4>0,'Balance Sheet'!K17/('Profit & Loss'!K4/365),0) -> 69.673153
A21: Inventory Turnover | B21: =IF('Balance Sheet'!B18>0,'Profit & Loss'!B4/'Balance Sheet'!B18,0) -> 8.6891487 | C21: =IF('Balance Sheet'!C18>0,'Profit & Loss'!C4/'Balance Sheet'!C18,0) -> 11.030555 | D21: =IF('Balance Sheet'!D18>0,'Profit & Loss'!D4/'Balance Sheet'!D18,0) -> 11.551664 | E21: =IF('Balance Sheet'!E18>0,'Profit & Loss'!E4/'Balance Sheet'!E18,0) -> 11.315268 | F21: =IF('Balance Sheet'!F18>0,'Profit & Loss'!F4/'Balance Sheet'!F18,0) -> 11.699445 | G21: =IF('Balance Sheet'!G18>0,'Profit & Loss'!G4/'Balance Sheet'!G18,0) -> 13.509294 | H21: =IF('Balance Sheet'!H18>0,'Profit & Loss'!H4/'Balance Sheet'!H18,0) -> 13.054788 | I21: =IF('Balance Sheet'!I18>0,'Profit & Loss'!I4/'Balance Sheet'!I18,0) -> 11.516384 | ... K21: =IF('Balance Sheet'!K18>0,'Profit & Loss'!K4/'Balance Sheet'!K18,0) -> 9.9115286
A23: Return on Equity | B23: =IF(SUM('Balance Sheet'!B4:B5)>0,'Profit & Loss'!B12/SUM('Balance Sheet'!B4:B5),"") -> 0.23236496 | C23: =IF(SUM('Balance Sheet'!C4:C5)>0,'Profit & Loss'!C12/SUM('Balance Sheet'!C4:C5),"") -> 0.2373581 | D23: =IF(SUM('Balance Sheet'!D4:D5)>0,'Profit & Loss'!D12/SUM('Balance Sheet'!D4:D5),"") -> 0.25618957 | E23: =IF(SUM('Balance Sheet'!E4:E5)>0,'Profit & Loss'!E12/SUM('Balance Sheet'!E4:E5),"") -> 0.29676089 | F23: =IF(SUM('Balance Sheet'!F4:F5)>0,'Profit & Loss'!F12/SUM('Balance Sheet'!F4:F5),"") -> 0.29005514 | G23: =IF(SUM('Balance Sheet'!G4:G5)>0,'Profit & Loss'!G12/SUM('Balance Sheet'!G4:G5),"") -> 0.31994691 | H23: =IF(SUM('Balance Sheet'!H4:H5)>0,'Profit & Loss'!H12/SUM('Balance Sheet'!H4:H5),"") -> 0.3480844 | I23: =IF(SUM('Balance Sheet'!I4:I5)>0,'Profit & Loss'!I12/SUM('Balance Sheet'!I4:I5),"") -> 0.3035771 | ... K23: =IF(SUM('Balance Sheet'!K4:K5)>0,'Profit & Loss'!K12/SUM('Balance Sheet'!K4:K5),"") -> 0.32659501
A24: Return on Capital Emp | C24: =IF((B4+B5+B6+C4+C5+C6)>0,('Profit & Loss'!C10+'Profit & Loss'!C9)*2/(B4+B5+B6+C4+C5+C6),"") -> 0.31426758 | D24: =IF((C4+C5+C6+D4+D5+D6)>0,('Profit & Loss'!D10+'Profit & Loss'!D9)*2/(C4+C5+C6+D4+D5+D6),"") -> 0.34152351 | E24: =IF((D4+D5+D6+E4+E5+E6)>0,('Profit & Loss'!E10+'Profit & Loss'!E9)*2/(D4+D5+D6+E4+E5+E6),"") -> 0.39728655 | F24: =IF((E4+E5+E6+F4+F5+F6)>0,('Profit & Loss'!F10+'Profit & Loss'!F9)*2/(E4+E5+E6+F4+F5+F6),"") -> 0.39944913 | G24: =IF((F4+F5+F6+G4+G5+G6)>0,('Profit & Loss'!G10+'Profit & Loss'!G9)*2/(F4+F5+F6+G4+G5+G6),"") -> 0.41361231 | H24: =IF((G4+G5+G6+H4+H5+H6)>0,('Profit & Loss'!H10+'Profit & Loss'!H9)*2/(G4+G5+G6+H4+H5+H6),"") -> 0.44317754 | I24: =IF((H4+H5+H6+I4+I5+I6)>0,('Profit & Loss'!I10+'Profit & Loss'!I9)*2/(H4+H5+H6+I4+I5+I6),"") -> 0.42206448 | J24: =IF((I4+I5+I6+J4+J5+J6)>0,('Profit & Loss'!J10+'Profit & Loss'!J9)*2/(I4+I5+I6+J4+J5+J6),"") -> 0.40306204 | K24: =IF((J4+J5+J6+K4+K5+K6)>0,('Profit & Loss'!K10+'Profit & Loss'!K9)*2/(J4+J5+J6+K4+K5+K6),"") -> 0.40483712

Sheet Cash Flow
A1: ='Balance Sheet'!A1 -> Infosys Ltd | E1: =UPDATE | J1: SCREENER.IN
A3: Narration | B3: ='Data Sheet'!B81 -> 42795 | C3: ='Data Sheet'!C81 -> 43160 | D3: ='Data Sheet'!D81 -> 43525 | E3: ='Data Sheet'!E81 -> 43891 | F3: ='Data Sheet'!F81 -> 44256 | G3: ='Data Sheet'!G81 -> 44621 | H3: ='Data Sheet'!H81 -> 44986 | I3: ='Data Sheet'!I81 -> 45352 | ... K3: ='Data Sheet'!K81 -> 46082
A4: Cash from Operating Activity | B4: ='Data Sheet'!B82 -> 11531 | C4: ='Data Sheet'!C82 -> 13218 | D4: ='Data Sheet'!D82 -> 14841 | E4: ='Data Sheet'!E82 -> 17003 | F4: ='Data Sheet'!F82 -> 23224 | G4: ='Data Sheet'!G82 -> 23885 | H4: ='Data Sheet'!H82 -> 22467 | I4: ='Data Sheet'!I82 -> 25210 | ... K4: ='Data Sheet'!K82 -> 33986
A5: Cash from Investing Activity | B5: ='Data Sheet'!B83 -> -14664 | C5: ='Data Sheet'!C83 -> 4533 | D5: ='Data Sheet'!D83 -> -632 | E5: ='Data Sheet'!E83 -> -331 | F5: ='Data Sheet'!F83 -> -7373 | G5: ='Data Sheet'!G83 -> -6485 | H5: ='Data Sheet'!H83 -> -1071 | I5: ='Data Sheet'!I83 -> -5093 | ... K5: ='Data Sheet'!K83 -> 3546
A6: Cash from Financing Activity | B6: ='Data Sheet'!B84 -> -6939 | C6: ='Data Sheet'!C84 -> -20505 | D6: ='Data Sheet'!D84 -> -14512 | E6: ='Data Sheet'!E84 -> -17591 | F6: ='Data Sheet'!F84 -> -9786 | G6: ='Data Sheet'!G84 -> -24642 | H6: ='Data Sheet'!H84 -> -26695 | I6: ='Data Sheet'!I84 -> -17504 | ... K6: ='Data Sheet'!K84 -> -39786
A7: Net Cash Flow | B7: ='Data Sheet'!B85 -> -10072 | C7: ='Data Sheet'!C85 -> -2754 | D7: ='Data Sheet'!D85 -> -303 | E7: ='Data Sheet'!E85 -> -919 | F7: ='Data Sheet'!F85 -> 6065 | G7: ='Data Sheet'!G85 -> -7242 | H7: ='Data Sheet'!H85 -> -5299 | I7: ='Data Sheet'!I85 -> 2613 | ... K7: ='Data Sheet'!K85 -> -2254

Sheet Customization
A1: How to use it?
A3: You can customize this workbook as you want.
B4: You can add custom formating, add conditional formating, add your own formulas… do ANYTHING.
B5: Please don't edit the "Data Sheet" only.
A7: After customization, you can upload this back on Screener.
B8: Upload on: | C8: https://www.screener.in/excel/
A10: Download your customized workbooks now onwards.
B11: Now whenever you will "Export to excel" from Screener, it will export your customized file.
A14: TESTING:
B15: This is a testing feature currently.
B16: You can report any formula errors on the worksheet at: support@screener.in

Sheet Common Size Statement
B2: ="Common Size Statement - "&'Data Sheet'!$B$1 -> Common Size Statement - Infosys Ltd
B4: Particulars | C4: ='Data Sheet'!B$16 -> 43160 | D4: ='Data Sheet'!C$16 -> 43525 | E4: ='Data Sheet'!D$16 -> 43891 | F4: ='Data Sheet'!E$16 -> 44256 | G4: ='Data Sheet'!F$16 -> 44621 | H4: ='Data Sheet'!G$16 -> 44986 | I4: ='Data Sheet'!H$16 -> 45352 | J4: ='Data Sheet'!I$16 -> 45717 | ... L4: ='Data Sheet'!K$16 -> TTM
B6: ='Data Sheet'!A17 -> Sales | C6: ='Data Sheet'!B17/'Data Sheet'!B$17 -> 1 | D6: ='Data Sheet'!C17/'Data Sheet'!C$17 -> 1 | E6: ='Data Sheet'!D17/'Data Sheet'!D$17 -> 1 | F6: ='Data Sheet'!E17/'Data Sheet'!E$17 -> 1 | G6: ='Data Sheet'!F17/'Data Sheet'!F$17 -> 1 | H6: ='Data Sheet'!G17/'Data Sheet'!G$17 -> 1 | I6: ='Data Sheet'!H17/'Data Sheet'!H$17 -> 1 | J6: ='Data Sheet'!I17/'Data Sheet'!I$17 -> 1 | ... L6: ='Data Sheet'!K17/'Data Sheet'!K$17 -> 1
B7: ='Data Sheet'!A18 -> Raw Material Cost | C7: ='Data Sheet'!B18/'Data Sheet'!B$17 -> 0 | D7: ='Data Sheet'!C18/'Data Sheet'!C$17 -> 0 | E7: ='Data Sheet'!D18/'Data Sheet'!D$17 -> 0 | F7: ='Data Sheet'!E18/'Data Sheet'!E$17 -> 0 | G7: ='Data Sheet'!F18/'Data Sheet'!F$17 -> 0 | H7: ='Data Sheet'!G18/'Data Sheet'!G$17 -> 0 | I7: ='Data Sheet'!H18/'Data Sheet'!H$17 -> 0 | J7: ='Data Sheet'!I18/'Data Sheet'!I$17 -> 0 | ... L7: ='Data Sheet'!K18/'Data Sheet'!K$17 -> 0
B8: ='Data Sheet'!A19 -> Change in Inventory | C8: ='Data Sheet'!B19/'Data Sheet'!B$17 -> 0 | D8: ='Data Sheet'!C19/'Data Sheet'!C$17 -> 0 | E8: ='Data Sheet'!D19/'Data Sheet'!D$17 -> 0 | F8: ='Data Sheet'!E19/'Data Sheet'!E$17 -> 0 | G8: ='Data Sheet'!F19/'Data Sheet'!F$17 -> 0 | H8: ='Data Sheet'!G19/'Data Sheet'!G$17 -> 0 | I8: ='Data Sheet'!H19/'Data Sheet'!H$17 -> 0 | J8: ='Data Sheet'!I19/'Data Sheet'!I$17 -> 0 | ... L8: ='Data Sheet'!K19/'Data Sheet'!K$17 -> 0
B9: ='Data Sheet'!A20 -> Power and Fuel | C9: ='Data Sheet'!B20/'Data Sheet'!B$17 -> 0 | D9: ='Data Sheet'!C20/'Data Sheet'!C$17 -> 0 | E9: ='Data Sheet'!D20/'Data Sheet'!D$17 -> 0 | F9: ='Data Sheet'!E20/'Data Sheet'!E$17 -> 0 | G9: ='Data Sheet'!F20/'Data Sheet'!F$17 -> 0 | H9: ='Data Sheet'!G20/'Data Sheet'!G$17 -> 0 | I9: ='Data Sheet'!H20/'Data Sheet'!H$17 -> 0 | J9: ='Data Sheet'!I20/'Data Sheet'!I$17 -> 0 | ... L9: ='Data Sheet'!K20/'Data Sheet'!K$17 -> 0
B10: ='Data Sheet'!A21 -> Other Mfr. Exp | C10: ='Data Sheet'!B21/'Data Sheet'!B$17 -> 0.11 | D10: ='Data Sheet'!C21/'Data Sheet'!C$17 -> 0.12 | E10: ='Data Sheet'!D21/'Data Sheet'!D$17 -> 0.12 | F10: ='Data Sheet'!E21/'Data Sheet'!E$17 -> 0.13 | G10: ='Data Sheet'!F21/'Data Sheet'!F$17 -> 0.17 | H10: ='Data Sheet'!G21/'Data Sheet'!G$17 -> 0.18 | I10: ='Data Sheet'!H21/'Data Sheet'!H$17 -> 0.18 | J10: ='Data Sheet'!I21/'Data Sheet'!I$17 -> 0.19 | ... L10: ='Data Sheet'!K21/'Data Sheet'!K$17 -> 0
B11: ='Data Sheet'!A22 -> Employee Cost | C11: ='Data Sheet'!B22/'Data Sheet'!B$17 -> 0.55 | D11: ='Data Sheet'!C22/'Data Sheet'!C$17 -> 0.55 | E11: ='Data Sheet'!D22/'Data Sheet'!D$17 -> 0.56 | F11: ='Data Sheet'!E22/'Data Sheet'!E$17 -> 0.55 | G11: ='Data Sheet'!F22/'Data Sheet'!F$17 -> 0.53 | H11: ='Data Sheet'!G22/'Data Sheet'!G$17 -> 0.53 | I11: ='Data Sheet'!H22/'Data Sheet'!H$17 -> 0.54 | J11: ='Data Sheet'!I22/'Data Sheet'!I$17 -> 0.53 | ... L11: ='Data Sheet'!K22/'Data Sheet'!K$17 -> 0
B12: ='Data Sheet'!A23 -> Selling and admin | C12: ='Data Sheet'!B23/'Data Sheet'!B$17 -> 0 | D12: ='Data Sheet'!C23/'Data Sheet'!C$17 -> 0 | E12: ='Data Sheet'!D23/'Data Sheet'!D$17 -> 0 | F12: ='Data Sheet'!E23/'Data Sheet'!E$17 -> 0 | G12: ='Data Sheet'!F23/'Data Sheet'!F$17 -> 0 | H12: ='Data Sheet'!G23/'Data Sheet'!G$17 -> 0 | I12: ='Data Sheet'!H23/'Data Sheet'!H$17 -> 0 | J12: ='Data Sheet'!I23/'Data Sheet'!I$17 -> 0 | ... L12: ='Data Sheet'!K23/'Data Sheet'!K$17 -> 0
B13: ='Data Sheet'!A24 -> Other Expenses | C13: ='Data Sheet'!B24/'Data Sheet'!B$17 -> 0.08 | D13: ='Data Sheet'!C24/'Data Sheet'!C$17 -> 0.09 | E13: ='Data Sheet'!D24/'Data Sheet'!D$17 -> 0.07 | F13: ='Data Sheet'!E24/'Data Sheet'!E$17 -> 0.04 | G13: ='Data Sheet'!F24/'Data Sheet'!F$17 -> 0.04 | H13: ='Data Sheet'!G24/'Data Sheet'!G$17 -> 0.05 | I13: ='Data Sheet'!H24/'Data Sheet'!H$17 -> 0.05 | J13: ='Data Sheet'!I24/'Data Sheet'!I$17 -> 0.04 | ... L13: ='Data Sheet'!K24/'Data Sheet'!K$17 -> 0
B14: ='Data Sheet'!A25 -> Other Income | C14: ='Data Sheet'!B25/'Data Sheet'!B$17 -> 0.046949888 | D14: ='Data Sheet'!C25/'Data Sheet'!C$17 -> 0.034859389 | E14: ='Data Sheet'!D25/'Data Sheet'!D$17 -> 0.030873104 | F14: ='Data Sheet'!E25/'Data Sheet'!E$17 -> 0.021906601 | G14: ='Data Sheet'!F25/'Data Sheet'!F$17 -> 0.018866994 | H14: ='Data Sheet'!G25/'Data Sheet'!G$17 -> 0.01840332 | I14: ='Data Sheet'!H25/'Data Sheet'!H$17 -> 0.030656602 | J14: ='Data Sheet'!I25/'Data Sheet'!I$17 -> 0.022087245 | ... L14: ='Data Sheet'!K25/'Data Sheet'!K$17 -> 0.016117498
B15: ='Data Sheet'!A26 -> Depreciation | C15: ='Data Sheet'!B26/'Data Sheet'!B$17 -> 0.026417288 | D15: ='Data Sheet'!C26/'Data Sheet'!C$17 -> 0.024324161 | E15: ='Data Sheet'!D26/'Data Sheet'!D$17 -> 0.031864392 | F15: ='Data Sheet'!E26/'Data Sheet'!E$17 -> 0.032516522 | G15: ='Data Sheet'!F26/'Data Sheet'!F$17 -> 0.028575891 | H15: ='Data Sheet'!G26/'Data Sheet'!G$17 -> 0.028787125 | I15: ='Data Sheet'!H26/'Data Sheet'!H$17 -> 0.030441856 | J15: ='Data Sheet'!I26/'Data Sheet'!I$17 -> 0.029523284 | ... L15: ='Data Sheet'!K26/'Data Sheet'!K$17 -> 0.027126155
B16: ='Data Sheet'!A27 -> Interest | C16: ='Data Sheet'!B27/'Data Sheet'!B$17 -> 0 | D16: ='Data Sheet'!C27/'Data Sheet'!C$17 -> 0 | E16: ='Data Sheet'!D27/'Data Sheet'!D$17 -> 0.0018724323 | F16: ='Data Sheet'!E27/'Data Sheet'!E$17 -> 0.0019408392 | G16: ='Data Sheet'!F27/'Data Sheet'!F$17 -> 0.0016441825 | H16: ='Data Sheet'!G27/'Data Sheet'!G$17 -> 0.0019350399 | I16: ='Data Sheet'!H27/'Data Sheet'!H$17 -> 0.003058502 | J16: ='Data Sheet'!I27/'Data Sheet'!I$17 -> 0.0025523038 | ... L16: ='Data Sheet'!K27/'Data Sheet'!K$17 -> 0.0023295879
B17: ='Data Sheet'!A28 -> Profit before tax | C17: ='Data Sheet'!B28/'Data Sheet'!B$17 -> 0.28742804 | D17: ='Data Sheet'!C28/'Data Sheet'!C$17 -> 0.25450257 | E17: ='Data Sheet'!D28/'Data Sheet'!D$17 -> 0.24239187 | F17: ='Data Sheet'!E28/'Data Sheet'!E$17 -> 0.26502906 | G17: ='Data Sheet'!F28/'Data Sheet'!F$17 -> 0.24753167 | H17: ='Data Sheet'!G28/'Data Sheet'!G$17 -> 0.22704014 | I17: ='Data Sheet'!H28/'Data Sheet'!H$17 -> 0.23419015 | J17: ='Data Sheet'!I28/'Data Sheet'!I$17 -> 0.23073808 | ... L17: ='Data Sheet'!K28/'Data Sheet'!K$17 -> 0.22365669
... B21: ='Data Sheet'!A32 -> EBITDA | C21: ='Data Sheet'!B32/'Data Sheet'!B$17 -> 0.31384532 | D21: ='Data Sheet'!C32/'Data Sheet'!C$17 -> 0.27882673 | E21: ='Data Sheet'!D32/'Data Sheet'!D$17 -> 0.27612869 | F21: ='Data Sheet'!E32/'Data Sheet'!E$17 -> 0.29948642 | G21: ='Data Sheet'!F32/'Data Sheet'!F$17 -> 0.27775174 | H21: ='Data Sheet'!G32/'Data Sheet'!G$17 -> 0.2577623 | I21: ='Data Sheet'!H32/'Data Sheet'!H$17 -> 0.26769051 | J21: ='Data Sheet'!I32/'Data Sheet'!I$17 -> 0.26281367 | ... L21: ='Data Sheet'!K32/'Data Sheet'!K$17 -> 0.25311244
B23: ="Common Size Balance Sheet - "&'Data Sheet'!$B$1 -> Common Size Balance Sheet - Infosys Ltd
B25: Particulars | C25: ='Data Sheet'!B$16 -> 43160 | D25: ='Data Sheet'!C$16 -> 43525 | E25: ='Data Sheet'!D$16 -> 43891 | F25: ='Data Sheet'!E$16 -> 44256 | G25: ='Data Sheet'!F$16 -> 44621 | H25: ='Data Sheet'!G$16 -> 44986 | I25: ='Data Sheet'!H$16 -> 45352 | J25: ='Data Sheet'!I$16 -> 45717 | ... L25: ='Data Sheet'!K$16 -> TTM
B27: Total Liabilities | C27: ='Data Sheet'!B61/'Data Sheet'!B$61 -> 1 | D27: ='Data Sheet'!C61/'Data Sheet'!C$61 -> 1 | E27: ='Data Sheet'!D61/'Data Sheet'!D$61 -> 1 | F27: ='Data Sheet'!E61/'Data Sheet'!E$61 -> 1 | G27: ='Data Sheet'!F61/'Data Sheet'!F$61 -> 1 | H27: ='Data Sheet'!G61/'Data Sheet'!G$61 -> 1 | I27: ='Data Sheet'!H61/'Data Sheet'!H$61 -> 1 | J27: ='Data Sheet'!I61/'Data Sheet'!I$61 -> 1 | ... L27: ='Data Sheet'!K61/'Data Sheet'!K$61 -> 1
B28: ='Data Sheet'!A57 -> Equity Share Capital | C28: ='Data Sheet'!B57/'Data Sheet'!B$61 -> 0.013758599 | D28: ='Data Sheet'!C57/'Data Sheet'!C$61 -> 0.013711578 | E28: ='Data Sheet'!D57/'Data Sheet'!D$61 -> 0.025813052 | F28: ='Data Sheet'!E57/'Data Sheet'!E$61 -> 0.023115468 | G28: ='Data Sheet'!F57/'Data Sheet'!F$61 -> 0.019756118 | H28: ='Data Sheet'!G57/'Data Sheet'!G$61 -> 0.017973254 | I28: ='Data Sheet'!H57/'Data Sheet'!H$61 -> 0.01660567 | J28: ='Data Sheet'!I57/'Data Sheet'!I$61 -> 0.015225702 | ... L28: ='Data Sheet'!K57/'Data Sheet'!K$61 -> 0.013118324
B29: ='Data Sheet'!A58 -> Reserves | C29: ='Data Sheet'!B58/'Data Sheet'!B$61 -> 0.8158705 | D29: ='Data Sheet'!C58/'Data Sheet'!C$61 -> 0.80448399 | E29: ='Data Sheet'!D58/'Data Sheet'!D$61 -> 0.74677039 | F29: ='Data Sheet'!E58/'Data Sheet'!E$61 -> 0.68984749 | G29: ='Data Sheet'!F58/'Data Sheet'!F$61 -> 0.69041307 | H29: ='Data Sheet'!G58/'Data Sheet'!G$61 -> 0.627539 | I29: ='Data Sheet'!H58/'Data Sheet'!H$61 -> 0.58860638 | J29: ='Data Sheet'!I58/'Data Sheet'!I$61 -> 0.6325908 | ... L29: ='Data Sheet'!K58/'Data Sheet'!K$61 -> 0.58869128
B30: ='Data Sheet'!A59 -> Borrowings | C30: ='Data Sheet'!B59/'Data Sheet'!B$61 -> 0 | D30: ='Data Sheet'!C59/'Data Sheet'!C$61 -> 0 | E30: ='Data Sheet'!D59/'Data Sheet'!D$61 -> 0 | F30: ='Data Sheet'!E59/'Data Sheet'!E$61 -> 0.05046841 | G30: ='Data Sheet'!F59/'Data Sheet'!F$61 -> 0.049529816 | H30: ='Data Sheet'!G59/'Data Sheet'!G$61 -> 0.046894945 | I30: ='Data Sheet'!H59/'Data Sheet'!H$61 -> 0.066607275 | J30: ='Data Sheet'!I59/'Data Sheet'!I$61 -> 0.061454198 | ... L30: ='Data Sheet'!K59/'Data Sheet'!K$61 -> 0.059473193
B31: ='Data Sheet'!A60 -> Other Liabilities | C31: ='Data Sheet'!B60/'Data Sheet'!B$61 -> 0.1703709 | D31: ='Data Sheet'!C60/'Data Sheet'!C$61 -> 0.18180443 | E31: ='Data Sheet'!D60/'Data Sheet'!D$61 -> 0.22741655 | F31: ='Data Sheet'!E60/'Data Sheet'!E$61 -> 0.23656863 | G31: ='Data Sheet'!F60/'Data Sheet'!F$61 -> 0.24030099 | H31: ='Data Sheet'!G60/'Data Sheet'!G$61 -> 0.3075928 | I31: ='Data Sheet'!H60/'Data Sheet'!H$61 -> 0.32818068 | J31: ='Data Sheet'!I60/'Data Sheet'!I$61 -> 0.2907293 | ... L31: ='Data Sheet'!K60/'Data Sheet'!K$61 -> 0.3387172
B33: Total Assets | C33: ='Data Sheet'!B66/'Data Sheet'!B$66 -> 1 | D33: ='Data Sheet'!C66/'Data Sheet'!C$66 -> 1 | E33: ='Data Sheet'!D66/'Data Sheet'!D$66 -> 1 | F33: ='Data Sheet'!E66/'Data Sheet'!E$66 -> 1 | G33: ='Data Sheet'!F66/'Data Sheet'!F$66 -> 1 | H33: ='Data Sheet'!G66/'Data Sheet'!G$66 -> 1 | I33: ='Data Sheet'!H66/'Data Sheet'!H$66 -> 1 | J33: ='Data Sheet'!I66/'Data Sheet'!I$66 -> 1 | ... L33: ='Data Sheet'!K66/'Data Sheet'!K$66 -> 1
B34: Fixed Assets Net Block | C34: ='Data Sheet'!B62/'Data Sheet'!B$66 -> 0.17052725 | D34: ='Data Sheet'!C62/'Data Sheet'!C$66 -> 0.1584645 | E34: ='Data Sheet'!D62/'Data Sheet'!D$66 -> 0.18687698 | F34: ='Data Sheet'!E62/'Data Sheet'!E$66 -> 0.25913943 | G34: ='Data Sheet'!F62/'Data Sheet'!F$66 -> 0.23723154 | H34: ='Data Sheet'!G62/'Data Sheet'!G$66 -> 0.22102477 | I34: ='Data Sheet'!H62/'Data Sheet'!H$66 -> 0.23455809 | J34: ='Data Sheet'!I62/'Data Sheet'!I$66 -> 0.20307308 | ... L34: ='Data Sheet'!K62/'Data Sheet'!K$66 -> 0.21887639
B35: ='Data Sheet'!A63 -> Capital Work in Progress | C35: ='Data Sheet'!B63/'Data Sheet'!B$66 -> 0.01641651 | D35: ='Data Sheet'!C63/'Data Sheet'!C$66 -> 0.020239701 | E35: ='Data Sheet'!D63/'Data Sheet'!D$66 -> 0.016510837 | F35: ='Data Sheet'!E63/'Data Sheet'!E$66 -> 0.010392157 | G35: ='Data Sheet'!F63/'Data Sheet'!F$66 -> 0.0085758667 | H35: ='Data Sheet'!G63/'Data Sheet'!G$66 -> 0.0035638102 | I35: ='Data Sheet'!H63/'Data Sheet'!H$66 -> 0.0023114707 | J35: ='Data Sheet'!I63/'Data Sheet'!I$66 -> 0.002154095 | ... L35: ='Data Sheet'!K63/'Data Sheet'!K$66 -> 0.0034092088
B36: ='Data Sheet'!A64 -> Investments | C36: ='Data Sheet'!B64/'Data Sheet'!B$66 -> 0.19751527 | D36: ='Data Sheet'!C64/'Data Sheet'!C$66 -> 0.15328486 | E36: ='Data Sheet'!D64/'Data Sheet'!D$66 -> 0.13395427 | F36: ='Data Sheet'!E64/'Data Sheet'!E$66 -> 0.09577342 | G36: ='Data Sheet'!F64/'Data Sheet'!F$66 -> 0.13212602 | H36: ='Data Sheet'!G64/'Data Sheet'!G$66 -> 0.17411269 | I36: ='Data Sheet'!H64/'Data Sheet'!H$66 -> 0.15632926 | J36: ='Data Sheet'!I64/'Data Sheet'!I$66 -> 0.18102485 | ... L36: ='Data Sheet'!K64/'Data Sheet'!K$66 -> 0.14181271
B37: ='Data Sheet'!A65 -> Other Assets | C37: ='Data Sheet'!B74/'Data Sheet'!B66 -> 0.097631933 | D37: ='Data Sheet'!C74/'Data Sheet'!C66 -> 0.15817351 | E37: ='Data Sheet'!D74/'Data Sheet'!D66 -> 0.16002236 | F37: ='Data Sheet'!E74/'Data Sheet'!E66 -> 0.13343867 | G37: ='Data Sheet'!F74/'Data Sheet'!F66 -> 0.11602385 | H37: ='Data Sheet'!G74/'Data Sheet'!G66 -> 0.16409675 | I37: ='Data Sheet'!H74/'Data Sheet'!H66 -> 0.2105753 | J37: ='Data Sheet'!I74/'Data Sheet'!I66 -> 0.17901867 | ... L37: ='Data Sheet'!K74/'Data Sheet'!K66 -> 0.14294073
B38: ='Data Sheet'!A67 -> Receivables | C38: ='Data Sheet'!B67/'Data Sheet'!B$66 -> 0.14819358 | D38: ='Data Sheet'!C67/'Data Sheet'!C$66 -> 0.16562276 | E38: ='Data Sheet'!D67/'Data Sheet'!D$66 -> 0.17637333 | F38: ='Data Sheet'!E67/'Data Sheet'!E$66 -> 0.20138344 | G38: ='Data Sheet'!F67/'Data Sheet'!F$66 -> 0.17946071 | H38: ='Data Sheet'!G67/'Data Sheet'!G$66 -> 0.19445039 | I38: ='Data Sheet'!H67/'Data Sheet'!H$66 -> 0.20405149 | J38: ='Data Sheet'!I67/'Data Sheet'!I$66 -> 0.22197471 | ... L38: ='Data Sheet'!K67/'Data Sheet'!K$66 -> 0.22836514
B39: ='Data Sheet'!A68 -> Inventory | C39: ='Data Sheet'!B68/'Data Sheet'!B$66 -> 0.097610285 | D39: ='Data Sheet'!C68/'Data Sheet'!C$66 -> 0.094457271 | E39: ='Data Sheet'!D68/'Data Sheet'!D$66 -> 0.093492732 | F39: ='Data Sheet'!E68/'Data Sheet'!E$66 -> 0.096724728 | G39: ='Data Sheet'!F68/'Data Sheet'!F$66 -> 0.096707872 | H39: ='Data Sheet'!G68/'Data Sheet'!G$66 -> 0.093071559 | I39: ='Data Sheet'!H68/'Data Sheet'!H$66 -> 0.094474622 | J39: ='Data Sheet'!I68/'Data Sheet'!I$66 -> 0.10404999 | ... L39: ='Data Sheet'!K68/'Data Sheet'!K$66 -> 0.12070258
B40: ='Data Sheet'!A69 -> Cash & Bank | C40: ='Data Sheet'!B69/'Data Sheet'!B$66 -> 0.27210516 | D40: ='Data Sheet'!C69/'Data Sheet'!C$66 -> 0.2497574 | E40: ='Data Sheet'!D69/'Data Sheet'!D$66 -> 0.23276949 | F40: ='Data Sheet'!E69/'Data Sheet'!E$66 -> 0.20314815 | G40: ='Data Sheet'!F69/'Data Sheet'!F$66 -> 0.22987415 | H40: ='Data Sheet'!G69/'Data Sheet'!G$66 -> 0.14968003 | I40: ='Data Sheet'!H69/'Data Sheet'!H$66 -> 0.097699766 | J40: ='Data Sheet'!I69/'Data Sheet'!I$66 -> 0.1087046 | ... L40: ='Data Sheet'!K69/'Data Sheet'!K$66 -> 0.14389324

Sheet Data Sheet
A1: COMPANY NAME | B1: Infosys Ltd | E1: =IF(B2<>B3, "A NEW VERSION OF THE WORKSHEET IS AVAILABLE", "")
A2: LATEST VERSION | B2: 2.1 | E2: PLEASE DO NOT MAKE ANY CHANGES TO THIS SHEET
A3: CURRENT VERSION | B3: 2.1
A5: META
A6: Number of shares | B6: =IF(B9>0, B9/B8, 0) -> 405.97812
A7: Face Value | B7: 5
A8: Current Price | B8: 1051
A9: Market Capitalization | B9: 426683
A15: PROFIT & LOSS
A16: Report Date | B16: 43160 | C16: 43525 | D16: 43891 | E16: 44256 | F16: 44621 | G16: 44986 | H16: 45352 | I16: 45717 | J16: 46082 | K16: TTM
A17: Sales | B17: 70522 | C17: 82675 | D17: 90791 | E17: 100472 | F17: 121641 | G17: 146767 | H17: 153670 | I17: 162990 | J17: 178650 | K17: 184582
A18: Raw Material Cost | B18: 0 | C18: 0 | D18: 0 | E18: 0 | F18: 0 | G18: 0 | H18: 0 | I18: 0 | J18: 0 | K18: 0
A19: Change in Inventory | B19: 0 | C19: 0 | D19: 0 | E19: 0 | F19: 0 | G19: 0 | H19: 0 | I19: 0 | J19: 0 | K19: 0
A20: Power and Fuel | B20: 0 | C20: 0 | D20: 0 | E20: 0 | F20: 0 | G20: 0 | H20: 0 | I20: 0 | J20: 0 | K20: 0
A21: Other Mfr. Exp | B21: 7757.42 | C21: 9921 | D21: 10894.92 | E21: 13061.36 | F21: 20678.97 | G21: 26418.06 | H21: 27660.6 | I21: 30968.1 | J21: 33943.5 | K21: 0
A22: Employee Cost | B22: 38787.1 | C22: 45471.25 | D22: 50842.96 | E22: 55259.6 | F22: 64469.73 | G22: 77786.51 | H22: 82981.8 | I22: 86384.7 | J22: 94684.5 | K22: 0
A23: Selling and admin | B23: 0 | C23: 0 | D23: 0 | E23: 0 | F23: 0 | G23: 0 | H23: 0 | I23: 0 | J23: 0 | K23: 0
A24: Other Expenses | B24: 5641.76 | C24: 7440.75 | D24: 6355.37 | E24: 4018.88 | F24: 4865.64 | G24: 7338.35 | H24: 7683.5 | I24: 6519.6 | J24: 8932.5 | K24: 0
A25: Other Income | B25: 3311 | C25: 2882 | D25: 2803 | E25: 2201 | F25: 2295 | G25: 2701 | H25: 4711 | I25: 3600 | J25: 3033 | K25: 2975
A26: Depreciation | B26: 1863 | C26: 2011 | D26: 2893 | E26: 3267 | F26: 3476 | G26: 4225 | H26: 4678 | I26: 4812 | J26: 4902 | K26: 5007
A27: Interest | B27: 0 | C27: 0 | D27: 170 | E27: 195 | F27: 200 | G27: 284 | H27: 470 | I27: 416 | J27: 416 | K27: 430
A28: Profit before tax | B28: 20270 | C28: 21041 | D28: 22007 | E28: 26628 | F28: 30110 | G28: 33322 | H28: 35988 | I28: 37608 | J28: 39995 | K28: 41283
... A31: Dividend Amount | B31: 9457.11 | C31: 9246 | D31: 7487.55 | E31: 11459.57 | F31: 13066.14 | G31: 13982.64 | H31: 19161.04 | I31: 17922.5 | J31: 19452.84 | K31: 0
A32: EBITDA | B32: =SUM(B26:B28) -> 22133 | C32: =SUM(C26:C28) -> 23052 | D32: =SUM(D26:D28) -> 25070 | E32: =SUM(E26:E28) -> 30090 | F32: =SUM(F26:F28) -> 33786 | G32: =SUM(G26:G28) -> 37831 | H32: =SUM(H26:H28) -> 41136 | I32: =SUM(I26:I28) -> 42836 | ... K32: =SUM(K26:K28) -> 46720
B33: =B30+B29+B27+B26 -> 38162 | C33: =C30+C29+C27+C26 -> 38462 | D33: =D30+D29+D27+D26 -> 41709 | E33: =E30+E29+E27+E26 -> 49513 | F33: =F30+F29+F27+F26 -> 55932 | G33: =G30+G29+G27+G26 -> 61939 | H33: =H30+H29+H27+H26 -> 67384 | I33: =I30+I29+I27+I26 -> 69586 | ... K33: =K30+K29+K27+K26 -> 77045
A40: Quarters
A41: Report Date | B41: 45352 | C41: 45444 | D41: 45536 | E41: 45627 | F41: 45717 | G41: 45809 | H41: 45901 | I41: 45992 | J41: 46082 | K41: 46174
A42: Sales | B42: 37923 | C42: 39315 | D42: 40986 | E42: 41764 | F42: 40925 | G42: 42279 | H42: 44490 | I42: 45479 | J42: 46402 | K42: 48211
A43: Expenses | B43: 29139 | C43: 29878 | D43: 31177 | E43: 31649 | F43: 31051 | G43: 32336 | H43: 33955 | I43: 34845 | J43: 35235 | K43: 36802
A44: Other Income | B44: 2729 | C44: 838 | D44: 712 | E44: 859 | F44: 1190 | G44: 1042 | H44: 982 | I44: -150 | J44: 1159 | K44: 984
A45: Depreciation | B45: 1163 | C45: 1149 | D45: 1160 | E45: 1203 | F45: 1299 | G45: 1140 | H45: 1182 | I45: 1155 | J45: 1424 | K45: 1246
A46: Interest | B46: 110 | C46: 105 | D46: 108 | E46: 101 | F46: 102 | G46: 105 | H46: 106 | I46: 100 | J46: 105 | K46: 119
A47: Profit before tax | B47: 10240 | C47: 9021 | D47: 9253 | E47: 9670 | F47: 9663 | G47: 9740 | H47: 10229 | I47: 9229 | J47: 10797 | K47: 11028
A48: Tax | B48: 10240 | C48: 9021 | D48: 9253 | E48: 9670 | F48: 9663 | G48: 9740 | H48: 10229 | I48: 9229 | J48: 10797 | K48: 11028
A49: Net profit | B49: 7975 | C49: 6374 | D49: 6516 | E49: 6822 | F49: 7038 | G49: 6924 | H49: 7375 | I49: 6666 | J49: 8509 | K49: 7775
A50: Operating Profit | B50: 8784 | C50: 9437 | D50: 9809 | E50: 10115 | F50: 9874 | G50: 9943 | H50: 10535 | I50: 10634 | J50: 11167 | K50: 11409
A55: BALANCE SHEET
A56: Report Date | B56: 42795 | C56: 43160 | D56: 43525 | E56: 43891 | F56: 44256 | G56: 44621 | H56: 44986 | I56: 45352 | J56: 45717 | K56: 46082
A57: Equity Share Capital | B57: 1144 | C57: 1088 | D57: 2170 | E57: 2122 | F57: 2124 | G57: 2098 | H57: 2069 | I57: 2071 | J57: 2073 | K57: 2024
A58: Reserves | B58: 67838 | C58: 63835 | D58: 62778 | E58: 63328 | F58: 74227 | G58: 73252 | H58: 73338 | I58: 86045 | J58: 93745 | K58: 90828
A59: Borrowings | B59: 0 | C59: 0 | D59: 0 | E59: 4633 | F59: 5325 | G59: 5474 | H59: 8299 | I59: 8359 | J59: 8227 | K59: 9176
A60: Other Liabilities | B60: 14166 | C60: 14426 | D60: 19118 | E60: 21717 | F60: 25835 | G60: 35905 | H60: 40890 | I60: 39545 | J60: 43750 | K60: 52260
A61: Total | B61: 83148 | C61: 79349 | D61: 84066 | E61: 91800 | F61: 107511 | G61: 116729 | H61: 124596 | I61: 136020 | J61: 147795 | K61: 154288
A62: Net Block | B62: 14179 | C62: 12574 | D62: 15710 | E62: 23789 | F62: 25505 | G62: 25800 | H62: 29225 | I62: 27622 | J62: 30961 | K62: 33770
A63: Capital Work in Progress | B63: 1365 | C63: 1606 | D63: 1388 | E63: 954 | F63: 922 | G63: 416 | H63: 288 | I63: 293 | J63: 814 | K63: 526
A64: Investments | B64: 16423 | C64: 12163 | D64: 11261 | E64: 8792 | F64: 14205 | G64: 20324 | H64: 19478 | I64: 24623 | J64: 23541 | K64: 21880
A65: Other Assets | B65: 51181 | C65: 53006 | D65: 55707 | E65: 58265 | F65: 66879 | G65: 70189 | H65: 75605 | I65: 83482 | J65: 92479 | K65: 98112
A66: Total | B66: 83148 | C66: 79349 | D66: 84066 | E66: 91800 | F66: 107511 | G66: 116729 | H66: 124596 | I66: 136020 | J66: 147795 | K66: 154288
A67: Receivables | B67: 12322 | C67: 13142 | D67: 14827 | E67: 18487 | F67: 19294 | G67: 22698 | H67: 25424 | I67: 30193 | J67: 31158 | K67: 35234
... A70: No. of Equity Shares | B70: 2288000000 | C70: 2176000000 | D70: 4340000000 | E70: 4244000000 | F70: 4248000000 | G70: 4196000000 | H70: 4138000000 | I70: 4142000000 | J70: 4146000000 | K70: 4048000000
A71: New Bonus Shares
A72: Face value | B72: 5 | C72: 5 | D72: 5 | E72: 5 | F72: 5 | G72: 5 | H72: 5 | I72: 5 | J72: 5 | K72: 5
B74: =B65-SUM(B67:B69) -> 8117.9 | C74: =C65-SUM(C67:C69) -> 12550.91 | D74: =D65-SUM(D67:D69) -> 13452.44 | E74: =E65-SUM(E67:E69) -> 12249.67 | F74: =F65-SUM(F67:F69) -> 12473.84 | G74: =G65-SUM(G67:G69) -> 19154.85 | H74: =H65-SUM(H67:H69) -> 26236.84 | I74: =I65-SUM(I67:I69) -> 24350.12 | ... K74: =K65-SUM(K67:K69) -> 22054.04
A75: Other Assets | B75: =B65-SUM(B67:B69) -> 8117.9 | C75: =C65-SUM(C67:C69) -> 12550.91 | D75: =D65-SUM(D67:D69) -> 13452.44 | E75: =E65-SUM(E67:E69) -> 12249.67 | F75: =F65-SUM(F67:F69) -> 12473.84 | G75: =G65-SUM(G67:G69) -> 19154.85 | H75: =H65-SUM(H67:H69) -> 26236.84 | I75: =I65-SUM(I67:I69) -> 24350.12 | ... K75: =K65-SUM(K67:K69) -> 22054.04
A80: CASH FLOW:
A81: Report Date | B81: 42795 | C81: 43160 | D81: 43525 | E81: 43891 | F81: 44256 | G81: 44621 | H81: 44986 | I81: 45352 | J81: 45717 | K81: 46082
A82: Cash from Operating Activity | B82: 11531 | C82: 13218 | D82: 14841 | E82: 17003 | F82: 23224 | G82: 23885 | H82: 22467 | I82: 25210 | J82: 35694 | K82: 33986
A83: Cash from Investing Activity | B83: -14664 | C83: 4533 | D83: -632 | E83: -331 | F83: -7373 | G83: -6485 | H83: -1071 | I83: -5093 | J83: -1864 | K83: 3546
A84: Cash from Financing Activity | B84: -6939 | C84: -20505 | D84: -14512 | E84: -17591 | F84: -9786 | G84: -24642 | H84: -26695 | I84: -17504 | J84: -24161 | K84: -39786
A85: Net Cash Flow | B85: -10072 | C85: -2754 | D85: -303 | E85: -919 | F85: 6065 | G85: -7242 | H85: -5299 | I85: 2613 | J85: 9669 | K85: -2254
A90: PRICE: | B90: 515.6 | C90: 580.38 | D90: 741.9 | E90: 731.7 | F90: 1253.3 | G90: 1723.3 | H90: 1479.3 | I90: 1656.3 | J90: 1687.7 | K90: 1300.1
A92: DERIVED:
A93: Adjusted Equity Shares in Cr | B93: 459.41 | C93: 459.41 | D93: 459.41 | E93: 459.41 | F93: 459.41 | G93: 459.41 | H93: 459.41 | I93: 459.41 | J93: 459.41 | K93: 459.41

Sheet Cash Flow Statement
B2: Cash Flow Statement - Infosys Ltd
B4: Particulars | C4: 42064 | D4: 42430 | E4: 42795 | F4: 43160 | G4: 43525 | H4: 43891 | I4: 44256 | J4: 44621 | K4: 44986 | L4: 45352 | M4: 45717 | N4: 46082
B6: Cash from Operating Activity - | C6: 8353 | D6: 10028 | E6: 11531 | F6: 13218 | G6: 14841 | H6: 17003 | I6: 23224 | J6: 23885 | K6: 22467 | L6: 25210 | M6: 35694 | N6: 33986
B7: Profit from operations | C7: 15946 | D7: 17839 | E7: 19340 | F7: 19963 | G7: 22126 | H7: 23920 | I7: 28845 | J7: 32921 | K7: 37605 | L7: 39523 | M7: 41591 | N7: 45273
B8: Receivables | C8: -1475 | D8: -1654 | E8: -1743 | F8: -1523 | G8: -2881 | H8: -3861 | I8: -1835 | J8: -7937 | K8: -7076 | L8: -2667 | M8: -1769 | N8: -5177
B9: Inventory | C9: 0 | D9: 0 | E9: 0 | F9: 0 | G9: 0 | H9: 0 | I9: 0 | J9: 0 | K9: 0 | L9: 0 | M9: 0 | N9: 0
B10: Payables | C10: 0 | D10: 242 | E10: -19 | F10: 328 | G10: 916 | H10: -373 | I10: -245 | J10: 1489 | K10: -279 | L10: 91 | M10: 176 | N10: -26
B11: Working capital changes | C11: -842 | D11: -1946 | E11: -2156 | F11: 84 | G11: -453 | H11: -2367 | I11: 768 | J11: -1424 | K11: -6344 | L11: -5082 | M11: -295 | N11: -2639
B12: Direct taxes | C12: -6751 | D12: -5865 | E12: -5653 | F12: -6829 | G12: -6832 | H12: -4550 | I12: -6389 | J12: -7612 | K12: -8794 | L12: -9231 | M12: -5602 | N12: -8648
B13: Cash from Investing Activity - | C13: 999 | D13: -885 | E13: -14664 | F13: 4533 | G13: -632 | H13: -331 | I13: -7373 | J13: -6485 | K13: -1071 | L13: -5093 | M13: -1864 | N13: 3546
B14: Fixed assets purchased | C14: -2247 | D14: -2723 | E14: -2760 | F14: -1998 | G14: -2445 | H14: -3307 | I14: -2107 | J14: -2161 | K14: -2579 | L14: -2201 | M14: -2237 | N14: -2727
B15: Fixed assets sold | C15: 0 | D15: 0 | E15: 0 | F15: 0 | G15: 0 | H15: 0 | I15: 0 | J15: 0 | K15: 0 | L15: 0 | M15: 0 | N15: 0
B16: Investments purchased | C16: -23923 | D16: -24577 | E16: -66410 | F16: -69159 | G16: -79410 | H16: -37482 | I16: -46738 | J16: -59951 | K16: -75800 | L16: -78092 | M16: -82742 | N16: -82617
... B32: Net Cash Flow | C32: 4417 | D32: 2330 | E32: -10072 | F32: -2754 | G32: -303 | H32: -919 | I32: 6065 | J32: -7242 | K32: -5299 | L32: 2613 | M32: 9669 | N32: -2254

Sheet Historical FS
B2: ="Historical Financial Statement - "&'Data Sheet'!$B$1 -> Historical Financial Statement - Infosys Ltd
B3: Particulars | C3: ='Data Sheet'!B56 -> 42795 | D3: ='Data Sheet'!C56 -> 43160 | E3: ='Data Sheet'!D56 -> 43525 | F3: ='Data Sheet'!E56 -> 43891 | G3: ='Data Sheet'!F56 -> 44256 | H3: ='Data Sheet'!G56 -> 44621 | I3: ='Data Sheet'!H56 -> 44986 | J3: ='Data Sheet'!I56 -> 45352 | ... L3: ='Data Sheet'!K56 -> 46082 | M3: LTM
A5: # | B5: Income Statement
B7: Sales | C7: ='Data Sheet'!B17 -> 70522 | D7: ='Data Sheet'!C17 -> 82675 | E7: ='Data Sheet'!D17 -> 90791 | F7: ='Data Sheet'!E17 -> 100472 | G7: ='Data Sheet'!F17 -> 121641 | H7: ='Data Sheet'!G17 -> 146767 | I7: ='Data Sheet'!H17 -> 153670 | J7: ='Data Sheet'!I17 -> 162990 | ... L7: ='Data Sheet'!K17 -> 184582
B8: Sales Growth | C8: - | D8: =D7/C7-1 -> 0.1723292 | E8: =E7/D7-1 -> 0.098167523 | F8: =F7/E7-1 -> 0.10662951 | G8: =G7/F7-1 -> 0.21069552 | H8: =H7/G7-1 -> 0.20655864 | I8: =I7/H7-1 -> 0.047033734 | J8: =J7/I7-1 -> 0.060649444 | K8: =K7/J7-1 -> 0.096079514 | L8: =L7/K7-1 -> 0.03320459
B10: Cost of Goods Sold | C10: =SUM('Data Sheet'!B18,'Data Sheet'!B20:B22)-'Data Sheet'!B19 -> 46544.52 | D10: =SUM('Data Sheet'!C18,'Data Sheet'!C20:C22)-'Data Sheet'!C19 -> 55392.25 | E10: =SUM('Data Sheet'!D18,'Data Sheet'!D20:D22)-'Data Sheet'!D19 -> 61737.88 | F10: =SUM('Data Sheet'!E18,'Data Sheet'!E20:E22)-'Data Sheet'!E19 -> 68320.96 | G10: =SUM('Data Sheet'!F18,'Data Sheet'!F20:F22)-'Data Sheet'!F19 -> 85148.7 | H10: =SUM('Data Sheet'!G18,'Data Sheet'!G20:G22)-'Data Sheet'!G19 -> 104204.57 | I10: =SUM('Data Sheet'!H18,'Data Sheet'!H20:H22)-'Data Sheet'!H19 -> 110642.4 | J10: =SUM('Data Sheet'!I18,'Data Sheet'!I20:I22)-'Data Sheet'!I19 -> 117352.8 | ... L10: =SUM('Data Sheet'!K18,'Data Sheet'!K20:K22)-'Data Sheet'!K19 -> 0
B11: COGS % Sales | C11: =C10/C7 -> 0.66 | D11: =D10/D7 -> 0.67 | E11: =E10/E7 -> 0.68 | F11: =F10/F7 -> 0.68 | G11: =G10/G7 -> 0.7 | H11: =H10/H7 -> 0.71 | I11: =I10/I7 -> 0.72 | J11: =J10/J7 -> 0.72 | ... L11: =L10/L7 -> 0
B13: Gross Profit | C13: =C7-C10 -> 23977.48 | D13: =D7-D10 -> 27282.75 | E13: =E7-E10 -> 29053.12 | F13: =F7-F10 -> 32151.04 | G13: =G7-G10 -> 36492.3 | H13: =H7-H10 -> 42562.43 | I13: =I7-I10 -> 43027.6 | J13: =J7-J10 -> 45637.2 | ... L13: =L7-L10 -> 184582
B14: Gross Profit % Sales | C14: =C13/C7 -> 0.34 | D14: =D13/D7 -> 0.33 | E14: =E13/E7 -> 0.32 | F14: =F13/F7 -> 0.32 | G14: =G13/G7 -> 0.3 | H14: =H13/H7 -> 0.29 | I14: =I13/I7 -> 0.28 | J14: =J13/J7 -> 0.28 | ... L14: =L13/L7 -> 1
B16: Selling % General Expenses | C16: ='Data Sheet'!B23 -> 0 | D16: ='Data Sheet'!C23 -> 0 | E16: ='Data Sheet'!D23 -> 0 | F16: ='Data Sheet'!E23 -> 0 | G16: ='Data Sheet'!F23 -> 0 | H16: ='Data Sheet'!G23 -> 0 | I16: ='Data Sheet'!H23 -> 0 | J16: ='Data Sheet'!I23 -> 0 | ... L16: ='Data Sheet'!K23 -> 0
B17: S&G % Sales | C17: =C16/C7 -> 0 | D17: =D16/D7 -> 0 | E17: =E16/E7 -> 0 | F17: =F16/F7 -> 0 | G17: =G16/G7 -> 0 | H17: =H16/H7 -> 0 | I17: =I16/I7 -> 0 | J17: =J16/J7 -> 0 | ... L17: =L16/L7 -> 0
B19: EBITDA | C19: =C13-C16 -> 23977.48 | D19: =D13-D16 -> 27282.75 | E19: =E13-E16 -> 29053.12 | F19: =F13-F16 -> 32151.04 | G19: =G13-G16 -> 36492.3 | H19: =H13-H16 -> 42562.43 | I19: =I13-I16 -> 43027.6 | J19: =J13-J16 -> 45637.2 | ... L19: =L13-L16 -> 184582
B20: EBITDA % Sales | C20: =C19/C7 -> 0.34 | D20: =D19/D7 -> 0.33 | E20: =E19/E7 -> 0.32 | F20: =F19/F7 -> 0.32 | G20: =G19/G7 -> 0.3 | H20: =H19/H7 -> 0.29 | I20: =I19/I7 -> 0.28 | J20: =J19/J7 -> 0.28 | ... L20: =L19/L7 -> 1
B22: Depreciation | C22: ='Data Sheet'!B26 -> 1863 | D22: ='Data Sheet'!C26 -> 2011 | E22: ='Data Sheet'!D26 -> 2893 | F22: ='Data Sheet'!E26 -> 3267 | G22: ='Data Sheet'!F26 -> 3476 | H22: ='Data Sheet'!G26 -> 4225 | I22: ='Data Sheet'!H26 -> 4678 | J22: ='Data Sheet'!I26 -> 4812 | ... L22: ='Data Sheet'!K26 -> 5007
B23: Depreciation % Sales | C23: =C22/C7 -> 0.026417288 | D23: =D22/D7 -> 0.024324161 | E23: =E22/E7 -> 0.031864392 | F23: =F22/F7 -> 0.032516522 | G23: =G22/G7 -> 0.028575891 | H23: =H22/H7 -> 0.028787125 | I23: =I22/I7 -> 0.030441856 | J23: =J22/J7 -> 0.029523284 | ... L23: =L22/L7 -> 0.027126155
B25: EBIT | C25: =C19-C22 -> 22114.48 | D25: =D19-D22 -> 25271.75 | E25: =E19-E22 -> 26160.12 | F25: =F19-F22 -> 28884.04 | G25: =G19-G22 -> 33016.3 | H25: =H19-H22 -> 38337.43 | I25: =I19-I22 -> 38349.6 | J25: =J19-J22 -> 40825.2 | ... L25: =L19-L22 -> 179575
B26: EBIT % Sales | C26: =C25/C7 -> 0.31358271 | D26: =D25/D7 -> 0.30567584 | E26: =E25/E7 -> 0.28813561 | F26: =F25/F7 -> 0.28748348 | G26: =G25/G7 -> 0.27142411 | H26: =H25/H7 -> 0.26121287 | I26: =I25/I7 -> 0.24955814 | J26: =J25/J7 -> 0.25047672 | ... L26: =L25/L7 -> 0.97287384
B28: Interest | C28: ='Data Sheet'!B27 -> 0 | D28: ='Data Sheet'!C27 -> 0 | E28: ='Data Sheet'!D27 -> 170 | F28: ='Data Sheet'!E27 -> 195 | G28: ='Data Sheet'!F27 -> 200 | H28: ='Data Sheet'!G27 -> 284 | I28: ='Data Sheet'!H27 -> 470 | J28: ='Data Sheet'!I27 -> 416 | ... L28: ='Data Sheet'!K27 -> 430
B29: Interest % Sales | C29: =C28/C7 -> 0 | D29: =D28/D7 -> 0 | E29: =E28/E7 -> 0.0018724323 | F29: =F28/F7 -> 0.0019408392 | G29: =G28/G7 -> 0.0016441825 | H29: =H28/H7 -> 0.0019350399 | I29: =I28/I7 -> 0.003058502 | J29: =J28/J7 -> 0.0025523038 | ... L29: =L28/L7 -> 0.0023295879
B31: Earning Before Tax | C31: =C25-C28 -> 22114.48 | D31: =D25-D28 -> 25271.75 | E31: =E25-E28 -> 25990.12 | F31: =F25-F28 -> 28689.04 | G31: =G25-G28 -> 32816.3 | H31: =H25-H28 -> 38053.43 | I31: =I25-I28 -> 37879.6 | J31: =J25-J28 -> 40409.2 | ... L31: =L25-L28 -> 179145
B32: EBT % Sales | C32: =C31/C7 -> 0.31358271 | D32: =D31/D7 -> 0.30567584 | E32: =E31/E7 -> 0.28626318 | F32: =F31/F7 -> 0.28554264 | G32: =G31/G7 -> 0.26977993 | H32: =H31/H7 -> 0.25927783 | I32: =I31/I7 -> 0.24649964 | J32: =J31/J7 -> 0.24792441 | ... L32: =L31/L7 -> 0.97054426
B34: Tax Rate | C34: ='Data Sheet'!B29 -> 20270 | D34: ='Data Sheet'!C29 -> 21041 | E34: ='Data Sheet'!D29 -> 22007 | F34: ='Data Sheet'!E29 -> 26628 | G34: ='Data Sheet'!F29 -> 30110 | H34: ='Data Sheet'!G29 -> 33322 | I34: ='Data Sheet'!H29 -> 35988 | J34: ='Data Sheet'!I29 -> 37608 | ... L34: ='Data Sheet'!K29 -> 41283
B35: Effective Tax Rate | C35: =C34/C31 -> 0.91659401 | D35: =D34/D31 -> 0.83258975 | E35: =E34/E31 -> 0.84674484 | F35: =F34/F31 -> 0.92815932 | G35: =G34/G31 -> 0.91753184 | H35: =H34/H31 -> 0.87566351 | I35: =I34/I31 -> 0.95006283 | J35: =J34/J31 -> 0.93067915 | ... L35: =L34/L31 -> 0.23044461
B37: Net Profit | C37: =C31-C34 -> 1844.48 | D37: =D31-D34 -> 4230.75 | E37: =E31-E34 -> 3983.12 | F37: =F31-F34 -> 2061.04 | G37: =G31-G34 -> 2706.3 | H37: =H31-H34 -> 4731.43 | I37: =I31-I34 -> 1891.6 | J37: =J31-J34 -> 2801.2 | ... L37: =L31-L34 -> 137862
B38: Net Profit % Sales | C38: =C37/C7 -> 0.026154675 | D38: =D37/D7 -> 0.051173269 | E38: =E37/E7 -> 0.043871309 | F38: =F37/F7 -> 0.020513576 | G38: =G37/G7 -> 0.022248255 | H38: =H37/H7 -> 0.032237696 | I38: =I37/I7 -> 0.012309494 | J38: =J37/J7 -> 0.01718633 | ... L38: =L37/L7 -> 0.74688756
B40: No. of Equity Shares | C40: ='Data Sheet'!B93 -> 459.41 | D40: ='Data Sheet'!C93 -> 459.41 | E40: ='Data Sheet'!D93 -> 459.41 | F40: ='Data Sheet'!E93 -> 459.41 | G40: ='Data Sheet'!F93 -> 459.41 | H40: ='Data Sheet'!G93 -> 459.41 | I40: ='Data Sheet'!H93 -> 459.41 | J40: ='Data Sheet'!I93 -> 459.41 | ... L40: ='Data Sheet'!K93 -> 459.41
B42: Earning per Share | C42: =C37/C40 -> 4.0148887 | D42: =D37/D40 -> 9.2090943 | E42: =E37/E40 -> 8.6700768 | F42: =F37/F40 -> 4.4862759 | G42: =G37/G40 -> 5.8908165 | H42: =H37/H40 -> 10.298927 | I42: =I37/I40 -> 4.117455 | J42: =J37/J40 -> 6.0973858 | ... L42: =L37/L40 -> 300.08489
B43: EPS Growth | C43: - | D43: =D42/C42-1 -> 1.2937359 | E43: =E42/D42-1 -> -0.058530993 | F43: =F42/E42-1 -> -0.48255639 | G43: =G42/F42-1 -> 0.31307495 | H43: =H42/G42-1 -> 0.74830211 | I43: =I42/H42-1 -> -0.60020543 | J43: =J42/I42-1 -> 0.48086276 | K43: =K42/J42-1 -> 0.68106526 | L43: =L42/K42-1 -> 28.276279
B45: Dividend per Share | C45: ='Data Sheet'!B31/'Historical FS'!C40 -> 20.585338 | D45: ='Data Sheet'!C31/'Historical FS'!D40 -> 20.125814 | E45: ='Data Sheet'!D31/'Historical FS'!E40 -> 16.298187 | F45: ='Data Sheet'!E31/'Historical FS'!F40 -> 24.944102 | G45: ='Data Sheet'!F31/'Historical FS'!G40 -> 28.441131 | H45: ='Data Sheet'!G31/'Historical FS'!H40 -> 30.436081 | I45: ='Data Sheet'!H31/'Historical FS'!I40 -> 41.70793 | J45: ='Data Sheet'!I31/'Historical FS'!J40 -> 39.011994 | ... L45: ='Data Sheet'!K31/'Historical FS'!L40 -> 0
B46: Dividend Payout Ratio | C46: =C45/C42 -> 5.12725 | D46: =D45/D42 -> 2.1854281 | E46: =E45/E42 -> 1.8798203 | F46: =F45/F42 -> 5.560091 | G46: =G45/G42 -> 4.8280457 | H46: =H45/H42 -> 2.9552672 | I46: =I45/I42 -> 10.129541 | J46: =J45/J42 -> 6.3981508 | ... L46: =L45/L42 -> 0
B48: Retained Earnings | C48: =(1-C46) -> -4.12725 | D48: =(1-D46) -> -1.1854281 | E48: =(1-E46) -> -0.87982034 | F48: =(1-F46) -> -4.560091 | G48: =(1-G46) -> -3.8280457 | H48: =(1-H46) -> -1.9552672 | I48: =(1-I46) -> -9.1295411 | J48: =(1-J46) -> -5.3981508 | ... L48: =(1-L46) -> 1
B50: Balance Sheet
B51: ='Data Sheet'!A57 -> Equity Share Capital | C51: ='Data Sheet'!B57 -> 1144 | D51: ='Data Sheet'!C57 -> 1088 | E51: ='Data Sheet'!D57 -> 2170 | F51: ='Data Sheet'!E57 -> 2122 | G51: ='Data Sheet'!F57 -> 2124 | H51: ='Data Sheet'!G57 -> 2098 | I51: ='Data Sheet'!H57 -> 2069 | ... L51: ='Data Sheet'!K57 -> 2024
B52: ='Data Sheet'!A58 -> Reserves | C52: ='Data Sheet'!B58 -> 67838 | D52: ='Data Sheet'!C58 -> 63835 | E52: ='Data Sheet'!D58 -> 62778 | F52: ='Data Sheet'!E58 -> 63328 | G52: ='Data Sheet'!F58 -> 74227 | H52: ='Data Sheet'!G58 -> 73252 | I52: ='Data Sheet'!H58 -> 73338 | ... L52: ='Data Sheet'!K58 -> 90828
B53: ='Data Sheet'!A59 -> Borrowings | C53: ='Data Sheet'!B59 -> 0 | D53: ='Data Sheet'!C59 -> 0 | E53: ='Data Sheet'!D59 -> 0 | F53: ='Data Sheet'!E59 -> 4633 | G53: ='Data Sheet'!F59 -> 5325 | H53: ='Data Sheet'!G59 -> 5474 | I53: ='Data Sheet'!H59 -> 8299 | ... L53: ='Data Sheet'!K59 -> 9176
B54: ='Data Sheet'!A60 -> Other Liabilities | C54: ='Data Sheet'!B60 -> 14166 | D54: ='Data Sheet'!C60 -> 14426 | E54: ='Data Sheet'!D60 -> 19118 | F54: ='Data Sheet'!E60 -> 21717 | G54: ='Data Sheet'!F60 -> 25835 | H54: ='Data Sheet'!G60 -> 35905 | I54: ='Data Sheet'!H60 -> 40890 | ... L54: ='Data Sheet'!K60 -> 52260
B55: Total Liabilities | C55: =SUM(C51:C54) -> 83148 | D55: =SUM(D51:D54) -> 79349 | E55: =SUM(E51:E54) -> 84066 | F55: =SUM(F51:F54) -> 91800 | G55: =SUM(G51:G54) -> 107511 | H55: =SUM(H51:H54) -> 116729 | I55: =SUM(I51:I54) -> 124596 | J55: =SUM(J51:J54) -> 136020 | ... L55: =SUM(L51:L54) -> 154288
B57: Fixed Asset Net Block | C57: ='Data Sheet'!B62 -> 14179 | D57: ='Data Sheet'!C62 -> 12574 | E57: ='Data Sheet'!D62 -> 15710 | F57: ='Data Sheet'!E62 -> 23789 | G57: ='Data Sheet'!F62 -> 25505 | H57: ='Data Sheet'!G62 -> 25800 | I57: ='Data Sheet'!H62 -> 29225 | J57: ='Data Sheet'!I62 -> 27622 | ... L57: ='Data Sheet'!K62 -> 33770
B58: ='Data Sheet'!A63 -> Capital Work in Progress | C58: ='Data Sheet'!B63 -> 1365 | D58: ='Data Sheet'!C63 -> 1606 | E58: ='Data Sheet'!D63 -> 1388 | F58: ='Data Sheet'!E63 -> 954 | G58: ='Data Sheet'!F63 -> 922 | H58: ='Data Sheet'!G63 -> 416 | I58: ='Data Sheet'!H63 -> 288 | ... L58: ='Data Sheet'!K63 -> 526
B59: ='Data Sheet'!A64 -> Investments | C59: ='Data Sheet'!B64 -> 16423 | D59: ='Data Sheet'!C64 -> 12163 | E59: ='Data Sheet'!D64 -> 11261 | F59: ='Data Sheet'!E64 -> 8792 | G59: ='Data Sheet'!F64 -> 14205 | H59: ='Data Sheet'!G64 -> 20324 | I59: ='Data Sheet'!H64 -> 19478 | ... L59: ='Data Sheet'!K64 -> 21880
B60: ='Data Sheet'!A65 -> Other Assets | C60: ='Data Sheet'!B75 -> 8117.9 | D60: ='Data Sheet'!C75 -> 12550.91 | E60: ='Data Sheet'!D75 -> 13452.44 | F60: ='Data Sheet'!E75 -> 12249.67 | G60: ='Data Sheet'!F75 -> 12473.84 | H60: ='Data Sheet'!G75 -> 19154.85 | I60: ='Data Sheet'!H75 -> 26236.84 | J60: ='Data Sheet'!I75 -> 24350.12 | ... O60: ='Data Sheet'!N75 -> 0
B61: Total Non Current Assets | C61: =SUM(C57:C60) -> 40084.9 | D61: =SUM(D57:D60) -> 38893.91 | E61: =SUM(E57:E60) -> 41811.44 | F61: =SUM(F57:F60) -> 45784.67 | G61: =SUM(G57:G60) -> 53105.84 | H61: =SUM(H57:H60) -> 65694.85 | I61: =SUM(I57:I60) -> 75227.84 | J61: =SUM(J57:J60) -> 76888.12 | ... L61: =SUM(L57:L60) -> 78230.04
B63: ='Data Sheet'!A67 -> Receivables | C63: ='Data Sheet'!B67 -> 12322 | D63: ='Data Sheet'!C67 -> 13142 | E63: ='Data Sheet'!D67 -> 14827 | F63: ='Data Sheet'!E67 -> 18487 | G63: ='Data Sheet'!F67 -> 19294 | H63: ='Data Sheet'!G67 -> 22698 | I63: ='Data Sheet'!H67 -> 25424 | ... L63: ='Data Sheet'!K67 -> 35234
B64: ='Data Sheet'!A68 -> Inventory | C64: ='Data Sheet'!B68 -> 8116.1 | D64: ='Data Sheet'!C68 -> 7495.09 | E64: ='Data Sheet'!D68 -> 7859.56 | F64: ='Data Sheet'!E68 -> 8879.33 | G64: ='Data Sheet'!F68 -> 10397.16 | H64: ='Data Sheet'!G68 -> 10864.15 | I64: ='Data Sheet'!H68 -> 11771.16 | ... L64: ='Data Sheet'!K68 -> 18622.96
B65: ='Data Sheet'!A69 -> Cash & Bank | C65: ='Data Sheet'!B69 -> 22625 | D65: ='Data Sheet'!C69 -> 19818 | E65: ='Data Sheet'!D69 -> 19568 | F65: ='Data Sheet'!E69 -> 18649 | G65: ='Data Sheet'!F69 -> 24714 | H65: ='Data Sheet'!G69 -> 17472 | I65: ='Data Sheet'!H69 -> 12173 | ... L65: ='Data Sheet'!K69 -> 22201
B66: Total Current Assets | C66: =SUM(C63:C65) -> 43063.1 | D66: =SUM(D63:D65) -> 40455.09 | E66: =SUM(E63:E65) -> 42254.56 | F66: =SUM(F63:F65) -> 46015.33 | G66: =SUM(G63:G65) -> 54405.16 | H66: =SUM(H63:H65) -> 51034.15 | I66: =SUM(I63:I65) -> 49368.16 | J66: =SUM(J63:J65) -> 59131.88 | ... L66: =SUM(L63:L65) -> 76057.96
B68: Total Assets | C68: =C61+C66 -> 83148 | D68: =D61+D66 -> 79349 | E68: =E61+E66 -> 84066 | F68: =F61+F66 -> 91800 | G68: =G61+G66 -> 107511 | H68: =H61+H66 -> 116729 | I68: =I61+I66 -> 124596 | J68: =J61+J66 -> 136020 | ... L68: =L61+L66 -> 154288
B70: Check | C70: =C68=C55 -> TRUE | D70: =D68=D55 -> TRUE | E70: =E68=E55 -> TRUE | F70: =F68=F55 -> TRUE | G70: =G68=G55 -> TRUE | H70: =H68=H55 -> TRUE | I70: =I68=I55 -> TRUE | J70: =J68=J55 -> TRUE | ... L70: =L68=L55 -> TRUE
B72: Cash Flow Statement
B73: Operating Activity
B74: ='Cash Flow Statement'!B7 -> Profit from operations | C74: ='Cash Flow Statement'!E7 -> 19340 | D74: ='Cash Flow Statement'!F7 -> 19963 | E74: ='Cash Flow Statement'!G7 -> 22126 | F74: ='Cash Flow Statement'!H7 -> 23920 | G74: ='Cash Flow Statement'!I7 -> 28845 | H74: ='Cash Flow Statement'!J7 -> 32921 | I74: ='Cash Flow Statement'!K7 -> 37605 | J74: ='Cash Flow Statement'!L7 -> 39523 | ... L74: ='Cash Flow Statement'!N7 -> 45273
B75: ='Cash Flow Statement'!B8 -> Receivables | C75: ='Cash Flow Statement'!E8 -> -1743 | D75: ='Cash Flow Statement'!F8 -> -1523 | E75: ='Cash Flow Statement'!G8 -> -2881 | F75: ='Cash Flow Statement'!H8 -> -3861 | G75: ='Cash Flow Statement'!I8 -> -1835 | H75: ='Cash Flow Statement'!J8 -> -7937 | I75: ='Cash Flow Statement'!K8 -> -7076 | J75: ='Cash Flow Statement'!L8 -> -2667 | ... L75: ='Cash Flow Statement'!N8 -> -5177
B76: ='Cash Flow Statement'!B9 -> Inventory | C76: ='Cash Flow Statement'!E9 -> 0 | D76: ='Cash Flow Statement'!F9 -> 0 | E76: ='Cash Flow Statement'!G9 -> 0 | F76: ='Cash Flow Statement'!H9 -> 0 | G76: ='Cash Flow Statement'!I9 -> 0 | H76: ='Cash Flow Statement'!J9 -> 0 | I76: ='Cash Flow Statement'!K9 -> 0 | J76: ='Cash Flow Statement'!L9 -> 0 | ... L76: ='Cash Flow Statement'!N9 -> 0
B77: ='Cash Flow Statement'!B10 -> Payables | C77: ='Cash Flow Statement'!E10 -> -19 | D77: ='Cash Flow Statement'!F10 -> 328 | E77: ='Cash Flow Statement'!G10 -> 916 | F77: ='Cash Flow Statement'!H10 -> -373 | G77: ='Cash Flow Statement'!I10 -> -245 | H77: ='Cash Flow Statement'!J10 -> 1489 | I77: ='Cash Flow Statement'!K10 -> -279 | J77: ='Cash Flow Statement'!L10 -> 91 | ... L77: ='Cash Flow Statement'!N10 -> -26
B78: ='Cash Flow Statement'!B11 -> Working capital changes | C78: ='Cash Flow Statement'!E11 -> -2156 | D78: ='Cash Flow Statement'!F11 -> 84 | E78: ='Cash Flow Statement'!G11 -> -453 | F78: ='Cash Flow Statement'!H11 -> -2367 | G78: ='Cash Flow Statement'!I11 -> 768 | H78: ='Cash Flow Statement'!J11 -> -1424 | I78: ='Cash Flow Statement'!K11 -> -6344 | J78: ='Cash Flow Statement'!L11 -> -5082 | ... L78: ='Cash Flow Statement'!N11 -> -2639
B79: ='Cash Flow Statement'!B12 -> Direct taxes | C79: ='Cash Flow Statement'!E12 -> -5653 | D79: ='Cash Flow Statement'!F12 -> -6829 | E79: ='Cash Flow Statement'!G12 -> -6832 | F79: ='Cash Flow Statement'!H12 -> -4550 | G79: ='Cash Flow Statement'!I12 -> -6389 | H79: ='Cash Flow Statement'!J12 -> -7612 | I79: ='Cash Flow Statement'!K12 -> -8794 | J79: ='Cash Flow Statement'!L12 -> -9231 | ... L79: ='Cash Flow Statement'!N12 -> -8648
B80: Cash From Operating Activities | C80: =SUM(C74:C79) -> 9769 | D80: =SUM(D74:D79) -> 12023 | E80: =SUM(E74:E79) -> 12876 | F80: =SUM(F74:F79) -> 12769 | G80: =SUM(G74:G79) -> 21144 | H80: =SUM(H74:H79) -> 17437 | I80: =SUM(I74:I79) -> 15112 | J80: =SUM(J74:J79) -> 22634 | ... L80: =SUM(L74:L79) -> 28783
B82: Investing Activities
B83: ='Cash Flow Statement'!B14 -> Fixed assets purchased | C83: ='Cash Flow Statement'!E14 -> -2760 | D83: ='Cash Flow Statement'!F14 -> -1998 | E83: ='Cash Flow Statement'!G14 -> -2445 | F83: ='Cash Flow Statement'!H14 -> -3307 | G83: ='Cash Flow Statement'!I14 -> -2107 | H83: ='Cash Flow Statement'!J14 -> -2161 | I83: ='Cash Flow Statement'!K14 -> -2579 | J83: ='Cash Flow Statement'!L14 -> -2201 | ... L83: ='Cash Flow Statement'!N14 -> -2727
B84: ='Cash Flow Statement'!B15 -> Fixed assets sold | C84: ='Cash Flow Statement'!E15 -> 0 | D84: ='Cash Flow Statement'!F15 -> 0 | E84: ='Cash Flow Statement'!G15 -> 0 | F84: ='Cash Flow Statement'!H15 -> 0 | G84: ='Cash Flow Statement'!I15 -> 0 | H84: ='Cash Flow Statement'!J15 -> 0 | I84: ='Cash Flow Statement'!K15 -> 0 | J84: ='Cash Flow Statement'!L15 -> 0 | ... L84: ='Cash Flow Statement'!N15 -> 0
B85: ='Cash Flow Statement'!B16 -> Investments purchased | C85: ='Cash Flow Statement'!E16 -> -66410 | D85: ='Cash Flow Statement'!F16 -> -69159 | E85: ='Cash Flow Statement'!G16 -> -79410 | F85: ='Cash Flow Statement'!H16 -> -37482 | G85: ='Cash Flow Statement'!I16 -> -46738 | H85: ='Cash Flow Statement'!J16 -> -59951 | I85: ='Cash Flow Statement'!K16 -> -75800 | J85: ='Cash Flow Statement'!L16 -> -78092 | ... L85: ='Cash Flow Statement'!N16 -> -82617
B86: ='Cash Flow Statement'!B17 -> Investments sold | C86: ='Cash Flow Statement'!E17 -> 52048 | D86: ='Cash Flow Statement'!F17 -> 74003 | E86: ='Cash Flow Statement'!G17 -> 78098 | F86: ='Cash Flow Statement'!H17 -> 38861 | G86: ='Cash Flow Statement'!I17 -> 40381 | H86: ='Cash Flow Statement'!J17 -> 57356 | I86: ='Cash Flow Statement'!K17 -> 76722 | J86: ='Cash Flow Statement'!L17 -> 72930 | ... L86: ='Cash Flow Statement'!N17 -> 89699
B87: ='Cash Flow Statement'!B18 -> Interest received | C87: ='Cash Flow Statement'!E18 -> 0 | D87: ='Cash Flow Statement'!F18 -> 0 | E87: ='Cash Flow Statement'!G18 -> 0 | F87: ='Cash Flow Statement'!H18 -> 0 | G87: ='Cash Flow Statement'!I18 -> 0 | H87: ='Cash Flow Statement'!J18 -> 0 | I87: ='Cash Flow Statement'!K18 -> 0 | J87: ='Cash Flow Statement'!L18 -> 0 | ... L87: ='Cash Flow Statement'!N18 -> 0
B88: ='Cash Flow Statement'!B19 -> Dividends received | C88: ='Cash Flow Statement'!E19 -> 2753 | D88: ='Cash Flow Statement'!F19 -> 1768 | E88: ='Cash Flow Statement'!G19 -> 1557 | F88: ='Cash Flow Statement'!H19 -> 1929 | G88: ='Cash Flow Statement'!I19 -> 1418 | H88: ='Cash Flow Statement'!J19 -> 1898 | I88: ='Cash Flow Statement'!K19 -> 1525 | J88: ='Cash Flow Statement'!L19 -> 1768 | ... L88: ='Cash Flow Statement'!N19 -> 2713
B89: ='Cash Flow Statement'!B20 -> Invest in subsidiaries | C89: ='Cash Flow Statement'!E20 -> 0 | D89: ='Cash Flow Statement'!F20 -> 0 | E89: ='Cash Flow Statement'!G20 -> 0 | F89: ='Cash Flow Statement'!H20 -> 0 | G89: ='Cash Flow Statement'!I20 -> 0 | H89: ='Cash Flow Statement'!J20 -> 0 | I89: ='Cash Flow Statement'!K20 -> 0 | J89: ='Cash Flow Statement'!L20 -> 0 | ... L89: ='Cash Flow Statement'!N20 -> 0
B90: ='Cash Flow Statement'!B21 -> Investment in group cos | C90: ='Cash Flow Statement'!E21 -> 0 | D90: ='Cash Flow Statement'!F21 -> 0 | E90: ='Cash Flow Statement'!G21 -> 0 | F90: ='Cash Flow Statement'!H21 -> 0 | G90: ='Cash Flow Statement'!I21 -> 0 | H90: ='Cash Flow Statement'!J21 -> 0 | I90: ='Cash Flow Statement'!K21 -> 0 | J90: ='Cash Flow Statement'!L21 -> 0 | ... L90: ='Cash Flow Statement'!N21 -> 0
B91: ='Cash Flow Statement'!B22 -> Redemp n Canc of Shares | C91: ='Cash Flow Statement'!E22 -> 0 | D91: ='Cash Flow Statement'!F22 -> 0 | E91: ='Cash Flow Statement'!G22 -> 0 | F91: ='Cash Flow Statement'!H22 -> 0 | G91: ='Cash Flow Statement'!I22 -> 0 | H91: ='Cash Flow Statement'!J22 -> 0 | I91: ='Cash Flow Statement'!K22 -> 0 | J91: ='Cash Flow Statement'!L22 -> 0 | ... L91: ='Cash Flow Statement'!N22 -> 0
B92: ='Cash Flow Statement'!B23 -> Other investing items | C92: ='Cash Flow Statement'!E23 -> -131 | D92: ='Cash Flow Statement'!F23 -> 49 | E92: ='Cash Flow Statement'!G23 -> 1592 | F92: ='Cash Flow Statement'!H23 -> -224 | G92: ='Cash Flow Statement'!I23 -> -327 | H92: ='Cash Flow Statement'!J23 -> -3627 | I92: ='Cash Flow Statement'!K23 -> -939 | J92: ='Cash Flow Statement'!L23 -> 502 | ... L92: ='Cash Flow Statement'!N23 -> -3522
B93: Cash From Investing Activities | C93: =SUM(C83:C92) -> -14500 | D93: =SUM(D83:D92) -> 4663 | E93: =SUM(E83:E92) -> -608 | F93: =SUM(F83:F92) -> -223 | G93: =SUM(G83:G92) -> -7373 | H93: =SUM(H83:H92) -> -6485 | I93: =SUM(I83:I92) -> -1071 | J93: =SUM(J83:J92) -> -5093 | ... L93: =SUM(L83:L92) -> 3546
B95: Financing Activities
B96: ='Cash Flow Statement'!B25 -> Proceeds from shares | C96: ='Cash Flow Statement'!E25 -> 0 | D96: ='Cash Flow Statement'!F25 -> 5 | E96: ='Cash Flow Statement'!G25 -> 6 | F96: ='Cash Flow Statement'!H25 -> 6 | G96: ='Cash Flow Statement'!I25 -> 15 | H96: ='Cash Flow Statement'!J25 -> 21 | I96: ='Cash Flow Statement'!K25 -> 35 | J96: ='Cash Flow Statement'!L25 -> 5 | ... L96: ='Cash Flow Statement'!N25 -> 2
B97: ='Cash Flow Statement'!B26 -> Proceeds from borrowings | C97: ='Cash Flow Statement'!E26 -> 0 | D97: ='Cash Flow Statement'!F26 -> 0 | E97: ='Cash Flow Statement'!G26 -> 0 | F97: ='Cash Flow Statement'!H26 -> 0 | G97: ='Cash Flow Statement'!I26 -> 0 | H97: ='Cash Flow Statement'!J26 -> 0 | I97: ='Cash Flow Statement'!K26 -> 0 | J97: ='Cash Flow Statement'!L26 -> 0 | ... L97: ='Cash Flow Statement'!N26 -> 0
B98: ='Cash Flow Statement'!B27 -> Repayment of borrowings | C98: ='Cash Flow Statement'!E27 -> 0 | D98: ='Cash Flow Statement'!F27 -> 0 | E98: ='Cash Flow Statement'!G27 -> 0 | F98: ='Cash Flow Statement'!H27 -> 0 | G98: ='Cash Flow Statement'!I27 -> 0 | H98: ='Cash Flow Statement'!J27 -> 0 | I98: ='Cash Flow Statement'!K27 -> 0 | J98: ='Cash Flow Statement'!L27 -> 0 | ... L98: ='Cash Flow Statement'!N27 -> 0
B99: ='Cash Flow Statement'!B28 -> Interest paid fin | C99: ='Cash Flow Statement'!E28 -> 0 | D99: ='Cash Flow Statement'!F28 -> 0 | E99: ='Cash Flow Statement'!G28 -> 0 | F99: ='Cash Flow Statement'!H28 -> 0 | G99: ='Cash Flow Statement'!I28 -> 0 | H99: ='Cash Flow Statement'!J28 -> 0 | I99: ='Cash Flow Statement'!K28 -> 0 | J99: ='Cash Flow Statement'!L28 -> 0 | ... L99: ='Cash Flow Statement'!N28 -> 0
B100: ='Cash Flow Statement'!B29 -> Dividends paid | C100: ='Cash Flow Statement'!E29 -> -6939 | D100: ='Cash Flow Statement'!F29 -> -7464 | E100: ='Cash Flow Statement'!G29 -> -13705 | F100: ='Cash Flow Statement'!H29 -> -9548 | G100: ='Cash Flow Statement'!I29 -> -9137 | H100: ='Cash Flow Statement'!J29 -> -12731 | I100: ='Cash Flow Statement'!K29 -> -13653 | J100: ='Cash Flow Statement'!L29 -> -14731 | ... L100: ='Cash Flow Statement'!N29 -> -18656
B101: ='Cash Flow Statement'!B30 -> Financial liabilities | C101: ='Cash Flow Statement'!E30 -> 0 | D101: ='Cash Flow Statement'!F30 -> 0 | E101: ='Cash Flow Statement'!G30 -> 0 | F101: ='Cash Flow Statement'!H30 -> -571 | G101: ='Cash Flow Statement'!I30 -> -698 | H101: ='Cash Flow Statement'!J30 -> -915 | I101: ='Cash Flow Statement'!K30 -> -1231 | J101: ='Cash Flow Statement'!L30 -> -2024 | ... L101: ='Cash Flow Statement'!N30 -> -2824
B102: ='Cash Flow Statement'!B31 -> Other financing items | C102: ='Cash Flow Statement'!E31 -> 0 | D102: ='Cash Flow Statement'!F31 -> -13046 | E102: ='Cash Flow Statement'!G31 -> -813 | F102: ='Cash Flow Statement'!H31 -> -7478 | G102: ='Cash Flow Statement'!I31 -> 34 | H102: ='Cash Flow Statement'!J31 -> -11017 | I102: ='Cash Flow Statement'!K31 -> -11846 | J102: ='Cash Flow Statement'!L31 -> -754 | ... L102: ='Cash Flow Statement'!N31 -> -18308
B103: Cash From Financing Activities | C103: =SUM(C96:C102) -> -6939 | D103: =SUM(D96:D102) -> -20505 | E103: =SUM(E96:E102) -> -14512 | F103: =SUM(F96:F102) -> -17591 | G103: =SUM(G96:G102) -> -9786 | H103: =SUM(H96:H102) -> -24642 | I103: =SUM(I96:I102) -> -26695 | J103: =SUM(J96:J102) -> -17504 | ... L103: =SUM(L96:L102) -> -39786
B105: Net Cash Flow | C105: =C80+C93+C103 -> -11670 | D105: =D80+D93+D103 -> -3819 | E105: =E80+E93+E103 -> -2244 | F105: =F80+F93+F103 -> -5045 | G105: =G80+G93+G103 -> 3985 | H105: =H80+H93+H103 -> -13690 | I105: =I80+I93+I103 -> -12654 | J105: =J80+J93+J103 -> 37 | ... L105: =L80+L93+L103 -> -7457

Sheet Ratio Analysis
B2: ="Ratio Analysis - "&'Data Sheet'!$B$1 -> Ratio Analysis - Infosys Ltd
B3: Years | C3: ='Data Sheet'!B56 -> 42795 | D3: ='Data Sheet'!C56 -> 43160 | E3: ='Data Sheet'!D56 -> 43525 | F3: ='Data Sheet'!E56 -> 43891 | G3: ='Data Sheet'!F56 -> 44256 | H3: ='Data Sheet'!G56 -> 44621 | I3: ='Data Sheet'!H56 -> 44986 | J3: ='Data Sheet'!I56 -> 45352 | ... L3: ='Data Sheet'!K56 -> 46082 | M3: Trend | N3: Mean | O3: Median
B5: SalesGrowth | D5: =IFERROR('Historical FS'!D8,0) -> 0.1723292 | E5: =IFERROR('Historical FS'!E8,0) -> 0.098167523 | F5: =IFERROR('Historical FS'!F8,0) -> 0.10662951 | G5: =IFERROR('Historical FS'!G8,0) -> 0.21069552 | H5: =IFERROR('Historical FS'!H8,0) -> 0.20655864 | I5: =IFERROR('Historical FS'!I8,0) -> 0.047033734 | J5: =IFERROR('Historical FS'!J8,0) -> 0.060649444 | K5: =IFERROR('Historical FS'!K8,0) -> 0.096079514 | L5: =IFERROR('Historical FS'!L8,0) -> 0.03320459 | N5: =IFERROR(AVERAGE(D5:L5),0) -> 0.11459419 | O5: =IFERROR(MEDIAN(D5:L5),0) -> 0.098167523
B6: EBITDA Growth | D6: =IFERROR(('Historical FS'!D19/'Historical FS'!C19-1),0) -> 0.13784893 | E6: =IFERROR(('Historical FS'!E19/'Historical FS'!D19-1),0) -> 0.06488972 | F6: =IFERROR(('Historical FS'!F19/'Historical FS'!E19-1),0) -> 0.10662951 | G6: =IFERROR(('Historical FS'!G19/'Historical FS'!F19-1),0) -> 0.13502705 | H6: =IFERROR(('Historical FS'!H19/'Historical FS'!G19-1),0) -> 0.16634002 | I6: =IFERROR(('Historical FS'!I19/'Historical FS'!H19-1),0) -> 0.010929122 | J6: =IFERROR(('Historical FS'!J19/'Historical FS'!I19-1),0) -> 0.060649444 | K6: =IFERROR(('Historical FS'!K19/'Historical FS'!J19-1),0) -> 0.096079514 | L6: =IFERROR(('Historical FS'!L19/'Historical FS'!K19-1),0) -> 2.6900164 | N6: =IFERROR(AVERAGE(D6:L6),0) -> 0.38537886 | O6: =IFERROR(MEDIAN(D6:L6),0) -> 0.10662951
B7: EBIT Growth | D7: =IFERROR(('Historical FS'!D25/'Historical FS'!C25-1),0) -> 0.14276935 | E7: =IFERROR(('Historical FS'!E25/'Historical FS'!D25-1),0) -> 0.03515269 | F7: =IFERROR(('Historical FS'!F25/'Historical FS'!E25-1),0) -> 0.1041249 | G7: =IFERROR(('Historical FS'!G25/'Historical FS'!F25-1),0) -> 0.14306378 | H7: =IFERROR(('Historical FS'!H25/'Historical FS'!G25-1),0) -> 0.16116676 | I7: =IFERROR(('Historical FS'!I25/'Historical FS'!H25-1),0) -> 0.00031744434 | J7: =IFERROR(('Historical FS'!J25/'Historical FS'!I25-1),0) -> 0.064553476 | K7: =IFERROR(('Historical FS'!K25/'Historical FS'!J25-1),0) -> 0.10519973 | L7: =IFERROR(('Historical FS'!L25/'Historical FS'!K25-1),0) -> 2.9799424 | N7: =IFERROR(AVERAGE(D7:L7),0) -> 0.41514339 | O7: =IFERROR(MEDIAN(D7:L7),0) -> 0.10519973
B8: Net Profit Growth | D8: =IFERROR(('Historical FS'!D37/'Historical FS'!C37-1),0) -> 1.2937359 | E8: =IFERROR(('Historical FS'!E37/'Historical FS'!D37-1),0) -> -0.058530993 | F8: =IFERROR(('Historical FS'!F37/'Historical FS'!E37-1),0) -> -0.48255639 | G8: =IFERROR(('Historical FS'!G37/'Historical FS'!F37-1),0) -> 0.31307495 | H8: =IFERROR(('Historical FS'!H37/'Historical FS'!G37-1),0) -> 0.74830211 | I8: =IFERROR(('Historical FS'!I37/'Historical FS'!H37-1),0) -> -0.60020543 | J8: =IFERROR(('Historical FS'!J37/'Historical FS'!I37-1),0) -> 0.48086276 | K8: =IFERROR(('Historical FS'!K37/'Historical FS'!J37-1),0) -> 0.68106526 | L8: =IFERROR(('Historical FS'!L37/'Historical FS'!K37-1),0) -> 28.276279 | N8: =IFERROR(AVERAGE(D8:L8),0) -> 3.4057808 | O8: =IFERROR(MEDIAN(D8:L8),0) -> 0.48086276
B9: Dividend Growth | D9: =IFERROR(('Historical FS'!D45/'Historical FS'!C45-1),0) -> -0.022322887 | E9: =IFERROR(('Historical FS'!E45/'Historical FS'!D45-1),0) -> -0.19018494 | F9: =IFERROR(('Historical FS'!F45/'Historical FS'!E45-1),0) -> 0.53048327 | G9: =IFERROR(('Historical FS'!G45/'Historical FS'!F45-1),0) -> 0.14019461 | H9: =IFERROR(('Historical FS'!H45/'Historical FS'!G45-1),0) -> 0.070143133 | I9: =IFERROR(('Historical FS'!I45/'Historical FS'!H45-1),0) -> 0.37034494 | J9: =IFERROR(('Historical FS'!J45/'Historical FS'!I45-1),0) -> -0.064638454 | K9: =IFERROR(('Historical FS'!K45/'Historical FS'!J45-1),0) -> 0.085386525 | L9: =IFERROR(('Historical FS'!L45/'Historical FS'!K45-1),0) -> -1 | N9: =IFERROR(AVERAGE(D9:L9),0) -> -0.0089548669 | O9: =IFERROR(MEDIAN(D9:L9),0) -> 0.070143133
B11: Gross Margin | C11: =IFERROR('Historical FS'!C14,0) -> 0.34 | D11: =IFERROR('Historical FS'!D14,0) -> 0.33 | E11: =IFERROR('Historical FS'!E14,0) -> 0.32 | F11: =IFERROR('Historical FS'!F14,0) -> 0.32 | G11: =IFERROR('Historical FS'!G14,0) -> 0.3 | H11: =IFERROR('Historical FS'!H14,0) -> 0.29 | I11: =IFERROR('Historical FS'!I14,0) -> 0.28 | J11: =IFERROR('Historical FS'!J14,0) -> 0.28 | ... L11: =IFERROR('Historical FS'!L14,0) -> 1 | N11: =IFERROR(AVERAGE(C11:L11),0) -> 0.374 | O11: =IFERROR(MEDIAN(C11:L11),0) -> 0.31
B12: EBITDA Margin | C12: =IFERROR('Historical FS'!C20,0) -> 0.34 | D12: =IFERROR('Historical FS'!D20,0) -> 0.33 | E12: =IFERROR('Historical FS'!E20,0) -> 0.32 | F12: =IFERROR('Historical FS'!F20,0) -> 0.32 | G12: =IFERROR('Historical FS'!G20,0) -> 0.3 | H12: =IFERROR('Historical FS'!H20,0) -> 0.29 | I12: =IFERROR('Historical FS'!I20,0) -> 0.28 | J12: =IFERROR('Historical FS'!J20,0) -> 0.28 | ... L12: =IFERROR('Historical FS'!L20,0) -> 1 | N12: =IFERROR(AVERAGE(C12:L12),0) -> 0.374 | O12: =IFERROR(MEDIAN(C12:L12),0) -> 0.31
B13: EBIT Margin | C13: =IFERROR('Historical FS'!C26,0) -> 0.31358271 | D13: =IFERROR('Historical FS'!D26,0) -> 0.30567584 | E13: =IFERROR('Historical FS'!E26,0) -> 0.28813561 | F13: =IFERROR('Historical FS'!F26,0) -> 0.28748348 | G13: =IFERROR('Historical FS'!G26,0) -> 0.27142411 | H13: =IFERROR('Historical FS'!H26,0) -> 0.26121287 | I13: =IFERROR('Historical FS'!I26,0) -> 0.24955814 | J13: =IFERROR('Historical FS'!J26,0) -> 0.25047672 | ... L13: =IFERROR('Historical FS'!L26,0) -> 0.97287384 | N13: =IFERROR(AVERAGE(C13:L13),0) -> 0.34529842 | O13: =IFERROR(MEDIAN(C13:L13),0) -> 0.27945379
B14: EBT Margin | C14: =IFERROR('Historical FS'!C32,0) -> 0.31358271 | D14: =IFERROR('Historical FS'!D32,0) -> 0.30567584 | E14: =IFERROR('Historical FS'!E32,0) -> 0.28626318 | F14: =IFERROR('Historical FS'!F32,0) -> 0.28554264 | G14: =IFERROR('Historical FS'!G32,0) -> 0.26977993 | H14: =IFERROR('Historical FS'!H32,0) -> 0.25927783 | I14: =IFERROR('Historical FS'!I32,0) -> 0.24649964 | J14: =IFERROR('Historical FS'!J32,0) -> 0.24792441 | ... L14: =IFERROR('Historical FS'!L32,0) -> 0.97054426 | N14: =IFERROR(AVERAGE(C14:L14),0) -> 0.34353227 | O14: =IFERROR(MEDIAN(C14:L14),0) -> 0.27766128
B15: Net Profit Margin | C15: =IFERROR('Historical FS'!C38,0) -> 0.026154675 | D15: =IFERROR('Historical FS'!D38,0) -> 0.051173269 | E15: =IFERROR('Historical FS'!E38,0) -> 0.043871309 | F15: =IFERROR('Historical FS'!F38,0) -> 0.020513576 | G15: =IFERROR('Historical FS'!G38,0) -> 0.022248255 | H15: =IFERROR('Historical FS'!H38,0) -> 0.032237696 | I15: =IFERROR('Historical FS'!I38,0) -> 0.012309494 | J15: =IFERROR('Historical FS'!J38,0) -> 0.01718633 | ... L15: =IFERROR('Historical FS'!L38,0) -> 0.74688756 | N15: =IFERROR(AVERAGE(C15:L15),0) -> 0.099894097 | O15: =IFERROR(MEDIAN(C15:L15),0) -> 0.026256739
B17: SalesExpenses%sales | C17: =IFERROR('Historical FS'!C17,0) -> 0 | D17: =IFERROR('Historical FS'!D17,0) -> 0 | E17: =IFERROR('Historical FS'!E17,0) -> 0 | F17: =IFERROR('Historical FS'!F17,0) -> 0 | G17: =IFERROR('Historical FS'!G17,0) -> 0 | H17: =IFERROR('Historical FS'!H17,0) -> 0 | I17: =IFERROR('Historical FS'!I17,0) -> 0 | J17: =IFERROR('Historical FS'!J17,0) -> 0 | ... L17: =IFERROR('Historical FS'!L17,0) -> 0 | N17: =IFERROR(AVERAGE(C17:L17),0) -> 0 | O17: =IFERROR(MEDIAN(C17:L17),0) -> 0
B18: Depreciation%Sales | C18: =IFERROR('Historical FS'!C23,0) -> 0.026417288 | D18: =IFERROR('Historical FS'!D23,0) -> 0.024324161 | E18: =IFERROR('Historical FS'!E23,0) -> 0.031864392 | F18: =IFERROR('Historical FS'!F23,0) -> 0.032516522 | G18: =IFERROR('Historical FS'!G23,0) -> 0.028575891 | H18: =IFERROR('Historical FS'!H23,0) -> 0.028787125 | I18: =IFERROR('Historical FS'!I23,0) -> 0.030441856 | J18: =IFERROR('Historical FS'!J23,0) -> 0.029523284 | ... L18: =IFERROR('Historical FS'!L23,0) -> 0.027126155 | N18: =IFERROR(AVERAGE(C18:L18),0) -> 0.02870158 | O18: =IFERROR(MEDIAN(C18:L18),0) -> 0.028681508
B19: OperatingIncome%sales | C19: =C13 -> 0.31358271 | D19: =D13 -> 0.30567584 | E19: =E13 -> 0.28813561 | F19: =F13 -> 0.28748348 | G19: =G13 -> 0.27142411 | H19: =H13 -> 0.26121287 | I19: =I13 -> 0.24955814 | J19: =J13 -> 0.25047672 | ... L19: =L13 -> 0.97287384 | N19: =IFERROR(AVERAGE(C19:L19),0) -> 0.34529842 | O19: =IFERROR(MEDIAN(C19:L19),0) -> 0.27945379
B21: Return on Capital Employed | C21: =IFERROR('Historical FS'!C25/SUM('Historical FS'!C51:'Historical FS'!C53),0) -> 0.32058334 | D21: =IFERROR('Historical FS'!D25/SUM('Historical FS'!D51:'Historical FS'!D53),0) -> 0.38925727 | E21: =IFERROR('Historical FS'!E25/SUM('Historical FS'!E51:'Historical FS'!E53),0) -> 0.40278561 | F21: =IFERROR('Historical FS'!F25/SUM('Historical FS'!F51:'Historical FS'!F53),0) -> 0.41214046 | G21: =IFERROR('Historical FS'!G25/SUM('Historical FS'!G51:'Historical FS'!G53),0) -> 0.40423503 | H21: =IFERROR('Historical FS'!H25/SUM('Historical FS'!H51:'Historical FS'!H53),0) -> 0.47433225 | I21: =IFERROR('Historical FS'!I25/SUM('Historical FS'!I51:'Historical FS'!I53),0) -> 0.45814637 | J21: =IFERROR('Historical FS'!J25/SUM('Historical FS'!J51:'Historical FS'!J53),0) -> 0.4231687 | ... L21: =IFERROR('Historical FS'!L25/SUM('Historical FS'!L51:'Historical FS'!L53),0) -> 1.7600561 | N21: =IFERROR(AVERAGE(C21:L21),0) -> 0.54783636 | O21: =IFERROR(MEDIAN(C21:L21),0) -> 0.41765458
B22: Retained Earnings% | C22: =IFERROR('Historical FS'!C48,0) -> -4.12725 | D22: =IFERROR('Historical FS'!D48,0) -> -1.1854281 | E22: =IFERROR('Historical FS'!E48,0) -> -0.87982034 | F22: =IFERROR('Historical FS'!F48,0) -> -4.560091 | G22: =IFERROR('Historical FS'!G48,0) -> -3.8280457 | H22: =IFERROR('Historical FS'!H48,0) -> -1.9552672 | I22: =IFERROR('Historical FS'!I48,0) -> -9.1295411 | J22: =IFERROR('Historical FS'!J48,0) -> -5.3981508 | ... L22: =IFERROR('Historical FS'!L48,0) -> 1 | N22: =IFERROR(AVERAGE(C22:L22),0) -> -3.3194586 | O22: =IFERROR(MEDIAN(C22:L22),0) -> -3.4795187
B23: Return on Equity% | C23: =IFERROR('Historical FS'!C37/SUM('Historical FS'!C51:'Historical FS'!C52),0) -> 0.026738569 | D23: =IFERROR('Historical FS'!D37/SUM('Historical FS'!D51:'Historical FS'!D52),0) -> 0.065165658 | E23: =IFERROR('Historical FS'!E37/SUM('Historical FS'!E51:'Historical FS'!E52),0) -> 0.061327831 | F23: =IFERROR('Historical FS'!F37/SUM('Historical FS'!F51:'Historical FS'!F52),0) -> 0.031490298 | G23: =IFERROR('Historical FS'!G37/SUM('Historical FS'!G51:'Historical FS'!G52),0) -> 0.035445508 | H23: =IFERROR('Historical FS'!H37/SUM('Historical FS'!H51:'Historical FS'!H52),0) -> 0.062792701 | I23: =IFERROR('Historical FS'!I37/SUM('Historical FS'!I51:'Historical FS'!I52),0) -> 0.025085204 | J23: =IFERROR('Historical FS'!J37/SUM('Historical FS'!J51:'Historical FS'!J52),0) -> 0.031789913 | ... L23: =IFERROR('Historical FS'!L37/SUM('Historical FS'!L51:'Historical FS'!L52),0) -> 1.4847499 | N23: =IFERROR(AVERAGE(C23:L23),0) -> 0.18737309 | O23: =IFERROR(MEDIAN(C23:L23),0) -> 0.042295381
B24: Self Sustained Growth Rate | C24: =IFERROR(C22*C23,0) -> -0.11035676 | D24: =IFERROR(D22*D23,0) -> -0.077249203 | E24: =IFERROR(E22*E23,0) -> -0.053957474 | F24: =IFERROR(F22*F23,0) -> -0.14359862 | G24: =IFERROR(G22*G23,0) -> -0.13568702 | H24: =IFERROR(H22*H23,0) -> -0.12277651 | I24: =IFERROR(I22*I23,0) -> -0.2290164 | J24: =IFERROR(J22*J23,0) -> -0.17160675 | ... L24: =IFERROR(L22*L23,0) -> 1.4847499 | N24: =IFERROR(AVERAGE(C24:L24),0) -> 0.028662779 | O24: =IFERROR(MEDIAN(C24:L24),0) -> -0.12923177
B25: Interest Coverage Ratio | C25: =IFERROR('Historical FS'!C25/'Historical FS'!C28,0) -> 0 | D25: =IFERROR('Historical FS'!D25/'Historical FS'!D28,0) -> 0 | E25: =IFERROR('Historical FS'!E25/'Historical FS'!E28,0) -> 153.88306 | F25: =IFERROR('Historical FS'!F25/'Historical FS'!F28,0) -> 148.12328 | G25: =IFERROR('Historical FS'!G25/'Historical FS'!G28,0) -> 165.0815 | H25: =IFERROR('Historical FS'!H25/'Historical FS'!H28,0) -> 134.99095 | I25: =IFERROR('Historical FS'!I25/'Historical FS'!I28,0) -> 81.594894 | J25: =IFERROR('Historical FS'!J25/'Historical FS'!J28,0) -> 98.1375 | ... L25: =IFERROR('Historical FS'!L25/'Historical FS'!L28,0) -> 417.61628 | N25: =IFERROR(AVERAGE(C25:L25),0) -> 130.7889 | O25: =IFERROR(MEDIAN(C25:L25),0) -> 121.72624
B27: Debtor Turnover Ratio | C27: =IFERROR('Historical FS'!C7/'Historical FS'!C63,0) -> 5.7232592 | D27: =IFERROR('Historical FS'!D7/'Historical FS'!D63,0) -> 6.2908994 | E27: =IFERROR('Historical FS'!E7/'Historical FS'!E63,0) -> 6.123356 | F27: =IFERROR('Historical FS'!F7/'Historical FS'!F63,0) -> 5.4347379 | G27: =IFERROR('Historical FS'!G7/'Historical FS'!G63,0) -> 6.3046025 | H27: =IFERROR('Historical FS'!H7/'Historical FS'!H63,0) -> 6.4660763 | I27: =IFERROR('Historical FS'!I7/'Historical FS'!I63,0) -> 6.0442889 | J27: =IFERROR('Historical FS'!J7/'Historical FS'!J63,0) -> 5.3982711 | ... L27: =IFERROR('Historical FS'!L7/'Historical FS'!L63,0) -> 5.2387467 | N27: =IFERROR(AVERAGE(C27:L27),0) -> 5.8757918 | O27: =IFERROR(MEDIAN(C27:L27),0) -> 5.8889844
B28: Creditor Turnover Ratio | C28: =IFERROR('Historical FS'!C7/'Historical FS'!C54,0) -> 4.9782578 | D28: =IFERROR('Historical FS'!D7/'Historical FS'!D54,0) -> 5.7309719 | E28: =IFERROR('Historical FS'!E7/'Historical FS'!E54,0) -> 4.74898 | F28: =IFERROR('Historical FS'!F7/'Historical FS'!F54,0) -> 4.6264217 | G28: =IFERROR('Historical FS'!G7/'Historical FS'!G54,0) -> 4.7083801 | H28: =IFERROR('Historical FS'!H7/'Historical FS'!H54,0) -> 4.087648 | I28: =IFERROR('Historical FS'!I7/'Historical FS'!I54,0) -> 3.7581316 | J28: =IFERROR('Historical FS'!J7/'Historical FS'!J54,0) -> 4.1216336 | ... L28: =IFERROR('Historical FS'!L7/'Historical FS'!L54,0) -> 3.5319939 | N28: =IFERROR(AVERAGE(C28:L28),0) -> 4.4375847 | O28: =IFERROR(MEDIAN(C28:L28),0) -> 4.3740276
B29: Inventory Turnover | C29: =IFERROR('Historical FS'!C7/'Historical FS'!C64,0) -> 8.6891487 | D29: =IFERROR('Historical FS'!D7/'Historical FS'!D64,0) -> 11.030555 | E29: =IFERROR('Historical FS'!E7/'Historical FS'!E64,0) -> 11.551664 | F29: =IFERROR('Historical FS'!F7/'Historical FS'!F64,0) -> 11.315268 | G29: =IFERROR('Historical FS'!G7/'Historical FS'!G64,0) -> 11.699445 | H29: =IFERROR('Historical FS'!H7/'Historical FS'!H64,0) -> 13.509294 | I29: =IFERROR('Historical FS'!I7/'Historical FS'!I64,0) -> 13.054788 | J29: =IFERROR('Historical FS'!J7/'Historical FS'!J64,0) -> 11.516384 | ... L29: =IFERROR('Historical FS'!L7/'Historical FS'!L64,0) -> 9.9115286 | N29: =IFERROR(AVERAGE(C29:L29),0) -> 11.370249 | O29: =IFERROR(MEDIAN(C29:L29),0) -> 11.4704
B30: Fixed Assets Turnover | C30: =IFERROR('Historical FS'!C7/'Historical FS'!C57,0) -> 4.9736935 | D30: =IFERROR('Historical FS'!D7/'Historical FS'!D57,0) -> 6.5750756 | E30: =IFERROR('Historical FS'!E7/'Historical FS'!E57,0) -> 5.7791852 | F30: =IFERROR('Historical FS'!F7/'Historical FS'!F57,0) -> 4.2234646 | G30: =IFERROR('Historical FS'!G7/'Historical FS'!G57,0) -> 4.7693001 | H30: =IFERROR('Historical FS'!H7/'Historical FS'!H57,0) -> 5.6886434 | I30: =IFERROR('Historical FS'!I7/'Historical FS'!I57,0) -> 5.2581694 | J30: =IFERROR('Historical FS'!J7/'Historical FS'!J57,0) -> 5.9007313 | ... L30: =IFERROR('Historical FS'!L7/'Historical FS'!L57,0) -> 5.4658573 | N30: =IFERROR(AVERAGE(C30:L30),0) -> 5.4404283 | O30: =IFERROR(MEDIAN(C30:L30),0) -> 5.5772503
B31: Capital Turnover Ratio | C31: =IFERROR('Historical FS'!C7/SUM('Historical FS'!C51:'Historical FS'!C52),0) -> 1.0223247 | D31: =IFERROR('Historical FS'!D7/SUM('Historical FS'!D51:'Historical FS'!D52),0) -> 1.2734316 | E31: =IFERROR('Historical FS'!E7/SUM('Historical FS'!E51:'Historical FS'!E52),0) -> 1.3979029 | F31: =IFERROR('Historical FS'!F7/SUM('Historical FS'!F51:'Historical FS'!F52),0) -> 1.5350955 | G31: =IFERROR('Historical FS'!G7/SUM('Historical FS'!G51:'Historical FS'!G52),0) -> 1.5931815 | H31: =IFERROR('Historical FS'!H7/SUM('Historical FS'!H51:'Historical FS'!H52),0) -> 1.9478036 | I31: =IFERROR('Historical FS'!I7/SUM('Historical FS'!I51:'Historical FS'!I52),0) -> 2.0378745 | J31: =IFERROR('Historical FS'!J7/SUM('Historical FS'!J51:'Historical FS'!J52),0) -> 1.8497208 | ... L31: =IFERROR('Historical FS'!L7/SUM('Historical FS'!L51:'Historical FS'!L52),0) -> 1.9879163 | N31: =IFERROR(AVERAGE(C31:L31),0) -> 1.6509724 | O31: =IFERROR(MEDIAN(C31:L31),0) -> 1.7214512
B33: (in days)
B34: Debtor Days | C34: =IFERROR(365/C27,0) -> 63.77485 | D34: =IFERROR(365/D27,0) -> 58.020321 | E34: =IFERROR(365/E27,0) -> 59.607836 | F34: =IFERROR(365/F27,0) -> 67.160552 | G34: =IFERROR(365/G27,0) -> 57.894213 | H34: =IFERROR(365/H27,0) -> 56.448452 | I34: =IFERROR(365/I27,0) -> 60.387584 | J34: =IFERROR(365/J27,0) -> 67.61424 | ... L34: =IFERROR(365/L27,0) -> 69.673153 | N34: =IFERROR(AVERAGE(C34:L34),0) -> 62.424014 | O34: =IFERROR(MEDIAN(C34:L34),0) -> 62.023263
B35: Payable Days | C35: =IFERROR(365/C28,0) -> 73.318822 | D35: =IFERROR(365/D28,0) -> 63.689023 | E35: =IFERROR(365/E28,0) -> 76.858609 | F35: =IFERROR(365/F28,0) -> 78.894667 | G35: =IFERROR(365/G28,0) -> 77.521354 | H35: =IFERROR(365/H28,0) -> 89.293404 | I35: =IFERROR(365/I28,0) -> 97.122731 | J35: =IFERROR(365/J28,0) -> 88.55712 | ... L35: =IFERROR(365/L28,0) -> 103.34106 | N35: =IFERROR(AVERAGE(C35:L35),0) -> 83.798246 | O35: =IFERROR(MEDIAN(C35:L35),0) -> 83.725894
B36: Inventory Days | C36: =IFERROR(365/C29,0) -> 42.006416 | D36: =IFERROR(365/D29,0) -> 33.089904 | E36: =IFERROR(365/E29,0) -> 31.597178 | F36: =IFERROR(365/F29,0) -> 32.2573 | G36: =IFERROR(365/G29,0) -> 31.198062 | H36: =IFERROR(365/H29,0) -> 27.018436 | I36: =IFERROR(365/I29,0) -> 27.95909 | J36: =IFERROR(365/J29,0) -> 31.693976 | ... L36: =IFERROR(365/L29,0) -> 36.825803 | N36: =IFERROR(AVERAGE(C36:L36),0) -> 32.559528 | O36: =IFERROR(MEDIAN(C36:L36),0) -> 31.821546
B37: Cash Conversion Cycle | C37: =SUM(C34,C36)-C35 -> 32.462444 | D37: =SUM(D34,D36)-D35 -> 27.421202 | E37: =SUM(E34,E36)-E35 -> 14.346404 | F37: =SUM(F34,F36)-F35 -> 20.523185 | G37: =SUM(G34,G36)-G35 -> 11.570921 | H37: =SUM(H34,H36)-H35 -> -5.8265158 | I37: =SUM(I34,I36)-I35 -> -8.7760565 | J37: =SUM(J34,J36)-J35 -> 10.751096 | ... L37: =SUM(L34,L36)-L35 -> 3.1578941 | N37: =IFERROR(AVERAGE(C37:L37),0) -> 11.185296 | O37: =IFERROR(MEDIAN(C37:L37),0) -> 11.161009
B39: CFO/Sales | C39: =IFERROR('Historical FS'!C80/'Historical FS'!C7,0) -> 0.13852415 | D39: =IFERROR('Historical FS'!D80/'Historical FS'!D7,0) -> 0.14542486 | E39: =IFERROR('Historical FS'!E80/'Historical FS'!E7,0) -> 0.14182022 | F39: =IFERROR('Historical FS'!F80/'Historical FS'!F7,0) -> 0.12709013 | G39: =IFERROR('Historical FS'!G80/'Historical FS'!G7,0) -> 0.17382297 | H39: =IFERROR('Historical FS'!H80/'Historical FS'!H7,0) -> 0.11880736 | I39: =IFERROR('Historical FS'!I80/'Historical FS'!I7,0) -> 0.0983406 | J39: =IFERROR('Historical FS'!J80/'Historical FS'!J7,0) -> 0.13886742 | ... L39: =IFERROR('Historical FS'!L80/'Historical FS'!L7,0) -> 0.15593612 | N39: =IFERROR(AVERAGE(C39:L39),0) -> 0.14295154 | O39: =IFERROR(MEDIAN(C39:L39),0) -> 0.14034382
B40: CFO/Total Assets | C40: =IFERROR('Historical FS'!C80/'Historical FS'!C68,0) -> 0.1174893 | D40: =IFERROR('Historical FS'!D80/'Historical FS'!D68,0) -> 0.1515205 | E40: =IFERROR('Historical FS'!E80/'Historical FS'!E68,0) -> 0.15316537 | F40: =IFERROR('Historical FS'!F80/'Historical FS'!F68,0) -> 0.13909586 | G40: =IFERROR('Historical FS'!G80/'Historical FS'!G68,0) -> 0.19666825 | H40: =IFERROR('Historical FS'!H80/'Historical FS'!H68,0) -> 0.14938019 | I40: =IFERROR('Historical FS'!I80/'Historical FS'!I68,0) -> 0.121288 | J40: =IFERROR('Historical FS'!J80/'Historical FS'!J68,0) -> 0.166402 | ... L40: =IFERROR('Historical FS'!L80/'Historical FS'!L68,0) -> 0.18655372 | N40: =IFERROR(AVERAGE(C40:L40),0) -> 0.16122949 | O40: =IFERROR(MEDIAN(C40:L40),0) -> 0.15234293
B41: CFO/Total Debt | C41: =IFERROR('Historical FS'!C80/'Historical FS'!C53,0) -> 0 | D41: =IFERROR('Historical FS'!D80/'Historical FS'!D53,0) -> 0 | E41: =IFERROR('Historical FS'!E80/'Historical FS'!E53,0) -> 0 | F41: =IFERROR('Historical FS'!F80/'Historical FS'!F53,0) -> 2.7560976 | G41: =IFERROR('Historical FS'!G80/'Historical FS'!G53,0) -> 3.9707042 | H41: =IFERROR('Historical FS'!H80/'Historical FS'!H53,0) -> 3.185422 | I41: =IFERROR('Historical FS'!I80/'Historical FS'!I53,0) -> 1.8209423 | J41: =IFERROR('Historical FS'!J80/'Historical FS'!J53,0) -> 2.7077402 | ... L41: =IFERROR('Historical FS'!L80/'Historical FS'!L53,0) -> 3.1367698 | N41: =IFERROR(AVERAGE(C41:L41),0) -> 2.1722686 | O41: =IFERROR(MEDIAN(C41:L41),0) -> 2.7319189

Sheet Forecasting
B2: ='Data Sheet'!$B$1&" -"&'Data Sheet'!A17&" Forecasting" -> Infosys Ltd -Sales Forecasting | G2: ='Data Sheet'!$B$1&" -"&'Historical FS'!B19&" Forecasting" -> Infosys Ltd -EBITDA Forecasting | L2: ='Data Sheet'!$B$1&" -"&'Historical FS'!B37&" Forecasting" -> Infosys Ltd -Net Profit Forecasting
B3: Year Weight | C3: Year | D3: Sales | E3: Sales Growth | G3: Year Weight | H3: Year | I3: EBITDA | J3: EBITDA Growth | L3: Year Weight | M3: Year | N3: Net Profit | O3: Net Profit Growth
B5: 1 | C5: {=TRANSPOSE('Data Sheet'!B16:J16)} -> 43160 | D5: {=TRANSPOSE('Data Sheet'!B17:K17)} -> 70522 | E5: - | G5: 1 | H5: {=TRANSPOSE('Data Sheet'!B16:J16)} -> 43160 | I5: {=TRANSPOSE('Historical FS'!C19:L19)} -> 23977.48 | J5: - | L5: 1 | M5: {=TRANSPOSE('Data Sheet'!B16:J16)} -> 43160 | N5: {=TRANSPOSE('Historical FS'!C37:L37)} -> 1844.48 | O5: -
B6: =B5+1 -> 2 | C6: 43525 | D6: 82675 | E6: =D6/D5-1 -> 0.1723292 | G6: =G5+1 -> 2 | H6: 43525 | I6: 27282.75 | J6: =I6/I5-1 -> 0.13784893 | L6: =L5+1 -> 2 | M6: 43525 | N6: 4230.75 | O6: =N6/N5-1 -> 1.2937359
B7: =B6+1 -> 3 | C7: 43891 | D7: 90791 | E7: =D7/D6-1 -> 0.098167523 | G7: =G6+1 -> 3 | H7: 43891 | I7: 29053.12 | J7: =I7/I6-1 -> 0.06488972 | L7: =L6+1 -> 3 | M7: 43891 | N7: 3983.12 | O7: =N7/N6-1 -> -0.058530993
B8: =B7+1 -> 4 | C8: 44256 | D8: 100472 | E8: =D8/D7-1 -> 0.10662951 | G8: =G7+1 -> 4 | H8: 44256 | I8: 32151.04 | J8: =I8/I7-1 -> 0.10662951 | L8: =L7+1 -> 4 | M8: 44256 | N8: 2061.04 | O8: =N8/N7-1 -> -0.48255639
B9: =B8+1 -> 5 | C9: 44621 | D9: 121641 | E9: =D9/D8-1 -> 0.21069552 | G9: =G8+1 -> 5 | H9: 44621 | I9: 36492.3 | J9: =I9/I8-1 -> 0.13502705 | L9: =L8+1 -> 5 | M9: 44621 | N9: 2706.3 | O9: =N9/N8-1 -> 0.31307495
B10: =B9+1 -> 6 | C10: 44986 | D10: 146767 | E10: =D10/D9-1 -> 0.20655864 | G10: =G9+1 -> 6 | H10: 44986 | I10: 42562.43 | J10: =I10/I9-1 -> 0.16634002 | L10: =L9+1 -> 6 | M10: 44986 | N10: 4731.43 | O10: =N10/N9-1 -> 0.74830211
B11: =B10+1 -> 7 | C11: 45352 | D11: 153670 | E11: =D11/D10-1 -> 0.047033734 | G11: =G10+1 -> 7 | H11: 45352 | I11: 43027.6 | J11: =I11/I10-1 -> 0.010929122 | L11: =L10+1 -> 7 | M11: 45352 | N11: 1891.6 | O11: =N11/N10-1 -> -0.60020543
B12: =B11+1 -> 8 | C12: 45717 | D12: 162990 | E12: =D12/D11-1 -> 0.060649444 | G12: =G11+1 -> 8 | H12: 45717 | I12: 45637.2 | J12: =I12/I11-1 -> 0.060649444 | L12: =L11+1 -> 8 | M12: 45717 | N12: 2801.2 | O12: =N12/N11-1 -> 0.48086276
B13: =B12+1 -> 9 | C13: 46082 | D13: 178650 | E13: =D13/D12-1 -> 0.096079514 | G13: =G12+1 -> 9 | H13: 46082 | I13: 50022 | J13: =I13/I12-1 -> 0.096079514 | L13: =L12+1 -> 9 | M13: 46082 | N13: 4709 | O13: =N13/N12-1 -> 0.68106526
B14: =B13+1 -> 10 | C14: =C13+365 -> 46447 | D14: 184582 | E14: =D14/D13-1 -> 0.03320459 | G14: =G13+1 -> 10 | H14: =H13+365 -> 46447 | I14: 184582 | J14: =I14/I13-1 -> 2.6900164 | L14: =L13+1 -> 10 | M14: =M13+365 -> 46447 | N14: 137862 | O14: =N14/N13-1 -> 28.276279
B15: =B14+1 -> 11 | C15: =C14+365 -> 46812 | D15: =FORECAST(B15,$D$5:$D$14,$B$5:$B$14) -> 204078.67 | E15: =D15/D14-1 -> 0.10562605 | G15: =G14+1 -> 11 | H15: =H14+365 -> 46812 | I15: =FORECAST(G15,$I$5:$I$14,$G$5:$G$14) -> 109019.98 | J15: =I15/I14-1 -> -0.4093683 | L15: =L14+1 -> 11 | M15: =M14+365 -> 46812 | N15: =FORECAST(L15,$N$5:$N$14,$L$5:$L$14) -> 57452.513 | O15: =N15/N14-1 -> -0.5832607
B16: =B15+1 -> 12 | C16: =C15+365 -> 47177 | D16: =FORECAST(B16,$D$5:$D$14,$B$5:$B$14) -> 217679.15 | E16: =D16/D15-1 -> 0.066643344 | G16: =G15+1 -> 12 | H16: =H15+365 -> 47177 | I16: =FORECAST(G16,$I$5:$I$14,$G$5:$G$14) -> 119482.01 | J16: =I16/I15-1 -> 0.095964374 | L16: =L15+1 -> 12 | M16: =M15+365 -> 47177 | N16: =FORECAST(L16,$N$5:$N$14,$L$5:$L$14) -> 64865.317 | O16: =N16/N15-1 -> 0.12902488
B17: =B16+1 -> 13 | C17: =C16+365 -> 47542 | D17: =FORECAST(B17,$D$5:$D$14,$B$5:$B$14) -> 231279.64 | E17: =D17/D16-1 -> 0.062479501 | G17: =G16+1 -> 13 | H17: =H16+365 -> 47542 | I17: =FORECAST(G17,$I$5:$I$14,$G$5:$G$14) -> 129944.05 | J17: =I17/I16-1 -> 0.087561582 | L17: =L16+1 -> 13 | M17: =M16+365 -> 47542 | N17: =FORECAST(L17,$N$5:$N$14,$L$5:$L$14) -> 72278.121 | O17: =N17/N16-1 -> 0.11427993
B18: =B17+1 -> 14 | C18: =C17+365 -> 47907 | D18: =FORECAST(B18,$D$5:$D$14,$B$5:$B$14) -> 244880.12 | E18: =D18/D17-1 -> 0.058805371 | G18: =G17+1 -> 14 | H18: =H17+365 -> 47907 | I18: =FORECAST(G18,$I$5:$I$14,$G$5:$G$14) -> 140406.08 | J18: =I18/I17-1 -> 0.080511838 | L18: =L17+1 -> 14 | M18: =M17+365 -> 47907 | N18: =FORECAST(L18,$N$5:$N$14,$L$5:$L$14) -> 79690.925 | O18: =N18/N17-1 -> 0.10255944
B19: =B18+1 -> 15 | C19: =C18+365 -> 48272 | D19: =FORECAST(B19,$D$5:$D$14,$B$5:$B$14) -> 258480.61 | E19: =D19/D18-1 -> 0.055539359 | G19: =G18+1 -> 15 | H19: =H18+365 -> 48272 | I19: =FORECAST(G19,$I$5:$I$14,$G$5:$G$14) -> 150868.12 | J19: =I19/I18-1 -> 0.074512685 | L19: =L18+1 -> 15 | M19: =M18+365 -> 48272 | N19: =FORECAST(L19,$N$5:$N$14,$L$5:$L$14) -> 87103.729 | O19: =N19/N18-1 -> 0.093019423

Sheet Rm
B6: Return on Markets
B8: Date | C8: Annual
B9: ='Raw Data'!B6 -> 2025 | C9: ='Raw Data'!C6 -> 0.1051
B10: ='Raw Data'!B7 -> 2024 | C10: ='Raw Data'!C7 -> 0.0875
B11: ='Raw Data'!B8 -> 2023 | C11: ='Raw Data'!C8 -> 0.1942
B12: ='Raw Data'!B9 -> 2022 | C12: ='Raw Data'!C9 -> 0.0432 | E12: Average Market Returns | H12: =AVERAGE(C9:C32) -> 0.1769625
B13: ='Raw Data'!B10 -> 2021 | C13: ='Raw Data'!C10 -> 0.2412 | E13: Dividend Yield | H13: 0.0128
B14: ='Raw Data'!B11 -> 2020 | C14: ='Raw Data'!C11 -> 0.149 | E14: Total Market Returns | H14: =SUM(H12:H13) -> 0.1897625
B15: ='Raw Data'!B12 -> 2019 | C15: ='Raw Data'!C12 -> 0.1202
B16: ='Raw Data'!B13 -> 2018 | C16: ='Raw Data'!C13 -> 0.0315
B17: ='Raw Data'!B14 -> 2017 | C17: ='Raw Data'!C14 -> 0.2865
B18: ='Raw Data'!B15 -> 2016 | C18: ='Raw Data'!C15 -> 0.0301
B19: ='Raw Data'!B16 -> 2015 | C19: ='Raw Data'!C16 -> -0.0406
B20: ='Raw Data'!B17 -> 2014 | C20: ='Raw Data'!C17 -> 0.3139
B21: ='Raw Data'!B18 -> 2013 | C21: ='Raw Data'!C18 -> 0.0676
B22: ='Raw Data'!B19 -> 2012 | C22: ='Raw Data'!C19 -> 0.277
B23: ='Raw Data'!B20 -> 2011 | C23: ='Raw Data'!C20 -> -0.2462
B24: ='Raw Data'!B21 -> 2010 | C24: ='Raw Data'!C21 -> 0.1795
B25: ='Raw Data'!B22 -> 2009 | C25: ='Raw Data'!C22 -> 0.7576
B26: ='Raw Data'!B23 -> 2008 | C26: ='Raw Data'!C23 -> -0.5179
... B32: ='Raw Data'!B29 -> 2002 | C32: ='Raw Data'!C29 -> 0.0325

Sheet Beta-Regression
B6: Beta Regression
B7: ='Data Sheet'!B1&" Daily Returns" -> Infosys Ltd Daily Returns | F7: Nifty 50 Daily Returns | J7: Beta Drifting
B9: Date | C9: Closing Price | D9: Daily Returns | F9: Date | G9: Closing Price | H9: Daily Returns | J9: Levered Raw Beta | L9: =O11 -> 0.13125961
B10: ='Raw Data'!G6 -> 46283 | C10: 285.05 | D10: - | F10: ='Raw Data'!G6 -> 46283 | G10: ='Raw Data'!J6 -> 23346.4 | H10: - | J10: Raw Beta Weight | L10: 0.75
B11: ='Raw Data'!G7 -> 46282 | C11: 286.25 | D11: =C10/C11-1 -> -0.0041921397 | F11: ='Raw Data'!G7 -> 46282 | G11: ='Raw Data'!J7 -> 23270.6 | H11: =G10/G11-1 -> 0.003257329 | N11: Beta 1 | O11: =SLOPE(D10:D256, H10:H256) -> 0.13125961
B12: ='Raw Data'!G8 -> 46281 | C12: 284.65 | D12: =C11/C12-1 -> 0.005620938 | F12: ='Raw Data'!G8 -> 46281 | G12: ='Raw Data'!J8 -> 23217.6 | H12: =G11/G12-1 -> 0.002282751 | J12: Market Beta | L12: 1 | N12: Beta 2 | O12: =_xlfn.COVARIANCE.S(D10:D256, H10:H256)/_xlfn.VAR.S(H10:H256) -> 0.13125961
B13: ='Raw Data'!G9 -> 46280 | C13: 285.85 | D13: =C12/C13-1 -> -0.0041980059 | F13: ='Raw Data'!G9 -> 46280 | G13: ='Raw Data'!J9 -> 23118.6 | H13: =G12/G13-1 -> 0.0042822662 | J13: Market Beta Weight | L13: 0.25
B14: ='Raw Data'!G10 -> 46276 | C14: 283.45 | D14: =C13/C14-1 -> 0.0084671018 | F14: ='Raw Data'!G10 -> 46276 | G14: ='Raw Data'!J10 -> 23398.1 | H14: =G13/G14-1 -> -0.011945414
B15: ='Raw Data'!G11 -> 46275 | C15: 281.3 | D15: =C14/C15-1 -> 0.0076430857 | F15: ='Raw Data'!G11 -> 46275 | G15: ='Raw Data'!J11 -> 23477.8 | H15: =G14/G15-1 -> -0.0033946963 | J15: Adjusted Beta | L15: =(L9*L10)+(L12*L13) -> 0.34844471
B16: ='Raw Data'!G12 -> 46274 | C16: 280.8 | D16: =C15/C16-1 -> 0.0017806268 | F16: ='Raw Data'!G12 -> 46274 | G16: ='Raw Data'!J12 -> 23431.5 | H16: =G15/G16-1 -> 0.0019759725
B17: ='Raw Data'!G13 -> 46273 | C17: 281 | D17: =C16/C17-1 -> -0.00071174377 | F17: ='Raw Data'!G13 -> 46273 | G17: ='Raw Data'!J13 -> 23635.1 | H17: =G16/G17-1 -> -0.0086143067
B18: ='Raw Data'!G14 -> 46272 | C18: 282.7 | D18: =C17/C18-1 -> -0.0060134418 | F18: ='Raw Data'!G14 -> 46272 | G18: ='Raw Data'!J14 -> 23779.15 | H18: =G17/G18-1 -> -0.006057828
B19: ='Raw Data'!G15 -> 46269 | C19: 280.7 | D19: =C18/C19-1 -> 0.0071250445 | F19: ='Raw Data'!G15 -> 46269 | G19: ='Raw Data'!J15 -> 23897.7 | H19: =G18/G19-1 -> -0.0049607284
B20: ='Raw Data'!G16 -> 46268 | C20: 279.35 | D20: =C19/C20-1 -> 0.0048326472 | F20: ='Raw Data'!G16 -> 46268 | G20: ='Raw Data'!J16 -> 23873.45 | H20: =G19/G20-1 -> 0.0010157728
B21: ='Raw Data'!G17 -> 46267 | C21: 276.65 | D21: =C20/C21-1 -> 0.0097596241 | F21: ='Raw Data'!G17 -> 46267 | G21: ='Raw Data'!J17 -> 23914.45 | H21: =G20/G21-1 -> -0.0017144446
B22: ='Raw Data'!G18 -> 46266 | C22: 275.55 | D22: =C21/C22-1 -> 0.003992016 | F22: ='Raw Data'!G18 -> 46266 | G22: ='Raw Data'!J18 -> 24055.8 | H22: =G21/G22-1 -> -0.0058759218
B23: ='Raw Data'!G19 -> 46265 | C23: 279.65 | D23: =C22/C23-1 -> -0.014661184 | F23: ='Raw Data'!G19 -> 46265 | G23: ='Raw Data'!J19 -> 24080.4 | H23: =G22/G23-1 -> -0.0010215777
B24: ='Raw Data'!G20 -> 46262 | C24: 281.75 | D24: =C23/C24-1 -> -0.0074534161 | F24: ='Raw Data'!G20 -> 46262 | G24: ='Raw Data'!J20 -> 24175.65 | H24: =G23/G24-1 -> -0.0039399147
B25: ='Raw Data'!G21 -> 46261 | C25: 282.05 | D25: =C24/C25-1 -> -0.0010636412 | F25: ='Raw Data'!G21 -> 46261 | G25: ='Raw Data'!J21 -> 24090.85 | H25: =G24/G25-1 -> 0.0035200086
B26: ='Raw Data'!G22 -> 46260 | C26: 280.65 | D26: =C25/C26-1 -> 0.0049884197 | F26: ='Raw Data'!G22 -> 46260 | G26: ='Raw Data'!J22 -> 24207.75 | H26: =G25/G26-1 -> -0.004829032
B27: ='Raw Data'!G23 -> 46259 | C27: 288.75 | D27: =C26/C27-1 -> -0.028051948 | F27: ='Raw Data'!G23 -> 46259 | G27: ='Raw Data'!J23 -> 24334.55 | H27: =G26/G27-1 -> -0.0052106984
... B252: ='Raw Data'!G248 -> 45925 | C252: 414.15 | D252: =C251/C252-1 -> -0.0051913558 | F252: ='Raw Data'!G248 -> 45925 | G252: ='Raw Data'!J248 -> 24890.85 | H252: =G251/G252-1 -> -0.0094874221

Sheet WACC
B6: Weighted Average Cost of Capital
B8: All figures are in INR unless stated otherwise
B10: Peer Comps
E11: Total Debt | F11: Total Equity | H11: Debt /Equity | I11: Debt /Capital | J11: Levered Beta | K11: Unlevered Beta
B12: Name of the Comp | D12: Country | G12: Tax Rate
B14: ='Raw Data'!O24 -> TCS | D14: ='Raw Data'!Q24 -> India | E14: ='Raw Data'!R24 -> 190401.9 | F14: ='Raw Data'!S24 -> 761607.42 | G14: ='Raw Data'!T24 -> 0.3 | H14: =E14/F14 -> 0.25000006 | I14: =E14/SUM(E14:F14) -> 0.20000004 | J14: 1 | K14: =J14/(1+(1-G14)*H14) -> 0.8510638
B15: ='Raw Data'!O25 -> Infosys Ltd | D15: ='Raw Data'!Q25 -> India | E15: ='Raw Data'!R25 -> 9176 | F15: ='Raw Data'!S25 -> 426683 | G15: ='Raw Data'!T25 -> 0.3 | H15: =E15/F15 -> 0.021505427 | I15: =E15/SUM(E15:F15) -> 0.02105268 | J15: ='Beta-Regression'!L15 -> 0.34844471 | K15: =J15/(1+(1-G15)*H15) -> 0.34327708
B16: ='Raw Data'!O26 -> HCL Technologies | D16: ='Raw Data'!Q26 -> India | E16: ='Raw Data'!R26 -> 84754.5 | F16: ='Raw Data'!S26 -> 339018.18 | G16: ='Raw Data'!T26 -> 0.3 | H16: =E16/F16 -> 0.24999987 | I16: =E16/SUM(E16:F16) -> 0.19999992 | J16: 1 | K16: =J16/(1+(1-G16)*H16) -> 0.8510639
B17: ='Raw Data'!O27 -> Wipro | D17: ='Raw Data'!Q27 -> India | E17: ='Raw Data'!R27 -> 41311 | F17: ='Raw Data'!S27 -> 165244.04 | G17: ='Raw Data'!T27 -> 0.3 | H17: =E17/F17 -> 0.24999994 | I17: =E17/SUM(E17:F17) -> 0.19999996 | J17: 1 | K17: =J17/(1+(1-G17)*H17) -> 0.85106386
B18: ='Raw Data'!O28 -> Tech Mahindra | D18: ='Raw Data'!Q28 -> India | E18: ='Raw Data'!R28 -> 37664.1 | F18: ='Raw Data'!S28 -> 150656.36 | G18: ='Raw Data'!T28 -> 0.3 | H18: =E18/F18 -> 0.25000007 | I18: =E18/SUM(E18:F18) -> 0.20000004 | J18: 1 | K18: =J18/(1+(1-G18)*H18) -> 0.8510638
F20: Average | G20: =AVERAGE(G14:G18) -> 0.3 | H20: =AVERAGE(H14:H18) -> 0.20430107 | I20: =AVERAGE(I14:I18) -> 0.16421053 | J20: =AVERAGE(J14:J18) -> 0.86968894 | K20: =AVERAGE(K14:K18) -> 0.74950649
F21: Median | G21: =MEDIAN(G14:G18) -> 0.3 | H21: =MEDIAN(H14:H18) -> 0.24999994 | I21: =MEDIAN(I14:I18) -> 0.19999996 | J21: =MEDIAN(J14:J18) -> 1 | K21: =MEDIAN(K14:K18) -> 0.8510638
B24: Cost of Debt | G24: Cost of Capital
B26: Pre-Tax Cost of Debt | E26: 0.0805 | G26: Risk Free Rate | K26: 0.07
B27: Tax Rate | E27: =G15 -> 0.3 | G27: Equity Risk Premium | K27: 0.065
B28: Post-Tax Cost of Debt | E28: =E26*(1-E27) -> 0.05635 | G28: Levered Beta | K28: =K36 -> 0.96811187
G29: Cost of Capital | K29: =K26+K27*K28 -> 0.13292727
B31: Capital Structure | G31: Levered Beta
D33: Current | E33: Target | G33: Comps Median Unlevered Beta | K33: =K21 -> 0.8510638
B34: Total Debt | C34: =E15 -> 9176 | D34: =C34/C$36 -> 0.02105268 | E34: =I20 -> 0.16421053 | G34: Target Debt/Equity | K34: =E38 -> 0.19647355
B35: Market Capitalization | C35: =F15 -> 426683 | D35: =C35/C$36 -> 0.97894732 | E35: =E36-E34 -> 0.83578947 | G35: Tax Rate | K35: =E27 -> 0.3
B36: Total Capital | C36: =SUM(C34:C35) -> 435859 | D36: =C36/C$36 -> 1 | E36: =D36 -> 1 | G36: Levered Beta | K36: =K33*(1+(1-K35)*K34) -> 0.96811187
B38: Debt /Equity | D38: =D34/D35 -> 0.021505427 | E38: =E34/E35 -> 0.19647355 | G38: WACC
G40: Cost of Equity | K40: =K29 -> 0.13292727
G41: Equity Weight | K41: =E35 -> 0.83578947
G43: Cost of Debt | K43: =E28 -> 0.05635
G44: Debt Weight | K44: =E34 -> 0.16421053
G46: WACC | K46: =(K40*K41)+(K43*K44) -> 0.12035248

Sheet Intrinsic Valuation
B6: Calculation of ROIC | H6: ='Raw FS'!J$3 -> 44621 | I6: ='Raw FS'!K$3 -> 44986 | J6: ='Raw FS'!L$3 -> 45352 | K6: ='Raw FS'!M$3 -> 45717 | L6: ='Raw FS'!N$3 -> 46082
B8: Current Assets
B9: ='Raw FS'!B39 -> Inventories | H9: ='Raw FS'!J39 -> 10864 | I9: ='Raw FS'!K39 -> 11771 | J9: ='Raw FS'!L39 -> 14153 | K9: ='Raw FS'!M39 -> 15638 | L9: ='Raw FS'!N39 -> 18623
B10: Trade Receivables | H10: ='Raw FS'!J40 -> 22698 | I10: ='Raw FS'!K40 -> 25424 | J10: ='Raw FS'!L40 -> 30193 | K10: ='Raw FS'!M40 -> 31158 | L10: ='Raw FS'!N40 -> 35234
B11: ='Raw FS'!B42 -> Loans n Advances | H11: ='Raw FS'!J42 -> 2491 | I11: ='Raw FS'!K42 -> 3242 | J11: ='Raw FS'!L42 -> 10330 | K11: ='Raw FS'!M42 -> 6717 | L11: ='Raw FS'!N42 -> 6808
B12: ='Raw FS'!B43 -> Other asset items | H12: ='Raw FS'!J43 -> 27528 | I12: ='Raw FS'!K43 -> 34766 | J12: ='Raw FS'!L43 -> 28173 | K12: ='Raw FS'!M43 -> 30149 | L12: ='Raw FS'!N43 -> 33869
B13: Total Current Assets | H13: =SUM(H9:H12) -> 63581 | I13: =SUM(I9:I12) -> 75203 | J13: =SUM(J9:J12) -> 82849 | K13: =SUM(K9:K12) -> 83662 | L13: =SUM(L9:L12) -> 94534
B15: Current Liabilities
B16: ='Raw FS'!B14 -> Trade Payables | H16: ='Raw FS'!J14 -> 4134 | I16: ='Raw FS'!K14 -> 3865 | J16: ='Raw FS'!L14 -> 3956 | K16: ='Raw FS'!M14 -> 4164 | L16: ='Raw FS'!N14 -> 4744
B17: ='Raw FS'!B15 -> Advance from Customers | H17: ='Raw FS'!J15 -> 0 | I17: ='Raw FS'!K15 -> 0 | J17: ='Raw FS'!L15 -> 0 | K17: ='Raw FS'!M15 -> 0 | L17: ='Raw FS'!N15 -> 0
B18: ='Raw FS'!B16 -> Other liability items | H18: ='Raw FS'!J16 -> 31385 | I18: ='Raw FS'!K16 -> 36637 | J18: ='Raw FS'!L16 -> 35244 | K18: ='Raw FS'!M16 -> 39201 | L18: ='Raw FS'!N16 -> 47071
B19: Total Current Liabilities | H19: =SUM(H16:H18) -> 35519 | I19: =SUM(I16:I18) -> 40502 | J19: =SUM(J16:J18) -> 39200 | K19: =SUM(K16:K18) -> 43365 | L19: =SUM(L16:L18) -> 51815
A21: # | B21: Net Working Capital | H21: =H13-H19 -> 28062 | I21: =I13-I19 -> 34701 | J21: =J13-J19 -> 43649 | K21: =K13-K19 -> 40297 | L21: =L13-L19 -> 42719
B23: Non Current Assets
B24: ='Raw FS'!B22 -> Land | H24: ='Raw FS'!J22 -> 2066 | I24: ='Raw FS'!K22 -> 2054 | J24: ='Raw FS'!L22 -> 2037 | K24: ='Raw FS'!M22 -> 2079 | L24: ='Raw FS'!N22 -> 1990
B25: ='Raw FS'!B23 -> Building | H25: ='Raw FS'!J23 -> 16760 | I25: ='Raw FS'!K23 -> 16903 | J25: ='Raw FS'!L23 -> 16515 | K25: ='Raw FS'!M23 -> 16376 | L25: ='Raw FS'!N23 -> 17193
B26: ='Raw FS'!B24 -> Plant Machinery | H26: ='Raw FS'!J24 -> 3210 | I26: ='Raw FS'!K24 -> 3302 | J26: ='Raw FS'!L24 -> 3428 | K26: ='Raw FS'!M24 -> 3461 | L26: ='Raw FS'!N24 -> 3714
B27: ='Raw FS'!B25 -> Equipments | H27: ='Raw FS'!J25 -> 1427 | I27: ='Raw FS'!K25 -> 1482 | J27: ='Raw FS'!L25 -> 1528 | K27: ='Raw FS'!M25 -> 1628 | L27: ='Raw FS'!N25 -> 1732
B28: ='Raw FS'!B26 -> Furniture n fittings | H28: ='Raw FS'!J26 -> 2278 | I28: ='Raw FS'!K26 -> 2303 | J28: ='Raw FS'!L26 -> 2326 | K28: ='Raw FS'!M26 -> 2340 | L28: ='Raw FS'!N26 -> 2438
B29: ='Raw FS'!B27 -> Railway sidings | H29: ='Raw FS'!J27 -> 2 | I29: ='Raw FS'!K27 -> 2 | J29: ='Raw FS'!L27 -> 2 | K29: ='Raw FS'!M27 -> 2 | L29: ='Raw FS'!N27 -> 2
B30: ='Raw FS'!B28 -> Vehicles | H30: ='Raw FS'!J28 -> 71 | I30: ='Raw FS'!K28 -> 60 | J30: ='Raw FS'!L28 -> 62 | K30: ='Raw FS'!M28 -> 72 | L30: ='Raw FS'!N28 -> 70
B31: ='Raw FS'!B29 -> Intangible Assets | H31: ='Raw FS'!J29 -> 6495 | I31: ='Raw FS'!K29 -> 7594 | J31: ='Raw FS'!L29 -> 7652 | K31: ='Raw FS'!M29 -> 10626 | L31: ='Raw FS'!N29 -> 12729
B32: ='Raw FS'!B30 -> Other fixed assets | H32: ='Raw FS'!J30 -> 2766 | I32: ='Raw FS'!K30 -> 3281 | J32: ='Raw FS'!L30 -> 3294 | K32: ='Raw FS'!M30 -> 5184 | L32: ='Raw FS'!N30 -> 6296
B33: ='Raw FS'!B31 -> Gross Block | H33: ='Raw FS'!J31 -> 45009 | I33: ='Raw FS'!K31 -> 48877 | J33: ='Raw FS'!L31 -> 49195 | K33: ='Raw FS'!M31 -> 54691 | L33: ='Raw FS'!N31 -> 59762
B34: ='Raw FS'!B32 -> Accumulated Depreciation | H34: ='Raw FS'!J32 -> 19209 | I34: ='Raw FS'!K32 -> 19652 | J34: ='Raw FS'!L32 -> 21573 | K34: ='Raw FS'!M32 -> 23730 | L34: ='Raw FS'!N32 -> 25992
B35: Net Non Current Assets | H35: ='Raw FS'!J33 -> 25800 | I35: ='Raw FS'!K33 -> 29225 | J35: ='Raw FS'!L33 -> 27622 | K35: ='Raw FS'!M33 -> 30961 | L35: ='Raw FS'!N33 -> 33770
B37: Invested Capital | H37: =H35+H21 -> 53862 | I37: =I35+I21 -> 63926 | J37: =J35+J21 -> 71271 | K37: =K35+K21 -> 71258 | L37: =L35+L21 -> 76489
B38: EBIT | H38: ='Raw FS'!Z11+'Raw FS'!Z9 -> 30310 | I38: ='Raw FS'!AA11+'Raw FS'!AA9 -> 33606 | J38: ='Raw FS'!AB11+'Raw FS'!AB9 -> 36458 | K38: ='Raw FS'!AC11+'Raw FS'!AC9 -> 38024 | L38: ='Raw FS'!AD11+'Raw FS'!AD9 -> 40411
B40: ROIC | H40: =H38/H37 -> 0.5627344 | I40: =I38/I37 -> 0.52570159 | J40: =J38/J37 -> 0.51154046 | K40: =K38/K37 -> 0.53361026 | L40: =L38/L37 -> 0.52832433
B42: Calculation of Reinvestment Rate | H42: ='Raw FS'!J$3 -> 44621 | I42: ='Raw FS'!K$3 -> 44986 | J42: ='Raw FS'!L$3 -> 45352 | K42: ='Raw FS'!M$3 -> 45717 | L42: ='Raw FS'!N$3 -> 46082
B44: Net Capex | H44: =-SUM('Raw FS'!Z27:Z28) -> 2028 | I44: =-SUM('Raw FS'!AA27:AA28) -> 2530 | J44: =-SUM('Raw FS'!AB27:AB28) -> 2094 | K44: =-SUM('Raw FS'!AC27:AC28) -> 2062 | L44: =-SUM('Raw FS'!AD27:AD28) -> 2677
B45: Change in Work Cap | H45: - | I45: =I21-H21 -> 6639 | J45: =J21-I21 -> 8948 | K45: =K21-J21 -> -3352 | L45: =L21-K21 -> 2422
B47: EBIT | H47: =H38 -> 30310 | I47: =I38 -> 33606 | J47: =J38 -> 36458 | K47: =K38 -> 38024 | L47: =L38 -> 40411
B48: Tax Rate | H48: =WACC!E27 -> 0.3 | I48: =H48 -> 0.3 | J48: =I48 -> 0.3 | K48: =J48 -> 0.3 | L48: =K48 -> 0.3
B49: EBIT(1-T) | H49: =H47*(1-H48) -> 21217 | I49: =I47*(1-I48) -> 23524.2 | J49: =J47*(1-J48) -> 25520.6 | K49: =K47*(1-K48) -> 26616.8 | L49: =L47*(1-L48) -> 28287.7
B51: Reinvestment | H51: - | I51: =SUM(I44:I45) -> 9169 | J51: =SUM(J44:J45) -> 11042 | K51: =SUM(K44:K45) -> -1290 | L51: =SUM(L44:L45) -> 5099
B52: Reinvestment Rate | H52: - | I52: =I51/I49 -> 0.38976883 | J52: =J51/J49 -> 0.43267008 | K52: =K51/K49 -> -0.048465631 | L52: =L51/L49 -> 0.18025502
J54: 4 Year Average | L54: =AVERAGE(I52:L52) -> 0.23855708
J55: 4 Year Median | L55: =MEDIAN(I52:L52) -> 0.28501193
B57: Calculation of Growth Rate | H57: ='Raw FS'!J$3 -> 44621 | I57: ='Raw FS'!K$3 -> 44986 | J57: ='Raw FS'!L$3 -> 45352 | K57: ='Raw FS'!M$3 -> 45717 | L57: ='Raw FS'!N$3 -> 46082
B59: ROIC | H59: =H40 -> 0.5627344 | I59: =I40 -> 0.52570159 | J59: =J40 -> 0.51154046 | K59: =K40 -> 0.53361026 | L59: =L40 -> 0.52832433
B60: Reinvestment Rate | H60: - | I60: =I52 -> 0.38976883 | J60: =J52 -> 0.43267008 | K60: =K52 -> -0.048465631 | L60: =L52 -> 0.18025502
B62: Intrinsic Growth | I62: =I59*I60 -> 0.2049021 | J62: =J59*J60 -> 0.22132825 | K62: =K59*K60 -> -0.025861758 | L62: =L59*L60 -> 0.095233115
J64: 4 Year Average | L64: =AVERAGE(I62:L62) -> 0.12390043
J65: 4 Year Median | L65: =MEDIAN(I62:L62) -> 0.15006761

Sheet DCF
B6: Calculation of PV of FCFF | H6: ='Data Sheet'!K56 -> 46082 | I6: =H6+365 -> 46447 | J6: =I6+365 -> 46812 | K6: =J6+365 -> 47177 | L6: =K6+365 -> 47542 | M6: =L6+365 -> 47907
B8: EBIT | H8: ='Intrinsic Valuation'!L38 -> 40411 | I8: =H8*(1+$D$18) -> 42512.372 | J8: =I8*(1+$D$18) -> 44723.015 | K8: =J8*(1+$D$18) -> 47048.612 | L8: =K8*(1+$D$18) -> 49495.14 | M8: =L8*(1+$D$18) -> 52068.887
B9: Tax Rate | H9: =WACC!G14 -> 0.3 | I9: =H9 -> 0.3 | J9: =I9 -> 0.3 | K9: =J9 -> 0.3 | L9: =K9 -> 0.3 | M9: =L9 -> 0.3
B10: EBIT(1-T) | H10: =H8*(1-H9) -> 28287.7 | I10: =I8*(1-I9) -> 29758.66 | J10: =J8*(1-J9) -> 31306.111 | K10: =K8*(1-K9) -> 32934.028 | L10: =L8*(1-L9) -> 34646.598 | M10: =M8*(1-M9) -> 36448.221
B11: Less: Reinvestment Rate | H11: ='Intrinsic Valuation'!$L$55 -> 0.28501193 | I11: =MIN(0.85, MAX(0.15, 'Intrinsic Valuation'!$L$55)) -> 0.28501193 | J11: =$I$11+($M$11-$I$11)/4*1 -> 0.29684822 | K11: =$I$11+($M$11-$I$11)/4*2 -> 0.30868451 | L11: =$I$11+($M$11-$I$11)/4*3 -> 0.3205208 | M11: =D21 -> 0.3323571
B12: Free Cash Flow to Firm | H12: =H10*(1-H11) -> 20225.368 | I12: =I10*(1-MIN(0.85, I11)) -> 21277.087 | J12: =J10*(1-MIN(0.85, J11)) -> 22012.947 | K12: =K10*(1-MIN(0.85, K11)) -> 22767.804 | L12: =L10*(1-MIN(0.85, L11)) -> 23541.643 | M12: =M10*(1-MIN(0.85, M11)) -> 24334.396
B13: Mid Year Convention | H13: - | I13: 0.5 | J13: =I13+1 -> 1.5 | K13: =J13+1 -> 2.5 | L13: =K13+1 -> 3.5 | M13: =L13+1 -> 4.5
B14: Discounting Factor | I14: =1/(1+$D$20)^I13 -> 0.94476253 | J14: =1/(1+$D$20)^J13 -> 0.84327259 | K14: =1/(1+$D$20)^K13 -> 0.75268507 | L14: =1/(1+$D$20)^L13 -> 0.67182881 | M14: =1/(1+$D$20)^M13 -> 0.59965843
B16: PV of FCFF | I16: =I12*I14 -> 20101.795 | J16: =J12*J14 -> 18562.915 | K16: =K12*K14 -> 17136.986 | L16: =L12*L14 -> 15815.954 | M16: =M12*M14 -> 14592.326
B18: Expected Growth Rate | D18: 0.052
B19: Terminal Growth Rate | D19: 0.04
B20: WACC | D20: =WACC!K46 -> 0.12035248
B21: Terminal Reinvestment Rate | D21: =D19/D20 -> 0.3323571
B23: Calculation of Terminal Value
B25: FCFF(n+1) | D25: =M12*(1+D19) -> 25307.772
B26: WACC | D26: =D20 -> 0.12035248
B27: Terminal Growth Rate | D27: =D19 -> 0.04
B29: Terminal value | D29: =D25/(D26-D27) -> 314959.45
B31: Calculation of Equity Value
B33: PV of FCFF | D33: =SUM(I16:M16) -> 86209.976
B34: Terminal value | D34: =D29*M14 -> 188868.09
B35: Value of Operating Assets | D35: =SUM(D33:D34) -> 275078.06
B37: Add: Cash | D37: ='Data Sheet'!K69 -> 22201
B38: Less: Debt | D38: ='Data Sheet'!K59 -> 9176
B39: Equity Value | D39: =D35+D37-D38 -> 288103.06
B40: No. of Shares | D40: ='Data Sheet'!K70/10000000 -> 404.8
B42: Equity Value per Share | D42: =D39/D40 -> 711.71706
B44: Share Price | D44: 1051
B45: Discount /Premium | D45: =D44/D42 -> 1.4767104

Sheet Raw Data
B6: 2025 | C6: 0.1051 | G6: 46283 | H6: 1051.4 | J6: 23346.4
B7: 2024 | C7: 0.0875 | G7: 46282 | H7: 1058.6 | J7: 23270.6
B8: 2023 | C8: 0.1942 | G8: 46281 | H8: 1060 | J8: 23217.6
B9: 2022 | C9: 0.0432 | G9: 46280 | H9: 1077 | J9: 23118.6
B10: 2021 | C10: 0.2412 | G10: 46276 | H10: 1037.7 | J10: 23398.1
B11: 2020 | C11: 0.149 | G11: 46275 | H11: 1036.5 | J11: 23477.8 | N11: S.No. | O11: Name | P11: CMP Rs. | Q11: No. Eq. Shares Cr. | R11: Mar Cap Rs.Cr. | S11: Debt Rs.Cr. | T11: Cash End Rs.Cr. | U11: EV Rs.Cr. | V11: Sales Rs.Cr. | W11: EV / EBITDA | X11: NP 12M Rs.Cr.
B12: 2019 | C12: 0.1202 | G12: 46274 | H12: 1035 | J12: 23431.5 | N12: 1 | O12: Hind. Unilever | P12: 2087.2 | Q12: 234.96 | R12: 494084.03 | S12: 1478 | T12: 3248 | U12: 492314.03 | V12: 66052 | W12: 30.61 | X12: 14971
B13: 2018 | C13: 0.0315 | G13: 46273 | H13: 1082 | J13: 23635.1 | N13: 2 | O13: ITC | P13: 282.65 | Q13: 1252.95 | R13: 354889.69 | S13: 2399.06 | T13: 3008.79 | U13: 354279.96 | V13: 76487.98 | W13: 12.44 | X13: 20183.53
B14: 2017 | C14: 0.2865 | G14: 46272 | H14: 1087.5 | J14: 23779.15 | N14: 3 | O14: Hindustan Foods | P14: 585.6 | Q14: 12.12 | R14: 7105.77 | S14: 1088.26 | T14: 51.71 | U14: 8142.32 | V14: 4400.19 | W14: 20.53 | X14: 158.3
B15: 2016 | C15: 0.0301 | G15: 46269 | H15: 1130 | J15: 23897.7 | N15: 4 | O15: Godavari Bioref. | P15: 240.1 | Q15: 5.12 | R15: 1227 | S15: 530.76 | T15: 32.15 | U15: 1725.61 | V15: 2012.58 | W15: 12.74 | X15: 0.22
B16: 2015 | C16: -0.0406 | G16: 46268 | H16: 1130.3 | J16: 23873.45 | N16: 5 | O16: Davangere Sugar | P16: 3.08 | Q16: 143 | R16: 440.44 | S16: 250.05 | T16: 6.57 | U16: 683.92 | V16: 238.77 | W16: 13.43 | X16: 8.51
B17: 2014 | C17: 0.3139 | G17: 46267 | H17: 1140 | J17: 23914.45
B18: 2013 | C18: 0.0676 | G18: 46266 | H18: 1156 | J18: 24055.8
B19: 2012 | C19: 0.277 | G19: 46265 | H19: 1133.8 | J19: 24080.4
B20: 2011 | C20: -0.2462 | G20: 46262 | H20: 1144 | J20: 24175.65
B21: 2010 | C21: 0.1795 | G21: 46261 | H21: 1110.8 | J21: 24090.85
B22: 2009 | C22: 0.7576 | G22: 46260 | H22: 1120 | J22: 24207.75
B23: 2008 | C23: -0.5179 | G23: 46259 | H23: 1144 | J23: 24334.55
B24: 2007 | C24: 0.5477 | G24: 46258 | H24: 1130 | J24: 24219.05 | O24: TCS | Q24: India | R24: 190401.9 | S24: 761607.42 | T24: 0.3
B25: 2006 | C25: 0.3983 | G25: 46255 | H25: 1121 | J25: 24252 | O25: Infosys Ltd | Q25: =Q24 -> India | R25: 9176 | S25: 426683 | T25: =T24 -> 0.3
B26: 2005 | C26: 0.3634 | G26: 46254 | H26: 1130 | J26: 24231.85 | O26: HCL Technologies | Q26: =Q25 -> India | R26: 84754.5 | S26: 339018.18 | T26: =T25 -> 0.3
B27: 2004 | C27: 0.1068 | G27: 46253 | H27: 1119.8 | J27: 24078.3 | O27: Wipro | Q27: =Q26 -> India | R27: 41311 | S27: 165244.04 | T27: =T26 -> 0.3
B28: 2003 | C28: 0.719 | G28: 46252 | H28: 1115 | J28: 24154.9 | O28: Tech Mahindra | Q28: =Q27 -> India | R28: 37664.1 | S28: 150656.36 | T28: =T27 -> 0.3
B29: 2002 | C29: 0.0325 | G29: 46251 | H29: 1139.9 | J29: 24287.65
G30: 46248 | H30: 1169.2 | J30: 24366
G31: 46247 | H31: 1175 | J31: 24395.85
G32: 46246 | H32: 1176.1 | J32: 24435.95
G33: 46245 | H33: 1190.7 | J33: 24471.7
G34: 46244 | H34: 1183 | J34: 24583.8
G35: 46241 | H35: 1175.1 | J35: 24570.65
G36: 46240 | H36: 1165 | J36: 24636
G37: 46239 | H37: 1174 | J37: 24624.65
G38: 46238 | H38: 1167.5 | J38: 24614.9
G39: 46237 | H39: 1180 | J39: 24774.3
G40: 46234 | H40: 1130.1 | J40: 24383.6
G41: 46233 | H41: 1155.1 | J41: 24317.15
... G252: 45919 | H252: 1540.2 | J252: 25327.05

Sheet Comp_Valuation
B6: Amount in crores
B7: Company Comparable Valuation
D9: Market Data | K9: Financials | O9: Valuation
B10: Company | C10: Ticker | D10: Share Price | E10: Share Outstanding | F10: Equity Value | G10: Net Debt value | H10: Enterprise Value | K10: Revenue | L10: EBITDA | M10: Net Income | O10: EV/Revenue | P10: EV/EBITDA | Q10: P/E
B12: ='Raw FS'!L57 -> TCS | D12: ='Raw FS'!M57 -> 2105 | E12: ='Raw FS'!N57 -> 361.81 | F12: =D12*E12 -> 761610.05 | G12: ='Raw FS'!AS56 -> 152321.49 | H12: ='Raw FS'!AT56 -> 913928.91 | K12: ='Raw FS'!AU56 -> 289100 | L12: ='Raw FS'!AV56 -> 14499.903 | M12: ='Raw FS'!AW56 -> 53680 | O12: =$H12/K12 -> 3.1612899 | P12: =$H12/L12 -> 63.03 | Q12: =F12/M12 -> 14.187967
B13: ='Raw FS'!L58 -> Infosys | D13: ='Raw FS'!M58 -> 1051.4 | E13: ='Raw FS'!N58 -> 405.82 | F13: =D13*E13 -> 426679.15 | G13: ='Raw FS'!AS57 -> -13025 | H13: ='Raw FS'!AT57 -> 413657.56 | K13: ='Raw FS'!AU57 -> 192844 | L13: ='Raw FS'!AV57 -> 10354.382 | M13: ='Raw FS'!AW57 -> 31100 | O13: =$H13/K13 -> 2.1450372 | P13: =$H13/L13 -> 39.95 | Q13: =F13/M13 -> 13.719587
B14: ='Raw FS'!L59 -> HCL Technologies | D14: ='Raw FS'!M59 -> 1249.3 | E14: ='Raw FS'!N59 -> 271.37 | F14: =D14*E14 -> 339022.54 | G14: ='Raw FS'!AS58 -> 67803.63 | H14: ='Raw FS'!AT58 -> 406821.81 | K14: ='Raw FS'!AU58 -> 138316 | L14: ='Raw FS'!AV58 -> 13382.296 | M14: ='Raw FS'!AW58 -> 18504 | O14: =$H14/K14 -> 2.9412491 | P14: =$H14/L14 -> 30.4 | Q14: =F14/M14 -> 18.321581
B15: ='Raw FS'!L60 -> Wipro | D15: ='Raw FS'!M60 -> 166.83 | E15: ='Raw FS'!N60 -> 990.49 | F15: =D15*E15 -> 165243.45 | G15: ='Raw FS'!AS59 -> 33048.81 | H15: ='Raw FS'!AT59 -> 198292.85 | K15: ='Raw FS'!AU59 -> 97914.4 | L15: ='Raw FS'!AV59 -> 11115.07 | M15: ='Raw FS'!AW59 -> 13425.2 | O15: =$H15/K15 -> 2.0251653 | P15: =$H15/L15 -> 17.84 | Q15: =F15/M15 -> 12.308453
B16: ='Raw FS'!L61 -> Tech Mahindra | D16: ='Raw FS'!M61 -> 1537.1 | E16: ='Raw FS'!N61 -> 98.01 | F16: =D16*E16 -> 150651.17 | G16: ='Raw FS'!AS60 -> 30131.27 | H16: ='Raw FS'!AT60 -> 180787.63 | K16: ='Raw FS'!AU60 -> 62847.6 | L16: ='Raw FS'!AV60 -> 7819.5342 | M16: ='Raw FS'!AW60 -> 5945.2 | O16: =$H16/K16 -> 2.8766036 | P16: =$H16/L16 -> 23.12 | Q16: =F16/M16 -> 25.339967
B17: ='Raw FS'!L62 -> LTM | D17: ='Raw FS'!M62 -> 4275.1 | E17: ='Raw FS'!N62 -> 29.66 | F17: =D17*E17 -> 126799.47 | G17: ='Raw FS'!AS61 -> 25361.72 | H17: ='Raw FS'!AT61 -> 152170.3 | K17: ='Raw FS'!AU61 -> 46432 | L17: ='Raw FS'!AV61 -> 5140.8885 | M17: ='Raw FS'!AW61 -> 5874.4 | O17: =$H17/K17 -> 3.2772721 | P17: =$H17/L17 -> 29.6 | Q17: =F17/M17 -> 21.585092
B18: ='Raw FS'!L63 -> Oracle Fin.Serv. | D18: ='Raw FS'!M63 -> 11896 | E18: ='Raw FS'!N63 -> 8.71 | F18: =D18*E18 -> 103614.16 | G18: ='Raw FS'!AS62 -> 20718.82 | H18: ='Raw FS'!AT62 -> 124312.91 | K18: ='Raw FS'!AU62 -> 12500.8 | L18: ='Raw FS'!AV62 -> 2745.4265 | M18: ='Raw FS'!AW62 -> 5662 | O18: =$H18/K18 -> 9.9443964 | P18: =$H18/L18 -> 45.28 | Q18: =F18/M18 -> 18.299922
B19: ='Raw FS'!L64 -> Persistent Systems | D19: ='Raw FS'!M64 -> 5416 | E19: ='Raw FS'!N64 -> 15.77 | F19: =D19*E19 -> 85410.32 | G19: ='Raw FS'!AS63 -> 17087.48 | H19: ='Raw FS'!AT63 -> 102524.88 | K19: ='Raw FS'!AU63 -> 17212.92 | L19: ='Raw FS'!AV63 -> 2983.844 | M19: ='Raw FS'!AW63 -> 1932.16 | O19: =$H19/K19 -> 5.9562747 | P19: =$H19/L19 -> 34.36 | Q19: =F19/M19 -> 44.204579
B20: ='Raw FS'!L65 -> Coforge | D20: ='Raw FS'!M65 -> 1841 | E20: ='Raw FS'!N65 -> 44.3 | F20: =D20*E20 -> 81556.3 | G20: ='Raw FS'!AS64 -> 16310.46 | H20: ='Raw FS'!AT64 -> 97862.73 | K20: ='Raw FS'!AU64 -> 22110.8 | L20: ='Raw FS'!AV64 -> 4164.3715 | M20: ='Raw FS'!AW64 -> 2126.8 | O20: =$H20/K20 -> 4.4260149 | P20: =$H20/L20 -> 23.5 | Q20: =F20/M20 -> 38.346953
B21: ='Raw FS'!L66 -> Mphasis | D21: ='Raw FS'!M66 -> 2300.4 | E21: ='Raw FS'!N66 -> 19.09 | F21: =D21*E21 -> 43914.636 | G21: ='Raw FS'!AS65 -> 8785.2 | H21: ='Raw FS'!AT65 -> 52711.19 | K21: ='Raw FS'!AU65 -> 17536.2 | L21: ='Raw FS'!AV65 -> 2386.2014 | M21: ='Raw FS'!AW65 -> 1958.04 | O21: =$H21/K21 -> 3.0058502 | P21: =$H21/L21 -> 22.09 | Q21: =F21/M21 -> 22.427854
B23: High | O23: =MAX((O12,O14:O21)) -> 9.9443964 | P23: =MAX((P12,P14:P21)) -> 63.03 | Q23: =MAX((Q12,Q14:Q21)) -> 44.204579
B24: 25th Percentile | O24: =QUARTILE((O12,O14:O21),1) -> 2.9412491 | P24: =QUARTILE((P12,P14:P21),1) -> 23.12 | Q24: =QUARTILE((Q12,Q14:Q21),1) -> 18.299922
B25: Median | O25: =MEDIAN((O12,O14:O21)) -> 3.1612899 | P25: =MEDIAN((P12,P14:P21)) -> 29.6 | Q25: =MEDIAN((Q12,Q14:Q21)) -> 21.585092
B26: Average | O26: =AVERAGE((O12,O14:O21)) -> 4.1793462 | P26: =AVERAGE((P12,P14:P21)) -> 32.135556 | Q26: =AVERAGE((Q12,Q14:Q21)) -> 23.891374
B27: 75th Percentile | O27: =QUARTILE((O12,O14:O21),3) -> 4.4260149 | P27: =QUARTILE((P12,P14:P21),3) -> 34.36 | Q27: =QUARTILE((Q12,Q14:Q21),3) -> 25.339967
B28: Low | O28: =MIN((O12,O14:O21)) -> 2.0251653 | P28: =MIN((P12,P14:P21)) -> 17.84 | Q28: =MIN((Q12,Q14:Q21)) -> 12.308453
B30: Infosys Ltd Comparable Valuation | O30: EV/Revenue | P30: EV/EBITDA | Q30: P/E
B32: Implied Enterprise Value | O32: =K13*O26 -> 805961.85 | P32: =L13*P26 -> 332743.82 | Q32: =M13*Q26 -> 743021.74
B33: Net Debt Value | O33: =$G$13 -> -13025 | P33: =$G$13 -> -13025 | Q33: =$G$13 -> -13025
B34: Implied Market Value | O34: =O32-O33 -> 818986.85 | P34: =P32-P33 -> 345768.82 | Q34: =Q32 -> 743021.74
B35: Share Outstanding | O35: =$E$13 -> 405.82 | P35: =$E$13 -> 405.82 | Q35: =$E$13 -> 405.82
B37: Implied Value per Share | O37: =O34/O35 -> 2018.1037 | P37: =P34/P35 -> 852.02508 | Q37: =Q34/Q35 -> 1830.9146
B38: Source : Screener.in
O39: =IF(O37>$D$13,"Overvalued","Undervalued") -> Overvalued | P39: =IF(P37>$D$13,"Overvalued","Undervalued") -> Undervalued | Q39: =IF(Q37>$D$13,"Overvalued","Undervalued") -> Overvalued

Sheet Dupont Analysis
B2: ='Data Sheet'!B1 -> Infosys Ltd
B3: =CONCATENATE("(",VLOOKUP(B2,'List of Stocks'!B2:E5442,3,FALSE)," | ","BSE Code: ",VLOOKUP('Dupont Analysis'!B2,'List of Stocks'!B2:E5442,2,FALSE)) -> (INFY | BSE Code: 500209
B4: =CONCATENATE(" ","INR "&'Data Sheet'!B8) -> INR 1051
B5: 52 Week (High - INR - 1,728.00 & low INR - 982.00)
B6: About the Company
B8: Infosys Limited is an Indian multinational technology company that offers information technology, business consulting, and outsourcing services. Founded in 1981 by seven engineers, the company is headquartered in Bengaluru and considered one of the Big Six Indian IT companies.
B15: Financial Summary
B35: Recent Updates
A37: • | B37: India has a once-in-a-generation semiconductor demand window: Infosys SVP
A39: • | B39: Stocks in news: Infosys, Mazagon Dock, Fortis Healthcare, JSW Energy and Kalpataru Projects
A41: • | B41: Infosys, TCS, other IT stocks in focus after first Fed rate hike in 3 years. Will inflationary pressures o
A43: • | B43: Ex-Infosys CEO Vishal Sikka’s startup Hang Ten Systems raises $53 million
A45: • | B45: Market wrap: SBI, HDFC Life, TCS, Infosys top gainers and losers on Nifty and Sensex on Thursday
A47: • | B47: ITC Limited’s Q1 FY27 net profit plunged 27% year-on-year to approximately ₹3,579 crore, missing street estimates due to sharp cigarette excise duty hikes and geopolitical disruptions.
B54: Dupont Analysis - Return on Equity & Return on Assets
B58: Return on Equity
E59: ='Data Sheet'!G$56 -> 44621 | F59: ='Data Sheet'!H$56 -> 44986 | G59: ='Data Sheet'!I$56 -> 45352 | H59: ='Data Sheet'!J$56 -> 45717 | I59: ='Data Sheet'!K$56 -> 46082
B60: Net Profit | E60: =E66 -> 24108 | F60: =F66 -> 26248 | G60: =G66 -> 26750 | H60: =H66 -> 29474 | I60: =I66 -> 30325
B61: Average Shareholder's Equity | E61: =E75 -> 75850.5 | F61: =F75 -> 75378.5 | G61: =G75 -> 81761.5 | H61: =H75 -> 91967 | I61: =I75 -> 94335
B62: Return on Equity | E62: =E60/E61 -> 0.31783574 | F62: =F60/F61 -> 0.348216 | G62: =G60/G61 -> 0.3271711 | H62: =H60/H61 -> 0.32048452 | I62: =I60/I61 -> 0.32146075
B64: ROE - Dupont Analysis
E65: ='Data Sheet'!G$56 -> 44621 | F65: ='Data Sheet'!H$56 -> 44986 | G65: ='Data Sheet'!I$56 -> 45352 | H65: ='Data Sheet'!J$56 -> 45717 | I65: ='Data Sheet'!K$56 -> 46082
B66: Net Profit | E66: ='Data Sheet'!G30 -> 24108 | F66: ='Data Sheet'!H30 -> 26248 | G66: ='Data Sheet'!I30 -> 26750 | H66: ='Data Sheet'!J30 -> 29474 | I66: ='Data Sheet'!K30 -> 30325
B67: Revenue | E67: ='Data Sheet'!G17 -> 146767 | F67: ='Data Sheet'!H17 -> 153670 | G67: ='Data Sheet'!I17 -> 162990 | H67: ='Data Sheet'!J17 -> 178650 | I67: ='Data Sheet'!K17 -> 184582
B68: Net Profit Margin (A) | E68: =E66/E67 -> 0.16426036 | F68: =F66/F67 -> 0.17080757 | G68: =G66/G67 -> 0.1641205 | H68: =H66/H67 -> 0.16498181 | I68: =I66/I67 -> 0.16429013
B70: Revenue | E70: =E67 -> 146767 | F70: =F67 -> 153670 | G70: =G67 -> 162990 | H70: =H67 -> 178650 | I70: =I67 -> 184582
B71: Average Total Assets | E71: =SUM('Data Sheet'!F66:G66)/2 -> 112120 | F71: =SUM('Data Sheet'!G66:H66)/2 -> 120662.5 | G71: =SUM('Data Sheet'!H66:I66)/2 -> 130308 | H71: =SUM('Data Sheet'!I66:J66)/2 -> 141907.5 | I71: =SUM('Data Sheet'!J66:K66)/2 -> 151041.5
B72: Asset Turnover Ratio (B) | E72: =E70/E71 -> 1.3090171 | F72: =F70/F71 -> 1.2735523 | G72: =G70/G71 -> 1.2508058 | H72: =H70/H71 -> 1.2589187 | I72: =I70/I71 -> 1.2220615
B74: Average Total Assets | E74: =E71 -> 112120 | F74: =F71 -> 120662.5 | G74: =G71 -> 130308 | H74: =H71 -> 141907.5 | I74: =I71 -> 151041.5
B75: Average Shareholder's Equity | E75: =(SUM('Data Sheet'!F57:F58)+SUM('Data Sheet'!G57:G58))/2 -> 75850.5 | F75: =(SUM('Data Sheet'!G57:G58)+SUM('Data Sheet'!H57:H58))/2 -> 75378.5 | G75: =(SUM('Data Sheet'!H57:H58)+SUM('Data Sheet'!I57:I58))/2 -> 81761.5 | H75: =(SUM('Data Sheet'!I57:I58)+SUM('Data Sheet'!J57:J58))/2 -> 91967 | I75: =(SUM('Data Sheet'!J57:J58)+SUM('Data Sheet'!K57:K58))/2 -> 94335
B76: Equity Multiplier (C) | E76: =E74/E75 -> 1.4781709 | F76: =F74/F75 -> 1.6007549 | G76: =G74/G75 -> 1.5937575 | H76: =H74/H75 -> 1.5430263 | I76: =I74/I75 -> 1.6011184
B78: Return on Equity(A*B*C) | E78: =E68*E72*E76 -> 0.31783574 | F78: =F68*F72*F76 -> 0.348216 | G78: =G68*G72*G76 -> 0.3271711 | H78: =H68*H72*H76 -> 0.32048452 | I78: =I68*I72*I76 -> 0.32146075
B80: Return on Assets
E81: ='Data Sheet'!G$56 -> 44621 | F81: ='Data Sheet'!H$56 -> 44986 | G81: ='Data Sheet'!I$56 -> 45352 | H81: ='Data Sheet'!J$56 -> 45717 | I81: ='Data Sheet'!K$56 -> 46082
B82: Net Profit | E82: =E66 -> 24108 | F82: =F66 -> 26248 | G82: =G66 -> 26750 | H82: =H66 -> 29474 | I82: =I66 -> 30325
B83: Average Total Assets | E83: =E74 -> 112120 | F83: =F74 -> 120662.5 | G83: =G74 -> 130308 | H83: =H74 -> 141907.5 | I83: =I74 -> 151041.5
B84: Return on Assets | E84: =E82/E83 -> 0.21501962 | F84: =F82/F83 -> 0.21753237 | G84: =G82/G83 -> 0.20528287 | H84: =H82/H83 -> 0.20769868 | I84: =I82/I83 -> 0.20077264
B86: ROA - Dupont Equation
E87: ='Data Sheet'!G$56 -> 44621 | F87: ='Data Sheet'!H$56 -> 44986 | G87: ='Data Sheet'!I$56 -> 45352 | H87: ='Data Sheet'!J$56 -> 45717 | I87: ='Data Sheet'!K$56 -> 46082
B88: Net Profit | E88: =E66 -> 24108 | F88: =F66 -> 26248 | G88: =G66 -> 26750 | H88: =H66 -> 29474 | I88: =I66 -> 30325
B89: Revenue | E89: =E67 -> 146767 | F89: =F67 -> 153670 | G89: =G67 -> 162990 | H89: =H67 -> 178650 | I89: =I67 -> 184582
B90: Net Profit Margin (A) | E90: =E68 -> 0.16426036 | F90: =F68 -> 0.17080757 | G90: =G68 -> 0.1641205 | H90: =H68 -> 0.16498181 | I90: =I68 -> 0.16429013
B92: Revenue | E92: =E67 -> 146767 | F92: =F67 -> 153670 | G92: =G67 -> 162990 | H92: =H67 -> 178650 | I92: =I67 -> 184582
B93: Average Total Assets | E93: =E71 -> 112120 | F93: =F71 -> 120662.5 | G93: =G71 -> 130308 | H93: =H71 -> 141907.5 | I93: =I71 -> 151041.5
B94: Asset Turnover Ratio (B) | E94: =E72 -> 1.3090171 | F94: =F72 -> 1.2735523 | G94: =G72 -> 1.2508058 | H94: =H72 -> 1.2589187 | I94: =I72 -> 1.2220615
B96: Return on Assets (A*B) | E96: =E90*E94 -> 0.21501962 | F96: =F90*F94 -> 0.21753237 | G96: =G90*G94 -> 0.20528287 | H96: =H90*H94 -> 0.20769868 | I96: =I90*I94 -> 0.20077264

Sheet Altman's Z Score
B2: ='Data Sheet'!B1 -> Infosys Ltd
B3: =CONCATENATE("(",VLOOKUP(B2,'List of Stocks'!B2:E5442,3,FALSE)," | ","BSE Code: ",VLOOKUP('Altman''s Z Score'!B2,'List of Stocks'!B2:E5442,2,FALSE)) -> (INFY | BSE Code: 500209
B4: =CONCATENATE(" ","INR "&'Data Sheet'!B8) -> INR 1051
B5: 52 Week (High - INR - 1,728.00 & low INR - 982.00)
B6: About the Company
B8: Infosys Limited is an Indian multinational technology company that offers information technology, business consulting, and outsourcing services. Founded in 1981 by seven engineers, the company is headquartered in Bengaluru and considered one of the Big Six Indian IT companies.
B14: Financial Summary
B34: Recent Updates
A36: • | B36: India has a once-in-a-generation semiconductor demand window: Infosys SVP
A38: • | B38: Stocks in news: Infosys, Mazagon Dock, Fortis Healthcare, JSW Energy and Kalpataru Projects
A40: • | B40: Infosys, TCS, other IT stocks in focus after first Fed rate hike in 3 years. Will inflationary pressures o
A42: • | B42: Ex-Infosys CEO Vishal Sikka’s startup Hang Ten Systems raises $53 million
A44: • | B44: Market wrap: SBI, HDFC Life, TCS, Infosys top gainers and losers on Nifty and Sensex on Thursday
A46: • | B46: ITC Limited’s Q1 FY27 net profit plunged 27% year-on-year to approximately ₹3,579 crore, missing street estimates due to sharp cigarette excise duty hikes and geopolitical disruptions.
B53: Altman's Z Score Analysis Calculation
B57: Working Capital /Total assets (A)
E58: ='Data Sheet'!G$56 -> 44621 | F58: ='Data Sheet'!H$56 -> 44986 | G58: ='Data Sheet'!I$56 -> 45352 | H58: ='Data Sheet'!J$56 -> 45717 | I58: ='Data Sheet'!K$56 -> 46082
B59: Working Capital | E59: ='Data Sheet'!G65-'Data Sheet'!G60 -> 34284 | F59: ='Data Sheet'!H65-'Data Sheet'!H60 -> 34715 | G59: ='Data Sheet'!I65-'Data Sheet'!I60 -> 43937 | H59: ='Data Sheet'!J65-'Data Sheet'!J60 -> 48729 | I59: ='Data Sheet'!K65-'Data Sheet'!K60 -> 45852
B60: Total Assets | E60: ='Data Sheet'!G66 -> 116729 | F60: ='Data Sheet'!H66 -> 124596 | G60: ='Data Sheet'!I66 -> 136020 | H60: ='Data Sheet'!J66 -> 147795 | I60: ='Data Sheet'!K66 -> 154288
B61: Working Capital / Total assets (A) | E61: =E59/E60 -> 0.29370593 | F61: =F59/F60 -> 0.2786205 | G61: =G59/G60 -> 0.32301867 | H61: =H59/H60 -> 0.32970669 | I61: =I59/I60 -> 0.29718449
B63: Retained Earnings /Total Assets (B)
E64: ='Data Sheet'!G$56 -> 44621 | F64: ='Data Sheet'!H$56 -> 44986 | G64: ='Data Sheet'!I$56 -> 45352 | H64: ='Data Sheet'!J$56 -> 45717 | I64: ='Data Sheet'!K$56 -> 46082
B65: Retained Earnings | E65: ='Data Sheet'!G58 -> 73252 | F65: ='Data Sheet'!H58 -> 73338 | G65: ='Data Sheet'!I58 -> 86045 | H65: ='Data Sheet'!J58 -> 93745 | I65: ='Data Sheet'!K58 -> 90828
B66: Total Assets | E66: =E60 -> 116729 | F66: =F60 -> 124596 | G66: =G60 -> 136020 | H66: =H60 -> 147795 | I66: =I60 -> 154288
B67: Retained Earnings /Total Assets (B) | E67: =E65/E66 -> 0.627539 | F67: =F65/F66 -> 0.58860638 | G67: =G65/G66 -> 0.6325908 | H67: =H65/H66 -> 0.63429074 | I67: =I65/I66 -> 0.58869128
B69: EBIT /Total Assets (C)
E70: ='Data Sheet'!G$56 -> 44621 | F70: ='Data Sheet'!H$56 -> 44986 | G70: ='Data Sheet'!I$56 -> 45352 | H70: ='Data Sheet'!J$56 -> 45717 | I70: ='Data Sheet'!K$56 -> 46082
B71: EBIT | E71: ='Intrinsic Valuation'!H47 -> 30310 | F71: ='Intrinsic Valuation'!I47 -> 33606 | G71: ='Intrinsic Valuation'!J47 -> 36458 | H71: ='Intrinsic Valuation'!K47 -> 38024 | I71: ='Intrinsic Valuation'!L47 -> 40411
B72: Total Assets | E72: =E66 -> 116729 | F72: =F66 -> 124596 | G72: =G66 -> 136020 | H72: =H66 -> 147795 | I72: =I66 -> 154288
B73: EBIT /Total Assets (C) | E73: =E71/E72 -> 0.25966127 | F73: =F71/F72 -> 0.26971973 | G73: =G71/G72 -> 0.26803411 | H73: =H71/H72 -> 0.25727528 | I73: =I71/I72 -> 0.26191927
B75: Market Cap /Long Term Liabilities (D)
E76: ='Data Sheet'!G$56 -> 44621 | F76: ='Data Sheet'!H$56 -> 44986 | G76: ='Data Sheet'!I$56 -> 45352 | H76: ='Data Sheet'!J$56 -> 45717 | I76: ='Data Sheet'!K$56 -> 46082
B77: Market Capital | E77: ='Data Sheet'!G90*'Data Sheet'!G93 -> 791701.25 | F77: ='Data Sheet'!H90*'Data Sheet'!H93 -> 679605.21 | G77: ='Data Sheet'!I90*'Data Sheet'!I93 -> 760920.78 | H77: ='Data Sheet'!J90*'Data Sheet'!J93 -> 775346.26 | I77: ='Data Sheet'!K90*'Data Sheet'!K93 -> 597278.94
B78: Long Term Liabilities | E78: =SUM('Data Sheet'!G59:G60) -> 41379 | F78: =SUM('Data Sheet'!H59:H60) -> 49189 | G78: =SUM('Data Sheet'!I59:I60) -> 47904 | H78: =SUM('Data Sheet'!J59:J60) -> 51977 | I78: =SUM('Data Sheet'!K59:K60) -> 61436
B79: Market Cap /Long Term Liabilities (D) | E79: =E77/E78 -> 19.132924 | F79: =F77/F78 -> 13.816203 | G79: =G77/G78 -> 15.884285 | H79: =H77/H78 -> 14.917103 | I79: =I77/I78 -> 9.7219699
B81: Total Sales /Total Assets (E)
E82: ='Data Sheet'!G$56 -> 44621 | F82: ='Data Sheet'!H$56 -> 44986 | G82: ='Data Sheet'!I$56 -> 45352 | H82: ='Data Sheet'!J$56 -> 45717 | I82: ='Data Sheet'!K$56 -> 46082
B83: Total Sales | E83: ='Data Sheet'!G17 -> 146767 | F83: ='Data Sheet'!H17 -> 153670 | G83: ='Data Sheet'!I17 -> 162990 | H83: ='Data Sheet'!J17 -> 178650 | I83: ='Data Sheet'!K17 -> 184582
B84: Total Assets | E84: =E72 -> 116729 | F84: =F72 -> 124596 | G84: =G72 -> 136020 | H84: =H72 -> 147795 | I84: =I72 -> 154288
B85: Total Sales /Total Assets (E) | E85: =E83/E84 -> 1.2573311 | F85: =F83/F84 -> 1.2333462 | G85: =G83/G84 -> 1.1982797 | H85: =H83/H84 -> 1.2087689 | I85: =I83/I84 -> 1.1963471
B87: Altman's Z Score
E88: ='Data Sheet'!G$56 -> 44621 | F88: ='Data Sheet'!H$56 -> 44986 | G88: ='Data Sheet'!I$56 -> 45352 | H88: ='Data Sheet'!J$56 -> 45717 | I88: ='Data Sheet'!K$56 -> 46082
B89: Final Score | E89: =(1.2*E61)+(1.4*E67)+(3.3*E73)+(0.6*E79)+(E85*1) -> 14.824969 | F89: =(1.2*F61)+(1.4*F67)+(3.3*F73)+(0.6*F79)+(F85*1) -> 11.571537 | G89: =(1.2*G61)+(1.4*G67)+(3.3*G73)+(0.6*G79)+(G85*1) -> 12.886613 | H89: =(1.2*H61)+(1.4*H67)+(3.3*H73)+(0.6*H79)+(H85*1) -> 12.291694 | I89: =(1.2*I61)+(1.4*I67)+(3.3*I73)+(0.6*I79)+(I85*1) -> 9.0746518
B90: Financial Stability | E90: =IF(E89<1.81,"Distressed",IF(E89>3,"Strong","Grey Zone")) -> Strong | F90: =IF(F89<1.81,"Distressed",IF(F89>3,"Strong","Grey Zone")) -> Strong | G90: =IF(G89<1.81,"Distressed",IF(G89>3,"Strong","Grey Zone")) -> Strong | H90: =IF(H89<1.81,"Distressed",IF(H89>3,"Strong","Grey Zone")) -> Strong | I90: =IF(I89<1.81,"Distressed",IF(I89>3,"Strong","Grey Zone")) -> Strong

Sheet Raw FS
B3: Particulars | C3: 42064 | D3: 42430 | E3: 42795 | F3: 43160 | G3: 43525 | H3: 43891 | I3: 44256 | J3: 44621 | K3: 44986 | L3: 45352 | M3: 45717 | N3: 46082 | S3: 42064 | T3: 42430 | U3: 42795 | V3: 43160 | W3: 43525 | X3: 43891 | Y3: 44256 | Z3: 44621 | AA3: 44986 | AB3: 45352 | AC3: 45717 | AD3: 46082 | AE3: TTM
R4: Sales + | S4: 53319 | T4: 62441 | U4: 68484 | V4: 70522 | W4: 82675 | X4: 90791 | Y4: 100472 | Z4: 121641 | AA4: 146767 | AB4: 153670 | AC4: 162990 | AD4: 178650 | AE4: 184582
B5: Equity Capital | C5: 572 | D5: 1144 | E5: 1144 | F5: 1088 | G5: 2170 | H5: 2122 | I5: 2124 | J5: 2098 | K5: 2069 | L5: 2071 | M5: 2073 | N5: 2024 | R5: Expenses + | S5: 38436 | T5: 45362 | U5: 49880 | V5: 51700 | W5: 62505 | X5: 68524 | Y5: 72583 | Z5: 90150 | AA5: 111637 | AB5: 117245 | AC5: 123754 | AD5: 136370 | AE5: 140837
B6: Reserves | C6: 50164 | D6: 60600 | E6: 67838 | F6: 63835 | G6: 62778 | H6: 63328 | I6: 74227 | J6: 73252 | K6: 73338 | L6: 86045 | M6: 93745 | N6: 90828 | R6: Operating Profit | S6: 14883 | T6: 17079 | U6: 18604 | V6: 18822 | W6: 20170 | X6: 22267 | Y6: 27889 | Z6: 31491 | AA6: 35130 | AB6: 36425 | AC6: 39236 | AD6: 42280 | AE6: 43745
B7: Borrowings - | C7: 0 | D7: 0 | E7: 0 | F7: 0 | G7: 0 | H7: 4633 | I7: 5325 | J7: 5474 | K7: 8299 | L7: 8359 | M7: 8227 | N7: 9176 | R7: OPM % | S7: 28 | T7: 27 | U7: 27 | V7: 27 | W7: 24 | X7: 25 | Y7: 28 | Z7: 26 | AA7: 24 | AB7: 24 | AC7: 24 | AD7: 24 | AE7: 24
B8: Long term Borrowings | C8: 61 | D8: 27 | E8: 18 | F8: 12 | G8: 8 | H8: 6 | I8: 6 | J8: 5 | K8: 3 | L8: 2 | M8: 0 | N8: 60 | R8: Other Income + | S8: 3430 | T8: 3120 | U8: 3050 | V8: 3311 | W8: 2882 | X8: 2803 | Y8: 2201 | Z8: 2295 | AA8: 2701 | AB8: 4711 | AC8: 3600 | AD8: 3033 | AE8: 2975
B9: Short term Borrowings | C9: 195 | D9: 44 | E9: 19 | F9: 17 | G9: 2 | H9: 1 | I9: 4 | J9: 1 | K9: 35 | L9: 10 | M9: 91 | N9: 2126 | R9: Interest | S9: 12 | T9: 0 | U9: 0 | V9: 0 | W9: 0 | X9: 170 | Y9: 195 | Z9: 200 | AA9: 284 | AB9: 470 | AC9: 416 | AD9: 416 | AE9: 430
B10: Lease Liabilities | C10: 0 | D10: 0 | E10: 0 | F10: 0 | G10: 0 | H10: 4633 | I10: 5325 | J10: 5474 | K10: 8299 | L10: 8359 | M10: 8227 | N10: 9176 | R10: Depreciation | S10: 1017 | T10: 1459 | U10: 1703 | V10: 1863 | W10: 2011 | X10: 2893 | Y10: 3267 | Z10: 3476 | AA10: 4225 | AB10: 4678 | AC10: 4812 | AD10: 4902 | AE10: 5007
B11: Other Borrowings | C11: 13 | D11: 13 | E11: 8 | F11: 7 | G11: 3 | H11: 2 | I11: 0 | J11: 0 | K11: 0 | L11: 0 | M11: 0 | N11: 0 | R11: Profit before tax | S11: 17284 | T11: 18740 | U11: 19951 | V11: 20270 | W11: 21041 | X11: 22007 | Y11: 26628 | Z11: 30110 | AA11: 33322 | AB11: 35988 | AC11: 37608 | AD11: 39995 | AE11: 41283
B12: Other Liabilities - | C12: 15553 | D12: 13354 | E12: 14166 | F12: 14426 | G12: 19118 | H12: 21717 | I12: 25835 | J12: 35905 | K12: 40890 | L12: 39545 | M12: 43750 | N12: 52260 | R12: Tax % | S12: 28 | T12: 28 | U12: 28 | V12: 21 | W12: 27 | X12: 24 | Y12: 27 | Z12: 26 | AA12: 28 | AB12: 27 | AC12: 29 | AD12: 26 | AE12: 0
B13: Non controlling int | C13: 0 | D13: 0 | E13: 0 | F13: 1 | G13: 58 | H13: 394 | I13: 431 | J13: 386 | K13: 388 | L13: 345 | M13: 385 | N13: 445 | R13: Net Profit + | S13: 12372 | T13: 13489 | U13: 14353 | V13: 16029 | W13: 15410 | X13: 16639 | Y13: 19423 | Z13: 22146 | AA13: 24108 | AB13: 26248 | AC13: 26750 | AD13: 29474 | AE13: 30325
B14: Trade Payables | C14: 140 | D14: 386 | E14: 367 | F14: 694 | G14: 1655 | H14: 2852 | I14: 2645 | J14: 4134 | K14: 3865 | L14: 3956 | M14: 4164 | N14: 4744 | S14: 26.93 | T14: 29.36 | U14: 31.24 | V14: 36.69 | W14: 35.26 | X14: 38.96 | Y14: 45.42 | Z14: 52.56 | AA14: 58.08 | AB14: 63.2 | AC14: 64.32 | AD14: 72.59 | AE14: 74.25
B15: Advance from Customers | C15: 27 | D15: 28 | E15: 0 | F15: 0 | G15: 0 | H15: 0 | I15: 0 | J15: 0 | K15: 0 | L15: 0 | M15: 0 | N15: 0 | S15: 55 | T15: 41 | U15: 41 | V15: 59 | W15: 60 | X15: 45 | Y15: 59 | Z15: 59 | AA15: 58 | AB15: 73 | AC15: 67 | AD15: 66 | AE15: 0
B16: Other liability items | C16: 15386 | D16: 12940 | E16: 13799 | F16: 13731 | G16: 17405 | H16: 18471 | I16: 22759 | J16: 31385 | K16: 36637 | L16: 35244 | M16: 39201 | N16: 47071
B18: Total Liabilities | C18: 66289 | D18: 75098 | E18: 83148 | F18: 79349 | G18: 84066 | H18: 91800 | I18: 107511 | J18: 116729 | K18: 124596 | L18: 136020 | M18: 147795 | N18: 154288 | S18: 42064 | T18: 42430 | U18: 42795 | V18: 43160 | W18: 43525 | X18: 43891 | Y18: 44256 | Z18: 44621 | AA18: 44986 | AB18: 45352 | AC18: 45717 | AD18: 46082
R19: Cash from Operating Activity - | S19: 8353 | T19: 10028 | U19: 11531 | V19: 13218 | W19: 14841 | X19: 17003 | Y19: 23224 | Z19: 23885 | AA19: 22467 | AB19: 25210 | AC19: 35694 | AD19: 33986
R20: Profit from operations | S20: 15946 | T20: 17839 | U20: 19340 | V20: 19963 | W20: 22126 | X20: 23920 | Y20: 28845 | Z20: 32921 | AA20: 37605 | AB20: 39523 | AC20: 41591 | AD20: 45273
B21: Fixed Assets - | C21: 11346 | D21: 13386 | E21: 14179 | F21: 12574 | G21: 15710 | H21: 23789 | I21: 25505 | J21: 25800 | K21: 29225 | L21: 27622 | M21: 30961 | N21: 33770 | R21: Receivables | S21: -1475 | T21: -1654 | U21: -1743 | V21: -1523 | W21: -2881 | X21: -3861 | Y21: -1835 | Z21: -7937 | AA21: -7076 | AB21: -2667 | AC21: -1769 | AD21: -5177
B22: Land | C22: 1564 | D22: 1622 | E22: 1095 | F22: 1229 | G22: 1307 | H22: 1950 | I22: 2035 | J22: 2066 | K22: 2054 | L22: 2037 | M22: 2079 | N22: 1990 | R22: Inventory | S22: -505 | T22: -693 | U22: 593 | V22: 602 | W22: -359 | X22: -508 | Y22: -1460 | Z22: -466 | AA22: -1098 | AB22: -2545 | AC22: -2975 | AD22: -3306
B23: Building | C23: 6102 | D23: 6325 | E23: 8419 | F23: 9334 | G23: 10270 | H23: 15104 | I23: 16394 | J23: 16760 | K23: 16903 | L23: 16515 | M23: 16376 | N23: 17193 | R23: Payables | S23: 0 | T23: 242 | U23: -19 | V23: 328 | W23: 916 | X23: -373 | Y23: -245 | Z23: 1489 | AA23: -279 | AB23: 91 | AC23: 176 | AD23: -26
B24: Plant Machinery | C24: 1427 | D24: 1759 | E24: 2048 | F24: 2306 | G24: 2709 | H24: 3185 | I24: 3296 | J24: 3210 | K24: 3302 | L24: 3428 | M24: 3461 | N24: 3714 | R24: Working capital changes | S24: -842 | T24: -1946 | U24: -2156 | V24: 84 | W24: -453 | X24: -2367 | Y24: 768 | Z24: -1424 | AA24: -6344 | AB24: -5082 | AC24: -295 | AD24: -2639
B25: Equipments | C25: 676 | D25: 839 | E25: 922 | F25: 1002 | G25: 1101 | H25: 1265 | I25: 1371 | J25: 1427 | K25: 1482 | L25: 1528 | M25: 1628 | N25: 1732 | R25: Direct taxes | S25: -6751 | T25: -5865 | U25: -5653 | V25: -6829 | W25: -6832 | X25: -4550 | Y25: -6389 | Z25: -7612 | AA25: -8794 | AB25: -9231 | AC25: -5602 | AD25: -8648
B26: Furniture n fittings | C26: 958 | D26: 1444 | E26: 1277 | F26: 1393 | G26: 1620 | H26: 2073 | I26: 2149 | J26: 2278 | K26: 2303 | L26: 2326 | M26: 2340 | N26: 2438 | R26: Cash from Investing Activity - | S26: 999 | T26: -885 | U26: -14664 | V26: 4533 | W26: -632 | X26: -331 | Y26: -7373 | Z26: -6485 | AA26: -1071 | AB26: -5093 | AC26: -1864 | AD26: 3546
B27: Railway sidings | C27: 2 | D27: 2 | E27: 2 | F27: 2 | G27: 2 | H27: 2 | I27: 2 | J27: 2 | K27: 2 | L27: 2 | M27: 2 | N27: 2 | R27: Fixed assets purchased | S27: -2247 | T27: -2723 | U27: -2760 | V27: -1998 | W27: -2445 | X27: -3307 | Y27: -2107 | Z27: -2161 | AA27: -2579 | AB27: -2201 | AC27: -2237 | AD27: -2727
B28: Vehicles | C28: 34 | D28: 29 | E28: 31 | F28: 31 | G28: 38 | H28: 69 | I28: 73 | J28: 71 | K28: 60 | L28: 62 | M28: 72 | N28: 70 | R28: Fixed assets sold | S28: 9 | T28: 8 | U28: 50 | V28: 80 | W28: 28 | X28: 27 | Y28: 3 | Z28: 133 | AA28: 49 | AB28: 107 | AC28: 175 | AD28: 50
B29: Intangible Assets | C29: 3637 | D29: 3858 | E29: 3743 | F29: 2237 | G29: 3640 | H29: 5528 | I29: 6373 | J29: 6495 | K29: 7594 | L29: 7652 | M29: 10626 | N29: 12729 | R29: Investments purchased | S29: -23923 | T29: -24577 | U29: -66410 | V29: -69159 | W29: -79410 | X29: -37482 | Y29: -46738 | Z29: -59951 | AA29: -75800 | AB29: -78092 | AC29: -82742 | AD29: -82617
B30: Other fixed assets | C30: 71 | D30: 931 | E30: 899 | F30: 545 | G30: 1093 | H30: 2289 | I30: 2730 | J30: 2766 | K30: 3281 | L30: 3294 | M30: 5184 | N30: 6296 | R30: Investments sold | S30: 25253 | T30: 24980 | U30: 52048 | V30: 74003 | W30: 78098 | X30: 38861 | Y30: 40381 | Z30: 57356 | AA30: 76722 | AB30: 72930 | AC30: 84877 | AD30: 89699
B31: Gross Block | C31: 17816 | D31: 21293 | E31: 23379 | F31: 22980 | G31: 28065 | H31: 38886 | I31: 43153 | J31: 45009 | K31: 48877 | L31: 49195 | M31: 54691 | N31: 59762 | R31: Interest received | S31: 2551 | T31: 2383 | U31: 0 | V31: 0 | W31: 0 | X31: 0 | Y31: 0 | Z31: 0 | AA31: 0 | AB31: 0 | AC31: 0 | AD31: 0
B32: Accumulated Depreciation | C32: 6470 | D32: 7907 | E32: 9200 | F32: 10406 | G32: 12355 | H32: 15097 | I32: 17648 | J32: 19209 | K32: 19652 | L32: 21573 | M32: 23730 | N32: 25992 | R32: Dividends received | S32: 0 | T32: 0 | U32: 2753 | V32: 1768 | W32: 1557 | X32: 1929 | Y32: 1418 | Z32: 1898 | AA32: 1525 | AB32: 1768 | AC32: 2040 | AD32: 2713
B33: Net Block | C33: 11346 | D33: 13386 | E33: 14179 | F33: 12574 | G33: 15710 | H33: 23789 | I33: 25505 | J33: 25800 | K33: 29225 | L33: 27622 | M33: 30961 | N33: 33770 | R33: Invest in subsidiaries | S33: 0 | T33: -8 | U33: 0 | V33: 0 | W33: 0 | X33: 0 | Y33: 0 | Z33: 0 | AA33: 0 | AB33: 0 | AC33: 0 | AD33: 0
R34: Investment in group cos | S34: 741 | T34: -59 | U34: -131 | V34: 49 | W34: 1592 | X34: -224 | Y34: -327 | Z34: -3627 | AA34: -939 | AB34: 502 | AC34: -3802 | AD34: -3522
B35: CWIP | C35: 776 | D35: 960 | E35: 1365 | F35: 1606 | G35: 1388 | H35: 954 | I35: 922 | J35: 416 | K35: 288 | L35: 293 | M35: 814 | N35: 526 | R35: Redemp n Canc of Shares | S35: 0 | T35: 0 | U35: 129 | V35: 18 | W35: 18 | X35: 0 | Y35: 0 | Z35: 0 | AA35: 56 | AB35: 0 | AC35: 0 | AD35: 0
B36: Investments | C36: 2270 | D36: 1892 | E36: 16423 | F36: 12163 | G36: 11261 | H36: 8792 | I36: 14205 | J36: 20324 | K36: 19478 | L36: 24623 | M36: 23541 | N36: 21880 | R36: Other investing items | S36: -4935 | T36: -6813 | U36: -6939 | V36: -20505 | W36: -14512 | X36: -17591 | Y36: -9786 | Z36: -24642 | AA36: -26695 | AB36: -17504 | AC36: -24161 | AD36: -39786
R37: Cash from Financing Activity - | S37: 0 | T37: 0 | U37: 0 | V37: 5 | W37: 6 | X37: 6 | Y37: 15 | Z37: 21 | AA37: 35 | AB37: 5 | AC37: 6 | AD37: 2
B38: Other Assets - | C38: 51897 | D38: 58860 | E38: 51181 | F38: 53006 | G38: 55707 | H38: 58265 | I38: 66879 | J38: 70189 | K38: 75605 | L38: 83482 | M38: 92479 | N38: 98112 | R38: Proceeds from shares | S38: 979 | T38: 532 | U38: 1067 | V38: 913 | W38: 969 | X38: 625 | Y38: 291 | Z38: 292 | AA38: 2477 | AB38: 1443 | AC38: 797 | AD38: 405
B39: Inventories | C39: 8587 | D39: 9062 | E39: 8116 | F39: 7495 | G39: 7860 | H39: 8879 | I39: 10397 | J39: 10864 | K39: 11771 | L39: 14153 | M39: 15638 | N39: 18623 | R39: Proceeds from borrowings | S39: 0 | T39: 0 | U39: 0 | V39: 0 | W39: 0 | X39: 0 | Y39: 0 | Z39: 0 | AA39: 0 | AB39: 0 | AC39: -985 | AD39: 0
B40: Trade receivables + | C40: 9713 | D40: 11330 | E40: 12322 | F40: 13142 | G40: 14827 | H40: 18487 | I40: 19294 | J40: 22698 | K40: 25424 | L40: 30193 | M40: 31158 | N40: 35234 | R40: Repayment of borrowings | S40: -20 | T40: -13 | U40: -13 | V40: -8 | W40: -18 | X40: -3 | Y40: -2 | Z40: -1 | AA40: -1 | AB40: -2 | AC40: -54 | AD40: -105
B41: Cash Equivalents | C41: 30367 | D41: 32697 | E41: 22625 | F41: 19818 | G41: 19568 | H41: 18649 | I41: 24714 | J41: 17472 | K41: 12173 | L41: 14786 | M41: 24455 | N41: 22201 | R41: Interest paid fin | S41: -4935 | T41: -6813 | U41: -6939 | V41: -7464 | W41: -13705 | X41: -9548 | Y41: -9137 | Z41: -12731 | AA41: -13653 | AB41: -14731 | AC41: -20289 | AD41: -18656
B42: Loans n Advances | C42: 399 | D42: 614 | E42: 844 | F42: 830 | G42: 1524 | H42: 1359 | I42: 1460 | J42: 2491 | K42: 3242 | L42: 10330 | M42: 6717 | N42: 6808 | R42: Dividends paid | S42: -4876 | T42: -5133 | U42: -6994 | V42: -5952 | W42: -6519 | X42: -7302 | Y42: -18881 | Z42: -13788 | AA42: -15418 | AB42: -19899 | AC42: -17782 | AD42: -18271
B43: Other asset items | C43: 11418 | D43: 14219 | E43: 15390 | F43: 19216 | G43: 19788 | H43: 19770 | I43: 21411 | J43: 27528 | K43: 34766 | L43: 28173 | M43: 30149 | N43: 33869 | R43: Financial liabilities | S43: 0 | T43: 0 | U43: 0 | V43: 0 | W43: 0 | X43: -49 | Y43: -55 | Z43: -59 | AA43: -59 | AB43: -67 | AC43: -66 | AD43: -68
B44: Total Assets | C44: 66289 | D44: 75098 | E44: 83148 | F44: 79349 | G44: 84066 | H44: 91800 | I44: 107511 | J44: 116729 | K44: 124596 | L44: 136020 | M44: 147795 | N44: 154288 | R44: Other financing items | S44: -734 | T44: -971 | U44: -1335 | V44: -1136 | W44: -1203 | X44: -1409 | Y44: 55 | Z44: 15 | AA44: 35 | AB44: 12 | AC44: 28 | AD44: -146
R45: Net Cash Flow | S45: 4417 | T45: 2330 | U45: -10072 | V45: -2754 | W45: -303 | X45: -919 | Y45: 6065 | Z45: -7242 | AA45: -5299 | AB45: 2613 | AC45: 9669 | AD45: -2254 | AT45: Interest paid fin | AU45: -18 | AV45: -2 | AW45: -14 | AX45: -6 | AY45: -7 | AZ45: -90 | BA45: -92 | BB45: -82 | BC45: -88 | BD45: -110 | BE45: -130 | BF45: -133
AT46: Dividends paid | AU46: -2912 | AV46: -3354 | AW46: -3572 | AX46: -3911 | AY46: -4554 | AZ46: -5196 | BA46: -8811 | BB46: -7526 | BC46: -8474 | BD46: -9416 | BE46: -12473 | BF46: -10124
AT47: Financial liabilities | AU47: 0 | AV47: 0 | AW47: 0 | AX47: 0 | AY47: 0 | AZ47: -373 | BA47: -406 | BB47: -407 | BC47: -467 | BD47: -423 | BE47: -498 | BF47: -507
AT48: Other financing items | AU48: -533 | AV48: -685 | AW48: -728 | AX48: -781 | AY48: -928 | AZ48: -1061 | BA48: 0 | BB48: 0 | BC48: -2 | BD48: 0 | BE48: 0 | BF48: 0
AT49: Net Cash Flow | AU49: -33 | AV49: 25 | AW49: -202 | AX49: 21 | AY49: -28 | AZ49: 2595 | BA49: -1374 | BB49: -695 | BC49: -446 | BD49: 111 | BE49: 5258 | BF49: -3487
AR55: Mar Cap Rs.Cr. | AS55: Net Debt | AT55: EV Rs.Cr. | AU55: Sales Rs.Cr. | AV55: EBITDA | AW55: NP 12M Rs.Cr. | AX55: EV / EBITDA | AZ55: Debt Rs.Cr. | BA55: Cash End Rs.Cr.
K56: S.No. | L56: Infosys Ltd | M56: 1051 | N56: 404.8 | AR56: 761607.42 | AS56: =AZ56-BA56 -> 152321.49 | AT56: =AR56+AS56 -> 913928.91 | AU56: 289100 | AV56: =AT56/AX56 -> 14499.903 | AW56: 53680 | AX56: 63.03 | AZ56: 190401.86 | BA56: 38080.37
K57: 1 | L57: TCS | M57: 2105 | N57: 361.81 | AR57: 426682.56 | AS57: =AZ57-BA57 -> -13025 | AT57: =AR57+AS57 -> 413657.56 | AU57: 192844 | AV57: =AT57/AX57 -> 10354.382 | AW57: 31100 | AX57: 39.95 | AZ57: 9176 | BA57: 22201
K58: 2 | L58: Infosys | M58: 1051.4 | N58: 405.82 | AR58: 339018.18 | AS58: =AZ58-BA58 -> 67803.63 | AT58: =AR58+AS58 -> 406821.81 | AU58: 138316 | AV58: =AT58/AX58 -> 13382.296 | AW58: 18504 | AX58: 30.4 | AZ58: 84754.54 | BA58: 16950.91
K59: 3 | L59: HCL Technologies | M59: 1249.3 | N59: 271.37 | AR59: 165244.04 | AS59: =AZ59-BA59 -> 33048.81 | AT59: =AR59+AS59 -> 198292.85 | AU59: 97914.4 | AV59: =AT59/AX59 -> 11115.07 | AW59: 13425.2 | AX59: 17.84 | AZ59: 41311.01 | BA59: 8262.2
K60: 4 | L60: Wipro | M60: 166.83 | N60: 990.49 | AR60: 150656.36 | AS60: =AZ60-BA60 -> 30131.27 | AT60: =AR60+AS60 -> 180787.63 | AU60: 62847.6 | AV60: =AT60/AX60 -> 7819.5342 | AW60: 5945.2 | AX60: 23.12 | AZ60: 37664.09 | BA60: 7532.82
K61: 5 | L61: Tech Mahindra | M61: 1537.1 | N61: 98.01 | AR61: 126808.58 | AS61: =AZ61-BA61 -> 25361.72 | AT61: =AR61+AS61 -> 152170.3 | AU61: 46432 | AV61: =AT61/AX61 -> 5140.8885 | AW61: 5874.4 | AX61: 29.6 | AZ61: 31702.15 | BA61: 6340.43
K62: 6 | L62: LTM | M62: 4275.1 | N62: 29.66 | AR62: 103594.09 | AS62: =AZ62-BA62 -> 20718.82 | AT62: =AR62+AS62 -> 124312.91 | AU62: 12500.8 | AV62: =AT62/AX62 -> 2745.4265 | AW62: 5662 | AX62: 45.28 | AZ62: 25898.52 | BA62: 5179.7
K63: 7 | L63: Oracle Fin.Serv. | M63: 11896 | N63: 8.71 | AR63: 85437.4 | AS63: =AZ63-BA63 -> 17087.48 | AT63: =AR63+AS63 -> 102524.88 | AU63: 17212.92 | AV63: =AT63/AX63 -> 2983.844 | AW63: 1932.16 | AX63: 34.36 | AZ63: 21359.35 | BA63: 4271.87
K64: 8 | L64: Persistent Systems | M64: 5416 | N64: 15.77 | AR64: 81552.27 | AS64: =AZ64-BA64 -> 16310.46 | AT64: =AR64+AS64 -> 97862.73 | AU64: 22110.8 | AV64: =AT64/AX64 -> 4164.3715 | AW64: 2126.8 | AX64: 23.5 | AZ64: 20388.07 | BA64: 4077.61
K65: 9 | L65: Coforge | M65: 1841 | N65: 44.3 | AR65: 43925.99 | AS65: =AZ65-BA65 -> 8785.2 | AT65: =AR65+AS65 -> 52711.19 | AU65: 17536.2 | AV65: =AT65/AX65 -> 2386.2014 | AW65: 1958.04 | AX65: 22.09 | AZ65: 10981.5 | BA65: 2196.3
K66: 10 | L66: Mphasis | M66: 2300.4 | N66: 19.09

Sheet List of Stocks
B2: COMPANY_NAME | C2: BSE | D2: NSE | E2: Industry
B3: 20 MICRONS LTD | C3: 533022 | D3: 20MICRONS | E3: Mining
B4: 21ST CENTURY MANAGEMENT SERVICES LTD | C4: 526921 | D4: 21STCENMGM | E4: Other Financial Services
B5: 3I INFOTECH LTD | C5: 532628 | D5: 3IINFOTECH | E5: IT Consulting & Software
B6: 3M (INDIA) LTD | C6: 523395 | D6: 3M(INDIA) | E6: Diversified
B7: 3M INDIA LTD | C7: 523395 | D7: 3MINDIA | E7: Diversified
B8: 3P LAND HOLDINGS LTD | C8: 516092 | D8: 3PLAND | E8: Paper & Paper Products
B9: 5PAISA CAPITAL LTD | C9: 540776 | D9: 5PAISA | E9: Other Financial Services
B10: 63 MOONS TECHNOLOGIES LTD | C10: 526881 | D10: 63MOONS | E10: IT Consulting & Software
B11: 7NR RETAIL LTD | C11: 540615 | D11: Not Listed | E11: Specialty Retail
B12: 7SEAS ENTERTAINMENT LTD | C12: 540874 | D12: Not Listed | E12: Movies & Entertainment
B13: 8K MILES SOFTWARE SERVICES LTD | C13: 512161 | D13: 8KMILES | E13: Internet Software & Services
B14: A & M FEBCON LTD | C14: 540697 | D14: Not Listed | E14: Industrial Machinery
B15: A AND M JUMBO BAGS LTD | C15: Not Listed | D15: AMJUMBO | E15: SME
B16: A INFRASTRUCTURE LTD | C16: 539620 | D16: Not Listed | E16: Cement & Cement Products
B17: A K SPINTEX LTD | C17: 539300 | D17: Not Listed | E17: Textiles
B18: A K CAPITAL SERVICES LTD | C18: 530499 | D18: Not Listed | E18: Finance (including NBFCs)
B19: A.F. Enterprises Ltd | C19: 538351 | D19: AFEL | E19: Investment Companies
B20: A-1 ACID LTD | C20: 542012 | D20: Not Listed | E20: Comm.Trading & Distribution
B21: A2Z INFRA ENGINEERING LTD | C21: 533292 | D21: A2ZINFRA | E21: Utilities:Non-Elec.
B22: AADHAAR VENTURES (INDIA) LTD | C22: 531611 | D22: Not Listed | E22: Finance (including NBFCs)
B23: AADHAAR VENTURES INDIA LTD | C23: 531611 | D23: Not Listed | E23: Finance (including NBFCs)
B24: AAKASH EXPLORATION SERVICES LTD | C24: Not Listed | D24: AAKASH | E24: SME
B25: AANANDA LAKSHMI SPINNING MILLS LTD | C25: 539096 | D25: Not Listed | E25: Textiles
B26: AANCHAL ISPAT LTD | C26: 538812 | D26: Not Listed | E26: Iron & Steel/Interm.Products
B27: AAR COMMERCIAL COMPANY LTD | C27: 539632 | D27: Not Listed | E27: Distributors
B28: Aar Shyam India Investment Company Ltd | C28: 542377 | D28: AARSHYAM | E28: Finance (including NBFCs)
B29: AAREY DRUGS & PHARMACEUTICALS LTD | C29: 524412 | D29: Not Listed | E29: Pharmaceuticals
B30: AARON INDUSTRIES LTD | C30: Not Listed | D30: AARON | E30: SME
B31: Aartech Solonics Ltd | C31: 542580 | D31: AARTECH | E31: Heavy Electrical Equipment
B32: AARTI DRUGS LTD | C32: 524348 | D32: AARTIDRUGS | E32: Pharmaceuticals
B33: AARTI INDUSTRIES LTD | C33: 524208 | D33: AARTIIND | E33: Commodity Chemicals
B34: AARV INFRATEL LTD | C34: 526488 | D34: Not Listed | E34: Textiles
B35: AARVEE DENIMS & EXPORTS LTD | C35: 514274 | D35: AARVEEDEN | E35: Textiles
B36: AARVI ENCON LTD | C36: Not Listed | D36: AARVI | E36: SME
B37: AASHEE INFOTECH LTD | C37: 519319 | D37: Not Listed | E37: Internet Software & Services
B38: AASWA TRADING & EXPORTS LTD | C38: 512038 | D38: Not Listed | E38: Comm.Trading & Distribution
B39: AAVAS FINANCIERS LTD | C39: 541988 | D39: AAVAS | E39: Housing Finance
B40: AAYUSH FOOD AND HERBS LTD | C40: 539528 | D40: Not Listed | E40: Packaged Foods
B41: ABAN OFFSHORE LTD | C41: 523204 | D41: ABAN | E41: Exploration & Production
B42: ABANS ENTERPRISES LTD | C42: 512165 | D42: Not Listed | E42: Comm.Trading & Distribution
B43: ABB INDIA LTD | C43: 500002 | D43: ABB | E43: Heavy Electrical Equipment
B44: ABBOTT (INDIA) LTD | C44: 500488 | D44: ABBOT(INDIA) | E44: Pharmaceuticals
B45: ABBOTT INDIA LTD | C45: 500488 | D45: ABBOTINDIA | E45: Pharmaceuticals
B46: ABC (INDIA) LTD | C46: 520123 | D46: Not Listed | E46: Surface Transportation
B47: ABC GAS INTERNATIONAL LTD | C47: 513119 | D47: Not Listed | E47: Copper
B48: ABC INDIA LTD | C48: 520123 | D48: Not Listed | E48: Surface Transportation
... B56: ABIRAMI FINANCIAL SERVICES INDIA LTD | C56: 511756 | D56: Not Listed | E56: Finance (including NBFCs)
B57: ABM INTERNATIONAL LTD | C57: Not Listed | D57: ABMINTLTD | E57: Others
B58: ABM KNOWLEDGEWARE LTD | C58: 531161 | D58: Not Listed | E58: IT Software Products
B59: ACC LTD | C59: 500410 | D59: ACC | E59: Cement & Cement Products
B60: ACCEL LTD | C60: 517494 | D60: Not Listed | E60: Storage Media & Peripherals
B61: ACCELYA KALE SOLUTIONS LTD | C61: 532268 | D61: ACCELYA | E61: IT Consulting & Software
B62: ACCORD SYNERGY LTD | C62: Not Listed | D62: ACCORD | E62: SME
B63: ACCURACY SHIPPING LTD | C63: Not Listed | D63: ACCURACY | E63: SME
B64: ACE EDUTREND LTD | C64: 530093 | D64: Not Listed | E64: Education
B65: ACE INTEGRATED SOLUTIONS LTD | C65: Not Listed | D65: ACEINTEG | E65: SME
B66: ACE MEN ENGG WORKS LTD | C66: 539661 | D66: Not Listed | E66: Distributors
B67: ACE SOFTWARE EXPORTS LTD | C67: 531525 | D67: Not Listed | E67: IT Software Products
B68: Achal Investments Ltd | C68: 538570 | D68: ACHAL | E68: Other Financial Services
B69: ACI INFOCOM LTD | C69: 517356 | D69: Not Listed | E69: Storage Media & Peripherals
B70: ACKNIT INDUSTRIES LTD | C70: 530043 | D70: Not Listed | E70: Other Apparels & Accessories
B71: ACME RESOURCES LTD | C71: 539391 | D71: Not Listed | E71: Finance (including NBFCs)
B72: ACROW INDIA LTD. | C72: 513149 | D72: ACROW | E72: Iron &amp; Steel Products
B73: ACRYSIL LTD | C73: 524091 | D73: Not Listed | E73: Plastic Products
B74: ACTION CONSTRUCTION EQUIPMENT LTD | C74: 532762 | D74: ACE | E74: Transport Related Services
B75: ACTION FINANCIAL SERVICES (INDIA) LTD | C75: 511706 | D75: Not Listed | E75: Other Financial Services
B76: ACTION FINANCIAL SERVICES INDIA LTD | C76: 511706 | D76: Not Listed | E76: Other Financial Services
B77: ACTIVE CLOTHING CO LTD | C77: 541144 | D77: Not Listed | E77: Other Apparels & Accessories
... B135: AGRI-TECH INDIA LTD | C135: 537292 | D135: AGRITECH | E135: Other Agricultural Products
B136: AGRO PHOS (INDIA) LTD | C136: Not Listed | D136: AGROPHOS | E136: SME
B137: AGRO PHOS INDIA LTD | C137: Not Listed | D137: AGROPHOS | E137: SME
B138: AGRO TECH FOODS LTD | C138: 500215 | D138: ATFL | E138: Other Agricultural Products
B139: AHIMSA INDUSTRIES LTD | C139: Not Listed | D139: AHIMSA | E139: SME
B140: AHLADA ENGINEERS LTD | C140: Not Listed | D140: AHLADA | E140: SME
B141: AHLUWALIA CONTRACTS (INDIA) LTD | C141: 532811 | D141: AHLUCONT | E141: Realty
B142: AHLUWALIA CONTRACTS INDIA LTD | C142: 532811 | D142: AHLUCONT | E142: Realty
B143: AHMEDABAD STEELCRAFT LTD | C143: 522273 | D143: Not Listed | E143: Iron & Steel/Interm.Products
B144: AI CHAMPDANY INDUSTRIES LTD | C144: 532806 | D144: Not Listed | E144: Jute & Jute Products
B145: AIA ENGINEERING LTD | C145: 532683 | D145: AIAENG | E145: Other Industrial Goods
B146: AIMCO PESTICIDES LTD | C146: 524288 | D146: Not Listed | E146: Agrochemicals
B147: AIRAN LTD | C147: Not Listed | D147: AIRAN | E147: SME
B148: AIRO LAM LTD | C148: Not Listed | D148: AIROLAM | E148: SME
B149: AISHWARYA TELECOM LTD | C149: 532975 | D149: Not Listed | E149: Telecom Equipment
B150: AJANTA PHARMA LTD | C150: 532331 | D150: AJANTPHARM | E150: Pharmaceuticals
B151: AJANTA SOYA LTD | C151: 519216 | D151: Not Listed | E151: Edible Oils
B152: AJCON GLOBAL SERVICES LTD | C152: 511692 | D152: Not Listed | E152: Other Financial Services
B153: AJEL LTD | C153: 530713 | D153: Not Listed | E153: IT Consulting & Software
B154: AJMERA REALTY & INFRA (INDIA) LTD | C154: 513349 | D154: AJMERA | E154: Realty
B155: AJMERA REALTY & INFRA INDIA LTD | C155: 513349 | D155: AJMERA | E155: Realty
B156: AJOONI BIOTECH LTD | C156: Not Listed | D156: AJOONI | E156: SME
B157: AJWA FUN WORLD & RESORT LTD | C157: 526628 | D157: Not Listed | E157: Other Leisure Facilities
B158: AKAR AUTO INDUSTRIES LTD | C158: 530621 | D158: Not Listed | E158: Industrial Machinery
B159: AKASH INFRA PROJECTS LTD | C159: Not Listed | D159: AKASH | E159: SME
B160: AKASHDEEP METAL INDUSTRIES LTD | C160: 538778 | D160: Not Listed | E160: Finance (including NBFCs)
B161: AKG EXIM LTD | C161: Not Listed | D161: AKG | E161: SME
B162: AKI (INDIA) LTD | C162: 542020 | D162: Not Listed | E162: Other Apparels & Accessories
B163: AKI INDIA LTD | C163: 542020 | D163: Not Listed | E163: Other Apparels & Accessories
B164: AKM LACE AND EMBROTEX LTD | C164: 540718 | D164: Not Listed | E164: Textiles
B165: AKME STAR HOUSING FINANCE LTD | C165: 539017 | D165: Not Listed | E165: Housing Finance
...
