Workbook
Name UPDATE: '[1]Data Sheet'!$E$1
Name UPDATE: 'Data Sheet'!$E$1

Sheet AI Valuation Summary
A1: MAHINDRA & MAHINDRA LTD (M&M) - Institutional Valuation
A4: Current Price | B4: Intrinsic Value | C4: Margin of Safety | D4: Verdict | E4: WACC | F4: Altman Z-Score | G4: DuPont ROE
A5: =DCF!D44 -> 3055 | B5: =DCF!D42 -> 917.42829 | C5: =(B5-A5)/A5 -> -0.69969614 | D5: =IF(C5>0.15,"UNDERVALUED / BUY",IF(C5<-0.15,"OVERVALUED / SELL","FAIRLY VALUED / HOLD")) -> OVERVALUED / SELL | E5: =DCF!D20 -> 0.11887681 | F5: ='Altman''s Z Score'!I89 -> 3.1701491 | G5: ='Dupont Analysis'!I78 -> 0.21890723
B7: KEY VALUATION PARAMETERS & LIVE MODEL INPUTS
B8: Discount Rate (WACC) | C8: =WACC!K46 -> 0.11887681 | D8: 0
B9: Cost of Equity (Ke) | C9: =WACC!K29 -> 0.13579955 | D9: 0
B10: Risk-Free Rate (Rf) | C10: =WACC!K26 -> 0.07 | D10: 0
B11: Equity Risk Premium (ERP) | C11: =WACC!K27 -> 0.065 | D11: 0
B12: Levered Beta | C12: =WACC!K28 -> 1.0123008 | D12: 0
B13: Terminal Growth Rate | C13: =DCF!D19 -> 0.04 | D13: 0
B14: Cost of Debt (Kd) | C14: =WACC!K39 -> 0 | D14: 0
B15: Cash & Liquid Investments | C15: ='Data Sheet'!K69 -> 31979 | D15: #,##0.00
B16: Total Debt & Borrowings | C16: ='Data Sheet'!K59 -> 136936 | D16: #,##0.00
B17: Shares Outstanding | C17: ='Data Sheet'!K70/10000000 -> 111.8 | D17: #,##0.00
B18: Sector Median EV/Revenue | C18: =Comp_Valuation!O25 -> 3.0308712 | D18: 0.00"x"
B19: Sector Median EV/EBITDA | C19: =Comp_Valuation!P25 -> 20.20578 | D19: 0.00"x"
A20: 5-Year Discounted Cash Flow (DCF) Schedule (Amounts in ₹ Cr) | B20: Sector Median P/E | C20: =Comp_Valuation!Q25 -> 41.122955 | D20: 0.00"x"
A21: Year | B21: EBIT | C21: NOPAT | D21: Reinvest Rate | E21: FCFF | F21: Discount Factor | G21: PV of FCFF
A22: Year 1 | B22: =DCF!I8 -> 36584.352 | C22: =DCF!I10 -> 25609.046 | D22: =DCF!I11 -> 0.85 | E22: =DCF!I12 -> 3841.357 | F22: =DCF!I14 -> 0.94538534 | G22: =DCF!I16 -> 3631.5626
A23: Year 2 | B23: =DCF!J8 -> 38486.738 | C23: =DCF!J10 -> 26940.717 | D23: =DCF!J11 -> 0.7216207 | E23: =DCF!J12 -> 7499.738 | F23: =DCF!J14 -> 0.8449414 | G23: =DCF!J16 -> 6336.8391
A24: Year 3 | B24: =DCF!K8 -> 40488.049 | C24: =DCF!K10 -> 28341.634 | D24: =DCF!K11 -> 0.59324139 | E24: =DCF!K12 -> 11528.204 | F24: =DCF!K14 -> 0.75516929 | G24: =DCF!K16 -> 8705.7453
A25: Year 4 | B25: =DCF!L8 -> 42593.427 | C25: =DCF!L10 -> 29815.399 | D25: =DCF!L11 -> 0.46486209 | E25: =DCF!L12 -> 15955.35 | F25: =DCF!L14 -> 0.67493515 | G25: =DCF!L16 -> 10768.827
A26: Year 5 | B26: =DCF!M8 -> 44808.285 | C26: =DCF!M10 -> 31365.8 | D26: =DCF!M11 -> 0.33648278 | E26: =DCF!M12 -> 20811.748 | F26: =DCF!M14 -> 0.60322561 | G26: =DCF!M16 -> 12554.18
B28: Enterprise to Equity Value Bridge
B29: PV of 5-Year FCFFs | C29: =DCF!D33 -> 41997.153 | D29: ₹ Cr
B30: Terminal Value | C30: =DCF!D29 -> 274405.34 | D30: ₹ Cr
B31: PV of Terminal Value | C31: =DCF!D34 -> 165528.33 | D31: ₹ Cr
B32: Enterprise Value (Operating Assets) | C32: =DCF!D35 -> 207525.48 | D32: ₹ Cr
B33: Add: Estimated Cash & Liquid Assets | C33: =DCF!D37 -> 31979 | D33: ₹ Cr
B34: Less: Total Debt & Borrowings | C34: =DCF!D38 -> 136936 | D34: ₹ Cr
B35: Net Equity Value | C35: =DCF!D39 -> 102568.48 | D35: ₹ Cr
B36: Shares Outstanding | C36: =DCF!D40 -> 111.8 | D36: Cr shares
B37: Intrinsic Value per Share | C37: =DCF!D42 -> 917.42829 | D37: ₹
B38: Current Market Price | C38: =DCF!D44 -> 3055 | D38: ₹
B39: Margin of Safety / Discount | C39: =(C37-C38)/C38 -> -0.69969614 | D39: %

Sheet Profit & Loss
A1: ='Data Sheet'!B1 -> MAHINDRA & MAHINDRA LTD | H1: =UPDATE | M1: SCREENER.IN
A3: Narration | B3: ='Data Sheet'!B16 -> 42795 | C3: ='Data Sheet'!C16 -> 43160 | D3: ='Data Sheet'!D16 -> 43525 | E3: ='Data Sheet'!E16 -> 43891 | F3: ='Data Sheet'!F16 -> 44256 | G3: ='Data Sheet'!G16 -> 44621 | H3: ='Data Sheet'!H16 -> 44986 | I3: ='Data Sheet'!I16 -> 45352 | ... K3: ='Data Sheet'!K16 -> 46082 | L3: Trailing | M3: Best Case | N3: Worst Case
A4: Sales | B4: ='Data Sheet'!B17 -> 83773 | C4: ='Data Sheet'!C17 -> 92094 | D4: ='Data Sheet'!D17 -> 104721 | E4: ='Data Sheet'!E17 -> 75382 | F4: ='Data Sheet'!F17 -> 74278 | G4: ='Data Sheet'!G17 -> 90171 | H4: ='Data Sheet'!H17 -> 121362 | I4: ='Data Sheet'!I17 -> 139078 | ... K4: ='Data Sheet'!K17 -> 198639 | L4: =SUM(Quarters!H4:K4) -> 211376 | M4: =$K4+M23*K4 -> 247831.19 | N4: =$K4+N23*L4 -> 218882.09
A5: Expenses | B5: =SUM('Data Sheet'!B18,'Data Sheet'!B20:B24, -1*'Data Sheet'!B19) -> 72882.51 | C5: =SUM('Data Sheet'!C18,'Data Sheet'!C20:C24, -1*'Data Sheet'!C19) -> 79200.84 | D5: =SUM('Data Sheet'!D18,'Data Sheet'!D20:D24, -1*'Data Sheet'!D19) -> 89012.85 | E5: =SUM('Data Sheet'!E18,'Data Sheet'!E20:E24, -1*'Data Sheet'!E19) -> 65582.34 | F5: =SUM('Data Sheet'!F18,'Data Sheet'!F20:F24, -1*'Data Sheet'!F19) -> 63136.3 | G5: =SUM('Data Sheet'!G18,'Data Sheet'!G20:G24, -1*'Data Sheet'!G19) -> 74841.93 | H5: =SUM('Data Sheet'!H18,'Data Sheet'!H20:H24, -1*'Data Sheet'!H19) -> 100730.46 | I5: =SUM('Data Sheet'!I18,'Data Sheet'!I20:I24, -1*'Data Sheet'!I19) -> 114043.96 | ... K5: =SUM('Data Sheet'!K18,'Data Sheet'!K20:K24, -1*'Data Sheet'!K19) -> 160897.59 | L5: =SUM(Quarters!H5:K5) -> 171320 | M5: =M4-M6 -> 200869.24 | N5: =N4-N6 -> 182472
A6: Operating Profit | B6: =B4-B5 -> 10890.49 | C6: =C4-C5 -> 12893.16 | D6: =D4-D5 -> 15708.15 | E6: =E4-E5 -> 9799.66 | F6: =F4-F5 -> 11141.7 | G6: =G4-G5 -> 15329.07 | H6: =H4-H5 -> 20631.54 | I6: =I4-I5 -> 25034.04 | ... K6: =K4-K5 -> 37741.41 | L6: =SUM(Quarters!H6:K6) -> 40054 | M6: =M4*M24 -> 46961.957 | N6: =N4*N24 -> 36410.088
A7: Other Income | B7: ='Data Sheet'!B25 -> 2077 | C7: ='Data Sheet'!C25 -> 4366 | D7: ='Data Sheet'!D25 -> 2676 | E7: ='Data Sheet'!E25 -> 885 | F7: ='Data Sheet'!F25 -> 1152 | G7: ='Data Sheet'!G25 -> 3204 | H7: ='Data Sheet'!H25 -> 3922 | I7: ='Data Sheet'!I25 -> 3298 | ... K7: ='Data Sheet'!K25 -> 5118 | L7: =SUM(Quarters!H7:K7) -> 4368 | M7: 0 | N7: 0
A8: Depreciation | B8: ='Data Sheet'!B26 -> 2813 | C8: ='Data Sheet'!C26 -> 3280 | D8: ='Data Sheet'!D26 -> 3991 | E8: ='Data Sheet'!E26 -> 3367 | F8: ='Data Sheet'!F26 -> 3378 | G8: ='Data Sheet'!G26 -> 3508 | H8: ='Data Sheet'!H26 -> 4357 | I8: ='Data Sheet'!I26 -> 4724 | ... K8: ='Data Sheet'!K26 -> 7322 | L8: =SUM(Quarters!H8:K8) -> 7535 | M8: =+$L8 -> 7535 | N8: =+$L8 -> 7535
A9: Interest | B9: ='Data Sheet'!B27 -> 3648 | C9: ='Data Sheet'!C27 -> 3987 | D9: ='Data Sheet'!D27 -> 5021 | E9: ='Data Sheet'!E27 -> 6021 | F9: ='Data Sheet'!F27 -> 6102 | G9: ='Data Sheet'!G27 -> 5018 | H9: ='Data Sheet'!H27 -> 5830 | I9: ='Data Sheet'!I27 -> 7488 | ... K9: ='Data Sheet'!K27 -> 9591 | L9: =SUM(Quarters!H9:K9) -> 9719 | M9: =+$L9 -> 9719 | N9: =+$L9 -> 9719
A10: Profit before tax | B10: ='Data Sheet'!B28 -> 6350 | C10: ='Data Sheet'!C28 -> 10326 | D10: ='Data Sheet'!D28 -> 8871 | E10: ='Data Sheet'!E28 -> 1655 | F10: ='Data Sheet'!F28 -> 3158 | G10: ='Data Sheet'!G28 -> 9362 | H10: ='Data Sheet'!H28 -> 14060 | I10: ='Data Sheet'!I28 -> 15978 | ... K10: ='Data Sheet'!K28 -> 25185 | L10: =SUM(Quarters!H10:K10) -> 27169 | M10: =M6+M7-SUM(M8:M9) -> 29707.957 | N10: =N6+N7-SUM(N8:N9) -> 19156.088
A11: Tax | B11: ='Data Sheet'!B29 -> 6350 | C11: ='Data Sheet'!C29 -> 10326 | D11: ='Data Sheet'!D29 -> 8871 | E11: ='Data Sheet'!E29 -> 1655 | F11: ='Data Sheet'!F29 -> 3158 | G11: ='Data Sheet'!G29 -> 9362 | H11: ='Data Sheet'!H29 -> 14060 | I11: ='Data Sheet'!I29 -> 15978 | ... K11: ='Data Sheet'!K29 -> 25185 | L11: =SUM(Quarters!H11:K11) -> 27169 | M11: =IF($L10>0,$L11/$L10,0) -> 1 | N11: =IF($L10>0,$L11/$L10,0) -> 1
A12: Net profit | B12: ='Data Sheet'!B30 -> 4051 | C12: ='Data Sheet'!C30 -> 7958 | D12: ='Data Sheet'!D30 -> 6017 | E12: ='Data Sheet'!E30 -> -321 | F12: ='Data Sheet'!F30 -> 1512 | G12: ='Data Sheet'!G30 -> 7253 | H12: ='Data Sheet'!H30 -> 11374 | I12: ='Data Sheet'!I30 -> 12270 | ... K12: ='Data Sheet'!K30 -> 18622 | L12: =SUM(Quarters!H12:K12) -> 20243 | M12: =M10-M11*M10 -> 0 | N12: =N10-N11*N10 -> 0
A13: EPS | B13: =IF('Data Sheet'!B93>0,B12/'Data Sheet'!B93,0) -> 30.265222 | C13: =IF('Data Sheet'!C93>0,C12/'Data Sheet'!C93,0) -> 59.454613 | D13: =IF('Data Sheet'!D93>0,D12/'Data Sheet'!D93,0) -> 44.953306 | E13: =IF('Data Sheet'!E93>0,E12/'Data Sheet'!E93,0) -> -2.3982069 | F13: =IF('Data Sheet'!F93>0,F12/'Data Sheet'!F93,0) -> 11.296227 | G13: =IF('Data Sheet'!G93>0,G12/'Data Sheet'!G93,0) -> 54.187523 | H13: =IF('Data Sheet'!H93>0,H12/'Data Sheet'!H93,0) -> 84.975719 | I13: =IF('Data Sheet'!I93>0,I12/'Data Sheet'!I93,0) -> 91.66978 | ... K13: =IF('Data Sheet'!K93>0,K12/'Data Sheet'!K93,0) -> 139.12589 | L13: =IF('Data Sheet'!$B6>0,'Profit & Loss'!L12/'Data Sheet'!$B6,0) -> 162.82662 | M13: =IF('Data Sheet'!$B6>0,'Profit & Loss'!M12/'Data Sheet'!$B6,0) -> 0 | N13: =IF('Data Sheet'!$B6>0,'Profit & Loss'!N12/'Data Sheet'!$B6,0) -> 0
A14: Price to earning | B14: =IF(B15>0,B15/B13,"") -> 21.841241 | C14: =IF(C15>0,C15/C13,"") -> 12.321163 | D14: =IF(D15>0,D15/D13,"") -> 14.452775 | E14: =IF(E15>0,E15/E13,"") -> -190.57988 | F14: =IF(F15>0,F15/F13,"") -> 71.386667 | G14: =IF(G15>0,G15/G13,"") -> 13.514181 | H14: =IF(H15>0,H15/H13,"") -> 14.92897 | I14: =IF(I15>0,I15/I13,"") -> 21.382183 | ... K14: =IF(K15>0,K15/K13,"") -> 24.419611 | L14: =IF(L13>0,L15/L13,0) -> 18.762288 | M14: =M25 -> 22.28782 | N14: =N25 -> 18.762288
A15: Price | B15: ='Data Sheet'!B90 -> 661.03 | C15: ='Data Sheet'!C90 -> 732.55 | D15: ='Data Sheet'!D90 -> 649.7 | E15: ='Data Sheet'!E90 -> 457.05 | F15: ='Data Sheet'!F90 -> 806.4 | G15: ='Data Sheet'!G90 -> 732.3 | H15: ='Data Sheet'!H90 -> 1268.6 | I15: ='Data Sheet'!I90 -> 1960.1 | ... K15: ='Data Sheet'!K90 -> 3397.4 | L15: ='Data Sheet'!B8 -> 3055 | M15: =M13*M14 -> 0 | N15: =N13*N14 -> 0
A17: RATIOS:
A18: Dividend Payout | B18: =IF('Data Sheet'!B30>0, 'Data Sheet'!B31/'Data Sheet'!B30, 0) -> 0.22 | C18: =IF('Data Sheet'!C30>0, 'Data Sheet'!C31/'Data Sheet'!C30, 0) -> 0.11 | D18: =IF('Data Sheet'!D30>0, 'Data Sheet'!D31/'Data Sheet'!D30, 0) -> 0.17 | E18: =IF('Data Sheet'!E30>0, 'Data Sheet'!E31/'Data Sheet'!E30, 0) -> 0 | F18: =IF('Data Sheet'!F30>0, 'Data Sheet'!F31/'Data Sheet'!F30, 0) -> 0.54 | G18: =IF('Data Sheet'!G30>0, 'Data Sheet'!G31/'Data Sheet'!G30, 0) -> 0.2 | H18: =IF('Data Sheet'!H30>0, 'Data Sheet'!H31/'Data Sheet'!H30, 0) -> 0.18 | I18: =IF('Data Sheet'!I30>0, 'Data Sheet'!I31/'Data Sheet'!I30, 0) -> 0.21 | ... K18: =IF('Data Sheet'!K30>0, 'Data Sheet'!K31/'Data Sheet'!K30, 0) -> 0.22
A19: OPM | B19: =IF(B6>0,B6/B4,0) -> 0.13 | C19: =IF(C6>0,C6/C4,0) -> 0.14 | D19: =IF(D6>0,D6/D4,0) -> 0.15 | E19: =IF(E6>0,E6/E4,0) -> 0.13 | F19: =IF(F6>0,F6/F4,0) -> 0.15 | G19: =IF(G6>0,G6/G4,0) -> 0.17 | H19: =IF(H6>0,H6/H4,0) -> 0.17 | I19: =IF(I6>0,I6/I4,0) -> 0.18 | ... L19: =IF(L6>0,L6/L4,0) -> 0.18949171
G22: TRENDS: | H22: 10 YEARS | I22: 7 YEARS | J22: 5 YEARS | K22: 3 YEARS | L22: RECENT | M22: BEST | N22: WORST
G23: Sales Growth | H23: =IF(B4=0,"",POWER($K4/B4,1/9)-1) -> 0.10068303 | I23: =IF(D4=0,"",POWER($K4/D4,1/7)-1) -> 0.09576816 | J23: =IF(F4=0,"",POWER($K4/F4,1/5)-1) -> 0.21742121 | K23: =IF(H4=0,"",POWER($K4/H4, 1/3)-1) -> 0.1784937 | L23: =IF(ISERROR(MAX(IF(J4=0,"",(K4-J4)/J4),IF(K4=0,"",(L4-K4)/K4))),"",MAX(IF(J4=0,"",(K4-J4)/J4),IF(K4=0,"",(L4-K4)/K4))) -> 0.24764621 | M23: =MAX(K23:L23) -> 0.24764621 | N23: =MIN(H23:L23) -> 0.09576816
G24: OPM | H24: =IF(SUM(B4:$K$4)=0,"",SUMPRODUCT(B19:$K$19,B4:$K$4)/SUM(B4:$K$4)) -> 0.16634567 | I24: =IF(SUM(E4:$K$4)=0,"",SUMPRODUCT(E19:$K$19,E4:$K$4)/SUM(E4:$K$4)) -> 0.17471605 | J24: =IF(SUM(G4:$K$4)=0,"",SUMPRODUCT(G19:$K$19,G4:$K$4)/SUM(G4:$K$4)) -> 0.18206528 | K24: =IF(SUM(I4:$K$4)=0, "", SUMPRODUCT(I19:$K$19,I4:$K$4)/SUM(I4:$K$4)) -> 0.18720124 | L24: =L19 -> 0.18949171 | M24: =MAX(K24:L24) -> 0.18949171 | N24: =MIN(H24:L24) -> 0.16634567
G25: Price to Earning | H25: =IF(ISERROR(AVERAGEIF(B14:$L14,">0")),"",AVERAGEIF(B14:$L14,">0")) -> 23.759628 | I25: =IF(ISERROR(AVERAGEIF(E14:$L14,">0")),"",AVERAGEIF(E14:$L14,">0")) -> 26.9973 | J25: =IF(ISERROR(AVERAGEIF(G14:$L14,">0")),"",AVERAGEIF(G14:$L14,">0")) -> 19.599072 | K25: =IF(ISERROR(AVERAGEIF(I14:$L14,">0")),"",AVERAGEIF(I14:$L14,">0")) -> 22.28782 | L25: =L14 -> 18.762288 | M25: =MAX(K25:L25) -> 22.28782 | N25: =MIN(H25:L25) -> 18.762288

Sheet Quarters
A1: ='Profit & Loss'!A1 -> MAHINDRA & MAHINDRA LTD | E1: =UPDATE | J1: SCREENER.IN
A3: Narration | B3: ='Data Sheet'!B41 -> 45352 | C3: ='Data Sheet'!C41 -> 45444 | D3: ='Data Sheet'!D41 -> 45536 | E3: ='Data Sheet'!E41 -> 45627 | F3: ='Data Sheet'!F41 -> 45717 | G3: ='Data Sheet'!G41 -> 45809 | H3: ='Data Sheet'!H41 -> 45901 | I3: ='Data Sheet'!I41 -> 45992 | ... K3: ='Data Sheet'!K41 -> 46174
A4: Sales | B4: ='Data Sheet'!B42 -> 35452 | C4: ='Data Sheet'!C42 -> 37218 | D4: ='Data Sheet'!D42 -> 37924 | E4: ='Data Sheet'!E42 -> 41470 | F4: ='Data Sheet'!F42 -> 42599 | G4: ='Data Sheet'!G42 -> 45529 | H4: ='Data Sheet'!H42 -> 46106 | I4: ='Data Sheet'!I42 -> 52100 | ... K4: ='Data Sheet'!K42 -> 58188
A5: Expenses | B5: ='Data Sheet'!B43 -> 28848 | C5: ='Data Sheet'!C43 -> 29975 | D5: ='Data Sheet'!D43 -> 30790 | E5: ='Data Sheet'!E43 -> 33239 | F5: ='Data Sheet'!F43 -> 34658 | G5: ='Data Sheet'!G43 -> 37117 | H5: ='Data Sheet'!H43 -> 37166 | I5: ='Data Sheet'!I43 -> 41939 | ... K5: ='Data Sheet'!K43 -> 47360
A6: Operating Profit | B6: ='Data Sheet'!B50 -> 6604 | C6: ='Data Sheet'!C50 -> 7243 | D6: ='Data Sheet'!D50 -> 7133 | E6: ='Data Sheet'!E50 -> 8231 | F6: ='Data Sheet'!F50 -> 7942 | G6: ='Data Sheet'!G50 -> 8412 | H6: ='Data Sheet'!H50 -> 8940 | I6: ='Data Sheet'!I50 -> 10160 | ... K6: ='Data Sheet'!K50 -> 10827
A7: Other Income | B7: ='Data Sheet'!B44 -> 750 | C7: ='Data Sheet'!C44 -> 733 | D7: ='Data Sheet'!D44 -> 1126 | E7: ='Data Sheet'!E44 -> 719 | F7: ='Data Sheet'!F44 -> 1110 | G7: ='Data Sheet'!G44 -> 1210 | H7: ='Data Sheet'!H44 -> 1134 | I7: ='Data Sheet'!I44 -> 976 | ... K7: ='Data Sheet'!K44 -> 1121
A8: Depreciation | B8: ='Data Sheet'!B45 -> 1335 | C8: ='Data Sheet'!C45 -> 1248 | D8: ='Data Sheet'!D45 -> 1302 | E8: ='Data Sheet'!E45 -> 1495 | F8: ='Data Sheet'!F45 -> 2029 | G8: ='Data Sheet'!G45 -> 1548 | H8: ='Data Sheet'!H45 -> 1669 | I8: ='Data Sheet'!I45 -> 2163 | ... K8: ='Data Sheet'!K45 -> 1760
A9: Interest | B9: ='Data Sheet'!B46 -> 1989 | C9: ='Data Sheet'!C46 -> 2108 | D9: ='Data Sheet'!D46 -> 2217 | E9: ='Data Sheet'!E46 -> 2362 | F9: ='Data Sheet'!F46 -> 2397 | G9: ='Data Sheet'!G46 -> 2431 | H9: ='Data Sheet'!H46 -> 2347 | I9: ='Data Sheet'!I46 -> 2405 | ... K9: ='Data Sheet'!K46 -> 2560
A10: Profit before tax | B10: ='Data Sheet'!B47 -> 4030 | C10: ='Data Sheet'!C47 -> 4621 | D10: ='Data Sheet'!D47 -> 4740 | E10: ='Data Sheet'!E47 -> 5092 | F10: ='Data Sheet'!F47 -> 4627 | G10: ='Data Sheet'!G47 -> 5644 | H10: ='Data Sheet'!H47 -> 6058 | I10: ='Data Sheet'!I47 -> 6569 | ... K10: ='Data Sheet'!K47 -> 7628
A11: Tax | B11: ='Data Sheet'!B48 -> 4030 | C11: ='Data Sheet'!C48 -> 4621 | D11: ='Data Sheet'!D48 -> 4740 | E11: ='Data Sheet'!E48 -> 5092 | F11: ='Data Sheet'!F48 -> 4627 | G11: ='Data Sheet'!G48 -> 5644 | H11: ='Data Sheet'!H48 -> 6058 | I11: ='Data Sheet'!I48 -> 6569 | ... K11: ='Data Sheet'!K48 -> 7628
A12: Net profit | B12: ='Data Sheet'!B49 -> 3125 | C12: ='Data Sheet'!C49 -> 3546 | D12: ='Data Sheet'!D49 -> 3361 | E12: ='Data Sheet'!E49 -> 3624 | F12: ='Data Sheet'!F49 -> 3542 | G12: ='Data Sheet'!G49 -> 4377 | H12: ='Data Sheet'!H49 -> 3964 | I12: ='Data Sheet'!I49 -> 5021 | ... K12: ='Data Sheet'!K49 -> 5998
A14: OPM | B14: =IF(B4>0,B6/B4,"") -> 0.18628004 | C14: =IF(C4>0,C6/C4,"") -> 0.19461013 | D14: =IF(D4>0,D6/D4,"") -> 0.1880867 | E14: =IF(E4>0,E6/E4,"") -> 0.19848083 | F14: =IF(F4>0,F6/F4,"") -> 0.1864363 | G14: =IF(G4>0,G6/G4,"") -> 0.18476136 | H14: =IF(H4>0,H6/H4,"") -> 0.19390101 | I14: =IF(I4>0,I6/I4,"") -> 0.1950096 | ... K14: =IF(K4>0,K6/K4,"") -> 0.18606929

Sheet Balance Sheet
A1: ='Profit & Loss'!A1 -> MAHINDRA & MAHINDRA LTD | E1: =UPDATE | J1: SCREENER.IN
A3: Narration | B3: ='Data Sheet'!B56 -> 42795 | C3: ='Data Sheet'!C56 -> 43160 | D3: ='Data Sheet'!D56 -> 43525 | E3: ='Data Sheet'!E56 -> 43891 | F3: ='Data Sheet'!F56 -> 44256 | G3: ='Data Sheet'!G56 -> 44621 | H3: ='Data Sheet'!H56 -> 44986 | I3: ='Data Sheet'!I56 -> 45352 | ... K3: ='Data Sheet'!K56 -> 46082
A4: Equity Share Capital | B4: ='Data Sheet'!B57 -> 311 | C4: ='Data Sheet'!C57 -> 543 | D4: ='Data Sheet'!D57 -> 544 | E4: ='Data Sheet'!E57 -> 554 | F4: ='Data Sheet'!F57 -> 555 | G4: ='Data Sheet'!G57 -> 556 | H4: ='Data Sheet'!H57 -> 557 | I4: ='Data Sheet'!I57 -> 557 | ... K4: ='Data Sheet'!K57 -> 559
A5: Reserves | B5: ='Data Sheet'!B58 -> 29467 | C5: ='Data Sheet'!C58 -> 36232 | D5: ='Data Sheet'!D58 -> 39439 | E5: ='Data Sheet'!E58 -> 39415 | F5: ='Data Sheet'!F58 -> 41027 | G5: ='Data Sheet'!G58 -> 46567 | H5: ='Data Sheet'!H58 -> 55809 | I5: ='Data Sheet'!I58 -> 65633 | ... K5: ='Data Sheet'!K58 -> 92538
A6: Borrowings | B6: ='Data Sheet'!B59 -> 48762 | C6: ='Data Sheet'!C59 -> 55898 | D6: ='Data Sheet'!D59 -> 70848 | E6: ='Data Sheet'!E59 -> 82092 | F6: ='Data Sheet'!F59 -> 80625 | G6: ='Data Sheet'!G59 -> 77605 | H6: ='Data Sheet'!H59 -> 92647 | I6: ='Data Sheet'!I59 -> 108647 | ... K6: ='Data Sheet'!K59 -> 136936
A7: Other Liabilities | B7: ='Data Sheet'!B60 -> 35296 | C7: ='Data Sheet'!C60 -> 43696 | D7: ='Data Sheet'!D60 -> 51057 | E7: ='Data Sheet'!E60 -> 43655 | F7: ='Data Sheet'!F60 -> 42762 | G7: ='Data Sheet'!G60 -> 47661 | H7: ='Data Sheet'!H60 -> 55270 | I7: ='Data Sheet'!I60 -> 59884 | ... K7: ='Data Sheet'!K60 -> 86021
A8: Total | B8: ='Data Sheet'!B61 -> 113835 | C8: ='Data Sheet'!C61 -> 136369 | D8: ='Data Sheet'!D61 -> 161889 | E8: ='Data Sheet'!E61 -> 165716 | F8: ='Data Sheet'!F61 -> 164968 | G8: ='Data Sheet'!G61 -> 172388 | H8: ='Data Sheet'!H61 -> 204283 | I8: ='Data Sheet'!I61 -> 234722 | ... K8: ='Data Sheet'!K61 -> 316054
A10: Net Block | B10: ='Data Sheet'!B62 -> 20989 | C10: ='Data Sheet'!C62 -> 26182 | D10: ='Data Sheet'!D62 -> 28983 | E10: ='Data Sheet'!E62 -> 29689 | F10: ='Data Sheet'!F62 -> 21380 | G10: ='Data Sheet'!G62 -> 26018 | H10: ='Data Sheet'!H62 -> 27140 | I10: ='Data Sheet'!I62 -> 28129 | ... K10: ='Data Sheet'!K62 -> 38459
A11: Capital Work in Progress | B11: ='Data Sheet'!B63 -> 4279 | C11: ='Data Sheet'!C63 -> 4269 | D11: ='Data Sheet'!D63 -> 4760 | E11: ='Data Sheet'!E63 -> 6856 | F11: ='Data Sheet'!F63 -> 7873 | G11: ='Data Sheet'!G63 -> 6703 | H11: ='Data Sheet'!H63 -> 3969 | I11: ='Data Sheet'!I63 -> 8039 | ... K11: ='Data Sheet'!K63 -> 7740
A12: Investments | B12: ='Data Sheet'!B64 -> 14662 | C12: ='Data Sheet'!C64 -> 16018 | D12: ='Data Sheet'!D64 -> 18268 | E12: ='Data Sheet'!E64 -> 19210 | F12: ='Data Sheet'!F64 -> 28778 | G12: ='Data Sheet'!G64 -> 30060 | H12: ='Data Sheet'!H64 -> 35272 | I12: ='Data Sheet'!I64 -> 35208 | ... K12: ='Data Sheet'!K64 -> 40324
A13: Other Assets | B13: ='Data Sheet'!B65 -> 73905 | C13: ='Data Sheet'!C65 -> 89900 | D13: ='Data Sheet'!D65 -> 109878 | E13: ='Data Sheet'!E65 -> 109960 | F13: ='Data Sheet'!F65 -> 106938 | G13: ='Data Sheet'!G65 -> 109607 | H13: ='Data Sheet'!H65 -> 137902 | I13: ='Data Sheet'!I65 -> 163345 | ... K13: ='Data Sheet'!K65 -> 229531
A14: Total | B14: ='Data Sheet'!B66 -> 113835 | C14: ='Data Sheet'!C66 -> 136369 | D14: ='Data Sheet'!D66 -> 161889 | E14: ='Data Sheet'!E66 -> 165716 | F14: ='Data Sheet'!F66 -> 164968 | G14: ='Data Sheet'!G66 -> 172388 | H14: ='Data Sheet'!H66 -> 204283 | I14: ='Data Sheet'!I66 -> 234722 | ... K14: ='Data Sheet'!K66 -> 316054
A16: Working Capital | B16: =B13-B7 -> 38609 | C16: =C13-C7 -> 46204 | D16: =D13-D7 -> 58821 | E16: =E13-E7 -> 66305 | F16: =F13-F7 -> 64176 | G16: =G13-G7 -> 61946 | H16: =H13-H7 -> 82632 | I16: =I13-I7 -> 103461 | ... K16: =K13-K7 -> 143510
A17: Debtors | B17: ='Data Sheet'!B67 -> 7199 | C17: ='Data Sheet'!C67 -> 8490 | D17: ='Data Sheet'!D67 -> 8678 | E17: ='Data Sheet'!E67 -> 6928 | F17: ='Data Sheet'!F67 -> 6008 | G17: ='Data Sheet'!G67 -> 6374 | H17: ='Data Sheet'!H67 -> 7028 | I17: ='Data Sheet'!I67 -> 7459 | ... K17: ='Data Sheet'!K67 -> 9064
A18: Inventory | B18: ='Data Sheet'!B68 -> 8886 | C18: ='Data Sheet'!C68 -> 9336 | D18: ='Data Sheet'!D68 -> 12200 | E18: ='Data Sheet'!E68 -> 11112 | F18: ='Data Sheet'!F68 -> 9615 | G18: ='Data Sheet'!G68 -> 11596 | H18: ='Data Sheet'!H68 -> 16855 | I18: ='Data Sheet'!I68 -> 18590 | ... K18: ='Data Sheet'!K68 -> 22044
A20: Debtor Days | B20: =IF('Profit & Loss'!B4>0,'Balance Sheet'!B17/('Profit & Loss'!B4/365),0) -> 31.366132 | C20: =IF('Profit & Loss'!C4>0,'Balance Sheet'!C17/('Profit & Loss'!C4/365),0) -> 33.648772 | D20: =IF('Profit & Loss'!D4>0,'Balance Sheet'!D17/('Profit & Loss'!D4/365),0) -> 30.246751 | E20: =IF('Profit & Loss'!E4>0,'Balance Sheet'!E17/('Profit & Loss'!E4/365),0) -> 33.545409 | F20: =IF('Profit & Loss'!F4>0,'Balance Sheet'!F17/('Profit & Loss'!F4/365),0) -> 29.523143 | G20: =IF('Profit & Loss'!G4>0,'Balance Sheet'!G17/('Profit & Loss'!G4/365),0) -> 25.801089 | H20: =IF('Profit & Loss'!H4>0,'Balance Sheet'!H17/('Profit & Loss'!H4/365),0) -> 21.136929 | I20: =IF('Profit & Loss'!I4>0,'Balance Sheet'!I17/('Profit & Loss'!I4/365),0) -> 19.575598 | ... K20: =IF('Profit & Loss'!K4>0,'Balance Sheet'!K17/('Profit & Loss'!K4/365),0) -> 16.655138
A21: Inventory Turnover | B21: =IF('Balance Sheet'!B18>0,'Profit & Loss'!B4/'Balance Sheet'!B18,0) -> 9.4275264 | C21: =IF('Balance Sheet'!C18>0,'Profit & Loss'!C4/'Balance Sheet'!C18,0) -> 9.8643959 | D21: =IF('Balance Sheet'!D18>0,'Profit & Loss'!D4/'Balance Sheet'!D18,0) -> 8.5836885 | E21: =IF('Balance Sheet'!E18>0,'Profit & Loss'!E4/'Balance Sheet'!E18,0) -> 6.7838373 | F21: =IF('Balance Sheet'!F18>0,'Profit & Loss'!F4/'Balance Sheet'!F18,0) -> 7.725221 | G21: =IF('Balance Sheet'!G18>0,'Profit & Loss'!G4/'Balance Sheet'!G18,0) -> 7.7760435 | H21: =IF('Balance Sheet'!H18>0,'Profit & Loss'!H4/'Balance Sheet'!H18,0) -> 7.200356 | I21: =IF('Balance Sheet'!I18>0,'Profit & Loss'!I4/'Balance Sheet'!I18,0) -> 7.4813341 | ... K21: =IF('Balance Sheet'!K18>0,'Profit & Loss'!K4/'Balance Sheet'!K18,0) -> 9.0110234
A23: Return on Equity | B23: =IF(SUM('Balance Sheet'!B4:B5)>0,'Profit & Loss'!B12/SUM('Balance Sheet'!B4:B5),"") -> 0.13604003 | C23: =IF(SUM('Balance Sheet'!C4:C5)>0,'Profit & Loss'!C12/SUM('Balance Sheet'!C4:C5),"") -> 0.21639701 | D23: =IF(SUM('Balance Sheet'!D4:D5)>0,'Profit & Loss'!D12/SUM('Balance Sheet'!D4:D5),"") -> 0.15048896 | E23: =IF(SUM('Balance Sheet'!E4:E5)>0,'Profit & Loss'!E12/SUM('Balance Sheet'!E4:E5),"") -> -0.0080312242 | F23: =IF(SUM('Balance Sheet'!F4:F5)>0,'Profit & Loss'!F12/SUM('Balance Sheet'!F4:F5),"") -> 0.036361887 | G23: =IF(SUM('Balance Sheet'!G4:G5)>0,'Profit & Loss'!G12/SUM('Balance Sheet'!G4:G5),"") -> 0.15391635 | H23: =IF(SUM('Balance Sheet'!H4:H5)>0,'Profit & Loss'!H12/SUM('Balance Sheet'!H4:H5),"") -> 0.20178831 | I23: =IF(SUM('Balance Sheet'!I4:I5)>0,'Profit & Loss'!I12/SUM('Balance Sheet'!I4:I5),"") -> 0.18537543 | ... K23: =IF(SUM('Balance Sheet'!K4:K5)>0,'Profit & Loss'!K12/SUM('Balance Sheet'!K4:K5),"") -> 0.20002793
A24: Return on Capital Emp | C24: =IF((B4+B5+B6+C4+C5+C6)>0,('Profit & Loss'!C10+'Profit & Loss'!C9)*2/(B4+B5+B6+C4+C5+C6),"") -> 0.16719525 | D24: =IF((C4+C5+C6+D4+D5+D6)>0,('Profit & Loss'!D10+'Profit & Loss'!D9)*2/(C4+C5+C6+D4+D5+D6),"") -> 0.13652803 | E24: =IF((D4+D5+D6+E4+E5+E6)>0,('Profit & Loss'!E10+'Profit & Loss'!E9)*2/(D4+D5+D6+E4+E5+E6),"") -> 0.065918967 | F24: =IF((E4+E5+E6+F4+F5+F6)>0,('Profit & Loss'!F10+'Profit & Loss'!F9)*2/(E4+E5+E6+F4+F5+F6),"") -> 0.075818363 | G24: =IF((F4+F5+F6+G4+G5+G6)>0,('Profit & Loss'!G10+'Profit & Loss'!G9)*2/(F4+F5+F6+G4+G5+G6),"") -> 0.1164679 | H24: =IF((G4+G5+G6+H4+H5+H6)>0,('Profit & Loss'!H10+'Profit & Loss'!H9)*2/(G4+G5+G6+H4+H5+H6),"") -> 0.14531985 | I24: =IF((H4+H5+H6+I4+I5+I6)>0,('Profit & Loss'!I10+'Profit & Loss'!I9)*2/(H4+H5+H6+I4+I5+I6),"") -> 0.14491894 | J24: =IF((I4+I5+I6+J4+J5+J6)>0,('Profit & Loss'!J10+'Profit & Loss'!J9)*2/(I4+I5+I6+J4+J5+J6),"") -> 0.14787569 | K24: =IF((J4+J5+J6+K4+K5+K6)>0,('Profit & Loss'!K10+'Profit & Loss'!K9)*2/(J4+J5+J6+K4+K5+K6),"") -> 0.15948745

Sheet Cash Flow
A1: ='Balance Sheet'!A1 -> MAHINDRA & MAHINDRA LTD | E1: =UPDATE | J1: SCREENER.IN
A3: Narration | B3: ='Data Sheet'!B81 -> 42795 | C3: ='Data Sheet'!C81 -> 43160 | D3: ='Data Sheet'!D81 -> 43525 | E3: ='Data Sheet'!E81 -> 43891 | F3: ='Data Sheet'!F81 -> 44256 | G3: ='Data Sheet'!G81 -> 44621 | H3: ='Data Sheet'!H81 -> 44986 | I3: ='Data Sheet'!I81 -> 45352 | ... K3: ='Data Sheet'!K81 -> 46082
A4: Cash from Operating Activity | B4: ='Data Sheet'!B82 -> 183 | C4: ='Data Sheet'!C82 -> 682 | D4: ='Data Sheet'!D82 -> -4347 | E4: ='Data Sheet'!E82 -> -1457 | F4: ='Data Sheet'!F82 -> 17909 | G4: ='Data Sheet'!G82 -> 9248 | H4: ='Data Sheet'!H82 -> -7074 | I4: ='Data Sheet'!I82 -> -5630 | ... K4: ='Data Sheet'!K82 -> 11657
A5: Cash from Investing Activity | B5: ='Data Sheet'!B83 -> -5875 | C5: ='Data Sheet'!C83 -> -5467 | D5: ='Data Sheet'!D83 -> -7174 | E5: ='Data Sheet'!E83 -> -6870 | F5: ='Data Sheet'!F83 -> -19686 | G5: ='Data Sheet'!G83 -> -3252 | H5: ='Data Sheet'!H83 -> -8866 | I5: ='Data Sheet'!I83 -> -5615 | ... K5: ='Data Sheet'!K83 -> -17680
A6: Cash from Financing Activity | B6: ='Data Sheet'!B84 -> 6108 | C6: ='Data Sheet'!C84 -> 6314 | D6: ='Data Sheet'!D84 -> 13194 | E6: ='Data Sheet'!E84 -> 6933 | F6: ='Data Sheet'!F84 -> 406 | G6: ='Data Sheet'!G84 -> -5883 | H6: ='Data Sheet'!H84 -> 15946 | I6: ='Data Sheet'!I84 -> 12281 | ... K6: ='Data Sheet'!K84 -> 5391
A7: Net Cash Flow | B7: ='Data Sheet'!B85 -> 416 | C7: ='Data Sheet'!C85 -> 1529 | D7: ='Data Sheet'!D85 -> 1672 | E7: ='Data Sheet'!E85 -> -1394 | F7: ='Data Sheet'!F85 -> -1370 | G7: ='Data Sheet'!G85 -> 113 | H7: ='Data Sheet'!H85 -> 6 | I7: ='Data Sheet'!I85 -> 1037 | ... K7: ='Data Sheet'!K85 -> -632

Sheet Customization
A1: How to use it?
A3: You can customize this workbook as you want.
B4: You can add custom formating, add conditional formating, add your own formulas… do ANYTHING.
B5: Please don't edit the "Data Sheet" only.
A7: After customization, you can upload this back on Screener.
B8: Upload on: | C8: https://www.screener.in/excel/
A10: Download your customized workbooks now onwards.
B11: Now whenever you will "Export to excel" from Screener, it will export your customized file.
A14: TESTING:
B15: This is a testing feature currently.
B16: You can report any formula errors on the worksheet at: support@screener.in

Sheet Common Size Statement
B2: ="Common Size Statement - "&'Data Sheet'!$B$1 -> Common Size Statement - MAHINDRA & MAHINDRA LTD
B4: Particulars | C4: ='Data Sheet'!B$16 -> 42795 | D4: ='Data Sheet'!C$16 -> 43160 | E4: ='Data Sheet'!D$16 -> 43525 | F4: ='Data Sheet'!E$16 -> 43891 | G4: ='Data Sheet'!F$16 -> 44256 | H4: ='Data Sheet'!G$16 -> 44621 | I4: ='Data Sheet'!H$16 -> 44986 | J4: ='Data Sheet'!I$16 -> 45352 | ... L4: ='Data Sheet'!K$16 -> 46082
B6: ='Data Sheet'!A17 -> Sales | C6: ='Data Sheet'!B17/'Data Sheet'!B$17 -> 1 | D6: ='Data Sheet'!C17/'Data Sheet'!C$17 -> 1 | E6: ='Data Sheet'!D17/'Data Sheet'!D$17 -> 1 | F6: ='Data Sheet'!E17/'Data Sheet'!E$17 -> 1 | G6: ='Data Sheet'!F17/'Data Sheet'!F$17 -> 1 | H6: ='Data Sheet'!G17/'Data Sheet'!G$17 -> 1 | I6: ='Data Sheet'!H17/'Data Sheet'!H$17 -> 1 | J6: ='Data Sheet'!I17/'Data Sheet'!I$17 -> 1 | ... L6: ='Data Sheet'!K17/'Data Sheet'!K$17 -> 1
B7: ='Data Sheet'!A18 -> Raw Material Cost | C7: ='Data Sheet'!B18/'Data Sheet'!B$17 -> 0.6 | D7: ='Data Sheet'!C18/'Data Sheet'!C$17 -> 0.58 | E7: ='Data Sheet'!D18/'Data Sheet'!D$17 -> 0.57 | F7: ='Data Sheet'!E18/'Data Sheet'!E$17 -> 0.51 | G7: ='Data Sheet'!F18/'Data Sheet'!F$17 -> 0.52 | H7: ='Data Sheet'!G18/'Data Sheet'!G$17 -> 0.57 | I7: ='Data Sheet'!H18/'Data Sheet'!H$17 -> 0.61 | J7: ='Data Sheet'!I18/'Data Sheet'!I$17 -> 0.6 | ... L7: ='Data Sheet'!K18/'Data Sheet'!K$17 -> 0.62
B8: ='Data Sheet'!A19 -> Change in Inventory | C8: ='Data Sheet'!B19/'Data Sheet'!B$17 -> 0 | D8: ='Data Sheet'!C19/'Data Sheet'!C$17 -> 0 | E8: ='Data Sheet'!D19/'Data Sheet'!D$17 -> 0 | F8: ='Data Sheet'!E19/'Data Sheet'!E$17 -> 0 | G8: ='Data Sheet'!F19/'Data Sheet'!F$17 -> 0 | H8: ='Data Sheet'!G19/'Data Sheet'!G$17 -> 0 | I8: ='Data Sheet'!H19/'Data Sheet'!H$17 -> 0 | J8: ='Data Sheet'!I19/'Data Sheet'!I$17 -> 0 | ... L8: ='Data Sheet'!K19/'Data Sheet'!K$17 -> 0
B9: ='Data Sheet'!A20 -> Power and Fuel | C9: ='Data Sheet'!B20/'Data Sheet'!B$17 -> 0 | D9: ='Data Sheet'!C20/'Data Sheet'!C$17 -> 0 | E9: ='Data Sheet'!D20/'Data Sheet'!D$17 -> 0 | F9: ='Data Sheet'!E20/'Data Sheet'!E$17 -> 0 | G9: ='Data Sheet'!F20/'Data Sheet'!F$17 -> 0 | H9: ='Data Sheet'!G20/'Data Sheet'!G$17 -> 0 | I9: ='Data Sheet'!H20/'Data Sheet'!H$17 -> 0 | J9: ='Data Sheet'!I20/'Data Sheet'!I$17 -> 0 | ... L9: ='Data Sheet'!K20/'Data Sheet'!K$17 -> 0
B10: ='Data Sheet'!A21 -> Other Mfr. Exp | C10: ='Data Sheet'!B21/'Data Sheet'!B$17 -> 0.05 | D10: ='Data Sheet'!C21/'Data Sheet'!C$17 -> 0.05 | E10: ='Data Sheet'!D21/'Data Sheet'!D$17 -> 0.05 | F10: ='Data Sheet'!E21/'Data Sheet'!E$17 -> 0.05 | G10: ='Data Sheet'!F21/'Data Sheet'!F$17 -> 0.04 | H10: ='Data Sheet'!G21/'Data Sheet'!G$17 -> 0.04 | I10: ='Data Sheet'!H21/'Data Sheet'!H$17 -> 0.04 | J10: ='Data Sheet'!I21/'Data Sheet'!I$17 -> 0.03 | ... L10: ='Data Sheet'!K21/'Data Sheet'!K$17 -> 0.03
B11: ='Data Sheet'!A22 -> Employee Cost | C11: ='Data Sheet'!B22/'Data Sheet'!B$17 -> 0.11 | D11: ='Data Sheet'!C22/'Data Sheet'!C$17 -> 0.11 | E11: ='Data Sheet'!D22/'Data Sheet'!D$17 -> 0.11 | F11: ='Data Sheet'!E22/'Data Sheet'!E$17 -> 0.11 | G11: ='Data Sheet'!F22/'Data Sheet'!F$17 -> 0.11 | H11: ='Data Sheet'!G22/'Data Sheet'!G$17 -> 0.09 | I11: ='Data Sheet'!H22/'Data Sheet'!H$17 -> 0.08 | J11: ='Data Sheet'!I22/'Data Sheet'!I$17 -> 0.08 | ... L11: ='Data Sheet'!K22/'Data Sheet'!K$17 -> 0.06
B12: ='Data Sheet'!A23 -> Selling and admin | C12: ='Data Sheet'!B23/'Data Sheet'!B$17 -> 0 | D12: ='Data Sheet'!C23/'Data Sheet'!C$17 -> 0 | E12: ='Data Sheet'!D23/'Data Sheet'!D$17 -> 0 | F12: ='Data Sheet'!E23/'Data Sheet'!E$17 -> 0 | G12: ='Data Sheet'!F23/'Data Sheet'!F$17 -> 0 | H12: ='Data Sheet'!G23/'Data Sheet'!G$17 -> 0 | I12: ='Data Sheet'!H23/'Data Sheet'!H$17 -> 0 | J12: ='Data Sheet'!I23/'Data Sheet'!I$17 -> 0 | ... L12: ='Data Sheet'!K23/'Data Sheet'!K$17 -> 0
B13: ='Data Sheet'!A24 -> Other Expenses | C13: ='Data Sheet'!B24/'Data Sheet'!B$17 -> 0.11 | D13: ='Data Sheet'!C24/'Data Sheet'!C$17 -> 0.12 | E13: ='Data Sheet'!D24/'Data Sheet'!D$17 -> 0.12 | F13: ='Data Sheet'!E24/'Data Sheet'!E$17 -> 0.2 | G13: ='Data Sheet'!F24/'Data Sheet'!F$17 -> 0.18 | H13: ='Data Sheet'!G24/'Data Sheet'!G$17 -> 0.13 | I13: ='Data Sheet'!H24/'Data Sheet'!H$17 -> 0.1 | J13: ='Data Sheet'!I24/'Data Sheet'!I$17 -> 0.11 | ... L13: ='Data Sheet'!K24/'Data Sheet'!K$17 -> 0.1
B14: ='Data Sheet'!A25 -> Other Income | C14: ='Data Sheet'!B25/'Data Sheet'!B$17 -> 0.024793191 | D14: ='Data Sheet'!C25/'Data Sheet'!C$17 -> 0.047408083 | E14: ='Data Sheet'!D25/'Data Sheet'!D$17 -> 0.025553614 | F14: ='Data Sheet'!E25/'Data Sheet'!E$17 -> 0.011740203 | G14: ='Data Sheet'!F25/'Data Sheet'!F$17 -> 0.015509303 | H14: ='Data Sheet'!G25/'Data Sheet'!G$17 -> 0.035532488 | I14: ='Data Sheet'!H25/'Data Sheet'!H$17 -> 0.032316541 | J14: ='Data Sheet'!I25/'Data Sheet'!I$17 -> 0.023713312 | ... L14: ='Data Sheet'!K25/'Data Sheet'!K$17 -> 0.025765333
B15: ='Data Sheet'!A26 -> Depreciation | C15: ='Data Sheet'!B26/'Data Sheet'!B$17 -> 0.033578838 | D15: ='Data Sheet'!C26/'Data Sheet'!C$17 -> 0.035615784 | E15: ='Data Sheet'!D26/'Data Sheet'!D$17 -> 0.03811079 | F15: ='Data Sheet'!E26/'Data Sheet'!E$17 -> 0.044665835 | G15: ='Data Sheet'!F26/'Data Sheet'!F$17 -> 0.0454778 | H15: ='Data Sheet'!G26/'Data Sheet'!G$17 -> 0.03890386 | I15: ='Data Sheet'!H26/'Data Sheet'!H$17 -> 0.035900859 | J15: ='Data Sheet'!I26/'Data Sheet'!I$17 -> 0.033966551 | ... L15: ='Data Sheet'!K26/'Data Sheet'!K$17 -> 0.036860838
B16: ='Data Sheet'!A27 -> Interest | C16: ='Data Sheet'!B27/'Data Sheet'!B$17 -> 0.04354625 | D16: ='Data Sheet'!C27/'Data Sheet'!C$17 -> 0.043292723 | E16: ='Data Sheet'!D27/'Data Sheet'!D$17 -> 0.047946448 | F16: ='Data Sheet'!E27/'Data Sheet'!E$17 -> 0.079873179 | G16: ='Data Sheet'!F27/'Data Sheet'!F$17 -> 0.082150839 | H16: ='Data Sheet'!G27/'Data Sheet'!G$17 -> 0.055649821 | I16: ='Data Sheet'!H27/'Data Sheet'!H$17 -> 0.048038101 | J16: ='Data Sheet'!I27/'Data Sheet'!I$17 -> 0.053840291 | ... L16: ='Data Sheet'!K27/'Data Sheet'!K$17 -> 0.04828357
B17: ='Data Sheet'!A28 -> Profit before tax | C17: ='Data Sheet'!B28/'Data Sheet'!B$17 -> 0.075800079 | D17: ='Data Sheet'!C28/'Data Sheet'!C$17 -> 0.11212457 | E17: ='Data Sheet'!D28/'Data Sheet'!D$17 -> 0.084710803 | F17: ='Data Sheet'!E28/'Data Sheet'!E$17 -> 0.021954843 | G17: ='Data Sheet'!F28/'Data Sheet'!F$17 -> 0.042515954 | H17: ='Data Sheet'!G28/'Data Sheet'!G$17 -> 0.10382495 | I17: ='Data Sheet'!H28/'Data Sheet'!H$17 -> 0.11585175 | J17: ='Data Sheet'!I28/'Data Sheet'!I$17 -> 0.11488517 | ... L17: ='Data Sheet'!K28/'Data Sheet'!K$17 -> 0.12678779
... B21: ='Data Sheet'!A32 -> EBITDA | C21: ='Data Sheet'!B32/'Data Sheet'!B$17 -> 0 | D21: ='Data Sheet'!C32/'Data Sheet'!C$17 -> 0 | E21: ='Data Sheet'!D32/'Data Sheet'!D$17 -> 0 | F21: ='Data Sheet'!E32/'Data Sheet'!E$17 -> 0 | G21: ='Data Sheet'!F32/'Data Sheet'!F$17 -> 0 | H21: ='Data Sheet'!G32/'Data Sheet'!G$17 -> 0 | I21: ='Data Sheet'!H32/'Data Sheet'!H$17 -> 0 | J21: ='Data Sheet'!I32/'Data Sheet'!I$17 -> 0 | ... L21: ='Data Sheet'!K32/'Data Sheet'!K$17 -> 0
B23: ="Common Size Balance Sheet - "&'Data Sheet'!$B$1 -> Common Size Balance Sheet - MAHINDRA & MAHINDRA LTD
B25: Particulars | C25: ='Data Sheet'!B$16 -> 42795 | D25: ='Data Sheet'!C$16 -> 43160 | E25: ='Data Sheet'!D$16 -> 43525 | F25: ='Data Sheet'!E$16 -> 43891 | G25: ='Data Sheet'!F$16 -> 44256 | H25: ='Data Sheet'!G$16 -> 44621 | I25: ='Data Sheet'!H$16 -> 44986 | J25: ='Data Sheet'!I$16 -> 45352 | ... L25: ='Data Sheet'!K$16 -> 46082
B27: Total Liabilities | C27: ='Data Sheet'!B61/'Data Sheet'!B$61 -> 1 | D27: ='Data Sheet'!C61/'Data Sheet'!C$61 -> 1 | E27: ='Data Sheet'!D61/'Data Sheet'!D$61 -> 1 | F27: ='Data Sheet'!E61/'Data Sheet'!E$61 -> 1 | G27: ='Data Sheet'!F61/'Data Sheet'!F$61 -> 1 | H27: ='Data Sheet'!G61/'Data Sheet'!G$61 -> 1 | I27: ='Data Sheet'!H61/'Data Sheet'!H$61 -> 1 | J27: ='Data Sheet'!I61/'Data Sheet'!I$61 -> 1 | ... L27: ='Data Sheet'!K61/'Data Sheet'!K$61 -> 1
B28: ='Data Sheet'!A57 -> Equity Share Capital | C28: ='Data Sheet'!B57/'Data Sheet'!B$61 -> 0.0027320244 | D28: ='Data Sheet'!C57/'Data Sheet'!C$61 -> 0.0039818434 | E28: ='Data Sheet'!D57/'Data Sheet'!D$61 -> 0.0033603271 | F28: ='Data Sheet'!E57/'Data Sheet'!E$61 -> 0.0033430689 | G28: ='Data Sheet'!F57/'Data Sheet'!F$61 -> 0.0033642888 | H28: ='Data Sheet'!G57/'Data Sheet'!G$61 -> 0.0032252825 | I28: ='Data Sheet'!H57/'Data Sheet'!H$61 -> 0.0027266097 | J28: ='Data Sheet'!I57/'Data Sheet'!I$61 -> 0.00237302 | ... L28: ='Data Sheet'!K57/'Data Sheet'!K$61 -> 0.0017686851
B29: ='Data Sheet'!A58 -> Reserves | C29: ='Data Sheet'!B58/'Data Sheet'!B$61 -> 0.25885712 | D29: ='Data Sheet'!C58/'Data Sheet'!C$61 -> 0.26569088 | E29: ='Data Sheet'!D58/'Data Sheet'!D$61 -> 0.24361754 | F29: ='Data Sheet'!E58/'Data Sheet'!E$61 -> 0.23784668 | G29: ='Data Sheet'!F58/'Data Sheet'!F$61 -> 0.24869672 | H29: ='Data Sheet'!G58/'Data Sheet'!G$61 -> 0.27012901 | I29: ='Data Sheet'!H58/'Data Sheet'!H$61 -> 0.27319454 | J29: ='Data Sheet'!I58/'Data Sheet'!I$61 -> 0.27962015 | ... L29: ='Data Sheet'!K58/'Data Sheet'!K$61 -> 0.29279174
B30: ='Data Sheet'!A59 -> Borrowings | C30: ='Data Sheet'!B59/'Data Sheet'!B$61 -> 0.42835683 | D30: ='Data Sheet'!C59/'Data Sheet'!C$61 -> 0.40990254 | E30: ='Data Sheet'!D59/'Data Sheet'!D$61 -> 0.43763319 | F30: ='Data Sheet'!E59/'Data Sheet'!E$61 -> 0.49537763 | G30: ='Data Sheet'!F59/'Data Sheet'!F$61 -> 0.48873115 | H30: ='Data Sheet'!G59/'Data Sheet'!G$61 -> 0.45017635 | I30: ='Data Sheet'!H59/'Data Sheet'!H$61 -> 0.45352281 | J30: ='Data Sheet'!I59/'Data Sheet'!I$61 -> 0.46287523 | ... L30: ='Data Sheet'!K59/'Data Sheet'!K$61 -> 0.43326773
B31: ='Data Sheet'!A60 -> Other Liabilities | C31: ='Data Sheet'!B60/'Data Sheet'!B$61 -> 0.31006281 | D31: ='Data Sheet'!C60/'Data Sheet'!C$61 -> 0.32042473 | E31: ='Data Sheet'!D60/'Data Sheet'!D$61 -> 0.31538276 | F31: ='Data Sheet'!E60/'Data Sheet'!E$61 -> 0.26343262 | G31: ='Data Sheet'!F60/'Data Sheet'!F$61 -> 0.25921391 | H31: ='Data Sheet'!G60/'Data Sheet'!G$61 -> 0.27647516 | I31: ='Data Sheet'!H60/'Data Sheet'!H$61 -> 0.27055604 | J31: ='Data Sheet'!I60/'Data Sheet'!I$61 -> 0.25512734 | ... L31: ='Data Sheet'!K60/'Data Sheet'!K$61 -> 0.27217184
B33: Total Assets | C33: ='Data Sheet'!B66/'Data Sheet'!B$66 -> 1 | D33: ='Data Sheet'!C66/'Data Sheet'!C$66 -> 1 | E33: ='Data Sheet'!D66/'Data Sheet'!D$66 -> 1 | F33: ='Data Sheet'!E66/'Data Sheet'!E$66 -> 1 | G33: ='Data Sheet'!F66/'Data Sheet'!F$66 -> 1 | H33: ='Data Sheet'!G66/'Data Sheet'!G$66 -> 1 | I33: ='Data Sheet'!H66/'Data Sheet'!H$66 -> 1 | J33: ='Data Sheet'!I66/'Data Sheet'!I$66 -> 1 | ... L33: ='Data Sheet'!K66/'Data Sheet'!K$66 -> 1
B34: Fixed Assets Net Block | C34: ='Data Sheet'!B62/'Data Sheet'!B$66 -> 0.1843809 | D34: ='Data Sheet'!C62/'Data Sheet'!C$66 -> 0.19199378 | E34: ='Data Sheet'!D62/'Data Sheet'!D$66 -> 0.17903008 | F34: ='Data Sheet'!E62/'Data Sheet'!E$66 -> 0.17915591 | G34: ='Data Sheet'!F62/'Data Sheet'!F$66 -> 0.12960089 | H34: ='Data Sheet'!G62/'Data Sheet'!G$66 -> 0.15092698 | I34: ='Data Sheet'!H62/'Data Sheet'!H$66 -> 0.13285491 | J34: ='Data Sheet'!I62/'Data Sheet'!I$66 -> 0.11983964 | ... L34: ='Data Sheet'!K62/'Data Sheet'!K$66 -> 0.1216849
B35: ='Data Sheet'!A63 -> Capital Work in Progress | C35: ='Data Sheet'!B63/'Data Sheet'!B$66 -> 0.037589494 | D35: ='Data Sheet'!C63/'Data Sheet'!C$66 -> 0.031304769 | E35: ='Data Sheet'!D63/'Data Sheet'!D$66 -> 0.029402862 | F35: ='Data Sheet'!E63/'Data Sheet'!E$66 -> 0.041371986 | G35: ='Data Sheet'!F63/'Data Sheet'!F$66 -> 0.047724407 | H35: ='Data Sheet'!G63/'Data Sheet'!G$66 -> 0.038883217 | I35: ='Data Sheet'!H63/'Data Sheet'!H$66 -> 0.019428929 | J35: ='Data Sheet'!I63/'Data Sheet'!I$66 -> 0.034249027 | ... L35: ='Data Sheet'!K63/'Data Sheet'!K$66 -> 0.024489486
B36: ='Data Sheet'!A64 -> Investments | C36: ='Data Sheet'!B64/'Data Sheet'!B$66 -> 0.12880046 | D36: ='Data Sheet'!C64/'Data Sheet'!C$66 -> 0.11746071 | E36: ='Data Sheet'!D64/'Data Sheet'!D$66 -> 0.11284275 | F36: ='Data Sheet'!E64/'Data Sheet'!E$66 -> 0.11592121 | G36: ='Data Sheet'!F64/'Data Sheet'!F$66 -> 0.17444595 | H36: ='Data Sheet'!G64/'Data Sheet'!G$66 -> 0.17437409 | I36: ='Data Sheet'!H64/'Data Sheet'!H$66 -> 0.17266243 | J36: ='Data Sheet'!I64/'Data Sheet'!I$66 -> 0.14999872 | ... L36: ='Data Sheet'!K64/'Data Sheet'!K$66 -> 0.12758579
B37: ='Data Sheet'!A65 -> Other Assets | C37: ='Data Sheet'!B74/'Data Sheet'!B66 -> 0 | D37: ='Data Sheet'!C74/'Data Sheet'!C66 -> 0 | E37: ='Data Sheet'!D74/'Data Sheet'!D66 -> 0 | F37: ='Data Sheet'!E74/'Data Sheet'!E66 -> 0 | G37: ='Data Sheet'!F74/'Data Sheet'!F66 -> 0 | H37: ='Data Sheet'!G74/'Data Sheet'!G66 -> 0 | I37: ='Data Sheet'!H74/'Data Sheet'!H66 -> 0 | J37: ='Data Sheet'!I74/'Data Sheet'!I66 -> 0 | ... L37: ='Data Sheet'!K74/'Data Sheet'!K66 -> 0
B38: ='Data Sheet'!A67 -> Receivables | C38: ='Data Sheet'!B67/'Data Sheet'!B$66 -> 0.063240655 | D38: ='Data Sheet'!C67/'Data Sheet'!C$66 -> 0.062257551 | E38: ='Data Sheet'!D67/'Data Sheet'!D$66 -> 0.05360463 | F38: ='Data Sheet'!E67/'Data Sheet'!E$66 -> 0.041806464 | G38: ='Data Sheet'!F67/'Data Sheet'!F$66 -> 0.036419184 | H38: ='Data Sheet'!G67/'Data Sheet'!G$66 -> 0.036974731 | I38: ='Data Sheet'!H67/'Data Sheet'!H$66 -> 0.034403254 | J38: ='Data Sheet'!I67/'Data Sheet'!I$66 -> 0.031778018 | ... L38: ='Data Sheet'!K67/'Data Sheet'!K$66 -> 0.028678644
B39: ='Data Sheet'!A68 -> Inventory | C39: ='Data Sheet'!B68/'Data Sheet'!B$66 -> 0.078060351 | D39: ='Data Sheet'!C68/'Data Sheet'!C$66 -> 0.068461307 | E39: ='Data Sheet'!D68/'Data Sheet'!D$66 -> 0.075360278 | F39: ='Data Sheet'!E68/'Data Sheet'!E$66 -> 0.067054479 | G39: ='Data Sheet'!F68/'Data Sheet'!F$66 -> 0.058284031 | H39: ='Data Sheet'!G68/'Data Sheet'!G$66 -> 0.067266863 | I39: ='Data Sheet'!H68/'Data Sheet'!H$66 -> 0.082508089 | J39: ='Data Sheet'!I68/'Data Sheet'!I$66 -> 0.079200075 | ... L39: ='Data Sheet'!K68/'Data Sheet'!K$66 -> 0.069747575
B40: ='Data Sheet'!A69 -> Cash & Bank | C40: ='Data Sheet'!B69/'Data Sheet'!B$66 -> 0.040883735 | D40: ='Data Sheet'!C69/'Data Sheet'!C$66 -> 0.048016778 | E40: ='Data Sheet'!D69/'Data Sheet'!D$66 -> 0.053956723 | F40: ='Data Sheet'!E69/'Data Sheet'!E$66 -> 0.047738299 | G40: ='Data Sheet'!F69/'Data Sheet'!F$66 -> 0.077906018 | H40: ='Data Sheet'!G69/'Data Sheet'!G$66 -> 0.064494048 | I40: ='Data Sheet'!H69/'Data Sheet'!H$66 -> 0.055183251 | J40: ='Data Sheet'!I69/'Data Sheet'!I$66 -> 0.051179693 | ... L40: ='Data Sheet'!K69/'Data Sheet'!K$66 -> 0.10118208

Sheet Data Sheet
A1: COMPANY NAME | B1: MAHINDRA & MAHINDRA LTD | E1: =IF(B2<>B3, "A NEW VERSION OF THE WORKSHEET IS AVAILABLE", "")
A2: LATEST VERSION | B2: 2.1 | E2: PLEASE DO NOT MAKE ANY CHANGES TO THIS SHEET
A3: CURRENT VERSION | B3: 2.1
A5: META
A6: Number of shares | B6: =IF(B9>0, B9/B8, 0) -> 124.32242
A7: Face Value | B7: 5
A8: Current Price | B8: 3055
A9: Market Capitalization | B9: 379805
A15: PROFIT & LOSS
A16: Report Date | B16: 42795 | C16: 43160 | D16: 43525 | E16: 43891 | F16: 44256 | G16: 44621 | H16: 44986 | I16: 45352 | J16: 45717 | K16: 46082
A17: Sales | B17: 83773 | C17: 92094 | D17: 104721 | E17: 75382 | F17: 74278 | G17: 90171 | H17: 121362 | I17: 139078 | J17: 159211 | K17: 198639
A18: Raw Material Cost | B18: 50263.8 | C18: 53414.52 | D18: 59690.97 | E18: 38444.82 | F18: 38624.56 | G18: 51397.47 | H18: 74030.82 | I18: 83446.8 | J18: 95526.6 | K18: 123156.18
A19: Change in Inventory | B19: 0 | C19: 0 | D19: 0 | E19: 0 | F19: 0 | G19: 0 | H19: 0 | I19: 0 | J19: 0 | K19: 0
A20: Power and Fuel | B20: 0 | C20: 0 | D20: 0 | E20: 0 | F20: 0 | G20: 0 | H20: 0 | I20: 0 | J20: 0 | K20: 0
A21: Other Mfr. Exp | B21: 4188.65 | C21: 4604.7 | D21: 5236.05 | E21: 3769.1 | F21: 2971.12 | G21: 3606.84 | H21: 4854.48 | I21: 4172.34 | J21: 4776.33 | K21: 5959.17
A22: Employee Cost | B22: 9215.03 | C22: 10130.34 | D22: 11519.31 | E22: 8292.02 | F22: 8170.58 | G22: 8115.39 | H22: 9708.96 | I22: 11126.24 | J22: 11144.77 | K22: 11918.34
A23: Selling and admin | B23: 0 | C23: 0 | D23: 0 | E23: 0 | F23: 0 | G23: 0 | H23: 0 | I23: 0 | J23: 0 | K23: 0
A24: Other Expenses | B24: 9215.03 | C24: 11051.28 | D24: 12566.52 | E24: 15076.4 | F24: 13370.04 | G24: 11722.23 | H24: 12136.2 | I24: 15298.58 | J24: 17513.21 | K24: 19863.9
A25: Other Income | B25: 2077 | C25: 4366 | D25: 2676 | E25: 885 | F25: 1152 | G25: 3204 | H25: 3922 | I25: 3298 | J25: 3718 | K25: 5118
A26: Depreciation | B26: 2813 | C26: 3280 | D26: 3991 | E26: 3367 | F26: 3378 | G26: 3508 | H26: 4357 | I26: 4724 | J26: 6074 | K26: 7322
A27: Interest | B27: 3648 | C27: 3987 | D27: 5021 | E27: 6021 | F27: 6102 | G27: 5018 | H27: 5830 | I27: 7488 | J27: 9083 | K27: 9591
... A32: EBITDA | B32: 0 | C32: 0 | D32: 0 | E32: 0 | F32: 0 | G32: 0 | H32: 0 | I32: 0 | J32: 0 | K32: 0
B33: =B30+B29+B27+B26 -> 16862 | C33: =C30+C29+C27+C26 -> 25551 | D33: =D30+D29+D27+D26 -> 23900 | E33: =E30+E29+E27+E26 -> 10722 | F33: =F30+F29+F27+F26 -> 14150 | G33: =G30+G29+G27+G26 -> 25141 | H33: =H30+H29+H27+H26 -> 35621 | I33: =I30+I29+I27+I26 -> 40460 | ... K33: =K30+K29+K27+K26 -> 60720
A40: Quarters
A41: Report Date | B41: 45352 | C41: 45444 | D41: 45536 | E41: 45627 | F41: 45717 | G41: 45809 | H41: 45901 | I41: 45992 | J41: 46082 | K41: 46174
A42: Sales | B42: 35452 | C42: 37218 | D42: 37924 | E42: 41470 | F42: 42599 | G42: 45529 | H42: 46106 | I42: 52100 | J42: 54982 | K42: 58188
A43: Expenses | B43: 28848 | C43: 29975 | D43: 30790 | E43: 33239 | F43: 34658 | G43: 37117 | H43: 37166 | I43: 41939 | J43: 44855 | K43: 47360
A44: Other Income | B44: 750 | C44: 733 | D44: 1126 | E44: 719 | F44: 1110 | G44: 1210 | H44: 1134 | I44: 976 | J44: 1137 | K44: 1121
A45: Depreciation | B45: 1335 | C45: 1248 | D45: 1302 | E45: 1495 | F45: 2029 | G45: 1548 | H45: 1669 | I45: 2163 | J45: 1943 | K45: 1760
A46: Interest | B46: 1989 | C46: 2108 | D46: 2217 | E46: 2362 | F46: 2397 | G46: 2431 | H46: 2347 | I46: 2405 | J46: 2407 | K46: 2560
A47: Profit before tax | B47: 4030 | C47: 4621 | D47: 4740 | E47: 5092 | F47: 4627 | G47: 5644 | H47: 6058 | I47: 6569 | J47: 6914 | K47: 7628
A48: Tax | B48: 4030 | C48: 4621 | D48: 4740 | E48: 5092 | F48: 4627 | G48: 5644 | H48: 6058 | I48: 6569 | J48: 6914 | K48: 7628
A49: Net profit | B49: 3125 | C49: 3546 | D49: 3361 | E49: 3624 | F49: 3542 | G49: 4377 | H49: 3964 | I49: 5021 | J49: 5260 | K49: 5998
A50: Operating Profit | B50: 6604 | C50: 7243 | D50: 7133 | E50: 8231 | F50: 7942 | G50: 8412 | H50: 8940 | I50: 10160 | J50: 10127 | K50: 10827
A55: BALANCE SHEET
A56: Report Date | B56: 42795 | C56: 43160 | D56: 43525 | E56: 43891 | F56: 44256 | G56: 44621 | H56: 44986 | I56: 45352 | J56: 45717 | K56: 46082
A57: Equity Share Capital | B57: 311 | C57: 543 | D57: 544 | E57: 554 | F57: 555 | G57: 556 | H57: 557 | I57: 557 | J57: 558 | K57: 559
A58: Reserves | B58: 29467 | C58: 36232 | D58: 39439 | E58: 39415 | F58: 41027 | G58: 46567 | H58: 55809 | I58: 65633 | J58: 76481 | K58: 92538
A59: Borrowings | B59: 48762 | C59: 55898 | D59: 70848 | E59: 82092 | F59: 80625 | G59: 77605 | H59: 92647 | I59: 108647 | J59: 129025 | K59: 136936
A60: Other Liabilities | B60: 35296 | C60: 43696 | D60: 51057 | E60: 43655 | F60: 42762 | G60: 47661 | H60: 55270 | I60: 59884 | J60: 69950 | K60: 86021
A61: Total | B61: 113835 | C61: 136369 | D61: 161889 | E61: 165716 | F61: 164968 | G61: 172388 | H61: 204283 | I61: 234722 | J61: 276013 | K61: 316054
A62: Net Block | B62: 20989 | C62: 26182 | D62: 28983 | E62: 29689 | F62: 21380 | G62: 26018 | H62: 27140 | I62: 28129 | J62: 34636 | K62: 38459
A63: Capital Work in Progress | B63: 4279 | C63: 4269 | D63: 4760 | E63: 6856 | F63: 7873 | G63: 6703 | H63: 3969 | I63: 8039 | J63: 8298 | K63: 7740
A64: Investments | B64: 14662 | C64: 16018 | D64: 18268 | E64: 19210 | F64: 28778 | G64: 30060 | H64: 35272 | I64: 35208 | J64: 41309 | K64: 40324
A65: Other Assets | B65: 73905 | C65: 89900 | D65: 109878 | E65: 109960 | F65: 106938 | G65: 109607 | H65: 137902 | I65: 163345 | J65: 191771 | K65: 229531
A66: Total | B66: 113835 | C66: 136369 | D66: 161889 | E66: 165716 | F66: 164968 | G66: 172388 | H66: 204283 | I66: 234722 | J66: 276013 | K66: 316054
A67: Receivables | B67: 7199 | C67: 8490 | D67: 8678 | E67: 6928 | F67: 6008 | G67: 6374 | H67: 7028 | I67: 7459 | J67: 8280 | K67: 9064
... A70: No. of Equity Shares | B70: 622000000 | C70: 1086000000 | D70: 1088000000 | E70: 1108000000 | F70: 1110000000 | G70: 1112000000 | H70: 1114000000 | I70: 1114000000 | J70: 1116000000 | K70: 1118000000
A71: New Bonus Shares
A72: Face value | B72: 5 | C72: 5 | D72: 5 | E72: 5 | F72: 5 | G72: 5 | H72: 5 | I72: 5 | J72: 5 | K72: 5
B73: 0 | C73: 0 | D73: 0 | E73: 0 | F73: 0 | G73: 0 | H73: 0 | I73: 0 | J73: 0 | K73: 0
B74: 0 | C74: 0 | D74: 0 | E74: 0 | F74: 0 | G74: 0 | H74: 0 | I74: 0 | J74: 0 | K74: 0
A75: Other Assets | B75: =B65-SUM(B67:B69) -> 53166 | C75: =C65-SUM(C67:C69) -> 65526 | D75: =D65-SUM(D67:D69) -> 80265 | E75: =E65-SUM(E67:E69) -> 84009 | F75: =F65-SUM(F67:F69) -> 78463 | G75: =G65-SUM(G67:G69) -> 80519 | H75: =H65-SUM(H67:H69) -> 102746 | I75: =I65-SUM(I67:I69) -> 125283 | ... K75: =K65-SUM(K67:K69) -> 166444
A80: CASH FLOW:
A81: Report Date | B81: 42795 | C81: 43160 | D81: 43525 | E81: 43891 | F81: 44256 | G81: 44621 | H81: 44986 | I81: 45352 | J81: 45717 | K81: 46082
A82: Cash from Operating Activity | B82: 183 | C82: 682 | D82: -4347 | E82: -1457 | F82: 17909 | G82: 9248 | H82: -7074 | I82: -5630 | J82: 3176 | K82: 11657
A83: Cash from Investing Activity | B83: -5875 | C83: -5467 | D83: -7174 | E83: -6870 | F83: -19686 | G83: -3252 | H83: -8866 | I83: -5615 | J83: -18616 | K83: -17680
A84: Cash from Financing Activity | B84: 6108 | C84: 6314 | D84: 13194 | E84: 6933 | F84: 406 | G84: -5883 | H84: 15946 | I84: 12281 | J84: 15834 | K84: 5391
A85: Net Cash Flow | B85: 416 | C85: 1529 | D85: 1672 | E85: -1394 | F85: -1370 | G85: 113 | H85: 6 | I85: 1037 | J85: 394 | K85: -632
A90: PRICE: | B90: 661.03 | C90: 732.55 | D90: 649.7 | E90: 457.05 | F90: 806.4 | G90: 732.3 | H90: 1268.6 | I90: 1960.1 | J90: 2585.1 | K90: 3397.4
A92: DERIVED:
A93: Adjusted Equity Shares in Cr | B93: 133.85 | C93: 133.85 | D93: 133.85 | E93: 133.85 | F93: 133.85 | G93: 133.85 | H93: 133.85 | I93: 133.85 | J93: 133.85 | K93: 133.85

Sheet Cash Flow Statement
B2: Cash Flow Statement - MAHINDRA & MAHINDRA LTD
B4: Particulars | C4: 42064 | D4: 42430 | E4: 42795 | F4: 43160 | G4: 43525 | H4: 43891 | I4: 44256 | J4: 44621 | K4: 44986 | L4: 45352 | M4: 45717 | N4: 46082
B6: Cash from Operating Activity - | C6: 1055 | D6: 2385 | E6: 183 | F6: 682 | G6: -4347 | H6: -1457 | I6: 17909 | J6: 9248 | K6: -7074 | L6: -5630 | M6: 3176 | N6: 11657
B7: Profit from operations | C7: 6454 | D7: 7595 | E7: 7911 | F7: 10159 | G7: 11112 | H7: 7774 | I7: 7588 | J7: 10515 | K7: 15642 | L7: 17541 | M7: 22050 | N7: 28938
B8: Receivables | C8: -575 | D8: 177 | E8: -8609 | F8: -11918 | G8: -13712 | H8: -1516 | I8: 4896 | J8: -2506 | K8: -21702 | L8: -21777 | M8: -20952 | N8: -19186
B9: Inventory | C9: -62 | D9: -1113 | E9: 241 | F9: -256 | G9: -2276 | H9: 1316 | I9: 226 | J9: -2173 | K9: -5252 | L9: -1753 | M9: -1646 | N9: -593
B10: Payables | C10: 1169 | D10: 1939 | E10: 2645 | F10: 5361 | G10: 3466 | H10: -6775 | I10: 7049 | J10: 4972 | K10: 7013 | L10: 4354 | M10: 8485 | N10: 8763
B11: Working capital changes | C11: -3698 | D11: -3238 | E11: -5724 | F11: -6813 | G11: -12522 | H11: -6974 | I11: 12171 | J11: 293 | K11: -19941 | L11: -19175 | M11: -14113 | N11: -11016
B12: Direct taxes | C12: -1701 | D12: -1973 | E12: -2005 | F12: -2664 | G12: -2937 | H12: -2257 | I12: -1850 | J12: -1560 | K12: -2775 | L12: -3996 | M12: -4761 | N12: -6265
B13: Cash from Investing Activity - | C13: -4357 | D13: -5506 | E13: -5875 | F13: -5467 | G13: -7174 | H13: -6870 | I13: -19686 | J13: -3252 | K13: -8866 | L13: -5615 | M13: -18616 | N13: -17680
B14: Fixed assets purchased | C14: -4759 | D14: -4172 | E14: -5026 | F14: -5906 | G14: -7340 | H14: -6896 | I14: -5989 | J14: -6040 | K14: -6305 | L14: -9946 | M14: -10392 | N14: -9605
B15: Fixed assets sold | C15: 43 | D15: 59 | E15: 63 | F15: 115 | G15: 142 | H15: 102 | I15: 1364 | J15: 120 | K15: 138 | L15: 273 | M15: 583 | N15: 493
B16: Investments purchased | C16: -80047 | D16: -87898 | E16: -132173 | F16: -155159 | G16: -196474 | H16: -198568 | I16: -120055 | J16: -87740 | K16: -50165 | L16: -49927 | M16: -90595 | N16: -141518
... B32: Net Cash Flow | C32: -1633 | D32: -154 | E32: 416 | F32: 1529 | G32: 1672 | H32: -1394 | I32: -1370 | J32: 113 | K32: 6 | L32: 1037 | M32: 394 | N32: -632

Sheet Historical FS
B2: ="Historical Financial Statement - "&'Data Sheet'!$B$1 -> Historical Financial Statement - MAHINDRA & MAHINDRA LTD
B3: Particulars | C3: ='Data Sheet'!B56 -> 42795 | D3: ='Data Sheet'!C56 -> 43160 | E3: ='Data Sheet'!D56 -> 43525 | F3: ='Data Sheet'!E56 -> 43891 | G3: ='Data Sheet'!F56 -> 44256 | H3: ='Data Sheet'!G56 -> 44621 | I3: ='Data Sheet'!H56 -> 44986 | J3: ='Data Sheet'!I56 -> 45352 | ... L3: ='Data Sheet'!K56 -> 46082 | M3: LTM
A5: # | B5: Income Statement
B7: Sales | C7: ='Data Sheet'!B17 -> 83773 | D7: ='Data Sheet'!C17 -> 92094 | E7: ='Data Sheet'!D17 -> 104721 | F7: ='Data Sheet'!E17 -> 75382 | G7: ='Data Sheet'!F17 -> 74278 | H7: ='Data Sheet'!G17 -> 90171 | I7: ='Data Sheet'!H17 -> 121362 | J7: ='Data Sheet'!I17 -> 139078 | ... L7: ='Data Sheet'!K17 -> 198639
B8: Sales Growth | C8: - | D8: =D7/C7-1 -> 0.099327946 | E8: =E7/D7-1 -> 0.13710991 | F8: =F7/E7-1 -> -0.28016348 | G8: =G7/F7-1 -> -0.014645406 | H8: =H7/G7-1 -> 0.21396645 | I8: =I7/H7-1 -> 0.34590944 | J8: =J7/I7-1 -> 0.1459765 | K8: =K7/J7-1 -> 0.14476049 | L8: =L7/K7-1 -> 0.24764621
B10: Cost of Goods Sold | C10: =SUM('Data Sheet'!B18,'Data Sheet'!B20:B22)-'Data Sheet'!B19 -> 63667.48 | D10: =SUM('Data Sheet'!C18,'Data Sheet'!C20:C22)-'Data Sheet'!C19 -> 68149.56 | E10: =SUM('Data Sheet'!D18,'Data Sheet'!D20:D22)-'Data Sheet'!D19 -> 76446.33 | F10: =SUM('Data Sheet'!E18,'Data Sheet'!E20:E22)-'Data Sheet'!E19 -> 50505.94 | G10: =SUM('Data Sheet'!F18,'Data Sheet'!F20:F22)-'Data Sheet'!F19 -> 49766.26 | H10: =SUM('Data Sheet'!G18,'Data Sheet'!G20:G22)-'Data Sheet'!G19 -> 63119.7 | I10: =SUM('Data Sheet'!H18,'Data Sheet'!H20:H22)-'Data Sheet'!H19 -> 88594.26 | J10: =SUM('Data Sheet'!I18,'Data Sheet'!I20:I22)-'Data Sheet'!I19 -> 98745.38 | ... L10: =SUM('Data Sheet'!K18,'Data Sheet'!K20:K22)-'Data Sheet'!K19 -> 141033.69
B11: COGS % Sales | C11: =C10/C7 -> 0.76 | D11: =D10/D7 -> 0.74 | E11: =E10/E7 -> 0.73 | F11: =F10/F7 -> 0.67 | G11: =G10/G7 -> 0.67 | H11: =H10/H7 -> 0.7 | I11: =I10/I7 -> 0.73 | J11: =J10/J7 -> 0.71 | ... L11: =L10/L7 -> 0.71
B13: Gross Profit | C13: =C7-C10 -> 20105.52 | D13: =D7-D10 -> 23944.44 | E13: =E7-E10 -> 28274.67 | F13: =F7-F10 -> 24876.06 | G13: =G7-G10 -> 24511.74 | H13: =H7-H10 -> 27051.3 | I13: =I7-I10 -> 32767.74 | J13: =J7-J10 -> 40332.62 | ... L13: =L7-L10 -> 57605.31
B14: Gross Profit % Sales | C14: =C13/C7 -> 0.24 | D14: =D13/D7 -> 0.26 | E14: =E13/E7 -> 0.27 | F14: =F13/F7 -> 0.33 | G14: =G13/G7 -> 0.33 | H14: =H13/H7 -> 0.3 | I14: =I13/I7 -> 0.27 | J14: =J13/J7 -> 0.29 | ... L14: =L13/L7 -> 0.29
B16: Selling % General Expenses | C16: ='Data Sheet'!B23 -> 0 | D16: ='Data Sheet'!C23 -> 0 | E16: ='Data Sheet'!D23 -> 0 | F16: ='Data Sheet'!E23 -> 0 | G16: ='Data Sheet'!F23 -> 0 | H16: ='Data Sheet'!G23 -> 0 | I16: ='Data Sheet'!H23 -> 0 | J16: ='Data Sheet'!I23 -> 0 | ... L16: ='Data Sheet'!K23 -> 0
B17: S&G % Sales | C17: =C16/C7 -> 0 | D17: =D16/D7 -> 0 | E17: =E16/E7 -> 0 | F17: =F16/F7 -> 0 | G17: =G16/G7 -> 0 | H17: =H16/H7 -> 0 | I17: =I16/I7 -> 0 | J17: =J16/J7 -> 0 | ... L17: =L16/L7 -> 0
B19: EBITDA | C19: =C13-C16 -> 20105.52 | D19: =D13-D16 -> 23944.44 | E19: =E13-E16 -> 28274.67 | F19: =F13-F16 -> 24876.06 | G19: =G13-G16 -> 24511.74 | H19: =H13-H16 -> 27051.3 | I19: =I13-I16 -> 32767.74 | J19: =J13-J16 -> 40332.62 | ... L19: =L13-L16 -> 57605.31
B20: EBITDA % Sales | C20: =C19/C7 -> 0.24 | D20: =D19/D7 -> 0.26 | E20: =E19/E7 -> 0.27 | F20: =F19/F7 -> 0.33 | G20: =G19/G7 -> 0.33 | H20: =H19/H7 -> 0.3 | I20: =I19/I7 -> 0.27 | J20: =J19/J7 -> 0.29 | ... L20: =L19/L7 -> 0.29
B22: Depreciation | C22: ='Data Sheet'!B26 -> 2813 | D22: ='Data Sheet'!C26 -> 3280 | E22: ='Data Sheet'!D26 -> 3991 | F22: ='Data Sheet'!E26 -> 3367 | G22: ='Data Sheet'!F26 -> 3378 | H22: ='Data Sheet'!G26 -> 3508 | I22: ='Data Sheet'!H26 -> 4357 | J22: ='Data Sheet'!I26 -> 4724 | ... L22: ='Data Sheet'!K26 -> 7322
B23: Depreciation % Sales | C23: =C22/C7 -> 0.033578838 | D23: =D22/D7 -> 0.035615784 | E23: =E22/E7 -> 0.03811079 | F23: =F22/F7 -> 0.044665835 | G23: =G22/G7 -> 0.0454778 | H23: =H22/H7 -> 0.03890386 | I23: =I22/I7 -> 0.035900859 | J23: =J22/J7 -> 0.033966551 | ... L23: =L22/L7 -> 0.036860838
B25: EBIT | C25: =C19-C22 -> 17292.52 | D25: =D19-D22 -> 20664.44 | E25: =E19-E22 -> 24283.67 | F25: =F19-F22 -> 21509.06 | G25: =G19-G22 -> 21133.74 | H25: =H19-H22 -> 23543.3 | I25: =I19-I22 -> 28410.74 | J25: =J19-J22 -> 35608.62 | ... L25: =L19-L22 -> 50283.31
B26: EBIT % Sales | C26: =C25/C7 -> 0.20642116 | D26: =D25/D7 -> 0.22438422 | E26: =E25/E7 -> 0.23188921 | F26: =F25/F7 -> 0.28533416 | G26: =G25/G7 -> 0.2845222 | H26: =H25/H7 -> 0.26109614 | I26: =I25/I7 -> 0.23409914 | J26: =J25/J7 -> 0.25603345 | ... L26: =L25/L7 -> 0.25313916
B28: Interest | C28: ='Data Sheet'!B27 -> 3648 | D28: ='Data Sheet'!C27 -> 3987 | E28: ='Data Sheet'!D27 -> 5021 | F28: ='Data Sheet'!E27 -> 6021 | G28: ='Data Sheet'!F27 -> 6102 | H28: ='Data Sheet'!G27 -> 5018 | I28: ='Data Sheet'!H27 -> 5830 | J28: ='Data Sheet'!I27 -> 7488 | ... L28: ='Data Sheet'!K27 -> 9591
B29: Interest % Sales | C29: =C28/C7 -> 0.04354625 | D29: =D28/D7 -> 0.043292723 | E29: =E28/E7 -> 0.047946448 | F29: =F28/F7 -> 0.079873179 | G29: =G28/G7 -> 0.082150839 | H29: =H28/H7 -> 0.055649821 | I29: =I28/I7 -> 0.048038101 | J29: =J28/J7 -> 0.053840291 | ... L29: =L28/L7 -> 0.04828357
B31: Earning Before Tax | C31: =C25-C28 -> 13644.52 | D31: =D25-D28 -> 16677.44 | E31: =E25-E28 -> 19262.67 | F31: =F25-F28 -> 15488.06 | G31: =G25-G28 -> 15031.74 | H31: =H25-H28 -> 18525.3 | I31: =I25-I28 -> 22580.74 | J31: =J25-J28 -> 28120.62 | ... L31: =L25-L28 -> 40692.31
B32: EBT % Sales | C32: =C31/C7 -> 0.16287491 | D32: =D31/D7 -> 0.18109149 | E32: =E31/E7 -> 0.18394276 | F32: =F31/F7 -> 0.20546099 | G32: =G31/G7 -> 0.20237136 | H32: =H31/H7 -> 0.20544632 | I32: =I31/I7 -> 0.18606104 | J32: =J31/J7 -> 0.20219316 | ... L32: =L31/L7 -> 0.20485559
B34: Tax Rate | C34: ='Data Sheet'!B29 -> 6350 | D34: ='Data Sheet'!C29 -> 10326 | E34: ='Data Sheet'!D29 -> 8871 | F34: ='Data Sheet'!E29 -> 1655 | G34: ='Data Sheet'!F29 -> 3158 | H34: ='Data Sheet'!G29 -> 9362 | I34: ='Data Sheet'!H29 -> 14060 | J34: ='Data Sheet'!I29 -> 15978 | ... L34: ='Data Sheet'!K29 -> 25185
B35: Effective Tax Rate | C35: =C34/C31 -> 0.4653883 | D35: =D34/D31 -> 0.61915978 | E35: =E34/E31 -> 0.46052806 | F35: =F34/F31 -> 0.10685651 | G35: =G34/G31 -> 0.21008879 | H35: =H34/H31 -> 0.50536294 | I35: =I34/I31 -> 0.62265453 | J35: =J34/J31 -> 0.56819515 | ... L35: =L34/L31 -> 0.61891301
B37: Net Profit | C37: =C31-C34 -> 7294.52 | D37: =D31-D34 -> 6351.44 | E37: =E31-E34 -> 10391.67 | F37: =F31-F34 -> 13833.06 | G37: =G31-G34 -> 11873.74 | H37: =H31-H34 -> 9163.3 | I37: =I31-I34 -> 8520.74 | J37: =J31-J34 -> 12142.62 | ... L37: =L31-L34 -> 15507.31
B38: Net Profit % Sales | C38: =C37/C7 -> 0.087074833 | D38: =D37/D7 -> 0.068966925 | E38: =E37/E7 -> 0.099231959 | F38: =F37/F7 -> 0.18350614 | G38: =G37/G7 -> 0.15985541 | H38: =H37/H7 -> 0.10162136 | I38: =I37/I7 -> 0.070209291 | J38: =J37/J7 -> 0.087307985 | ... L38: =L37/L7 -> 0.078067801
B40: No. of Equity Shares | C40: ='Data Sheet'!B93 -> 133.85 | D40: ='Data Sheet'!C93 -> 133.85 | E40: ='Data Sheet'!D93 -> 133.85 | F40: ='Data Sheet'!E93 -> 133.85 | G40: ='Data Sheet'!F93 -> 133.85 | H40: ='Data Sheet'!G93 -> 133.85 | I40: ='Data Sheet'!H93 -> 133.85 | J40: ='Data Sheet'!I93 -> 133.85 | ... L40: ='Data Sheet'!K93 -> 133.85
B42: Earning per Share | C42: =C37/C40 -> 54.497721 | D42: =D37/D40 -> 47.451924 | E42: =E37/E40 -> 77.636683 | F42: =F37/F40 -> 103.34748 | G42: =G37/G40 -> 88.709301 | H42: =H37/H40 -> 68.45947 | I42: =I37/I40 -> 63.658872 | J42: =J37/J40 -> 90.718117 | ... L42: =L37/L40 -> 115.85588
B43: EPS Growth | C43: - | D43: =D42/C42-1 -> -0.12928609 | E43: =E42/D42-1 -> 0.63611244 | F43: =F42/E42-1 -> 0.33116814 | G43: =G42/F42-1 -> -0.14164039 | H43: =H42/G42-1 -> -0.2282718 | I43: =I42/H42-1 -> -0.070123209 | J43: =J42/I42-1 -> 0.42506637 | K43: =K42/J42-1 -> 0.11395234 | L43: =L42/K42-1 -> 0.14645616
B45: Dividend per Share | C45: ='Data Sheet'!B31/'Historical FS'!C40 -> 6.6583489 | D45: ='Data Sheet'!C31/'Historical FS'!D40 -> 6.5400075 | E45: ='Data Sheet'!D31/'Historical FS'!E40 -> 7.642062 | F45: ='Data Sheet'!E31/'Historical FS'!F40 -> -4.9163242 | G45: ='Data Sheet'!F31/'Historical FS'!G40 -> 6.0999626 | H45: ='Data Sheet'!G31/'Historical FS'!H40 -> 10.837505 | I45: ='Data Sheet'!H31/'Historical FS'!I40 -> 15.295629 | J45: ='Data Sheet'!I31/'Historical FS'!J40 -> 19.250654 | ... L45: ='Data Sheet'!K31/'Historical FS'!L40 -> 30.607695
B46: Dividend Payout Ratio | C46: =C45/C42 -> 0.12217665 | D46: =D45/D42 -> 0.13782386 | E46: =E45/E42 -> 0.098433649 | F46: =F45/F42 -> -0.047570819 | G46: =G45/G42 -> 0.068763507 | H46: =H45/H42 -> 0.15830541 | I46: =I45/I42 -> 0.24027491 | J46: =J45/J42 -> 0.21220297 | ... L46: =L45/L42 -> 0.26418766
B48: Retained Earnings | C48: =(1-C46) -> 0.87782335 | D48: =(1-D46) -> 0.86217614 | E48: =(1-E46) -> 0.90156635 | F48: =(1-F46) -> 1.0475708 | G48: =(1-G46) -> 0.93123649 | H48: =(1-H46) -> 0.84169459 | I48: =(1-I46) -> 0.75972509 | J48: =(1-J46) -> 0.78779703 | ... L48: =(1-L46) -> 0.73581234
B50: Balance Sheet
B51: ='Data Sheet'!A57 -> Equity Share Capital | C51: ='Data Sheet'!B57 -> 311 | D51: ='Data Sheet'!C57 -> 543 | E51: ='Data Sheet'!D57 -> 544 | F51: ='Data Sheet'!E57 -> 554 | G51: ='Data Sheet'!F57 -> 555 | H51: ='Data Sheet'!G57 -> 556 | I51: ='Data Sheet'!H57 -> 557 | ... L51: ='Data Sheet'!K57 -> 559
B52: ='Data Sheet'!A58 -> Reserves | C52: ='Data Sheet'!B58 -> 29467 | D52: ='Data Sheet'!C58 -> 36232 | E52: ='Data Sheet'!D58 -> 39439 | F52: ='Data Sheet'!E58 -> 39415 | G52: ='Data Sheet'!F58 -> 41027 | H52: ='Data Sheet'!G58 -> 46567 | I52: ='Data Sheet'!H58 -> 55809 | ... L52: ='Data Sheet'!K58 -> 92538
B53: ='Data Sheet'!A59 -> Borrowings | C53: ='Data Sheet'!B59 -> 48762 | D53: ='Data Sheet'!C59 -> 55898 | E53: ='Data Sheet'!D59 -> 70848 | F53: ='Data Sheet'!E59 -> 82092 | G53: ='Data Sheet'!F59 -> 80625 | H53: ='Data Sheet'!G59 -> 77605 | I53: ='Data Sheet'!H59 -> 92647 | ... L53: ='Data Sheet'!K59 -> 136936
B54: ='Data Sheet'!A60 -> Other Liabilities | C54: ='Data Sheet'!B60 -> 35296 | D54: ='Data Sheet'!C60 -> 43696 | E54: ='Data Sheet'!D60 -> 51057 | F54: ='Data Sheet'!E60 -> 43655 | G54: ='Data Sheet'!F60 -> 42762 | H54: ='Data Sheet'!G60 -> 47661 | I54: ='Data Sheet'!H60 -> 55270 | ... L54: ='Data Sheet'!K60 -> 86021
B55: Total Liabilities | C55: =SUM(C51:C54) -> 113836 | D55: =SUM(D51:D54) -> 136369 | E55: =SUM(E51:E54) -> 161888 | F55: =SUM(F51:F54) -> 165716 | G55: =SUM(G51:G54) -> 164969 | H55: =SUM(H51:H54) -> 172389 | I55: =SUM(I51:I54) -> 204283 | J55: =SUM(J51:J54) -> 234721 | ... L55: =SUM(L51:L54) -> 316054
B57: Fixed Asset Net Block | C57: ='Data Sheet'!B62 -> 20989 | D57: ='Data Sheet'!C62 -> 26182 | E57: ='Data Sheet'!D62 -> 28983 | F57: ='Data Sheet'!E62 -> 29689 | G57: ='Data Sheet'!F62 -> 21380 | H57: ='Data Sheet'!G62 -> 26018 | I57: ='Data Sheet'!H62 -> 27140 | J57: ='Data Sheet'!I62 -> 28129 | ... L57: ='Data Sheet'!K62 -> 38459
B58: ='Data Sheet'!A63 -> Capital Work in Progress | C58: ='Data Sheet'!B63 -> 4279 | D58: ='Data Sheet'!C63 -> 4269 | E58: ='Data Sheet'!D63 -> 4760 | F58: ='Data Sheet'!E63 -> 6856 | G58: ='Data Sheet'!F63 -> 7873 | H58: ='Data Sheet'!G63 -> 6703 | I58: ='Data Sheet'!H63 -> 3969 | ... L58: ='Data Sheet'!K63 -> 7740
B59: ='Data Sheet'!A64 -> Investments | C59: ='Data Sheet'!B64 -> 14662 | D59: ='Data Sheet'!C64 -> 16018 | E59: ='Data Sheet'!D64 -> 18268 | F59: ='Data Sheet'!E64 -> 19210 | G59: ='Data Sheet'!F64 -> 28778 | H59: ='Data Sheet'!G64 -> 30060 | I59: ='Data Sheet'!H64 -> 35272 | ... L59: ='Data Sheet'!K64 -> 40324
B60: ='Data Sheet'!A65 -> Other Assets | C60: ='Data Sheet'!B75 -> 53166 | D60: ='Data Sheet'!C75 -> 65526 | E60: ='Data Sheet'!D75 -> 80265 | F60: ='Data Sheet'!E75 -> 84009 | G60: ='Data Sheet'!F75 -> 78463 | H60: ='Data Sheet'!G75 -> 80519 | I60: ='Data Sheet'!H75 -> 102746 | J60: ='Data Sheet'!I75 -> 125283 | ... O60: ='Data Sheet'!N75 -> 0
B61: Total Non Current Assets | C61: =SUM(C57:C60) -> 93096 | D61: =SUM(D57:D60) -> 111995 | E61: =SUM(E57:E60) -> 132276 | F61: =SUM(F57:F60) -> 139764 | G61: =SUM(G57:G60) -> 136494 | H61: =SUM(H57:H60) -> 143300 | I61: =SUM(I57:I60) -> 169127 | J61: =SUM(J57:J60) -> 196659 | ... L61: =SUM(L57:L60) -> 252967
B63: ='Data Sheet'!A67 -> Receivables | C63: ='Data Sheet'!B67 -> 7199 | D63: ='Data Sheet'!C67 -> 8490 | E63: ='Data Sheet'!D67 -> 8678 | F63: ='Data Sheet'!E67 -> 6928 | G63: ='Data Sheet'!F67 -> 6008 | H63: ='Data Sheet'!G67 -> 6374 | I63: ='Data Sheet'!H67 -> 7028 | ... L63: ='Data Sheet'!K67 -> 9064
B64: ='Data Sheet'!A68 -> Inventory | C64: ='Data Sheet'!B68 -> 8886 | D64: ='Data Sheet'!C68 -> 9336 | E64: ='Data Sheet'!D68 -> 12200 | F64: ='Data Sheet'!E68 -> 11112 | G64: ='Data Sheet'!F68 -> 9615 | H64: ='Data Sheet'!G68 -> 11596 | I64: ='Data Sheet'!H68 -> 16855 | ... L64: ='Data Sheet'!K68 -> 22044
B65: ='Data Sheet'!A69 -> Cash & Bank | C65: ='Data Sheet'!B69 -> 4654 | D65: ='Data Sheet'!C69 -> 6548 | E65: ='Data Sheet'!D69 -> 8735 | F65: ='Data Sheet'!E69 -> 7911 | G65: ='Data Sheet'!F69 -> 12852 | H65: ='Data Sheet'!G69 -> 11118 | I65: ='Data Sheet'!H69 -> 11273 | ... L65: ='Data Sheet'!K69 -> 31979
B66: Total Current Assets | C66: =SUM(C63:C65) -> 20739 | D66: =SUM(D63:D65) -> 24374 | E66: =SUM(E63:E65) -> 29613 | F66: =SUM(F63:F65) -> 25951 | G66: =SUM(G63:G65) -> 28475 | H66: =SUM(H63:H65) -> 29088 | I66: =SUM(I63:I65) -> 35156 | J66: =SUM(J63:J65) -> 38062 | ... L66: =SUM(L63:L65) -> 63087
B68: Total Assets | C68: =C61+C66 -> 113835 | D68: =D61+D66 -> 136369 | E68: =E61+E66 -> 161889 | F68: =F61+F66 -> 165715 | G68: =G61+G66 -> 164969 | H68: =H61+H66 -> 172388 | I68: =I61+I66 -> 204283 | J68: =J61+J66 -> 234721 | ... L68: =L61+L66 -> 316054
B70: Check | C70: =C68=C55 -> FALSE | D70: =D68=D55 -> TRUE | E70: =E68=E55 -> FALSE | F70: =F68=F55 -> FALSE | G70: =G68=G55 -> TRUE | H70: =H68=H55 -> FALSE | I70: =I68=I55 -> TRUE | J70: =J68=J55 -> TRUE | ... L70: =L68=L55 -> TRUE
B72: Cash Flow Statement
B73: Operating Activity
B74: ='Cash Flow Statement'!B7 -> Profit from operations | C74: ='Cash Flow Statement'!E7 -> 7911 | D74: ='Cash Flow Statement'!F7 -> 10159 | E74: ='Cash Flow Statement'!G7 -> 11112 | F74: ='Cash Flow Statement'!H7 -> 7774 | G74: ='Cash Flow Statement'!I7 -> 7588 | H74: ='Cash Flow Statement'!J7 -> 10515 | I74: ='Cash Flow Statement'!K7 -> 15642 | J74: ='Cash Flow Statement'!L7 -> 17541 | ... L74: ='Cash Flow Statement'!N7 -> 28938
B75: ='Cash Flow Statement'!B8 -> Receivables | C75: ='Cash Flow Statement'!E8 -> -8609 | D75: ='Cash Flow Statement'!F8 -> -11918 | E75: ='Cash Flow Statement'!G8 -> -13712 | F75: ='Cash Flow Statement'!H8 -> -1516 | G75: ='Cash Flow Statement'!I8 -> 4896 | H75: ='Cash Flow Statement'!J8 -> -2506 | I75: ='Cash Flow Statement'!K8 -> -21702 | J75: ='Cash Flow Statement'!L8 -> -21777 | ... L75: ='Cash Flow Statement'!N8 -> -19186
B76: ='Cash Flow Statement'!B9 -> Inventory | C76: ='Cash Flow Statement'!E9 -> 241 | D76: ='Cash Flow Statement'!F9 -> -256 | E76: ='Cash Flow Statement'!G9 -> -2276 | F76: ='Cash Flow Statement'!H9 -> 1316 | G76: ='Cash Flow Statement'!I9 -> 226 | H76: ='Cash Flow Statement'!J9 -> -2173 | I76: ='Cash Flow Statement'!K9 -> -5252 | J76: ='Cash Flow Statement'!L9 -> -1753 | ... L76: ='Cash Flow Statement'!N9 -> -593
B77: ='Cash Flow Statement'!B10 -> Payables | C77: ='Cash Flow Statement'!E10 -> 2645 | D77: ='Cash Flow Statement'!F10 -> 5361 | E77: ='Cash Flow Statement'!G10 -> 3466 | F77: ='Cash Flow Statement'!H10 -> -6775 | G77: ='Cash Flow Statement'!I10 -> 7049 | H77: ='Cash Flow Statement'!J10 -> 4972 | I77: ='Cash Flow Statement'!K10 -> 7013 | J77: ='Cash Flow Statement'!L10 -> 4354 | ... L77: ='Cash Flow Statement'!N10 -> 8763
B78: ='Cash Flow Statement'!B11 -> Working capital changes | C78: ='Cash Flow Statement'!E11 -> -5724 | D78: ='Cash Flow Statement'!F11 -> -6813 | E78: ='Cash Flow Statement'!G11 -> -12522 | F78: ='Cash Flow Statement'!H11 -> -6974 | G78: ='Cash Flow Statement'!I11 -> 12171 | H78: ='Cash Flow Statement'!J11 -> 293 | I78: ='Cash Flow Statement'!K11 -> -19941 | J78: ='Cash Flow Statement'!L11 -> -19175 | ... L78: ='Cash Flow Statement'!N11 -> -11016
B79: ='Cash Flow Statement'!B12 -> Direct taxes | C79: ='Cash Flow Statement'!E12 -> -2005 | D79: ='Cash Flow Statement'!F12 -> -2664 | E79: ='Cash Flow Statement'!G12 -> -2937 | F79: ='Cash Flow Statement'!H12 -> -2257 | G79: ='Cash Flow Statement'!I12 -> -1850 | H79: ='Cash Flow Statement'!J12 -> -1560 | I79: ='Cash Flow Statement'!K12 -> -2775 | J79: ='Cash Flow Statement'!L12 -> -3996 | ... L79: ='Cash Flow Statement'!N12 -> -6265
B80: Cash From Operating Activities | C80: =SUM(C74:C79) -> -5541 | D80: =SUM(D74:D79) -> -6131 | E80: =SUM(E74:E79) -> -16869 | F80: =SUM(F74:F79) -> -8432 | G80: =SUM(G74:G79) -> 30080 | H80: =SUM(H74:H79) -> 9541 | I80: =SUM(I74:I79) -> -27015 | J80: =SUM(J74:J79) -> -24806 | ... L80: =SUM(L74:L79) -> 641
B82: Investing Activities
B83: ='Cash Flow Statement'!B14 -> Fixed assets purchased | C83: ='Cash Flow Statement'!E14 -> -5026 | D83: ='Cash Flow Statement'!F14 -> -5906 | E83: ='Cash Flow Statement'!G14 -> -7340 | F83: ='Cash Flow Statement'!H14 -> -6896 | G83: ='Cash Flow Statement'!I14 -> -5989 | H83: ='Cash Flow Statement'!J14 -> -6040 | I83: ='Cash Flow Statement'!K14 -> -6305 | J83: ='Cash Flow Statement'!L14 -> -9946 | ... L83: ='Cash Flow Statement'!N14 -> -9605
B84: ='Cash Flow Statement'!B15 -> Fixed assets sold | C84: ='Cash Flow Statement'!E15 -> 63 | D84: ='Cash Flow Statement'!F15 -> 115 | E84: ='Cash Flow Statement'!G15 -> 142 | F84: ='Cash Flow Statement'!H15 -> 102 | G84: ='Cash Flow Statement'!I15 -> 1364 | H84: ='Cash Flow Statement'!J15 -> 120 | I84: ='Cash Flow Statement'!K15 -> 138 | J84: ='Cash Flow Statement'!L15 -> 273 | ... L84: ='Cash Flow Statement'!N15 -> 493
B85: ='Cash Flow Statement'!B16 -> Investments purchased | C85: ='Cash Flow Statement'!E16 -> -132173 | D85: ='Cash Flow Statement'!F16 -> -155159 | E85: ='Cash Flow Statement'!G16 -> -196474 | F85: ='Cash Flow Statement'!H16 -> -198568 | G85: ='Cash Flow Statement'!I16 -> -120055 | H85: ='Cash Flow Statement'!J16 -> -87740 | I85: ='Cash Flow Statement'!K16 -> -50165 | J85: ='Cash Flow Statement'!L16 -> -49927 | ... L85: ='Cash Flow Statement'!N16 -> -141518
B86: ='Cash Flow Statement'!B17 -> Investments sold | C86: ='Cash Flow Statement'!E17 -> 130940 | D86: ='Cash Flow Statement'!F17 -> 154631 | E86: ='Cash Flow Statement'!G17 -> 195898 | F86: ='Cash Flow Statement'!H17 -> 198132 | G86: ='Cash Flow Statement'!I17 -> 111749 | H86: ='Cash Flow Statement'!J17 -> 87446 | I86: ='Cash Flow Statement'!K17 -> 46269 | J86: ='Cash Flow Statement'!L17 -> 50919 | ... L86: ='Cash Flow Statement'!N17 -> 144887
B87: ='Cash Flow Statement'!B18 -> Interest received | C87: ='Cash Flow Statement'!E18 -> 346 | D87: ='Cash Flow Statement'!F18 -> 254 | E87: ='Cash Flow Statement'!G18 -> 314 | F87: ='Cash Flow Statement'!H18 -> 372 | G87: ='Cash Flow Statement'!I18 -> 431 | H87: ='Cash Flow Statement'!J18 -> 420 | I87: ='Cash Flow Statement'!K18 -> 464 | J87: ='Cash Flow Statement'!L18 -> 703 | ... L87: ='Cash Flow Statement'!N18 -> 1559
B88: ='Cash Flow Statement'!B19 -> Dividends received | C88: ='Cash Flow Statement'!E19 -> 409 | D88: ='Cash Flow Statement'!F19 -> 316 | E88: ='Cash Flow Statement'!G19 -> 466 | F88: ='Cash Flow Statement'!H19 -> 722 | G88: ='Cash Flow Statement'!I19 -> 577 | H88: ='Cash Flow Statement'!J19 -> 1247 | I88: ='Cash Flow Statement'!K19 -> 1397 | J88: ='Cash Flow Statement'!L19 -> 1213 | ... L88: ='Cash Flow Statement'!N19 -> 1287
B89: ='Cash Flow Statement'!B20 -> Invest in subsidiaries | C89: ='Cash Flow Statement'!E20 -> 0 | D89: ='Cash Flow Statement'!F20 -> 0 | E89: ='Cash Flow Statement'!G20 -> 0 | F89: ='Cash Flow Statement'!H20 -> 0 | G89: ='Cash Flow Statement'!I20 -> 0 | H89: ='Cash Flow Statement'!J20 -> 0 | I89: ='Cash Flow Statement'!K20 -> 0 | J89: ='Cash Flow Statement'!L20 -> 0 | ... L89: ='Cash Flow Statement'!N20 -> 0
B90: ='Cash Flow Statement'!B21 -> Investment in group cos | C90: ='Cash Flow Statement'!E21 -> -647 | D90: ='Cash Flow Statement'!F21 -> -704 | E90: ='Cash Flow Statement'!G21 -> -319 | F90: ='Cash Flow Statement'!H21 -> -418 | G90: ='Cash Flow Statement'!I21 -> -359 | H90: ='Cash Flow Statement'!J21 -> -222 | I90: ='Cash Flow Statement'!K21 -> -62 | J90: ='Cash Flow Statement'!L21 -> -249 | ... L90: ='Cash Flow Statement'!N21 -> -785
B91: ='Cash Flow Statement'!B22 -> Redemp n Canc of Shares | C91: ='Cash Flow Statement'!E22 -> 88 | D91: ='Cash Flow Statement'!F22 -> 1677 | E91: ='Cash Flow Statement'!G22 -> 717 | F91: ='Cash Flow Statement'!H22 -> 175 | G91: ='Cash Flow Statement'!I22 -> 316 | H91: ='Cash Flow Statement'!J22 -> 617 | I91: ='Cash Flow Statement'!K22 -> 1863 | J91: ='Cash Flow Statement'!L22 -> 1043 | ... L91: ='Cash Flow Statement'!N22 -> 2283
B92: ='Cash Flow Statement'!B23 -> Other investing items | C92: ='Cash Flow Statement'!E23 -> 209 | D92: ='Cash Flow Statement'!F23 -> -290 | E92: ='Cash Flow Statement'!G23 -> -577 | F92: ='Cash Flow Statement'!H23 -> -437 | G92: ='Cash Flow Statement'!I23 -> -7457 | H92: ='Cash Flow Statement'!J23 -> 1494 | I92: ='Cash Flow Statement'!K23 -> -1786 | J92: ='Cash Flow Statement'!L23 -> -78 | ... L92: ='Cash Flow Statement'!N23 -> -15084
B93: Cash From Investing Activities | C93: =SUM(C83:C92) -> -5791 | D93: =SUM(D83:D92) -> -5066 | E93: =SUM(E83:E92) -> -7173 | F93: =SUM(F83:F92) -> -6816 | G93: =SUM(G83:G92) -> -19423 | H93: =SUM(H83:H92) -> -2658 | I93: =SUM(I83:I92) -> -8187 | J93: =SUM(J83:J92) -> -6049 | ... L93: =SUM(L83:L92) -> -16483
B95: Financing Activities
B96: ='Cash Flow Statement'!B25 -> Proceeds from shares | C96: ='Cash Flow Statement'!E25 -> 12 | D96: ='Cash Flow Statement'!F25 -> 4 | E96: ='Cash Flow Statement'!G25 -> 1 | F96: ='Cash Flow Statement'!H25 -> 1243 | G96: ='Cash Flow Statement'!I25 -> 1 | H96: ='Cash Flow Statement'!J25 -> 1 | I96: ='Cash Flow Statement'!K25 -> 1 | J96: ='Cash Flow Statement'!L25 -> 1 | ... L96: ='Cash Flow Statement'!N25 -> 1
B97: ='Cash Flow Statement'!B26 -> Proceeds from borrowings | C97: ='Cash Flow Statement'!E26 -> 0 | D97: ='Cash Flow Statement'!F26 -> 0 | E97: ='Cash Flow Statement'!G26 -> 71389 | F97: ='Cash Flow Statement'!H26 -> 52618 | G97: ='Cash Flow Statement'!I26 -> 38100 | H97: ='Cash Flow Statement'!J26 -> 53880 | I97: ='Cash Flow Statement'!K26 -> 55622 | J97: ='Cash Flow Statement'!L26 -> 61308 | ... L97: ='Cash Flow Statement'!N26 -> 79722
B98: ='Cash Flow Statement'!B27 -> Repayment of borrowings | C98: ='Cash Flow Statement'!E27 -> 0 | D98: ='Cash Flow Statement'!F27 -> 0 | E98: ='Cash Flow Statement'!G27 -> -56352 | F98: ='Cash Flow Statement'!H27 -> -44044 | G98: ='Cash Flow Statement'!I27 -> -37505 | H98: ='Cash Flow Statement'!J27 -> -57223 | I98: ='Cash Flow Statement'!K27 -> -37056 | J98: ='Cash Flow Statement'!L27 -> -46805 | ... L98: ='Cash Flow Statement'!N27 -> -72089
B99: ='Cash Flow Statement'!B28 -> Interest paid fin | C99: ='Cash Flow Statement'!E28 -> -471 | D99: ='Cash Flow Statement'!F28 -> -521 | E99: ='Cash Flow Statement'!G28 -> -723 | F99: ='Cash Flow Statement'!H28 -> -624 | G99: ='Cash Flow Statement'!I28 -> -809 | H99: ='Cash Flow Statement'!J28 -> -680 | I99: ='Cash Flow Statement'!K28 -> -734 | J99: ='Cash Flow Statement'!L28 -> -597 | ... L99: ='Cash Flow Statement'!N28 -> -344
B100: ='Cash Flow Statement'!B29 -> Dividends paid | C100: ='Cash Flow Statement'!E29 -> -936 | D100: ='Cash Flow Statement'!F29 -> -963 | E100: ='Cash Flow Statement'!G29 -> -1134 | F100: ='Cash Flow Statement'!H29 -> -1398 | G100: ='Cash Flow Statement'!I29 -> -271 | H100: ='Cash Flow Statement'!J29 -> -1037 | I100: ='Cash Flow Statement'!K29 -> -1522 | J100: ='Cash Flow Statement'!L29 -> -2247 | ... L100: ='Cash Flow Statement'!N29 -> -3376
B101: ='Cash Flow Statement'!B30 -> Financial liabilities | C101: ='Cash Flow Statement'!E30 -> 0 | D101: ='Cash Flow Statement'!F30 -> 0 | E101: ='Cash Flow Statement'!G30 -> 0 | F101: ='Cash Flow Statement'!H30 -> -558 | G101: ='Cash Flow Statement'!I30 -> -553 | H101: ='Cash Flow Statement'!J30 -> -583 | I101: ='Cash Flow Statement'!K30 -> -751 | J101: ='Cash Flow Statement'!L30 -> -786 | ... L101: ='Cash Flow Statement'!N30 -> -967
B102: ='Cash Flow Statement'!B31 -> Other financing items | C102: ='Cash Flow Statement'!E31 -> 7503 | D102: ='Cash Flow Statement'!F31 -> 7794 | E102: ='Cash Flow Statement'!G31 -> 12 | F102: ='Cash Flow Statement'!H31 -> -304 | G102: ='Cash Flow Statement'!I31 -> 1444 | H102: ='Cash Flow Statement'!J31 -> -240 | I102: ='Cash Flow Statement'!K31 -> 386 | J102: ='Cash Flow Statement'!L31 -> 1408 | ... L102: ='Cash Flow Statement'!N31 -> 2445
B103: Cash From Financing Activities | C103: =SUM(C96:C102) -> 6108 | D103: =SUM(D96:D102) -> 6314 | E103: =SUM(E96:E102) -> 13193 | F103: =SUM(F96:F102) -> 6933 | G103: =SUM(G96:G102) -> 407 | H103: =SUM(H96:H102) -> -5882 | I103: =SUM(I96:I102) -> 15946 | J103: =SUM(J96:J102) -> 12282 | ... L103: =SUM(L96:L102) -> 5392
B105: Net Cash Flow | C105: =C80+C93+C103 -> -5224 | D105: =D80+D93+D103 -> -4883 | E105: =E80+E93+E103 -> -10849 | F105: =F80+F93+F103 -> -8315 | G105: =G80+G93+G103 -> 11064 | H105: =H80+H93+H103 -> 1001 | I105: =I80+I93+I103 -> -19256 | J105: =J80+J93+J103 -> -18573 | ... L105: =L80+L93+L103 -> -10450

Sheet Ratio Analysis
B2: ="Ratio Analysis - "&'Data Sheet'!$B$1 -> Ratio Analysis - MAHINDRA & MAHINDRA LTD
B3: Years | C3: ='Data Sheet'!B56 -> 42795 | D3: ='Data Sheet'!C56 -> 43160 | E3: ='Data Sheet'!D56 -> 43525 | F3: ='Data Sheet'!E56 -> 43891 | G3: ='Data Sheet'!F56 -> 44256 | H3: ='Data Sheet'!G56 -> 44621 | I3: ='Data Sheet'!H56 -> 44986 | J3: ='Data Sheet'!I56 -> 45352 | ... L3: ='Data Sheet'!K56 -> 46082 | M3: Trend | N3: Mean | O3: Median
B5: SalesGrowth | D5: =IFERROR('Historical FS'!D8,0) -> 0.099327946 | E5: =IFERROR('Historical FS'!E8,0) -> 0.13710991 | F5: =IFERROR('Historical FS'!F8,0) -> -0.28016348 | G5: =IFERROR('Historical FS'!G8,0) -> -0.014645406 | H5: =IFERROR('Historical FS'!H8,0) -> 0.21396645 | I5: =IFERROR('Historical FS'!I8,0) -> 0.34590944 | J5: =IFERROR('Historical FS'!J8,0) -> 0.1459765 | K5: =IFERROR('Historical FS'!K8,0) -> 0.14476049 | L5: =IFERROR('Historical FS'!L8,0) -> 0.24764621 | N5: =IFERROR(AVERAGE(D5:L5),0) -> 0.11554312 | O5: =IFERROR(MEDIAN(D5:L5),0) -> 0.14476049
B6: EBITDA Growth | D6: =IFERROR(('Historical FS'!D19/'Historical FS'!C19-1),0) -> 0.19093861 | E6: =IFERROR(('Historical FS'!E19/'Historical FS'!D19-1),0) -> 0.18084491 | F6: =IFERROR(('Historical FS'!F19/'Historical FS'!E19-1),0) -> -0.12019981 | G6: =IFERROR(('Historical FS'!G19/'Historical FS'!F19-1),0) -> -0.014645406 | H6: =IFERROR(('Historical FS'!H19/'Historical FS'!G19-1),0) -> 0.10360586 | I6: =IFERROR(('Historical FS'!I19/'Historical FS'!H19-1),0) -> 0.21131849 | J6: =IFERROR(('Historical FS'!J19/'Historical FS'!I19-1),0) -> 0.23086365 | K6: =IFERROR(('Historical FS'!K19/'Historical FS'!J19-1),0) -> 0.18423499 | L6: =IFERROR(('Historical FS'!L19/'Historical FS'!K19-1),0) -> 0.206058 | N6: =IFERROR(AVERAGE(D6:L6),0) -> 0.13033548 | O6: =IFERROR(MEDIAN(D6:L6),0) -> 0.18423499
B7: EBIT Growth | D7: =IFERROR(('Historical FS'!D25/'Historical FS'!C25-1),0) -> 0.19499298 | E7: =IFERROR(('Historical FS'!E25/'Historical FS'!D25-1),0) -> 0.1751429 | F7: =IFERROR(('Historical FS'!F25/'Historical FS'!E25-1),0) -> -0.11425826 | G7: =IFERROR(('Historical FS'!G25/'Historical FS'!F25-1),0) -> -0.017449391 | H7: =IFERROR(('Historical FS'!H25/'Historical FS'!G25-1),0) -> 0.11401484 | I7: =IFERROR(('Historical FS'!I25/'Historical FS'!H25-1),0) -> 0.20674417 | J7: =IFERROR(('Historical FS'!J25/'Historical FS'!I25-1),0) -> 0.25335067 | K7: =IFERROR(('Historical FS'!K25/'Historical FS'!J25-1),0) -> 0.17076427 | L7: =IFERROR(('Historical FS'!L25/'Historical FS'!K25-1),0) -> 0.20614426 | N7: =IFERROR(AVERAGE(D7:L7),0) -> 0.13216072 | O7: =IFERROR(MEDIAN(D7:L7),0) -> 0.1751429
B8: Net Profit Growth | D8: =IFERROR(('Historical FS'!D37/'Historical FS'!C37-1),0) -> -0.12928609 | E8: =IFERROR(('Historical FS'!E37/'Historical FS'!D37-1),0) -> 0.63611244 | F8: =IFERROR(('Historical FS'!F37/'Historical FS'!E37-1),0) -> 0.33116814 | G8: =IFERROR(('Historical FS'!G37/'Historical FS'!F37-1),0) -> -0.14164039 | H8: =IFERROR(('Historical FS'!H37/'Historical FS'!G37-1),0) -> -0.2282718 | I8: =IFERROR(('Historical FS'!I37/'Historical FS'!H37-1),0) -> -0.070123209 | J8: =IFERROR(('Historical FS'!J37/'Historical FS'!I37-1),0) -> 0.42506637 | K8: =IFERROR(('Historical FS'!K37/'Historical FS'!J37-1),0) -> 0.11395234 | L8: =IFERROR(('Historical FS'!L37/'Historical FS'!K37-1),0) -> 0.14645616 | N8: =IFERROR(AVERAGE(D8:L8),0) -> 0.12038155 | O8: =IFERROR(MEDIAN(D8:L8),0) -> 0.11395234
B9: Dividend Growth | D9: =IFERROR(('Historical FS'!D45/'Historical FS'!C45-1),0) -> -0.017773389 | E9: =IFERROR(('Historical FS'!E45/'Historical FS'!D45-1),0) -> 0.16850968 | F9: =IFERROR(('Historical FS'!F45/'Historical FS'!E45-1),0) -> -1.6433243 | G9: =IFERROR(('Historical FS'!G45/'Historical FS'!F45-1),0) -> -2.2407568 | H9: =IFERROR(('Historical FS'!H45/'Historical FS'!G45-1),0) -> 0.77665099 | I9: =IFERROR(('Historical FS'!I45/'Historical FS'!H45-1),0) -> 0.41136082 | J9: =IFERROR(('Historical FS'!J45/'Historical FS'!I45-1),0) -> 0.25857218 | K9: =IFERROR(('Historical FS'!K45/'Historical FS'!J45-1),0) -> 0.20156014 | L9: =IFERROR(('Historical FS'!L45/'Historical FS'!K45-1),0) -> 0.32324309 | N9: =IFERROR(AVERAGE(D9:L9),0) -> -0.19577307 | O9: =IFERROR(MEDIAN(D9:L9),0) -> 0.20156014
B11: Gross Margin | C11: =IFERROR('Historical FS'!C14,0) -> 0.24 | D11: =IFERROR('Historical FS'!D14,0) -> 0.26 | E11: =IFERROR('Historical FS'!E14,0) -> 0.27 | F11: =IFERROR('Historical FS'!F14,0) -> 0.33 | G11: =IFERROR('Historical FS'!G14,0) -> 0.33 | H11: =IFERROR('Historical FS'!H14,0) -> 0.3 | I11: =IFERROR('Historical FS'!I14,0) -> 0.27 | J11: =IFERROR('Historical FS'!J14,0) -> 0.29 | ... L11: =IFERROR('Historical FS'!L14,0) -> 0.29 | N11: =IFERROR(AVERAGE(C11:L11),0) -> 0.288 | O11: =IFERROR(MEDIAN(C11:L11),0) -> 0.29
B12: EBITDA Margin | C12: =IFERROR('Historical FS'!C20,0) -> 0.24 | D12: =IFERROR('Historical FS'!D20,0) -> 0.26 | E12: =IFERROR('Historical FS'!E20,0) -> 0.27 | F12: =IFERROR('Historical FS'!F20,0) -> 0.33 | G12: =IFERROR('Historical FS'!G20,0) -> 0.33 | H12: =IFERROR('Historical FS'!H20,0) -> 0.3 | I12: =IFERROR('Historical FS'!I20,0) -> 0.27 | J12: =IFERROR('Historical FS'!J20,0) -> 0.29 | ... L12: =IFERROR('Historical FS'!L20,0) -> 0.29 | N12: =IFERROR(AVERAGE(C12:L12),0) -> 0.288 | O12: =IFERROR(MEDIAN(C12:L12),0) -> 0.29
B13: EBIT Margin | C13: =IFERROR('Historical FS'!C26,0) -> 0.20642116 | D13: =IFERROR('Historical FS'!D26,0) -> 0.22438422 | E13: =IFERROR('Historical FS'!E26,0) -> 0.23188921 | F13: =IFERROR('Historical FS'!F26,0) -> 0.28533416 | G13: =IFERROR('Historical FS'!G26,0) -> 0.2845222 | H13: =IFERROR('Historical FS'!H26,0) -> 0.26109614 | I13: =IFERROR('Historical FS'!I26,0) -> 0.23409914 | J13: =IFERROR('Historical FS'!J26,0) -> 0.25603345 | ... L13: =IFERROR('Historical FS'!L26,0) -> 0.25313916 | N13: =IFERROR(AVERAGE(C13:L13),0) -> 0.24987682 | O13: =IFERROR(MEDIAN(C13:L13),0) -> 0.25458631
B14: EBT Margin | C14: =IFERROR('Historical FS'!C32,0) -> 0.16287491 | D14: =IFERROR('Historical FS'!D32,0) -> 0.18109149 | E14: =IFERROR('Historical FS'!E32,0) -> 0.18394276 | F14: =IFERROR('Historical FS'!F32,0) -> 0.20546099 | G14: =IFERROR('Historical FS'!G32,0) -> 0.20237136 | H14: =IFERROR('Historical FS'!H32,0) -> 0.20544632 | I14: =IFERROR('Historical FS'!I32,0) -> 0.18606104 | J14: =IFERROR('Historical FS'!J32,0) -> 0.20219316 | ... L14: =IFERROR('Historical FS'!L32,0) -> 0.20485559 | N14: =IFERROR(AVERAGE(C14:L14),0) -> 0.19390969 | O14: =IFERROR(MEDIAN(C14:L14),0) -> 0.20228226
B15: Net Profit Margin | C15: =IFERROR('Historical FS'!C38,0) -> 0.087074833 | D15: =IFERROR('Historical FS'!D38,0) -> 0.068966925 | E15: =IFERROR('Historical FS'!E38,0) -> 0.099231959 | F15: =IFERROR('Historical FS'!F38,0) -> 0.18350614 | G15: =IFERROR('Historical FS'!G38,0) -> 0.15985541 | H15: =IFERROR('Historical FS'!H38,0) -> 0.10162136 | I15: =IFERROR('Historical FS'!I38,0) -> 0.070209291 | J15: =IFERROR('Historical FS'!J38,0) -> 0.087307985 | ... L15: =IFERROR('Historical FS'!L38,0) -> 0.078067801 | N15: =IFERROR(AVERAGE(C15:L15),0) -> 0.10208 | O15: =IFERROR(MEDIAN(C15:L15),0) -> 0.087191409
B17: SalesExpenses%sales | C17: =IFERROR('Historical FS'!C17,0) -> 0 | D17: =IFERROR('Historical FS'!D17,0) -> 0 | E17: =IFERROR('Historical FS'!E17,0) -> 0 | F17: =IFERROR('Historical FS'!F17,0) -> 0 | G17: =IFERROR('Historical FS'!G17,0) -> 0 | H17: =IFERROR('Historical FS'!H17,0) -> 0 | I17: =IFERROR('Historical FS'!I17,0) -> 0 | J17: =IFERROR('Historical FS'!J17,0) -> 0 | ... L17: =IFERROR('Historical FS'!L17,0) -> 0 | N17: =IFERROR(AVERAGE(C17:L17),0) -> 0 | O17: =IFERROR(MEDIAN(C17:L17),0) -> 0
B18: Depreciation%Sales | C18: =IFERROR('Historical FS'!C23,0) -> 0.033578838 | D18: =IFERROR('Historical FS'!D23,0) -> 0.035615784 | E18: =IFERROR('Historical FS'!E23,0) -> 0.03811079 | F18: =IFERROR('Historical FS'!F23,0) -> 0.044665835 | G18: =IFERROR('Historical FS'!G23,0) -> 0.0454778 | H18: =IFERROR('Historical FS'!H23,0) -> 0.03890386 | I18: =IFERROR('Historical FS'!I23,0) -> 0.035900859 | J18: =IFERROR('Historical FS'!J23,0) -> 0.033966551 | ... L18: =IFERROR('Historical FS'!L23,0) -> 0.036860838 | N18: =IFERROR(AVERAGE(C18:L18),0) -> 0.038123178 | O18: =IFERROR(MEDIAN(C18:L18),0) -> 0.037485814
B19: OperatingIncome%sales | C19: =C13 -> 0.20642116 | D19: =D13 -> 0.22438422 | E19: =E13 -> 0.23188921 | F19: =F13 -> 0.28533416 | G19: =G13 -> 0.2845222 | H19: =H13 -> 0.26109614 | I19: =I13 -> 0.23409914 | J19: =J13 -> 0.25603345 | ... L19: =L13 -> 0.25313916 | N19: =IFERROR(AVERAGE(C19:L19),0) -> 0.24987682 | O19: =IFERROR(MEDIAN(C19:L19),0) -> 0.25458631
B21: Return on Capital Employed | C21: =IFERROR('Historical FS'!C25/SUM('Historical FS'!C51:'Historical FS'!C53),0) -> 0.22017469 | D21: =IFERROR('Historical FS'!D25/SUM('Historical FS'!D51:'Historical FS'!D53),0) -> 0.22298231 | E21: =IFERROR('Historical FS'!E25/SUM('Historical FS'!E51:'Historical FS'!E53),0) -> 0.21910539 | F21: =IFERROR('Historical FS'!F25/SUM('Historical FS'!F51:'Historical FS'!F53),0) -> 0.17621566 | G21: =IFERROR('Historical FS'!G25/SUM('Historical FS'!G51:'Historical FS'!G53),0) -> 0.17293396 | H21: =IFERROR('Historical FS'!H25/SUM('Historical FS'!H51:'Historical FS'!H53),0) -> 0.18875714 | I21: =IFERROR('Historical FS'!I25/SUM('Historical FS'!I51:'Historical FS'!I53),0) -> 0.19065947 | J21: =IFERROR('Historical FS'!J25/SUM('Historical FS'!J51:'Historical FS'!J53),0) -> 0.20366753 | ... L21: =IFERROR('Historical FS'!L25/SUM('Historical FS'!L51:'Historical FS'!L53),0) -> 0.21859172 | N21: =IFERROR(AVERAGE(C21:L21),0) -> 0.20154003 | O21: =IFERROR(MEDIAN(C21:L21),0) -> 0.20298996
B22: Retained Earnings% | C22: =IFERROR('Historical FS'!C48,0) -> 0.87782335 | D22: =IFERROR('Historical FS'!D48,0) -> 0.86217614 | E22: =IFERROR('Historical FS'!E48,0) -> 0.90156635 | F22: =IFERROR('Historical FS'!F48,0) -> 1.0475708 | G22: =IFERROR('Historical FS'!G48,0) -> 0.93123649 | H22: =IFERROR('Historical FS'!H48,0) -> 0.84169459 | I22: =IFERROR('Historical FS'!I48,0) -> 0.75972509 | J22: =IFERROR('Historical FS'!J48,0) -> 0.78779703 | ... L22: =IFERROR('Historical FS'!L48,0) -> 0.73581234 | N22: =IFERROR(AVERAGE(C22:L22),0) -> 0.85165103 | O22: =IFERROR(MEDIAN(C22:L22),0) -> 0.85193536
B23: Return on Equity% | C23: =IFERROR('Historical FS'!C37/SUM('Historical FS'!C51:'Historical FS'!C52),0) -> 0.2449634 | D23: =IFERROR('Historical FS'!D37/SUM('Historical FS'!D51:'Historical FS'!D52),0) -> 0.17271081 | E23: =IFERROR('Historical FS'!E37/SUM('Historical FS'!E51:'Historical FS'!E52),0) -> 0.25990221 | F23: =IFERROR('Historical FS'!F37/SUM('Historical FS'!F51:'Historical FS'!F52),0) -> 0.34609472 | G23: =IFERROR('Historical FS'!G37/SUM('Historical FS'!G51:'Historical FS'!G52),0) -> 0.28555 | H23: =IFERROR('Historical FS'!H37/SUM('Historical FS'!H51:'Historical FS'!H52),0) -> 0.19445494 | I23: =IFERROR('Historical FS'!I37/SUM('Historical FS'!I51:'Historical FS'!I52),0) -> 0.15116808 | J23: =IFERROR('Historical FS'!J37/SUM('Historical FS'!J51:'Historical FS'!J52),0) -> 0.18345097 | ... L23: =IFERROR('Historical FS'!L37/SUM('Historical FS'!L51:'Historical FS'!L52),0) -> 0.16657153 | N23: =IFERROR(AVERAGE(C23:L23),0) -> 0.2180444 | O23: =IFERROR(MEDIAN(C23:L23),0) -> 0.18895296
B24: Self Sustained Growth Rate | C24: =IFERROR(C22*C23,0) -> 0.21503459 | D24: =IFERROR(D22*D23,0) -> 0.14890714 | E24: =IFERROR(E22*E23,0) -> 0.23431909 | F24: =IFERROR(F22*F23,0) -> 0.36255873 | G24: =IFERROR(G22*G23,0) -> 0.26591458 | H24: =IFERROR(H22*H23,0) -> 0.16367167 | I24: =IFERROR(I22*I23,0) -> 0.11484618 | J24: =IFERROR(J22*J23,0) -> 0.14452213 | ... L24: =IFERROR(L22*L23,0) -> 0.12256539 | N24: =IFERROR(AVERAGE(C24:L24),0) -> 0.19077286 | O24: =IFERROR(MEDIAN(C24:L24),0) -> 0.1562894
B25: Interest Coverage Ratio | C25: =IFERROR('Historical FS'!C25/'Historical FS'!C28,0) -> 4.7402741 | D25: =IFERROR('Historical FS'!D25/'Historical FS'!D28,0) -> 5.1829546 | E25: =IFERROR('Historical FS'!E25/'Historical FS'!E28,0) -> 4.836421 | F25: =IFERROR('Historical FS'!F25/'Historical FS'!F28,0) -> 3.5723401 | G25: =IFERROR('Historical FS'!G25/'Historical FS'!G28,0) -> 3.463412 | H25: =IFERROR('Historical FS'!H25/'Historical FS'!H28,0) -> 4.6917696 | I25: =IFERROR('Historical FS'!I25/'Historical FS'!I28,0) -> 4.8731973 | J25: =IFERROR('Historical FS'!J25/'Historical FS'!J28,0) -> 4.7554247 | ... L25: =IFERROR('Historical FS'!L25/'Historical FS'!L28,0) -> 5.2427599 | N25: =IFERROR(AVERAGE(C25:L25),0) -> 4.5948369 | O25: =IFERROR(MEDIAN(C25:L25),0) -> 4.7478494
B27: Debtor Turnover Ratio | C27: =IFERROR('Historical FS'!C7/'Historical FS'!C63,0) -> 11.636755 | D27: =IFERROR('Historical FS'!D7/'Historical FS'!D63,0) -> 10.84735 | E27: =IFERROR('Historical FS'!E7/'Historical FS'!E63,0) -> 12.067412 | F27: =IFERROR('Historical FS'!F7/'Historical FS'!F63,0) -> 10.880774 | G27: =IFERROR('Historical FS'!G7/'Historical FS'!G63,0) -> 12.363182 | H27: =IFERROR('Historical FS'!H7/'Historical FS'!H63,0) -> 14.14669 | I27: =IFERROR('Historical FS'!I7/'Historical FS'!I63,0) -> 17.268355 | J27: =IFERROR('Historical FS'!J7/'Historical FS'!J63,0) -> 18.645663 | ... L27: =IFERROR('Historical FS'!L7/'Historical FS'!L63,0) -> 21.915159 | N27: =IFERROR(AVERAGE(C27:L27),0) -> 14.899972 | O27: =IFERROR(MEDIAN(C27:L27),0) -> 13.254936
B28: Creditor Turnover Ratio | C28: =IFERROR('Historical FS'!C7/'Historical FS'!C54,0) -> 2.3734417 | D28: =IFERROR('Historical FS'!D7/'Historical FS'!D54,0) -> 2.1076071 | E28: =IFERROR('Historical FS'!E7/'Historical FS'!E54,0) -> 2.0510606 | F28: =IFERROR('Historical FS'!F7/'Historical FS'!F54,0) -> 1.7267667 | G28: =IFERROR('Historical FS'!G7/'Historical FS'!G54,0) -> 1.7370095 | H28: =IFERROR('Historical FS'!H7/'Historical FS'!H54,0) -> 1.8919242 | I28: =IFERROR('Historical FS'!I7/'Historical FS'!I54,0) -> 2.1958024 | J28: =IFERROR('Historical FS'!J7/'Historical FS'!J54,0) -> 2.3224567 | ... L28: =IFERROR('Historical FS'!L7/'Historical FS'!L54,0) -> 2.3091919 | N28: =IFERROR(AVERAGE(C28:L28),0) -> 2.099133 | O28: =IFERROR(MEDIAN(C28:L28),0) -> 2.1517048
B29: Inventory Turnover | C29: =IFERROR('Historical FS'!C7/'Historical FS'!C64,0) -> 9.4275264 | D29: =IFERROR('Historical FS'!D7/'Historical FS'!D64,0) -> 9.8643959 | E29: =IFERROR('Historical FS'!E7/'Historical FS'!E64,0) -> 8.5836885 | F29: =IFERROR('Historical FS'!F7/'Historical FS'!F64,0) -> 6.7838373 | G29: =IFERROR('Historical FS'!G7/'Historical FS'!G64,0) -> 7.725221 | H29: =IFERROR('Historical FS'!H7/'Historical FS'!H64,0) -> 7.7760435 | I29: =IFERROR('Historical FS'!I7/'Historical FS'!I64,0) -> 7.200356 | J29: =IFERROR('Historical FS'!J7/'Historical FS'!J64,0) -> 7.4813341 | ... L29: =IFERROR('Historical FS'!L7/'Historical FS'!L64,0) -> 9.0110234 | N29: =IFERROR(AVERAGE(C29:L29),0) -> 8.1684374 | O29: =IFERROR(MEDIAN(C29:L29),0) -> 7.8034956
B30: Fixed Assets Turnover | C30: =IFERROR('Historical FS'!C7/'Historical FS'!C57,0) -> 3.9912811 | D30: =IFERROR('Historical FS'!D7/'Historical FS'!D57,0) -> 3.5174547 | E30: =IFERROR('Historical FS'!E7/'Historical FS'!E57,0) -> 3.613187 | F30: =IFERROR('Historical FS'!F7/'Historical FS'!F57,0) -> 2.5390549 | G30: =IFERROR('Historical FS'!G7/'Historical FS'!G57,0) -> 3.4741815 | H30: =IFERROR('Historical FS'!H7/'Historical FS'!H57,0) -> 3.465716 | I30: =IFERROR('Historical FS'!I7/'Historical FS'!I57,0) -> 4.4717023 | J30: =IFERROR('Historical FS'!J7/'Historical FS'!J57,0) -> 4.9442924 | ... L30: =IFERROR('Historical FS'!L7/'Historical FS'!L57,0) -> 5.1649549 | N30: =IFERROR(AVERAGE(C30:L30),0) -> 3.9778516 | O30: =IFERROR(MEDIAN(C30:L30),0) -> 3.8022341
B31: Capital Turnover Ratio | C31: =IFERROR('Historical FS'!C7/SUM('Historical FS'!C51:'Historical FS'!C52),0) -> 2.8132514 | D31: =IFERROR('Historical FS'!D7/SUM('Historical FS'!D51:'Historical FS'!D52),0) -> 2.5042556 | E31: =IFERROR('Historical FS'!E7/SUM('Historical FS'!E51:'Historical FS'!E52),0) -> 2.6191381 | F31: =IFERROR('Historical FS'!F7/SUM('Historical FS'!F51:'Historical FS'!F52),0) -> 1.8860117 | G31: =IFERROR('Historical FS'!G7/SUM('Historical FS'!G51:'Historical FS'!G52),0) -> 1.7863018 | H31: =IFERROR('Historical FS'!H7/SUM('Historical FS'!H51:'Historical FS'!H52),0) -> 1.9135242 | I31: =IFERROR('Historical FS'!I7/SUM('Historical FS'!I51:'Historical FS'!I52),0) -> 2.1531065 | J31: =IFERROR('Historical FS'!J7/SUM('Historical FS'!J51:'Historical FS'!J52),0) -> 2.1011935 | ... L31: =IFERROR('Historical FS'!L7/SUM('Historical FS'!L51:'Historical FS'!L52),0) -> 2.1336778 | N31: =IFERROR(AVERAGE(C31:L31),0) -> 2.1977089 | O31: =IFERROR(MEDIAN(C31:L31),0) -> 2.1174357
B33: (in days)
B34: Debtor Days | C34: =IFERROR(365/C27,0) -> 31.366132 | D34: =IFERROR(365/D27,0) -> 33.648772 | E34: =IFERROR(365/E27,0) -> 30.246751 | F34: =IFERROR(365/F27,0) -> 33.545409 | G34: =IFERROR(365/G27,0) -> 29.523143 | H34: =IFERROR(365/H27,0) -> 25.801089 | I34: =IFERROR(365/I27,0) -> 21.136929 | J34: =IFERROR(365/J27,0) -> 19.575598 | ... L34: =IFERROR(365/L27,0) -> 16.655138 | N34: =IFERROR(AVERAGE(C34:L34),0) -> 26.048132 | O34: =IFERROR(MEDIAN(C34:L34),0) -> 27.662116
B35: Payable Days | C35: =IFERROR(365/C28,0) -> 153.78511 | D35: =IFERROR(365/D28,0) -> 173.18218 | E35: =IFERROR(365/E28,0) -> 177.95671 | F35: =IFERROR(365/F28,0) -> 211.37772 | G35: =IFERROR(365/G28,0) -> 210.13126 | H35: =IFERROR(365/H28,0) -> 192.92528 | I35: =IFERROR(365/I28,0) -> 166.22625 | J35: =IFERROR(365/J28,0) -> 157.16116 | ... L35: =IFERROR(365/L28,0) -> 158.06395 | N35: =IFERROR(AVERAGE(C35:L35),0) -> 176.11739 | O35: =IFERROR(MEDIAN(C35:L35),0) -> 169.70422
B36: Inventory Days | C36: =IFERROR(365/C29,0) -> 38.716412 | D36: =IFERROR(365/D29,0) -> 37.001759 | E36: =IFERROR(365/E29,0) -> 42.522512 | F36: =IFERROR(365/F29,0) -> 53.804356 | G36: =IFERROR(365/G29,0) -> 47.247839 | H36: =IFERROR(365/H29,0) -> 46.939038 | I36: =IFERROR(365/I29,0) -> 50.691938 | J36: =IFERROR(365/J29,0) -> 48.78809 | ... L36: =IFERROR(365/L29,0) -> 40.505943 | N36: =IFERROR(AVERAGE(C36:L36),0) -> 45.282783 | O36: =IFERROR(MEDIAN(C36:L36),0) -> 46.774489
B37: Cash Conversion Cycle | C37: =SUM(C34,C36)-C35 -> -83.702565 | D37: =SUM(D34,D36)-D35 -> -102.53165 | E37: =SUM(E34,E36)-E35 -> -105.18745 | F37: =SUM(F34,F36)-F35 -> -124.02795 | G37: =SUM(G34,G36)-G35 -> -133.36028 | H37: =SUM(H34,H36)-H35 -> -120.18515 | I37: =SUM(I34,I36)-I35 -> -94.397381 | J37: =SUM(J34,J36)-J35 -> -88.797473 | ... L37: =SUM(L34,L36)-L35 -> -100.90287 | N37: =IFERROR(AVERAGE(C37:L37),0) -> -104.78647 | O37: =IFERROR(MEDIAN(C37:L37),0) -> -101.71726
B39: CFO/Sales | C39: =IFERROR('Historical FS'!C80/'Historical FS'!C7,0) -> -0.066143029 | D39: =IFERROR('Historical FS'!D80/'Historical FS'!D7,0) -> -0.066573284 | E39: =IFERROR('Historical FS'!E80/'Historical FS'!E7,0) -> -0.16108517 | F39: =IFERROR('Historical FS'!F80/'Historical FS'!F7,0) -> -0.11185694 | G39: =IFERROR('Historical FS'!G80/'Historical FS'!G7,0) -> 0.40496513 | H39: =IFERROR('Historical FS'!H80/'Historical FS'!H7,0) -> 0.10581007 | I39: =IFERROR('Historical FS'!I80/'Historical FS'!I7,0) -> -0.22259851 | J39: =IFERROR('Historical FS'!J80/'Historical FS'!J7,0) -> -0.17836034 | ... L39: =IFERROR('Historical FS'!L80/'Historical FS'!L7,0) -> 0.0032269595 | N39: =IFERROR(AVERAGE(C39:L39),0) -> -0.036131012 | O39: =IFERROR(MEDIAN(C39:L39),0) -> -0.067634143
B40: CFO/Total Assets | C40: =IFERROR('Historical FS'!C80/'Historical FS'!C68,0) -> -0.048675715 | D40: =IFERROR('Historical FS'!D80/'Historical FS'!D68,0) -> -0.044958898 | E40: =IFERROR('Historical FS'!E80/'Historical FS'!E68,0) -> -0.10420103 | F40: =IFERROR('Historical FS'!F80/'Historical FS'!F68,0) -> -0.050882539 | G40: =IFERROR('Historical FS'!G80/'Historical FS'!G68,0) -> 0.18233729 | H40: =IFERROR('Historical FS'!H80/'Historical FS'!H68,0) -> 0.05534608 | I40: =IFERROR('Historical FS'!I80/'Historical FS'!I68,0) -> -0.13224302 | J40: =IFERROR('Historical FS'!J80/'Historical FS'!J68,0) -> -0.10568292 | ... L40: =IFERROR('Historical FS'!L80/'Historical FS'!L68,0) -> 0.0020281344 | N40: =IFERROR(AVERAGE(C40:L40),0) -> -0.028655741 | O40: =IFERROR(MEDIAN(C40:L40),0) -> -0.046817307
B41: CFO/Total Debt | C41: =IFERROR('Historical FS'!C80/'Historical FS'!C53,0) -> -0.11363357 | D41: =IFERROR('Historical FS'!D80/'Historical FS'!D53,0) -> -0.10968192 | E41: =IFERROR('Historical FS'!E80/'Historical FS'!E53,0) -> -0.23810129 | F41: =IFERROR('Historical FS'!F80/'Historical FS'!F53,0) -> -0.10271403 | G41: =IFERROR('Historical FS'!G80/'Historical FS'!G53,0) -> 0.37308527 | H41: =IFERROR('Historical FS'!H80/'Historical FS'!H53,0) -> 0.12294311 | I41: =IFERROR('Historical FS'!I80/'Historical FS'!I53,0) -> -0.29159066 | J41: =IFERROR('Historical FS'!J80/'Historical FS'!J53,0) -> -0.22831739 | ... L41: =IFERROR('Historical FS'!L80/'Historical FS'!L53,0) -> 0.0046810189 | N41: =IFERROR(AVERAGE(C41:L41),0) -> -0.066809598 | O41: =IFERROR(MEDIAN(C41:L41),0) -> -0.10619797

Sheet Forecasting
B2: ='Data Sheet'!$B$1&" -"&'Data Sheet'!A17&" Forecasting" -> MAHINDRA & MAHINDRA LTD -Sales Forecasting | G2: ='Data Sheet'!$B$1&" -"&'Historical FS'!B19&" Forecasting" -> MAHINDRA & MAHINDRA LTD -EBITDA Forecasting | L2: ='Data Sheet'!$B$1&" -"&'Historical FS'!B37&" Forecasting" -> MAHINDRA & MAHINDRA LTD -Net Profit Forecasting
B3: Year Weight | C3: Year | D3: Sales | E3: Sales Growth | G3: Year Weight | H3: Year | I3: EBITDA | J3: EBITDA Growth | L3: Year Weight | M3: Year | N3: Net Profit | O3: Net Profit Growth
B5: 1 | C5: {=TRANSPOSE('Data Sheet'!B16:J16)} -> 42795 | D5: {=TRANSPOSE('Data Sheet'!B17:K17)} -> 83773 | E5: - | G5: 1 | H5: {=TRANSPOSE('Data Sheet'!B16:J16)} -> 42795 | I5: {=TRANSPOSE('Historical FS'!C19:L19)} -> 20105.52 | J5: - | L5: 1 | M5: {=TRANSPOSE('Data Sheet'!B16:J16)} -> 42795 | N5: {=TRANSPOSE('Historical FS'!C37:L37)} -> 7294.52 | O5: -
B6: =B5+1 -> 2 | C6: 43160 | D6: 92094 | E6: =D6/D5-1 -> 0.099327946 | G6: =G5+1 -> 2 | H6: 43160 | I6: 23944.44 | J6: =I6/I5-1 -> 0.19093861 | L6: =L5+1 -> 2 | M6: 43160 | N6: 6351.44 | O6: =N6/N5-1 -> -0.12928609
B7: =B6+1 -> 3 | C7: 43525 | D7: 104721 | E7: =D7/D6-1 -> 0.13710991 | G7: =G6+1 -> 3 | H7: 43525 | I7: 28274.67 | J7: =I7/I6-1 -> 0.18084491 | L7: =L6+1 -> 3 | M7: 43525 | N7: 10391.67 | O7: =N7/N6-1 -> 0.63611244
B8: =B7+1 -> 4 | C8: 43891 | D8: 75382 | E8: =D8/D7-1 -> -0.28016348 | G8: =G7+1 -> 4 | H8: 43891 | I8: 24876.06 | J8: =I8/I7-1 -> -0.12019981 | L8: =L7+1 -> 4 | M8: 43891 | N8: 13833.06 | O8: =N8/N7-1 -> 0.33116814
B9: =B8+1 -> 5 | C9: 44256 | D9: 74278 | E9: =D9/D8-1 -> -0.014645406 | G9: =G8+1 -> 5 | H9: 44256 | I9: 24511.74 | J9: =I9/I8-1 -> -0.014645406 | L9: =L8+1 -> 5 | M9: 44256 | N9: 11873.74 | O9: =N9/N8-1 -> -0.14164039
B10: =B9+1 -> 6 | C10: 44621 | D10: 90171 | E10: =D10/D9-1 -> 0.21396645 | G10: =G9+1 -> 6 | H10: 44621 | I10: 27051.3 | J10: =I10/I9-1 -> 0.10360586 | L10: =L9+1 -> 6 | M10: 44621 | N10: 9163.3 | O10: =N10/N9-1 -> -0.2282718
B11: =B10+1 -> 7 | C11: 44986 | D11: 121362 | E11: =D11/D10-1 -> 0.34590944 | G11: =G10+1 -> 7 | H11: 44986 | I11: 32767.74 | J11: =I11/I10-1 -> 0.21131849 | L11: =L10+1 -> 7 | M11: 44986 | N11: 8520.74 | O11: =N11/N10-1 -> -0.070123209
B12: =B11+1 -> 8 | C12: 45352 | D12: 139078 | E12: =D12/D11-1 -> 0.1459765 | G12: =G11+1 -> 8 | H12: 45352 | I12: 40332.62 | J12: =I12/I11-1 -> 0.23086365 | L12: =L11+1 -> 8 | M12: 45352 | N12: 12142.62 | O12: =N12/N11-1 -> 0.42506637
B13: =B12+1 -> 9 | C13: 45717 | D13: 159211 | E13: =D13/D12-1 -> 0.14476049 | G13: =G12+1 -> 9 | H13: 45717 | I13: 47763.3 | J13: =I13/I12-1 -> 0.18423499 | L13: =L12+1 -> 9 | M13: 45717 | N13: 13526.3 | O13: =N13/N12-1 -> 0.11395234
B14: =B13+1 -> 10 | C14: =C13+365 -> 46082 | D14: 198639 | E14: =D14/D13-1 -> 0.24764621 | G14: =G13+1 -> 10 | H14: =H13+365 -> 46082 | I14: 57605.31 | J14: =I14/I13-1 -> 0.206058 | L14: =L13+1 -> 10 | M14: =M13+365 -> 46082 | N14: 15507.31 | O14: =N14/N13-1 -> 0.14645616
B15: =B14+1 -> 11 | C15: =C14+365 -> 46447 | D15: =FORECAST(B15,$D$5:$D$14,$B$5:$B$14) -> 174845.27 | E15: =D15/D14-1 -> -0.1197838 | G15: =G14+1 -> 11 | H15: =H14+365 -> 46447 | I15: =FORECAST(G15,$I$5:$I$14,$G$5:$G$14) -> 52414.419 | J15: =I15/I14-1 -> -0.090111322 | L15: =L14+1 -> 11 | M15: =M14+365 -> 46447 | N15: =FORECAST(L15,$N$5:$N$14,$L$5:$L$14) -> 14668.686 | O15: =N15/N14-1 -> -0.05407927
B16: =B15+1 -> 12 | C16: =C15+365 -> 46812 | D16: =FORECAST(B16,$D$5:$D$14,$B$5:$B$14) -> 185931.52 | E16: =D16/D15-1 -> 0.063406054 | G16: =G15+1 -> 12 | H16: =H15+365 -> 46812 | I16: =FORECAST(G16,$I$5:$I$14,$G$5:$G$14) -> 55994.628 | J16: =I16/I15-1 -> 0.068305802 | L16: =L15+1 -> 12 | M16: =M15+365 -> 46812 | N16: =FORECAST(L16,$N$5:$N$14,$L$5:$L$14) -> 15361.089 | O16: =N16/N15-1 -> 0.04720279
B17: =B16+1 -> 13 | C17: =C16+365 -> 47177 | D17: =FORECAST(B17,$D$5:$D$14,$B$5:$B$14) -> 197017.76 | E17: =D17/D16-1 -> 0.05962544 | G17: =G16+1 -> 13 | H17: =H16+365 -> 47177 | I17: =FORECAST(G17,$I$5:$I$14,$G$5:$G$14) -> 59574.837 | J17: =I17/I16-1 -> 0.063938436 | L17: =L16+1 -> 13 | M17: =M16+365 -> 47177 | N17: =FORECAST(L17,$N$5:$N$14,$L$5:$L$14) -> 16053.492 | O17: =N17/N16-1 -> 0.045075119
B18: =B17+1 -> 14 | C18: =C17+365 -> 47542 | D18: =FORECAST(B18,$D$5:$D$14,$B$5:$B$14) -> 208104.01 | E18: =D18/D17-1 -> 0.056270299 | G18: =G17+1 -> 14 | H18: =H17+365 -> 47542 | I18: =FORECAST(G18,$I$5:$I$14,$G$5:$G$14) -> 63155.046 | J18: =I18/I17-1 -> 0.060095992 | L18: =L17+1 -> 14 | M18: =M17+365 -> 47542 | N18: =FORECAST(L18,$N$5:$N$14,$L$5:$L$14) -> 16745.895 | O18: =N18/N17-1 -> 0.043130985
B19: =B18+1 -> 15 | C19: =C18+365 -> 47907 | D19: =FORECAST(B19,$D$5:$D$14,$B$5:$B$14) -> 219190.26 | E19: =D19/D18-1 -> 0.053272632 | G19: =G18+1 -> 15 | H19: =H18+365 -> 47907 | I19: =FORECAST(G19,$I$5:$I$14,$G$5:$G$14) -> 66735.255 | J19: =I19/I18-1 -> 0.056689199 | L19: =L18+1 -> 15 | M19: =M18+365 -> 47907 | N19: =FORECAST(L19,$N$5:$N$14,$L$5:$L$14) -> 17438.298 | O19: =N19/N18-1 -> 0.041347621

Sheet Rm
B6: Return on Markets
B8: Date | C8: Annual
B9: ='Raw Data'!B6 -> 2025 | C9: ='Raw Data'!C6 -> 0.1051
B10: ='Raw Data'!B7 -> 2024 | C10: ='Raw Data'!C7 -> 0.0875
B11: ='Raw Data'!B8 -> 2023 | C11: ='Raw Data'!C8 -> 0.1942
B12: ='Raw Data'!B9 -> 2022 | C12: ='Raw Data'!C9 -> 0.0432 | E12: Average Market Returns | H12: =AVERAGE(C9:C32) -> 0.1769625
B13: ='Raw Data'!B10 -> 2021 | C13: ='Raw Data'!C10 -> 0.2412 | E13: Dividend Yield | H13: 0.0128
B14: ='Raw Data'!B11 -> 2020 | C14: ='Raw Data'!C11 -> 0.149 | E14: Total Market Returns | H14: =SUM(H12:H13) -> 0.1897625
B15: ='Raw Data'!B12 -> 2019 | C15: ='Raw Data'!C12 -> 0.1202
B16: ='Raw Data'!B13 -> 2018 | C16: ='Raw Data'!C13 -> 0.0315
B17: ='Raw Data'!B14 -> 2017 | C17: ='Raw Data'!C14 -> 0.2865
B18: ='Raw Data'!B15 -> 2016 | C18: ='Raw Data'!C15 -> 0.0301
B19: ='Raw Data'!B16 -> 2015 | C19: ='Raw Data'!C16 -> -0.0406
B20: ='Raw Data'!B17 -> 2014 | C20: ='Raw Data'!C17 -> 0.3139
B21: ='Raw Data'!B18 -> 2013 | C21: ='Raw Data'!C18 -> 0.0676
B22: ='Raw Data'!B19 -> 2012 | C22: ='Raw Data'!C19 -> 0.277
B23: ='Raw Data'!B20 -> 2011 | C23: ='Raw Data'!C20 -> -0.2462
B24: ='Raw Data'!B21 -> 2010 | C24: ='Raw Data'!C21 -> 0.1795
B25: ='Raw Data'!B22 -> 2009 | C25: ='Raw Data'!C22 -> 0.7576
B26: ='Raw Data'!B23 -> 2008 | C26: ='Raw Data'!C23 -> -0.5179
... B32: ='Raw Data'!B29 -> 2002 | C32: ='Raw Data'!C29 -> 0.0325

Sheet Beta-Regression
B6: Beta Regression
B7: ='Data Sheet'!B1&" Daily Returns" -> MAHINDRA & MAHINDRA LTD Daily Returns | F7: Nifty 50 Daily Returns | J7: Beta Drifting
B9: Date | C9: Closing Price | D9: Daily Returns | F9: Date | G9: Closing Price | H9: Daily Returns | J9: Levered Raw Beta | L9: =O11 -> 1.4167342
B10: ='Raw Data'!G6 -> 46286 | C10: ='Raw Data'!H6 -> 3055.3 | D10: - | F10: ='Raw Data'!G6 -> 46286 | G10: ='Raw Data'!J6 -> 23414.3 | H10: - | J10: Raw Beta Weight | L10: 0.75
B11: ='Raw Data'!G7 -> 46283 | C11: ='Raw Data'!H7 -> 3052 | D11: =C10/C11-1 -> 0.0010812582 | F11: ='Raw Data'!G7 -> 46283 | G11: ='Raw Data'!J7 -> 23346.4 | H11: =G10/G11-1 -> 0.0029083713 | N11: Beta 1 | O11: =SLOPE(D10:D252, H10:H252) -> 1.4167342
B12: ='Raw Data'!G8 -> 46282 | C12: ='Raw Data'!H8 -> 3076.5 | D12: =C11/C12-1 -> -0.007963595 | F12: ='Raw Data'!G8 -> 46282 | G12: ='Raw Data'!J8 -> 23270.6 | H12: =G11/G12-1 -> 0.003257329 | J12: Market Beta | L12: 1 | N12: Beta 2 | O12: =_xlfn.COVARIANCE.S(D10:D252, H10:H252)/_xlfn.VAR.S(H10:H252) -> 1.4167342
B13: ='Raw Data'!G9 -> 46281 | C13: ='Raw Data'!H9 -> 3070 | D13: =C12/C13-1 -> 0.0021172638 | F13: ='Raw Data'!G9 -> 46281 | G13: ='Raw Data'!J9 -> 23217.6 | H13: =G12/G13-1 -> 0.002282751 | J13: Market Beta Weight | L13: 0.25
B14: ='Raw Data'!G10 -> 46280 | C14: ='Raw Data'!H10 -> 3029.5 | D14: =C13/C14-1 -> 0.013368543 | F14: ='Raw Data'!G10 -> 46280 | G14: ='Raw Data'!J10 -> 23118.6 | H14: =G13/G14-1 -> 0.0042822662
B15: ='Raw Data'!G11 -> 46276 | C15: ='Raw Data'!H11 -> 3107 | D15: =C14/C15-1 -> -0.024943676 | F15: ='Raw Data'!G11 -> 46276 | G15: ='Raw Data'!J11 -> 23398.1 | H15: =G14/G15-1 -> -0.011945414 | J15: Adjusted Beta | L15: =(L9*L10)+(L12*L13) -> 1.3125507
B16: ='Raw Data'!G12 -> 46275 | C16: ='Raw Data'!H12 -> 3123.8 | D16: =C15/C16-1 -> -0.0053780652 | F16: ='Raw Data'!G12 -> 46275 | G16: ='Raw Data'!J12 -> 23477.8 | H16: =G15/G16-1 -> -0.0033946963
B17: ='Raw Data'!G13 -> 46274 | C17: ='Raw Data'!H13 -> 3150 | D17: =C16/C17-1 -> -0.0083174603 | F17: ='Raw Data'!G13 -> 46274 | G17: ='Raw Data'!J13 -> 23431.5 | H17: =G16/G17-1 -> 0.0019759725
B18: ='Raw Data'!G14 -> 46273 | C18: ='Raw Data'!H14 -> 3160 | D18: =C17/C18-1 -> -0.003164557 | F18: ='Raw Data'!G14 -> 46273 | G18: ='Raw Data'!J14 -> 23635.1 | H18: =G17/G18-1 -> -0.0086143067
B19: ='Raw Data'!G15 -> 46272 | C19: ='Raw Data'!H15 -> 3160 | D19: =C18/C19-1 -> 0 | F19: ='Raw Data'!G15 -> 46272 | G19: ='Raw Data'!J15 -> 23779.15 | H19: =G18/G19-1 -> -0.006057828
B20: ='Raw Data'!G16 -> 46269 | C20: ='Raw Data'!H16 -> 3170 | D20: =C19/C20-1 -> -0.0031545741 | F20: ='Raw Data'!G16 -> 46269 | G20: ='Raw Data'!J16 -> 23897.7 | H20: =G19/G20-1 -> -0.0049607284
B21: ='Raw Data'!G17 -> 46268 | C21: ='Raw Data'!H17 -> 3150 | D21: =C20/C21-1 -> 0.0063492063 | F21: ='Raw Data'!G17 -> 46268 | G21: ='Raw Data'!J17 -> 23873.45 | H21: =G20/G21-1 -> 0.0010157728
B22: ='Raw Data'!G18 -> 46267 | C22: ='Raw Data'!H18 -> 3190 | D22: =C21/C22-1 -> -0.012539185 | F22: ='Raw Data'!G18 -> 46267 | G22: ='Raw Data'!J18 -> 23914.45 | H22: =G21/G22-1 -> -0.0017144446
B23: ='Raw Data'!G19 -> 46266 | C23: ='Raw Data'!H19 -> 3259 | D23: =C22/C23-1 -> -0.021172139 | F23: ='Raw Data'!G19 -> 46266 | G23: ='Raw Data'!J19 -> 24055.8 | H23: =G22/G23-1 -> -0.0058759218
B24: ='Raw Data'!G20 -> 46265 | C24: ='Raw Data'!H20 -> 3282 | D24: =C23/C24-1 -> -0.007007922 | F24: ='Raw Data'!G20 -> 46265 | G24: ='Raw Data'!J20 -> 24080.4 | H24: =G23/G24-1 -> -0.0010215777
B25: ='Raw Data'!G21 -> 46262 | C25: ='Raw Data'!H21 -> 3334 | D25: =C24/C25-1 -> -0.015596881 | F25: ='Raw Data'!G21 -> 46262 | G25: ='Raw Data'!J21 -> 24175.65 | H25: =G24/G25-1 -> -0.0039399147
B26: ='Raw Data'!G22 -> 46261 | C26: ='Raw Data'!H22 -> 3330 | D26: =C25/C26-1 -> 0.0012012012 | F26: ='Raw Data'!G22 -> 46261 | G26: ='Raw Data'!J22 -> 24090.85 | H26: =G25/G26-1 -> 0.0035200086
B27: ='Raw Data'!G23 -> 46260 | C27: ='Raw Data'!H23 -> 3398.2 | D27: =C26/C27-1 -> -0.020069449 | F27: ='Raw Data'!G23 -> 46260 | G27: ='Raw Data'!J23 -> 24207.75 | H27: =G26/G27-1 -> -0.004829032
... B256: ='Raw Data'!G252 -> 45922 | C256: ='Raw Data'!H252 -> 3584.8 | D256: =C255/C256-1 -> 0.0083128766 | F256: ='Raw Data'!G252 -> 45922 | G256: ='Raw Data'!J252 -> 25202.35 | H256: =G255/G256-1 -> -0.0013034499

Sheet WACC
B6: Weighted Average Cost of Capital
B8: All figures are in INR unless stated otherwise
B10: Peer Comps
E11: Total Debt | F11: Total Equity | H11: Debt /Equity | I11: Debt /Capital | J11: Levered Beta | K11: Unlevered Beta
B12: Name of the Comp | D12: Country | G12: Tax Rate
B14: ='Raw Data'!O24 -> Maruti Suzuki | D14: ='Raw Data'!Q24 -> India | E14: ='Raw Data'!R24 -> 95193.02 | F14: ='Raw Data'!S24 -> 380772.09 | G14: ='Raw Data'!T24 -> 0.3 | H14: =E14/F14 -> 0.24999999 | I14: =E14/SUM(E14:F14) -> 0.2 | J14: 1 | K14: =J14/(1+(1-G14)*H14) -> 0.85106383
B15: ='Raw Data'!O25 -> MAHINDRA & MAHINDRA LTD | D15: ='Raw Data'!Q25 -> India | E15: ='Raw Data'!R25 -> 136936 | F15: ='Raw Data'!S25 -> 379805 | G15: ='Raw Data'!T25 -> 0.3 | H15: =E15/F15 -> 0.36054291 | I15: =E15/SUM(E15:F15) -> 0.26499929 | J15: ='Beta-Regression'!L15 -> 1.3125507 | K15: =J15/(1+(1-G15)*H15) -> 1.048045
B16: ='Raw Data'!O26 -> Hyundai Motor I | D16: ='Raw Data'!Q26 -> India | E16: ='Raw Data'!R26 -> 44351.36 | F16: ='Raw Data'!S26 -> 177405.45 | G16: ='Raw Data'!T26 -> 0.3 | H16: =E16/F16 -> 0.24999999 | I16: =E16/SUM(E16:F16) -> 0.19999999 | J16: 1 | K16: =J16/(1+(1-G16)*H16) -> 0.85106384
B17: ='Raw Data'!O27 -> Tata Motors PVeh | D17: ='Raw Data'!Q27 -> India | E17: ='Raw Data'!R27 -> 27773.61 | F17: ='Raw Data'!S27 -> 111094.43 | G17: ='Raw Data'!T27 -> 0.3 | H17: =E17/F17 -> 0.25000002 | I17: =E17/SUM(E17:F17) -> 0.20000001 | J17: 1 | K17: =J17/(1+(1-G17)*H17) -> 0.85106382
B18: ='Raw Data'!O28 -> Force Motors | D18: ='Raw Data'!Q28 -> India | E18: ='Raw Data'!R28 -> 5700.54 | F18: ='Raw Data'!S28 -> 22802.17 | G18: ='Raw Data'!T28 -> 0.3 | H18: =E18/F18 -> 0.24999989 | I18: =E18/SUM(E18:F18) -> 0.19999993 | J18: 1 | K18: =J18/(1+(1-G18)*H18) -> 0.85106389
F20: Average | G20: =AVERAGE(G14:G18) -> 0.3 | H20: =AVERAGE(H14:H18) -> 0.27210856 | I20: =AVERAGE(I14:I18) -> 0.21299984 | J20: =AVERAGE(J14:J18) -> 1.0625101 | K20: =AVERAGE(K14:K18) -> 0.89046008
F21: Median | G21: =MEDIAN(G14:G18) -> 0.3 | H21: =MEDIAN(H14:H18) -> 0.24999999 | I21: =MEDIAN(I14:I18) -> 0.2 | J21: =MEDIAN(J14:J18) -> 1 | K21: =MEDIAN(K14:K18) -> 0.85106384
B24: Cost of Debt | G24: Cost of Capital
B26: Pre-Tax Cost of Debt | E26: 0.0805 | G26: Risk Free Rate | K26: 0.07
B27: Tax Rate | E27: =G15 -> 0.3 | G27: Equity Risk Premium | K27: 0.065
B28: Post-Tax Cost of Debt | E28: =E26*(1-E27) -> 0.05635 | G28: Levered Beta | K28: =K36 -> 1.0123008
G29: Cost of Capital | K29: =K26+K27*K28 -> 0.13579955
B31: Capital Structure | G31: Levered Beta
D33: Current | E33: Target | G33: Comps Median Unlevered Beta | K33: =K21 -> 0.85106384
B34: Total Debt | C34: =E15 -> 136936 | D34: =C34/C$36 -> 0.26499929 | E34: =I20 -> 0.21299984 | G34: Target Debt/Equity | K34: =E38 -> 0.27064778
B35: Market Capitalization | C35: =F15 -> 379805 | D35: =C35/C$36 -> 0.73500071 | E35: =E36-E34 -> 0.78700016 | G35: Tax Rate | K35: =E27 -> 0.3
B36: Total Capital | C36: =SUM(C34:C35) -> 516741 | D36: =C36/C$36 -> 1 | E36: =D36 -> 1 | G36: Levered Beta | K36: =K33*(1+(1-K35)*K34) -> 1.0123008
B38: Debt /Equity | D38: =D34/D35 -> 0.36054291 | E38: =E34/E35 -> 0.27064778 | G38: WACC
G40: Cost of Equity | K40: =K29 -> 0.13579955
G41: Equity Weight | K41: =E35 -> 0.78700016
G43: Cost of Debt | K43: =E28 -> 0.05635
G44: Debt Weight | K44: =E34 -> 0.21299984
G46: WACC | K46: =(K40*K41)+(K43*K44) -> 0.11887681

Sheet Intrinsic Valuation
B6: Calculation of ROIC | H6: ='Raw FS'!J$3 -> 44621 | I6: ='Raw FS'!K$3 -> 44986 | J6: ='Raw FS'!L$3 -> 45352 | K6: ='Raw FS'!M$3 -> 45717 | L6: ='Raw FS'!N$3 -> 46082
B8: Current Assets
B9: ='Raw FS'!B39 -> Inventories | H9: ='Raw FS'!J39 -> 11596 | I9: ='Raw FS'!K39 -> 16855 | J9: ='Raw FS'!L39 -> 18590 | K9: ='Raw FS'!M39 -> 20331 | L9: ='Raw FS'!N39 -> 22044
B10: Trade Receivables | H10: ='Raw FS'!J40 -> 6374 | I10: ='Raw FS'!K40 -> 7028 | J10: ='Raw FS'!L40 -> 7459 | K10: ='Raw FS'!M40 -> 8280 | L10: ='Raw FS'!N40 -> 9064
B11: ='Raw FS'!B42 -> Loans n Advances | H11: ='Raw FS'!J42 -> 29242 | I11: ='Raw FS'!K42 -> 34685 | J11: ='Raw FS'!L42 -> 39060 | K11: ='Raw FS'!M42 -> 44645 | L11: ='Raw FS'!N42 -> 51137
B12: ='Raw FS'!B43 -> Other asset items | H12: ='Raw FS'!J43 -> 51277 | I12: ='Raw FS'!K43 -> 68061 | J12: ='Raw FS'!L43 -> 86222 | K12: ='Raw FS'!M43 -> 97900 | L12: ='Raw FS'!N43 -> 115307
B13: Total Current Assets | H13: =SUM(H9:H12) -> 98489 | I13: =SUM(I9:I12) -> 126629 | J13: =SUM(J9:J12) -> 151331 | K13: =SUM(K9:K12) -> 171156 | L13: =SUM(L9:L12) -> 197552
B15: Current Liabilities
B16: ='Raw FS'!B14 -> Trade Payables | H16: ='Raw FS'!J14 -> 19037 | I16: ='Raw FS'!K14 -> 23836 | J16: ='Raw FS'!L14 -> 25666 | K16: ='Raw FS'!M14 -> 30855 | L16: ='Raw FS'!N14 -> 37889
B17: ='Raw FS'!B15 -> Advance from Customers | H17: ='Raw FS'!J15 -> 0 | I17: ='Raw FS'!K15 -> 0 | J17: ='Raw FS'!L15 -> 0 | K17: ='Raw FS'!M15 -> 0 | L17: ='Raw FS'!N15 -> 0
B18: ='Raw FS'!B16 -> Other liability items | H18: ='Raw FS'!J16 -> 18921 | I18: ='Raw FS'!K16 -> 20719 | J18: ='Raw FS'!L16 -> 22900 | K18: ='Raw FS'!M16 -> 27035 | L18: ='Raw FS'!N16 -> 31738
B19: Total Current Liabilities | H19: =SUM(H16:H18) -> 37958 | I19: =SUM(I16:I18) -> 44555 | J19: =SUM(J16:J18) -> 48566 | K19: =SUM(K16:K18) -> 57890 | L19: =SUM(L16:L18) -> 69627
A21: # | B21: Net Working Capital | H21: =H13-H19 -> 60531 | I21: =I13-I19 -> 82074 | J21: =J13-J19 -> 102765 | K21: =K13-K19 -> 113266 | L21: =L13-L19 -> 127925
B23: Non Current Assets
B24: ='Raw FS'!B22 -> Land | H24: ='Raw FS'!J22 -> 1931 | I24: ='Raw FS'!K22 -> 1977 | J24: ='Raw FS'!L22 -> 2098 | K24: ='Raw FS'!M22 -> 2115 | L24: ='Raw FS'!N22 -> 2166
B25: ='Raw FS'!B23 -> Building | H25: ='Raw FS'!J23 -> 9728 | I25: ='Raw FS'!K23 -> 10862 | J25: ='Raw FS'!L23 -> 11496 | K25: ='Raw FS'!M23 -> 13100 | L25: ='Raw FS'!N23 -> 14886
B26: ='Raw FS'!B24 -> Plant Machinery | H26: ='Raw FS'!J24 -> 26484 | I26: ='Raw FS'!K24 -> 24928 | J26: ='Raw FS'!L24 -> 27230 | K26: ='Raw FS'!M24 -> 32547 | L26: ='Raw FS'!N24 -> 37437
B27: ='Raw FS'!B25 -> Equipments | H27: ='Raw FS'!J25 -> 445 | I27: ='Raw FS'!K25 -> 452 | J27: ='Raw FS'!L25 -> 481 | K27: ='Raw FS'!M25 -> 493 | L27: ='Raw FS'!N25 -> 542
B28: ='Raw FS'!B26 -> Furniture n fittings | H28: ='Raw FS'!J26 -> 844 | I28: ='Raw FS'!K26 -> 925 | J28: ='Raw FS'!L26 -> 1011 | K28: ='Raw FS'!M26 -> 1118 | L28: ='Raw FS'!N26 -> 1245
B29: ='Raw FS'!B27 -> Railway sidings | H29: ='Raw FS'!J27 -> 2 | I29: ='Raw FS'!K27 -> 2 | J29: ='Raw FS'!L27 -> 2 | K29: ='Raw FS'!M27 -> 2 | L29: ='Raw FS'!N27 -> 2
B30: ='Raw FS'!B28 -> Vehicles | H30: ='Raw FS'!J28 -> 1080 | I30: ='Raw FS'!K28 -> 1238 | J30: ='Raw FS'!L28 -> 1356 | K30: ='Raw FS'!M28 -> 1593 | L30: ='Raw FS'!N28 -> 1686
B31: ='Raw FS'!B29 -> Intangible Assets | H31: ='Raw FS'!J29 -> 7015 | I31: ='Raw FS'!K29 -> 10625 | J31: ='Raw FS'!L29 -> 11589 | K31: ='Raw FS'!M29 -> 13723 | L31: ='Raw FS'!N29 -> 16243
B32: ='Raw FS'!B30 -> Other fixed assets | H32: ='Raw FS'!J30 -> 999 | I32: ='Raw FS'!K30 -> 1084 | J32: ='Raw FS'!L30 -> 1202 | K32: ='Raw FS'!M30 -> 1454 | L32: ='Raw FS'!N30 -> 1750
B33: ='Raw FS'!B31 -> Gross Block | H33: ='Raw FS'!J31 -> 48526 | I33: ='Raw FS'!K31 -> 52090 | J33: ='Raw FS'!L31 -> 56462 | K33: ='Raw FS'!M31 -> 66143 | L33: ='Raw FS'!N31 -> 75955
B34: ='Raw FS'!B32 -> Accumulated Depreciation | H34: ='Raw FS'!J32 -> 22508 | I34: ='Raw FS'!K32 -> 24950 | J34: ='Raw FS'!L32 -> 28333 | K34: ='Raw FS'!M32 -> 31506 | L34: ='Raw FS'!N32 -> 37496
B35: Net Non Current Assets | H35: ='Raw FS'!J33 -> 26018 | I35: ='Raw FS'!K33 -> 27140 | J35: ='Raw FS'!L33 -> 28129 | K35: ='Raw FS'!M33 -> 34636 | L35: ='Raw FS'!N33 -> 38459
B37: Invested Capital | H37: =H35+H21 -> 86549 | I37: =I35+I21 -> 109214 | J37: =J35+J21 -> 130894 | K37: =K35+K21 -> 147902 | L37: =L35+L21 -> 166384
B38: EBIT | H38: ='Raw FS'!Z11+'Raw FS'!Z9 -> 14380 | I38: ='Raw FS'!AA11+'Raw FS'!AA9 -> 19890 | J38: ='Raw FS'!AB11+'Raw FS'!AB9 -> 23466 | K38: ='Raw FS'!AC11+'Raw FS'!AC9 -> 28163 | L38: ='Raw FS'!AD11+'Raw FS'!AD9 -> 34776
B40: ROIC | H40: =H38/H37 -> 0.16614866 | I40: =I38/I37 -> 0.18211951 | J40: =J38/J37 -> 0.17927483 | K40: =K38/K37 -> 0.19041663 | L40: =L38/L37 -> 0.20901048
B42: Calculation of Reinvestment Rate | H42: ='Raw FS'!J$3 -> 44621 | I42: ='Raw FS'!K$3 -> 44986 | J42: ='Raw FS'!L$3 -> 45352 | K42: ='Raw FS'!M$3 -> 45717 | L42: ='Raw FS'!N$3 -> 46082
B44: Net Capex | H44: =-SUM('Raw FS'!Z27:Z28) -> 5920 | I44: =-SUM('Raw FS'!AA27:AA28) -> 6167 | J44: =-SUM('Raw FS'!AB27:AB28) -> 9673 | K44: =-SUM('Raw FS'!AC27:AC28) -> 9809 | L44: =-SUM('Raw FS'!AD27:AD28) -> 9112
B45: Change in Work Cap | H45: - | I45: =I21-H21 -> 21543 | J45: =J21-I21 -> 20691 | K45: =K21-J21 -> 10501 | L45: =L21-K21 -> 14659
B47: EBIT | H47: =H38 -> 14380 | I47: =I38 -> 19890 | J47: =J38 -> 23466 | K47: =K38 -> 28163 | L47: =L38 -> 34776
B48: Tax Rate | H48: =WACC!E27 -> 0.3 | I48: =H48 -> 0.3 | J48: =I48 -> 0.3 | K48: =J48 -> 0.3 | L48: =K48 -> 0.3
B49: EBIT(1-T) | H49: =H47*(1-H48) -> 10066 | I49: =I47*(1-I48) -> 13923 | J49: =J47*(1-J48) -> 16426.2 | K49: =K47*(1-K48) -> 19714.1 | L49: =L47*(1-L48) -> 24343.2
B51: Reinvestment | H51: - | I51: =SUM(I44:I45) -> 27710 | J51: =SUM(J44:J45) -> 30364 | K51: =SUM(K44:K45) -> 20310 | L51: =SUM(L44:L45) -> 23771
B52: Reinvestment Rate | H52: - | I52: =I51/I49 -> 1.990232 | J52: =J51/J49 -> 1.8485103 | K52: =K51/K49 -> 1.0302271 | L52: =L51/L49 -> 0.97649446
J54: 4 Year Average | L54: =AVERAGE(I52:L52) -> 1.461366
J55: 4 Year Median | L55: =MEDIAN(I52:L52) -> 1.4393687
B57: Calculation of Growth Rate | H57: ='Raw FS'!J$3 -> 44621 | I57: ='Raw FS'!K$3 -> 44986 | J57: ='Raw FS'!L$3 -> 45352 | K57: ='Raw FS'!M$3 -> 45717 | L57: ='Raw FS'!N$3 -> 46082
B59: ROIC | H59: =H40 -> 0.16614866 | I59: =I40 -> 0.18211951 | J59: =J40 -> 0.17927483 | K59: =K40 -> 0.19041663 | L59: =L40 -> 0.20901048
B60: Reinvestment Rate | H60: - | I60: =I52 -> 1.990232 | J60: =J52 -> 1.8485103 | K60: =K52 -> 1.0302271 | L60: =L52 -> 0.97649446
B62: Intrinsic Growth | I62: =I59*I60 -> 0.36246007 | J62: =J59*J60 -> 0.33139138 | K62: =K59*K60 -> 0.19617237 | L62: =L59*L60 -> 0.20409758
J64: 4 Year Average | L64: =AVERAGE(I62:L62) -> 0.27353035
J65: 4 Year Median | L65: =MEDIAN(I62:L62) -> 0.26774448

Sheet DCF
B6: Calculation of PV of FCFF | H6: ='Data Sheet'!K56 -> 46082 | I6: =H6+365 -> 46447 | J6: =I6+365 -> 46812 | K6: =J6+365 -> 47177 | L6: =K6+365 -> 47542 | M6: =L6+365 -> 47907
B8: EBIT | H8: ='Intrinsic Valuation'!L38 -> 34776 | I8: =H8*(1+$D$18) -> 36584.352 | J8: =I8*(1+$D$18) -> 38486.738 | K8: =J8*(1+$D$18) -> 40488.049 | L8: =K8*(1+$D$18) -> 42593.427 | M8: =L8*(1+$D$18) -> 44808.285
B9: Tax Rate | H9: =WACC!G14 -> 0.3 | I9: =H9 -> 0.3 | J9: =I9 -> 0.3 | K9: =J9 -> 0.3 | L9: =K9 -> 0.3 | M9: =L9 -> 0.3
B10: EBIT(1-T) | H10: =H8*(1-H9) -> 24343.2 | I10: =I8*(1-I9) -> 25609.046 | J10: =J8*(1-J9) -> 26940.717 | K10: =K8*(1-K9) -> 28341.634 | L10: =L8*(1-L9) -> 29815.399 | M10: =M8*(1-M9) -> 31365.8
B11: Less: Reinvestment Rate | H11: ='Intrinsic Valuation'!$L$55 -> 1.4393687 | I11: =MIN(0.85, MAX(0.15, 'Intrinsic Valuation'!$L$55)) -> 0.85 | J11: =$I$11+($M$11-$I$11)/4*1 -> 0.7216207 | K11: =$I$11+($M$11-$I$11)/4*2 -> 0.59324139 | L11: =$I$11+($M$11-$I$11)/4*3 -> 0.46486209 | M11: =D21 -> 0.33648278
B12: Free Cash Flow to Firm | H12: =H10*(1-H11) -> -10695.64 | I12: =I10*(1-MIN(0.85, I11)) -> 3841.357 | J12: =J10*(1-MIN(0.85, J11)) -> 7499.738 | K12: =K10*(1-MIN(0.85, K11)) -> 11528.204 | L12: =L10*(1-MIN(0.85, L11)) -> 15955.35 | M12: =M10*(1-MIN(0.85, M11)) -> 20811.748
B13: Mid Year Convention | H13: - | I13: 0.5 | J13: =I13+1 -> 1.5 | K13: =J13+1 -> 2.5 | L13: =K13+1 -> 3.5 | M13: =L13+1 -> 4.5
B14: Discounting Factor | I14: =1/(1+$D$20)^I13 -> 0.94538534 | J14: =1/(1+$D$20)^J13 -> 0.8449414 | K14: =1/(1+$D$20)^K13 -> 0.75516929 | L14: =1/(1+$D$20)^L13 -> 0.67493515 | M14: =1/(1+$D$20)^M13 -> 0.60322561
B16: PV of FCFF | I16: =I12*I14 -> 3631.5626 | J16: =J12*J14 -> 6336.8391 | K16: =K12*K14 -> 8705.7453 | L16: =L12*L14 -> 10768.827 | M16: =M12*M14 -> 12554.18
B18: Expected Growth Rate | D18: 0.052
B19: Terminal Growth Rate | D19: 0.04
B20: WACC | D20: =WACC!K46 -> 0.11887681
B21: Terminal Reinvestment Rate | D21: =D19/D20 -> 0.33648278
B23: Calculation of Terminal Value
B25: FCFF(n+1) | D25: =M12*(1+D19) -> 21644.218
B26: WACC | D26: =D20 -> 0.11887681
B27: Terminal Growth Rate | D27: =D19 -> 0.04
B29: Terminal value | D29: =D25/(D26-D27) -> 274405.34
B31: Calculation of Equity Value
B33: PV of FCFF | D33: =SUM(I16:M16) -> 41997.153
B34: Terminal value | D34: =D29*M14 -> 165528.33
B35: Value of Operating Assets | D35: =SUM(D33:D34) -> 207525.48
B37: Add: Cash | D37: ='Data Sheet'!K69 -> 31979
B38: Less: Debt | D38: ='Data Sheet'!K59 -> 136936
B39: Equity Value | D39: =D35+D37-D38 -> 102568.48
B40: No. of Shares | D40: ='Data Sheet'!K70/10000000 -> 111.8
B42: Equity Value per Share | D42: =D39/D40 -> 917.42829
B44: Share Price | D44: ='Data Sheet'!B8 -> 3055
B45: Discount /Premium | D45: =D44/D42 -> 3.3299605

Sheet Raw Data
B6: 2025 | C6: 0.1051 | G6: 46286 | H6: 3055.3 | J6: 23414.3
B7: 2024 | C7: 0.0875 | G7: 46283 | H7: 3052 | J7: 23346.4
B8: 2023 | C8: 0.1942 | G8: 46282 | H8: 3076.5 | J8: 23270.6
B9: 2022 | C9: 0.0432 | G9: 46281 | H9: 3070 | J9: 23217.6
B10: 2021 | C10: 0.2412 | G10: 46280 | H10: 3029.5 | J10: 23118.6
B11: 2020 | C11: 0.149 | G11: 46276 | H11: 3107 | J11: 23398.1 | N11: S.No. | O11: Name | P11: CMP Rs. | Q11: No. Eq. Shares Cr. | R11: Mar Cap Rs.Cr. | S11: Debt Rs.Cr. | T11: Cash End Rs.Cr. | U11: EV Rs.Cr. | V11: Sales Rs.Cr. | W11: EV / EBITDA | X11: NP 12M Rs.Cr.
B12: 2019 | C12: 0.1202 | G12: 46275 | H12: 3123.8 | J12: 23477.8 | N12: 1 | O12: Maruti Suzuki | P12: 12153 | Q12: 31.33 | R12: 380772.09 | S12: 95193.02 | T12: 19038.6 | U12: 456926.51 | V12: 66052 | W12: 30.61 | X12: 14971
B13: 2018 | C13: 0.0315 | G13: 46274 | H13: 3150 | J13: 23431.5 | N13: 2 | O13: MAHINDRA & MAHINDRA LTD | P13: 0 | Q13: 82.75 | R13: 379805 | S13: 136936 | T13: 8870.27 | U13: 212886.54 | V13: 76487.98 | W13: 12.44 | X13: 20183.53
B14: 2017 | C14: 0.2865 | G14: 46273 | H14: 3160 | J14: 23635.1 | N14: 3 | O14: Hyundai Motor I | P14: 2144 | Q14: 368.29 | R14: 177405.45 | S14: 44351.36 | T14: 5554.72 | U14: 133313.32 | V14: 4400.19 | W14: 20.53 | X14: 158.3
B15: 2016 | C15: 0.0301 | G15: 46272 | H15: 3160 | J15: 23779.15 | N15: 4 | O15: Tata Motors PVeh | P15: 301.65 | Q15: 1.3 | R15: 111094.43 | S15: 27773.61 | T15: 1140.11 | U15: 27362.6 | V15: 2012.58 | W15: 12.74 | X15: 0.22
B16: 2015 | C16: -0.0406 | G16: 46269 | H16: 3170 | J16: 23897.7 | N16: 5 | O16: Force Motors | P16: 17485 | Q16: 8.2 | R16: 22802.17 | S16: 5700.54 | T16: 494.68 | U16: 11872.29 | V16: 238.77 | W16: 13.43 | X16: 8.51
B17: 2014 | C17: 0.3139 | G17: 46268 | H17: 3150 | J17: 23873.45 | N17: 6 | O17: Mercury EV-Tech | P17: 39.81 | Q17: 19.02 | R17: 757.23 | S17: 189.31 | T17: 37.86 | U17: 908.68
B18: 2013 | C18: 0.0676 | G18: 46267 | H18: 3190 | J18: 23914.45
B19: 2012 | C19: 0.277 | G19: 46266 | H19: 3259 | J19: 24055.8
B20: 2011 | C20: -0.2462 | G20: 46265 | H20: 3282 | J20: 24080.4
B21: 2010 | C21: 0.1795 | G21: 46262 | H21: 3334 | J21: 24175.65
B22: 2009 | C22: 0.7576 | G22: 46261 | H22: 3330 | J22: 24090.85
B23: 2008 | C23: -0.5179 | G23: 46260 | H23: 3398.2 | J23: 24207.75
B24: 2007 | C24: 0.5477 | G24: 46259 | H24: 3443 | J24: 24334.55 | O24: Maruti Suzuki | Q24: India | R24: 95193.02 | S24: 380772.09 | T24: 0.3
B25: 2006 | C25: 0.3983 | G25: 46258 | H25: 3414.1 | J25: 24219.05 | O25: MAHINDRA & MAHINDRA LTD | Q25: =Q24 -> India | R25: 136936 | S25: 379805 | T25: =T24 -> 0.3
B26: 2005 | C26: 0.3634 | G26: 46255 | H26: 3412.2 | J26: 24252 | O26: Hyundai Motor I | Q26: =Q25 -> India | R26: 44351.36 | S26: 177405.45 | T26: =T25 -> 0.3
B27: 2004 | C27: 0.1068 | G27: 46254 | H27: 3424.8 | J27: 24231.85 | O27: Tata Motors PVeh | Q27: =Q26 -> India | R27: 27773.61 | S27: 111094.43 | T27: =T26 -> 0.3
B28: 2003 | C28: 0.719 | G28: 46253 | H28: 3415 | J28: 24078.3 | O28: Force Motors | Q28: =Q27 -> India | R28: 5700.54 | S28: 22802.17 | T28: =T27 -> 0.3
B29: 2002 | C29: 0.0325 | G29: 46252 | H29: 3421.5 | J29: 24154.9
G30: 46251 | H30: 3390.4 | J30: 24287.65
G31: 46248 | H31: 3428.3 | J31: 24366
G32: 46247 | H32: 3428.2 | J32: 24395.85
G33: 46246 | H33: 3403.6 | J33: 24435.95
G34: 46245 | H34: 3460.1 | J34: 24471.7
G35: 46244 | H35: 3517 | J35: 24583.8
G36: 46241 | H36: 3502 | J36: 24570.65
G37: 46240 | H37: 3406 | J37: 24636
G38: 46239 | H38: 3455.4 | J38: 24624.65
G39: 46238 | H39: 3433 | J39: 24614.9
G40: 46237 | H40: 3428.6 | J40: 24774.3
G41: 46234 | H41: 3398.5 | J41: 24383.6
... G252: 45922 | H252: 3584.8 | J252: 25202.35

Sheet Comp_Valuation
B6: Amount in crores
B7: Company Comparable Valuation
D9: Market Data | K9: Financials | O9: Valuation
B10: Company | C10: Ticker | D10: Share Price | E10: Share Outstanding | F10: Equity Value | G10: Net Debt value | H10: Enterprise Value | I10: EV/Revenue | J10: EV/EBITDA | K10: Revenue | L10: EBITDA | M10: Net Income | O10: EV/Revenue | P10: EV/EBITDA | Q10: P/E
B12: ='Raw FS'!L57 -> Maruti Suzuki | C12: MARUTI | D12: ='Raw FS'!M57 -> 12153 | E12: ='Raw FS'!N57 -> 31.33 | F12: =D12*E12 -> 380753.49 | G12: ='Raw FS'!AS57 -> 76154.42 | H12: ='Raw FS'!AT57 -> 456926.51 | I12: =IF(G12>0, F12/G12, "N/A") -> 4.9997556 | J12: =IF(H12>0, F12/H12, "N/A") -> 0.83329262 | K12: ='Raw FS'!AU57 -> 209879.2 | L12: ='Raw FS'!AV57 -> 31481.88 | M12: ='Raw FS'!AW57 -> 13787.6 | O12: =IFERROR($H12/K12, "N/A") -> 2.1770929 | P12: =IFERROR($H12/L12, "N/A") -> 14.513952 | Q12: =IFERROR(F12/M12, "N/A") -> 27.615647
B13: ='Raw FS'!L58 -> Hyundai Motor I | C13: HYUNDAI | D13: ='Raw FS'!M58 -> 2144 | E13: ='Raw FS'!N58 -> 82.75 | F13: =D13*E13 -> 177416 | G13: ='Raw FS'!AS58 -> 35481.09 | H13: ='Raw FS'!AT58 -> 212886.54 | I13: =IF(G13>0, F13/G13, "N/A") -> 5.0002973 | J13: =IF(H13>0, F13/H13, "N/A") -> 0.83338289 | K13: ='Raw FS'!AU58 -> 65338.52 | L13: ='Raw FS'!AV58 -> 9800.78 | M13: ='Raw FS'!AW58 -> 3554.48 | O13: =IFERROR($H13/K13, "N/A") -> 3.2582088 | P13: =IFERROR($H13/L13, "N/A") -> 21.721387 | Q13: =IFERROR(F13/M13, "N/A") -> 49.913349
B14: ='Raw FS'!L59 -> Tata Motors PVeh | C14: TMPV | D14: ='Raw FS'!M59 -> 301.65 | E14: ='Raw FS'!N59 -> 368.29 | F14: =D14*E14 -> 111094.68 | G14: ='Raw FS'!AS59 -> 22218.89 | H14: ='Raw FS'!AT59 -> 133313.32 | I14: =IF(G14>0, F14/G14, "N/A") -> 5.0000103 | J14: =IF(H14>0, F14/H14, "N/A") -> 0.83333517 | K14: ='Raw FS'!AU59 -> 383196 | L14: ='Raw FS'!AV59 -> 57479.4 | M14: ='Raw FS'!AW59 -> 3436 | O14: =IFERROR($H14/K14, "N/A") -> 0.34789852 | P14: =IFERROR($H14/L14, "N/A") -> 2.3193234 | Q14: =IFERROR(F14/M14, "N/A") -> 32.332561
B15: ='Raw FS'!L60 -> Force Motors | C15: FORCEMOT | D15: ='Raw FS'!M60 -> 17485 | E15: ='Raw FS'!N60 -> 1.3 | F15: =D15*E15 -> 22730.5 | G15: ='Raw FS'!AS60 -> 4560.43 | H15: ='Raw FS'!AT60 -> 27362.6 | I15: =IF(G15>0, F15/G15, "N/A") -> 4.9842888 | J15: =IF(H15>0, F15/H15, "N/A") -> 0.83071419 | K15: ='Raw FS'!AU60 -> 9760.04 | L15: ='Raw FS'!AV60 -> 1464.01 | M15: ='Raw FS'!AW60 -> 866.36 | O15: =IFERROR($H15/K15, "N/A") -> 2.8035336 | P15: =IFERROR($H15/L15, "N/A") -> 18.690173 | Q15: =IFERROR(F15/M15, "N/A") -> 26.236784
B16: ='Raw FS'!L61 -> Olectra Greentec | C16: OLECTRA | D16: ='Raw FS'!M61 -> 1205.8 | E16: ='Raw FS'!N61 -> 8.2 | F16: =D16*E16 -> 9887.56 | G16: ='Raw FS'!AS61 -> 1978.71 | H16: ='Raw FS'!AT61 -> 11872.29 | I16: =IF(G16>0, F16/G16, "N/A") -> 4.9969728 | J16: =IF(H16>0, F16/H16, "N/A") -> 0.83282669 | K16: ='Raw FS'!AU61 -> 2302.04 | L16: ='Raw FS'!AV61 -> 345.31 | M16: ='Raw FS'!AW61 -> 106.64 | O16: =IFERROR($H16/K16, "N/A") -> 5.1572909 | P16: =IFERROR($H16/L16, "N/A") -> 34.381541 | Q16: =IFERROR(F16/M16, "N/A") -> 92.719055
B17: ='Raw FS'!L62 -> Mercury EV-Tech | C17: MERCURYEV | D17: ='Raw FS'!M62 -> 39.81 | E17: ='Raw FS'!N62 -> 19.02 | F17: =D17*E17 -> 757.1862 | G17: ='Raw FS'!AS62 -> 151.45 | H17: ='Raw FS'!AT62 -> 908.68 | I17: =IF(G17>0, F17/G17, "N/A") -> 4.9995787 | J17: =IF(H17>0, F17/H17, "N/A") -> 0.83328146 | K17: ='Raw FS'!AU62 -> 133.52 | L17: ='Raw FS'!AV62 -> 20.03 | M17: ='Raw FS'!AW62 -> 6.6 | O17: =IFERROR($H17/K17, "N/A") -> 6.8055722 | P17: =IFERROR($H17/L17, "N/A") -> 45.365951 | Q17: =IFERROR(F17/M17, "N/A") -> 114.72518
B23: High | I23: =MAX(I12:I17) -> 5.0002973 | J23: =MAX(J12:J17) -> 0.83338289 | O23: =MAX(O12:O17) -> 6.8055722 | P23: =MAX(P12:P17) -> 45.365951 | Q23: =MAX(Q12:Q17) -> 114.72518
B24: 25th Percentile | I24: =_xlfn.QUARTILE.INC(I12:I17,1) -> 4.9976243 | J24: =_xlfn.QUARTILE.INC(J12:J17,1) -> 0.83294038 | O24: =_xlfn.QUARTILE.INC(O12:O17,1) -> 2.3337031 | P24: =_xlfn.QUARTILE.INC(P12:P17,1) -> 15.558008 | Q24: =_xlfn.QUARTILE.INC(Q12:Q17,1) -> 28.794875
B25: Median | I25: =MEDIAN(I12:I17) -> 4.9996672 | J25: =MEDIAN(J12:J17) -> 0.83328704 | O25: =MEDIAN(O12:O17) -> 3.0308712 | P25: =MEDIAN(P12:P17) -> 20.20578 | Q25: =MEDIAN(Q12:Q17) -> 41.122955
B26: Average | I26: =AVERAGE(I12:I17) -> 4.9968173 | J26: =AVERAGE(J12:J17) -> 0.8328055 | O26: =AVERAGE(O12:O17) -> 3.4249328 | P26: =AVERAGE(P12:P17) -> 22.832055 | Q26: =AVERAGE(Q12:Q17) -> 57.257096
B27: 75th Percentile | I27: =_xlfn.QUARTILE.INC(I12:I17,3) -> 4.9999466 | J27: =_xlfn.QUARTILE.INC(J12:J17,3) -> 0.83332453 | O27: =_xlfn.QUARTILE.INC(O12:O17,3) -> 4.6825204 | P27: =_xlfn.QUARTILE.INC(P12:P17,3) -> 31.216503 | Q27: =_xlfn.QUARTILE.INC(Q12:Q17,3) -> 82.017628
B28: Low | I28: =MIN(I12:I17) -> 4.9842888 | J28: =MIN(J12:J17) -> 0.83071419 | O28: =MIN(O12:O17) -> 0.34789852 | P28: =MIN(P12:P17) -> 2.3193234 | Q28: =MIN(Q12:Q17) -> 26.236784
B30: MAHINDRA & MAHINDRA LTD Comparable Valuation | I30: EV/Revenue | J30: EV/EBITDA | O30: EV/Revenue | P30: EV/EBITDA | Q30: P/E
B32: Implied Enterprise Value | O32: ='Raw FS'!AU56*O26 -> 680325.23 | P32: ='Raw FS'!AV56*P26 -> 1386362.4 | Q32: ='Raw FS'!AW56*Q26 -> 1066241.6
B33: Net Debt Value | O33: ='Raw FS'!AS56 -> 104957 | P33: ='Raw FS'!AS56 -> 104957 | Q33: ='Raw FS'!AS56 -> 104957
B34: Implied Market Value | O34: =O32-O33 -> 575368.23 | P34: =P32-P33 -> 1281405.4 | Q34: =Q32 -> 1066241.6
B35: Share Outstanding | O35: ='Raw FS'!N56 -> 124.32242 | P35: ='Raw FS'!N56 -> 124.32242 | Q35: ='Raw FS'!N56 -> 124.32242
B37: Implied Value per Share | O37: =O34/O35 -> 4628.0327 | P37: =P34/P35 -> 10307.114 | Q37: =Q34/Q35 -> 8576.4227
B38: Source : Screener.in
B39: Verdict | O39: =IF(O37>'Raw FS'!M56,"Undervalued","Overvalued") -> Undervalued | P39: =IF(P37="N/A","N/A",IF(P37>'Raw FS'!M56,"Undervalued","Overvalued")) -> Undervalued | Q39: =IF(Q37>'Raw FS'!M56,"Undervalued","Overvalued") -> Undervalued

Sheet Dupont Analysis
B2: ='Data Sheet'!B1 -> MAHINDRA & MAHINDRA LTD
B3: =CONCATENATE("(",VLOOKUP(B2,'List of Stocks'!B2:E5442,3,FALSE)," | ","BSE Code: ",VLOOKUP('Dupont Analysis'!B2,'List of Stocks'!B2:E5442,2,FALSE)) -> (M&M | BSE Code: 500520
B4: =CONCATENATE(" ","INR "&'Data Sheet'!B8) -> INR 3055
B5: 52 Week (High - INR - 3,840.00 & low INR - 2,896.00)
B6: About the Company
B8: Mahindra Automotive is an Indian automobile manufacturing company headquartered in Mumbai. It was established in 1945 as Mahindra & Mohammed and later renamed Mahindra & Mahindra. Part of the Mahindra Group, Mahindra Automotive is one of the largest SUV manufacturers by production in India and the Mahindra Tractors subsidiary is the largest manufacturer of tractors in the world by volume. It was ranked 18th on a list of top companies in India by Fortune India 500 in 2025. Its major competitors in the Indian vehicular market include Maruti Suzuki and Tata Motors. Anish Shah is the current CEO and Managing Director of Mahindra Automotive.
B15: Financial Summary
B35: Recent Updates
A37: • | B37: Mahindra's Rajesh Jejurikar on How it Became A Design First Auto-Maker
A39: • | B39: ‘When we stop asking 'Who will fix this?’: Anand Mahindra praises Maharashtra town's people who revived a dying river and won Rs 1 crore prize
A41: • | B41: M&M Share Price Today, M&M Stock Price Live NSE/BSE Updates
A43: • | B43: Why Traditional Research Doesn’t Work in Mahindra: The Brand Equity Show
A45: • | B45: Mahindra XUV 3XO REVX EDGE launched at ₹9.39 lakh; petrol automatic variant added to REVX M(O)
A47: • | B47: MAHINDRA & MAHINDRA LTD continued strategic operational investments and customer engagements to drive sustainable long-term business performance.
B54: Dupont Analysis - Return on Equity & Return on Assets
B58: Return on Equity
E59: ='Data Sheet'!G$56 -> 44621 | F59: ='Data Sheet'!H$56 -> 44986 | G59: ='Data Sheet'!I$56 -> 45352 | H59: ='Data Sheet'!J$56 -> 45717 | I59: ='Data Sheet'!K$56 -> 46082
B60: Net Profit | E60: =E66 -> 7253 | F60: =F66 -> 11374 | G60: =G66 -> 12270 | H60: =H66 -> 14073 | I60: =I66 -> 18622
B61: Average Shareholder's Equity | E61: =E75 -> 44352.5 | F61: =F75 -> 51744.5 | G61: =G75 -> 61278 | H61: =H75 -> 71614.5 | I61: =I75 -> 85068
B62: Return on Equity | E62: =E60/E61 -> 0.1635308 | F62: =F60/F61 -> 0.2198108 | G62: =G60/G61 -> 0.20023499 | H62: =H60/H61 -> 0.19651048 | I62: =I60/I61 -> 0.21890723
B64: ROE - Dupont Analysis
E65: ='Data Sheet'!G$56 -> 44621 | F65: ='Data Sheet'!H$56 -> 44986 | G65: ='Data Sheet'!I$56 -> 45352 | H65: ='Data Sheet'!J$56 -> 45717 | I65: ='Data Sheet'!K$56 -> 46082
B66: Net Profit | E66: ='Data Sheet'!G30 -> 7253 | F66: ='Data Sheet'!H30 -> 11374 | G66: ='Data Sheet'!I30 -> 12270 | H66: ='Data Sheet'!J30 -> 14073 | I66: ='Data Sheet'!K30 -> 18622
B67: Revenue | E67: ='Data Sheet'!G17 -> 90171 | F67: ='Data Sheet'!H17 -> 121362 | G67: ='Data Sheet'!I17 -> 139078 | H67: ='Data Sheet'!J17 -> 159211 | I67: ='Data Sheet'!K17 -> 198639
B68: Net Profit Margin (A) | E68: =E66/E67 -> 0.08043606 | F68: =F66/F67 -> 0.093719616 | G68: =G66/G67 -> 0.088223874 | H68: =H66/H67 -> 0.088392134 | I68: =I66/I67 -> 0.093747955
B70: Revenue | E70: =E67 -> 90171 | F70: =F67 -> 121362 | G70: =G67 -> 139078 | H70: =H67 -> 159211 | I70: =I67 -> 198639
B71: Average Total Assets | E71: =SUM('Data Sheet'!F66:G66)/2 -> 168678 | F71: =SUM('Data Sheet'!G66:H66)/2 -> 188335.5 | G71: =SUM('Data Sheet'!H66:I66)/2 -> 219502.5 | H71: =SUM('Data Sheet'!I66:J66)/2 -> 255367.5 | I71: =SUM('Data Sheet'!J66:K66)/2 -> 296033.5
B72: Asset Turnover Ratio (B) | E72: =E70/E71 -> 0.53457475 | F72: =F70/F71 -> 0.64439259 | G72: =G70/G71 -> 0.63360554 | H72: =H70/H71 -> 0.62345835 | I72: =I70/I71 -> 0.67100176
B74: Average Total Assets | E74: =E71 -> 168678 | F74: =F71 -> 188335.5 | G74: =G71 -> 219502.5 | H74: =H71 -> 255367.5 | I74: =I71 -> 296033.5
B75: Average Shareholder's Equity | E75: =(SUM('Data Sheet'!F57:F58)+SUM('Data Sheet'!G57:G58))/2 -> 44352.5 | F75: =(SUM('Data Sheet'!G57:G58)+SUM('Data Sheet'!H57:H58))/2 -> 51744.5 | G75: =(SUM('Data Sheet'!H57:H58)+SUM('Data Sheet'!I57:I58))/2 -> 61278 | H75: =(SUM('Data Sheet'!I57:I58)+SUM('Data Sheet'!J57:J58))/2 -> 71614.5 | I75: =(SUM('Data Sheet'!J57:J58)+SUM('Data Sheet'!K57:K58))/2 -> 85068
B76: Equity Multiplier (C) | E76: =E74/E75 -> 3.8031227 | F76: =F74/F75 -> 3.6397202 | G76: =G74/G75 -> 3.5820768 | H76: =H74/H75 -> 3.5658631 | I76: =I74/I75 -> 3.4799631
B78: Return on Equity(A*B*C) | E78: =E68*E72*E76 -> 0.1635308 | F78: =F68*F72*F76 -> 0.2198108 | G78: =G68*G72*G76 -> 0.20023499 | H78: =H68*H72*H76 -> 0.19651048 | I78: =I68*I72*I76 -> 0.21890723
B80: Return on Assets
E81: ='Data Sheet'!G$56 -> 44621 | F81: ='Data Sheet'!H$56 -> 44986 | G81: ='Data Sheet'!I$56 -> 45352 | H81: ='Data Sheet'!J$56 -> 45717 | I81: ='Data Sheet'!K$56 -> 46082
B82: Net Profit | E82: =E66 -> 7253 | F82: =F66 -> 11374 | G82: =G66 -> 12270 | H82: =H66 -> 14073 | I82: =I66 -> 18622
B83: Average Total Assets | E83: =E74 -> 168678 | F83: =F74 -> 188335.5 | G83: =G74 -> 219502.5 | H83: =H74 -> 255367.5 | I83: =I74 -> 296033.5
B84: Return on Assets | E84: =E82/E83 -> 0.042999087 | F84: =F82/F83 -> 0.060392226 | G84: =G82/G83 -> 0.055899136 | H84: =H82/H83 -> 0.055108814 | I84: =I82/I83 -> 0.062905043
B86: ROA - Dupont Equation
E87: ='Data Sheet'!G$56 -> 44621 | F87: ='Data Sheet'!H$56 -> 44986 | G87: ='Data Sheet'!I$56 -> 45352 | H87: ='Data Sheet'!J$56 -> 45717 | I87: ='Data Sheet'!K$56 -> 46082
B88: Net Profit | E88: =E66 -> 7253 | F88: =F66 -> 11374 | G88: =G66 -> 12270 | H88: =H66 -> 14073 | I88: =I66 -> 18622
B89: Revenue | E89: =E67 -> 90171 | F89: =F67 -> 121362 | G89: =G67 -> 139078 | H89: =H67 -> 159211 | I89: =I67 -> 198639
B90: Net Profit Margin (A) | E90: =E68 -> 0.08043606 | F90: =F68 -> 0.093719616 | G90: =G68 -> 0.088223874 | H90: =H68 -> 0.088392134 | I90: =I68 -> 0.093747955
B92: Revenue | E92: =E67 -> 90171 | F92: =F67 -> 121362 | G92: =G67 -> 139078 | H92: =H67 -> 159211 | I92: =I67 -> 198639
B93: Average Total Assets | E93: =E71 -> 168678 | F93: =F71 -> 188335.5 | G93: =G71 -> 219502.5 | H93: =H71 -> 255367.5 | I93: =I71 -> 296033.5
B94: Asset Turnover Ratio (B) | E94: =E72 -> 0.53457475 | F94: =F72 -> 0.64439259 | G94: =G72 -> 0.63360554 | H94: =H72 -> 0.62345835 | I94: =I72 -> 0.67100176
B96: Return on Assets (A*B) | E96: =E90*E94 -> 0.042999087 | F96: =F90*F94 -> 0.060392226 | G96: =G90*G94 -> 0.055899136 | H96: =H90*H94 -> 0.055108814 | I96: =I90*I94 -> 0.062905043

Sheet Altman's Z Score
B2: ='Data Sheet'!B1 -> MAHINDRA & MAHINDRA LTD
B3: =CONCATENATE("(",VLOOKUP(B2,'List of Stocks'!B2:E5442,3,FALSE)," | ","BSE Code: ",VLOOKUP('Altman''s Z Score'!B2,'List of Stocks'!B2:E5442,2,FALSE)) -> (M&M | BSE Code: 500520
B4: =CONCATENATE(" ","INR "&'Data Sheet'!B8) -> INR 3055
B5: 52 Week (High - INR - 3,840.00 & low INR - 2,896.00)
B6: About the Company
B8: Mahindra Automotive is an Indian automobile manufacturing company headquartered in Mumbai. It was established in 1945 as Mahindra & Mohammed and later renamed Mahindra & Mahindra. Part of the Mahindra Group, Mahindra Automotive is one of the largest SUV manufacturers by production in India and the Mahindra Tractors subsidiary is the largest manufacturer of tractors in the world by volume. It was ranked 18th on a list of top companies in India by Fortune India 500 in 2025. Its major competitors in the Indian vehicular market include Maruti Suzuki and Tata Motors. Anish Shah is the current CEO and Managing Director of Mahindra Automotive.
B14: Financial Summary
B34: Recent Updates
A36: • | B36: Mahindra's Rajesh Jejurikar on How it Became A Design First Auto-Maker
A38: • | B38: ‘When we stop asking 'Who will fix this?’: Anand Mahindra praises Maharashtra town's people who revived a dying river and won Rs 1 crore prize
A40: • | B40: M&M Share Price Today, M&M Stock Price Live NSE/BSE Updates
A42: • | B42: Why Traditional Research Doesn’t Work in Mahindra: The Brand Equity Show
A44: • | B44: Mahindra XUV 3XO REVX EDGE launched at ₹9.39 lakh; petrol automatic variant added to REVX M(O)
A46: • | B46: MAHINDRA & MAHINDRA LTD continued strategic operational investments and customer engagements to drive sustainable long-term business performance.
B53: Altman's Z Score Analysis Calculation
B57: Working Capital /Total assets (A)
E58: ='Data Sheet'!G$56 -> 44621 | F58: ='Data Sheet'!H$56 -> 44986 | G58: ='Data Sheet'!I$56 -> 45352 | H58: ='Data Sheet'!J$56 -> 45717 | I58: ='Data Sheet'!K$56 -> 46082
B59: Working Capital | E59: ='Data Sheet'!G65-'Data Sheet'!G60 -> 61946 | F59: ='Data Sheet'!H65-'Data Sheet'!H60 -> 82632 | G59: ='Data Sheet'!I65-'Data Sheet'!I60 -> 103461 | H59: ='Data Sheet'!J65-'Data Sheet'!J60 -> 121821 | I59: ='Data Sheet'!K65-'Data Sheet'!K60 -> 143510
B60: Total Assets | E60: ='Data Sheet'!G66 -> 172388 | F60: ='Data Sheet'!H66 -> 204283 | G60: ='Data Sheet'!I66 -> 234722 | H60: ='Data Sheet'!J66 -> 276013 | I60: ='Data Sheet'!K66 -> 316054
B61: Working Capital / Total assets (A) | E61: =E59/E60 -> 0.35934056 | F61: =F59/F60 -> 0.40449768 | G61: =G59/G60 -> 0.44078101 | H61: =H59/H60 -> 0.44135965 | I61: =I59/I60 -> 0.45406798
B63: Retained Earnings /Total Assets (B)
E64: ='Data Sheet'!G$56 -> 44621 | F64: ='Data Sheet'!H$56 -> 44986 | G64: ='Data Sheet'!I$56 -> 45352 | H64: ='Data Sheet'!J$56 -> 45717 | I64: ='Data Sheet'!K$56 -> 46082
B65: Retained Earnings | E65: ='Data Sheet'!G58 -> 46567 | F65: ='Data Sheet'!H58 -> 55809 | G65: ='Data Sheet'!I58 -> 65633 | H65: ='Data Sheet'!J58 -> 76481 | I65: ='Data Sheet'!K58 -> 92538
B66: Total Assets | E66: =E60 -> 172388 | F66: =F60 -> 204283 | G66: =G60 -> 234722 | H66: =H60 -> 276013 | I66: =I60 -> 316054
B67: Retained Earnings /Total Assets (B) | E67: =E65/E66 -> 0.27012901 | F67: =F65/F66 -> 0.27319454 | G67: =G65/G66 -> 0.27962015 | H67: =H65/H66 -> 0.27709202 | I67: =I65/I66 -> 0.29279174
B69: EBIT /Total Assets (C)
E70: ='Data Sheet'!G$56 -> 44621 | F70: ='Data Sheet'!H$56 -> 44986 | G70: ='Data Sheet'!I$56 -> 45352 | H70: ='Data Sheet'!J$56 -> 45717 | I70: ='Data Sheet'!K$56 -> 46082
B71: EBIT | E71: ='Intrinsic Valuation'!H47 -> 14380 | F71: ='Intrinsic Valuation'!I47 -> 19890 | G71: ='Intrinsic Valuation'!J47 -> 23466 | H71: ='Intrinsic Valuation'!K47 -> 28163 | I71: ='Intrinsic Valuation'!L47 -> 34776
B72: Total Assets | E72: =E66 -> 172388 | F72: =F66 -> 204283 | G72: =G66 -> 234722 | H72: =H66 -> 276013 | I72: =I66 -> 316054
B73: EBIT /Total Assets (C) | E73: =E71/E72 -> 0.083416479 | F73: =F71/F72 -> 0.09736493 | G73: =G71/G72 -> 0.099973586 | H73: =H71/H72 -> 0.10203505 | I73: =I71/I72 -> 0.11003183
B75: Market Cap /Long Term Liabilities (D)
E76: ='Data Sheet'!G$56 -> 44621 | F76: ='Data Sheet'!H$56 -> 44986 | G76: ='Data Sheet'!I$56 -> 45352 | H76: ='Data Sheet'!J$56 -> 45717 | I76: ='Data Sheet'!K$56 -> 46082
B77: Market Capital | E77: ='Data Sheet'!G90*'Data Sheet'!G93 -> 98018.355 | F77: ='Data Sheet'!H90*'Data Sheet'!H93 -> 169802.11 | G77: ='Data Sheet'!I90*'Data Sheet'!I93 -> 262359.38 | H77: ='Data Sheet'!J90*'Data Sheet'!J93 -> 346015.63 | I77: ='Data Sheet'!K90*'Data Sheet'!K93 -> 454741.99
B78: Long Term Liabilities | E78: =SUM('Data Sheet'!G59:G60) -> 125266 | F78: =SUM('Data Sheet'!H59:H60) -> 147917 | G78: =SUM('Data Sheet'!I59:I60) -> 168531 | H78: =SUM('Data Sheet'!J59:J60) -> 198975 | I78: =SUM('Data Sheet'!K59:K60) -> 222957
B79: Market Cap /Long Term Liabilities (D) | E79: =E77/E78 -> 0.78248172 | F79: =F77/F78 -> 1.1479553 | G79: =G77/G78 -> 1.5567426 | H79: =H77/H78 -> 1.7389905 | I79: =I77/I78 -> 2.039595
B81: Total Sales /Total Assets (E)
E82: ='Data Sheet'!G$56 -> 44621 | F82: ='Data Sheet'!H$56 -> 44986 | G82: ='Data Sheet'!I$56 -> 45352 | H82: ='Data Sheet'!J$56 -> 45717 | I82: ='Data Sheet'!K$56 -> 46082
B83: Total Sales | E83: ='Data Sheet'!G17 -> 90171 | F83: ='Data Sheet'!H17 -> 121362 | G83: ='Data Sheet'!I17 -> 139078 | H83: ='Data Sheet'!J17 -> 159211 | I83: ='Data Sheet'!K17 -> 198639
B84: Total Assets | E84: =E72 -> 172388 | F84: =F72 -> 204283 | G84: =G72 -> 234722 | H84: =H72 -> 276013 | I84: =I72 -> 316054
B85: Total Sales /Total Assets (E) | E85: =E83/E84 -> 0.52307005 | F85: =F83/F84 -> 0.59408761 | G85: =G83/G84 -> 0.59252222 | H85: =H83/H84 -> 0.57682428 | I85: =I83/I84 -> 0.62849703
B87: Altman's Z Score
E88: ='Data Sheet'!G$56 -> 44621 | F88: ='Data Sheet'!H$56 -> 44986 | G88: ='Data Sheet'!I$56 -> 45352 | H88: ='Data Sheet'!J$56 -> 45717 | I88: ='Data Sheet'!K$56 -> 46082
B89: Final Score | E89: =(1.2*E61)+(1.4*E67)+(3.3*E73)+(0.6*E79)+(E85*1) -> 2.0772227 | F89: =(1.2*F61)+(1.4*F67)+(3.3*F73)+(0.6*F79)+(F85*1) -> 2.4720347 | G89: =(1.2*G61)+(1.4*G67)+(3.3*G73)+(0.6*G79)+(G85*1) -> 2.776886 | H89: =(1.2*H61)+(1.4*H67)+(3.3*H73)+(0.6*H79)+(H85*1) -> 2.8744946 | I89: =(1.2*I61)+(1.4*I67)+(3.3*I73)+(0.6*I79)+(I85*1) -> 3.1701491
B90: Financial Stability | E90: =IF(E89<1.81,"Distressed",IF(E89>3,"Strong","Grey Zone")) -> Grey Zone | F90: =IF(F89<1.81,"Distressed",IF(F89>3,"Strong","Grey Zone")) -> Grey Zone | G90: =IF(G89<1.81,"Distressed",IF(G89>3,"Strong","Grey Zone")) -> Grey Zone | H90: =IF(H89<1.81,"Distressed",IF(H89>3,"Strong","Grey Zone")) -> Grey Zone | I90: =IF(I89<1.81,"Distressed",IF(I89>3,"Strong","Grey Zone")) -> Strong

Sheet Raw FS
B3: Particulars | C3: 42064 | D3: 42430 | E3: 42795 | F3: 43160 | G3: 43525 | H3: 43891 | I3: 44256 | J3: 44621 | K3: 44986 | L3: 45352 | M3: 45717 | N3: 46082 | S3: 42064 | T3: 42430 | U3: 42795 | V3: 43160 | W3: 43525 | X3: 43891 | Y3: 44256 | Z3: 44621 | AA3: 44986 | AB3: 45352 | AC3: 45717 | AD3: 46082 | AE3: TTM
R4: Sales + | S4: 71448 | T4: 75841 | U4: 83773 | V4: 92094 | W4: 104721 | X4: 75382 | Y4: 74278 | Z4: 90171 | AA4: 121362 | AB4: 139078 | AC4: 159211 | AD4: 198639 | AE4: 211375
B5: Equity Capital | C5: 296 | D5: 270 | E5: 311 | F5: 543 | G5: 544 | H5: 554 | I5: 555 | J5: 556 | K5: 557 | L5: 557 | M5: 558 | N5: 559 | R5: Expenses + | S5: 62655 | T5: 65759 | U5: 73038 | V5: 78868 | W5: 89514 | X5: 65224 | Y5: 62791 | Z5: 75488 | AA5: 101037 | AB5: 114186 | AC5: 128693 | AD5: 161659 | AE5: 171321
B6: Reserves | C6: 25561 | D6: 26222 | E6: 29467 | F6: 36232 | G6: 39439 | H6: 39415 | I6: 41027 | J6: 46567 | K6: 55809 | L6: 65633 | M6: 76481 | N6: 92538 | R6: Operating Profit | S6: 8793 | T6: 10082 | U6: 10735 | V6: 13226 | W6: 15207 | X6: 10158 | Y6: 11487 | Z6: 14683 | AA6: 20325 | AB6: 24892 | AC6: 30518 | AD6: 36980 | AE6: 40054
B7: Borrowings - | C7: 37911 | D7: 41553 | E7: 48762 | F7: 55898 | G7: 70848 | H7: 82092 | I7: 80625 | J7: 77605 | K7: 92647 | L7: 108647 | M7: 129025 | N7: 136936 | R7: OPM % | S7: 12 | T7: 13 | U7: 13 | V7: 14 | W7: 15 | X7: 13 | Y7: 15 | Z7: 16 | AA7: 17 | AB7: 18 | AC7: 19 | AD7: 19 | AE7: 19
B8: Long term Borrowings | C8: 22327 | D8: 23599 | E8: 30125 | F8: 33809 | G8: 43526 | H8: 52298 | I8: 52778 | J8: 48625 | K8: 55427 | L8: 69741 | M8: 83782 | N8: 76443 | R8: Other Income + | S8: 800 | T8: 1399 | U8: 2077 | V8: 4366 | W8: 2676 | X8: 885 | Y8: 1152 | Z8: 3204 | AA8: 3922 | AB8: 3298 | AC8: 3718 | AD8: 5118 | AE8: 4369
B9: Short term Borrowings | C9: 7177 | D9: 7077 | E9: 10122 | F9: 11326 | G9: 10541 | H9: 10218 | I9: 4647 | J9: 26042 | K9: 33740 | L9: 35484 | M9: 41466 | N9: 56145 | R9: Interest | S9: 3157 | T9: 3368 | U9: 3648 | V9: 3987 | W9: 5021 | X9: 6021 | Y9: 6102 | Z9: 5018 | AA9: 5830 | AB9: 7488 | AC9: 9083 | AD9: 9591 | AE9: 9720
B10: Lease Liabilities | C10: 0 | D10: 0 | E10: 0 | F10: 0 | G10: 0 | H10: 0 | I10: 2666 | J10: 2938 | K10: 3480 | L10: 3422 | M10: 3776 | N10: 4349 | R10: Depreciation | S10: 2124 | T10: 2442 | U10: 2813 | V10: 3280 | W10: 3991 | X10: 3367 | Y10: 3378 | Z10: 3508 | AA10: 4357 | AB10: 4724 | AC10: 6074 | AD10: 7322 | AE10: 7535
B11: Other Borrowings | C11: 8407 | D11: 10877 | E11: 8516 | F11: 10763 | G11: 16781 | H11: 19577 | I11: 20533 | J11: 0 | K11: -400 | L11: -2022 | M11: -4075 | N11: -2973 | R11: Profit before tax | S11: 4313 | T11: 5672 | U11: 6350 | V11: 10326 | W11: 8871 | X11: 1655 | Y11: 3158 | Z11: 9362 | AA11: 14060 | AB11: 15978 | AC11: 19080 | AD11: 25185 | AE11: 27169
B12: Other Liabilities - | C12: 30608 | D12: 31806 | E12: 35296 | F12: 43696 | G12: 51057 | H12: 43655 | I12: 42762 | J12: 47661 | K12: 55270 | L12: 59884 | M12: 69950 | N12: 86021 | R12: Tax % | S12: 40 | T12: 37 | U12: 36 | V12: 23 | W12: 32 | X12: 119 | Y12: 52 | Z12: 23 | AA12: 19 | AB12: 23 | AC12: 26 | AD12: 26 | AE12: 0
B13: Non controlling int | C13: 5892 | D13: 5920 | E13: 6357 | F13: 8250 | G13: 8361 | H13: 7692 | I13: 9070 | J13: 9703 | K13: 10716 | L13: 11319 | M13: 12059 | N13: 16395 | R13: Net Profit + | S13: 3381 | T13: 3554 | U13: 4051 | V13: 7958 | W13: 6017 | X13: -321 | Y13: 1512 | Z13: 7253 | AA13: 11374 | AB13: 12270 | AC13: 14073 | AD13: 18622 | AE13: 20243
B14: Trade Payables | C14: 11421 | D14: 13376 | E14: 14797 | F14: 18287 | G14: 20992 | H14: 14985 | I14: 15506 | J14: 19037 | K14: 23836 | L14: 25666 | M14: 30855 | N14: 37889 | S14: 25.26 | T14: 25.35 | U14: 29.77 | V14: 60.41 | W14: 42.76 | X14: 1.02 | Y14: 14.58 | Z14: 52.91 | AA14: 82.68 | AB14: 90.62 | AC14: 103.97 | AD14: 137.5 | AE14: 148.52
B15: Advance from Customers | C15: 0 | D15: 801 | E15: 515 | F15: 844 | G15: 0 | H15: 0 | I15: 0 | J15: 0 | K15: 0 | L15: 0 | M15: 0 | N15: 0 | S15: 23 | T15: 21 | U15: 22 | V15: 11 | W15: 17 | X15: 205 | Y15: 54 | Z15: 20 | AA15: 18 | AB15: 21 | AC15: 22 | AD15: 22 | AE15: 0
B16: Other liability items | C16: 13295 | D16: 11709 | E16: 13627 | F16: 16314 | G16: 21704 | H16: 20977 | I16: 18185 | J16: 18921 | K16: 20719 | L16: 22900 | M16: 27035 | N16: 31738
B18: Total Liabilities | C18: 94376 | D18: 99852 | E18: 113835 | F18: 136369 | G18: 161889 | H18: 165716 | I18: 164968 | J18: 172388 | K18: 204283 | L18: 234722 | M18: 276013 | N18: 316054 | S18: 42064 | T18: 42430 | U18: 42795 | V18: 43160 | W18: 43525 | X18: 43891 | Y18: 44256 | Z18: 44621 | AA18: 44986 | AB18: 45352 | AC18: 45717 | AD18: 46082
R19: Cash from Operating Activity - | S19: 1055 | T19: 2385 | U19: 183 | V19: 682 | W19: -4347 | X19: -1457 | Y19: 17909 | Z19: 9248 | AA19: -7074 | AB19: -5630 | AC19: 3176 | AD19: 11657
R20: Profit from operations | S20: 6454 | T20: 7595 | U20: 7911 | V20: 10159 | W20: 11112 | X20: 7774 | Y20: 7588 | Z20: 10515 | AA20: 15642 | AB20: 17541 | AC20: 22050 | AD20: 28938
B21: Fixed Assets - | C21: 19047 | D21: 20585 | E21: 20989 | F21: 26182 | G21: 28983 | H21: 29689 | I21: 21380 | J21: 26018 | K21: 27140 | L21: 28129 | M21: 34636 | N21: 38459 | R21: Receivables | S21: -575 | T21: 177 | U21: -8609 | V21: -11918 | W21: -13712 | X21: -1516 | Y21: 4896 | Z21: -2506 | AA21: -21702 | AB21: -21777 | AC21: -20952 | AD21: -19186
B22: Land | C22: 3693 | D22: 3575 | E22: 4027 | F22: 4285 | G22: 4295 | H22: 4511 | I22: 1712 | J22: 1931 | K22: 1977 | L22: 2098 | M22: 2115 | N22: 2166 | R22: Inventory | S22: -62 | T22: -1113 | U22: 241 | V22: -256 | W22: -2276 | X22: 1316 | Y22: 226 | Z22: -2173 | AA22: -5252 | AB22: -1753 | AC22: -1646 | AD22: -593
B23: Building | C23: 7666 | D23: 7958 | E23: 8084 | F23: 8842 | G23: 9037 | H23: 11956 | I23: 8482 | J23: 9728 | K23: 10862 | L23: 11496 | M23: 13100 | N23: 14886 | R23: Payables | S23: 1169 | T23: 1939 | U23: 2645 | V23: 5361 | W23: 3466 | X23: -6775 | Y23: 7049 | Z23: 4972 | AA23: 7013 | AB23: 4354 | AC23: 8485 | AD23: 8763
B24: Plant Machinery | C24: 25285 | D24: 27333 | E24: 28316 | F24: 32713 | G24: 35762 | H24: 38492 | I24: 22386 | J24: 26484 | K24: 24928 | L24: 27230 | M24: 32547 | N24: 37437 | R24: Working capital changes | S24: -3698 | T24: -3238 | U24: -5724 | V24: -6813 | W24: -12522 | X24: -6974 | Y24: 12171 | Z24: 293 | AA24: -19941 | AB24: -19175 | AC24: -14113 | AD24: -11016
B25: Equipments | C25: 268 | D25: 317 | E25: 351 | F25: 372 | G25: 384 | H25: 417 | I25: 418 | J25: 445 | K25: 452 | L25: 481 | M25: 493 | N25: 542 | R25: Direct taxes | S25: -1701 | T25: -1973 | U25: -2005 | V25: -2664 | W25: -2937 | X25: -2257 | Y25: -1850 | Z25: -1560 | AA25: -2775 | AB25: -3996 | AC25: -4761 | AD25: -6265
B26: Furniture n fittings | C26: 909 | D26: 944 | E26: 974 | F26: 1059 | G26: 1079 | H26: 1160 | I26: 805 | J26: 844 | K26: 925 | L26: 1011 | M26: 1118 | N26: 1245 | R26: Cash from Investing Activity - | S26: -4357 | T26: -5506 | U26: -5875 | V26: -5467 | W26: -7174 | X26: -6870 | Y26: -19686 | Z26: -3252 | AA26: -8866 | AB26: -5615 | AC26: -18616 | AD26: -17680
B27: Railway sidings | C27: 2 | D27: 2 | E27: 2 | F27: 2 | G27: 2 | H27: 2 | I27: 2 | J27: 2 | K27: 2 | L27: 2 | M27: 2 | N27: 2 | R27: Fixed assets purchased | S27: -4759 | T27: -4172 | U27: -5026 | V27: -5906 | W27: -7340 | X27: -6896 | Y27: -5989 | Z27: -6040 | AA27: -6305 | AB27: -9946 | AC27: -10392 | AD27: -9605
B28: Vehicles | C28: 615 | D28: 652 | E28: 703 | F28: 788 | G28: 847 | H28: 1068 | I28: 986 | J28: 1080 | K28: 1238 | L28: 1356 | M28: 1593 | N28: 1686 | R28: Fixed assets sold | S28: 43 | T28: 59 | U28: 63 | V28: 115 | W28: 142 | X28: 102 | Y28: 1364 | Z28: 120 | AA28: 138 | AB28: 273 | AC28: 583 | AD28: 493
B29: Intangible Assets | C29: 890 | D29: 3298 | E29: 3915 | F29: 7216 | G29: 9696 | H29: 9733 | I29: 6932 | J29: 7015 | K29: 10625 | L29: 11589 | M29: 13723 | N29: 16243 | R29: Investments purchased | S29: -80047 | T29: -87898 | U29: -132173 | V29: -155159 | W29: -196474 | X29: -198568 | Y29: -120055 | Z29: -87740 | AA29: -50165 | AB29: -49927 | AC29: -90595 | AD29: -141518
B30: Other fixed assets | C30: 2236 | D30: 646 | E30: 758 | F30: 1064 | G30: 1113 | H30: 1265 | I30: 937 | J30: 999 | K30: 1084 | L30: 1202 | M30: 1454 | N30: 1750 | R30: Investments sold | S30: 79778 | T30: 86436 | U30: 130940 | V30: 154631 | W30: 195898 | X30: 198132 | Y30: 111749 | Z30: 87446 | AA30: 46269 | AB30: 50919 | AC30: 85257 | AD30: 144887
B31: Gross Block | C31: 41563 | D31: 44723 | E31: 47128 | F31: 56339 | G31: 62211 | H31: 68602 | I31: 42658 | J31: 48526 | K31: 52090 | L31: 56462 | M31: 66143 | N31: 75955 | R31: Interest received | S31: 356 | T31: 311 | U31: 346 | V31: 254 | W31: 314 | X31: 372 | Y31: 431 | Z31: 420 | AA31: 464 | AB31: 703 | AC31: 884 | AD31: 1559
B32: Accumulated Depreciation | C32: 22516 | D32: 24138 | E32: 26139 | F32: 30157 | G32: 33229 | H32: 38913 | I32: 21278 | J32: 22508 | K32: 24950 | L32: 28333 | M32: 31506 | N32: 37496 | R32: Dividends received | S32: 169 | T32: 208 | U32: 409 | V32: 316 | W32: 466 | X32: 722 | Y32: 577 | Z32: 1247 | AA32: 1397 | AB32: 1213 | AC32: 1374 | AD32: 1287
B33: Net Block | C33: 19047 | D33: 20585 | E33: 20989 | F33: 26182 | G33: 28983 | H33: 29689 | I33: 21380 | J33: 26018 | K33: 27140 | L33: 28129 | M33: 34636 | N33: 38459 | R33: Invest in subsidiaries | S33: 0 | T33: -8 | U33: 0 | V33: 0 | W33: 0 | X33: 0 | Y33: 0 | Z33: 0 | AA33: 0 | AB33: 0 | AC33: 0 | AD33: 0
R34: Investment in group cos | S34: -275 | T34: -94 | U34: 209 | V34: -290 | W34: -577 | X34: -437 | Y34: -7457 | Z34: 1494 | AA34: -1786 | AB34: -78 | AC34: -6075 | AD34: -15084
B35: CWIP | C35: 3032 | D35: 2371 | E35: 4279 | F35: 4269 | G35: 4760 | H35: 6856 | I35: 7873 | J35: 6703 | K35: 3969 | L35: 8039 | M35: 8298 | N35: 7740 | R35: Redemp n Canc of Shares | S35: 0 | T35: 0 | U35: 129 | V35: 18 | W35: 18 | X35: 0 | Y35: 0 | Z35: 0 | AA35: 56 | AB35: 0 | AC35: 0 | AD35: 0
B36: Investments | C36: 10027 | D36: 11603 | E36: 14662 | F36: 16018 | G36: 18268 | H36: 19210 | I36: 28778 | J36: 30060 | K36: 35272 | L36: 35208 | M36: 41309 | N36: 40324 | R36: Other investing items | S36: 1669 | T36: 2967 | U36: 6108 | V36: 6314 | W36: 13194 | X36: 6933 | Y36: 406 | Z36: -5883 | AA36: 15946 | AB36: 12281 | AC36: 15834 | AD36: 5391
R37: Cash from Financing Activity - | S37: 3 | T37: 18 | U37: 12 | V37: 4 | W37: 1 | X37: 1243 | Y37: 1 | Z37: 1 | AA37: 1 | AB37: 1 | AC37: 1 | AD37: 1
B38: Other Assets - | C38: 62270 | D38: 65293 | E38: 73905 | F38: 89900 | G38: 109878 | H38: 109960 | I38: 106938 | J38: 109607 | K38: 137902 | L38: 163345 | M38: 191771 | N38: 229531 | R38: Proceeds from shares | S38: 0 | T38: 0 | U38: 0 | V38: 0 | W38: 71389 | X38: 52618 | Y38: 38100 | Z38: 53880 | AA38: 55622 | AB38: 61308 | AC38: 82590 | AD38: 79722
B39: Inventories | C39: 8453 | D39: 9116 | E39: 8886 | F39: 9336 | G39: 12200 | H39: 11112 | I39: 9615 | J39: 11596 | K39: 16855 | L39: 18590 | M39: 20331 | N39: 22044 | R39: Proceeds from borrowings | S39: 0 | T39: 0 | U39: 0 | V39: 0 | W39: -56352 | X39: -44044 | Y39: -37505 | Z39: -57223 | AA39: -37056 | AB39: -46805 | AC39: -64689 | AD39: -72089
B40: Trade receivables + | C40: 5476 | D40: 5818 | E40: 7199 | F40: 8490 | G40: 8678 | H40: 6928 | I40: 6008 | J40: 6374 | K40: 7028 | L40: 7459 | M40: 8280 | N40: 9064 | R40: Repayment of borrowings | S40: -489 | T40: -443 | U40: -471 | V40: -521 | W40: -723 | X40: -624 | Y40: -809 | Z40: -680 | AA40: -734 | AB40: -597 | AC40: -436 | AD40: -344
B41: Cash Equivalents | C41: 4912 | D41: 4528 | E41: 4654 | F41: 6548 | G41: 8735 | H41: 7911 | I41: 12852 | J41: 11118 | K41: 11273 | L41: 12013 | M41: 20615 | N41: 31979 | R41: Interest paid fin | S41: -1200 | T41: -932 | U41: -936 | V41: -963 | W41: -1134 | X41: -1398 | Y41: -271 | Z41: -1037 | AA41: -1522 | AB41: -2247 | AC41: -2806 | AD41: -3376
B42: Loans n Advances | C42: -772 | D42: -1096 | E42: 20566 | F42: 24614 | G42: 29130 | H42: 27859 | I42: 29080 | J42: 29242 | K42: 34685 | L42: 39060 | M42: 44645 | N42: 51137 | R42: Dividends paid | S42: -4876 | T42: -5133 | U42: -6994 | V42: -5952 | W42: -6519 | X42: -7302 | Y42: -18881 | Z42: -13788 | AA42: -15418 | AB42: -19899 | AC42: -17782 | AD42: -18271
B43: Other asset items | C43: 44201 | D43: 46928 | E43: 32599 | F43: 40913 | G43: 51135 | H43: 56150 | I43: 49383 | J43: 51277 | K43: 68061 | L43: 86222 | M43: 97900 | N43: 115307 | R43: Financial liabilities | S43: 0 | T43: 0 | U43: 0 | V43: 0 | W43: 0 | X43: -49 | Y43: -55 | Z43: -59 | AA43: -59 | AB43: -67 | AC43: -66 | AD43: -68
B44: Total Assets | C44: 94376 | D44: 99852 | E44: 113835 | F44: 136369 | G44: 161889 | H44: 165716 | I44: 164968 | J44: 172388 | K44: 204283 | L44: 234722 | M44: 276013 | N44: 316054 | R44: Other financing items | S44: -734 | T44: -971 | U44: -1335 | V44: -1136 | W44: -1203 | X44: -1409 | Y44: 55 | Z44: 15 | AA44: 35 | AB44: 12 | AC44: 28 | AD44: -146
R45: Net Cash Flow | S45: -1633 | T45: -154 | U45: 416 | V45: 1529 | W45: 1672 | X45: -1394 | Y45: -1370 | Z45: 113 | AA45: 6 | AB45: 1037 | AC45: 394 | AD45: -632 | AT45: Interest paid fin | AU45: -18 | AV45: -2 | AW45: -14 | AX45: -6 | AY45: -7 | AZ45: -90 | BA45: -92 | BB45: -82 | BC45: -88 | BD45: -110 | BE45: -130 | BF45: -133
AT46: Dividends paid | AU46: -2912 | AV46: -3354 | AW46: -3572 | AX46: -3911 | AY46: -4554 | AZ46: -5196 | BA46: -8811 | BB46: -7526 | BC46: -8474 | BD46: -9416 | BE46: -12473 | BF46: -10124
AT47: Financial liabilities | AU47: 0 | AV47: 0 | AW47: 0 | AX47: 0 | AY47: 0 | AZ47: -373 | BA47: -406 | BB47: -407 | BC47: -467 | BD47: -423 | BE47: -498 | BF47: -507
AT48: Other financing items | AU48: -533 | AV48: -685 | AW48: -728 | AX48: -781 | AY48: -928 | AZ48: -1061 | BA48: 0 | BB48: 0 | BC48: -2 | BD48: 0 | BE48: 0 | BF48: 0
AT49: Net Cash Flow | AU49: -33 | AV49: 25 | AW49: -202 | AX49: 21 | AY49: -28 | AZ49: 2595 | BA49: -1374 | BB49: -695 | BC49: -446 | BD49: 111 | BE49: 5258 | BF49: -3487
AR55: Mar Cap Rs.Cr. | AS55: Net Debt | AT55: EV Rs.Cr. | AU55: Sales Rs.Cr. | AV55: EBITDA | AW55: NP 12M Rs.Cr. | AX55: EV / EBITDA | AZ55: Debt Rs.Cr. | BA55: Cash End Rs.Cr.
K56: S.No. | L56: ='Data Sheet'!B1 -> MAHINDRA & MAHINDRA LTD | M56: ='Data Sheet'!B8 -> 3055 | N56: ='Data Sheet'!B6 -> 124.32242 | AR56: ='Data Sheet'!B9 -> 379805 | AS56: =AZ56-BA56 -> 104957 | AT56: =AR56+AS56 -> 484762 | AU56: ='Data Sheet'!K17 -> 198639 | AV56: ='Data Sheet'!K33 -> 60720 | AW56: ='Data Sheet'!K30 -> 18622 | AX56: 30.12 | AZ56: ='Data Sheet'!K59 -> 136936 | BA56: ='Data Sheet'!K69 -> 31979
K57: 1 | L57: Maruti Suzuki | M57: 12153 | N57: 31.33 | AR57: 380772.09 | AS57: =AZ57-BA57 -> 76154.42 | AT57: =AR57+AS57 -> 456926.51 | AU57: 209879.2 | AV57: 31481.88 | AW57: 13787.6 | AX57: 18.87 | AZ57: 95193.02 | BA57: 19038.6
K58: 2 | L58: Hyundai Motor I | M58: 2144 | N58: 82.75 | AR58: 177405.45 | AS58: =AZ58-BA58 -> 35481.09 | AT58: =AR58+AS58 -> 212886.54 | AU58: 65338.52 | AV58: 9800.78 | AW58: 3554.48 | AX58: 38.4 | AZ58: 44351.36 | BA58: 8870.27
K59: 3 | L59: Tata Motors PVeh | M59: 301.65 | N59: 368.29 | AR59: 111094.43 | AS59: =AZ59-BA59 -> 22218.89 | AT59: =AR59+AS59 -> 133313.32 | AU59: 383196 | AV59: 57479.4 | AW59: 3436 | AX59: 2.73 | AZ59: 27773.61 | BA59: 5554.72
K60: 4 | L60: Force Motors | M60: 17485 | N60: 1.3 | AR60: 22802.17 | AS60: =AZ60-BA60 -> 4560.43 | AT60: =AR60+AS60 -> 27362.6 | AU60: 9760.04 | AV60: 1464.01 | AW60: 866.36 | AX60: 36.05 | AZ60: 5700.54 | BA60: 1140.11
K61: 5 | L61: Olectra Greentec | M61: 1205.8 | N61: 8.2 | AR61: 9893.58 | AS61: =AZ61-BA61 -> 1978.71 | AT61: =AR61+AS61 -> 11872.29 | AU61: 2302.04 | AV61: 345.31 | AW61: 106.64 | AX61: 21.05 | AZ61: 2473.39 | BA61: 494.68
K62: 6 | L62: Mercury EV-Tech | M62: 39.81 | N62: 19.02 | AR62: 757.23 | AS62: =AZ62-BA62 -> 151.45 | AT62: =AR62+AS62 -> 908.68 | AU62: 133.52 | AV62: 20.03 | AW62: 6.6 | AX62: 2.64 | AZ62: 189.31 | BA62: 37.86

Sheet List of Stocks
B2: COMPANY_NAME | C2: BSE | D2: NSE | E2: Industry
B3: 20 MICRONS LTD | C3: 533022 | D3: 20MICRONS | E3: Mining
B4: 21ST CENTURY MANAGEMENT SERVICES LTD | C4: 526921 | D4: 21STCENMGM | E4: Other Financial Services
B5: 3I INFOTECH LTD | C5: 532628 | D5: 3IINFOTECH | E5: IT Consulting & Software
B6: 3M (INDIA) LTD | C6: 523395 | D6: 3M(INDIA) | E6: Diversified
B7: 3M INDIA LTD | C7: 523395 | D7: 3MINDIA | E7: Diversified
B8: 3P LAND HOLDINGS LTD | C8: 516092 | D8: 3PLAND | E8: Paper & Paper Products
B9: 5PAISA CAPITAL LTD | C9: 540776 | D9: 5PAISA | E9: Other Financial Services
B10: 63 MOONS TECHNOLOGIES LTD | C10: 526881 | D10: 63MOONS | E10: IT Consulting & Software
B11: 7NR RETAIL LTD | C11: 540615 | D11: Not Listed | E11: Specialty Retail
B12: 7SEAS ENTERTAINMENT LTD | C12: 540874 | D12: Not Listed | E12: Movies & Entertainment
B13: 8K MILES SOFTWARE SERVICES LTD | C13: 512161 | D13: 8KMILES | E13: Internet Software & Services
B14: A & M FEBCON LTD | C14: 540697 | D14: Not Listed | E14: Industrial Machinery
B15: A AND M JUMBO BAGS LTD | C15: Not Listed | D15: AMJUMBO | E15: SME
B16: A INFRASTRUCTURE LTD | C16: 539620 | D16: Not Listed | E16: Cement & Cement Products
B17: A K SPINTEX LTD | C17: 539300 | D17: Not Listed | E17: Textiles
B18: A K CAPITAL SERVICES LTD | C18: 530499 | D18: Not Listed | E18: Finance (including NBFCs)
B19: A.F. Enterprises Ltd | C19: 538351 | D19: AFEL | E19: Investment Companies
B20: A-1 ACID LTD | C20: 542012 | D20: Not Listed | E20: Comm.Trading & Distribution
B21: A2Z INFRA ENGINEERING LTD | C21: 533292 | D21: A2ZINFRA | E21: Utilities:Non-Elec.
B22: AADHAAR VENTURES (INDIA) LTD | C22: 531611 | D22: Not Listed | E22: Finance (including NBFCs)
B23: AADHAAR VENTURES INDIA LTD | C23: 531611 | D23: Not Listed | E23: Finance (including NBFCs)
B24: AAKASH EXPLORATION SERVICES LTD | C24: Not Listed | D24: AAKASH | E24: SME
B25: AANANDA LAKSHMI SPINNING MILLS LTD | C25: 539096 | D25: Not Listed | E25: Textiles
B26: AANCHAL ISPAT LTD | C26: 538812 | D26: Not Listed | E26: Iron & Steel/Interm.Products
B27: AAR COMMERCIAL COMPANY LTD | C27: 539632 | D27: Not Listed | E27: Distributors
B28: Aar Shyam India Investment Company Ltd | C28: 542377 | D28: AARSHYAM | E28: Finance (including NBFCs)
B29: AAREY DRUGS & PHARMACEUTICALS LTD | C29: 524412 | D29: Not Listed | E29: Pharmaceuticals
B30: AARON INDUSTRIES LTD | C30: Not Listed | D30: AARON | E30: SME
B31: Aartech Solonics Ltd | C31: 542580 | D31: AARTECH | E31: Heavy Electrical Equipment
B32: AARTI DRUGS LTD | C32: 524348 | D32: AARTIDRUGS | E32: Pharmaceuticals
B33: AARTI INDUSTRIES LTD | C33: 524208 | D33: AARTIIND | E33: Commodity Chemicals
B34: AARV INFRATEL LTD | C34: 526488 | D34: Not Listed | E34: Textiles
B35: AARVEE DENIMS & EXPORTS LTD | C35: 514274 | D35: AARVEEDEN | E35: Textiles
B36: AARVI ENCON LTD | C36: Not Listed | D36: AARVI | E36: SME
B37: AASHEE INFOTECH LTD | C37: 519319 | D37: Not Listed | E37: Internet Software & Services
B38: AASWA TRADING & EXPORTS LTD | C38: 512038 | D38: Not Listed | E38: Comm.Trading & Distribution
B39: AAVAS FINANCIERS LTD | C39: 541988 | D39: AAVAS | E39: Housing Finance
B40: AAYUSH FOOD AND HERBS LTD | C40: 539528 | D40: Not Listed | E40: Packaged Foods
B41: ABAN OFFSHORE LTD | C41: 523204 | D41: ABAN | E41: Exploration & Production
B42: ABANS ENTERPRISES LTD | C42: 512165 | D42: Not Listed | E42: Comm.Trading & Distribution
B43: ABB INDIA LTD | C43: 500002 | D43: ABB | E43: Heavy Electrical Equipment
B44: ABBOTT (INDIA) LTD | C44: 500488 | D44: ABBOT(INDIA) | E44: Pharmaceuticals
B45: ABBOTT INDIA LTD | C45: 500488 | D45: ABBOTINDIA | E45: Pharmaceuticals
B46: ABC (INDIA) LTD | C46: 520123 | D46: Not Listed | E46: Surface Transportation
B47: ABC GAS INTERNATIONAL LTD | C47: 513119 | D47: Not Listed | E47: Copper
B48: ABC INDIA LTD | C48: 520123 | D48: Not Listed | E48: Surface Transportation
... B56: ABIRAMI FINANCIAL SERVICES INDIA LTD | C56: 511756 | D56: Not Listed | E56: Finance (including NBFCs)
B57: ABM INTERNATIONAL LTD | C57: Not Listed | D57: ABMINTLTD | E57: Others
B58: ABM KNOWLEDGEWARE LTD | C58: 531161 | D58: Not Listed | E58: IT Software Products
B59: ACC LTD | C59: 500410 | D59: ACC | E59: Cement & Cement Products
B60: ACCEL LTD | C60: 517494 | D60: Not Listed | E60: Storage Media & Peripherals
B61: ACCELYA KALE SOLUTIONS LTD | C61: 532268 | D61: ACCELYA | E61: IT Consulting & Software
B62: ACCORD SYNERGY LTD | C62: Not Listed | D62: ACCORD | E62: SME
B63: ACCURACY SHIPPING LTD | C63: Not Listed | D63: ACCURACY | E63: SME
B64: ACE EDUTREND LTD | C64: 530093 | D64: Not Listed | E64: Education
B65: ACE INTEGRATED SOLUTIONS LTD | C65: Not Listed | D65: ACEINTEG | E65: SME
B66: ACE MEN ENGG WORKS LTD | C66: 539661 | D66: Not Listed | E66: Distributors
B67: ACE SOFTWARE EXPORTS LTD | C67: 531525 | D67: Not Listed | E67: IT Software Products
B68: Achal Investments Ltd | C68: 538570 | D68: ACHAL | E68: Other Financial Services
B69: ACI INFOCOM LTD | C69: 517356 | D69: Not Listed | E69: Storage Media & Peripherals
B70: ACKNIT INDUSTRIES LTD | C70: 530043 | D70: Not Listed | E70: Other Apparels & Accessories
B71: ACME RESOURCES LTD | C71: 539391 | D71: Not Listed | E71: Finance (including NBFCs)
B72: ACROW INDIA LTD. | C72: 513149 | D72: ACROW | E72: Iron &amp; Steel Products
B73: ACRYSIL LTD | C73: 524091 | D73: Not Listed | E73: Plastic Products
B74: ACTION CONSTRUCTION EQUIPMENT LTD | C74: 532762 | D74: ACE | E74: Transport Related Services
B75: ACTION FINANCIAL SERVICES (INDIA) LTD | C75: 511706 | D75: Not Listed | E75: Other Financial Services
B76: ACTION FINANCIAL SERVICES INDIA LTD | C76: 511706 | D76: Not Listed | E76: Other Financial Services
B77: ACTIVE CLOTHING CO LTD | C77: 541144 | D77: Not Listed | E77: Other Apparels & Accessories
... B135: AGRI-TECH INDIA LTD | C135: 537292 | D135: AGRITECH | E135: Other Agricultural Products
B136: AGRO PHOS (INDIA) LTD | C136: Not Listed | D136: AGROPHOS | E136: SME
B137: AGRO PHOS INDIA LTD | C137: Not Listed | D137: AGROPHOS | E137: SME
B138: AGRO TECH FOODS LTD | C138: 500215 | D138: ATFL | E138: Other Agricultural Products
B139: AHIMSA INDUSTRIES LTD | C139: Not Listed | D139: AHIMSA | E139: SME
B140: AHLADA ENGINEERS LTD | C140: Not Listed | D140: AHLADA | E140: SME
B141: AHLUWALIA CONTRACTS (INDIA) LTD | C141: 532811 | D141: AHLUCONT | E141: Realty
B142: AHLUWALIA CONTRACTS INDIA LTD | C142: 532811 | D142: AHLUCONT | E142: Realty
B143: AHMEDABAD STEELCRAFT LTD | C143: 522273 | D143: Not Listed | E143: Iron & Steel/Interm.Products
B144: AI CHAMPDANY INDUSTRIES LTD | C144: 532806 | D144: Not Listed | E144: Jute & Jute Products
B145: AIA ENGINEERING LTD | C145: 532683 | D145: AIAENG | E145: Other Industrial Goods
B146: AIMCO PESTICIDES LTD | C146: 524288 | D146: Not Listed | E146: Agrochemicals
B147: AIRAN LTD | C147: Not Listed | D147: AIRAN | E147: SME
B148: AIRO LAM LTD | C148: Not Listed | D148: AIROLAM | E148: SME
B149: AISHWARYA TELECOM LTD | C149: 532975 | D149: Not Listed | E149: Telecom Equipment
B150: AJANTA PHARMA LTD | C150: 532331 | D150: AJANTPHARM | E150: Pharmaceuticals
B151: AJANTA SOYA LTD | C151: 519216 | D151: Not Listed | E151: Edible Oils
B152: AJCON GLOBAL SERVICES LTD | C152: 511692 | D152: Not Listed | E152: Other Financial Services
B153: AJEL LTD | C153: 530713 | D153: Not Listed | E153: IT Consulting & Software
B154: AJMERA REALTY & INFRA (INDIA) LTD | C154: 513349 | D154: AJMERA | E154: Realty
B155: AJMERA REALTY & INFRA INDIA LTD | C155: 513349 | D155: AJMERA | E155: Realty
B156: AJOONI BIOTECH LTD | C156: Not Listed | D156: AJOONI | E156: SME
B157: AJWA FUN WORLD & RESORT LTD | C157: 526628 | D157: Not Listed | E157: Other Leisure Facilities
B158: AKAR AUTO INDUSTRIES LTD | C158: 530621 | D158: Not Listed | E158: Industrial Machinery
B159: AKASH INFRA PROJECTS LTD | C159: Not Listed | D159: AKASH | E159: SME
B160: AKASHDEEP METAL INDUSTRIES LTD | C160: 538778 | D160: Not Listed | E160: Finance (including NBFCs)
B161: AKG EXIM LTD | C161: Not Listed | D161: AKG | E161: SME
B162: AKI (INDIA) LTD | C162: 542020 | D162: Not Listed | E162: Other Apparels & Accessories
B163: AKI INDIA LTD | C163: 542020 | D163: Not Listed | E163: Other Apparels & Accessories
B164: AKM LACE AND EMBROTEX LTD | C164: 540718 | D164: Not Listed | E164: Textiles
B165: AKME STAR HOUSING FINANCE LTD | C165: 539017 | D165: Not Listed | E165: Housing Finance
...
