Workbook
Name UPDATE: 'Data Sheet'!$E$1
Name UPDATE: #REF!

Sheet AI Valuation Summary
A1: TATA STEEL LTD (TATASTEEL) - Institutional Valuation
A4: Current Price | B4: Intrinsic Value | C4: Margin of Safety | D4: Verdict | E4: WACC | F4: Altman Z-Score | G4: DuPont ROE
A5: =DCF!D44 | B5: =DCF!D42 | C5: =(B5-A5)/A5 | D5: =IF(C5>0.15,"UNDERVALUED / BUY",IF(C5<-0.15,"OVERVALUED / SELL","FAIRLY VALUED / HOLD")) | E5: =DCF!D20 | F5: ='Altman''s Z Score'!I89 | G5: ='Dupont Analysis'!I78
A7: THE 4 CORE VALUATION PILLARS | B7: KEY VALUATION PARAMETERS & LIVE MODEL INPUTS
A8: Pillar 1: FCF Engine | B8: Discount Rate (WACC) | C8: =WACC!K46 | D8: 0.00%
A9: Pillar 2: Growth Trajectory | B9: Cost of Equity (Ke) | C9: =WACC!K29 | D9: 0.00%
A10: Pillar 3: Cost of Capital (WACC) | B10: Risk-Free Rate (Rf) | C10: =WACC!K26 | D10: 0.00%
A11: Pillar 4: Relative Multiples | B11: Equity Risk Premium (ERP) | C11: =WACC!K27 | D11: 0.00%
B12: Levered Beta | C12: =WACC!K28 | D12: 0.00
A13: 5-Year Discounted Cash Flow (DCF) Schedule (Amounts in ₹ Cr) | B13: Terminal Growth Rate | C13: =DCF!D19 | D13: 0.00%
A14: Year | B14: Post-Tax Cost of Debt (Kd) | C14: =WACC!K43 | D14: 0.00% | E14: FCFF | F14: Discount Factor | G14: PV of FCFF
A15: Year 1 | B15: Cash & Liquid Investments | C15: ='Data Sheet'!K69 | D15: #,##0.00 | E15: =DCF!I12 | F15: =DCF!I14 | G15: =DCF!I16
A16: Year 2 | B16: Total Debt & Borrowings | C16: ='Data Sheet'!K59 | D16: #,##0.00 | E16: =DCF!J12 | F16: =DCF!J14 | G16: =DCF!J16
A17: Year 3 | B17: Shares Outstanding | C17: ='Data Sheet'!K70/10000000 | D17: #,##0.00 | E17: =DCF!K12 | F17: =DCF!K14 | G17: =DCF!K16
A18: Year 4 | B18: Sector Median EV/Revenue | C18: =Comp_Valuation!O25 | D18: 0.00"x" | E18: =DCF!L12 | F18: =DCF!L14 | G18: =DCF!L16
A19: Year 5 | B19: Sector Median EV/EBITDA | C19: =Comp_Valuation!P25 | D19: 0.00"x" | E19: =DCF!M12 | F19: =DCF!M14 | G19: =DCF!M16
A20: 5-Year Discounted Cash Flow (DCF) Schedule (Amounts in ₹ Cr) | B20: Sector Median P/E | C20: =Comp_Valuation!Q25 | D20: 0.00"x"
A21: Year | B21: EBIT | C21: NOPAT | D21: Reinvest Rate | E21: FCFF | F21: Discount Factor | G21: PV of FCFF
A22: Year 1 | B22: =DCF!I8 | C22: =DCF!I10 | D22: =DCF!I11 | E22: =DCF!I12 | F22: =DCF!I14 | G22: =DCF!I16
A23: Year 2 | B23: =DCF!J8 | C23: =DCF!J10 | D23: =DCF!J11 | E23: =DCF!J12 | F23: =DCF!J14 | G23: =DCF!J16
A24: Year 3 | B24: =DCF!K8 | C24: =DCF!K10 | D24: =DCF!K11 | E24: =DCF!K12 | F24: =DCF!K14 | G24: =DCF!K16
A25: Year 4 | B25: =DCF!L8 | C25: =DCF!L10 | D25: =DCF!L11 | E25: =DCF!L12 | F25: =DCF!L14 | G25: =DCF!L16
A26: Year 5 | B26: =DCF!M8 | C26: =DCF!M10 | D26: =DCF!M11 | E26: =DCF!M12 | F26: =DCF!M14 | G26: =DCF!M16
A27: Less: Total Debt & Borrowings | B27: =DCF!D38
A28: Net Equity Value | B28: Enterprise to Equity Value Bridge
A29: Shares Outstanding | B29: PV of 5-Year FCFFs | C29: =DCF!D33 | D29: ₹ Cr
A30: Intrinsic Value per Share | B30: Terminal Value | C30: =DCF!D29 | D30: ₹ Cr
A31: Current Market Price | B31: PV of Terminal Value | C31: =DCF!D34 | D31: ₹ Cr
A32: Margin of Safety / Discount | B32: Enterprise Value (Operating Assets) | C32: =DCF!D35 | D32: ₹ Cr
B33: Add: Estimated Cash & Liquid Assets | C33: =DCF!D37 | D33: ₹ Cr
B34: Less: Total Debt & Borrowings | C34: =DCF!D38 | D34: ₹ Cr
B35: Net Equity Value | C35: =DCF!D39 | D35: ₹ Cr
B36: Shares Outstanding | C36: =DCF!D40 | D36: Cr shares
B37: Intrinsic Value per Share | C37: =DCF!D42 | D37: ₹
B38: Current Market Price | C38: =DCF!D44 | D38: ₹
B39: Margin of Safety / Discount | C39: =(C37-C38)/C38 | D39: %

Sheet Profit & Loss
A1: ='Data Sheet'!B1 | H1: =UPDATE | M1: SCREENER.IN
A3: Narration | B3: ='Data Sheet'!B16 | C3: ='Data Sheet'!C16 | D3: ='Data Sheet'!D16 | E3: ='Data Sheet'!E16 | F3: ='Data Sheet'!F16 | G3: ='Data Sheet'!G16 | H3: ='Data Sheet'!H16 | I3: ='Data Sheet'!I16 | ... K3: ='Data Sheet'!K16 | L3: Trailing | M3: Best Case | N3: Worst Case
A4: Sales | B4: ='Data Sheet'!B17 | C4: ='Data Sheet'!C17 | D4: ='Data Sheet'!D17 | E4: ='Data Sheet'!E17 | F4: ='Data Sheet'!F17 | G4: ='Data Sheet'!G17 | H4: ='Data Sheet'!H17 | I4: ='Data Sheet'!I17 | ... K4: ='Data Sheet'!K17 | L4: =SUM(Quarters!H4:K4) | M4: =$K4+M23*K4 | N4: =$K4+N23*L4
A5: Expenses | B5: =SUM('Data Sheet'!B18,'Data Sheet'!B20:B24, -1*'Data Sheet'!B19) | C5: =SUM('Data Sheet'!C18,'Data Sheet'!C20:C24, -1*'Data Sheet'!C19) | D5: =SUM('Data Sheet'!D18,'Data Sheet'!D20:D24, -1*'Data Sheet'!D19) | E5: =SUM('Data Sheet'!E18,'Data Sheet'!E20:E24, -1*'Data Sheet'!E19) | F5: =SUM('Data Sheet'!F18,'Data Sheet'!F20:F24, -1*'Data Sheet'!F19) | G5: =SUM('Data Sheet'!G18,'Data Sheet'!G20:G24, -1*'Data Sheet'!G19) | H5: =SUM('Data Sheet'!H18,'Data Sheet'!H20:H24, -1*'Data Sheet'!H19) | I5: =SUM('Data Sheet'!I18,'Data Sheet'!I20:I24, -1*'Data Sheet'!I19) | ... K5: =SUM('Data Sheet'!K18,'Data Sheet'!K20:K24, -1*'Data Sheet'!K19) | L5: =SUM(Quarters!H5:K5) | M5: =M4-M6 | N5: =N4-N6
A6: Operating Profit | B6: =B4-B5 | C6: =C4-C5 | D6: =D4-D5 | E6: =E4-E5 | F6: =F4-F5 | G6: =G4-G5 | H6: =H4-H5 | I6: =I4-I5 | ... K6: =K4-K5 | L6: =SUM(Quarters!H6:K6) | M6: =M4*M24 | N6: =N4*N24
A7: Other Income | B7: ='Data Sheet'!B25 | C7: ='Data Sheet'!C25 | D7: ='Data Sheet'!D25 | E7: ='Data Sheet'!E25 | F7: ='Data Sheet'!F25 | G7: ='Data Sheet'!G25 | H7: ='Data Sheet'!H25 | I7: ='Data Sheet'!I25 | ... K7: ='Data Sheet'!K25 | L7: =SUM(Quarters!H7:K7) | M7: 0 | N7: 0
A8: Depreciation | B8: ='Data Sheet'!B26 | C8: ='Data Sheet'!C26 | D8: ='Data Sheet'!D26 | E8: ='Data Sheet'!E26 | F8: ='Data Sheet'!F26 | G8: ='Data Sheet'!G26 | H8: ='Data Sheet'!H26 | I8: ='Data Sheet'!I26 | ... K8: ='Data Sheet'!K26 | L8: =SUM(Quarters!H8:K8) | M8: =+$L8 | N8: =+$L8
A9: Interest | B9: ='Data Sheet'!B27 | C9: ='Data Sheet'!C27 | D9: ='Data Sheet'!D27 | E9: ='Data Sheet'!E27 | F9: ='Data Sheet'!F27 | G9: ='Data Sheet'!G27 | H9: ='Data Sheet'!H27 | I9: ='Data Sheet'!I27 | ... K9: ='Data Sheet'!K27 | L9: =SUM(Quarters!H9:K9) | M9: =+$L9 | N9: =+$L9
A10: Profit before tax | B10: ='Data Sheet'!B28 | C10: ='Data Sheet'!C28 | D10: ='Data Sheet'!D28 | E10: ='Data Sheet'!E28 | F10: ='Data Sheet'!F28 | G10: ='Data Sheet'!G28 | H10: ='Data Sheet'!H28 | I10: ='Data Sheet'!I28 | ... K10: ='Data Sheet'!K28 | L10: =SUM(Quarters!H10:K10) | M10: =M6+M7-SUM(M8:M9) | N10: =N6+N7-SUM(N8:N9)
A11: Tax | B11: ='Data Sheet'!B29 | C11: ='Data Sheet'!C29 | D11: ='Data Sheet'!D29 | E11: ='Data Sheet'!E29 | F11: ='Data Sheet'!F29 | G11: ='Data Sheet'!G29 | H11: ='Data Sheet'!H29 | I11: ='Data Sheet'!I29 | ... K11: ='Data Sheet'!K29 | L11: =SUM(Quarters!H11:K11) | M11: =IF($L10>0,$L11/$L10,0) | N11: =IF($L10>0,$L11/$L10,0)
A12: Net profit | B12: ='Data Sheet'!B30 | C12: ='Data Sheet'!C30 | D12: ='Data Sheet'!D30 | E12: ='Data Sheet'!E30 | F12: ='Data Sheet'!F30 | G12: ='Data Sheet'!G30 | H12: ='Data Sheet'!H30 | I12: ='Data Sheet'!I30 | ... K12: ='Data Sheet'!K30 | L12: =SUM(Quarters!H12:K12) | M12: =M10-M11*M10 | N12: =N10-N11*N10
A13: EPS | B13: =IF('Data Sheet'!B93>0,B12/'Data Sheet'!B93,0) | C13: =IF('Data Sheet'!C93>0,C12/'Data Sheet'!C93,0) | D13: =IF('Data Sheet'!D93>0,D12/'Data Sheet'!D93,0) | E13: =IF('Data Sheet'!E93>0,E12/'Data Sheet'!E93,0) | F13: =IF('Data Sheet'!F93>0,F12/'Data Sheet'!F93,0) | G13: =IF('Data Sheet'!G93>0,G12/'Data Sheet'!G93,0) | H13: =IF('Data Sheet'!H93>0,H12/'Data Sheet'!H93,0) | I13: =IF('Data Sheet'!I93>0,I12/'Data Sheet'!I93,0) | ... K13: =IF('Data Sheet'!K93>0,K12/'Data Sheet'!K93,0) | L13: =IF('Data Sheet'!$B6>0,'Profit & Loss'!L12/'Data Sheet'!$B6,0) | M13: =IF('Data Sheet'!$B6>0,'Profit & Loss'!M12/'Data Sheet'!$B6,0) | N13: =IF('Data Sheet'!$B6>0,'Profit & Loss'!N12/'Data Sheet'!$B6,0)
A14: Price to earning | B14: =IF(B15>0,B15/B13,"") | C14: =IF(C15>0,C15/C13,"") | D14: =IF(D15>0,D15/D13,"") | E14: =IF(E15>0,E15/E13,"") | F14: =IF(F15>0,F15/F13,"") | G14: =IF(G15>0,G15/G13,"") | H14: =IF(H15>0,H15/H13,"") | I14: =IF(I15>0,I15/I13,"") | ... K14: =IF(K15>0,K15/K13,"") | L14: =IF(L13>0,L15/L13,0) | M14: =M25 | N14: =N25
A15: Price | B15: ='Data Sheet'!B90 | C15: ='Data Sheet'!C90 | D15: ='Data Sheet'!D90 | E15: ='Data Sheet'!E90 | F15: ='Data Sheet'!F90 | G15: ='Data Sheet'!G90 | H15: ='Data Sheet'!H90 | I15: ='Data Sheet'!I90 | ... K15: ='Data Sheet'!K90 | L15: ='Data Sheet'!B8 | M15: =M13*M14 | N15: =N13*N14
A17: RATIOS:
A18: Dividend Payout | B18: =IF('Data Sheet'!B30>0, 'Data Sheet'!B31/'Data Sheet'!B30, 0) | C18: =IF('Data Sheet'!C30>0, 'Data Sheet'!C31/'Data Sheet'!C30, 0) | D18: =IF('Data Sheet'!D30>0, 'Data Sheet'!D31/'Data Sheet'!D30, 0) | E18: =IF('Data Sheet'!E30>0, 'Data Sheet'!E31/'Data Sheet'!E30, 0) | F18: =IF('Data Sheet'!F30>0, 'Data Sheet'!F31/'Data Sheet'!F30, 0) | G18: =IF('Data Sheet'!G30>0, 'Data Sheet'!G31/'Data Sheet'!G30, 0) | H18: =IF('Data Sheet'!H30>0, 'Data Sheet'!H31/'Data Sheet'!H30, 0) | I18: =IF('Data Sheet'!I30>0, 'Data Sheet'!I31/'Data Sheet'!I30, 0) | ... K18: =IF('Data Sheet'!K30>0, 'Data Sheet'!K31/'Data Sheet'!K30, 0)
A19: OPM | B19: =IF(B6>0,B6/B4,0) | C19: =IF(C6>0,C6/C4,0) | D19: =IF(D6>0,D6/D4,0) | E19: =IF(E6>0,E6/E4,0) | F19: =IF(F6>0,F6/F4,0) | G19: =IF(G6>0,G6/G4,0) | H19: =IF(H6>0,H6/H4,0) | I19: =IF(I6>0,I6/I4,0) | ... L19: =IF(L6>0,L6/L4,0)
G22: TRENDS: | H22: 10 YEARS | I22: 7 YEARS | J22: 5 YEARS | K22: 3 YEARS | L22: RECENT | M22: BEST | N22: WORST
G23: Sales Growth | H23: =IF(B4=0,"",POWER($K4/B4,1/9)-1) | I23: =IF(D4=0,"",POWER($K4/D4,1/7)-1) | J23: =IF(F4=0,"",POWER($K4/F4,1/5)-1) | K23: =IF(H4=0,"",POWER($K4/H4, 1/3)-1) | L23: =IF(ISERROR(MAX(IF(J4=0,"",(K4-J4)/J4),IF(K4=0,"",(L4-K4)/K4))),"",MAX(IF(J4=0,"",(K4-J4)/J4),IF(K4=0,"",(L4-K4)/K4))) | M23: =MAX(K23:L23) | N23: =MIN(H23:L23)
G24: OPM | H24: =IF(SUM(B4:$K$4)=0,"",SUMPRODUCT(B19:$K$19,B4:$K$4)/SUM(B4:$K$4)) | I24: =IF(SUM(E4:$K$4)=0,"",SUMPRODUCT(E19:$K$19,E4:$K$4)/SUM(E4:$K$4)) | J24: =IF(SUM(G4:$K$4)=0,"",SUMPRODUCT(G19:$K$19,G4:$K$4)/SUM(G4:$K$4)) | K24: =IF(SUM(I4:$K$4)=0, "", SUMPRODUCT(I19:$K$19,I4:$K$4)/SUM(I4:$K$4)) | L24: =L19 | M24: =MAX(K24:L24) | N24: =MIN(H24:L24)
G25: Price to Earning | H25: =IF(ISERROR(AVERAGEIF(B14:$L14,">0")),"",AVERAGEIF(B14:$L14,">0")) | I25: =IF(ISERROR(AVERAGEIF(E14:$L14,">0")),"",AVERAGEIF(E14:$L14,">0")) | J25: =IF(ISERROR(AVERAGEIF(G14:$L14,">0")),"",AVERAGEIF(G14:$L14,">0")) | K25: =IF(ISERROR(AVERAGEIF(I14:$L14,">0")),"",AVERAGEIF(I14:$L14,">0")) | L25: =L14 | M25: =MAX(K25:L25) | N25: =MIN(H25:L25)

Sheet Quarters
A1: ='Profit & Loss'!A1 | E1: =UPDATE | J1: SCREENER.IN
A3: Narration | B3: ='Data Sheet'!B41 | C3: ='Data Sheet'!C41 | D3: ='Data Sheet'!D41 | E3: ='Data Sheet'!E41 | F3: ='Data Sheet'!F41 | G3: ='Data Sheet'!G41 | H3: ='Data Sheet'!H41 | I3: ='Data Sheet'!I41 | ... K3: ='Data Sheet'!K41
A4: Sales | B4: ='Data Sheet'!B42 | C4: ='Data Sheet'!C42 | D4: ='Data Sheet'!D42 | E4: ='Data Sheet'!E42 | F4: ='Data Sheet'!F42 | G4: ='Data Sheet'!G42 | H4: ='Data Sheet'!H42 | I4: ='Data Sheet'!I42 | ... K4: ='Data Sheet'!K42
A5: Expenses | B5: ='Data Sheet'!B43 | C5: ='Data Sheet'!C43 | D5: ='Data Sheet'!D43 | E5: ='Data Sheet'!E43 | F5: ='Data Sheet'!F43 | G5: ='Data Sheet'!G43 | H5: ='Data Sheet'!H43 | I5: ='Data Sheet'!I43 | ... K5: ='Data Sheet'!K43
A6: Operating Profit | B6: ='Data Sheet'!B50 | C6: ='Data Sheet'!C50 | D6: ='Data Sheet'!D50 | E6: ='Data Sheet'!E50 | F6: ='Data Sheet'!F50 | G6: ='Data Sheet'!G50 | H6: ='Data Sheet'!H50 | I6: ='Data Sheet'!I50 | ... K6: ='Data Sheet'!K50
A7: Other Income | B7: ='Data Sheet'!B44 | C7: ='Data Sheet'!C44 | D7: ='Data Sheet'!D44 | E7: ='Data Sheet'!E44 | F7: ='Data Sheet'!F44 | G7: ='Data Sheet'!G44 | H7: ='Data Sheet'!H44 | I7: ='Data Sheet'!I44 | ... K7: ='Data Sheet'!K44
A8: Depreciation | B8: ='Data Sheet'!B45 | C8: ='Data Sheet'!C45 | D8: ='Data Sheet'!D45 | E8: ='Data Sheet'!E45 | F8: ='Data Sheet'!F45 | G8: ='Data Sheet'!G45 | H8: ='Data Sheet'!H45 | I8: ='Data Sheet'!I45 | ... K8: ='Data Sheet'!K45
A9: Interest | B9: ='Data Sheet'!B46 | C9: ='Data Sheet'!C46 | D9: ='Data Sheet'!D46 | E9: ='Data Sheet'!E46 | F9: ='Data Sheet'!F46 | G9: ='Data Sheet'!G46 | H9: ='Data Sheet'!H46 | I9: ='Data Sheet'!I46 | ... K9: ='Data Sheet'!K46
A10: Profit before tax | B10: ='Data Sheet'!B47 | C10: ='Data Sheet'!C47 | D10: ='Data Sheet'!D47 | E10: ='Data Sheet'!E47 | F10: ='Data Sheet'!F47 | G10: ='Data Sheet'!G47 | H10: ='Data Sheet'!H47 | I10: ='Data Sheet'!I47 | ... K10: ='Data Sheet'!K47
A11: Tax | B11: ='Data Sheet'!B48 | C11: ='Data Sheet'!C48 | D11: ='Data Sheet'!D48 | E11: ='Data Sheet'!E48 | F11: ='Data Sheet'!F48 | G11: ='Data Sheet'!G48 | H11: ='Data Sheet'!H48 | I11: ='Data Sheet'!I48 | ... K11: ='Data Sheet'!K48
A12: Net profit | B12: ='Data Sheet'!B49 | C12: ='Data Sheet'!C49 | D12: ='Data Sheet'!D49 | E12: ='Data Sheet'!E49 | F12: ='Data Sheet'!F49 | G12: ='Data Sheet'!G49 | H12: ='Data Sheet'!H49 | I12: ='Data Sheet'!I49 | ... K12: ='Data Sheet'!K49
A14: OPM | B14: =IF(B4>0,B6/B4,"") | C14: =IF(C4>0,C6/C4,"") | D14: =IF(D4>0,D6/D4,"") | E14: =IF(E4>0,E6/E4,"") | F14: =IF(F4>0,F6/F4,"") | G14: =IF(G4>0,G6/G4,"") | H14: =IF(H4>0,H6/H4,"") | I14: =IF(I4>0,I6/I4,"") | ... K14: =IF(K4>0,K6/K4,"")

Sheet Balance Sheet
A1: ='Profit & Loss'!A1 | E1: =UPDATE | J1: SCREENER.IN
A3: Narration | B3: ='Data Sheet'!B56 | C3: ='Data Sheet'!C56 | D3: ='Data Sheet'!D56 | E3: ='Data Sheet'!E56 | F3: ='Data Sheet'!F56 | G3: ='Data Sheet'!G56 | H3: ='Data Sheet'!H56 | I3: ='Data Sheet'!I56 | ... K3: ='Data Sheet'!K56
A4: Equity Share Capital | B4: ='Data Sheet'!B57 | C4: ='Data Sheet'!C57 | D4: ='Data Sheet'!D57 | E4: ='Data Sheet'!E57 | F4: ='Data Sheet'!F57 | G4: ='Data Sheet'!G57 | H4: ='Data Sheet'!H57 | I4: ='Data Sheet'!I57 | ... K4: ='Data Sheet'!K57
A5: Reserves | B5: ='Data Sheet'!B58 | C5: ='Data Sheet'!C58 | D5: ='Data Sheet'!D58 | E5: ='Data Sheet'!E58 | F5: ='Data Sheet'!F58 | G5: ='Data Sheet'!G58 | H5: ='Data Sheet'!H58 | I5: ='Data Sheet'!I58 | ... K5: ='Data Sheet'!K58
A6: Borrowings | B6: ='Data Sheet'!B59 | C6: ='Data Sheet'!C59 | D6: ='Data Sheet'!D59 | E6: ='Data Sheet'!E59 | F6: ='Data Sheet'!F59 | G6: ='Data Sheet'!G59 | H6: ='Data Sheet'!H59 | I6: ='Data Sheet'!I59 | ... K6: ='Data Sheet'!K59
A7: Other Liabilities | B7: ='Data Sheet'!B60 | C7: ='Data Sheet'!C60 | D7: ='Data Sheet'!D60 | E7: ='Data Sheet'!E60 | F7: ='Data Sheet'!F60 | G7: ='Data Sheet'!G60 | H7: ='Data Sheet'!H60 | I7: ='Data Sheet'!I60 | ... K7: ='Data Sheet'!K60
A8: Total | B8: ='Data Sheet'!B61 | C8: ='Data Sheet'!C61 | D8: ='Data Sheet'!D61 | E8: ='Data Sheet'!E61 | F8: ='Data Sheet'!F61 | G8: ='Data Sheet'!G61 | H8: ='Data Sheet'!H61 | I8: ='Data Sheet'!I61 | ... K8: ='Data Sheet'!K61
A10: Net Block | B10: ='Data Sheet'!B62 | C10: ='Data Sheet'!C62 | D10: ='Data Sheet'!D62 | E10: ='Data Sheet'!E62 | F10: ='Data Sheet'!F62 | G10: ='Data Sheet'!G62 | H10: ='Data Sheet'!H62 | I10: ='Data Sheet'!I62 | ... K10: ='Data Sheet'!K62
A11: Capital Work in Progress | B11: ='Data Sheet'!B63 | C11: ='Data Sheet'!C63 | D11: ='Data Sheet'!D63 | E11: ='Data Sheet'!E63 | F11: ='Data Sheet'!F63 | G11: ='Data Sheet'!G63 | H11: ='Data Sheet'!H63 | I11: ='Data Sheet'!I63 | ... K11: ='Data Sheet'!K63
A12: Investments | B12: ='Data Sheet'!B64 | C12: ='Data Sheet'!C64 | D12: ='Data Sheet'!D64 | E12: ='Data Sheet'!E64 | F12: ='Data Sheet'!F64 | G12: ='Data Sheet'!G64 | H12: ='Data Sheet'!H64 | I12: ='Data Sheet'!I64 | ... K12: ='Data Sheet'!K64
A13: Other Assets | B13: ='Data Sheet'!B65 | C13: ='Data Sheet'!C65 | D13: ='Data Sheet'!D65 | E13: ='Data Sheet'!E65 | F13: ='Data Sheet'!F65 | G13: ='Data Sheet'!G65 | H13: ='Data Sheet'!H65 | I13: ='Data Sheet'!I65 | ... K13: ='Data Sheet'!K65
A14: Total | B14: ='Data Sheet'!B66 | C14: ='Data Sheet'!C66 | D14: ='Data Sheet'!D66 | E14: ='Data Sheet'!E66 | F14: ='Data Sheet'!F66 | G14: ='Data Sheet'!G66 | H14: ='Data Sheet'!H66 | I14: ='Data Sheet'!I66 | ... K14: ='Data Sheet'!K66
A16: Working Capital | B16: =B13-B7 | C16: =C13-C7 | D16: =D13-D7 | E16: =E13-E7 | F16: =F13-F7 | G16: =G13-G7 | H16: =H13-H7 | I16: =I13-I7 | ... K16: =K13-K7
A17: Debtors | B17: ='Data Sheet'!B67 | C17: ='Data Sheet'!C67 | D17: ='Data Sheet'!D67 | E17: ='Data Sheet'!E67 | F17: ='Data Sheet'!F67 | G17: ='Data Sheet'!G67 | H17: ='Data Sheet'!H67 | I17: ='Data Sheet'!I67 | ... K17: ='Data Sheet'!K67
A18: Inventory | B18: ='Data Sheet'!B68 | C18: ='Data Sheet'!C68 | D18: ='Data Sheet'!D68 | E18: ='Data Sheet'!E68 | F18: ='Data Sheet'!F68 | G18: ='Data Sheet'!G68 | H18: ='Data Sheet'!H68 | I18: ='Data Sheet'!I68 | ... K18: ='Data Sheet'!K68
A20: Debtor Days | B20: =IF('Profit & Loss'!B4>0,'Balance Sheet'!B17/('Profit & Loss'!B4/365),0) | C20: =IF('Profit & Loss'!C4>0,'Balance Sheet'!C17/('Profit & Loss'!C4/365),0) | D20: =IF('Profit & Loss'!D4>0,'Balance Sheet'!D17/('Profit & Loss'!D4/365),0) | E20: =IF('Profit & Loss'!E4>0,'Balance Sheet'!E17/('Profit & Loss'!E4/365),0) | F20: =IF('Profit & Loss'!F4>0,'Balance Sheet'!F17/('Profit & Loss'!F4/365),0) | G20: =IF('Profit & Loss'!G4>0,'Balance Sheet'!G17/('Profit & Loss'!G4/365),0) | H20: =IF('Profit & Loss'!H4>0,'Balance Sheet'!H17/('Profit & Loss'!H4/365),0) | I20: =IF('Profit & Loss'!I4>0,'Balance Sheet'!I17/('Profit & Loss'!I4/365),0) | ... K20: =IF('Profit & Loss'!K4>0,'Balance Sheet'!K17/('Profit & Loss'!K4/365),0)
A21: Inventory Turnover | B21: =IF('Balance Sheet'!B18>0,'Profit & Loss'!B4/'Balance Sheet'!B18,0) | C21: =IF('Balance Sheet'!C18>0,'Profit & Loss'!C4/'Balance Sheet'!C18,0) | D21: =IF('Balance Sheet'!D18>0,'Profit & Loss'!D4/'Balance Sheet'!D18,0) | E21: =IF('Balance Sheet'!E18>0,'Profit & Loss'!E4/'Balance Sheet'!E18,0) | F21: =IF('Balance Sheet'!F18>0,'Profit & Loss'!F4/'Balance Sheet'!F18,0) | G21: =IF('Balance Sheet'!G18>0,'Profit & Loss'!G4/'Balance Sheet'!G18,0) | H21: =IF('Balance Sheet'!H18>0,'Profit & Loss'!H4/'Balance Sheet'!H18,0) | I21: =IF('Balance Sheet'!I18>0,'Profit & Loss'!I4/'Balance Sheet'!I18,0) | ... K21: =IF('Balance Sheet'!K18>0,'Profit & Loss'!K4/'Balance Sheet'!K18,0)
A23: Return on Equity | B23: =IF(SUM('Balance Sheet'!B4:B5)>0,'Profit & Loss'!B12/SUM('Balance Sheet'!B4:B5),"") | C23: =IF(SUM('Balance Sheet'!C4:C5)>0,'Profit & Loss'!C12/SUM('Balance Sheet'!C4:C5),"") | D23: =IF(SUM('Balance Sheet'!D4:D5)>0,'Profit & Loss'!D12/SUM('Balance Sheet'!D4:D5),"") | E23: =IF(SUM('Balance Sheet'!E4:E5)>0,'Profit & Loss'!E12/SUM('Balance Sheet'!E4:E5),"") | F23: =IF(SUM('Balance Sheet'!F4:F5)>0,'Profit & Loss'!F12/SUM('Balance Sheet'!F4:F5),"") | G23: =IF(SUM('Balance Sheet'!G4:G5)>0,'Profit & Loss'!G12/SUM('Balance Sheet'!G4:G5),"") | H23: =IF(SUM('Balance Sheet'!H4:H5)>0,'Profit & Loss'!H12/SUM('Balance Sheet'!H4:H5),"") | I23: =IF(SUM('Balance Sheet'!I4:I5)>0,'Profit & Loss'!I12/SUM('Balance Sheet'!I4:I5),"") | ... K23: =IF(SUM('Balance Sheet'!K4:K5)>0,'Profit & Loss'!K12/SUM('Balance Sheet'!K4:K5),"")
A24: Return on Capital Emp | C24: =IF((B4+B5+B6+C4+C5+C6)>0,('Profit & Loss'!C10+'Profit & Loss'!C9)*2/(B4+B5+B6+C4+C5+C6),"") | D24: =IF((C4+C5+C6+D4+D5+D6)>0,('Profit & Loss'!D10+'Profit & Loss'!D9)*2/(C4+C5+C6+D4+D5+D6),"") | E24: =IF((D4+D5+D6+E4+E5+E6)>0,('Profit & Loss'!E10+'Profit & Loss'!E9)*2/(D4+D5+D6+E4+E5+E6),"") | F24: =IF((E4+E5+E6+F4+F5+F6)>0,('Profit & Loss'!F10+'Profit & Loss'!F9)*2/(E4+E5+E6+F4+F5+F6),"") | G24: =IF((F4+F5+F6+G4+G5+G6)>0,('Profit & Loss'!G10+'Profit & Loss'!G9)*2/(F4+F5+F6+G4+G5+G6),"") | H24: =IF((G4+G5+G6+H4+H5+H6)>0,('Profit & Loss'!H10+'Profit & Loss'!H9)*2/(G4+G5+G6+H4+H5+H6),"") | I24: =IF((H4+H5+H6+I4+I5+I6)>0,('Profit & Loss'!I10+'Profit & Loss'!I9)*2/(H4+H5+H6+I4+I5+I6),"") | J24: =IF((I4+I5+I6+J4+J5+J6)>0,('Profit & Loss'!J10+'Profit & Loss'!J9)*2/(I4+I5+I6+J4+J5+J6),"") | K24: =IF((J4+J5+J6+K4+K5+K6)>0,('Profit & Loss'!K10+'Profit & Loss'!K9)*2/(J4+J5+J6+K4+K5+K6),"")

Sheet Cash Flow
A1: ='Balance Sheet'!A1 | E1: =UPDATE | J1: SCREENER.IN
A3: Narration | B3: ='Data Sheet'!B81 | C3: ='Data Sheet'!C81 | D3: ='Data Sheet'!D81 | E3: ='Data Sheet'!E81 | F3: ='Data Sheet'!F81 | G3: ='Data Sheet'!G81 | H3: ='Data Sheet'!H81 | I3: ='Data Sheet'!I81 | ... K3: ='Data Sheet'!K81
A4: Cash from Operating Activity | B4: ='Data Sheet'!B82 | C4: ='Data Sheet'!C82 | D4: ='Data Sheet'!D82 | E4: ='Data Sheet'!E82 | F4: ='Data Sheet'!F82 | G4: ='Data Sheet'!G82 | H4: ='Data Sheet'!H82 | I4: ='Data Sheet'!I82 | ... K4: ='Data Sheet'!K82
A5: Cash from Investing Activity | B5: ='Data Sheet'!B83 | C5: ='Data Sheet'!C83 | D5: ='Data Sheet'!D83 | E5: ='Data Sheet'!E83 | F5: ='Data Sheet'!F83 | G5: ='Data Sheet'!G83 | H5: ='Data Sheet'!H83 | I5: ='Data Sheet'!I83 | ... K5: ='Data Sheet'!K83
A6: Cash from Financing Activity | B6: ='Data Sheet'!B84 | C6: ='Data Sheet'!C84 | D6: ='Data Sheet'!D84 | E6: ='Data Sheet'!E84 | F6: ='Data Sheet'!F84 | G6: ='Data Sheet'!G84 | H6: ='Data Sheet'!H84 | I6: ='Data Sheet'!I84 | ... K6: ='Data Sheet'!K84
A7: Net Cash Flow | B7: ='Data Sheet'!B85 | C7: ='Data Sheet'!C85 | D7: ='Data Sheet'!D85 | E7: ='Data Sheet'!E85 | F7: ='Data Sheet'!F85 | G7: ='Data Sheet'!G85 | H7: ='Data Sheet'!H85 | I7: ='Data Sheet'!I85 | ... K7: ='Data Sheet'!K85

Sheet Customization
A1: How to use it?
A3: You can customize this workbook as you want.
B4: You can add custom formating, add conditional formating, add your own formulas… do ANYTHING.
B5: Please don't edit the "Data Sheet" only.
A7: After customization, you can upload this back on Screener.
B8: Upload on: | C8: https://www.screener.in/excel/
A10: Download your customized workbooks now onwards.
B11: Now whenever you will "Export to excel" from Screener, it will export your customized file.
A14: TESTING:
B15: This is a testing feature currently.
B16: You can report any formula errors on the worksheet at: support@screener.in

Sheet Common Size Statement
B2: ="Common Size Statement - "&'Data Sheet'!$B$1
B4: Particulars | C4: ='Data Sheet'!B$16 | D4: ='Data Sheet'!C$16 | E4: ='Data Sheet'!D$16 | F4: ='Data Sheet'!E$16 | G4: ='Data Sheet'!F$16 | H4: ='Data Sheet'!G$16 | I4: ='Data Sheet'!H$16 | J4: ='Data Sheet'!I$16 | ... L4: ='Data Sheet'!K$16
B6: ='Data Sheet'!A17 | C6: ='Data Sheet'!B17/'Data Sheet'!B$17 | D6: ='Data Sheet'!C17/'Data Sheet'!C$17 | E6: ='Data Sheet'!D17/'Data Sheet'!D$17 | F6: ='Data Sheet'!E17/'Data Sheet'!E$17 | G6: ='Data Sheet'!F17/'Data Sheet'!F$17 | H6: ='Data Sheet'!G17/'Data Sheet'!G$17 | I6: ='Data Sheet'!H17/'Data Sheet'!H$17 | J6: ='Data Sheet'!I17/'Data Sheet'!I$17 | ... L6: ='Data Sheet'!K17/'Data Sheet'!K$17
B7: ='Data Sheet'!A18 | C7: ='Data Sheet'!B18/'Data Sheet'!B$17 | D7: ='Data Sheet'!C18/'Data Sheet'!C$17 | E7: ='Data Sheet'!D18/'Data Sheet'!D$17 | F7: ='Data Sheet'!E18/'Data Sheet'!E$17 | G7: ='Data Sheet'!F18/'Data Sheet'!F$17 | H7: ='Data Sheet'!G18/'Data Sheet'!G$17 | I7: ='Data Sheet'!H18/'Data Sheet'!H$17 | J7: ='Data Sheet'!I18/'Data Sheet'!I$17 | ... L7: ='Data Sheet'!K18/'Data Sheet'!K$17
B8: ='Data Sheet'!A19 | C8: ='Data Sheet'!B19/'Data Sheet'!B$17 | D8: ='Data Sheet'!C19/'Data Sheet'!C$17 | E8: ='Data Sheet'!D19/'Data Sheet'!D$17 | F8: ='Data Sheet'!E19/'Data Sheet'!E$17 | G8: ='Data Sheet'!F19/'Data Sheet'!F$17 | H8: ='Data Sheet'!G19/'Data Sheet'!G$17 | I8: ='Data Sheet'!H19/'Data Sheet'!H$17 | J8: ='Data Sheet'!I19/'Data Sheet'!I$17 | ... L8: ='Data Sheet'!K19/'Data Sheet'!K$17
B9: ='Data Sheet'!A20 | C9: ='Data Sheet'!B20/'Data Sheet'!B$17 | D9: ='Data Sheet'!C20/'Data Sheet'!C$17 | E9: ='Data Sheet'!D20/'Data Sheet'!D$17 | F9: ='Data Sheet'!E20/'Data Sheet'!E$17 | G9: ='Data Sheet'!F20/'Data Sheet'!F$17 | H9: ='Data Sheet'!G20/'Data Sheet'!G$17 | I9: ='Data Sheet'!H20/'Data Sheet'!H$17 | J9: ='Data Sheet'!I20/'Data Sheet'!I$17 | ... L9: ='Data Sheet'!K20/'Data Sheet'!K$17
B10: ='Data Sheet'!A21 | C10: ='Data Sheet'!B21/'Data Sheet'!B$17 | D10: ='Data Sheet'!C21/'Data Sheet'!C$17 | E10: ='Data Sheet'!D21/'Data Sheet'!D$17 | F10: ='Data Sheet'!E21/'Data Sheet'!E$17 | G10: ='Data Sheet'!F21/'Data Sheet'!F$17 | H10: ='Data Sheet'!G21/'Data Sheet'!G$17 | I10: ='Data Sheet'!H21/'Data Sheet'!H$17 | J10: ='Data Sheet'!I21/'Data Sheet'!I$17 | ... L10: ='Data Sheet'!K21/'Data Sheet'!K$17
B11: ='Data Sheet'!A22 | C11: ='Data Sheet'!B22/'Data Sheet'!B$17 | D11: ='Data Sheet'!C22/'Data Sheet'!C$17 | E11: ='Data Sheet'!D22/'Data Sheet'!D$17 | F11: ='Data Sheet'!E22/'Data Sheet'!E$17 | G11: ='Data Sheet'!F22/'Data Sheet'!F$17 | H11: ='Data Sheet'!G22/'Data Sheet'!G$17 | I11: ='Data Sheet'!H22/'Data Sheet'!H$17 | J11: ='Data Sheet'!I22/'Data Sheet'!I$17 | ... L11: ='Data Sheet'!K22/'Data Sheet'!K$17
B12: ='Data Sheet'!A23 | C12: ='Data Sheet'!B23/'Data Sheet'!B$17 | D12: ='Data Sheet'!C23/'Data Sheet'!C$17 | E12: ='Data Sheet'!D23/'Data Sheet'!D$17 | F12: ='Data Sheet'!E23/'Data Sheet'!E$17 | G12: ='Data Sheet'!F23/'Data Sheet'!F$17 | H12: ='Data Sheet'!G23/'Data Sheet'!G$17 | I12: ='Data Sheet'!H23/'Data Sheet'!H$17 | J12: ='Data Sheet'!I23/'Data Sheet'!I$17 | ... L12: ='Data Sheet'!K23/'Data Sheet'!K$17
B13: ='Data Sheet'!A24 | C13: ='Data Sheet'!B24/'Data Sheet'!B$17 | D13: ='Data Sheet'!C24/'Data Sheet'!C$17 | E13: ='Data Sheet'!D24/'Data Sheet'!D$17 | F13: ='Data Sheet'!E24/'Data Sheet'!E$17 | G13: ='Data Sheet'!F24/'Data Sheet'!F$17 | H13: ='Data Sheet'!G24/'Data Sheet'!G$17 | I13: ='Data Sheet'!H24/'Data Sheet'!H$17 | J13: ='Data Sheet'!I24/'Data Sheet'!I$17 | ... L13: ='Data Sheet'!K24/'Data Sheet'!K$17
B14: ='Data Sheet'!A25 | C14: ='Data Sheet'!B25/'Data Sheet'!B$17 | D14: ='Data Sheet'!C25/'Data Sheet'!C$17 | E14: ='Data Sheet'!D25/'Data Sheet'!D$17 | F14: ='Data Sheet'!E25/'Data Sheet'!E$17 | G14: ='Data Sheet'!F25/'Data Sheet'!F$17 | H14: ='Data Sheet'!G25/'Data Sheet'!G$17 | I14: ='Data Sheet'!H25/'Data Sheet'!H$17 | J14: ='Data Sheet'!I25/'Data Sheet'!I$17 | ... L14: ='Data Sheet'!K25/'Data Sheet'!K$17
B15: ='Data Sheet'!A26 | C15: ='Data Sheet'!B26/'Data Sheet'!B$17 | D15: ='Data Sheet'!C26/'Data Sheet'!C$17 | E15: ='Data Sheet'!D26/'Data Sheet'!D$17 | F15: ='Data Sheet'!E26/'Data Sheet'!E$17 | G15: ='Data Sheet'!F26/'Data Sheet'!F$17 | H15: ='Data Sheet'!G26/'Data Sheet'!G$17 | I15: ='Data Sheet'!H26/'Data Sheet'!H$17 | J15: ='Data Sheet'!I26/'Data Sheet'!I$17 | ... L15: ='Data Sheet'!K26/'Data Sheet'!K$17
B16: ='Data Sheet'!A27 | C16: ='Data Sheet'!B27/'Data Sheet'!B$17 | D16: ='Data Sheet'!C27/'Data Sheet'!C$17 | E16: ='Data Sheet'!D27/'Data Sheet'!D$17 | F16: ='Data Sheet'!E27/'Data Sheet'!E$17 | G16: ='Data Sheet'!F27/'Data Sheet'!F$17 | H16: ='Data Sheet'!G27/'Data Sheet'!G$17 | I16: ='Data Sheet'!H27/'Data Sheet'!H$17 | J16: ='Data Sheet'!I27/'Data Sheet'!I$17 | ... L16: ='Data Sheet'!K27/'Data Sheet'!K$17
B17: ='Data Sheet'!A28 | C17: ='Data Sheet'!B28/'Data Sheet'!B$17 | D17: ='Data Sheet'!C28/'Data Sheet'!C$17 | E17: ='Data Sheet'!D28/'Data Sheet'!D$17 | F17: ='Data Sheet'!E28/'Data Sheet'!E$17 | G17: ='Data Sheet'!F28/'Data Sheet'!F$17 | H17: ='Data Sheet'!G28/'Data Sheet'!G$17 | I17: ='Data Sheet'!H28/'Data Sheet'!H$17 | J17: ='Data Sheet'!I28/'Data Sheet'!I$17 | ... L17: ='Data Sheet'!K28/'Data Sheet'!K$17
... B21: ='Data Sheet'!A32 | C21: ='Data Sheet'!B32/'Data Sheet'!B$17 | D21: ='Data Sheet'!C32/'Data Sheet'!C$17 | E21: ='Data Sheet'!D32/'Data Sheet'!D$17 | F21: ='Data Sheet'!E32/'Data Sheet'!E$17 | G21: ='Data Sheet'!F32/'Data Sheet'!F$17 | H21: ='Data Sheet'!G32/'Data Sheet'!G$17 | I21: ='Data Sheet'!H32/'Data Sheet'!H$17 | J21: ='Data Sheet'!I32/'Data Sheet'!I$17 | ... L21: ='Data Sheet'!K32/'Data Sheet'!K$17
B23: ="Common Size Balance Sheet - "&'Data Sheet'!$B$1
B25: Particulars | C25: ='Data Sheet'!B$16 | D25: ='Data Sheet'!C$16 | E25: ='Data Sheet'!D$16 | F25: ='Data Sheet'!E$16 | G25: ='Data Sheet'!F$16 | H25: ='Data Sheet'!G$16 | I25: ='Data Sheet'!H$16 | J25: ='Data Sheet'!I$16 | ... L25: ='Data Sheet'!K$16
B27: Total Liabilities | C27: ='Data Sheet'!B61/'Data Sheet'!B$61 | D27: ='Data Sheet'!C61/'Data Sheet'!C$61 | E27: ='Data Sheet'!D61/'Data Sheet'!D$61 | F27: ='Data Sheet'!E61/'Data Sheet'!E$61 | G27: ='Data Sheet'!F61/'Data Sheet'!F$61 | H27: ='Data Sheet'!G61/'Data Sheet'!G$61 | I27: ='Data Sheet'!H61/'Data Sheet'!H$61 | J27: ='Data Sheet'!I61/'Data Sheet'!I$61 | ... L27: ='Data Sheet'!K61/'Data Sheet'!K$61
B28: ='Data Sheet'!A57 | C28: ='Data Sheet'!B57/'Data Sheet'!B$61 | D28: ='Data Sheet'!C57/'Data Sheet'!C$61 | E28: ='Data Sheet'!D57/'Data Sheet'!D$61 | F28: ='Data Sheet'!E57/'Data Sheet'!E$61 | G28: ='Data Sheet'!F57/'Data Sheet'!F$61 | H28: ='Data Sheet'!G57/'Data Sheet'!G$61 | I28: ='Data Sheet'!H57/'Data Sheet'!H$61 | J28: ='Data Sheet'!I57/'Data Sheet'!I$61 | ... L28: ='Data Sheet'!K57/'Data Sheet'!K$61
B29: ='Data Sheet'!A58 | C29: ='Data Sheet'!B58/'Data Sheet'!B$61 | D29: ='Data Sheet'!C58/'Data Sheet'!C$61 | E29: ='Data Sheet'!D58/'Data Sheet'!D$61 | F29: ='Data Sheet'!E58/'Data Sheet'!E$61 | G29: ='Data Sheet'!F58/'Data Sheet'!F$61 | H29: ='Data Sheet'!G58/'Data Sheet'!G$61 | I29: ='Data Sheet'!H58/'Data Sheet'!H$61 | J29: ='Data Sheet'!I58/'Data Sheet'!I$61 | ... L29: ='Data Sheet'!K58/'Data Sheet'!K$61
B30: ='Data Sheet'!A59 | C30: ='Data Sheet'!B59/'Data Sheet'!B$61 | D30: ='Data Sheet'!C59/'Data Sheet'!C$61 | E30: ='Data Sheet'!D59/'Data Sheet'!D$61 | F30: ='Data Sheet'!E59/'Data Sheet'!E$61 | G30: ='Data Sheet'!F59/'Data Sheet'!F$61 | H30: ='Data Sheet'!G59/'Data Sheet'!G$61 | I30: ='Data Sheet'!H59/'Data Sheet'!H$61 | J30: ='Data Sheet'!I59/'Data Sheet'!I$61 | ... L30: ='Data Sheet'!K59/'Data Sheet'!K$61
B31: ='Data Sheet'!A60 | C31: ='Data Sheet'!B60/'Data Sheet'!B$61 | D31: ='Data Sheet'!C60/'Data Sheet'!C$61 | E31: ='Data Sheet'!D60/'Data Sheet'!D$61 | F31: ='Data Sheet'!E60/'Data Sheet'!E$61 | G31: ='Data Sheet'!F60/'Data Sheet'!F$61 | H31: ='Data Sheet'!G60/'Data Sheet'!G$61 | I31: ='Data Sheet'!H60/'Data Sheet'!H$61 | J31: ='Data Sheet'!I60/'Data Sheet'!I$61 | ... L31: ='Data Sheet'!K60/'Data Sheet'!K$61
B33: Total Assets | C33: ='Data Sheet'!B66/'Data Sheet'!B$66 | D33: ='Data Sheet'!C66/'Data Sheet'!C$66 | E33: ='Data Sheet'!D66/'Data Sheet'!D$66 | F33: ='Data Sheet'!E66/'Data Sheet'!E$66 | G33: ='Data Sheet'!F66/'Data Sheet'!F$66 | H33: ='Data Sheet'!G66/'Data Sheet'!G$66 | I33: ='Data Sheet'!H66/'Data Sheet'!H$66 | J33: ='Data Sheet'!I66/'Data Sheet'!I$66 | ... L33: ='Data Sheet'!K66/'Data Sheet'!K$66
B34: Fixed Assets Net Block | C34: ='Data Sheet'!B62/'Data Sheet'!B$66 | D34: ='Data Sheet'!C62/'Data Sheet'!C$66 | E34: ='Data Sheet'!D62/'Data Sheet'!D$66 | F34: ='Data Sheet'!E62/'Data Sheet'!E$66 | G34: ='Data Sheet'!F62/'Data Sheet'!F$66 | H34: ='Data Sheet'!G62/'Data Sheet'!G$66 | I34: ='Data Sheet'!H62/'Data Sheet'!H$66 | J34: ='Data Sheet'!I62/'Data Sheet'!I$66 | ... L34: ='Data Sheet'!K62/'Data Sheet'!K$66
B35: ='Data Sheet'!A63 | C35: ='Data Sheet'!B63/'Data Sheet'!B$66 | D35: ='Data Sheet'!C63/'Data Sheet'!C$66 | E35: ='Data Sheet'!D63/'Data Sheet'!D$66 | F35: ='Data Sheet'!E63/'Data Sheet'!E$66 | G35: ='Data Sheet'!F63/'Data Sheet'!F$66 | H35: ='Data Sheet'!G63/'Data Sheet'!G$66 | I35: ='Data Sheet'!H63/'Data Sheet'!H$66 | J35: ='Data Sheet'!I63/'Data Sheet'!I$66 | ... L35: ='Data Sheet'!K63/'Data Sheet'!K$66
B36: ='Data Sheet'!A64 | C36: ='Data Sheet'!B64/'Data Sheet'!B$66 | D36: ='Data Sheet'!C64/'Data Sheet'!C$66 | E36: ='Data Sheet'!D64/'Data Sheet'!D$66 | F36: ='Data Sheet'!E64/'Data Sheet'!E$66 | G36: ='Data Sheet'!F64/'Data Sheet'!F$66 | H36: ='Data Sheet'!G64/'Data Sheet'!G$66 | I36: ='Data Sheet'!H64/'Data Sheet'!H$66 | J36: ='Data Sheet'!I64/'Data Sheet'!I$66 | ... L36: ='Data Sheet'!K64/'Data Sheet'!K$66
B37: ='Data Sheet'!A65 | C37: ='Data Sheet'!B74/'Data Sheet'!B66 | D37: ='Data Sheet'!C74/'Data Sheet'!C66 | E37: ='Data Sheet'!D74/'Data Sheet'!D66 | F37: ='Data Sheet'!E74/'Data Sheet'!E66 | G37: ='Data Sheet'!F74/'Data Sheet'!F66 | H37: ='Data Sheet'!G74/'Data Sheet'!G66 | I37: ='Data Sheet'!H74/'Data Sheet'!H66 | J37: ='Data Sheet'!I74/'Data Sheet'!I66 | ... L37: ='Data Sheet'!K74/'Data Sheet'!K66
B38: ='Data Sheet'!A67 | C38: ='Data Sheet'!B67/'Data Sheet'!B$66 | D38: ='Data Sheet'!C67/'Data Sheet'!C$66 | E38: ='Data Sheet'!D67/'Data Sheet'!D$66 | F38: ='Data Sheet'!E67/'Data Sheet'!E$66 | G38: ='Data Sheet'!F67/'Data Sheet'!F$66 | H38: ='Data Sheet'!G67/'Data Sheet'!G$66 | I38: ='Data Sheet'!H67/'Data Sheet'!H$66 | J38: ='Data Sheet'!I67/'Data Sheet'!I$66 | ... L38: ='Data Sheet'!K67/'Data Sheet'!K$66
B39: ='Data Sheet'!A68 | C39: ='Data Sheet'!B68/'Data Sheet'!B$66 | D39: ='Data Sheet'!C68/'Data Sheet'!C$66 | E39: ='Data Sheet'!D68/'Data Sheet'!D$66 | F39: ='Data Sheet'!E68/'Data Sheet'!E$66 | G39: ='Data Sheet'!F68/'Data Sheet'!F$66 | H39: ='Data Sheet'!G68/'Data Sheet'!G$66 | I39: ='Data Sheet'!H68/'Data Sheet'!H$66 | J39: ='Data Sheet'!I68/'Data Sheet'!I$66 | ... L39: ='Data Sheet'!K68/'Data Sheet'!K$66
B40: ='Data Sheet'!A69 | C40: ='Data Sheet'!B69/'Data Sheet'!B$66 | D40: ='Data Sheet'!C69/'Data Sheet'!C$66 | E40: ='Data Sheet'!D69/'Data Sheet'!D$66 | F40: ='Data Sheet'!E69/'Data Sheet'!E$66 | G40: ='Data Sheet'!F69/'Data Sheet'!F$66 | H40: ='Data Sheet'!G69/'Data Sheet'!G$66 | I40: ='Data Sheet'!H69/'Data Sheet'!H$66 | J40: ='Data Sheet'!I69/'Data Sheet'!I$66 | ... L40: ='Data Sheet'!K69/'Data Sheet'!K$66

Sheet Data Sheet
A1: COMPANY NAME | B1: TATA STEEL LTD | E1: =IF(B2<>B3, "A NEW VERSION OF THE WORKSHEET IS AVAILABLE", "")
A2: LATEST VERSION | B2: 2.1 | E2: PLEASE DO NOT MAKE ANY CHANGES TO THIS SHEET
A3: CURRENT VERSION | B3: 2.1
A5: META
A6: Number of shares | B6: =IF(B9>0, B9/B8, 0)
A7: Face Value | B7: 1
A8: Current Price | B8: 177
A9: Market Capitalization | B9: 220719
A15: PROFIT & LOSS
A16: Report Date | B16: 42825 | C16: 43190 | D16: 43555 | E16: 43921 | F16: 44286 | G16: 44651 | H16: 45016 | I16: 45382 | J16: 45747 | K16: 46112
A17: Sales | B17: 112299 | C17: 123249 | D17: 157669 | E17: 139817 | F17: 156477 | G17: 243959 | H17: 243353 | I17: 229171 | J17: 218543 | K17: 232140
A18: Raw Material Cost | B18: 43843 | C18: 46137 | D18: 60877 | E18: 58040 | F18: 55101 | G18: 91077 | H18: 116597 | I18: 97506 | J18: 95097 | K18: 92628
A19: Change in Inventory | B19: -4538 | C19: 99 | D19: -97 | E19: -565 | F19: 1517 | G19: -7598 | H19: -3359 | I19: 4409 | J19: -97 | K19: 990
A20: Power and Fuel | B20: 0 | C20: 0 | D20: 0 | E20: 0 | F20: 0 | G20: 0 | H20: 0 | I20: 0 | J20: 0 | K20: 0
A21: Other Mfr. Exp | B21: 0 | C21: 0 | D21: 0 | E21: 0 | F21: 0 | G21: 0 | H21: 0 | I21: 0 | J21: 0 | K21: 0
A22: Employee Cost | B22: 0 | C22: 0 | D22: 0 | E22: 0 | F22: 0 | G22: 0 | H22: 0 | I22: 23971.29 | J22: 23405.96 | K22: 24583.63
A23: Selling and admin | B23: 14962.75 | C23: 13895 | D23: 16892.75 | E23: 16219.75 | F23: 17338.75 | G23: 24247.5 | H23: 24453.75 | I23: 20259.18 | J23: 18709.51 | K23: 19896.59
A24: Other Expenses | B24: 44888.25 | C24: 41685 | D24: 50678.25 | E24: 48659.25 | F24: 52016.25 | G24: 72742.5 | H24: 73361.25 | I24: 60777.53 | J24: 56128.53 | K24: 59689.78
A25: Other Income | B25: -3789 | C25: 10898 | D25: 1524 | E25: -2884 | F25: 180 | G25: 1300 | H25: 1569 | I25: -6005 | J25: 877 | K25: 738
A26: Depreciation | B26: 5673 | C26: 5742 | D26: 7342 | E26: 8441 | F26: 9234 | G26: 9101 | H26: 9335 | I26: 9882 | J26: 10421 | K26: 11955
A27: Interest | B27: 5072 | C27: 5455 | D27: 7660 | E27: 7533 | F27: 7607 | G27: 5462 | H27: 6299 | I27: 7508 | J27: 7341 | K27: 7167
... A31: Dividend Amount | B31: 0 | C31: 1596.87 | D31: 1368.3 | E31: 868.76 | F31: 3276 | G31: 6679.84 | H31: 4037.5 | I31: 0 | J31: 4157.94 | K31: 5007.56
A32: EBITDA | B32: =SUM(B26:B28) | C32: =SUM(C26:C28) | D32: =SUM(D26:D28) | E32: =SUM(E26:E28) | F32: =SUM(F26:F28) | G32: =SUM(G26:G28) | H32: =SUM(H26:H28) | I32: =SUM(I26:I28) | ... K32: =SUM(K26:K28)
B33: 0 | C33: 0 | D33: 0 | E33: 0 | F33: 0 | G33: 0 | H33: 0 | I33: 0 | J33: 0 | K33: 0
A40: Quarters
A41: Report Date | B41: 45382 | C41: 45473 | D41: 45565 | E41: 45657 | F41: 45747 | G41: 45838 | H41: 45930 | I41: 46022 | J41: 46112 | K41: 46203
A42: Sales | B42: 58687 | C42: 54771 | D42: 53905 | E42: 53648 | F42: 56218 | G42: 53178 | H42: 58689 | I42: 57002 | J42: 63270 | K42: 60794
A43: Expenses | B43: 52087 | C43: 48077 | D43: 47789 | E43: 47745 | F43: 49659 | G43: 45751 | H43: 49793 | I43: 48803 | J43: 53441 | K43: 51530
A44: Other Income | B44: -382 | C44: -6 | D44: 617 | E44: 142 | F44: 149 | G44: 236 | H44: -6 | I44: 465 | J44: 42 | K44: -17
A45: Depreciation | B45: 2568 | C45: 2535 | D45: 2597 | E45: 2569 | F45: 2720 | G45: 2744 | H45: 2893 | I45: 3049 | J45: 3268 | K45: 3640
A46: Interest | B46: 1842 | C46: 1777 | D46: 1971 | E46: 1804 | F46: 1789 | G46: 1852 | H46: 1775 | I46: 1747 | J46: 1792 | K46: 1771
A47: Profit before tax | B47: 1809 | C47: 2377 | D47: 2164 | E47: 1672 | F47: 2200 | G47: 3067 | H47: 4222 | I47: 3869 | J47: 4810 | K47: 3838
A48: Tax | B48: 452.25 | C48: 594.25 | D48: 541 | E48: 418 | F48: 550 | G48: 1060 | H48: 1039 | I48: 1139 | J48: 1845 | K48: 1453
A49: Net profit | B49: 1356.75 | C49: 1782.75 | D49: 1623 | E49: 1254 | F49: 1650 | G49: 2007 | H49: 3183 | I49: 2730 | J49: 2965 | K49: 2385
A50: Operating Profit | B50: 6601 | C50: 6694 | D50: 6116 | E50: 5903 | F50: 6559 | G50: 7428 | H50: 8897 | I50: 8200 | J50: 9829 | K50: 9264
A55: BALANCE SHEET
A56: Report Date | B56: 42825 | C56: 43190 | D56: 43555 | E56: 43921 | F56: 44286 | G56: 44651 | H56: 45016 | I56: 45382 | J56: 45747 | K56: 46112
A57: Equity Share Capital | B57: 970 | C57: 1145 | D57: 1145 | E57: 1145 | F57: 1198 | G57: 1221 | H57: 1221 | I57: 1247 | J57: 1247 | K57: 1247
A58: Reserves | B58: 36849 | C58: 59726 | D58: 67780 | E58: 72431 | F58: 73041 | G58: 113222 | H58: 101861 | I58: 90788 | J58: 89922 | K58: 100920
A59: Borrowings | B59: 83014 | C59: 92147 | D59: 100816 | E59: 116328 | F59: 88501 | G59: 75561 | H59: 84893 | I59: 87082 | J59: 94801 | K59: 92382
A60: Other Liabilities | B60: 51614 | C60: 55704 | D60: 63032 | E60: 59245 | F60: 81169 | G60: 92417 | H60: 97421 | I60: 90195 | J60: 89488 | K60: 101965
A61: Total | B61: 172447 | C61: 208722 | D61: 232773 | E61: 249149 | F61: 243909 | G61: 282422 | H61: 285396 | I61: 269312 | J61: 275459 | K61: 296515
A62: Net Block | B62: 92007 | C62: 96105 | D62: 124442 | E62: 134551 | F62: 135775 | G62: 133288 | H62: 146621 | I62: 148814 | J62: 150914 | K62: 179908
A63: Capital Work in Progress | B63: 15784 | C63: 16614 | D63: 18641 | E63: 19497 | F63: 19007 | G63: 22046 | H63: 31213 | I63: 34356 | J63: 41622 | K63: 28497
A64: Investments | B64: 12457 | C64: 17899 | D64: 5738 | E64: 6285 | F64: 10682 | G64: 13140 | H64: 8410 | I64: 6258 | J64: 6194 | K64: 7089
A65: Other Assets | B65: 52200 | C65: 78103 | D65: 83952 | E65: 88816 | F65: 78445 | G65: 113948 | H65: 99151 | I65: 79885 | J65: 76728 | K65: 81021
A66: Total | B66: 172447 | C66: 208722 | D66: 232773 | E66: 249149 | F66: 243909 | G66: 282422 | H66: 285396 | I66: 269312 | J66: 275459 | K66: 296515
A67: Receivables | B67: 11587 | C67: 12416 | D67: 11811 | E67: 7885 | F67: 9540 | G67: 12246 | H67: 8257 | I67: 6264 | J67: 5260 | K67: 4917
... A72: Face value | B72: 1 | C72: 1 | D72: 1 | E72: 1 | F72: 1 | G72: 1 | H72: 1 | I72: 1 | J72: 1 | K72: 1
B73: 0 | C73: 0 | D73: 0 | E73: 0 | F73: 0 | G73: 0 | H73: 0 | I73: 0 | J73: 0 | K73: 0
A74: Other Assets | B74: =B65-SUM(B67:B69) | C74: =C65-SUM(C67:C69) | D74: =D65-SUM(D67:D69) | E74: =E65-SUM(E67:E69) | F74: =F65-SUM(F67:F69) | G74: =G65-SUM(G67:G69) | H74: =H65-SUM(H67:H69) | I74: =I65-SUM(I67:I69) | ... K74: =K65-SUM(K67:K69)
B75: 0 | C75: 0 | D75: 0 | E75: 0 | F75: 0 | G75: 0 | H75: 0 | I75: 0 | J75: 0 | K75: 0
A80: CASH FLOW:
A81: Report Date | B81: 42825 | C81: 43190 | D81: 43555 | E81: 43921 | F81: 44286 | G81: 44651 | H81: 45016 | I81: 45382 | J81: 45747 | K81: 46112
A82: Cash from Operating Activity | B82: 10824 | C82: 8023 | D82: 25336 | E82: 20169 | F82: 44327 | G82: 44381 | H82: 21683 | I82: 20301 | J82: 23138 | K82: 35064
A83: Cash from Investing Activity | B83: -9490 | C83: -11730 | D83: -29176 | E83: -14012 | F83: -9437 | G83: -10905 | H83: -18179 | I83: -14253 | J83: -13611 | K83: -14397
A84: Cash from Financing Activity | B84: -2579 | C84: 6640 | D84: -673 | E84: -1695 | F84: -37090 | G84: -23401 | H84: -6981 | I84: -11097 | J84: -7002 | K84: -21387
A85: Net Cash Flow | B85: -1245 | C85: 2933 | D85: -4513 | E85: 4462 | F85: -2200 | G85: 10075 | H85: -3477 | I85: -5049 | J85: 2524 | K85: -720
A90: PRICE: | B90: 177 | C90: 177 | D90: 177 | E90: 177 | F90: 177 | G90: 177 | H90: 177 | I90: 177 | J90: 177 | K90: 177
A92: DERIVED:
A93: Adjusted Equity Shares in Cr | B93: 1247 | C93: 1247 | D93: 1247 | E93: 1247 | F93: 1247 | G93: 1247 | H93: 1247 | I93: 1247 | J93: 1247 | K93: 1247

Sheet Cash Flow Statement
B2: Cash Flow Statement - TATA STEEL LTD
B4: Particulars | C4: Mar 2015 | D4: Mar 2016 | E4: Mar 2017 | F4: Mar 2018 | G4: Mar 2019 | H4: Mar 2020 | I4: Mar 2021 | J4: Mar 2022 | K4: Mar 2023 | L4: Mar 2024 | M4: Mar 2025 | N4: Mar 2026
B6: Cash from Operating Activity - | C6: 11880 | D6: 11455 | E6: 10824 | F6: 8023 | G6: 25336 | H6: 20169 | I6: 44327 | J6: 44381 | K6: 21683 | L6: 20301 | M6: 23138 | N6: 35064
B7: Profit from operations | C7: 13955 | D7: 6824 | E7: 17581 | F7: 20187 | G7: 27840 | H7: 18078 | I7: 28540 | J7: 65900 | K7: 30908 | L7: 22237 | M7: 23929 | N7: 34219
B8: Receivables | C8: 1442 | D8: 0 | E8: 0 | F8: 0 | G8: 0 | H8: 0 | I8: 0 | J8: 0 | K8: 0 | L8: 0 | M8: 0 | N8: 0
B9: Inventory | C9: -485 | D9: 5618 | E9: -8243 | F9: -1595 | G9: -1069 | H9: 1562 | I9: 46 | J9: -16917 | K9: -4031 | L9: 5566 | M9: 4776 | N9: 1290
B10: Payables | C10: -605 | D10: 0 | E10: 0 | F10: 0 | G10: 0 | H10: 0 | I10: 0 | J10: 0 | K10: 0 | L10: 0 | M10: 0 | N10: 0
B11: Working capital changes | C11: 351 | D11: 6166 | E11: -4914 | F11: -9276 | G11: 2591 | H11: 4196 | I11: 16491 | J11: -9618 | K11: -3706 | L11: 3384 | M11: 2207 | N11: 5442
B12: Direct taxes | C12: -2427 | D12: -1534 | E12: -1843 | F12: -2888 | G12: -5094 | H12: -2106 | I12: -704 | J12: -11902 | K12: -5519 | L12: -5320 | M12: -2998 | N12: -4597
B13: Cash from Investing Activity - | C13: -9021 | D13: -8794 | E13: -9490 | F13: -11730 | G13: -29176 | H13: -14012 | I13: -9437 | J13: -10905 | K13: -18179 | L13: -14253 | M13: -13611 | N13: -14397
B14: Fixed assets purchased | C14: -13492 | D14: -10163 | E14: -7716 | F14: -7478 | G14: -9091 | H14: -10398 | I14: -6979 | J14: -10522 | K14: -14142 | L14: -18207 | M14: -15671 | N14: -14559
B15: Fixed assets sold | C15: 1444 | D15: 231 | E15: 289 | F15: 179 | G15: 467 | H15: 386 | I15: 445 | J15: 569 | K15: 328 | L15: 475 | M15: 1264 | N15: 1401
B16: Investments purchased | C16: 1531 | D16: -3796 | E16: -861 | F16: -8641 | G16: -490 | H16: -828 | I16: -3631 | J16: -1153 | K16: -326 | L16: -4 | M16: -393 | N16: -553
B17: Investments sold | C17: 262 | D17: 4275 | E17: 91 | F17: 3899 | G17: 13556 | H17: 121 | I17: 0 | J17: 63 | K17: 5191 | L17: 3171 | M17: 554 | N17: 20
... B32: Net Cash Flow | C32: 241 | D32: -2068 | E32: -1245 | F32: 2933 | G32: -4513 | H32: 4462 | I32: -2200 | J32: 10075 | K32: -3477 | L32: -5049 | M32: 2524 | N32: -720

Sheet Historical FS
B2: ="Historical Financial Statement - "&'Data Sheet'!$B$1
B3: Particulars | C3: ='Data Sheet'!B56 | D3: ='Data Sheet'!C56 | E3: ='Data Sheet'!D56 | F3: ='Data Sheet'!E56 | G3: ='Data Sheet'!F56 | H3: ='Data Sheet'!G56 | I3: ='Data Sheet'!H56 | J3: ='Data Sheet'!I56 | ... L3: ='Data Sheet'!K56 | M3: LTM
A5: # | B5: Income Statement
B7: Sales | C7: ='Data Sheet'!B17 | D7: ='Data Sheet'!C17 | E7: ='Data Sheet'!D17 | F7: ='Data Sheet'!E17 | G7: ='Data Sheet'!F17 | H7: ='Data Sheet'!G17 | I7: ='Data Sheet'!H17 | J7: ='Data Sheet'!I17 | ... L7: ='Data Sheet'!K17
B8: Sales Growth | C8: - | D8: =D7/C7-1 | E8: =E7/D7-1 | F8: =F7/E7-1 | G8: =G7/F7-1 | H8: =H7/G7-1 | I8: =I7/H7-1 | J8: =J7/I7-1 | K8: =K7/J7-1 | L8: =L7/K7-1
B10: Cost of Goods Sold | C10: =SUM('Data Sheet'!B18,'Data Sheet'!B20:B22)-'Data Sheet'!B19 | D10: =SUM('Data Sheet'!C18,'Data Sheet'!C20:C22)-'Data Sheet'!C19 | E10: =SUM('Data Sheet'!D18,'Data Sheet'!D20:D22)-'Data Sheet'!D19 | F10: =SUM('Data Sheet'!E18,'Data Sheet'!E20:E22)-'Data Sheet'!E19 | G10: =SUM('Data Sheet'!F18,'Data Sheet'!F20:F22)-'Data Sheet'!F19 | H10: =SUM('Data Sheet'!G18,'Data Sheet'!G20:G22)-'Data Sheet'!G19 | I10: =SUM('Data Sheet'!H18,'Data Sheet'!H20:H22)-'Data Sheet'!H19 | J10: =SUM('Data Sheet'!I18,'Data Sheet'!I20:I22)-'Data Sheet'!I19 | ... L10: =SUM('Data Sheet'!K18,'Data Sheet'!K20:K22)-'Data Sheet'!K19
B11: COGS % Sales | C11: =C10/C7 | D11: =D10/D7 | E11: =E10/E7 | F11: =F10/F7 | G11: =G10/G7 | H11: =H10/H7 | I11: =I10/I7 | J11: =J10/J7 | ... L11: =L10/L7
B13: Gross Profit | C13: =C7-C10 | D13: =D7-D10 | E13: =E7-E10 | F13: =F7-F10 | G13: =G7-G10 | H13: =H7-H10 | I13: =I7-I10 | J13: =J7-J10 | ... L13: =L7-L10
B14: Gross Profit % Sales | C14: =C13/C7 | D14: =D13/D7 | E14: =E13/E7 | F14: =F13/F7 | G14: =G13/G7 | H14: =H13/H7 | I14: =I13/I7 | J14: =J13/J7 | ... L14: =L13/L7
B16: Selling % General Expenses | C16: ='Data Sheet'!B23 | D16: ='Data Sheet'!C23 | E16: ='Data Sheet'!D23 | F16: ='Data Sheet'!E23 | G16: ='Data Sheet'!F23 | H16: ='Data Sheet'!G23 | I16: ='Data Sheet'!H23 | J16: ='Data Sheet'!I23 | ... O16: ='Data Sheet'!N23
B17: S&G % Sales | C17: =C16/C7 | D17: =D16/D7 | E17: =E16/E7 | F17: =F16/F7 | G17: =G16/G7 | H17: =H16/H7 | I17: =I16/I7 | J17: =J16/J7 | ... L17: =L16/L7
B19: EBITDA | C19: =C13-C16 | D19: =D13-D16 | E19: =E13-E16 | F19: =F13-F16 | G19: =G13-G16 | H19: =H13-H16 | I19: =I13-I16 | J19: =J13-J16 | ... L19: =L13-L16
B20: EBITDA % Sales | C20: =C19/C7 | D20: =D19/D7 | E20: =E19/E7 | F20: =F19/F7 | G20: =G19/G7 | H20: =H19/H7 | I20: =I19/I7 | J20: =J19/J7 | ... L20: =L19/L7
B22: Depreciation | C22: ='Data Sheet'!B26 | D22: ='Data Sheet'!C26 | E22: ='Data Sheet'!D26 | F22: ='Data Sheet'!E26 | G22: ='Data Sheet'!F26 | H22: ='Data Sheet'!G26 | I22: ='Data Sheet'!H26 | J22: ='Data Sheet'!I26 | ... L22: ='Data Sheet'!K26
B23: Depreciation % Sales | C23: =C22/C7 | D23: =D22/D7 | E23: =E22/E7 | F23: =F22/F7 | G23: =G22/G7 | H23: =H22/H7 | I23: =I22/I7 | J23: =J22/J7 | ... L23: =L22/L7
B25: EBIT | C25: =C19-C22 | D25: =D19-D22 | E25: =E19-E22 | F25: =F19-F22 | G25: =G19-G22 | H25: =H19-H22 | I25: =I19-I22 | J25: =J19-J22 | ... L25: =L19-L22
B26: EBIT % Sales | C26: =C25/C7 | D26: =D25/D7 | E26: =E25/E7 | F26: =F25/F7 | G26: =G25/G7 | H26: =H25/H7 | I26: =I25/I7 | J26: =J25/J7 | ... L26: =L25/L7
B28: Interest | C28: ='Data Sheet'!B27 | D28: ='Data Sheet'!C27 | E28: ='Data Sheet'!D27 | F28: ='Data Sheet'!E27 | G28: ='Data Sheet'!F27 | H28: ='Data Sheet'!G27 | I28: ='Data Sheet'!H27 | J28: ='Data Sheet'!I27 | ... L28: ='Data Sheet'!K27
B29: Interest % Sales | C29: =C28/C7 | D29: =D28/D7 | E29: =E28/E7 | F29: =F28/F7 | G29: =G28/G7 | H29: =H28/H7 | I29: =I28/I7 | J29: =J28/J7 | ... L29: =L28/L7
B31: Earning Before Tax | C31: =C25-C28 | D31: =D25-D28 | E31: =E25-E28 | F31: =F25-F28 | G31: =G25-G28 | H31: =H25-H28 | I31: =I25-I28 | J31: =J25-J28 | ... L31: =L25-L28
B32: EBT % Sales | C32: =C31/C7 | D32: =D31/D7 | E32: =E31/E7 | F32: =F31/F7 | G32: =G31/G7 | H32: =H31/H7 | I32: =I31/I7 | J32: =J31/J7 | ... L32: =L31/L7
B34: Tax Rate | C34: ='Data Sheet'!B29 | D34: ='Data Sheet'!C29 | E34: ='Data Sheet'!D29 | F34: ='Data Sheet'!E29 | G34: ='Data Sheet'!F29 | H34: ='Data Sheet'!G29 | I34: ='Data Sheet'!H29 | J34: ='Data Sheet'!I29 | ... L34: ='Data Sheet'!K29
B35: Effective Tax Rate | C35: =C34/C31 | D35: =D34/D31 | E35: =E34/E31 | F35: =F34/F31 | G35: =G34/G31 | H35: =H34/H31 | I35: =I34/I31 | J35: =J34/J31 | ... L35: =L34/L31
B37: Net Profit | C37: =C31-C34 | D37: =D31-D34 | E37: =E31-E34 | F37: =F31-F34 | G37: =G31-G34 | H37: =H31-H34 | I37: =I31-I34 | J37: =J31-J34 | ... L37: =L31-L34
B38: Net Profit % Sales | C38: =C37/C7 | D38: =D37/D7 | E38: =E37/E7 | F38: =F37/F7 | G38: =G37/G7 | H38: =H37/H7 | I38: =I37/I7 | J38: =J37/J7 | ... L38: =L37/L7
B40: No. of Equity Shares | C40: ='Data Sheet'!B93 | D40: ='Data Sheet'!C93 | E40: ='Data Sheet'!D93 | F40: ='Data Sheet'!E93 | G40: ='Data Sheet'!F93 | H40: ='Data Sheet'!G93 | I40: ='Data Sheet'!H93 | J40: ='Data Sheet'!I93 | ... L40: ='Data Sheet'!K93
B42: Earning per Share | C42: =C37/C40 | D42: =D37/D40 | E42: =E37/E40 | F42: =F37/F40 | G42: =G37/G40 | H42: =H37/H40 | I42: =I37/I40 | J42: =J37/J40 | ... L42: =L37/L40
B43: EPS Growth | C43: - | D43: =D42/C42-1 | E43: =E42/D42-1 | F43: =F42/E42-1 | G43: =G42/F42-1 | H43: =H42/G42-1 | I43: =I42/H42-1 | J43: =J42/I42-1 | K43: =K42/J42-1 | L43: =L42/K42-1
B45: Dividend per Share | C45: ='Data Sheet'!B31/'Historical FS'!C40 | D45: ='Data Sheet'!C31/'Historical FS'!D40 | E45: ='Data Sheet'!D31/'Historical FS'!E40 | F45: ='Data Sheet'!E31/'Historical FS'!F40 | G45: ='Data Sheet'!F31/'Historical FS'!G40 | H45: ='Data Sheet'!G31/'Historical FS'!H40 | I45: ='Data Sheet'!H31/'Historical FS'!I40 | J45: ='Data Sheet'!I31/'Historical FS'!J40 | ... L45: ='Data Sheet'!K31/'Historical FS'!L40
B46: Dividend Payout Ratio | C46: =C45/C42 | D46: =D45/D42 | E46: =E45/E42 | F46: =F45/F42 | G46: =G45/G42 | H46: =H45/H42 | I46: =I45/I42 | J46: =J45/J42 | ... L46: =L45/L42
B48: Retained Earnings | C48: =(1-C46) | D48: =(1-D46) | E48: =(1-E46) | F48: =(1-F46) | G48: =(1-G46) | H48: =(1-H46) | I48: =(1-I46) | J48: =(1-J46) | ... L48: =(1-L46)
B50: Balance Sheet
B51: ='Data Sheet'!A57 | C51: ='Data Sheet'!B57 | D51: ='Data Sheet'!C57 | E51: ='Data Sheet'!D57 | F51: ='Data Sheet'!E57 | G51: ='Data Sheet'!F57 | H51: ='Data Sheet'!G57 | I51: ='Data Sheet'!H57 | ... L51: ='Data Sheet'!K57
B52: ='Data Sheet'!A58 | C52: ='Data Sheet'!B58 | D52: ='Data Sheet'!C58 | E52: ='Data Sheet'!D58 | F52: ='Data Sheet'!E58 | G52: ='Data Sheet'!F58 | H52: ='Data Sheet'!G58 | I52: ='Data Sheet'!H58 | ... L52: ='Data Sheet'!K58
B53: ='Data Sheet'!A59 | C53: ='Data Sheet'!B59 | D53: ='Data Sheet'!C59 | E53: ='Data Sheet'!D59 | F53: ='Data Sheet'!E59 | G53: ='Data Sheet'!F59 | H53: ='Data Sheet'!G59 | I53: ='Data Sheet'!H59 | ... L53: ='Data Sheet'!K59
B54: ='Data Sheet'!A60 | C54: ='Data Sheet'!B60 | D54: ='Data Sheet'!C60 | E54: ='Data Sheet'!D60 | F54: ='Data Sheet'!E60 | G54: ='Data Sheet'!F60 | H54: ='Data Sheet'!G60 | I54: ='Data Sheet'!H60 | ... L54: ='Data Sheet'!K60
B55: Total Liabilities | C55: =SUM(C51:C54) | D55: =SUM(D51:D54) | E55: =SUM(E51:E54) | F55: =SUM(F51:F54) | G55: =SUM(G51:G54) | H55: =SUM(H51:H54) | I55: =SUM(I51:I54) | J55: =SUM(J51:J54) | ... L55: =SUM(L51:L54)
B57: Fixed Asset Net Block | C57: ='Data Sheet'!B62 | D57: ='Data Sheet'!C62 | E57: ='Data Sheet'!D62 | F57: ='Data Sheet'!E62 | G57: ='Data Sheet'!F62 | H57: ='Data Sheet'!G62 | I57: ='Data Sheet'!H62 | J57: ='Data Sheet'!I62 | ... L57: ='Data Sheet'!K62
B58: ='Data Sheet'!A63 | C58: ='Data Sheet'!B63 | D58: ='Data Sheet'!C63 | E58: ='Data Sheet'!D63 | F58: ='Data Sheet'!E63 | G58: ='Data Sheet'!F63 | H58: ='Data Sheet'!G63 | I58: ='Data Sheet'!H63 | ... L58: ='Data Sheet'!K63
B59: ='Data Sheet'!A64 | C59: ='Data Sheet'!B64 | D59: ='Data Sheet'!C64 | E59: ='Data Sheet'!D64 | F59: ='Data Sheet'!E64 | G59: ='Data Sheet'!F64 | H59: ='Data Sheet'!G64 | I59: ='Data Sheet'!H64 | ... L59: ='Data Sheet'!K64
B60: ='Data Sheet'!A65 | C60: ='Data Sheet'!B74 | D60: ='Data Sheet'!C74 | E60: ='Data Sheet'!D74 | F60: ='Data Sheet'!E74 | G60: ='Data Sheet'!F74 | H60: ='Data Sheet'!G74 | I60: ='Data Sheet'!H74 | J60: ='Data Sheet'!I74 | ... O60: ='Data Sheet'!N74
B61: Total Non Current Assets | C61: =SUM(C57:C60) | D61: =SUM(D57:D60) | E61: =SUM(E57:E60) | F61: =SUM(F57:F60) | G61: =SUM(G57:G60) | H61: =SUM(H57:H60) | I61: =SUM(I57:I60) | J61: =SUM(J57:J60) | ... L61: =SUM(L57:L60)
B63: ='Data Sheet'!A67 | C63: ='Data Sheet'!B67 | D63: ='Data Sheet'!C67 | E63: ='Data Sheet'!D67 | F63: ='Data Sheet'!E67 | G63: ='Data Sheet'!F67 | H63: ='Data Sheet'!G67 | I63: ='Data Sheet'!H67 | ... L63: ='Data Sheet'!K67
B64: ='Data Sheet'!A68 | C64: ='Data Sheet'!B68 | D64: ='Data Sheet'!C68 | E64: ='Data Sheet'!D68 | F64: ='Data Sheet'!E68 | G64: ='Data Sheet'!F68 | H64: ='Data Sheet'!G68 | I64: ='Data Sheet'!H68 | ... L64: ='Data Sheet'!K68
B65: ='Data Sheet'!A69 | C65: ='Data Sheet'!B69 | D65: ='Data Sheet'!C69 | E65: ='Data Sheet'!D69 | F65: ='Data Sheet'!E69 | G65: ='Data Sheet'!F69 | H65: ='Data Sheet'!G69 | I65: ='Data Sheet'!H69 | ... L65: ='Data Sheet'!K69
B66: Total Current Assets | C66: =SUM(C63:C65) | D66: =SUM(D63:D65) | E66: =SUM(E63:E65) | F66: =SUM(F63:F65) | G66: =SUM(G63:G65) | H66: =SUM(H63:H65) | I66: =SUM(I63:I65) | J66: =SUM(J63:J65) | ... L66: =SUM(L63:L65)
B68: Total Assets | C68: =C61+C66 | D68: =D61+D66 | E68: =E61+E66 | F68: =F61+F66 | G68: =G61+G66 | H68: =H61+H66 | I68: =I61+I66 | J68: =J61+J66 | ... L68: =L61+L66
B70: Check | C70: =C68=C55 | D70: =D68=D55 | E70: =E68=E55 | F70: =F68=F55 | G70: =G68=G55 | H70: =H68=H55 | I70: =I68=I55 | J70: =J68=J55 | ... L70: =L68=L55
B72: Cash Flow Statement
B73: Operating Activity
B74: ='Cash Flow Statement'!B7 | C74: ='Cash Flow Statement'!E7 | D74: ='Cash Flow Statement'!F7 | E74: ='Cash Flow Statement'!G7 | F74: ='Cash Flow Statement'!H7 | G74: ='Cash Flow Statement'!I7 | H74: ='Cash Flow Statement'!J7 | I74: ='Cash Flow Statement'!K7 | J74: ='Cash Flow Statement'!L7 | ... L74: ='Cash Flow Statement'!N7
B75: ='Cash Flow Statement'!B8 | C75: ='Cash Flow Statement'!E8 | D75: ='Cash Flow Statement'!F8 | E75: ='Cash Flow Statement'!G8 | F75: ='Cash Flow Statement'!H8 | G75: ='Cash Flow Statement'!I8 | H75: ='Cash Flow Statement'!J8 | I75: ='Cash Flow Statement'!K8 | J75: ='Cash Flow Statement'!L8 | ... L75: ='Cash Flow Statement'!N8
B76: ='Cash Flow Statement'!B9 | C76: ='Cash Flow Statement'!E9 | D76: ='Cash Flow Statement'!F9 | E76: ='Cash Flow Statement'!G9 | F76: ='Cash Flow Statement'!H9 | G76: ='Cash Flow Statement'!I9 | H76: ='Cash Flow Statement'!J9 | I76: ='Cash Flow Statement'!K9 | J76: ='Cash Flow Statement'!L9 | ... L76: ='Cash Flow Statement'!N9
B77: ='Cash Flow Statement'!B10 | C77: ='Cash Flow Statement'!E10 | D77: ='Cash Flow Statement'!F10 | E77: ='Cash Flow Statement'!G10 | F77: ='Cash Flow Statement'!H10 | G77: ='Cash Flow Statement'!I10 | H77: ='Cash Flow Statement'!J10 | I77: ='Cash Flow Statement'!K10 | J77: ='Cash Flow Statement'!L10 | ... L77: ='Cash Flow Statement'!N10
B78: ='Cash Flow Statement'!B11 | C78: ='Cash Flow Statement'!E11 | D78: ='Cash Flow Statement'!F11 | E78: ='Cash Flow Statement'!G11 | F78: ='Cash Flow Statement'!H11 | G78: ='Cash Flow Statement'!I11 | H78: ='Cash Flow Statement'!J11 | I78: ='Cash Flow Statement'!K11 | J78: ='Cash Flow Statement'!L11 | ... L78: ='Cash Flow Statement'!N11
B79: ='Cash Flow Statement'!B12 | C79: ='Cash Flow Statement'!E12 | D79: ='Cash Flow Statement'!F12 | E79: ='Cash Flow Statement'!G12 | F79: ='Cash Flow Statement'!H12 | G79: ='Cash Flow Statement'!I12 | H79: ='Cash Flow Statement'!J12 | I79: ='Cash Flow Statement'!K12 | J79: ='Cash Flow Statement'!L12 | ... L79: ='Cash Flow Statement'!N12
B80: Cash From Operating Activities | C80: =SUM(C74:C79) | D80: =SUM(D74:D79) | E80: =SUM(E74:E79) | F80: =SUM(F74:F79) | G80: =SUM(G74:G79) | H80: =SUM(H74:H79) | I80: =SUM(I74:I79) | J80: =SUM(J74:J79) | ... L80: =SUM(L74:L79)
B82: Investing Activities
B83: ='Cash Flow Statement'!B14 | C83: ='Cash Flow Statement'!E14 | D83: ='Cash Flow Statement'!F14 | E83: ='Cash Flow Statement'!G14 | F83: ='Cash Flow Statement'!H14 | G83: ='Cash Flow Statement'!I14 | H83: ='Cash Flow Statement'!J14 | I83: ='Cash Flow Statement'!K14 | J83: ='Cash Flow Statement'!L14 | ... L83: ='Cash Flow Statement'!N14
B84: ='Cash Flow Statement'!B15 | C84: ='Cash Flow Statement'!E15 | D84: ='Cash Flow Statement'!F15 | E84: ='Cash Flow Statement'!G15 | F84: ='Cash Flow Statement'!H15 | G84: ='Cash Flow Statement'!I15 | H84: ='Cash Flow Statement'!J15 | I84: ='Cash Flow Statement'!K15 | J84: ='Cash Flow Statement'!L15 | ... L84: ='Cash Flow Statement'!N15
B85: ='Cash Flow Statement'!B16 | C85: ='Cash Flow Statement'!E16 | D85: ='Cash Flow Statement'!F16 | E85: ='Cash Flow Statement'!G16 | F85: ='Cash Flow Statement'!H16 | G85: ='Cash Flow Statement'!I16 | H85: ='Cash Flow Statement'!J16 | I85: ='Cash Flow Statement'!K16 | J85: ='Cash Flow Statement'!L16 | ... L85: ='Cash Flow Statement'!N16
B86: ='Cash Flow Statement'!B17 | C86: ='Cash Flow Statement'!E17 | D86: ='Cash Flow Statement'!F17 | E86: ='Cash Flow Statement'!G17 | F86: ='Cash Flow Statement'!H17 | G86: ='Cash Flow Statement'!I17 | H86: ='Cash Flow Statement'!J17 | I86: ='Cash Flow Statement'!K17 | J86: ='Cash Flow Statement'!L17 | ... L86: ='Cash Flow Statement'!N17
B87: ='Cash Flow Statement'!B18 | C87: ='Cash Flow Statement'!E18 | D87: ='Cash Flow Statement'!F18 | E87: ='Cash Flow Statement'!G18 | F87: ='Cash Flow Statement'!H18 | G87: ='Cash Flow Statement'!I18 | H87: ='Cash Flow Statement'!J18 | I87: ='Cash Flow Statement'!K18 | J87: ='Cash Flow Statement'!L18 | ... L87: ='Cash Flow Statement'!N18
B88: ='Cash Flow Statement'!B19 | C88: ='Cash Flow Statement'!E19 | D88: ='Cash Flow Statement'!F19 | E88: ='Cash Flow Statement'!G19 | F88: ='Cash Flow Statement'!H19 | G88: ='Cash Flow Statement'!I19 | H88: ='Cash Flow Statement'!J19 | I88: ='Cash Flow Statement'!K19 | J88: ='Cash Flow Statement'!L19 | ... L88: ='Cash Flow Statement'!N19
B89: ='Cash Flow Statement'!B20 | C89: ='Cash Flow Statement'!E20 | D89: ='Cash Flow Statement'!F20 | E89: ='Cash Flow Statement'!G20 | F89: ='Cash Flow Statement'!H20 | G89: ='Cash Flow Statement'!I20 | H89: ='Cash Flow Statement'!J20 | I89: ='Cash Flow Statement'!K20 | J89: ='Cash Flow Statement'!L20 | ... L89: ='Cash Flow Statement'!N20
B90: ='Cash Flow Statement'!B21 | C90: ='Cash Flow Statement'!E21 | D90: ='Cash Flow Statement'!F21 | E90: ='Cash Flow Statement'!G21 | F90: ='Cash Flow Statement'!H21 | G90: ='Cash Flow Statement'!I21 | H90: ='Cash Flow Statement'!J21 | I90: ='Cash Flow Statement'!K21 | J90: ='Cash Flow Statement'!L21 | ... L90: ='Cash Flow Statement'!N21
B91: ='Cash Flow Statement'!B22 | C91: ='Cash Flow Statement'!E22 | D91: ='Cash Flow Statement'!F22 | E91: ='Cash Flow Statement'!G22 | F91: ='Cash Flow Statement'!H22 | G91: ='Cash Flow Statement'!I22 | H91: ='Cash Flow Statement'!J22 | I91: ='Cash Flow Statement'!K22 | J91: ='Cash Flow Statement'!L22 | ... L91: ='Cash Flow Statement'!N22
B92: ='Cash Flow Statement'!B23 | C92: ='Cash Flow Statement'!E23 | D92: ='Cash Flow Statement'!F23 | E92: ='Cash Flow Statement'!G23 | F92: ='Cash Flow Statement'!H23 | G92: ='Cash Flow Statement'!I23 | H92: ='Cash Flow Statement'!J23 | I92: ='Cash Flow Statement'!K23 | J92: ='Cash Flow Statement'!L23 | ... L92: ='Cash Flow Statement'!N23
B93: Cash From Investing Activities | C93: =SUM(C83:C92) | D93: =SUM(D83:D92) | E93: =SUM(E83:E92) | F93: =SUM(F83:F92) | G93: =SUM(G83:G92) | H93: =SUM(H83:H92) | I93: =SUM(I83:I92) | J93: =SUM(J83:J92) | ... L93: =SUM(L83:L92)
B95: Financing Activities
B96: ='Cash Flow Statement'!B25 | C96: ='Cash Flow Statement'!E25 | D96: ='Cash Flow Statement'!F25 | E96: ='Cash Flow Statement'!G25 | F96: ='Cash Flow Statement'!H25 | G96: ='Cash Flow Statement'!I25 | H96: ='Cash Flow Statement'!J25 | I96: ='Cash Flow Statement'!K25 | J96: ='Cash Flow Statement'!L25 | ... L96: ='Cash Flow Statement'!N25
B97: ='Cash Flow Statement'!B26 | C97: ='Cash Flow Statement'!E26 | D97: ='Cash Flow Statement'!F26 | E97: ='Cash Flow Statement'!G26 | F97: ='Cash Flow Statement'!H26 | G97: ='Cash Flow Statement'!I26 | H97: ='Cash Flow Statement'!J26 | I97: ='Cash Flow Statement'!K26 | J97: ='Cash Flow Statement'!L26 | ... L97: ='Cash Flow Statement'!N26
B98: ='Cash Flow Statement'!B27 | C98: ='Cash Flow Statement'!E27 | D98: ='Cash Flow Statement'!F27 | E98: ='Cash Flow Statement'!G27 | F98: ='Cash Flow Statement'!H27 | G98: ='Cash Flow Statement'!I27 | H98: ='Cash Flow Statement'!J27 | I98: ='Cash Flow Statement'!K27 | J98: ='Cash Flow Statement'!L27 | ... L98: ='Cash Flow Statement'!N27
B99: ='Cash Flow Statement'!B28 | C99: ='Cash Flow Statement'!E28 | D99: ='Cash Flow Statement'!F28 | E99: ='Cash Flow Statement'!G28 | F99: ='Cash Flow Statement'!H28 | G99: ='Cash Flow Statement'!I28 | H99: ='Cash Flow Statement'!J28 | I99: ='Cash Flow Statement'!K28 | J99: ='Cash Flow Statement'!L28 | ... L99: ='Cash Flow Statement'!N28
B100: ='Cash Flow Statement'!B29 | C100: ='Cash Flow Statement'!E29 | D100: ='Cash Flow Statement'!F29 | E100: ='Cash Flow Statement'!G29 | F100: ='Cash Flow Statement'!H29 | G100: ='Cash Flow Statement'!I29 | H100: ='Cash Flow Statement'!J29 | I100: ='Cash Flow Statement'!K29 | J100: ='Cash Flow Statement'!L29 | ... L100: ='Cash Flow Statement'!N29
B101: ='Cash Flow Statement'!B30 | C101: ='Cash Flow Statement'!E30 | D101: ='Cash Flow Statement'!F30 | E101: ='Cash Flow Statement'!G30 | F101: ='Cash Flow Statement'!H30 | G101: ='Cash Flow Statement'!I30 | H101: ='Cash Flow Statement'!J30 | I101: ='Cash Flow Statement'!K30 | J101: ='Cash Flow Statement'!L30 | ... L101: ='Cash Flow Statement'!N30
B102: ='Cash Flow Statement'!B31 | C102: ='Cash Flow Statement'!E31 | D102: ='Cash Flow Statement'!F31 | E102: ='Cash Flow Statement'!G31 | F102: ='Cash Flow Statement'!H31 | G102: ='Cash Flow Statement'!I31 | H102: ='Cash Flow Statement'!J31 | I102: ='Cash Flow Statement'!K31 | J102: ='Cash Flow Statement'!L31 | ... L102: ='Cash Flow Statement'!N31
B103: Cash From Financing Activities | C103: =SUM(C96:C102) | D103: =SUM(D96:D102) | E103: =SUM(E96:E102) | F103: =SUM(F96:F102) | G103: =SUM(G96:G102) | H103: =SUM(H96:H102) | I103: =SUM(I96:I102) | J103: =SUM(J96:J102) | ... L103: =SUM(L96:L102)
B105: Net Cash Flow | C105: =C80+C93+C103 | D105: =D80+D93+D103 | E105: =E80+E93+E103 | F105: =F80+F93+F103 | G105: =G80+G93+G103 | H105: =H80+H93+H103 | I105: =I80+I93+I103 | J105: =J80+J93+J103 | ... L105: =L80+L93+L103

Sheet Ratio Analysis
B2: ="Ratio Analysis - "&'Data Sheet'!$B$1
B3: Years | C3: ='Data Sheet'!B56 | D3: ='Data Sheet'!C56 | E3: ='Data Sheet'!D56 | F3: ='Data Sheet'!E56 | G3: ='Data Sheet'!F56 | H3: ='Data Sheet'!G56 | I3: ='Data Sheet'!H56 | J3: ='Data Sheet'!I56 | ... L3: ='Data Sheet'!K56 | M3: Trend | N3: Mean | O3: Median
B5: SalesGrowth | D5: =IFERROR('Historical FS'!D8,0) | E5: =IFERROR('Historical FS'!E8,0) | F5: =IFERROR('Historical FS'!F8,0) | G5: =IFERROR('Historical FS'!G8,0) | H5: =IFERROR('Historical FS'!H8,0) | I5: =IFERROR('Historical FS'!I8,0) | J5: =IFERROR('Historical FS'!J8,0) | K5: =IFERROR('Historical FS'!K8,0) | L5: =IFERROR('Historical FS'!L8,0) | N5: =IFERROR(AVERAGE(D5:L5),0) | O5: =IFERROR(MEDIAN(D5:L5),0)
B6: EBITDA Growth | D6: =IFERROR(('Historical FS'!D19/'Historical FS'!C19-1),0) | E6: =IFERROR(('Historical FS'!E19/'Historical FS'!D19-1),0) | F6: =IFERROR(('Historical FS'!F19/'Historical FS'!E19-1),0) | G6: =IFERROR(('Historical FS'!G19/'Historical FS'!F19-1),0) | H6: =IFERROR(('Historical FS'!H19/'Historical FS'!G19-1),0) | I6: =IFERROR(('Historical FS'!I19/'Historical FS'!H19-1),0) | J6: =IFERROR(('Historical FS'!J19/'Historical FS'!I19-1),0) | K6: =IFERROR(('Historical FS'!K19/'Historical FS'!J19-1),0) | L6: =IFERROR(('Historical FS'!L19/'Historical FS'!K19-1),0) | N6: =IFERROR(AVERAGE(D6:L6),0) | O6: =IFERROR(MEDIAN(D6:L6),0)
B7: EBIT Growth | D7: =IFERROR(('Historical FS'!D25/'Historical FS'!C25-1),0) | E7: =IFERROR(('Historical FS'!E25/'Historical FS'!D25-1),0) | F7: =IFERROR(('Historical FS'!F25/'Historical FS'!E25-1),0) | G7: =IFERROR(('Historical FS'!G25/'Historical FS'!F25-1),0) | H7: =IFERROR(('Historical FS'!H25/'Historical FS'!G25-1),0) | I7: =IFERROR(('Historical FS'!I25/'Historical FS'!H25-1),0) | J7: =IFERROR(('Historical FS'!J25/'Historical FS'!I25-1),0) | K7: =IFERROR(('Historical FS'!K25/'Historical FS'!J25-1),0) | L7: =IFERROR(('Historical FS'!L25/'Historical FS'!K25-1),0) | N7: =IFERROR(AVERAGE(D7:L7),0) | O7: =IFERROR(MEDIAN(D7:L7),0)
B8: Net Profit Growth | D8: =IFERROR(('Historical FS'!D37/'Historical FS'!C37-1),0) | E8: =IFERROR(('Historical FS'!E37/'Historical FS'!D37-1),0) | F8: =IFERROR(('Historical FS'!F37/'Historical FS'!E37-1),0) | G8: =IFERROR(('Historical FS'!G37/'Historical FS'!F37-1),0) | H8: =IFERROR(('Historical FS'!H37/'Historical FS'!G37-1),0) | I8: =IFERROR(('Historical FS'!I37/'Historical FS'!H37-1),0) | J8: =IFERROR(('Historical FS'!J37/'Historical FS'!I37-1),0) | K8: =IFERROR(('Historical FS'!K37/'Historical FS'!J37-1),0) | L8: =IFERROR(('Historical FS'!L37/'Historical FS'!K37-1),0) | N8: =IFERROR(AVERAGE(D8:L8),0) | O8: =IFERROR(MEDIAN(D8:L8),0)
B9: Dividend Growth | D9: =IFERROR(('Historical FS'!D45/'Historical FS'!C45-1),0) | E9: =IFERROR(('Historical FS'!E45/'Historical FS'!D45-1),0) | F9: =IFERROR(('Historical FS'!F45/'Historical FS'!E45-1),0) | G9: =IFERROR(('Historical FS'!G45/'Historical FS'!F45-1),0) | H9: =IFERROR(('Historical FS'!H45/'Historical FS'!G45-1),0) | I9: =IFERROR(('Historical FS'!I45/'Historical FS'!H45-1),0) | J9: =IFERROR(('Historical FS'!J45/'Historical FS'!I45-1),0) | K9: =IFERROR(('Historical FS'!K45/'Historical FS'!J45-1),0) | L9: =IFERROR(('Historical FS'!L45/'Historical FS'!K45-1),0) | N9: =IFERROR(AVERAGE(D9:L9),0) | O9: =IFERROR(MEDIAN(D9:L9),0)
B11: Gross Margin | C11: =IFERROR('Historical FS'!C14,0) | D11: =IFERROR('Historical FS'!D14,0) | E11: =IFERROR('Historical FS'!E14,0) | F11: =IFERROR('Historical FS'!F14,0) | G11: =IFERROR('Historical FS'!G14,0) | H11: =IFERROR('Historical FS'!H14,0) | I11: =IFERROR('Historical FS'!I14,0) | J11: =IFERROR('Historical FS'!J14,0) | ... L11: =IFERROR('Historical FS'!L14,0) | N11: =IFERROR(AVERAGE(C11:L11),0) | O11: =IFERROR(MEDIAN(C11:L11),0)
B12: EBITDA Margin | C12: =IFERROR('Historical FS'!C20,0) | D12: =IFERROR('Historical FS'!D20,0) | E12: =IFERROR('Historical FS'!E20,0) | F12: =IFERROR('Historical FS'!F20,0) | G12: =IFERROR('Historical FS'!G20,0) | H12: =IFERROR('Historical FS'!H20,0) | I12: =IFERROR('Historical FS'!I20,0) | J12: =IFERROR('Historical FS'!J20,0) | ... L12: =IFERROR('Historical FS'!L20,0) | N12: =IFERROR(AVERAGE(C12:L12),0) | O12: =IFERROR(MEDIAN(C12:L12),0)
B13: EBIT Margin | C13: =IFERROR('Historical FS'!C26,0) | D13: =IFERROR('Historical FS'!D26,0) | E13: =IFERROR('Historical FS'!E26,0) | F13: =IFERROR('Historical FS'!F26,0) | G13: =IFERROR('Historical FS'!G26,0) | H13: =IFERROR('Historical FS'!H26,0) | I13: =IFERROR('Historical FS'!I26,0) | J13: =IFERROR('Historical FS'!J26,0) | ... L13: =IFERROR('Historical FS'!L26,0) | N13: =IFERROR(AVERAGE(C13:L13),0) | O13: =IFERROR(MEDIAN(C13:L13),0)
B14: EBT Margin | C14: =IFERROR('Historical FS'!C32,0) | D14: =IFERROR('Historical FS'!D32,0) | E14: =IFERROR('Historical FS'!E32,0) | F14: =IFERROR('Historical FS'!F32,0) | G14: =IFERROR('Historical FS'!G32,0) | H14: =IFERROR('Historical FS'!H32,0) | I14: =IFERROR('Historical FS'!I32,0) | J14: =IFERROR('Historical FS'!J32,0) | ... L14: =IFERROR('Historical FS'!L32,0) | N14: =IFERROR(AVERAGE(C14:L14),0) | O14: =IFERROR(MEDIAN(C14:L14),0)
B15: Net Profit Margin | C15: =IFERROR('Historical FS'!C38,0) | D15: =IFERROR('Historical FS'!D38,0) | E15: =IFERROR('Historical FS'!E38,0) | F15: =IFERROR('Historical FS'!F38,0) | G15: =IFERROR('Historical FS'!G38,0) | H15: =IFERROR('Historical FS'!H38,0) | I15: =IFERROR('Historical FS'!I38,0) | J15: =IFERROR('Historical FS'!J38,0) | ... L15: =IFERROR('Historical FS'!L38,0) | N15: =IFERROR(AVERAGE(C15:L15),0) | O15: =IFERROR(MEDIAN(C15:L15),0)
B17: SalesExpenses%sales | C17: =IFERROR('Historical FS'!C17,0) | D17: =IFERROR('Historical FS'!D17,0) | E17: =IFERROR('Historical FS'!E17,0) | F17: =IFERROR('Historical FS'!F17,0) | G17: =IFERROR('Historical FS'!G17,0) | H17: =IFERROR('Historical FS'!H17,0) | I17: =IFERROR('Historical FS'!I17,0) | J17: =IFERROR('Historical FS'!J17,0) | ... L17: =IFERROR('Historical FS'!L17,0) | N17: =IFERROR(AVERAGE(C17:L17),0) | O17: =IFERROR(MEDIAN(C17:L17),0)
B18: Depreciation%Sales | C18: =IFERROR('Historical FS'!C23,0) | D18: =IFERROR('Historical FS'!D23,0) | E18: =IFERROR('Historical FS'!E23,0) | F18: =IFERROR('Historical FS'!F23,0) | G18: =IFERROR('Historical FS'!G23,0) | H18: =IFERROR('Historical FS'!H23,0) | I18: =IFERROR('Historical FS'!I23,0) | J18: =IFERROR('Historical FS'!J23,0) | ... L18: =IFERROR('Historical FS'!L23,0) | N18: =IFERROR(AVERAGE(C18:L18),0) | O18: =IFERROR(MEDIAN(C18:L18),0)
B19: OperatingIncome%sales | C19: =C13 | D19: =D13 | E19: =E13 | F19: =F13 | G19: =G13 | H19: =H13 | I19: =I13 | J19: =J13 | ... L19: =L13 | N19: =IFERROR(AVERAGE(C19:L19),0) | O19: =IFERROR(MEDIAN(C19:L19),0)
B21: Return on Capital Employed | C21: =IFERROR('Historical FS'!C25/SUM('Historical FS'!C51:'Historical FS'!C53),0) | D21: =IFERROR('Historical FS'!D25/SUM('Historical FS'!D51:'Historical FS'!D53),0) | E21: =IFERROR('Historical FS'!E25/SUM('Historical FS'!E51:'Historical FS'!E53),0) | F21: =IFERROR('Historical FS'!F25/SUM('Historical FS'!F51:'Historical FS'!F53),0) | G21: =IFERROR('Historical FS'!G25/SUM('Historical FS'!G51:'Historical FS'!G53),0) | H21: =IFERROR('Historical FS'!H25/SUM('Historical FS'!H51:'Historical FS'!H53),0) | I21: =IFERROR('Historical FS'!I25/SUM('Historical FS'!I51:'Historical FS'!I53),0) | J21: =IFERROR('Historical FS'!J25/SUM('Historical FS'!J51:'Historical FS'!J53),0) | ... L21: =IFERROR('Historical FS'!L25/SUM('Historical FS'!L51:'Historical FS'!L53),0) | N21: =IFERROR(AVERAGE(C21:L21),0) | O21: =IFERROR(MEDIAN(C21:L21),0)
B22: Retained Earnings% | C22: =IFERROR('Historical FS'!C48,0) | D22: =IFERROR('Historical FS'!D48,0) | E22: =IFERROR('Historical FS'!E48,0) | F22: =IFERROR('Historical FS'!F48,0) | G22: =IFERROR('Historical FS'!G48,0) | H22: =IFERROR('Historical FS'!H48,0) | I22: =IFERROR('Historical FS'!I48,0) | J22: =IFERROR('Historical FS'!J48,0) | ... L22: =IFERROR('Historical FS'!L48,0) | N22: =IFERROR(AVERAGE(C22:L22),0) | O22: =IFERROR(MEDIAN(C22:L22),0)
B23: Return on Equity% | C23: =IFERROR('Historical FS'!C37/SUM('Historical FS'!C51:'Historical FS'!C52),0) | D23: =IFERROR('Historical FS'!D37/SUM('Historical FS'!D51:'Historical FS'!D52),0) | E23: =IFERROR('Historical FS'!E37/SUM('Historical FS'!E51:'Historical FS'!E52),0) | F23: =IFERROR('Historical FS'!F37/SUM('Historical FS'!F51:'Historical FS'!F52),0) | G23: =IFERROR('Historical FS'!G37/SUM('Historical FS'!G51:'Historical FS'!G52),0) | H23: =IFERROR('Historical FS'!H37/SUM('Historical FS'!H51:'Historical FS'!H52),0) | I23: =IFERROR('Historical FS'!I37/SUM('Historical FS'!I51:'Historical FS'!I52),0) | J23: =IFERROR('Historical FS'!J37/SUM('Historical FS'!J51:'Historical FS'!J52),0) | ... L23: =IFERROR('Historical FS'!L37/SUM('Historical FS'!L51:'Historical FS'!L52),0) | N23: =IFERROR(AVERAGE(C23:L23),0) | O23: =IFERROR(MEDIAN(C23:L23),0)
B24: Self Sustained Growth Rate | C24: =IFERROR(C22*C23,0) | D24: =IFERROR(D22*D23,0) | E24: =IFERROR(E22*E23,0) | F24: =IFERROR(F22*F23,0) | G24: =IFERROR(G22*G23,0) | H24: =IFERROR(H22*H23,0) | I24: =IFERROR(I22*I23,0) | J24: =IFERROR(J22*J23,0) | ... L24: =IFERROR(L22*L23,0) | N24: =IFERROR(AVERAGE(C24:L24),0) | O24: =IFERROR(MEDIAN(C24:L24),0)
B25: Interest Coverage Ratio | C25: =IFERROR('Historical FS'!C25/'Historical FS'!C28,0) | D25: =IFERROR('Historical FS'!D25/'Historical FS'!D28,0) | E25: =IFERROR('Historical FS'!E25/'Historical FS'!E28,0) | F25: =IFERROR('Historical FS'!F25/'Historical FS'!F28,0) | G25: =IFERROR('Historical FS'!G25/'Historical FS'!G28,0) | H25: =IFERROR('Historical FS'!H25/'Historical FS'!H28,0) | I25: =IFERROR('Historical FS'!I25/'Historical FS'!I28,0) | J25: =IFERROR('Historical FS'!J25/'Historical FS'!J28,0) | ... L25: =IFERROR('Historical FS'!L25/'Historical FS'!L28,0) | N25: =IFERROR(AVERAGE(C25:L25),0) | O25: =IFERROR(MEDIAN(C25:L25),0)
B27: Debtor Turnover Ratio | C27: =IFERROR('Historical FS'!C7/'Historical FS'!C63,0) | D27: =IFERROR('Historical FS'!D7/'Historical FS'!D63,0) | E27: =IFERROR('Historical FS'!E7/'Historical FS'!E63,0) | F27: =IFERROR('Historical FS'!F7/'Historical FS'!F63,0) | G27: =IFERROR('Historical FS'!G7/'Historical FS'!G63,0) | H27: =IFERROR('Historical FS'!H7/'Historical FS'!H63,0) | I27: =IFERROR('Historical FS'!I7/'Historical FS'!I63,0) | J27: =IFERROR('Historical FS'!J7/'Historical FS'!J63,0) | ... L27: =IFERROR('Historical FS'!L7/'Historical FS'!L63,0) | N27: =IFERROR(AVERAGE(C27:L27),0) | O27: =IFERROR(MEDIAN(C27:L27),0)
B28: Creditor Turnover Ratio | C28: =IFERROR('Historical FS'!C7/'Historical FS'!C54,0) | D28: =IFERROR('Historical FS'!D7/'Historical FS'!D54,0) | E28: =IFERROR('Historical FS'!E7/'Historical FS'!E54,0) | F28: =IFERROR('Historical FS'!F7/'Historical FS'!F54,0) | G28: =IFERROR('Historical FS'!G7/'Historical FS'!G54,0) | H28: =IFERROR('Historical FS'!H7/'Historical FS'!H54,0) | I28: =IFERROR('Historical FS'!I7/'Historical FS'!I54,0) | J28: =IFERROR('Historical FS'!J7/'Historical FS'!J54,0) | ... L28: =IFERROR('Historical FS'!L7/'Historical FS'!L54,0) | N28: =IFERROR(AVERAGE(C28:L28),0) | O28: =IFERROR(MEDIAN(C28:L28),0)
B29: Inventory Turnover | C29: =IFERROR('Historical FS'!C7/'Historical FS'!C64,0) | D29: =IFERROR('Historical FS'!D7/'Historical FS'!D64,0) | E29: =IFERROR('Historical FS'!E7/'Historical FS'!E64,0) | F29: =IFERROR('Historical FS'!F7/'Historical FS'!F64,0) | G29: =IFERROR('Historical FS'!G7/'Historical FS'!G64,0) | H29: =IFERROR('Historical FS'!H7/'Historical FS'!H64,0) | I29: =IFERROR('Historical FS'!I7/'Historical FS'!I64,0) | J29: =IFERROR('Historical FS'!J7/'Historical FS'!J64,0) | ... L29: =IFERROR('Historical FS'!L7/'Historical FS'!L64,0) | N29: =IFERROR(AVERAGE(C29:L29),0) | O29: =IFERROR(MEDIAN(C29:L29),0)
B30: Fixed Assets Turnover | C30: =IFERROR('Historical FS'!C7/'Historical FS'!C57,0) | D30: =IFERROR('Historical FS'!D7/'Historical FS'!D57,0) | E30: =IFERROR('Historical FS'!E7/'Historical FS'!E57,0) | F30: =IFERROR('Historical FS'!F7/'Historical FS'!F57,0) | G30: =IFERROR('Historical FS'!G7/'Historical FS'!G57,0) | H30: =IFERROR('Historical FS'!H7/'Historical FS'!H57,0) | I30: =IFERROR('Historical FS'!I7/'Historical FS'!I57,0) | J30: =IFERROR('Historical FS'!J7/'Historical FS'!J57,0) | ... L30: =IFERROR('Historical FS'!L7/'Historical FS'!L57,0) | N30: =IFERROR(AVERAGE(C30:L30),0) | O30: =IFERROR(MEDIAN(C30:L30),0)
B31: Capital Turnover Ratio | C31: =IFERROR('Historical FS'!C7/SUM('Historical FS'!C51:'Historical FS'!C52),0) | D31: =IFERROR('Historical FS'!D7/SUM('Historical FS'!D51:'Historical FS'!D52),0) | E31: =IFERROR('Historical FS'!E7/SUM('Historical FS'!E51:'Historical FS'!E52),0) | F31: =IFERROR('Historical FS'!F7/SUM('Historical FS'!F51:'Historical FS'!F52),0) | G31: =IFERROR('Historical FS'!G7/SUM('Historical FS'!G51:'Historical FS'!G52),0) | H31: =IFERROR('Historical FS'!H7/SUM('Historical FS'!H51:'Historical FS'!H52),0) | I31: =IFERROR('Historical FS'!I7/SUM('Historical FS'!I51:'Historical FS'!I52),0) | J31: =IFERROR('Historical FS'!J7/SUM('Historical FS'!J51:'Historical FS'!J52),0) | ... L31: =IFERROR('Historical FS'!L7/SUM('Historical FS'!L51:'Historical FS'!L52),0) | N31: =IFERROR(AVERAGE(C31:L31),0) | O31: =IFERROR(MEDIAN(C31:L31),0)
B33: (in days)
B34: Debtor Days | C34: =IFERROR(365/C27,0) | D34: =IFERROR(365/D27,0) | E34: =IFERROR(365/E27,0) | F34: =IFERROR(365/F27,0) | G34: =IFERROR(365/G27,0) | H34: =IFERROR(365/H27,0) | I34: =IFERROR(365/I27,0) | J34: =IFERROR(365/J27,0) | ... L34: =IFERROR(365/L27,0) | N34: =IFERROR(AVERAGE(C34:L34),0) | O34: =IFERROR(MEDIAN(C34:L34),0)
B35: Payable Days | C35: =IFERROR(365/C28,0) | D35: =IFERROR(365/D28,0) | E35: =IFERROR(365/E28,0) | F35: =IFERROR(365/F28,0) | G35: =IFERROR(365/G28,0) | H35: =IFERROR(365/H28,0) | I35: =IFERROR(365/I28,0) | J35: =IFERROR(365/J28,0) | ... L35: =IFERROR(365/L28,0) | N35: =IFERROR(AVERAGE(C35:L35),0) | O35: =IFERROR(MEDIAN(C35:L35),0)
B36: Inventory Days | C36: =IFERROR(365/C29,0) | D36: =IFERROR(365/D29,0) | E36: =IFERROR(365/E29,0) | F36: =IFERROR(365/F29,0) | G36: =IFERROR(365/G29,0) | H36: =IFERROR(365/H29,0) | I36: =IFERROR(365/I29,0) | J36: =IFERROR(365/J29,0) | ... L36: =IFERROR(365/L29,0) | N36: =IFERROR(AVERAGE(C36:L36),0) | O36: =IFERROR(MEDIAN(C36:L36),0)
B37: Cash Conversion Cycle | C37: =SUM(C34,C36)-C35 | D37: =SUM(D34,D36)-D35 | E37: =SUM(E34,E36)-E35 | F37: =SUM(F34,F36)-F35 | G37: =SUM(G34,G36)-G35 | H37: =SUM(H34,H36)-H35 | I37: =SUM(I34,I36)-I35 | J37: =SUM(J34,J36)-J35 | ... L37: =SUM(L34,L36)-L35 | N37: =IFERROR(AVERAGE(C37:L37),0) | O37: =IFERROR(MEDIAN(C37:L37),0)
B39: CFO/Sales | C39: =IFERROR('Historical FS'!C80/'Historical FS'!C7,0) | D39: =IFERROR('Historical FS'!D80/'Historical FS'!D7,0) | E39: =IFERROR('Historical FS'!E80/'Historical FS'!E7,0) | F39: =IFERROR('Historical FS'!F80/'Historical FS'!F7,0) | G39: =IFERROR('Historical FS'!G80/'Historical FS'!G7,0) | H39: =IFERROR('Historical FS'!H80/'Historical FS'!H7,0) | I39: =IFERROR('Historical FS'!I80/'Historical FS'!I7,0) | J39: =IFERROR('Historical FS'!J80/'Historical FS'!J7,0) | ... L39: =IFERROR('Historical FS'!L80/'Historical FS'!L7,0) | N39: =IFERROR(AVERAGE(C39:L39),0) | O39: =IFERROR(MEDIAN(C39:L39),0)
B40: CFO/Total Assets | C40: =IFERROR('Historical FS'!C80/'Historical FS'!C68,0) | D40: =IFERROR('Historical FS'!D80/'Historical FS'!D68,0) | E40: =IFERROR('Historical FS'!E80/'Historical FS'!E68,0) | F40: =IFERROR('Historical FS'!F80/'Historical FS'!F68,0) | G40: =IFERROR('Historical FS'!G80/'Historical FS'!G68,0) | H40: =IFERROR('Historical FS'!H80/'Historical FS'!H68,0) | I40: =IFERROR('Historical FS'!I80/'Historical FS'!I68,0) | J40: =IFERROR('Historical FS'!J80/'Historical FS'!J68,0) | ... L40: =IFERROR('Historical FS'!L80/'Historical FS'!L68,0) | N40: =IFERROR(AVERAGE(C40:L40),0) | O40: =IFERROR(MEDIAN(C40:L40),0)
B41: CFO/Total Debt | C41: =IFERROR('Historical FS'!C80/'Historical FS'!C53,0) | D41: =IFERROR('Historical FS'!D80/'Historical FS'!D53,0) | E41: =IFERROR('Historical FS'!E80/'Historical FS'!E53,0) | F41: =IFERROR('Historical FS'!F80/'Historical FS'!F53,0) | G41: =IFERROR('Historical FS'!G80/'Historical FS'!G53,0) | H41: =IFERROR('Historical FS'!H80/'Historical FS'!H53,0) | I41: =IFERROR('Historical FS'!I80/'Historical FS'!I53,0) | J41: =IFERROR('Historical FS'!J80/'Historical FS'!J53,0) | ... L41: =IFERROR('Historical FS'!L80/'Historical FS'!L53,0) | N41: =IFERROR(AVERAGE(C41:L41),0) | O41: =IFERROR(MEDIAN(C41:L41),0)

Sheet Forecasting
B2: ='Data Sheet'!$B$1&" -"&'Data Sheet'!A17&" Forecasting" | G2: ='Data Sheet'!$B$1&" -"&'Historical FS'!B19&" Forecasting" | L2: ='Data Sheet'!$B$1&" -"&'Historical FS'!B37&" Forecasting"
B3: Year Weight | C3: Year | D3: Sales | E3: Sales Growth | G3: Year Weight | H3: Year | I3: EBITDA | J3: EBITDA Growth | L3: Year Weight | M3: Year | N3: Net Profit | O3: Net Profit Growth
B5: 1 | C5: {=TRANSPOSE('Data Sheet'!B16:J16)} | D5: {=TRANSPOSE('Data Sheet'!B17:K17)} | E5: - | G5: 1 | H5: {=TRANSPOSE('Data Sheet'!B16:J16)} | I5: {=TRANSPOSE('Historical FS'!C19:L19)} | J5: - | L5: 1 | M5: {=TRANSPOSE('Data Sheet'!B16:J16)} | N5: {=TRANSPOSE('Historical FS'!C37:L37)} | O5: -
B6: =B5+1 | C6: 43525 | D6: 86068 | E6: =D6/D5-1 | G6: =G5+1 | H6: 43525 | I6: 21517 | J6: =I6/I5-1 | L6: =L5+1 | M6: 43525 | N6: 7796 | O6: =N6/N5-1
B7: =B6+1 | C7: 43891 | D7: 75660 | E7: =D7/D6-1 | G7: =G6+1 | H7: 43891 | I7: 18158.4 | J7: =I7/I6-1 | L7: =L6+1 | M7: 43891 | N7: 7393.4 | O7: =N7/N6-1
B8: =B7+1 | C8: 44256 | D8: 70372 | E8: =D8/D7-1 | G8: =G7+1 | H8: 44256 | I8: 14778.12 | J8: =I8/I7-1 | L8: =L7+1 | M8: 44256 | N8: 6321.12 | O8: =N8/N7-1
B9: =B8+1 | C9: 44621 | D9: 88330 | E9: =D9/D8-1 | G9: =G8+1 | H9: 44621 | I9: 15899.4 | J9: =I9/I8-1 | L9: =L8+1 | M9: 44621 | N9: 8286.4 | O9: =N9/N8-1
B10: =B9+1 | C10: 44986 | D10: 118410 | E10: =D10/D9-1 | G10: =G9+1 | H10: 44986 | I10: 26050.2 | J10: =I10/I9-1 | L10: =L9+1 | M10: 44986 | N10: 10514.2 | O10: =N10/N9-1
B11: =B10+1 | C11: 45352 | D11: 141858 | E11: =D11/D10-1 | G11: =G10+1 | H11: 45352 | I11: 34045.92 | J11: =I11/I10-1 | L11: =L10+1 | M11: 45352 | N11: 11171.92 | O11: =N11/N10-1
B12: =B11+1 | C12: 45717 | D12: 152913 | E12: =D12/D11-1 | G12: =G11+1 | H12: 45717 | I12: 35169.99 | J12: =I12/I11-1 | L12: =L11+1 | M12: 45717 | N12: 9747.99 | O12: =N12/N11-1
B13: =B12+1 | C13: 46082 | D13: 183316 | E13: =D13/D12-1 | G13: =G12+1 | H13: 46082 | I13: 38496.36 | J13: =I13/I12-1 | L13: =L12+1 | M13: 46082 | N13: 12397.36 | O13: =N13/N12-1
B14: =B13+1 | C14: =C13+365 | D14: 197181 | E14: =D14/D13-1 | G14: =G13+1 | H14: =H13+365 | I14: 197181 | J14: =I14/I13-1 | L14: =L13+1 | M14: =M13+365 | N14: 171344 | O14: =N14/N13-1
B15: =B14+1 | C15: =C14+365 | D15: =FORECAST(B15,$D$5:$D$14,$B$5:$B$14) | E15: =D15/D14-1 | G15: =G14+1 | H15: =H14+365 | I15: =FORECAST(G15,$I$5:$I$14,$G$5:$G$14) | J15: =I15/I14-1 | L15: =L14+1 | M15: =M14+365 | N15: =FORECAST(L15,$N$5:$N$14,$L$5:$L$14) | O15: =N15/N14-1
B16: =B15+1 | C16: =C15+365 | D16: =FORECAST(B16,$D$5:$D$14,$B$5:$B$14) | E16: =D16/D15-1 | G16: =G15+1 | H16: =H15+365 | I16: =FORECAST(G16,$I$5:$I$14,$G$5:$G$14) | J16: =I16/I15-1 | L16: =L15+1 | M16: =M15+365 | N16: =FORECAST(L16,$N$5:$N$14,$L$5:$L$14) | O16: =N16/N15-1
B17: =B16+1 | C17: =C16+365 | D17: =FORECAST(B17,$D$5:$D$14,$B$5:$B$14) | E17: =D17/D16-1 | G17: =G16+1 | H17: =H16+365 | I17: =FORECAST(G17,$I$5:$I$14,$G$5:$G$14) | J17: =I17/I16-1 | L17: =L16+1 | M17: =M16+365 | N17: =FORECAST(L17,$N$5:$N$14,$L$5:$L$14) | O17: =N17/N16-1
B18: =B17+1 | C18: =C17+365 | D18: =FORECAST(B18,$D$5:$D$14,$B$5:$B$14) | E18: =D18/D17-1 | G18: =G17+1 | H18: =H17+365 | I18: =FORECAST(G18,$I$5:$I$14,$G$5:$G$14) | J18: =I18/I17-1 | L18: =L17+1 | M18: =M17+365 | N18: =FORECAST(L18,$N$5:$N$14,$L$5:$L$14) | O18: =N18/N17-1
B19: =B18+1 | C19: =C18+365 | D19: =FORECAST(B19,$D$5:$D$14,$B$5:$B$14) | E19: =D19/D18-1 | G19: =G18+1 | H19: =H18+365 | I19: =FORECAST(G19,$I$5:$I$14,$G$5:$G$14) | J19: =I19/I18-1 | L19: =L18+1 | M19: =M18+365 | N19: =FORECAST(L19,$N$5:$N$14,$L$5:$L$14) | O19: =N19/N18-1

Sheet Rm
B6: Return on Markets
B8: Date | C8: Annual
B9: ='Raw Data'!B6 | C9: ='Raw Data'!C6
B10: ='Raw Data'!B7 | C10: ='Raw Data'!C7
B11: ='Raw Data'!B8 | C11: ='Raw Data'!C8
B12: ='Raw Data'!B9 | C12: ='Raw Data'!C9 | E12: Average Market Returns | H12: =AVERAGE(C9:C32)
B13: ='Raw Data'!B10 | C13: ='Raw Data'!C10 | E13: Dividend Yield | H13: 0.0128
B14: ='Raw Data'!B11 | C14: ='Raw Data'!C11 | E14: Total Market Returns | H14: =SUM(H12:H13)
B15: ='Raw Data'!B12 | C15: ='Raw Data'!C12
B16: ='Raw Data'!B13 | C16: ='Raw Data'!C13
B17: ='Raw Data'!B14 | C17: ='Raw Data'!C14
B18: ='Raw Data'!B15 | C18: ='Raw Data'!C15
B19: ='Raw Data'!B16 | C19: ='Raw Data'!C16
B20: ='Raw Data'!B17 | C20: ='Raw Data'!C17
B21: ='Raw Data'!B18 | C21: ='Raw Data'!C18
B22: ='Raw Data'!B19 | C22: ='Raw Data'!C19
B23: ='Raw Data'!B20 | C23: ='Raw Data'!C20
B24: ='Raw Data'!B21 | C24: ='Raw Data'!C21
B25: ='Raw Data'!B22 | C25: ='Raw Data'!C22
B26: ='Raw Data'!B23 | C26: ='Raw Data'!C23
... B32: ='Raw Data'!B29 | C32: ='Raw Data'!C29

Sheet Beta-Regression
B6: Beta Regression
B7: ='Data Sheet'!B1&" Daily Returns" | F7: Nifty 50 Daily Returns | J7: Beta Drifting
B9: Date | C9: Closing Price | D9: Daily Returns | F9: Date | G9: Closing Price | H9: Daily Returns | J9: Levered Raw Beta | L9: =O11
B10: ='Raw Data'!G6 | C10: ='Raw Data'!H6 | D10: - | F10: ='Raw Data'!G6 | G10: ='Raw Data'!J6 | H10: - | J10: Raw Beta Weight | L10: 0.75
B11: ='Raw Data'!G7 | C11: ='Raw Data'!H7 | D11: =C10/C11-1 | F11: ='Raw Data'!G7 | G11: ='Raw Data'!J7 | H11: =G10/G11-1 | N11: Beta 1 | O11: =SLOPE(D10:D252, H10:H252)
B12: ='Raw Data'!G8 | C12: ='Raw Data'!H8 | D12: =C11/C12-1 | F12: ='Raw Data'!G8 | G12: ='Raw Data'!J8 | H12: =G11/G12-1 | J12: Market Beta | L12: 1 | N12: Beta 2 | O12: =_xlfn.COVARIANCE.S(D10:D252, H10:H252)/_xlfn.VAR.S(H10:H252)
B13: ='Raw Data'!G9 | C13: ='Raw Data'!H9 | D13: =C12/C13-1 | F13: ='Raw Data'!G9 | G13: ='Raw Data'!J9 | H13: =G12/G13-1 | J13: Market Beta Weight | L13: 0.25
B14: ='Raw Data'!G10 | C14: ='Raw Data'!H10 | D14: =C13/C14-1 | F14: ='Raw Data'!G10 | G14: ='Raw Data'!J10 | H14: =G13/G14-1
B15: ='Raw Data'!G11 | C15: ='Raw Data'!H11 | D15: =C14/C15-1 | F15: ='Raw Data'!G11 | G15: ='Raw Data'!J11 | H15: =G14/G15-1 | J15: Adjusted Beta | L15: =(L9*L10)+(L12*L13)
B16: ='Raw Data'!G12 | C16: ='Raw Data'!H12 | D16: =C15/C16-1 | F16: ='Raw Data'!G12 | G16: ='Raw Data'!J12 | H16: =G15/G16-1
B17: ='Raw Data'!G13 | C17: ='Raw Data'!H13 | D17: =C16/C17-1 | F17: ='Raw Data'!G13 | G17: ='Raw Data'!J13 | H17: =G16/G17-1
B18: ='Raw Data'!G14 | C18: ='Raw Data'!H14 | D18: =C17/C18-1 | F18: ='Raw Data'!G14 | G18: ='Raw Data'!J14 | H18: =G17/G18-1
B19: ='Raw Data'!G15 | C19: ='Raw Data'!H15 | D19: =C18/C19-1 | F19: ='Raw Data'!G15 | G19: ='Raw Data'!J15 | H19: =G18/G19-1
B20: ='Raw Data'!G16 | C20: ='Raw Data'!H16 | D20: =C19/C20-1 | F20: ='Raw Data'!G16 | G20: ='Raw Data'!J16 | H20: =G19/G20-1
B21: ='Raw Data'!G17 | C21: ='Raw Data'!H17 | D21: =C20/C21-1 | F21: ='Raw Data'!G17 | G21: ='Raw Data'!J17 | H21: =G20/G21-1
B22: ='Raw Data'!G18 | C22: ='Raw Data'!H18 | D22: =C21/C22-1 | F22: ='Raw Data'!G18 | G22: ='Raw Data'!J18 | H22: =G21/G22-1
B23: ='Raw Data'!G19 | C23: ='Raw Data'!H19 | D23: =C22/C23-1 | F23: ='Raw Data'!G19 | G23: ='Raw Data'!J19 | H23: =G22/G23-1
B24: ='Raw Data'!G20 | C24: ='Raw Data'!H20 | D24: =C23/C24-1 | F24: ='Raw Data'!G20 | G24: ='Raw Data'!J20 | H24: =G23/G24-1
B25: ='Raw Data'!G21 | C25: ='Raw Data'!H21 | D25: =C24/C25-1 | F25: ='Raw Data'!G21 | G25: ='Raw Data'!J21 | H25: =G24/G25-1
B26: ='Raw Data'!G22 | C26: ='Raw Data'!H22 | D26: =C25/C26-1 | F26: ='Raw Data'!G22 | G26: ='Raw Data'!J22 | H26: =G25/G26-1
B27: ='Raw Data'!G23 | C27: ='Raw Data'!H23 | D27: =C26/C27-1 | F27: ='Raw Data'!G23 | G27: ='Raw Data'!J23 | H27: =G26/G27-1
... B256: ='Raw Data'!G252 | C256: ='Raw Data'!H252 | D256: =C255/C256-1 | F256: ='Raw Data'!G252 | G256: ='Raw Data'!J252 | H256: =G255/G256-1

Sheet WACC
B6: Weighted Average Cost of Capital
B8: All figures are in INR unless stated otherwise
B10: Peer Comps
E11: Total Debt | F11: Total Equity | H11: Debt /Equity | I11: Debt /Capital | J11: Levered Beta | K11: Unlevered Beta
B12: Name of the Comp | D12: Country | G12: Tax Rate
B14: ='Raw Data'!O24 | D14: ='Raw Data'!Q24 | E14: ='Raw Data'!R24 | F14: ='Raw Data'!S24 | G14: ='Raw Data'!T24 | H14: =E14/F14 | I14: =E14/SUM(E14:F14) | J14: 1.34 | K14: =J14/(1+(1-G14)*H14)
B15: ='Raw Data'!O25 | D15: ='Raw Data'!Q25 | E15: ='Raw Data'!R25 | F15: ='Raw Data'!S25 | G15: ='Raw Data'!T25 | H15: =E15/F15 | I15: =E15/SUM(E15:F15) | J15: 1.4 | K15: =J15/(1+(1-G15)*H15)
B16: ='Raw Data'!O26 | D16: ='Raw Data'!Q26 | E16: ='Raw Data'!R26 | F16: ='Raw Data'!S26 | G16: ='Raw Data'!T26 | H16: =E16/F16 | I16: =E16/SUM(E16:F16) | J16: 1.1 | K16: =J16/(1+(1-G16)*H16)
B17: ='Raw Data'!O27 | D17: ='Raw Data'!Q27 | E17: ='Raw Data'!R27 | F17: ='Raw Data'!S27 | G17: ='Raw Data'!T27 | H17: =E17/F17 | I17: =E17/SUM(E17:F17) | J17: 1.38 | K17: =J17/(1+(1-G17)*H17)
B18: ='Raw Data'!O28 | D18: ='Raw Data'!Q28 | E18: ='Raw Data'!R28 | F18: ='Raw Data'!S28 | G18: ='Raw Data'!T28 | H18: =E18/F18 | I18: =E18/SUM(E18:F18) | J18: 1.15 | K18: =J18/(1+(1-G18)*H18)
F20: Average | G20: =AVERAGE(G14:G18) | H20: =AVERAGE(H14:H18) | I20: =AVERAGE(I14:I18) | J20: =AVERAGE(J14:J18) | K20: =AVERAGE(K14:K18)
F21: Median | G21: =MEDIAN(G14:G18) | H21: =MEDIAN(H14:H18) | I21: =MEDIAN(I14:I18) | J21: =MEDIAN(J14:J18) | K21: =MEDIAN(K14:K18)
B24: Cost of Debt | G24: Cost of Capital
B26: Pre-Tax Cost of Debt | E26: 0.0776 | G26: Risk Free Rate | K26: 0.068
B27: Tax Rate | E27: =G16 | G27: Equity Risk Premium | K27: 0.065
B28: Post-Tax Cost of Debt | E28: =E26*(1-E27) | G28: Levered Beta | K28: =K36
G29: Cost of Capital | K29: =K26+K27*K28
B31: Capital Structure | G31: Levered Beta
D33: Current | E33: Target | G33: Comps Median Unlevered Beta | K33: =K21
B34: Total Debt | C34: =E16 | D34: =C34/C$36 | E34: =I20 | G34: Target Debt/Equity | K34: =E38
B35: Market Capitalization | C35: =F16 | D35: =C35/C$36 | E35: =E36-E34 | G35: Tax Rate | K35: =E27
B36: Total Capital | C36: =SUM(C34:C35) | D36: =C36/C$36 | E36: =D36 | G36: Levered Beta | K36: =K33*(1+(1-K35)*K34)
B38: Debt /Equity | D38: =D34/D35 | E38: =E34/E35 | G38: WACC
G40: Cost of Equity | K40: =K29
G41: Equity Weight | K41: =E35
G43: Cost of Debt | K43: =E28
G44: Debt Weight | K44: =E34
G46: WACC | K46: =(K40*K41)+(K43*K44)

Sheet Intrinsic Valuation
B6: Calculation of ROIC | H6: ='Raw FS'!J$3 | I6: ='Raw FS'!K$3 | J6: ='Raw FS'!L$3 | K6: ='Raw FS'!M$3 | L6: ='Raw FS'!N$3
B8: Current Assets
B9: ='Raw FS'!B39 | H9: ='Raw FS'!J39 | I9: ='Raw FS'!K39 | J9: ='Raw FS'!L39 | K9: ='Raw FS'!M39 | L9: ='Raw FS'!N39
B10: Trade Receivables | H10: ='Raw FS'!J40 | I10: ='Raw FS'!K40 | J10: ='Raw FS'!L40 | K10: ='Raw FS'!M40 | L10: ='Raw FS'!N40
B11: ='Raw FS'!B42 | H11: ='Raw FS'!J42 | I11: ='Raw FS'!K42 | J11: ='Raw FS'!L42 | K11: ='Raw FS'!M42 | L11: ='Raw FS'!N42
B12: ='Raw FS'!B43 | H12: ='Raw FS'!J43 | I12: ='Raw FS'!K43 | J12: ='Raw FS'!L43 | K12: ='Raw FS'!M43 | L12: ='Raw FS'!N43
B13: Total Current Assets | H13: =SUM(H9:H12) | I13: =SUM(I9:I12) | J13: =SUM(J9:J12) | K13: =SUM(K9:K12) | L13: =SUM(L9:L12)
B15: Current Liabilities
B16: ='Raw FS'!B14 | H16: ='Raw FS'!J14 | I16: ='Raw FS'!K14 | J16: ='Raw FS'!L14 | K16: ='Raw FS'!M14 | L16: ='Raw FS'!N14
B17: ='Raw FS'!B15 | H17: ='Raw FS'!J15 | I17: ='Raw FS'!K15 | J17: ='Raw FS'!L15 | K17: ='Raw FS'!M15 | L17: ='Raw FS'!N15
B18: ='Raw FS'!B16 | H18: ='Raw FS'!J16 | I18: ='Raw FS'!K16 | J18: ='Raw FS'!L16 | K18: ='Raw FS'!M16 | L18: ='Raw FS'!N16
B19: Total Current Liabilities | H19: =SUM(H16:H18) | I19: =SUM(I16:I18) | J19: =SUM(J16:J18) | K19: =SUM(K16:K18) | L19: =SUM(L16:L18)
A21: # | B21: Net Working Capital | H21: =H13-H19 | I21: =I13-I19 | J21: =J13-J19 | K21: =K13-K19 | L21: =L13-L19
B23: Non Current Assets
B24: ='Raw FS'!B22 | H24: ='Raw FS'!J22 | I24: ='Raw FS'!K22 | J24: ='Raw FS'!L22 | K24: ='Raw FS'!M22 | L24: ='Raw FS'!N22
B25: ='Raw FS'!B23 | H25: ='Raw FS'!J23 | I25: ='Raw FS'!K23 | J25: ='Raw FS'!L23 | K25: ='Raw FS'!M23 | L25: ='Raw FS'!N23
B26: ='Raw FS'!B24 | H26: ='Raw FS'!J24 | I26: ='Raw FS'!K24 | J26: ='Raw FS'!L24 | K26: ='Raw FS'!M24 | L26: ='Raw FS'!N24
B27: ='Raw FS'!B25 | H27: ='Raw FS'!J25 | I27: ='Raw FS'!K25 | J27: ='Raw FS'!L25 | K27: ='Raw FS'!M25 | L27: ='Raw FS'!N25
B28: ='Raw FS'!B26 | H28: ='Raw FS'!J26 | I28: ='Raw FS'!K26 | J28: ='Raw FS'!L26 | K28: ='Raw FS'!M26 | L28: ='Raw FS'!N26
B29: ='Raw FS'!B27 | H29: ='Raw FS'!J27 | I29: ='Raw FS'!K27 | J29: ='Raw FS'!L27 | K29: ='Raw FS'!M27 | L29: ='Raw FS'!N27
B30: ='Raw FS'!B28 | H30: ='Raw FS'!J28 | I30: ='Raw FS'!K28 | J30: ='Raw FS'!L28 | K30: ='Raw FS'!M28 | L30: ='Raw FS'!N28
B31: ='Raw FS'!B29 | H31: ='Raw FS'!J29 | I31: ='Raw FS'!K29 | J31: ='Raw FS'!L29 | K31: ='Raw FS'!M29 | L31: ='Raw FS'!N29
B32: ='Raw FS'!B30 | H32: ='Raw FS'!J30 | I32: ='Raw FS'!K30 | J32: ='Raw FS'!L30 | K32: ='Raw FS'!M30 | L32: ='Raw FS'!N30
B33: ='Raw FS'!B31 | H33: ='Raw FS'!J31 | I33: ='Raw FS'!K31 | J33: ='Raw FS'!L31 | K33: ='Raw FS'!M31 | L33: ='Raw FS'!N31
B34: ='Raw FS'!B32 | H34: ='Raw FS'!J32 | I34: ='Raw FS'!K32 | J34: ='Raw FS'!L32 | K34: ='Raw FS'!M32 | L34: ='Raw FS'!N32
B35: Net Non Current Assets | H35: ='Raw FS'!J33 | I35: ='Raw FS'!K33 | J35: ='Raw FS'!L33 | K35: ='Raw FS'!M33 | L35: ='Raw FS'!N33
B37: Invested Capital | H37: =H35+H21 | I37: =I35+I21 | J37: =J35+J21 | K37: =K35+K21 | L37: =L35+L21
B38: EBIT | H38: ='Raw FS'!Z11+'Raw FS'!Z9 | I38: ='Raw FS'!AA11+'Raw FS'!AA9 | J38: ='Raw FS'!AB11+'Raw FS'!AB9 | K38: ='Raw FS'!AC11+'Raw FS'!AC9 | L38: ='Raw FS'!AD11+'Raw FS'!AD9
B40: ROIC | H40: =H38/H37 | I40: =I38/I37 | J40: =J38/J37 | K40: =K38/K37 | L40: =L38/L37
B42: Calculation of Reinvestment Rate | H42: ='Raw FS'!J$3 | I42: ='Raw FS'!K$3 | J42: ='Raw FS'!L$3 | K42: ='Raw FS'!M$3 | L42: ='Raw FS'!N$3
B44: Net Capex | H44: =-SUM('Raw FS'!Z27:Z28) | I44: =-SUM('Raw FS'!AA27:AA28) | J44: =-SUM('Raw FS'!AB27:AB28) | K44: =-SUM('Raw FS'!AC27:AC28) | L44: =-SUM('Raw FS'!AD27:AD28)
B45: Change in Work Cap | H45: - | I45: =I21-H21 | J45: =J21-I21 | K45: =K21-J21 | L45: =L21-K21
B47: EBIT | H47: =H38 | I47: =I38 | J47: =J38 | K47: =K38 | L47: =L38
B48: Tax Rate | H48: =WACC!E27 | I48: =H48 | J48: =I48 | K48: =J48 | L48: =K48
B49: EBIT(1-T) | H49: =H47*(1-H48) | I49: =I47*(1-I48) | J49: =J47*(1-J48) | K49: =K47*(1-K48) | L49: =L47*(1-L48)
B51: Reinvestment | H51: - | I51: =SUM(I44:I45) | J51: =SUM(J44:J45) | K51: =SUM(K44:K45) | L51: =SUM(L44:L45)
B52: Reinvestment Rate | H52: - | I52: =I51/I49 | J52: =J51/J49 | K52: =K51/K49 | L52: =L51/L49
J54: 4 Year Average | L54: =AVERAGE(I52:L52)
J55: 4 Year Median | L55: =MEDIAN(I52:L52)
B57: Calculation of Growth Rate | H57: ='Raw FS'!J$3 | I57: ='Raw FS'!K$3 | J57: ='Raw FS'!L$3 | K57: ='Raw FS'!M$3 | L57: ='Raw FS'!N$3
B59: ROIC | H59: =H40 | I59: =I40 | J59: =J40 | K59: =K40 | L59: =L40
B60: Reinvestment Rate | H60: - | I60: =I52 | J60: =J52 | K60: =K52 | L60: =L52
B62: Intrinsic Growth | I62: =I59*I60 | J62: =J59*J60 | K62: =K59*K60 | L62: =L59*L60
J64: 4 Year Average | L64: =AVERAGE(I62:L62)
J65: 4 Year Median | L65: =MEDIAN(I62:L62)

Sheet DCF
B6: Calculation of PV of FCFF | H6: ='Data Sheet'!K56 | I6: =H6+365 | J6: =I6+365 | K6: =J6+365 | L6: =K6+365 | M6: =L6+365
B8: EBIT | H8: ='Intrinsic Valuation'!L38 | I8: =H8*(1+$D$18) | J8: =I8*(1+$D$18) | K8: =J8*(1+$D$18) | L8: =K8*(1+$D$18) | M8: =L8*(1+$D$18)
B9: Tax Rate | H9: =WACC!G14 | I9: =H9 | J9: =I9 | K9: =J9 | L9: =K9 | M9: =L9
B10: EBIT(1-T) | H10: =H8*(1-H9) | I10: =I8*(1-I9) | J10: =J8*(1-J9) | K10: =K8*(1-K9) | L10: =L8*(1-L9) | M10: =M8*(1-M9)
B11: Less: Reinvestment Rate | H11: ='Intrinsic Valuation'!$L$55 | I11: =MIN(0.85, 'Intrinsic Valuation'!$L$55) | J11: =MIN(0.85, $I$11+($M$11-$I$11)/4*1) | K11: =MIN(0.85, $I$11+($M$11-$I$11)/4*2) | L11: =MIN(0.85, $I$11+($M$11-$I$11)/4*3) | M11: =MIN(0.85, D21)
B12: Free Cash Flow to Firm | H12: =H10*(1-H11) | I12: =I10*(1-I11) | J12: =J10*(1-J11) | K12: =K10*(1-K11) | L12: =L10*(1-L11) | M12: =M10*(1-M11)
B13: Mid Year Convention | H13: - | I13: 0.5 | J13: =I13+1 | K13: =J13+1 | L13: =K13+1 | M13: =L13+1
B14: Discounting Factor | I14: =1/(1+$D$20)^I13 | J14: =1/(1+$D$20)^J13 | K14: =1/(1+$D$20)^K13 | L14: =1/(1+$D$20)^L13 | M14: =1/(1+$D$20)^M13
B16: PV of FCFF | I16: =I12*I14 | J16: =J12*J14 | K16: =K12*K14 | L16: =L12*L14 | M16: =M12*M14
B18: Expected Growth Rate | D18: 0.052
B19: Terminal Growth Rate | D19: 0.04
B20: WACC | D20: =WACC!K46
B21: Terminal Reinvestment Rate | D21: =D19/D20
B23: Calculation of Terminal Value
B25: FCFF(n+1) | D25: =M12*(1+D19)
B26: WACC | D26: =D20
B27: Terminal Growth Rate | D27: =D19
B29: Terminal value | D29: =D25/(D26-D27)
B31: Calculation of Equity Value
B33: PV of FCFF | D33: =SUM(I16:M16)
B34: Terminal value | D34: =D29*M14
B35: Value of Operating Assets | D35: =SUM(D33:D34)
B37: Add: Cash | D37: ='Data Sheet'!K69
B38: Less: Debt | D38: ='Data Sheet'!K59
B39: Equity Value | D39: =D35+D37-D38
B40: No. of Shares | D40: ='Data Sheet'!K70/10000000
B42: Equity Value per Share | D42: =D39/D40
B44: Share Price | D44: ='Data Sheet'!B8
B45: Discount /Premium | D45: =D44/D42

Sheet Raw Data
B6: 2025 | C6: 0.1051 | G6: 2026-10-01 | H6: 177.12 | J6: 22361.95
B7: 2024 | C7: 0.0875 | G7: 2026-09-30 | H7: 184.3 | J7: 22620.45
B8: 2023 | C8: 0.1942 | G8: 2026-09-29 | H8: 188 | J8: 22716.2
B9: 2022 | C9: 0.0432 | G9: 2026-09-28 | H9: 186.3 | J9: 22780.25
B10: 2021 | C10: 0.2412 | G10: 2026-09-25 | H10: 187.97 | J10: 23140.5
B11: 2020 | C11: 0.149 | G11: 2026-09-24 | H11: 188.02 | J11: 23063.1 | N11: S.No. | O11: Name | P11: CMP Rs. | Q11: No. Eq. Shares Cr. | R11: Mar Cap Rs.Cr. | S11: Debt Rs.Cr. | T11: Cash End Rs.Cr. | U11: EV Rs.Cr. | V11: Sales Rs.Cr. | W11: EV / EBITDA | X11: NP 12M Rs.Cr.
B12: 2019 | C12: 0.1202 | G12: 2026-09-23 | H12: 190.82 | J12: 23446.8 | N12: 1 | O12: JSW Steel | P12: 1227.55 | Q12: 244.5454 | R12: 300191.7 | S12: 75047.9 | T12: 15009.6 | U12: 360230 | V12: 66052 | W12: 30.61 | X12: 14971
B13: 2018 | C13: 0.0315 | G13: 2026-09-22 | H13: 184.97 | J13: 23329 | N13: 2 | O13: Jindal Steel | P13: 1088 | Q13: 102.0087 | R13: 110985.5 | S13: 27746.4 | T13: 5549.3 | U13: 133182.6 | V13: 76487.98 | W13: 12.44 | X13: 20183.53
B14: 2017 | C14: 0.2865 | G14: 2026-09-21 | H14: 183.4 | J14: 23414.3 | N14: 3 | O14: TATA STEEL LTD | P14: 177 | Q14: 391.0381 | R14: 221395 | S14: 92382 | T14: 610.2 | U14: 14645.2 | V14: 4400.19 | W14: 20.53 | X14: 158.3
B15: 2016 | C15: 0.0301 | G15: 2026-09-18 | H15: 185.54 | J15: 23346.4 | N15: 4 | O15: Vedanta Iron & Steel | P15: 31.21 | Q15: 293.0621 | R15: 12204.3 | S15: 3051.1 | T15: 599.6 | U15: 14390.5 | V15: 2012.58 | W15: 12.74 | X15: 0.22
B16: 2015 | C16: -0.0406 | G16: 2026-09-17 | H16: 187.29 | J16: 23270.6 | N16: 5 | O16: NMDC Steel | P16: 40.92 | Q16: 422.5316 | R16: 11992.1 | S16: 2998 | T16: 11743.2 | U16: 281837.1 | V16: 238.77 | W16: 13.43 | X16: 8.51
B17: 2014 | C17: 0.3139 | G17: 2026-09-16 | H17: 183 | J17: 23217.6 | N17: 6 | O17: Hindalco Inds. | P17: 932.5 | Q17: 224.7226 | R17: 209553.8 | S17: 52388.5 | T17: 10477.7 | U17: 251464.6
B18: 2013 | C18: 0.0676 | G18: 2026-09-15 | H18: 183.65 | J18: 23118.6 | N18: 7 | O18: Vedanta Aluminium Metal | P18: 405.15 | Q18: 391.0389 | R18: 158429.4 | S18: 39607.3 | T18: 7921.5 | U18: 190115.2
B19: 2012 | C19: 0.277 | G19: 2026-09-14 | H19: 183 | J19: 23398.1 | N19: 8 | O19: Lloyds Metals | P19: 1781.6 | Q19: 56.305 | R19: 100312.9 | S19: 25078.2 | T19: 5015.6 | U19: 120375.4
B20: 2011 | C20: -0.2462 | G20: 2026-09-11 | H20: 183 | J20: 23398.1 | N20: 9 | O20: Tata Motors PVeh | P20: 303.8 | Q20: 368.29 | R20: 111886.25 | S20: 27971.56 | T20: 5594.31 | U20: 134263.5
B21: 2010 | C21: 0.1795 | G21: 2026-09-10 | H21: 186.78 | J21: 23477.8 | N21: 10 | O21: Hero Motocorp | P21: 5285.5 | Q21: 20.01 | R21: 105784.63 | S21: 26446.16 | T21: 5289.23 | U21: 126941.56
B22: 2009 | C22: 0.7576 | G22: 2026-09-09 | H22: 188.75 | J22: 23431.5
B23: 2008 | C23: -0.5179 | G23: 2026-09-08 | H23: 184.15 | J23: 23635.1
B24: 2007 | C24: 0.5477 | G24: 2026-09-07 | H24: 185.61 | J24: 23779.15 | O24: JSW Steel | Q24: India | R24: 75047.9 | S24: 300191.7 | T24: 0.3
B25: 2006 | C25: 0.3983 | G25: 2026-09-04 | H25: 188.79 | J25: 23897.7 | O25: Jindal Steel | Q25: =Q24 | R25: 27746.4 | S25: 110985.5 | T25: =T24
B26: 2005 | C26: 0.3634 | G26: 2026-09-03 | H26: 184.2 | J26: 23873.45 | O26: TATA STEEL LTD | Q26: =Q25 | R26: 92382 | S26: 221395 | T26: =T25
B27: 2004 | C27: 0.1068 | G27: 2026-09-02 | H27: 183.85 | J27: 23914.45 | O27: Vedanta Iron & Steel | Q27: =Q26 | R27: 3051.1 | S27: 12204.3 | T27: =T26
B28: 2003 | C28: 0.719 | G28: 2026-09-01 | H28: 184.07 | J28: 24055.8 | O28: NMDC Steel | Q28: =Q27 | R28: 2998 | S28: 11992.1 | T28: =T27
B29: 2002 | C29: 0.0325 | G29: 2026-08-31 | H29: 184.35 | J29: 24080.4
G30: 2026-08-28 | H30: 186.5 | J30: 24175.65
G31: 2026-08-27 | H31: 186.8 | J31: 24090.85
G32: 2026-08-26 | H32: 188.01 | J32: 24207.75
G33: 2026-08-25 | H33: 186.94 | J33: 24334.55
G34: 2026-08-24 | H34: 186.3 | J34: 24219.05
G35: 2026-08-21 | H35: 183 | J35: 24252
G36: 2026-08-20 | H36: 183.5 | J36: 24231.85
G37: 2026-08-19 | H37: 184 | J37: 24078.3
G38: 2026-08-18 | H38: 185.5 | J38: 24154.9
G39: 2026-08-17 | H39: 186 | J39: 24287.65
G40: 2026-08-14 | H40: 183.5 | J40: 24366
G41: 2026-08-13 | H41: 184.85 | J41: 24395.85
... G252: 2025-10-09 | H252: 176.42 | J252: 25181.8

Sheet Comp_Valuation
B6: Amount in crores
B7: Company Comparable Valuation
D9: Market Data | K9: Financials | O9: Valuation
B10: Company | C10: Ticker | D10: Share Price | E10: Share Outstanding | F10: Equity Value | G10: Net Debt value | H10: Enterprise Value | I10: EV/Revenue | J10: EV/EBITDA | K10: Revenue | L10: EBITDA | M10: Net Income | O10: EV/Revenue | P10: EV/EBITDA | Q10: P/E
B12: ='Raw FS'!L57 | C12: JSWSTEEL | D12: ='Raw FS'!M57 | E12: ='Raw FS'!N57 | F12: =D12*E12 | G12: ='Raw FS'!AS57 | H12: ='Raw FS'!AT57 | I12: =IF(OR(ISBLANK(K12), K12<=0), "N/A", IFERROR($H12/K12, "N/A")) | J12: =IF(OR(ISBLANK(L12), L12<=0), "N/A", IFERROR($H12/L12, "N/A")) | K12: ='Raw FS'!AU57 | L12: ='Raw FS'!AV57 | M12: ='Raw FS'!AW57 | O12: =IF(OR(ISBLANK(K12), K12<=0), "N/A", IFERROR($H12/K12, "N/A")) | P12: =IF(OR(ISBLANK(L12), L12<=0), "N/A", IFERROR($H12/L12, "N/A")) | Q12: =IF(OR(ISBLANK(M12), M12<=0), "N/A", IFERROR(F12/M12, "N/A"))
B13: ='Raw FS'!L58 | C13: JINDALSTEL | D13: ='Raw FS'!M58 | E13: ='Raw FS'!N58 | F13: =D13*E13 | G13: ='Raw FS'!AS58 | H13: ='Raw FS'!AT58 | I13: =IF(OR(ISBLANK(K13), K13<=0), "N/A", IFERROR($H13/K13, "N/A")) | J13: =IF(OR(ISBLANK(L13), L13<=0), "N/A", IFERROR($H13/L13, "N/A")) | K13: ='Raw FS'!AU58 | L13: ='Raw FS'!AV58 | M13: ='Raw FS'!AW58 | O13: =IF(OR(ISBLANK(K13), K13<=0), "N/A", IFERROR($H13/K13, "N/A")) | P13: =IF(OR(ISBLANK(L13), L13<=0), "N/A", IFERROR($H13/L13, "N/A")) | Q13: =IF(OR(ISBLANK(M13), M13<=0), "N/A", IFERROR(F13/M13, "N/A"))
B14: ='Raw FS'!L59 | C14: VISL | D14: ='Raw FS'!M59 | E14: ='Raw FS'!N59 | F14: =D14*E14 | G14: ='Raw FS'!AS59 | H14: ='Raw FS'!AT59 | I14: =IF(OR(ISBLANK(K14), K14<=0), "N/A", IFERROR($H14/K14, "N/A")) | J14: =IF(OR(ISBLANK(L14), L14<=0), "N/A", IFERROR($H14/L14, "N/A")) | K14: ='Raw FS'!AU59 | L14: ='Raw FS'!AV59 | M14: ='Raw FS'!AW59 | O14: =IF(OR(ISBLANK(K14), K14<=0), "N/A", IFERROR($H14/K14, "N/A")) | P14: =IF(OR(ISBLANK(L14), L14<=0), "N/A", IFERROR($H14/L14, "N/A")) | Q14: =IF(OR(ISBLANK(M14), M14<=0), "N/A", IFERROR(F14/M14, "N/A"))
B15: ='Raw FS'!L60 | C15: NSLNISP | D15: ='Raw FS'!M60 | E15: ='Raw FS'!N60 | F15: =D15*E15 | G15: ='Raw FS'!AS60 | H15: ='Raw FS'!AT60 | I15: =IF(OR(ISBLANK(K15), K15<=0), "N/A", IFERROR($H15/K15, "N/A")) | J15: =IF(OR(ISBLANK(L15), L15<=0), "N/A", IFERROR($H15/L15, "N/A")) | K15: ='Raw FS'!AU60 | L15: ='Raw FS'!AV60 | M15: ='Raw FS'!AW60 | O15: =IF(OR(ISBLANK(K15), K15<=0), "N/A", IFERROR($H15/K15, "N/A")) | P15: =IF(OR(ISBLANK(L15), L15<=0), "N/A", IFERROR($H15/L15, "N/A")) | Q15: =IF(OR(ISBLANK(M15), M15<=0), "N/A", IFERROR(F15/M15, "N/A"))
B16: ='Raw FS'!L61 | C16: HINDZINC | D16: ='Raw FS'!M61 | E16: ='Raw FS'!N61 | F16: =D16*E16 | G16: ='Raw FS'!AS61 | H16: ='Raw FS'!AT61 | I16: =IF(OR(ISBLANK(K16), K16<=0), "N/A", IFERROR($H16/K16, "N/A")) | J16: =IF(OR(ISBLANK(L16), L16<=0), "N/A", IFERROR($H16/L16, "N/A")) | K16: ='Raw FS'!AU61 | L16: ='Raw FS'!AV61 | M16: ='Raw FS'!AW61 | O16: =IF(OR(ISBLANK(K16), K16<=0), "N/A", IFERROR($H16/K16, "N/A")) | P16: =IF(OR(ISBLANK(L16), L16<=0), "N/A", IFERROR($H16/L16, "N/A")) | Q16: =IF(OR(ISBLANK(M16), M16<=0), "N/A", IFERROR(F16/M16, "N/A"))
B17: ='Raw FS'!L62 | C17: HINDALCO | D17: ='Raw FS'!M62 | E17: ='Raw FS'!N62 | F17: =D17*E17 | G17: ='Raw FS'!AS62 | H17: ='Raw FS'!AT62 | I17: =IF(OR(ISBLANK(K17), K17<=0), "N/A", IFERROR($H17/K17, "N/A")) | J17: =IF(OR(ISBLANK(L17), L17<=0), "N/A", IFERROR($H17/L17, "N/A")) | K17: ='Raw FS'!AU62 | L17: ='Raw FS'!AV62 | M17: ='Raw FS'!AW62 | O17: =IF(OR(ISBLANK(K17), K17<=0), "N/A", IFERROR($H17/K17, "N/A")) | P17: =IF(OR(ISBLANK(L17), L17<=0), "N/A", IFERROR($H17/L17, "N/A")) | Q17: =IF(OR(ISBLANK(M17), M17<=0), "N/A", IFERROR(F17/M17, "N/A"))
B18: ='Raw FS'!L63 | C18: VAML | D18: ='Raw FS'!M63 | E18: ='Raw FS'!N63 | F18: =D18*E18 | G18: ='Raw FS'!AS63 | H18: ='Raw FS'!AT63 | I18: =IF(OR(ISBLANK(K18), K18<=0), "N/A", IFERROR($H18/K18, "N/A")) | J18: =IF(OR(ISBLANK(L18), L18<=0), "N/A", IFERROR($H18/L18, "N/A")) | K18: ='Raw FS'!AU63 | L18: ='Raw FS'!AV63 | M18: ='Raw FS'!AW63 | O18: =IF(OR(ISBLANK(K18), K18<=0), "N/A", IFERROR($H18/K18, "N/A")) | P18: =IF(OR(ISBLANK(L18), L18<=0), "N/A", IFERROR($H18/L18, "N/A")) | Q18: =IF(OR(ISBLANK(M18), M18<=0), "N/A", IFERROR(F18/M18, "N/A"))
B19: ='Raw FS'!L64 | C19: LLOYDSME | D19: ='Raw FS'!M64 | E19: ='Raw FS'!N64 | F19: =D19*E19 | G19: ='Raw FS'!AS64 | H19: ='Raw FS'!AT64 | I19: =IF(OR(ISBLANK(K19), K19<=0), "N/A", IFERROR($H19/K19, "N/A")) | J19: =IF(OR(ISBLANK(L19), L19<=0), "N/A", IFERROR($H19/L19, "N/A")) | K19: ='Raw FS'!AU64 | L19: ='Raw FS'!AV64 | M19: ='Raw FS'!AW64 | O19: =IF(OR(ISBLANK(K19), K19<=0), "N/A", IFERROR($H19/K19, "N/A")) | P19: =IF(OR(ISBLANK(L19), L19<=0), "N/A", IFERROR($H19/L19, "N/A")) | Q19: =IF(OR(ISBLANK(M19), M19<=0), "N/A", IFERROR(F19/M19, "N/A"))
B23: High | I23: =MAX(I12:I19) | J23: =MAX(J12:J19) | O23: =MAX(O12:O19) | P23: =MAX(P12:P19) | Q23: =MAX(Q12:Q19)
B24: 25th Percentile | I24: =_xlfn.QUARTILE.INC(I12:I19,1) | J24: =_xlfn.QUARTILE.INC(J12:J19,1) | O24: =_xlfn.QUARTILE.INC(O12:O19,1) | P24: =_xlfn.QUARTILE.INC(P12:P19,1) | Q24: =_xlfn.QUARTILE.INC(Q12:Q19,1)
B25: Median | I25: =MEDIAN(I12:I19) | J25: =MEDIAN(J12:J19) | O25: =MEDIAN(O12:O19) | P25: =MEDIAN(P12:P19) | Q25: =MEDIAN(Q12:Q19)
B26: Average | I26: =AVERAGE(I12:I19) | J26: =AVERAGE(J12:J19) | O26: =AVERAGE(O12:O19) | P26: =AVERAGE(P12:P19) | Q26: =AVERAGE(Q12:Q19)
B27: 75th Percentile | I27: =_xlfn.QUARTILE.INC(I12:I19,3) | J27: =_xlfn.QUARTILE.INC(J12:J19,3) | O27: =_xlfn.QUARTILE.INC(O12:O19,3) | P27: =_xlfn.QUARTILE.INC(P12:P19,3) | Q27: =_xlfn.QUARTILE.INC(Q12:Q19,3)
B28: Low | I28: =MIN(I12:I19) | J28: =MIN(J12:J19) | O28: =MIN(O12:O19) | P28: =MIN(P12:P19) | Q28: =MIN(Q12:Q19)
B30: TATA STEEL LTD Comparable Valuation | I30: EV/Revenue | J30: EV/EBITDA | O30: EV/Revenue | P30: EV/EBITDA | Q30: P/E
B32: Implied Enterprise Value | I32: ='Raw FS'!AU56*I25 | J32: ='Raw FS'!AV56*J25 | O32: ='Raw FS'!AU56*O25 | P32: ='Raw FS'!AV56*P25 | Q32: ='Raw FS'!AW56*Q25
B33: Net Debt Value | I33: ='Raw FS'!AS56 | J33: ='Raw FS'!AS56 | O33: ='Raw FS'!AS56 | P33: ='Raw FS'!AS56 | Q33: 0
B34: Implied Market Value | I34: =I32-I33 | J34: =J32-J33 | O34: =O32-O33 | P34: =P32-P33 | Q34: =Q32
B35: Share Outstanding | I35: ='Raw FS'!N56 | J35: ='Raw FS'!N56 | O35: ='Raw FS'!N56 | P35: ='Raw FS'!N56 | Q35: ='Raw FS'!N56
B37: Implied Value per Share | I37: =I34/I35 | J37: =J34/J35 | O37: =O34/O35 | P37: =P34/P35 | Q37: =Q34/Q35
B38: Source : Screener.in
B39: Verdict | I39: =IF(I37="N/A","N/A",IF(I37>'Raw FS'!M56,"Undervalued","Overvalued")) | J39: =IF(J37="N/A","N/A",IF(J37>'Raw FS'!M56,"Undervalued","Overvalued")) | O39: =IF(O37="N/A","N/A",IF(O37>'Raw FS'!M56,"Undervalued","Overvalued")) | P39: =IF(P37="N/A","N/A",IF(P37>'Raw FS'!M56,"Undervalued","Overvalued")) | Q39: =IF(Q37="N/A","N/A",IF(Q37>'Raw FS'!M56,"Undervalued","Overvalued"))

Sheet Dupont Analysis
B2: ='Data Sheet'!B1
B3: =CONCATENATE("(",VLOOKUP(B2,'List of Stocks'!B2:E5442,3,FALSE)," | ","BSE Code: ",VLOOKUP('Dupont Analysis'!B2,'List of Stocks'!B2:E5442,2,FALSE))
B4: =CONCATENATE(" ","INR "&'Data Sheet'!B8)
B5: 52 Week (High - INR - 224.00 & low INR - 160.00)
B6: About the Company
B8: Tata Steel Limited is an Indian multinational steel company headquartered in Mumbai and is part of the Tata Group. Formerly known as Tata Iron and Steel Company Limited (TISCO), the company was established on 26 August 1907 in Jamshedpur.
B15: Financial Summary
B35: Recent Updates
A37: • | B37: Stocks in news: Tata Steel, KPI Green Energy, NLC India, Poonawalla Fincorp and Cummins India
A39: • | B39: Tata Steel extends Dutch green steel pact by five months to March 2027
A41: • | B41: ET Exclusive: Venu Srinivasan seeks probe into Tata Trusts over alleged governance lapses
A43: • | B43: Tata Steel, Adani Ports among top 10 stocks downgraded by Motilal Oswal after Q1 results - Earnings Impact
A45: • | B45: Market wrap: Tata Steel, HCL Tech, Bajaj Finance, Adani Ports top gainers and losers on Nifty and Sensex o
A47: • | B47: TATA STEEL LTD continued strategic operational investments and customer engagements to drive sustainable long-term business performance.
B54: Dupont Analysis - Return on Equity & Return on Assets
B58: Return on Equity
E59: ='Data Sheet'!G$56 | F59: ='Data Sheet'!H$56 | G59: ='Data Sheet'!I$56 | H59: ='Data Sheet'!J$56 | I59: ='Data Sheet'!K$56
B60: Net Profit | E60: =E66 | F60: =F66 | G60: =G66 | H60: =H66 | I60: =I66
B61: Average Shareholder's Equity | E61: =E75 | F61: =F75 | G61: =G75 | H61: =H75 | I61: =I75
B62: Return on Equity | E62: =E60/E61 | F62: =F60/F61 | G62: =G60/G61 | H62: =H60/H61 | I62: =I60/I61
B64: ROE - Dupont Analysis
E65: ='Data Sheet'!G$56 | F65: ='Data Sheet'!H$56 | G65: ='Data Sheet'!I$56 | H65: ='Data Sheet'!J$56 | I65: ='Data Sheet'!K$56
B66: Net Profit | E66: ='Data Sheet'!G30 | F66: ='Data Sheet'!H30 | G66: ='Data Sheet'!I30 | H66: ='Data Sheet'!J30 | I66: ='Data Sheet'!K30
B67: Revenue | E67: ='Data Sheet'!G17 | F67: ='Data Sheet'!H17 | G67: ='Data Sheet'!I17 | H67: ='Data Sheet'!J17 | I67: ='Data Sheet'!K17
B68: Net Profit Margin (A) | E68: =E66/E67 | F68: =F66/F67 | G68: =G66/G67 | H68: =H66/H67 | I68: =I66/I67
B70: Revenue | E70: =E67 | F70: =F67 | G70: =G67 | H70: =H67 | I70: =I67
B71: Average Total Assets | E71: =SUM('Data Sheet'!F66:G66)/2 | F71: =SUM('Data Sheet'!G66:H66)/2 | G71: =SUM('Data Sheet'!H66:I66)/2 | H71: =SUM('Data Sheet'!I66:J66)/2 | I71: =SUM('Data Sheet'!J66:K66)/2
B72: Asset Turnover Ratio (B) | E72: =E70/E71 | F72: =F70/F71 | G72: =G70/G71 | H72: =H70/H71 | I72: =I70/I71
B74: Average Total Assets | E74: =E71 | F74: =F71 | G74: =G71 | H74: =H71 | I74: =I71
B75: Average Shareholder's Equity | E75: =(SUM('Data Sheet'!F57:F58)+SUM('Data Sheet'!G57:G58))/2 | F75: =(SUM('Data Sheet'!G57:G58)+SUM('Data Sheet'!H57:H58))/2 | G75: =(SUM('Data Sheet'!H57:H58)+SUM('Data Sheet'!I57:I58))/2 | H75: =(SUM('Data Sheet'!I57:I58)+SUM('Data Sheet'!J57:J58))/2 | I75: =(SUM('Data Sheet'!J57:J58)+SUM('Data Sheet'!K57:K58))/2
B76: Equity Multiplier (C) | E76: =E74/E75 | F76: =F74/F75 | G76: =G74/G75 | H76: =H74/H75 | I76: =I74/I75
B78: Return on Equity(A*B*C) | E78: =E68*E72*E76 | F78: =F68*F72*F76 | G78: =G68*G72*G76 | H78: =H68*H72*H76 | I78: =I68*I72*I76
B80: Return on Assets
E81: ='Data Sheet'!G$56 | F81: ='Data Sheet'!H$56 | G81: ='Data Sheet'!I$56 | H81: ='Data Sheet'!J$56 | I81: ='Data Sheet'!K$56
B82: Net Profit | E82: =E66 | F82: =F66 | G82: =G66 | H82: =H66 | I82: =I66
B83: Average Total Assets | E83: =E74 | F83: =F74 | G83: =G74 | H83: =H74 | I83: =I74
B84: Return on Assets | E84: =E82/E83 | F84: =F82/F83 | G84: =G82/G83 | H84: =H82/H83 | I84: =I82/I83
B86: ROA - Dupont Equation
E87: ='Data Sheet'!G$56 | F87: ='Data Sheet'!H$56 | G87: ='Data Sheet'!I$56 | H87: ='Data Sheet'!J$56 | I87: ='Data Sheet'!K$56
B88: Net Profit | E88: =E66 | F88: =F66 | G88: =G66 | H88: =H66 | I88: =I66
B89: Revenue | E89: =E67 | F89: =F67 | G89: =G67 | H89: =H67 | I89: =I67
B90: Net Profit Margin (A) | E90: =E68 | F90: =F68 | G90: =G68 | H90: =H68 | I90: =I68
B92: Revenue | E92: =E67 | F92: =F67 | G92: =G67 | H92: =H67 | I92: =I67
B93: Average Total Assets | E93: =E71 | F93: =F71 | G93: =G71 | H93: =H71 | I93: =I71
B94: Asset Turnover Ratio (B) | E94: =E72 | F94: =F72 | G94: =G72 | H94: =H72 | I94: =I72
B96: Return on Assets (A*B) | E96: =E90*E94 | F96: =F90*F94 | G96: =G90*G94 | H96: =H90*H94 | I96: =I90*I94

Sheet Altman's Z Score
B2: ='Data Sheet'!B1
B3: =CONCATENATE("(",VLOOKUP(B2,'List of Stocks'!B2:E5442,3,FALSE)," | ","BSE Code: ",VLOOKUP('Altman''s Z Score'!B2,'List of Stocks'!B2:E5442,2,FALSE))
B4: =CONCATENATE(" ","INR "&'Data Sheet'!B8)
B5: 52 Week (High - INR - 224.00 & low INR - 160.00)
B6: About the Company
B8: Tata Steel Limited is an Indian multinational steel company headquartered in Mumbai and is part of the Tata Group. Formerly known as Tata Iron and Steel Company Limited (TISCO), the company was established on 26 August 1907 in Jamshedpur.
B14: Financial Summary
B34: Recent Updates
A36: • | B36: Stocks in news: Tata Steel, KPI Green Energy, NLC India, Poonawalla Fincorp and Cummins India
A38: • | B38: Tata Steel extends Dutch green steel pact by five months to March 2027
A40: • | B40: ET Exclusive: Venu Srinivasan seeks probe into Tata Trusts over alleged governance lapses
A42: • | B42: Tata Steel, Adani Ports among top 10 stocks downgraded by Motilal Oswal after Q1 results - Earnings Impact
A44: • | B44: Market wrap: Tata Steel, HCL Tech, Bajaj Finance, Adani Ports top gainers and losers on Nifty and Sensex o
A46: • | B46: TATA STEEL LTD continued strategic operational investments and customer engagements to drive sustainable long-term business performance.
B53: Altman's Z Score Analysis Calculation
B57: Working Capital /Total assets (A)
E58: ='Data Sheet'!G$56 | F58: ='Data Sheet'!H$56 | G58: ='Data Sheet'!I$56 | H58: ='Data Sheet'!J$56 | I58: ='Data Sheet'!K$56
B59: Working Capital | E59: ='Data Sheet'!G65-'Data Sheet'!G60 | F59: ='Data Sheet'!H65-'Data Sheet'!H60 | G59: ='Data Sheet'!I65-'Data Sheet'!I60 | H59: ='Data Sheet'!J65-'Data Sheet'!J60 | I59: ='Data Sheet'!K65-'Data Sheet'!K60
B60: Total Assets | E60: ='Data Sheet'!G66 | F60: ='Data Sheet'!H66 | G60: ='Data Sheet'!I66 | H60: ='Data Sheet'!J66 | I60: ='Data Sheet'!K66
B61: Working Capital / Total assets (A) | E61: =E59/E60 | F61: =F59/F60 | G61: =G59/G60 | H61: =H59/H60 | I61: =I59/I60
B63: Retained Earnings /Total Assets (B)
E64: ='Data Sheet'!G$56 | F64: ='Data Sheet'!H$56 | G64: ='Data Sheet'!I$56 | H64: ='Data Sheet'!J$56 | I64: ='Data Sheet'!K$56
B65: Retained Earnings | E65: ='Data Sheet'!G58 | F65: ='Data Sheet'!H58 | G65: ='Data Sheet'!I58 | H65: ='Data Sheet'!J58 | I65: ='Data Sheet'!K58
B66: Total Assets | E66: =E60 | F66: =F60 | G66: =G60 | H66: =H60 | I66: =I60
B67: Retained Earnings /Total Assets (B) | E67: =E65/E66 | F67: =F65/F66 | G67: =G65/G66 | H67: =H65/H66 | I67: =I65/I66
B69: EBIT /Total Assets (C)
E70: ='Data Sheet'!G$56 | F70: ='Data Sheet'!H$56 | G70: ='Data Sheet'!I$56 | H70: ='Data Sheet'!J$56 | I70: ='Data Sheet'!K$56
B71: EBIT | E71: ='Intrinsic Valuation'!H47 | F71: ='Intrinsic Valuation'!I47 | G71: ='Intrinsic Valuation'!J47 | H71: ='Intrinsic Valuation'!K47 | I71: ='Intrinsic Valuation'!L47
B72: Total Assets | E72: =E66 | F72: =F66 | G72: =G66 | H72: =H66 | I72: =I66
B73: EBIT /Total Assets (C) | E73: =E71/E72 | F73: =F71/F72 | G73: =G71/G72 | H73: =H71/H72 | I73: =I71/I72
B75: Market Cap /Long Term Liabilities (D)
E76: ='Data Sheet'!G$56 | F76: ='Data Sheet'!H$56 | G76: ='Data Sheet'!I$56 | H76: ='Data Sheet'!J$56 | I76: ='Data Sheet'!K$56
B77: Market Capital | E77: ='Data Sheet'!G90*'Data Sheet'!G93 | F77: ='Data Sheet'!H90*'Data Sheet'!H93 | G77: ='Data Sheet'!I90*'Data Sheet'!I93 | H77: ='Data Sheet'!J90*'Data Sheet'!J93 | I77: ='Data Sheet'!K90*'Data Sheet'!K93
B78: Long Term Liabilities | E78: =SUM('Data Sheet'!G59:G60) | F78: =SUM('Data Sheet'!H59:H60) | G78: =SUM('Data Sheet'!I59:I60) | H78: =SUM('Data Sheet'!J59:J60) | I78: =SUM('Data Sheet'!K59:K60)
B79: Market Cap /Long Term Liabilities (D) | E79: =E77/E78 | F79: =F77/F78 | G79: =G77/G78 | H79: =H77/H78 | I79: =I77/I78
B81: Total Sales /Total Assets (E)
E82: ='Data Sheet'!G$56 | F82: ='Data Sheet'!H$56 | G82: ='Data Sheet'!I$56 | H82: ='Data Sheet'!J$56 | I82: ='Data Sheet'!K$56
B83: Total Sales | E83: ='Data Sheet'!G17 | F83: ='Data Sheet'!H17 | G83: ='Data Sheet'!I17 | H83: ='Data Sheet'!J17 | I83: ='Data Sheet'!K17
B84: Total Assets | E84: =E72 | F84: =F72 | G84: =G72 | H84: =H72 | I84: =I72
B85: Total Sales /Total Assets (E) | E85: =E83/E84 | F85: =F83/F84 | G85: =G83/G84 | H85: =H83/H84 | I85: =I83/I84
B87: Altman's Z Score
E88: ='Data Sheet'!G$56 | F88: ='Data Sheet'!H$56 | G88: ='Data Sheet'!I$56 | H88: ='Data Sheet'!J$56 | I88: ='Data Sheet'!K$56
B89: Final Score | E89: =(1.2*E61)+(1.4*E67)+(3.3*E73)+(0.6*E79)+(E85*1) | F89: =(1.2*F61)+(1.4*F67)+(3.3*F73)+(0.6*F79)+(F85*1) | G89: =(1.2*G61)+(1.4*G67)+(3.3*G73)+(0.6*G79)+(G85*1) | H89: =(1.2*H61)+(1.4*H67)+(3.3*H73)+(0.6*H79)+(H85*1) | I89: =(1.2*I61)+(1.4*I67)+(3.3*I73)+(0.6*I79)+(I85*1)
B90: Financial Stability | E90: =IF(E89<1.81,"Distressed",IF(E89>3,"Strong","Grey Zone")) | F90: =IF(F89<1.81,"Distressed",IF(F89>3,"Strong","Grey Zone")) | G90: =IF(G89<1.81,"Distressed",IF(G89>3,"Strong","Grey Zone")) | H90: =IF(H89<1.81,"Distressed",IF(H89>3,"Strong","Grey Zone")) | I90: =IF(I89<1.81,"Distressed",IF(I89>3,"Strong","Grey Zone"))

Sheet Raw FS
B3: Particulars | C3: Mar 2015 | D3: Mar 2016 | E3: Mar 2017 | F3: Mar 2018 | G3: Mar 2019 | H3: Mar 2020 | I3: Mar 2021 | J3: Mar 2022 | K3: Mar 2023 | L3: Mar 2024 | M3: Mar 2025 | N3: Mar 2026 | S3: Mar 2015 | T3: Mar 2016 | U3: Mar 2017 | V3: Mar 2018 | W3: Mar 2019 | X3: Mar 2020 | Y3: Mar 2021 | Z3: Mar 2022 | AA3: Mar 2023 | AB3: Mar 2024 | AC3: Mar 2025 | AD3: Mar 2026 | AE3: TTM
C4: 0 | D4: 0 | E4: 0 | F4: 0 | G4: 0 | H4: 0 | I4: 0 | J4: 0 | K4: 0 | L4: 0 | M4: 0 | N4: 0 | R4: Sales + | S4: 139504 | T4: 101965 | U4: 112299 | V4: 123249 | W4: 157669 | X4: 139817 | Y4: 156477 | Z4: 243959 | AA4: 243353 | AB4: 229171 | AC4: 218543 | AD4: 232140 | AE4: 239756
B5: Equity Capital | C5: 971 | D5: 970 | E5: 970 | F5: 1145 | G5: 1145 | H5: 1145 | I5: 1198 | J5: 1221 | K5: 1221 | L5: 1247 | M5: 1247 | N5: 1247 | R5: Expenses + | S5: 136095 | T5: 102590 | U5: 99156 | V5: 101816 | W5: 128351 | X5: 122354 | Y5: 125973 | Z5: 180469 | AA5: 211053 | AB5: 206923 | AC5: 193244 | AD5: 197788 | AE5: 203567
B6: Reserves | C6: 30378 | D6: 42762 | E6: 36849 | F6: 59726 | G6: 67780 | H6: 72431 | I6: 73041 | J6: 113222 | K6: 101861 | L6: 90788 | M6: 89922 | N6: 100920 | R6: Operating Profit | S6: 3409 | T6: -625 | U6: 13144 | V6: 21433 | W6: 29318 | X6: 17463 | Y6: 30504 | Z6: 63490 | AA6: 32300 | AB6: 22248 | AC6: 25298 | AD6: 34352 | AE6: 36189
B7: Borrowings - | C7: 80701 | D7: 81987 | E7: 83014 | F7: 92147 | G7: 100816 | H7: 116328 | I7: 88501 | J7: 75561 | K7: 84893 | L7: 87082 | M7: 94801 | N7: 92382 | R7: OPM % | S7: 2.4 | T7: -0.6 | U7: 12 | V7: 17 | W7: 19 | X7: 12 | Y7: 19 | Z7: 26 | AA7: 13 | AB7: 10 | AC7: 12 | AD7: 15 | AE7: 15
B8: Long term Borrowings | C8: 65675 | D8: 64873 | E8: 64022 | F8: 72789 | G8: 80343 | H8: 94105 | I8: 65698 | J8: 44764 | K8: 51446 | L8: 51577 | M8: 68552 | N8: 63754 | R8: Other Income + | S8: 5994 | T8: 10346 | U8: -3789 | V8: 10898 | W8: 1524 | X8: -2884 | Y8: 180 | Z8: 1300 | AA8: 1569 | AB8: -6005 | AC8: 877 | AD8: 738 | AE8: 485
B9: Short term Borrowings | C9: 9599 | D9: 15722 | E9: 18328 | F9: 15885 | G9: 10802 | H9: 19184 | I9: 14969 | J9: 24065 | K9: 26571 | L9: 29997 | M9: 20412 | N9: 21203 | R9: Interest | S9: 4848 | T9: 4221 | U9: 5072 | V9: 5455 | W9: 7660 | X9: 7533 | Y9: 7607 | Z9: 5462 | AA9: 6299 | AB9: 7508 | AC9: 7341 | AD9: 7167 | AE9: 7085
B10: Lease Liabilities | C10: 0 | D10: 0 | E10: 0 | F10: 0 | G10: 0 | H10: 0 | I10: 7834 | J10: 6733 | K10: 6875 | L10: 5508 | M10: 5837 | N10: 7425 | R10: Depreciation | S10: 5944 | T10: 5306 | U10: 5673 | V10: 5742 | W10: 7342 | X10: 8441 | Y10: 9234 | Z10: 9101 | AA10: 9335 | AB10: 9882 | AC10: 10421 | AD10: 11955 | AE10: 12850
B11: Other Borrowings | C11: 5428 | D11: 1392 | E11: 664 | F11: 3453 | G11: 9658 | H11: 3039 | I11: 0 | J11: 0 | K11: 0 | L11: 0 | M11: 0 | N11: 0 | R11: Profit before tax | S11: -1388 | T11: 193 | U11: -1391 | V11: 21135 | W11: 15841 | X11: -1395 | Y11: 13844 | Z11: 50227 | AA11: 18235 | AB11: -1147 | AC11: 8413 | AD11: 15969 | AE11: 16739
B12: Other Liabilities - | C12: 47059 | D12: 51165 | E12: 51614 | F12: 55704 | G12: 63032 | H12: 59245 | I12: 81169 | J12: 92417 | K12: 97421 | L12: 90195 | M12: 89488 | N12: 101965 | R12: Tax % | S12: 185 | T12: 358 | U12: 200 | V12: 16 | W12: 42 | X12: -184 | Y12: 41 | Z12: 17 | AA12: 56 | AB12: 328 | AC12: 62 | AD12: 32 | AE12: 0
B13: Non controlling int | C13: 1704 | D13: 781 | E13: 1602 | F13: 937 | G13: 2364 | H13: 2587 | I13: 3270 | J13: 2655 | K13: 2093 | L13: 397 | M13: 183 | N13: 1613 | R13: Net Profit + | S13: -3939 | T13: -497 | U13: -4169 | V13: 17743 | W13: 9122 | X13: 1174 | Y13: 8190 | Z13: 41749 | AA13: 8075 | AB13: -4910 | AC13: 3174 | AD13: 10886 | AE13: 11264
B14: Trade Payables | C14: 19190 | D14: 18557 | E14: 18574 | F14: 20414 | G14: 21717 | H14: 21381 | I14: 25967 | J14: 36765 | K14: 37833 | L14: 30228 | M14: 29314 | N14: 34810 | S14: -3.48 | T14: -0.34 | U14: -3.76 | V14: 11.93 | W14: 9.07 | X14: 1.38 | Y14: 6.26 | Z14: 32.88 | AA14: 7.17 | AB14: -3.55 | AC14: 2.74 | AD14: 8.65 | AE14: 8.83
B15: Advance from Customers | C15: 367 | D15: 456 | E15: 566 | F15: 616 | G15: 819 | H15: 869 | I15: 2399 | J15: 3253 | K15: 3394 | L15: 2771 | M15: 1655 | N15: 2222 | S15: -20 | T15: -203 | U15: -23 | V15: 9 | W15: 15 | X15: 74 | Y15: 40 | Z15: 16 | AA15: 50 | AB15: -101 | AC15: 131 | AD15: 46 | AE15: 0
B16: Other liability items | C16: 25798 | D16: 31371 | E16: 30871 | F16: 33738 | G16: 38131 | H16: 34408 | I16: 49533 | J16: 49744 | K16: 54101 | L16: 56799 | M16: 58335 | N16: 63320
C17: 0 | D17: 0 | E17: 0 | F17: 0 | G17: 0 | H17: 0 | I17: 0 | J17: 0 | K17: 0 | L17: 0 | M17: 0 | N17: 0
B18: Total Liabilities | C18: 159109 | D18: 176884 | E18: 172447 | F18: 208722 | G18: 232773 | H18: 249149 | I18: 243909 | J18: 282422 | K18: 285396 | L18: 269312 | M18: 275459 | N18: 296515 | S18: 42064 | T18: 42430 | U18: 42795 | V18: 43160 | W18: 43525 | X18: 43891 | Y18: 44256 | Z18: 44621 | AA18: 44986 | AB18: 45352 | AC18: 45717 | AD18: 46082
C19: 0 | D19: 0 | E19: 0 | F19: 0 | G19: 0 | H19: 0 | I19: 0 | J19: 0 | K19: 0 | L19: 0 | M19: 0 | N19: 0 | R19: Cash from Operating Activity - | S19: 11880 | T19: 11455 | U19: 10824 | V19: 8023 | W19: 25336 | X19: 20169 | Y19: 44327 | Z19: 44381 | AA19: 21683 | AB19: 20301 | AC19: 23138 | AD19: 35064 | AE19: 0
C20: 0 | D20: 0 | E20: 0 | F20: 0 | G20: 0 | H20: 0 | I20: 0 | J20: 0 | K20: 0 | L20: 0 | M20: 0 | N20: 0 | R20: Profit from operations | S20: 13955 | T20: 6824 | U20: 17581 | V20: 20187 | W20: 27840 | X20: 18078 | Y20: 28540 | Z20: 65900 | AA20: 30908 | AB20: 22237 | AC20: 23929 | AD20: 34219 | AE20: 0
B21: Fixed Assets - | C21: 68100 | D21: 72200 | E21: 92007 | F21: 96105 | G21: 124442 | H21: 134551 | I21: 135775 | J21: 133288 | K21: 146621 | L21: 148814 | M21: 150914 | N21: 179908 | R21: Receivables | S21: 1442 | T21: 0 | U21: 0 | V21: 0 | W21: 0 | X21: 0 | Y21: 0 | Z21: 0 | AA21: 0 | AB21: 0 | AC21: 0 | AD21: 0 | AE21: 0
B22: Land | C22: 2433 | D22: 16499 | E22: 16545 | F22: 16955 | G22: 17126 | H22: 19853 | I22: 20656 | J22: 20770 | K22: 21701 | L22: 22067 | M22: 22299 | N22: 23659 | R22: Inventory | S22: -485 | T22: 5618 | U22: -8243 | V22: -1595 | W22: -1069 | X22: 1562 | Y22: 46 | Z22: -16917 | AA22: -4031 | AB22: 5566 | AC22: 4776 | AD22: 1290 | AE22: 0
B23: Building | C23: 14186 | D23: 11058 | E23: 11141 | F23: 12148 | G23: 21753 | H23: 25883 | I23: 26828 | J23: 27588 | K23: 28904 | L23: 30173 | M23: 31819 | N23: 36997 | R23: Payables | S23: -605 | T23: 0 | U23: 0 | V23: 0 | W23: 0 | X23: 0 | Y23: 0 | Z23: 0 | AA23: 0 | AB23: 0 | AC23: 0 | AD23: 0 | AE23: 0
B24: Plant Machinery | C24: 124249 | D24: 73865 | E24: 93462 | F24: 104889 | G24: 127435 | H24: 141914 | I24: 155596 | J24: 152754 | K24: 163134 | L24: 175111 | M24: 186115 | N24: 224912 | R24: Working capital changes | S24: 351 | T24: 6166 | U24: -4914 | V24: -9276 | W24: 2591 | X24: 4196 | Y24: 16491 | Z24: -9618 | AA24: -3706 | AB24: 3384 | AC24: 2207 | AD24: 5442 | AE24: 0
B25: Equipments | C25: 403 | D25: 414 | E25: 543 | F25: 668 | G25: 739 | H25: 796 | I25: 0 | J25: 0 | K25: 0 | L25: 0 | M25: 0 | N25: 0 | R25: Direct taxes | S25: -2427 | T25: -1534 | U25: -1843 | V25: -2888 | W25: -5094 | X25: -2106 | Y25: -704 | Z25: -11902 | AA25: -5519 | AB25: -5320 | AC25: -2998 | AD25: -4597 | AE25: 0
B26: Furniture n fittings | C26: 916 | D26: 0 | E26: 0 | F26: 0 | G26: 0 | H26: 19 | I26: 1047 | J26: 991 | K26: 1111 | L26: 1238 | M26: 1298 | N26: 1429 | R26: Cash from Investing Activity - | S26: -9021 | T26: -8794 | U26: -9490 | V26: -11730 | W26: -29176 | X26: -14012 | Y26: -9437 | Z26: -10905 | AA26: -18179 | AB26: -14253 | AC26: -13611 | AD26: -14397 | AE26: 0
B27: Railway sidings | C27: 1239 | D27: 757 | E27: 1350 | F27: 1397 | G27: 1549 | H27: 1676 | I27: 1671 | J27: 1780 | K27: 1841 | L27: 1872 | M27: 1890 | N27: 2384 | R27: Fixed assets purchased | S27: -13492 | T27: -10163 | U27: -7716 | V27: -7478 | W27: -9091 | X27: -10398 | Y27: -6979 | Z27: -10522 | AA27: -14142 | AB27: -18207 | AC27: -15671 | AD27: -14559 | AE27: 0
B28: Vehicles | C28: 376 | D28: 335 | E28: 352 | F28: 343 | G28: 398 | H28: 615 | I28: 681 | J28: 686 | K28: 749 | L28: 794 | M28: 830 | N28: 978 | R28: Fixed assets sold | S28: 1444 | T28: 231 | U28: 289 | V28: 179 | W28: 467 | X28: 386 | Y28: 445 | Z28: 569 | AA28: 328 | AB28: 475 | AC28: 1264 | AD28: 1401 | AE28: 0
B29: Intangible Assets | C29: 13500 | D29: 6026 | E29: 4990 | F29: 5810 | G29: 4293 | H29: 5868 | I29: 6289 | J29: 6229 | K29: 7572 | L29: 7772 | M29: 7896 | N29: 10230 | R29: Investments purchased | S29: 1531 | T29: -3796 | U29: -861 | V29: -8641 | W29: -490 | X29: -828 | Y29: -3631 | Z29: -1153 | AA29: -326 | AB29: -4 | AC29: -393 | AD29: -553 | AE29: 0
B30: Other fixed assets | C30: 7315 | D30: 5154 | E30: 2919 | F30: 3233 | G30: 3742 | H30: 4424 | I30: 5171 | J30: 10953 | K30: 20384 | L30: 20546 | M30: 20881 | N30: 22389 | R30: Investments sold | S30: 262 | T30: 4275 | U30: 91 | V30: 3899 | W30: 13556 | X30: 121 | Y30: 0 | Z30: 63 | AA30: 5191 | AB30: 3171 | AC30: 554 | AD30: 20 | AE30: 0
B31: Gross Block | C31: 164618 | D31: 114109 | E31: 131302 | F31: 145444 | G31: 177037 | H31: 201047 | I31: 217939 | J31: 221752 | K31: 245395 | L31: 259572 | M31: 273028 | N31: 322978 | R31: Interest received | S31: 211 | T31: 133 | U31: 140 | V31: 254 | W31: 175 | X31: 203 | Y31: 266 | Z31: 137 | AA31: 248 | AB31: 333 | AC31: 616 | AD31: 650 | AE31: 0
B32: Accumulated Depreciation | C32: 96518 | D32: 41909 | E32: 39295 | F32: 49339 | G32: 52595 | H32: 66496 | I32: 82164 | J32: 88464 | K32: 98773 | L32: 110758 | M32: 122114 | N32: 143070 | R32: Dividends received | S32: 127 | T32: 108 | U32: 85 | V32: 111 | W32: 148 | X32: 103 | Y32: 135 | Z32: 162 | AA32: 317 | AB32: 336 | AC32: 294 | AD32: 408 | AE32: 0
B33: Net Block | C33: 68100 | D33: 72200 | E33: 92007 | F33: 96105 | G33: 124442 | H33: 134551 | I33: 135775 | J33: 133288 | K33: 146621 | L33: 148814 | M33: 150914 | N33: 179908 | R33: Invest in subsidiaries | S33: 0 | T33: 0 | U33: 0 | V33: 0 | W33: 0 | X33: 0 | Y33: 0 | Z33: 0 | AA33: 0 | AB33: 0 | AC33: 0 | AD33: 0 | AE33: 0
C34: 0 | D34: 0 | E34: 0 | F34: 0 | G34: 0 | H34: 0 | I34: 0 | J34: 0 | K34: 0 | L34: 0 | M34: 0 | N34: 0 | R34: Investment in group cos | S34: 0 | T34: 0 | U34: 0 | V34: 0 | W34: 0 | X34: 0 | Y34: 0 | Z34: 0 | AA34: 0 | AB34: 0 | AC34: 0 | AD34: 0 | AE34: 0
B35: CWIP | C35: 28678 | D35: 35996 | E35: 15784 | F35: 16614 | G35: 18641 | H35: 19497 | I35: 19007 | J35: 22046 | K35: 31213 | L35: 34356 | M35: 41622 | N35: 28497 | R35: Redemp n Canc of Shares | S35: 1301 | T35: 0 | U35: 0 | V35: 34 | W35: 156 | X35: 378 | Y35: 90 | Z35: 1208 | AA35: 166 | AB35: 123 | AC35: 28 | AD35: 611 | AE35: 0
B36: Investments | C36: 3455 | D36: 10714 | E36: 12457 | F36: 17899 | G36: 5738 | H36: 6285 | I36: 10682 | J36: 13140 | K36: 8410 | L36: 6258 | M36: 6194 | N36: 7089 | R36: Other investing items | S36: -573 | T36: 496 | U36: -437 | V36: 166 | W36: 471 | X36: 456 | Y36: 236 | Z36: -1315 | AA36: 609 | AB36: -481 | AC36: -298 | AD36: 472 | AE36: 0
C37: 0 | D37: 0 | E37: 0 | F37: 0 | G37: 0 | H37: 0 | I37: 0 | J37: 0 | K37: 0 | L37: 0 | M37: 0 | N37: 0 | R37: Cash from Financing Activity - | S37: -2617 | T37: -4729 | U37: -2579 | V37: 6640 | W37: -673 | X37: -1695 | Y37: -37090 | Z37: -23401 | AA37: -6981 | AB37: -11097 | AC37: -7002 | AD37: -21387 | AE37: 0
B38: Other Assets - | C38: 58876 | D38: 57974 | E38: 52200 | F38: 78103 | G38: 83952 | H38: 88816 | I38: 78445 | J38: 113948 | K38: 99151 | L38: 79885 | M38: 76728 | N38: 81021 | R38: Proceeds from shares | S38: 13 | T38: 0 | U38: 652 | V38: 9087 | W38: 0 | X38: 188 | Y38: 3239 | Z38: 326 | AA38: 1 | AB38: 0 | AC38: 0 | AD38: 0 | AE38: 0
B39: Inventories | C39: 25150 | D39: 20013 | E39: 24804 | F39: 28331 | G39: 31656 | H39: 31069 | I39: 33276 | J39: 48824 | K39: 54415 | L39: 49158 | M39: 44590 | N39: 47249 | R39: Proceeds from borrowings | S39: 0 | T39: 0 | U39: 0 | V39: 0 | W39: 33344 | X39: 16574 | Y39: 9801 | Z39: 12439 | AA39: 16769 | AB39: 14120 | AC39: 23893 | AD39: 15954 | AE39: 0
B40: Trade receivables + | C40: 13310 | D40: 12066 | E40: 11587 | F40: 12416 | G40: 11811 | H40: 7885 | I40: 9540 | J40: 12246 | K40: 8257 | L40: 6264 | M40: 5260 | N40: 4917 | R40: Repayment of borrowings | S40: 0 | T40: 0 | U40: 0 | V40: 0 | W40: -25077 | X40: -7937 | Y40: -39177 | Z40: -26360 | AA40: -10226 | AB40: -11908 | AC40: -17627 | AD40: -23916 | AE40: 0
B41: Cash Equivalents | C41: 8750 | D41: 6186 | E41: 4921 | F41: 7938 | G41: 3341 | H41: 8055 | I41: 5782 | J41: 15899 | K41: 13357 | L41: 8678 | M41: 11647 | N41: 10058 | R41: Interest paid fin | S41: -5428 | T41: -5483 | U41: -4733 | V41: -5146 | W41: -6901 | X41: -7419 | Y41: -6804 | Z41: -4687 | AA41: -6120 | AB41: -8145 | AC41: -8119 | AD41: -8066 | AE41: 0
B42: Loans n Advances | C42: -182 | D42: 107 | E42: 98 | F42: 219 | G42: -56 | H42: 195 | I42: -193 | J42: -158 | K42: -90 | L42: -56 | M42: 49 | N42: 1167 | R42: Dividends paid | S42: -983 | T42: -788 | U42: -791 | V42: -982 | W42: -1186 | X42: -1507 | Y42: -1151 | Z42: -3020 | AA42: -6293 | AB42: -4429 | AC42: -4490 | AD42: -4490 | AE42: 0
B43: Other asset items | C43: 11848 | D43: 19602 | E43: 10790 | F43: 29200 | G43: 37200 | H43: 41613 | I43: 30039 | J43: 37137 | K43: 23211 | L43: 15842 | M43: 15182 | N43: 17630 | R43: Financial liabilities | S43: 0 | T43: -200 | U43: -208 | V43: -211 | W43: -276 | X43: -1029 | Y43: -1284 | Z43: -1310 | AA43: -1114 | AB43: -1140 | AC43: -971 | AD43: -1162 | AE43: 0
B44: Total Assets | C44: 159109 | D44: 176884 | E44: 172447 | F44: 208722 | G44: 232773 | H44: 249149 | I44: 243909 | J44: 282422 | K44: 285396 | L44: 269312 | M44: 275459 | N44: 296515 | R44: Other financing items | S44: 3781 | T44: 1743 | U44: 2501 | V44: 3892 | W44: -576 | X44: -564 | Y44: -1714 | Z44: -789 | AA44: 2 | AB44: 404 | AC44: 312 | AD44: 293 | AE44: 0
R45: Net Cash Flow | S45: 241 | T45: -2068 | U45: -1245 | V45: 2933 | W45: -4513 | X45: 4462 | Y45: -2200 | Z45: 10075 | AA45: -3477 | AB45: -5049 | AC45: 2524 | AD45: -720 | AE45: 0 | AT45: Interest paid fin | AU45: -18 | AV45: -2 | AW45: -14 | AX45: -6 | AY45: -7 | AZ45: -90 | BA45: -92 | BB45: -82 | BC45: -88 | BD45: -110 | BE45: -130 | BF45: -133
AT46: Dividends paid | AU46: -2912 | AV46: -3354 | AW46: -3572 | AX46: -3911 | AY46: -4554 | AZ46: -5196 | BA46: -8811 | BB46: -7526 | BC46: -8474 | BD46: -9416 | BE46: -12473 | BF46: -10124
AT47: Financial liabilities | AU47: 0 | AV47: 0 | AW47: 0 | AX47: 0 | AY47: 0 | AZ47: -373 | BA47: -406 | BB47: -407 | BC47: -467 | BD47: -423 | BE47: -498 | BF47: -507
AT48: Other financing items | AU48: -533 | AV48: -685 | AW48: -728 | AX48: -781 | AY48: -928 | AZ48: -1061 | BA48: 0 | BB48: 0 | BC48: -2 | BD48: 0 | BE48: 0 | BF48: 0
AT49: Net Cash Flow | AU49: -33 | AV49: 25 | AW49: -202 | AX49: 21 | AY49: -28 | AZ49: 2595 | BA49: -1374 | BB49: -695 | BC49: -446 | BD49: 111 | BE49: 5258 | BF49: -3487
AR55: Mar Cap Rs.Cr. | AS55: Net Debt | AT55: EV Rs.Cr. | AU55: Sales Rs.Cr. | AV55: EBITDA | AW55: NP 12M Rs.Cr. | AX55: EV / EBITDA | AZ55: Debt Rs.Cr. | BA55: Cash End Rs.Cr.
K56: S.No. | L56: ='Data Sheet'!B1 | M56: ='Data Sheet'!B8 | N56: ='Data Sheet'!B6 | AR56: ='Data Sheet'!B9 | AS56: =AZ56-BA56 | AT56: =AR56+AS56 | AU56: ='Data Sheet'!K17 | AV56: ='Data Sheet'!K32 | AW56: ='Data Sheet'!K30 | AX56: 18.87 | AZ56: ='Data Sheet'!K59 | BA56: ='Data Sheet'!K69
K57: 1 | L57: JSW Steel | M57: 1227.55 | N57: 244.5454 | AR57: 300191.7 | AS57: =AZ57-BA57 | AT57: =AR57+AS57 | AU57: 189456 | AV57: 28176 | AW57: 12060.73 | AX57: 15 | AZ57: 75047.9 | BA57: 15009.6
K58: 2 | L58: Jindal Steel | M58: 1088 | N58: 102.0087 | AR58: 110985.5 | AS58: =AZ58-BA58 | AT58: =AR58+AS58 | AU58: 61928.5 | AV58: 5062.8 | AW58: 3088.94 | AX58: 15 | AZ58: 27746.4 | BA58: 5549.3
K59: 3 | L59: Vedanta Iron & Steel | M59: 31.21 | N59: 391.0381 | AR59: 12204.3 | AS59: =AZ59-BA59 | AT59: =AR59+AS59 | AU59: 14648 | AV59: 726 | AW59: 484 | AX59: 15 | AZ59: 3051.1 | BA59: 610.2
K60: 4 | L60: NMDC Steel | M60: 40.92 | N60: 293.0621 | AR60: 11992.1 | AS60: =AZ60-BA60 | AT60: =AR60+AS60 | AU60: 14647.4 | AV60: 303.1 | AW60: 83.64 | AX60: 15 | AZ60: 2998 | BA60: 599.6
K61: 5 | L61: Hindustan Zinc | M61: 555.85 | N61: 422.5316 | AR61: 234864.2 | AS61: =AZ61-BA61 | AT61: =AR61+AS61 | AU61: 54748 | AV61: 32550 | AW61: 16896.71 | AX61: 15 | AZ61: 58716.1 | BA61: 11743.2
K62: 6 | L62: Hindalco Inds. | M62: 932.5 | N62: 224.7226 | AR62: 209553.8 | AS62: =AZ62-BA62 | AT62: =AR62+AS62 | AU62: 339300 | AV62: 42078 | AW62: 20913.56 | AX62: 15 | AZ62: 52388.5 | BA62: 10477.7
K63: 7 | L63: Vedanta Aluminium Metal | M63: 405.15 | N63: 391.0389 | AR63: 158429.4 | AS63: =AZ63-BA63 | AT63: =AR63+AS63 | AU63: 85572 | AV63: 39582 | AW63: 15779.82 | AX63: 15 | AZ63: 39607.3 | BA63: 7921.5
K64: 8 | L64: Lloyds Metals | M64: 1781.6 | N64: 56.305 | AR64: 100312.9 | AS64: =AZ64-BA64 | AT64: =AR64+AS64 | AU64: 29417.6 | AV64: 10403.3 | AW64: 4767.72 | AX64: 15 | AZ64: 25078.2 | BA64: 5015.6
K65: 9 | L65: Tata Motors PVeh | M65: 303.8 | N65: 368.29 | AR65: 105784.63 | AS65: =AZ65-BA65 | AT65: =AR65+AS65 | AU65: 52505.4 | AV65: =AT65/AX65 | AW65: 5671.72 | AX65: 35.22 | AZ65: 26446.16 | BA65: 5289.23
K66: 10 | L66: Hero Motocorp | M66: 5285.5 | N66: 20.01

Sheet List of Stocks
B2: COMPANY_NAME | C2: BSE | D2: NSE | E2: Industry
B3: 20 MICRONS LTD | C3: 533022 | D3: 20MICRONS | E3: Mining
B4: 21ST CENTURY MANAGEMENT SERVICES LTD | C4: 526921 | D4: 21STCENMGM | E4: Other Financial Services
B5: 3I INFOTECH LTD | C5: 532628 | D5: 3IINFOTECH | E5: IT Consulting & Software
B6: 3M (INDIA) LTD | C6: 523395 | D6: 3M(INDIA) | E6: Diversified
B7: 3M INDIA LTD | C7: 523395 | D7: 3MINDIA | E7: Diversified
B8: 3P LAND HOLDINGS LTD | C8: 516092 | D8: 3PLAND | E8: Paper & Paper Products
B9: 5PAISA CAPITAL LTD | C9: 540776 | D9: 5PAISA | E9: Other Financial Services
B10: 63 MOONS TECHNOLOGIES LTD | C10: 526881 | D10: 63MOONS | E10: IT Consulting & Software
B11: 7NR RETAIL LTD | C11: 540615 | D11: Not Listed | E11: Specialty Retail
B12: 7SEAS ENTERTAINMENT LTD | C12: 540874 | D12: Not Listed | E12: Movies & Entertainment
B13: 8K MILES SOFTWARE SERVICES LTD | C13: 512161 | D13: 8KMILES | E13: Internet Software & Services
B14: A & M FEBCON LTD | C14: 540697 | D14: Not Listed | E14: Industrial Machinery
B15: A AND M JUMBO BAGS LTD | C15: Not Listed | D15: AMJUMBO | E15: SME
B16: A INFRASTRUCTURE LTD | C16: 539620 | D16: Not Listed | E16: Cement & Cement Products
B17: A K SPINTEX LTD | C17: 539300 | D17: Not Listed | E17: Textiles
B18: A K CAPITAL SERVICES LTD | C18: 530499 | D18: Not Listed | E18: Finance (including NBFCs)
B19: A.F. Enterprises Ltd | C19: 538351 | D19: AFEL | E19: Investment Companies
B20: A-1 ACID LTD | C20: 542012 | D20: Not Listed | E20: Comm.Trading & Distribution
B21: A2Z INFRA ENGINEERING LTD | C21: 533292 | D21: A2ZINFRA | E21: Utilities:Non-Elec.
B22: AADHAAR VENTURES (INDIA) LTD | C22: 531611 | D22: Not Listed | E22: Finance (including NBFCs)
B23: AADHAAR VENTURES INDIA LTD | C23: 531611 | D23: Not Listed | E23: Finance (including NBFCs)
B24: AAKASH EXPLORATION SERVICES LTD | C24: Not Listed | D24: AAKASH | E24: SME
B25: AANANDA LAKSHMI SPINNING MILLS LTD | C25: 539096 | D25: Not Listed | E25: Textiles
B26: AANCHAL ISPAT LTD | C26: 538812 | D26: Not Listed | E26: Iron & Steel/Interm.Products
B27: AAR COMMERCIAL COMPANY LTD | C27: 539632 | D27: Not Listed | E27: Distributors
B28: Aar Shyam India Investment Company Ltd | C28: 542377 | D28: AARSHYAM | E28: Finance (including NBFCs)
B29: AAREY DRUGS & PHARMACEUTICALS LTD | C29: 524412 | D29: Not Listed | E29: Pharmaceuticals
B30: AARON INDUSTRIES LTD | C30: Not Listed | D30: AARON | E30: SME
B31: Aartech Solonics Ltd | C31: 542580 | D31: AARTECH | E31: Heavy Electrical Equipment
B32: AARTI DRUGS LTD | C32: 524348 | D32: AARTIDRUGS | E32: Pharmaceuticals
B33: AARTI INDUSTRIES LTD | C33: 524208 | D33: AARTIIND | E33: Commodity Chemicals
B34: AARV INFRATEL LTD | C34: 526488 | D34: Not Listed | E34: Textiles
B35: AARVEE DENIMS & EXPORTS LTD | C35: 514274 | D35: AARVEEDEN | E35: Textiles
B36: AARVI ENCON LTD | C36: Not Listed | D36: AARVI | E36: SME
B37: AASHEE INFOTECH LTD | C37: 519319 | D37: Not Listed | E37: Internet Software & Services
B38: AASWA TRADING & EXPORTS LTD | C38: 512038 | D38: Not Listed | E38: Comm.Trading & Distribution
B39: AAVAS FINANCIERS LTD | C39: 541988 | D39: AAVAS | E39: Housing Finance
B40: AAYUSH FOOD AND HERBS LTD | C40: 539528 | D40: Not Listed | E40: Packaged Foods
B41: ABAN OFFSHORE LTD | C41: 523204 | D41: ABAN | E41: Exploration & Production
B42: ABANS ENTERPRISES LTD | C42: 512165 | D42: Not Listed | E42: Comm.Trading & Distribution
B43: ABB INDIA LTD | C43: 500002 | D43: ABB | E43: Heavy Electrical Equipment
B44: ABBOTT (INDIA) LTD | C44: 500488 | D44: ABBOT(INDIA) | E44: Pharmaceuticals
B45: ABBOTT INDIA LTD | C45: 500488 | D45: ABBOTINDIA | E45: Pharmaceuticals
B46: ABC (INDIA) LTD | C46: 520123 | D46: Not Listed | E46: Surface Transportation
B47: ABC GAS INTERNATIONAL LTD | C47: 513119 | D47: Not Listed | E47: Copper
B48: ABC INDIA LTD | C48: 520123 | D48: Not Listed | E48: Surface Transportation
... B56: ABIRAMI FINANCIAL SERVICES INDIA LTD | C56: 511756 | D56: Not Listed | E56: Finance (including NBFCs)
B57: ABM INTERNATIONAL LTD | C57: Not Listed | D57: ABMINTLTD | E57: Others
B58: ABM KNOWLEDGEWARE LTD | C58: 531161 | D58: Not Listed | E58: IT Software Products
B59: ACC LTD | C59: 500410 | D59: ACC | E59: Cement & Cement Products
B60: ACCEL LTD | C60: 517494 | D60: Not Listed | E60: Storage Media & Peripherals
B61: ACCELYA KALE SOLUTIONS LTD | C61: 532268 | D61: ACCELYA | E61: IT Consulting & Software
B62: ACCORD SYNERGY LTD | C62: Not Listed | D62: ACCORD | E62: SME
B63: ACCURACY SHIPPING LTD | C63: Not Listed | D63: ACCURACY | E63: SME
B64: ACE EDUTREND LTD | C64: 530093 | D64: Not Listed | E64: Education
B65: ACE INTEGRATED SOLUTIONS LTD | C65: Not Listed | D65: ACEINTEG | E65: SME
B66: ACE MEN ENGG WORKS LTD | C66: 539661 | D66: Not Listed | E66: Distributors
B67: ACE SOFTWARE EXPORTS LTD | C67: 531525 | D67: Not Listed | E67: IT Software Products
B68: Achal Investments Ltd | C68: 538570 | D68: ACHAL | E68: Other Financial Services
B69: ACI INFOCOM LTD | C69: 517356 | D69: Not Listed | E69: Storage Media & Peripherals
B70: ACKNIT INDUSTRIES LTD | C70: 530043 | D70: Not Listed | E70: Other Apparels & Accessories
B71: ACME RESOURCES LTD | C71: 539391 | D71: Not Listed | E71: Finance (including NBFCs)
B72: ACROW INDIA LTD. | C72: 513149 | D72: ACROW | E72: Iron &amp; Steel Products
B73: ACRYSIL LTD | C73: 524091 | D73: Not Listed | E73: Plastic Products
B74: ACTION CONSTRUCTION EQUIPMENT LTD | C74: 532762 | D74: ACE | E74: Transport Related Services
B75: ACTION FINANCIAL SERVICES (INDIA) LTD | C75: 511706 | D75: Not Listed | E75: Other Financial Services
B76: ACTION FINANCIAL SERVICES INDIA LTD | C76: 511706 | D76: Not Listed | E76: Other Financial Services
B77: ACTIVE CLOTHING CO LTD | C77: 541144 | D77: Not Listed | E77: Other Apparels & Accessories
... B135: AGRI-TECH INDIA LTD | C135: 537292 | D135: AGRITECH | E135: Other Agricultural Products
B136: AGRO PHOS (INDIA) LTD | C136: Not Listed | D136: AGROPHOS | E136: SME
B137: AGRO PHOS INDIA LTD | C137: Not Listed | D137: AGROPHOS | E137: SME
B138: AGRO TECH FOODS LTD | C138: 500215 | D138: ATFL | E138: Other Agricultural Products
B139: AHIMSA INDUSTRIES LTD | C139: Not Listed | D139: AHIMSA | E139: SME
B140: AHLADA ENGINEERS LTD | C140: Not Listed | D140: AHLADA | E140: SME
B141: AHLUWALIA CONTRACTS (INDIA) LTD | C141: 532811 | D141: AHLUCONT | E141: Realty
B142: AHLUWALIA CONTRACTS INDIA LTD | C142: 532811 | D142: AHLUCONT | E142: Realty
B143: AHMEDABAD STEELCRAFT LTD | C143: 522273 | D143: Not Listed | E143: Iron & Steel/Interm.Products
B144: AI CHAMPDANY INDUSTRIES LTD | C144: 532806 | D144: Not Listed | E144: Jute & Jute Products
B145: AIA ENGINEERING LTD | C145: 532683 | D145: AIAENG | E145: Other Industrial Goods
B146: AIMCO PESTICIDES LTD | C146: 524288 | D146: Not Listed | E146: Agrochemicals
B147: AIRAN LTD | C147: Not Listed | D147: AIRAN | E147: SME
B148: AIRO LAM LTD | C148: Not Listed | D148: AIROLAM | E148: SME
B149: AISHWARYA TELECOM LTD | C149: 532975 | D149: Not Listed | E149: Telecom Equipment
B150: AJANTA PHARMA LTD | C150: 532331 | D150: AJANTPHARM | E150: Pharmaceuticals
B151: AJANTA SOYA LTD | C151: 519216 | D151: Not Listed | E151: Edible Oils
B152: AJCON GLOBAL SERVICES LTD | C152: 511692 | D152: Not Listed | E152: Other Financial Services
B153: AJEL LTD | C153: 530713 | D153: Not Listed | E153: IT Consulting & Software
B154: AJMERA REALTY & INFRA (INDIA) LTD | C154: 513349 | D154: AJMERA | E154: Realty
B155: AJMERA REALTY & INFRA INDIA LTD | C155: 513349 | D155: AJMERA | E155: Realty
B156: AJOONI BIOTECH LTD | C156: Not Listed | D156: AJOONI | E156: SME
B157: AJWA FUN WORLD & RESORT LTD | C157: 526628 | D157: Not Listed | E157: Other Leisure Facilities
B158: AKAR AUTO INDUSTRIES LTD | C158: 530621 | D158: Not Listed | E158: Industrial Machinery
B159: AKASH INFRA PROJECTS LTD | C159: Not Listed | D159: AKASH | E159: SME
B160: AKASHDEEP METAL INDUSTRIES LTD | C160: 538778 | D160: Not Listed | E160: Finance (including NBFCs)
B161: AKG EXIM LTD | C161: Not Listed | D161: AKG | E161: SME
B162: AKI (INDIA) LTD | C162: 542020 | D162: Not Listed | E162: Other Apparels & Accessories
B163: AKI INDIA LTD | C163: 542020 | D163: Not Listed | E163: Other Apparels & Accessories
B164: AKM LACE AND EMBROTEX LTD | C164: 540718 | D164: Not Listed | E164: Textiles
B165: AKME STAR HOUSING FINANCE LTD | C165: 539017 | D165: Not Listed | E165: Housing Finance
...
